Workbook
Name _33_: [1]RGDP!#REF!
Name _66UN: [2]HKBUD!#REF!
Name _A65600: [3]Control!#REF!
Name _A66000: [3]Control!#REF!
Name _A75000: [3]Control!#REF!
Name _KeP1: #REF!
Name _KeP10: #REF!
Name _KeP11: #REF!
Name _KeP12: #REF!
Name _KeP13: #REF!
Name _KeP14: #REF!
Name _KeP15: #REF!
Name _KeP16: #REF!
Name _KeP17: #REF!
Name _KeP18: #REF!
Name _KeP19: #REF!
Name _KeP2: #REF!
Name _KeP20: #REF!
Name _KeP21: #REF!
Name _KeP22: #REF!
Name _KeP23: #REF!
Name _KeP24: #REF!
Name _KeP25: #REF!
Name _KeP26: #REF!
Name _KeP27: #REF!
Name _KeP28: #REF!
Name _KeP29: #REF!
Name _KeP3: #REF!
Name _KeP30: #REF!
Name _KeP31: #REF!
Name _KeP32: #REF!
Name _KeP33: #REF!
Name _KeP34: #REF!
Name _KeP35: #REF!
Name _KeP36: #REF!
Name _KeP37: #REF!
Name _KeP38: #REF!
Name _KeP39: #REF!
Name _KeP4: #REF!
Name _KeP40: #REF!
Name _KeP41: #REF!
Name _KeP42: #REF!
Name _KeP43: #REF!
Name _KeP44: #REF!
Name _KeP45: #REF!
Name _KeP46: #REF!
Name _KeP47: #REF!
Name _KeP48: #REF!
Name _KeP49: #REF!
Name _KeP5: #REF!
Name _KeP50: #REF!
Name _KeP51: #REF!
Name _KeP52: #REF!
Name _KeP53: #REF!
Name _KeP54: #REF!
Name _KeP55: #REF!
Name _KeP56: #REF!
Name _KeP57: #REF!
Name _KeP58: #REF!
Name _KeP59: #REF!

Sheet 可租物业清单
A1: 该表格式由商业发展部自行设计
A2: 应包括商业发展部管辖的集团所有何租物业

Sheet 一-2、其他业务现金收入预算表
A1: 附表：2
A2: 返回
A3: 其他业务收入现金预算表
A4: =[12]表格索引!$B$4 -> 编制单位：广东******有限公司 | F4: =[12]表格索引!$C$4 -> 预算年度：2013年 | X4: 单位：万元
A5: 项 目 | C5: 上年转入本年应收帐款 | D5: 本年预计新增营业额 | E5: 本年预计应收营业额 | F5: 收款率％ | G5: 全年预计现金流入量 | X5: 应收未收帐款余额 | Y5: 预算责任人
E6: 本年预计应收营业额 | G6: １季度 | H6: 1月 | I6: 2月 | J6: 3月 | K6: ２季度 | L6: 4月 | M6: 5月 | N6: 6月 | O6: ３季度 | P6: 7月 | Q6: 8月 | R6: 9月 | S6: ４季度 | T6: 10月 | U6: 11月 | V6: 12月 | W6: 合计
W7: 金额 | X7: 金额
C8: (1) | D8: (2) | E8: (3)=(1)+(2) | F8: (4) | G8: (5) | K8: (6) | O8: (7) | S8: (8) | W8: (9)=(3)*(4)=(5)+(6)+(7)+(8) | X8: (10)=(3)-(9)
A9: 其他业务收入
A10: 一、租金收入 | C10: 0 | D10: =604.19*10000 -> 6041900 | E10: =604.19*10000 -> 6041900 | G10: =SUM(H10:J10) -> 1312800 | H10: =40.57*10000 -> 405700 | I10: =41.52*10000 -> 415200 | J10: =49.19*10000 -> 491900 | K10: =SUM(L10:N10) -> 0 | O10: =SUM(P10:R10) -> 0 | S10: =SUM(T10:V10) -> 0 | W10: =S10+O10+K10+G10 -> 1312800 | X10: =E10-W10 -> 4729100
A11: 二、物业收入 | E11: =C11+D11 -> 0 | G11: =SUM(H11:J11) -> 0 | K11: =SUM(L11:N11) -> 0 | O11: =SUM(P11:R11) -> 0 | S11: =SUM(T11:V11) -> 0 | W11: =S11+O11+K11+G11 -> 0 | X11: =E11-W11 -> 0
A12: 三、车位租金收入 | D12: 1539411.6 | E12: =C12+D12 -> 1539411.6 | G12: =SUM(H12:J12) -> 0 | K12: =SUM(L12:N12) -> 0 | O12: =SUM(P12:R12) -> 0 | S12: =SUM(T12:V12) -> 0 | W12: =S12+O12+K12+G12 -> 0 | X12: =E12-W12 -> 1539411.6
A13: 四、其他收入 | E13: =C13+D13 -> 0 | G13: =SUM(H13:J13) -> 0 | K13: =SUM(L13:N13) -> 0 | O13: =SUM(P13:R13) -> 0 | S13: =SUM(T13:V13) -> 0 | W13: =S13+O13+K13+G13 -> 0 | X13: =E13-W13 -> 0
E14: =C14+D14 -> 0 | G14: =SUM(H14:J14) -> 0 | K14: =SUM(L14:N14) -> 0 | O14: =SUM(P14:R14) -> 0 | S14: =SUM(T14:V14) -> 0 | W14: =S14+O14+K14+G14 -> 0 | X14: =E14-W14 -> 0
E15: =C15+D15 -> 0 | G15: =SUM(H15:J15) -> 0 | K15: =SUM(L15:N15) -> 0 | O15: =SUM(P15:R15) -> 0 | S15: =SUM(T15:V15) -> 0 | W15: =S15+O15+K15+G15 -> 0 | X15: =E15-W15 -> 0
E16: =C16+D16 -> 0 | G16: =SUM(H16:J16) -> 0 | K16: =SUM(L16:N16) -> 0 | O16: =SUM(P16:R16) -> 0 | S16: =SUM(T16:V16) -> 0 | W16: =S16+O16+K16+G16 -> 0 | X16: =E16-W16 -> 0
A17: 合计 | C17: =SUM(C10:C16) -> 0 | D17: =SUM(D10:D16) -> 7581311.6 | E17: =SUM(E10:E16) -> 7581311.6 | G17: =SUM(G10:G16) -> 1312800 | H17: =SUM(H10:H16) -> 405700 | I17: =SUM(I10:I16) -> 415200 | J17: =SUM(J10:J16) -> 491900 | K17: =SUM(K10:K16) -> 0 | L17: =SUM(L10:L16) -> 0 | M17: =SUM(M10:M16) -> 0 | N17: =SUM(N10:N16) -> 0 | ... X17: =SUM(X10:X16) -> 6268511.6
A18: 编制说明： | W18: 22 | X18: 制表人：
A19: 1、上年转入本年应收未收款；
A20: 2、本年预计销售收入：指依据预算年度经营计划，本年当期应该实现的销售收入；
A21: 3、指本年应该达到的现金收入总额，即“（1）”+“（2）”的合计数；
A22: 4、预计现金流入额：各级公司应根据“其他业务收入”会计科目明细填列，预计应该在本年实现的现金流入数按照月度分解；
A23: 5、应收未收帐款余额：
A24: 6、“其他业务收入”：各公司根据自身实际情况，按照会计科目“其他业务收入”分项明细填列；
A25: 7、商业发展部负责租金收放和车位租金收入的预算编制。
A26: 8、物业收入、其他收入由财务中心从物业公司及其他子公司预算表格获取数据填列。

Sheet 一-5其他成本
A1: 附表一-5
A2: 返回
A3: 其他业务成本支出现金预算表
A4: =[12]表格索引!$B$4 -> 编制单位：广东******有限公司 | K4: =[13]表格索引!C4 -> 预算年度：2013年 | T4: 单位：万元
A5: 项目 | C5: 全年预计现金流出量 | T5: 预算责任人
C6: 1季度 | D6: 1月 | E6: 2月 | F6: 3月 | G6: 2季度 | H6: 4月 | I6: 5月 | J6: 6月 | K6: 3季度 | L6: 7月 | M6: 8月 | N6: 9月 | O6: 4季度 | P6: 10月 | Q6: 11月 | R6: 12月 | S6: 全年
C7: (1) | G7: (2) | K7: (3) | O7: (4) | S7: (5)=(1)+(2)+(3)+(4)
A8: 一、租赁成本 | C8: =SUM(D8:F8) -> 0 | D8: ='[13]4、其他业务利润'!D13 -> 0 | E8: ='[13]4、其他业务利润'!E13 -> 0 | F8: ='[13]4、其他业务利润'!F13 -> 0 | G8: =SUM(H8:J8) -> 0 | H8: ='[13]4、其他业务利润'!H13 -> 0 | I8: ='[13]4、其他业务利润'!I13 -> 0 | J8: ='[13]4、其他业务利润'!J13 -> 0 | K8: =SUM(L8:N8) -> 0 | L8: ='[13]4、其他业务利润'!L13 -> 0 | M8: ='[13]4、其他业务利润'!M13 -> 0 | N8: ='[13]4、其他业务利润'!N13 -> 0 | O8: =SUM(P8:R8) -> 0 | P8: ='[13]4、其他业务利润'!P13 -> 0 | Q8: ='[13]4、其他业务利润'!Q13 -> 0 | R8: ='[13]4、其他业务利润'!R13 -> 0 | S8: =O8+K8+G8+C8 -> 0
A9: 二、物业管理成本 | C9: =SUM(D9:F9) -> 0 | G9: =SUM(H9:J9) -> 0 | K9: =SUM(L9:N9) -> 0 | O9: =SUM(P9:R9) -> 0 | S9: =O9+K9+G9+C9 -> 0
A10: 三、其他成本 | C10: =SUM(D10:F10) -> 0 | G10: =SUM(H10:J10) -> 0 | K10: =SUM(L10:N10) -> 0 | O10: =SUM(P10:R10) -> 0 | S10: =O10+K10+G10+C10 -> 0
C11: =SUM(D11:F11) -> 0 | G11: =SUM(H11:J11) -> 0 | K11: =SUM(L11:N11) -> 0 | O11: =SUM(P11:R11) -> 0 | S11: =O11+K11+G11+C11 -> 0
C12: =SUM(D12:F12) -> 0 | G12: =SUM(H12:J12) -> 0 | K12: =SUM(L12:N12) -> 0 | O12: =SUM(P12:R12) -> 0 | S12: =O12+K12+G12+C12 -> 0
C13: =SUM(D13:F13) -> 0 | G13: =SUM(H13:J13) -> 0 | K13: =SUM(L13:N13) -> 0 | O13: =SUM(P13:R13) -> 0 | S13: =O13+K13+G13+C13 -> 0
C14: =SUM(D14:F14) -> 0 | G14: =SUM(H14:J14) -> 0 | K14: =SUM(L14:N14) -> 0 | O14: =SUM(P14:R14) -> 0 | S14: =O14+K14+G14+C14 -> 0
C15: =SUM(D15:F15) -> 0 | G15: =SUM(H15:J15) -> 0 | K15: =SUM(L15:N15) -> 0 | O15: =SUM(P15:R15) -> 0 | S15: =O15+K15+G15+C15 -> 0
A16: 合 计 | C16: =SUM(C8:C15) -> 0 | D16: =SUM(D8:D15) -> 0 | E16: =SUM(E8:E15) -> 0 | F16: =SUM(F8:F15) -> 0 | G16: =SUM(G8:G15) -> 0 | H16: =SUM(H8:H15) -> 0 | I16: =SUM(I8:I15) -> 0 | J16: =SUM(J8:J15) -> 0 | ... S16: =SUM(S8:S15) -> 0
A17: 编制说明： | S17: 制表人：
A18: 1、按照非主营业务项目分别预计现金支出；
A19: 2、公司根据自身实际情况，按照成本明细项目填列。
A20: 3、假设：当年列支，当年全额结转。
A21: 4、其他业务的成本应有更明细的表格来支持本表。

Sheet 4、其他业务利润
A1: 附表：二--4
A2: 返回
A3: 其他业务利润预算表
A4: =[12]表格索引!$B$4 -> 编制单位：广东******有限公司 | O4: ='一-5其他成本'!K4 -> 预算年度：2013年 | V4: 单位：元
A5: 项 目 | C5: 1季度 | D5: 1月 | E5: 2月 | F5: 3月 | G5: 2季度 | H5: 4月 | I5: 5月 | J5: 6月 | K5: 3季度 | L5: 7月 | M5: 8月 | N5: 9月 | O5: 4季度 | P5: 10月 | Q5: 11月 | R5: 12月 | S5: 全年 | T5: 上年实际 | U5: 增减数 | V5: 增减（%） | W5: 预算责任人
C6: (1) | G6: (2) | K6: (3) | O6: (4) | S6: (5)=(1)+(2)+(3)+(4) | T6: (6) | U6: (7)=(5)-(6) | V6: (8)=((5)-(6))/(6)
A7: 一、其他业务收入
A8: 一、租金收入 | C8: =SUM(D8:F8) -> 1312800 | D8: ='一-2、其他业务现金收入预算表'!H10 -> 405700 | E8: ='一-2、其他业务现金收入预算表'!I10 -> 415200 | F8: ='一-2、其他业务现金收入预算表'!J10 -> 491900 | G8: =SUM(H8:J8) -> 0 | H8: ='一-2、其他业务现金收入预算表'!L10 -> 0 | I8: ='一-2、其他业务现金收入预算表'!M10 -> 0 | J8: ='一-2、其他业务现金收入预算表'!N10 -> 0 | K8: =SUM(L8:N8) -> 0 | L8: ='一-2、其他业务现金收入预算表'!P10 -> 0 | M8: ='一-2、其他业务现金收入预算表'!Q10 -> 0 | N8: ='一-2、其他业务现金收入预算表'!R10 -> 0 | O8: =SUM(P8:R8) -> 0 | P8: ='一-2、其他业务现金收入预算表'!T10 -> 0 | Q8: ='一-2、其他业务现金收入预算表'!U10 -> 0 | R8: ='一-2、其他业务现金收入预算表'!V10 -> 0 | S8: =O8+K8+G8+C8 -> 1312800 | U8: =S8-T8 -> 1312800 | V8: =IF(ISNUMBER(U8/T8),U8/T8,"")
A9: 二、物业收入 | C9: =SUM(D9:F9) -> 0 | D9: ='一-2、其他业务现金收入预算表'!H11 -> 0 | E9: ='一-2、其他业务现金收入预算表'!I11 -> 0 | F9: ='一-2、其他业务现金收入预算表'!J11 -> 0 | G9: =SUM(H9:J9) -> 0 | H9: ='一-2、其他业务现金收入预算表'!L11 -> 0 | I9: ='一-2、其他业务现金收入预算表'!M11 -> 0 | J9: ='一-2、其他业务现金收入预算表'!N11 -> 0 | K9: =SUM(L9:N9) -> 0 | L9: ='一-2、其他业务现金收入预算表'!P11 -> 0 | M9: ='一-2、其他业务现金收入预算表'!Q11 -> 0 | N9: ='一-2、其他业务现金收入预算表'!R11 -> 0 | O9: =SUM(P9:R9) -> 0 | P9: ='一-2、其他业务现金收入预算表'!T11 -> 0 | Q9: ='一-2、其他业务现金收入预算表'!U11 -> 0 | R9: ='一-2、其他业务现金收入预算表'!V11 -> 0 | S9: =O9+K9+G9+C9 -> 0 | U9: =S9-T9 -> 0 | V9: =IF(ISNUMBER(U9/T9),U9/T9,"")
A10: 三、其他收入 | C10: =SUM(D10:F10) -> 0 | D10: ='一-2、其他业务现金收入预算表'!H12 -> 0 | E10: ='一-2、其他业务现金收入预算表'!I12 -> 0 | F10: ='一-2、其他业务现金收入预算表'!J12 -> 0 | G10: =SUM(H10:J10) -> 0 | H10: ='一-2、其他业务现金收入预算表'!L12 -> 0 | I10: ='一-2、其他业务现金收入预算表'!M12 -> 0 | J10: ='一-2、其他业务现金收入预算表'!N12 -> 0 | K10: =SUM(L10:N10) -> 0 | L10: ='一-2、其他业务现金收入预算表'!P12 -> 0 | M10: ='一-2、其他业务现金收入预算表'!Q12 -> 0 | N10: ='一-2、其他业务现金收入预算表'!R12 -> 0 | O10: =SUM(P10:R10) -> 0 | P10: ='一-2、其他业务现金收入预算表'!T12 -> 0 | Q10: ='一-2、其他业务现金收入预算表'!U12 -> 0 | R10: ='一-2、其他业务现金收入预算表'!V12 -> 0 | S10: =O10+K10+G10+C10 -> 0 | U10: =S10-T10 -> 0 | V10: =IF(ISNUMBER(U10/T10),U10/T10,"")
A11: 小 计 | C11: ='[13]一-2、其他业务现金收入预算表'!G17 -> 0 | D11: ='一-2、其他业务现金收入预算表'!H17 -> 405700 | E11: ='一-2、其他业务现金收入预算表'!I17 -> 415200 | F11: ='一-2、其他业务现金收入预算表'!J17 -> 491900 | G11: ='一-2、其他业务现金收入预算表'!K17 -> 0 | H11: ='一-2、其他业务现金收入预算表'!L17 -> 0 | I11: ='一-2、其他业务现金收入预算表'!M17 -> 0 | J11: ='一-2、其他业务现金收入预算表'!N17 -> 0 | K11: ='一-2、其他业务现金收入预算表'!O17 -> 0 | ... R11: ='一-2、其他业务现金收入预算表'!V17 -> 0 | S11: =O11+K11+G11+C11 -> 0 | U11: =S11-T11 -> 0 | V11: =IF(ISNUMBER(U11/T11),U11/T11,"")
A12: 二、其他业务支出 | S12: =O12+K12+G12+C12 -> 0 | U12: =S12-T12 -> 0 | V12: =IF(ISNUMBER(U12/T12),U12/T12,"")
A13: 一、租赁成本 | C13: =SUM(D13:F13) -> 74960.88 | D13: =D11*0.0571 -> 23165.47 | E13: =E11*0.0571 -> 23707.92 | F13: =F11*0.0571 -> 28087.49 | G13: =SUM(H13:J13) -> 0 | H13: =H11*0.0571 -> 0 | I13: =I11*0.0571 -> 0 | J13: =J11*0.0571 -> 0 | K13: =SUM(L13:N13) -> 0 | L13: =L11*0.0571 -> 0 | M13: =M11*0.0571 -> 0 | N13: =N11*0.0571 -> 0 | O13: =SUM(P13:R13) -> 0 | P13: =P11*0.0571 -> 0 | Q13: =Q11*0.0571 -> 0 | R13: =R11*0.0571 -> 0 | S13: =O13+K13+G13+C13 -> 74960.88 | U13: =S13-T13 -> 74960.88 | V13: =IF(ISNUMBER(U13/T13),U13/T13,"")
A14: 二、物业管理成本 | C14: =SUM(D14:F14) -> 0 | D14: ='一-5其他成本'!D9 -> 0 | E14: ='一-5其他成本'!E9 -> 0 | F14: ='一-5其他成本'!F9 -> 0 | G14: =SUM(H14:J14) -> 0 | H14: ='一-5其他成本'!H9 -> 0 | I14: ='一-5其他成本'!I9 -> 0 | J14: ='一-5其他成本'!J9 -> 0 | K14: =SUM(L14:N14) -> 0 | L14: ='一-5其他成本'!L9 -> 0 | M14: ='一-5其他成本'!M9 -> 0 | N14: ='一-5其他成本'!N9 -> 0 | O14: =SUM(P14:R14) -> 0 | P14: ='一-5其他成本'!P9 -> 0 | Q14: ='一-5其他成本'!Q9 -> 0 | R14: ='一-5其他成本'!R9 -> 0 | S14: =O14+K14+G14+C14 -> 0 | U14: =S14-T14 -> 0 | V14: =IF(ISNUMBER(U14/T14),U14/T14,"")
A15: 三、其他成本 | C15: =SUM(D15:F15) -> 0 | D15: ='一-5其他成本'!D10 -> 0 | E15: ='一-5其他成本'!E10 -> 0 | F15: ='一-5其他成本'!F10 -> 0 | G15: =SUM(H15:J15) -> 0 | H15: ='一-5其他成本'!H10 -> 0 | I15: ='一-5其他成本'!I10 -> 0 | J15: ='一-5其他成本'!J10 -> 0 | K15: =SUM(L15:N15) -> 0 | L15: ='一-5其他成本'!L10 -> 0 | M15: ='一-5其他成本'!M10 -> 0 | N15: ='一-5其他成本'!N10 -> 0 | O15: =SUM(P15:R15) -> 0 | P15: ='一-5其他成本'!P10 -> 0 | Q15: ='一-5其他成本'!Q10 -> 0 | R15: ='一-5其他成本'!R10 -> 0 | S15: =O15+K15+G15+C15 -> 0 | U15: =S15-T15 -> 0 | V15: =IF(ISNUMBER(U15/T15),U15/T15,"")
A16: 小 计 | C16: =SUM(C13:C15) -> 74960.88 | D16: =SUM(D13:D15) -> 23165.47 | E16: =SUM(E13:E15) -> 23707.92 | F16: =SUM(F13:F15) -> 28087.49 | G16: =SUM(G13:G15) -> 0 | H16: =SUM(H13:H15) -> 0 | I16: =SUM(I13:I15) -> 0 | J16: =SUM(J13:J15) -> 0 | ... R16: =SUM(R13:R15) -> 0 | S16: =O16+K16+G16+C16 -> 74960.88 | U16: =S16-T16 -> 74960.88 | V16: =IF(ISNUMBER(U16/T16),U16/T16,"")
A17: 三、其他业务利润 | C17: =C11-C16 -> -74960.88 | D17: =D11-D16 -> 382534.53 | E17: =E11-E16 -> 391492.08 | F17: =F11-F16 -> 463812.51 | G17: =G11-G16 -> 0 | H17: =H11-H16 -> 0 | I17: =I11-I16 -> 0 | J17: =J11-J16 -> 0 | ... R17: =R11-R16 -> 0 | S17: =O17+K17+G17+C17 -> -74960.88 | U17: =S17-T17 -> -74960.88 | V17: =IF(ISNUMBER(U17/T17),U17/T17,"")
V18: 制表人：
D20: 10000 | E20: 0.05 | F20: =D20*E20 -> 500
D21: =F20 -> 500 | E21: 0.05 | F21: =D21*E21 -> 25
D22: =F20 -> 500 | E22: 0.07 | F22: =D22*E22 -> 35
D23: =D20 -> 10000 | E23: 0.001 | F23: =D23*E23 -> 10
D24: =D20*0.85 -> 8500 | E24: 0.001 | F24: =D24*E24 -> 8.5
F26: =SUM(F20:F25) -> 578.5
F28: =F26/D20 -> 0.05785
