Workbook

Sheet 薪酬预算校准表
B3: 薪酬预算校准表
B5: 当年实际截止月份 | C5: =人力资源规划一览表!C4 -> 44469
B6: 预算科目 | D6: ="B"&YEAR($C$5)+1 -> B2022 | E6: 校准状态 | F6: ="A"&YEAR($C$5)-1 -> A2020 | G6: ="E"&YEAR($C$5) -> E2021 | H6: ="E"&YEAR($C$5)&"/A"&YEAR($C$5) -> E2021/A2021 | K6: ="B"&YEAR($C$5)+1 -> B2022 | L6: ="B"&YEAR($C$5)+1&"/E"&YEAR($C$5) -> B2022/E2021 | O6: 说明
D7: (大帐) | F7: (细账) | G7: (细账) | H7: 变动额 | I7: % | J7: 分析 | K7: (细账) | L7: 变动额 | M7: % | N7: 分析
B8: 营业收入 | C8: ① | D8: 9300 | E8: =IF(AND(K8>=D8,K8/D8<=1.2),"已校准",IF(K8<D8,"未校准","可接受")) -> 未校准 | F8: 8700 | G8: 8900 | H8: =G8-F8 -> 200 | I8: =IFERROR(G8/F8-1,"NA") -> 0.023 | K8: 9000 | L8: =K8-G8 -> 100 | M8: =IFERROR(K8/J8-1,"NA") -> NA | O8: 依据公司、责任中心OTR填写
B9: 毛利率 | C9: ② | D9: 0.33 | F9: 0.34 | G9: 0.36 | H9: =G9-F9 -> 0.02 | I9: =IFERROR(G9/F9-1,"NA") -> 0.059 | K9: 0.35 | L9: =K9-G9 -> -0.01 | M9: =IFERROR(K9/J9-1,"NA") -> NA | O9: 依据公司、责任中心OTR选择填写
B10: 毛利额 | C10: ③ | D10: =D8*D9 -> 3069 | E10: =IF(AND(K10>=D10,K10/D10<=1.2),"已校准",IF(K10<D10,"未校准","可接受")) -> 已校准 | F10: =F8*F9 -> 2958 | G10: =G8*G9 -> 3204 | H10: =G10-F10 -> 246 | I10: =IFERROR(G10/F10-1,"NA") -> 0.083 | K10: =K8*K9 -> 3150 | L10: =K10-G10 -> -54 | M10: =IFERROR(K10/J10-1,"NA") -> NA | O10: ③=①*②
B12: 薪酬总包分配率 | C12: ④ | D12: 0.37 | F12: =F13/F10 -> 0.36 | G12: =G13/G10 -> 0.33 | H12: =G12-F12 -> -0.03 | I12: =IFERROR(G12/F12-1,"NA") -> -0.083 | K12: =K13/K10 -> 0.34 | L12: =K12-G12 -> 0.01 | M12: =IFERROR(K12/J12-1,"NA") -> NA | O12: 1.薪酬总包占毛利的比率。 2.毛利扣除所有管理成本后，为股东和劳动者共有剩余利润，薪酬总包分配率实质是劳动者与股东的分配比率。 3.应参照行业范围确认。
B13: 薪酬总包金额 | C13: ⑤ | D13: =D10*D12 -> 1136 | E13: =IF(AND(K13<=D13,D13/K13<=1.2),"已校准",IF(K13>D13,"未校准","可接受")) -> 已校准 | F13: =SUMIFS(薪酬明细!$O:$O,薪酬明细!$H:$H,">="&DATE(YEAR($C$5)-1,1,1),薪酬明细!$H:$H,"<="&EOMONTH(DATE(YEAR($C$5)-1,12,31),0),薪酬明细!$A:$A,"A")/10000 -> 1062 | G13: =SUMIFS(薪酬明细!$O:$O,薪酬明细!$H:$H,">="&DATE(YEAR($C$5),1,1),薪酬明细!$H:$H,"<="&EOMONTH(DATE(YEAR($C$5),MONTH($C$5),1),0),薪酬明细!A:A,"A")/10000+SUMIFS(薪酬明细!$O:$O,薪酬明细!$H:$H,">="&DATE(YEAR($C$5),MONTH($C$5)+1,1),薪酬明细!$H:$H,"<="&EOMONTH(DATE(YEAR($C$5),12,31),0),薪酬明细!A:A,"E")/10000 -> 1062 | H13: =G13-F13 -> 0 | I13: =IFERROR(G13/F13-1,"NA") -> 0 | K13: =SUMIFS(薪酬明细!$O:$O,薪酬明细!$H:$H,">="&DATE(YEAR($C$5)+1,1,1),薪酬明细!$H:$H,"<="&EOMONTH(DATE(YEAR($C$5)+1,12,31),0),薪酬明细!$A:$A,"B")/10000 -> 1062 | L13: =K13-G13 -> 0 | M13: =IFERROR(K13/J13-1,"NA") -> NA | O13: ⑤=③*④
B15: 固定薪酬总额 | C15: ⑥ | D15: 720 | E15: =IF(AND(K15<=D15,D15/K15<=1.2),"已校准",IF(K15>D15,"未校准","可接受")) -> 已校准 | F15: =SUMIFS(薪酬明细!$L:$L,薪酬明细!$H:$H,">="&DATE(YEAR($C$5)-1,1,1),薪酬明细!$H:$H,"<="&EOMONTH(DATE(YEAR($C$5)-1,12,31),0),薪酬明细!$A:$A,"A")/10000 -> 710 | G15: =SUMIFS(薪酬明细!$L:$L,薪酬明细!$H:$H,">="&DATE(YEAR($C$5),1,1),薪酬明细!$H:$H,"<="&EOMONTH(DATE(YEAR($C$5),MONTH($C$5),1),0),薪酬明细!A:A,"A")/10000+SUMIFS(薪酬明细!$L:$L,薪酬明细!$H:$H,">="&DATE(YEAR($C$5),MONTH($C$5)+1,1),薪酬明细!$H:$H,"<="&EOMONTH(DATE(YEAR($C$5),12,31),0),薪酬明细!A:A,"E")/10000 -> 710 | H15: =G15-F15 -> 0 | I15: =IFERROR(G15/F15-1,"NA") -> 0 | K15: =SUMIFS(薪酬明细!$L:$L,薪酬明细!$H:$H,">="&DATE(YEAR($C$5)+1,1,1),薪酬明细!$H:$H,"<="&EOMONTH(DATE(YEAR($C$5)+1,12,31),0),薪酬明细!$A:$A,"B")/10000 -> 710 | L15: =K15-G15 -> 0 | M15: =IFERROR(K15/J15-1,"NA") -> NA | O15: 根据各岗位人数和固定薪资标准计算
B16: 固定薪酬/营业收入 | C16: ⑦ | D16: =IFERROR(D15/D$8,"NA") -> 0.077 | F16: =IFERROR(F15/F$8,"NA") -> 0.082 | G16: =IFERROR(G15/G$8,"NA") -> 0.08 | H16: =G16-F16 -> -0.002 | I16: =IFERROR(G16/F16-1,"NA") -> -0.024 | K16: =IFERROR(K15/K$8,"NA") -> 0.079 | L16: =K16-G16 -> -0.001 | M16: =IFERROR(K16/J16-1,"NA") -> NA | O16: 占收入总额的比值
B17: 变动薪酬金额 | C17: ⑧ | D17: =D13-D15-D19 -> 341 | F17: =SUMIFS(薪酬明细!$M:$M,薪酬明细!$H:$H,">="&DATE(YEAR($C$5)-1,1,1),薪酬明细!$H:$H,"<="&EOMONTH(DATE(YEAR($C$5)-1,12,31),0),薪酬明细!$A:$A,"A")/10000 -> 276 | G17: =SUMIFS(薪酬明细!$M:$M,薪酬明细!$H:$H,">="&DATE(YEAR($C$5),1,1),薪酬明细!$H:$H,"<="&EOMONTH(DATE(YEAR($C$5),MONTH($C$5),1),0),薪酬明细!A:A,"A")/10000+SUMIFS(薪酬明细!$M:$M,薪酬明细!$H:$H,">="&DATE(YEAR($C$5),MONTH($C$5)+1,1),薪酬明细!$H:$H,"<="&EOMONTH(DATE(YEAR($C$5),12,31),0),薪酬明细!A:A,"E")/10000 -> 276 | H17: =G17-F17 -> 0 | I17: =IFERROR(G17/F17-1,"NA") -> 0 | K17: =SUMIFS(薪酬明细!$M:$M,薪酬明细!$H:$H,">="&DATE(YEAR($C$5)+1,1,1),薪酬明细!$H:$H,"<="&EOMONTH(DATE(YEAR($C$5)+1,12,31),0),薪酬明细!$A:$A,"B")/10000 -> 275 | L17: =K17-G17 -> -1 | M17: =IFERROR(K17/J17-1,"NA") -> NA | O17: ⑧=⑤-⑥-⑩
B18: 变动薪酬/营业收入 | C18: ⑨ | D18: =D17/D$8 -> 0.037 | E18: =IF(AND(K18<=D18,D18/K18<=1.2),"已校准",IF(K18>D18,"未校准","可接受")) -> 已校准 | F18: =F17/F$8 -> 0.032 | G18: =G17/G$8 -> 0.031 | H18: =G18-F18 -> -0.001 | I18: =IFERROR(G18/F18-1,"NA") -> -0.031 | K18: =K17/K$8 -> 0.031 | L18: =K18-G18 -> 0 | M18: =IFERROR(K18/J18-1,"NA") -> NA | O18: 占收入总额的比值
B19: 其他薪酬金额 | C19: ⑩ | D19: 75 | E19: =IF(AND(K19<=D19,D19/K19<=1.2),"已校准",IF(K19>D19,"未校准","可接受")) -> 未校准 | F19: =SUMIFS(薪酬明细!$N:$N,薪酬明细!$H:$H,">="&DATE(YEAR($C$5)-1,1,1),薪酬明细!$H:$H,"<="&EOMONTH(DATE(YEAR($C$5)-1,12,31),0),薪酬明细!$A:$A,"A")/10000 -> 76 | G19: =SUMIFS(薪酬明细!$N:$N,薪酬明细!$H:$H,">="&DATE(YEAR($C$5),1,1),薪酬明细!$H:$H,"<="&EOMONTH(DATE(YEAR($C$5),MONTH($C$5),1),0),薪酬明细!A:A,"A")/10000+SUMIFS(薪酬明细!$N:$N,薪酬明细!$H:$H,">="&DATE(YEAR($C$5),MONTH($C$5)+1,1),薪酬明细!$H:$H,"<="&EOMONTH(DATE(YEAR($C$5),12,31),0),薪酬明细!A:A,"E")/10000 -> 76 | H19: =G19-F19 -> 0 | I19: =IFERROR(G19/F19-1,"NA") -> 0 | K19: =SUMIFS(薪酬明细!$N:$N,薪酬明细!$H:$H,">="&DATE(YEAR($C$5)+1,1,1),薪酬明细!$H:$H,"<="&EOMONTH(DATE(YEAR($C$5)+1,12,31),0),薪酬明细!$A:$A,"B")/10000 -> 76 | L19: =K19-G19 -> 0 | M19: =IFERROR(K19/J19-1,"NA") -> NA | O19: 根据各岗位人数和其他薪资标准（如补贴等）计算
B20: 其他薪酬/营业收入 | C20: ⑪ | D20: =D19/D$8 -> 0.008 | F20: =F19/F$8 -> 0.009 | G20: =G19/G$8 -> 0.009 | H20: =G20-F20 -> 0 | I20: =IFERROR(G20/F20-1,"NA") -> 0 | K20: =K19/K$8 -> 0.008 | L20: =K20-G20 -> -0.001 | M20: =IFERROR(K20/J20-1,"NA") -> NA | O20: 占收入总额的比值
B22: 五险一金金额 | D22: =D13*D23 -> 341 | E22: =IF(AND(K22<=D22,D22/K22<=1.2),"已校准",IF(K22>D22,"未校准","可接受")) -> 可接受 | F22: =SUMIFS(社保明细!$J:$J,社保明细!$H:$H,">="&DATE(YEAR($C$5)-1,1,1),社保明细!$H:$H,"<="&EOMONTH(DATE(YEAR($C$5)-1,12,31),0),社保明细!$A:$A,"A")/10000 -> 208 | G22: =SUMIFS(社保明细!J:J,社保明细!$H:$H,">="&DATE(YEAR($C$5),1,1),社保明细!$H:$H,"<="&EOMONTH(DATE(YEAR($C$5),MONTH($C$5),1),0),社保明细!$A:$A,"A")/10000+SUMIFS(社保明细!J:J,社保明细!$H:$H,">="&DATE(YEAR($C$5),MONTH($C$5)+1,1),社保明细!$H:$H,"<="&EOMONTH(DATE(YEAR($C$5),12,31),0),社保明细!$A:$A,"E")/10000 -> 208 | H22: =G22-F22 -> 0 | I22: =IFERROR(G22/F22-1,"NA") -> 0 | K22: =SUMIFS(社保明细!$J:$J,社保明细!$H:$H,">="&DATE(YEAR($C$5)+1,1,1),社保明细!$H:$H,"<="&EOMONTH(DATE(YEAR($C$5)+1,12,31),0),社保明细!$A:$A,"B")/10000 -> 208 | L22: =K22-G22 -> 0 | M22: =IFERROR(K22/J22-1,"NA") -> NA | O22: 公司所承担的员工五险一金或其他法定保险占薪酬总额的比例
B23: 五险一金/薪酬总包 | D23: 0.3 | F23: =F22/F13 -> 0.196 | G23: =G22/G13 -> 0.196 | H23: =G23-F23 -> 0 | I23: =IFERROR(G23/F23-1,"NA") -> 0 | K23: =K22/K13 -> 0.196 | L23: =K23-G23 -> 0 | M23: =IFERROR(K23/J23-1,"NA") -> NA | O23: 公司所承担的员工五险一金或其他法定保险占薪酬总额的比例
B24: 福利费总额 | D24: =D13*D25 -> 159 | E24: =IF(AND(K24<=D24,D24/K24<=1.2),"已校准",IF(K24>D24,"未校准","可接受")) -> 可接受 | F24: =SUMIFS(福利费明细!$F:$F,福利费明细!$E:$E,">="&DATE(YEAR($C$5)-1,1,1),福利费明细!$E:$E,"<="&EOMONTH(DATE(YEAR($C$5)-1,12,31),0),福利费明细!$A:$A,"A")/10000 -> 50 | G24: =SUMIFS(福利费明细!$F:$F,福利费明细!$E:$E,">="&DATE(YEAR($C$5),1,1),福利费明细!$E:$E,"<="&EOMONTH(DATE(YEAR($C$5),MONTH($C$5),1),0),福利费明细!$A:$A,"A")/10000+SUMIFS(福利费明细!$F:$F,福利费明细!$E:$E,">="&DATE(YEAR($C$5),MONTH($C$5)+1,1),福利费明细!$E:$E,"<="&EOMONTH(DATE(YEAR($C$5),12,31),0),福利费明细!$A:$A,"E")/10000 -> 50 | H24: =G24-F24 -> 0 | I24: =IFERROR(G24/F24-1,"NA") -> 0 | K24: =SUMIFS(福利费明细!$F:$F,福利费明细!$E:$E,">="&DATE(YEAR($C$5)+1,1,1),福利费明细!$E:$E,"<="&EOMONTH(DATE(YEAR($C$5)+1,12,31),0),福利费明细!$A:$A,"B")/10000 -> 50 | L24: =K24-G24 -> 0 | M24: =IFERROR(K24/J24-1,"NA") -> NA | O24: 集体福利费用，如集体食堂
B25: 福利费/薪酬总包 | D25: 0.14 | F25: =F24/F13 -> 0.05 | G25: =G24/G13 -> 0.05 | H25: =G25-F25 -> 0 | I25: =IFERROR(G25/F25-1,"NA") -> 0 | K25: =K24/K13 -> 0.05 | L25: =K25-G25 -> 0 | M25: =IFERROR(K25/J25-1,"NA") -> NA | O25: 福利费占薪酬总包的比例
B26: 招聘费用总额 | D26: 11 | E26: =IF(AND(K26<=D26,D26/K26<=1.2),"已校准",IF(K26>D26,"未校准","可接受")) -> 未校准 | F26: =SUMIFS(招聘费明细!$G:$G,招聘费明细!$F:$F,">="&DATE(YEAR($C$5)-1,1,1),招聘费明细!$F:$F,"<="&EOMONTH(DATE(YEAR($C$5)-1,12,31),0),招聘费明细!$A:$A,"A")/10000 -> 11 | G26: =SUMIFS(招聘费明细!$G:$G,招聘费明细!$F:$F,">="&DATE(YEAR($C$5),1,1),招聘费明细!$F:$F,"<="&EOMONTH(DATE(YEAR($C$5),MONTH($C$5),1),0),招聘费明细!$A:$A,"A")/10000+SUMIFS(招聘费明细!$G:$G,招聘费明细!$F:$F,">="&DATE(YEAR($C$5),MONTH($C$5)+1,1),招聘费明细!$F:$F,"<="&EOMONTH(DATE(YEAR($C$5),12,31),0),招聘费明细!$A:$A,"E")/10000 -> 7 | H26: =G26-F26 -> -4 | I26: =IFERROR(G26/F26-1,"NA") -> 0 | K26: =SUMIFS(招聘费明细!$G:$G,招聘费明细!$F:$F,">="&DATE(YEAR($C$5)+1,1,1),招聘费明细!$F:$F,"<="&EOMONTH(DATE(YEAR($C$5)+1,12,31),0),招聘费明细!$A:$A,"B")/10000 -> 12 | L26: =K26-G26 -> 5 | M26: =IFERROR(K26/J26-1,"NA") -> NA | O26: 招聘的各种开支
B27: 招聘费/薪酬总包 | D27: =D26/D$13 -> 0.01 | F27: =F26/F$13 -> 0.01 | G27: =G26/G$13 -> 0.007 | H27: =G27-F27 -> 0 | I27: =IFERROR(G27/F27-1,"NA") -> -0.3 | K27: =K26/K$13 -> 0.011 | L27: =K27-G27 -> 0.004 | M27: =IFERROR(K27/J27-1,"NA") -> NA | O27: 招聘开支占薪酬总包的比例
B28: 培训费用总额 | D28: =D13*D29 -> 17 | E28: =IF(AND(K28<=D28,D28/K28<=1.2),"已校准",IF(K28>D28,"未校准","可接受")) -> 未校准 | F28: =SUMIFS(培训费明细!$G:$G,培训费明细!$F:$F,">="&DATE(YEAR($C$5)-1,1,1),培训费明细!$F:$F,"<="&EOMONTH(DATE(YEAR($C$5)-1,12,31),0),培训费明细!$A:$A,"A")/10000 -> 3 | G28: =SUMIFS(培训费明细!$G:$G,培训费明细!$F:$F,">="&DATE(YEAR($C$5),1,1),培训费明细!$F:$F,"<="&EOMONTH(DATE(YEAR($C$5),MONTH($C$5),1),0),培训费明细!$A:$A,"A")/10000+SUMIFS(培训费明细!$G:$G,培训费明细!$F:$F,">="&DATE(YEAR($C$5),MONTH($C$5)+1,1),培训费明细!$F:$F,"<="&EOMONTH(DATE(YEAR($C$5),12,31),0),培训费明细!$A:$A,"E")/10000 -> 22 | H28: =G28-F28 -> 19 | I28: =IFERROR(G28/F28-1,"NA") -> 6 | K28: =SUMIFS(培训费明细!$G:$G,培训费明细!$F:$F,">="&DATE(YEAR($C$5)+1,1,1),培训费明细!$F:$F,"<="&EOMONTH(DATE(YEAR($C$5)+1,12,31),0),培训费明细!$A:$A,"B")/10000 -> 30 | L28: =K28-G28 -> 8 | M28: =IFERROR(K28/J28-1,"NA") -> NA | O28: 用于团队学习成长的各种开支
B29: 培训费/薪酬总包 | D29: 0.015 | F29: =F28/F13 -> 0.003 | G29: =G28/G13 -> 0.021 | H29: =G29-F29 -> 0.018 | I29: =IFERROR(G29/F29-1,"NA") -> 6 | K29: =K28/K13 -> 0.028 | L29: =K29-G29 -> 0.007 | M29: =IFERROR(K29/J29-1,"NA") -> NA | O29: 学习培训成本占薪酬总包的比例
B31: 平均员工人数 | D31: =SUMIFS(薪酬明细!$K:$K,薪酬明细!$H:$H,">="&DATE(YEAR($C$5)-1,1,1),薪酬明细!$H:$H,"<="&EOMONTH(DATE(YEAR($C$5)-1,12,31),0),薪酬明细!$A:$A,"A")/12 -> 73 | F31: =SUMIFS(薪酬明细!$K:$K,薪酬明细!$H:$H,">="&DATE(YEAR($C$5)-1,1,1),薪酬明细!$H:$H,"<="&EOMONTH(DATE(YEAR($C$5)-1,12,31),0),薪酬明细!$A:$A,"A")/12 -> 73 | G31: =SUMIFS(薪酬明细!$K:$K,薪酬明细!$H:$H,">="&DATE(YEAR($C$5)-1,1,1),薪酬明细!$H:$H,"<="&EOMONTH(DATE(YEAR($C$5)-1,12,31),0),薪酬明细!$A:$A,"A")/12 -> 73 | H31: =G31-F31 -> 0 | I31: =IFERROR(G31/F31-1,"NA") -> 0 | K31: =SUMIFS(薪酬明细!$K:$K,薪酬明细!$H:$H,">="&DATE(YEAR($C$5)-1,1,1),薪酬明细!$H:$H,"<="&EOMONTH(DATE(YEAR($C$5)-1,12,31),0),薪酬明细!$A:$A,"A")/12 -> 73 | L31: =K31-G31 -> 0 | M31: =IFERROR(K31/J31-1,"NA") -> NA | O31: 年人数总和/12
B32: 年均人效 | D32: =D8/D31 -> 127 | E32: =IF(AND(K32>=D32,K32/D32<=1.2),"已校准",IF(K32<D32,"未校准","可接受")) -> 未校准 | F32: =F8/F31 -> 119 | G32: =G8/G31 -> 122 | H32: =G32-F32 -> 3 | I32: =IFERROR(G32/F32-1,"NA") -> 0 | K32: =K8/K31 -> 123 | L32: =K32-G32 -> 1 | M32: =IFERROR(K32/J32-1,"NA") -> NA | O32: 年销售额/年人数总和
B33: 年均薪酬 | D33: =D13/D31 -> 16 | F33: =F13/F31 -> 15 | G33: =G13/G31 -> 15 | H33: =G33-F33 -> 0 | I33: =IFERROR(G33/F33-1,"NA") -> 0 | K33: =K13/K31 -> 15 | L33: =K33-G33 -> 0 | M33: =IFERROR(K33/J33-1,"NA") -> NA | O33: 年薪酬总额/年人数总和
B34: 人效工资比 | D34: =D32/D33 -> 7.9 | E34: =IF(AND(K34>=D34,K34/D34<=1.2),"已校准",IF(K34<D34,"未校准","可接受")) -> 已校准 | F34: =F32/F33 -> 7.9 | G34: =G32/G33 -> 8.1 | H34: =G34-F34 -> 0 | I34: =IFERROR(G34/F34-1,"NA") -> 0 | K34: =K32/K33 -> 8.2 | L34: =K34-G34 -> 0 | M34: =IFERROR(K34/J34-1,"NA") -> NA | O34: 年均人效/年均薪酬
B36: A:实际数 E:估计数 B:预算数 YTD：从年初到当年实际截止日 YTG：当年实际截止日次日到年底
C37: 需要手工填入数据
C38: 需要手工填入分析说明
B40: 可接受 | C40: 上级预算与下级预算未校准，但差异不影响战略落地。可接受
B41: 未校准 | C41: 上级预算与下级预算的差异幅度超过可接受幅度，需要调整预算
B42: 已校准 | C42: 上级预算与下级预算的差异幅度在可接受幅度范围内。

Sheet 人力资源数据汇总
B2: 人力资源分类汇总表
C3: 当年实际截止月份 | G3: 44469
B5: 金额单位：万元 | G5: ="A"&YEAR($G$3)-1&"FY" -> A2020FY | H5: 其中： | T5: ="E"&YEAR($G$3)&"FY" -> E2021FY | U5: ="A"&YEAR($G$3)&TEXT(MONTH($G$3),"00")&"YTD" -> A202109YTD | V5: 其中： | AH5: ="E"&YEAR($G$3)&TEXT(MONTH($G$3),"00")&"YTG" -> E202109YTG | AI5: 其中： | AU5: ="B"&YEAR($G$3)+1&"FY" -> B2022FY | AV5: 其中：
G6: =LEFT(G5,1) -> A | H6: =LEFT(G5,1) -> A | I6: =H6 -> A | J6: =I6 -> A | K6: =J6 -> A | L6: =K6 -> A | M6: =L6 -> A | N6: =M6 -> A | O6: =N6 -> A | P6: =O6 -> A | ... S6: =R6 -> A | T6: =LEFT(T5,1) -> E | U6: =LEFT(U5,1) -> A | V6: =LEFT(U5,1) -> A | W6: =V6 -> A | X6: =W6 -> A | Y6: =X6 -> A | Z6: =Y6 -> A | AA6: =Z6 -> A | AB6: =AA6 -> A | AC6: =AB6 -> A | AD6: =AC6 -> A | ... AG6: =AF6 -> A | AH6: =LEFT(AH5,1) -> E | AI6: =LEFT(AH5,1) -> E | AJ6: =AI6 -> E | AK6: =AJ6 -> E | AL6: =AK6 -> E | AM6: =AL6 -> E | AN6: =AM6 -> E | AO6: =AN6 -> E | AP6: =AO6 -> E | AQ6: =AP6 -> E | ... AT6: =AS6 -> E | AU6: =LEFT(AU5,1) -> B | AV6: =LEFT(AU5,1) -> B | AW6: =AV6 -> B | AX6: =AW6 -> B | AY6: =AX6 -> B | AZ6: =AY6 -> B | BA6: =AZ6 -> B | BB6: =BA6 -> B | BC6: =BB6 -> B | BD6: =BC6 -> B | ... BG6: =BF6 -> B
G7: 合计 | H7: =YEAR($G$3)-1 -> 2020 | I7: =H7 -> 2020 | J7: =I7 -> 2020 | K7: =J7 -> 2020 | L7: =K7 -> 2020 | M7: =L7 -> 2020 | N7: =M7 -> 2020 | O7: =N7 -> 2020 | P7: =O7 -> 2020 | ... S7: =R7 -> 2020 | T7: 合计 | U7: 合计 | V7: =YEAR($G$3) -> 2021 | W7: =V7 -> 2021 | X7: =W7 -> 2021 | Y7: =X7 -> 2021 | Z7: =Y7 -> 2021 | AA7: =Z7 -> 2021 | AB7: =AA7 -> 2021 | AC7: =AB7 -> 2021 | AD7: =AC7 -> 2021 | ... AG7: =AF7 -> 2021 | AH7: 合计 | AI7: =YEAR($G$3) -> 2021 | AJ7: =AI7 -> 2021 | AK7: =AJ7 -> 2021 | AL7: =AK7 -> 2021 | AM7: =AL7 -> 2021 | AN7: =AM7 -> 2021 | AO7: =AN7 -> 2021 | AP7: =AO7 -> 2021 | AQ7: =AP7 -> 2021 | ... AT7: =AS7 -> 2021 | AU7: 合计 | AV7: =YEAR($G$3)+1 -> 2022 | AW7: =AV7 -> 2022 | AX7: =AW7 -> 2022 | AY7: =AX7 -> 2022 | AZ7: =AY7 -> 2022 | BA7: =AZ7 -> 2022 | BB7: =BA7 -> 2022 | BC7: =BB7 -> 2022 | BD7: =BC7 -> 2022 | ... BG7: =BF7 -> 2022
H8: 1 | I8: 2 | J8: 3 | K8: 4 | L8: 5 | M8: 6 | N8: 7 | O8: 8 | P8: 9 | Q8: 10 | R8: 11 | S8: 12 | V8: 1 | W8: 2 | X8: 3 | Y8: 4 | Z8: 5 | AA8: 6 | AB8: 7 | AC8: 8 | AD8: 9 | AE8: 10 | AF8: 11 | AG8: 12 | AI8: 1 | AJ8: 2 | AK8: 3 | AL8: 4 | AM8: 5 | AN8: 6 | AO8: 7 | AP8: 8 | AQ8: 9 | AR8: 10 | AS8: 11 | AT8: 12 | AV8: 1 | AW8: 2 | AX8: 3 | AY8: 4 | AZ8: 5 | BA8: 6 | BB8: 7 | BC8: 8 | BD8: 9 | BE8: 10 | BF8: 11 | BG8: 12
G9: =DATE(YEAR($G$3)-1,1,1) -> 43831 | H9: =DATE(H7,H8,1) -> 43831 | I9: =DATE(I7,I8,1) -> 43862 | J9: =DATE(J7,J8,1) -> 43891 | K9: =DATE(K7,K8,1) -> 43922 | L9: =DATE(L7,L8,1) -> 43952 | M9: =DATE(M7,M8,1) -> 43983 | N9: =DATE(N7,N8,1) -> 44013 | O9: =DATE(O7,O8,1) -> 44044 | ... S9: =DATE(S7,S8,1) -> 44166 | T9: =DATE(YEAR($G$3),1,1) -> 44197 | U9: =DATE(YEAR($G$3),1,1) -> 44197 | V9: =DATE(V7,V8,1) -> 44197 | W9: =DATE(W7,W8,1) -> 44228 | X9: =DATE(X7,X8,1) -> 44256 | Y9: =DATE(Y7,Y8,1) -> 44287 | Z9: =DATE(Z7,Z8,1) -> 44317 | AA9: =DATE(AA7,AA8,1) -> 44348 | AB9: =DATE(AB7,AB8,1) -> 44378 | AC9: =DATE(AC7,AC8,1) -> 44409 | ... AG9: =DATE(AG7,AG8,1) -> 44531 | AH9: =DATE(YEAR($G$3),MONTH($G$3)+1,1) -> 44470 | AI9: =DATE(AI7,AI8,1) -> 44197 | AJ9: =DATE(AJ7,AJ8,1) -> 44228 | AK9: =DATE(AK7,AK8,1) -> 44256 | AL9: =DATE(AL7,AL8,1) -> 44287 | AM9: =DATE(AM7,AM8,1) -> 44317 | AN9: =DATE(AN7,AN8,1) -> 44348 | AO9: =DATE(AO7,AO8,1) -> 44378 | AP9: =DATE(AP7,AP8,1) -> 44409 | ... AT9: =DATE(AT7,AT8,1) -> 44531 | AU9: =DATE(YEAR($G$3)+1,1,1) -> 44562 | AV9: =DATE(AV7,AV8,1) -> 44562 | AW9: =DATE(AW7,AW8,1) -> 44593 | AX9: =DATE(AX7,AX8,1) -> 44621 | AY9: =DATE(AY7,AY8,1) -> 44652 | AZ9: =DATE(AZ7,AZ8,1) -> 44682 | BA9: =DATE(BA7,BA8,1) -> 44713 | BB9: =DATE(BB7,BB8,1) -> 44743 | BC9: =DATE(BC7,BC8,1) -> 44774 | ... BG9: =DATE(BG7,BG8,1) -> 44896
G10: =EOMONTH(DATE(YEAR($G$3)-1,12,1),0) -> 44196 | H10: =EOMONTH(H9,0) -> 43861 | I10: =EOMONTH(I9,0) -> 43890 | J10: =EOMONTH(J9,0) -> 43921 | K10: =EOMONTH(K9,0) -> 43951 | L10: =EOMONTH(L9,0) -> 43982 | M10: =EOMONTH(M9,0) -> 44012 | N10: =EOMONTH(N9,0) -> 44043 | O10: =EOMONTH(O9,0) -> 44074 | ... S10: =EOMONTH(S9,0) -> 44196 | T10: =EOMONTH(DATE(YEAR($G$3),12,1),0) -> 44561 | U10: =EOMONTH(DATE(YEAR($G$3),MONTH(G3),1),0) -> 44469 | V10: =EOMONTH(V9,0) -> 44227 | W10: =EOMONTH(W9,0) -> 44255 | X10: =EOMONTH(X9,0) -> 44286 | Y10: =EOMONTH(Y9,0) -> 44316 | Z10: =EOMONTH(Z9,0) -> 44347 | AA10: =EOMONTH(AA9,0) -> 44377 | AB10: =EOMONTH(AB9,0) -> 44408 | AC10: =EOMONTH(AC9,0) -> 44439 | ... AG10: =EOMONTH(AG9,0) -> 44561 | AH10: =EOMONTH(DATE(YEAR($G$3),12,1),0) -> 44561 | AI10: =EOMONTH(AI9,0) -> 44227 | AJ10: =EOMONTH(AJ9,0) -> 44255 | AK10: =EOMONTH(AK9,0) -> 44286 | AL10: =EOMONTH(AL9,0) -> 44316 | AM10: =EOMONTH(AM9,0) -> 44347 | AN10: =EOMONTH(AN9,0) -> 44377 | AO10: =EOMONTH(AO9,0) -> 44408 | AP10: =EOMONTH(AP9,0) -> 44439 | ... AT10: =EOMONTH(AT9,0) -> 44561 | AU10: =EOMONTH(DATE(YEAR($G$3)+1,12,1),0) -> 44926 | AV10: =EOMONTH(AV9,0) -> 44592 | AW10: =EOMONTH(AW9,0) -> 44620 | AX10: =EOMONTH(AX9,0) -> 44651 | AY10: =EOMONTH(AY9,0) -> 44681 | AZ10: =EOMONTH(AZ9,0) -> 44712 | BA10: =EOMONTH(BA9,0) -> 44742 | BB10: =EOMONTH(BB9,0) -> 44773 | BC10: =EOMONTH(BC9,0) -> 44804 | ... BG10: =EOMONTH(BG9,0) -> 44926
B11: 注册人数
B12: 合计 | E12: * | F12: * | G12: =COUNTIFS(人员状况!$C:$C,$E12,人员状况!$D:$D,$F12,人员状况!$G:$G,"<="&G$10,人员状况!$H:$H,">="&G$10+1) -> 70 | H12: =COUNTIFS(人员状况!$C:$C,$E12,人员状况!$D:$D,$F12,人员状况!$G:$G,"<="&H$10,人员状况!$H:$H,">="&H$10+1) -> 71 | I12: =COUNTIFS(人员状况!$C:$C,$E12,人员状况!$D:$D,$F12,人员状况!$G:$G,"<="&I$10,人员状况!$H:$H,">="&I$10+1) -> 71 | J12: =COUNTIFS(人员状况!$C:$C,$E12,人员状况!$D:$D,$F12,人员状况!$G:$G,"<="&J$10,人员状况!$H:$H,">="&J$10+1) -> 71 | K12: =COUNTIFS(人员状况!$C:$C,$E12,人员状况!$D:$D,$F12,人员状况!$G:$G,"<="&K$10,人员状况!$H:$H,">="&K$10+1) -> 71 | L12: =COUNTIFS(人员状况!$C:$C,$E12,人员状况!$D:$D,$F12,人员状况!$G:$G,"<="&L$10,人员状况!$H:$H,">="&L$10+1) -> 71 | M12: =COUNTIFS(人员状况!$C:$C,$E12,人员状况!$D:$D,$F12,人员状况!$G:$G,"<="&M$10,人员状况!$H:$H,">="&M$10+1) -> 71 | N12: =COUNTIFS(人员状况!$C:$C,$E12,人员状况!$D:$D,$F12,人员状况!$G:$G,"<="&N$10,人员状况!$H:$H,">="&N$10+1) -> 71 | ... S12: =COUNTIFS(人员状况!$C:$C,$E12,人员状况!$D:$D,$F12,人员状况!$G:$G,"<="&S$10,人员状况!$H:$H,">="&S$10+1) -> 70 | T12: =AT12 -> 68 | U12: =COUNTIFS(人员状况!$C:$C,$E12,人员状况!$D:$D,$F12,人员状况!$G:$G,"<="&U$10,人员状况!$H:$H,">="&U$10+1) -> 69 | V12: =IF(MONTH($G$3)>=V$8,COUNTIFS(人员状况!$C:$C,$E12,人员状况!$D:$D,$F12,人员状况!$G:$G,"<="&V$10,人员状况!$H:$H,">="&V$10+1),0) -> 70 | W12: =IF(MONTH($G$3)>=W$8,COUNTIFS(人员状况!$C:$C,$E12,人员状况!$D:$D,$F12,人员状况!$G:$G,"<="&W$10,人员状况!$H:$H,">="&W$10+1),0) -> 70 | X12: =IF(MONTH($G$3)>=X$8,COUNTIFS(人员状况!$C:$C,$E12,人员状况!$D:$D,$F12,人员状况!$G:$G,"<="&X$10,人员状况!$H:$H,">="&X$10+1),0) -> 70 | Y12: =IF(MONTH($G$3)>=Y$8,COUNTIFS(人员状况!$C:$C,$E12,人员状况!$D:$D,$F12,人员状况!$G:$G,"<="&Y$10,人员状况!$H:$H,">="&Y$10+1),0) -> 68 | Z12: =IF(MONTH($G$3)>=Z$8,COUNTIFS(人员状况!$C:$C,$E12,人员状况!$D:$D,$F12,人员状况!$G:$G,"<="&Z$10,人员状况!$H:$H,">="&Z$10+1),0) -> 69 | AA12: =IF(MONTH($G$3)>=AA$8,COUNTIFS(人员状况!$C:$C,$E12,人员状况!$D:$D,$F12,人员状况!$G:$G,"<="&AA$10,人员状况!$H:$H,">="&AA$10+1),0) -> 69 | AB12: =IF(MONTH($G$3)>=AB$8,COUNTIFS(人员状况!$C:$C,$E12,人员状况!$D:$D,$F12,人员状况!$G:$G,"<="&AB$10,人员状况!$H:$H,">="&AB$10+1),0) -> 70 | AC12: =IF(MONTH($G$3)>=AC$8,COUNTIFS(人员状况!$C:$C,$E12,人员状况!$D:$D,$F12,人员状况!$G:$G,"<="&AC$10,人员状况!$H:$H,">="&AC$10+1),0) -> 69 | ... AG12: =IF(MONTH($G$3)>=AG$8,COUNTIFS(人员状况!$C:$C,$E12,人员状况!$D:$D,$F12,人员状况!$G:$G,"<="&AG$10,人员状况!$H:$H,">="&AG$10+1),0) -> 0 | AH12: =AT12 -> 68 | AI12: =IF(MONTH($G$3)>=AI$8,0,S12+SUMIFS(预计变动!$F:$F,预计变动!$A:$A,$E12,预计变动!$B:$B,$F12,预计变动!$I:$I,">="&AI$9,预计变动!$I:$I,"<="&AI$10)) -> 0 | AJ12: =IF(MONTH($G$3)>=AJ$8,0,IF(V12=0,AI12,V12)+SUMIFS(预计变动!$F:$F,预计变动!$A:$A,$E12,预计变动!$B:$B,$F12,预计变动!$I:$I,">="&AJ$9,预计变动!$I:$I,"<="&AJ$10)) -> 0 | AK12: =IF(MONTH($G$3)>=AK$8,0,IF(W12=0,AJ12,W12)+SUMIFS(预计变动!$F:$F,预计变动!$A:$A,$E12,预计变动!$B:$B,$F12,预计变动!$I:$I,">="&AK$9,预计变动!$I:$I,"<="&AK$10)) -> 0 | AL12: =IF(MONTH($G$3)>=AL$8,0,IF(X12=0,AK12,X12)+SUMIFS(预计变动!$F:$F,预计变动!$A:$A,$E12,预计变动!$B:$B,$F12,预计变动!$I:$I,">="&AL$9,预计变动!$I:$I,"<="&AL$10)) -> 0 | AM12: =IF(MONTH($G$3)>=AM$8,0,IF(Y12=0,AL12,Y12)+SUMIFS(预计变动!$F:$F,预计变动!$A:$A,$E12,预计变动!$B:$B,$F12,预计变动!$I:$I,">="&AM$9,预计变动!$I:$I,"<="&AM$10)) -> 0 | AN12: =IF(MONTH($G$3)>=AN$8,0,IF(Z12=0,AM12,Z12)+SUMIFS(预计变动!$F:$F,预计变动!$A:$A,$E12,预计变动!$B:$B,$F12,预计变动!$I:$I,">="&AN$9,预计变动!$I:$I,"<="&AN$10)) -> 0 | AO12: =IF(MONTH($G$3)>=AO$8,0,IF(AA12=0,AN12,AA12)+SUMIFS(预计变动!$F:$F,预计变动!$A:$A,$E12,预计变动!$B:$B,$F12,预计变动!$I:$I,">="&AO$9,预计变动!$I:$I,"<="&AO$10)) -> 0 | AP12: =IF(MONTH($G$3)>=AP$8,0,IF(AB12=0,AO12,AB12)+SUMIFS(预计变动!$F:$F,预计变动!$A:$A,$E12,预计变动!$B:$B,$F12,预计变动!$I:$I,">="&AP$9,预计变动!$I:$I,"<="&AP$10)) -> 0 | AQ12: =IF(MONTH($G$3)>=AQ$8,0,IF(AC12=0,AP12,AC12)+SUMIFS(预计变动!$F:$F,预计变动!$A:$A,$E12,预计变动!$B:$B,$F12,预计变动!$I:$I,">="&AQ$9,预计变动!$I:$I,"<="&AQ$10)) -> 0 | AR12: =IF(MONTH($G$3)>AR$8,0,IF(AD12=0,AQ12,AD12)+SUMIFS(预计变动!$F:$F,预计变动!$A:$A,$E12,预计变动!$B:$B,$F12,预计变动!$I:$I,">="&AR$9,预计变动!$I:$I,"<="&AR$10)) -> 69 | AS12: =IF(MONTH($G$3)>AS$8,0,IF(AE12=0,AR12,AE12)+SUMIFS(预计变动!$F:$F,预计变动!$A:$A,$E12,预计变动!$B:$B,$F12,预计变动!$I:$I,">="&AS$9,预计变动!$I:$I,"<="&AS$10)) -> 70 | AT12: =IF(MONTH($G$3)>AT$8,0,IF(AF12=0,AS12,AF12)+SUMIFS(预计变动!$F:$F,预计变动!$A:$A,$E12,预计变动!$B:$B,$F12,预计变动!$I:$I,">="&AT$9,预计变动!$I:$I,"<="&AT$10)) -> 68 | AU12: =BG12 -> 74 | AV12: =AT12+SUMIFS(预计变动!$F:$F,预计变动!$A:$A,$E12,预计变动!$B:$B,$F12,预计变动!$I:$I,">="&AV$9,预计变动!$I:$I,"<="&AV$10) -> 68 | AW12: =AV12+SUMIFS(预计变动!$F:$F,预计变动!$A:$A,$E12,预计变动!$B:$B,$F12,预计变动!$I:$I,">="&AW$9,预计变动!$I:$I,"<="&AW$10) -> 68 | AX12: =AW12+SUMIFS(预计变动!$F:$F,预计变动!$A:$A,$E12,预计变动!$B:$B,$F12,预计变动!$I:$I,">="&AX$9,预计变动!$I:$I,"<="&AX$10) -> 73 | AY12: =AX12+SUMIFS(预计变动!$F:$F,预计变动!$A:$A,$E12,预计变动!$B:$B,$F12,预计变动!$I:$I,">="&AY$9,预计变动!$I:$I,"<="&AY$10) -> 73 | AZ12: =AY12+SUMIFS(预计变动!$F:$F,预计变动!$A:$A,$E12,预计变动!$B:$B,$F12,预计变动!$I:$I,">="&AZ$9,预计变动!$I:$I,"<="&AZ$10) -> 74 | BA12: =AZ12+SUMIFS(预计变动!$F:$F,预计变动!$A:$A,$E12,预计变动!$B:$B,$F12,预计变动!$I:$I,">="&BA$9,预计变动!$I:$I,"<="&BA$10) -> 74 | BB12: =BA12+SUMIFS(预计变动!$F:$F,预计变动!$A:$A,$E12,预计变动!$B:$B,$F12,预计变动!$I:$I,">="&BB$9,预计变动!$I:$I,"<="&BB$10) -> 74 | BC12: =BB12+SUMIFS(预计变动!$F:$F,预计变动!$A:$A,$E12,预计变动!$B:$B,$F12,预计变动!$I:$I,">="&BC$9,预计变动!$I:$I,"<="&BC$10) -> 74 | BD12: =BC12+SUMIFS(预计变动!$F:$F,预计变动!$A:$A,$E12,预计变动!$B:$B,$F12,预计变动!$I:$I,">="&BD$9,预计变动!$I:$I,"<="&BD$10) -> 74 | ... BG12: =BF12+SUMIFS(预计变动!$F:$F,预计变动!$A:$A,$E12,预计变动!$B:$B,$F12,预计变动!$I:$I,">="&BG$9,预计变动!$I:$I,"<="&BG$10) -> 74
C13: 流程中心 | E13: =IF(C13<>"",C13,#REF!) -> 流程中心 | F13: =IF(D13<>"",D13,"*") -> * | G13: =COUNTIFS(人员状况!$C:$C,$E13,人员状况!$D:$D,$F13,人员状况!$G:$G,"<="&G$10,人员状况!$H:$H,">="&G$10+1) -> 34 | H13: =COUNTIFS(人员状况!$C:$C,$E13,人员状况!$D:$D,$F13,人员状况!$G:$G,"<="&H$10,人员状况!$H:$H,">="&H$10+1) -> 35 | I13: =COUNTIFS(人员状况!$C:$C,$E13,人员状况!$D:$D,$F13,人员状况!$G:$G,"<="&I$10,人员状况!$H:$H,">="&I$10+1) -> 35 | J13: =COUNTIFS(人员状况!$C:$C,$E13,人员状况!$D:$D,$F13,人员状况!$G:$G,"<="&J$10,人员状况!$H:$H,">="&J$10+1) -> 35 | K13: =COUNTIFS(人员状况!$C:$C,$E13,人员状况!$D:$D,$F13,人员状况!$G:$G,"<="&K$10,人员状况!$H:$H,">="&K$10+1) -> 35 | L13: =COUNTIFS(人员状况!$C:$C,$E13,人员状况!$D:$D,$F13,人员状况!$G:$G,"<="&L$10,人员状况!$H:$H,">="&L$10+1) -> 35 | M13: =COUNTIFS(人员状况!$C:$C,$E13,人员状况!$D:$D,$F13,人员状况!$G:$G,"<="&M$10,人员状况!$H:$H,">="&M$10+1) -> 35 | N13: =COUNTIFS(人员状况!$C:$C,$E13,人员状况!$D:$D,$F13,人员状况!$G:$G,"<="&N$10,人员状况!$H:$H,">="&N$10+1) -> 35 | ... S13: =COUNTIFS(人员状况!$C:$C,$E13,人员状况!$D:$D,$F13,人员状况!$G:$G,"<="&S$10,人员状况!$H:$H,">="&S$10+1) -> 34 | T13: =AT13 -> 31 | U13: =COUNTIFS(人员状况!$C:$C,$E13,人员状况!$D:$D,$F13,人员状况!$G:$G,"<="&U$10,人员状况!$H:$H,">="&U$10+1) -> 32 | V13: =IF(MONTH($G$3)>=V$8,COUNTIFS(人员状况!$C:$C,$E13,人员状况!$D:$D,$F13,人员状况!$G:$G,"<="&V$10,人员状况!$H:$H,">="&V$10+1),0) -> 34 | W13: =IF(MONTH($G$3)>=W$8,COUNTIFS(人员状况!$C:$C,$E13,人员状况!$D:$D,$F13,人员状况!$G:$G,"<="&W$10,人员状况!$H:$H,">="&W$10+1),0) -> 34 | X13: =IF(MONTH($G$3)>=X$8,COUNTIFS(人员状况!$C:$C,$E13,人员状况!$D:$D,$F13,人员状况!$G:$G,"<="&X$10,人员状况!$H:$H,">="&X$10+1),0) -> 34 | Y13: =IF(MONTH($G$3)>=Y$8,COUNTIFS(人员状况!$C:$C,$E13,人员状况!$D:$D,$F13,人员状况!$G:$G,"<="&Y$10,人员状况!$H:$H,">="&Y$10+1),0) -> 32 | Z13: =IF(MONTH($G$3)>=Z$8,COUNTIFS(人员状况!$C:$C,$E13,人员状况!$D:$D,$F13,人员状况!$G:$G,"<="&Z$10,人员状况!$H:$H,">="&Z$10+1),0) -> 33 | AA13: =IF(MONTH($G$3)>=AA$8,COUNTIFS(人员状况!$C:$C,$E13,人员状况!$D:$D,$F13,人员状况!$G:$G,"<="&AA$10,人员状况!$H:$H,">="&AA$10+1),0) -> 33 | AB13: =IF(MONTH($G$3)>=AB$8,COUNTIFS(人员状况!$C:$C,$E13,人员状况!$D:$D,$F13,人员状况!$G:$G,"<="&AB$10,人员状况!$H:$H,">="&AB$10+1),0) -> 33 | AC13: =IF(MONTH($G$3)>=AC$8,COUNTIFS(人员状况!$C:$C,$E13,人员状况!$D:$D,$F13,人员状况!$G:$G,"<="&AC$10,人员状况!$H:$H,">="&AC$10+1),0) -> 32 | ... AG13: =IF(MONTH($G$3)>=AG$8,COUNTIFS(人员状况!$C:$C,$E13,人员状况!$D:$D,$F13,人员状况!$G:$G,"<="&AG$10,人员状况!$H:$H,">="&AG$10+1),0) -> 0 | AH13: =AT13 -> 31 | AI13: =IF(MONTH($G$3)>=AI$8,0,S13+SUMIFS(预计变动!$F:$F,预计变动!$A:$A,$E13,预计变动!$B:$B,$F13,预计变动!$I:$I,">="&AI$9,预计变动!$I:$I,"<="&AI$10)) -> 0 | AJ13: =IF(MONTH($G$3)>=AJ$8,0,IF(V13=0,AI13,V13)+SUMIFS(预计变动!$F:$F,预计变动!$A:$A,$E13,预计变动!$B:$B,$F13,预计变动!$I:$I,">="&AJ$9,预计变动!$I:$I,"<="&AJ$10)) -> 0 | AK13: =IF(MONTH($G$3)>=AK$8,0,IF(W13=0,AJ13,W13)+SUMIFS(预计变动!$F:$F,预计变动!$A:$A,$E13,预计变动!$B:$B,$F13,预计变动!$I:$I,">="&AK$9,预计变动!$I:$I,"<="&AK$10)) -> 0 | AL13: =IF(MONTH($G$3)>=AL$8,0,IF(X13=0,AK13,X13)+SUMIFS(预计变动!$F:$F,预计变动!$A:$A,$E13,预计变动!$B:$B,$F13,预计变动!$I:$I,">="&AL$9,预计变动!$I:$I,"<="&AL$10)) -> 0 | AM13: =IF(MONTH($G$3)>=AM$8,0,IF(Y13=0,AL13,Y13)+SUMIFS(预计变动!$F:$F,预计变动!$A:$A,$E13,预计变动!$B:$B,$F13,预计变动!$I:$I,">="&AM$9,预计变动!$I:$I,"<="&AM$10)) -> 0 | AN13: =IF(MONTH($G$3)>=AN$8,0,IF(Z13=0,AM13,Z13)+SUMIFS(预计变动!$F:$F,预计变动!$A:$A,$E13,预计变动!$B:$B,$F13,预计变动!$I:$I,">="&AN$9,预计变动!$I:$I,"<="&AN$10)) -> 0 | AO13: =IF(MONTH($G$3)>=AO$8,0,IF(AA13=0,AN13,AA13)+SUMIFS(预计变动!$F:$F,预计变动!$A:$A,$E13,预计变动!$B:$B,$F13,预计变动!$I:$I,">="&AO$9,预计变动!$I:$I,"<="&AO$10)) -> 0 | AP13: =IF(MONTH($G$3)>=AP$8,0,IF(AB13=0,AO13,AB13)+SUMIFS(预计变动!$F:$F,预计变动!$A:$A,$E13,预计变动!$B:$B,$F13,预计变动!$I:$I,">="&AP$9,预计变动!$I:$I,"<="&AP$10)) -> 0 | AQ13: =IF(MONTH($G$3)>=AQ$8,0,IF(AC13=0,AP13,AC13)+SUMIFS(预计变动!$F:$F,预计变动!$A:$A,$E13,预计变动!$B:$B,$F13,预计变动!$I:$I,">="&AQ$9,预计变动!$I:$I,"<="&AQ$10)) -> 0 | AR13: =IF(MONTH($G$3)>AR$8,0,IF(AD13=0,AQ13,AD13)+SUMIFS(预计变动!$F:$F,预计变动!$A:$A,$E13,预计变动!$B:$B,$F13,预计变动!$I:$I,">="&AR$9,预计变动!$I:$I,"<="&AR$10)) -> 32 | AS13: =IF(MONTH($G$3)>AS$8,0,IF(AE13=0,AR13,AE13)+SUMIFS(预计变动!$F:$F,预计变动!$A:$A,$E13,预计变动!$B:$B,$F13,预计变动!$I:$I,">="&AS$9,预计变动!$I:$I,"<="&AS$10)) -> 33 | AT13: =IF(MONTH($G$3)>AT$8,0,IF(AF13=0,AS13,AF13)+SUMIFS(预计变动!$F:$F,预计变动!$A:$A,$E13,预计变动!$B:$B,$F13,预计变动!$I:$I,">="&AT$9,预计变动!$I:$I,"<="&AT$10)) -> 31 | AU13: =BG13 -> 37 | AV13: =AT13+SUMIFS(预计变动!$F:$F,预计变动!$A:$A,$E13,预计变动!$B:$B,$F13,预计变动!$I:$I,">="&AV$9,预计变动!$I:$I,"<="&AV$10) -> 31 | AW13: =AV13+SUMIFS(预计变动!$F:$F,预计变动!$A:$A,$E13,预计变动!$B:$B,$F13,预计变动!$I:$I,">="&AW$9,预计变动!$I:$I,"<="&AW$10) -> 31 | AX13: =AW13+SUMIFS(预计变动!$F:$F,预计变动!$A:$A,$E13,预计变动!$B:$B,$F13,预计变动!$I:$I,">="&AX$9,预计变动!$I:$I,"<="&AX$10) -> 36 | AY13: =AX13+SUMIFS(预计变动!$F:$F,预计变动!$A:$A,$E13,预计变动!$B:$B,$F13,预计变动!$I:$I,">="&AY$9,预计变动!$I:$I,"<="&AY$10) -> 36 | AZ13: =AY13+SUMIFS(预计变动!$F:$F,预计变动!$A:$A,$E13,预计变动!$B:$B,$F13,预计变动!$I:$I,">="&AZ$9,预计变动!$I:$I,"<="&AZ$10) -> 37 | BA13: =AZ13+SUMIFS(预计变动!$F:$F,预计变动!$A:$A,$E13,预计变动!$B:$B,$F13,预计变动!$I:$I,">="&BA$9,预计变动!$I:$I,"<="&BA$10) -> 37 | BB13: =BA13+SUMIFS(预计变动!$F:$F,预计变动!$A:$A,$E13,预计变动!$B:$B,$F13,预计变动!$I:$I,">="&BB$9,预计变动!$I:$I,"<="&BB$10) -> 37 | BC13: =BB13+SUMIFS(预计变动!$F:$F,预计变动!$A:$A,$E13,预计变动!$B:$B,$F13,预计变动!$I:$I,">="&BC$9,预计变动!$I:$I,"<="&BC$10) -> 37 | BD13: =BC13+SUMIFS(预计变动!$F:$F,预计变动!$A:$A,$E13,预计变动!$B:$B,$F13,预计变动!$I:$I,">="&BD$9,预计变动!$I:$I,"<="&BD$10) -> 37 | ... BG13: =BF13+SUMIFS(预计变动!$F:$F,预计变动!$A:$A,$E13,预计变动!$B:$B,$F13,预计变动!$I:$I,">="&BG$9,预计变动!$I:$I,"<="&BG$10) -> 37
D14: 销售中心 | E14: =IF(C14<>"",C14,E13) -> 流程中心 | F14: =IF(D14<>"",D14,"*") -> 销售中心 | G14: =COUNTIFS(人员状况!$C:$C,$E14,人员状况!$D:$D,$F14,人员状况!$G:$G,"<="&G$10,人员状况!$H:$H,">="&G$10+1) -> 13 | H14: =COUNTIFS(人员状况!$C:$C,$E14,人员状况!$D:$D,$F14,人员状况!$G:$G,"<="&H$10,人员状况!$H:$H,">="&H$10+1) -> 13 | I14: =COUNTIFS(人员状况!$C:$C,$E14,人员状况!$D:$D,$F14,人员状况!$G:$G,"<="&I$10,人员状况!$H:$H,">="&I$10+1) -> 13 | J14: =COUNTIFS(人员状况!$C:$C,$E14,人员状况!$D:$D,$F14,人员状况!$G:$G,"<="&J$10,人员状况!$H:$H,">="&J$10+1) -> 13 | K14: =COUNTIFS(人员状况!$C:$C,$E14,人员状况!$D:$D,$F14,人员状况!$G:$G,"<="&K$10,人员状况!$H:$H,">="&K$10+1) -> 13 | L14: =COUNTIFS(人员状况!$C:$C,$E14,人员状况!$D:$D,$F14,人员状况!$G:$G,"<="&L$10,人员状况!$H:$H,">="&L$10+1) -> 13 | M14: =COUNTIFS(人员状况!$C:$C,$E14,人员状况!$D:$D,$F14,人员状况!$G:$G,"<="&M$10,人员状况!$H:$H,">="&M$10+1) -> 13 | N14: =COUNTIFS(人员状况!$C:$C,$E14,人员状况!$D:$D,$F14,人员状况!$G:$G,"<="&N$10,人员状况!$H:$H,">="&N$10+1) -> 13 | ... S14: =COUNTIFS(人员状况!$C:$C,$E14,人员状况!$D:$D,$F14,人员状况!$G:$G,"<="&S$10,人员状况!$H:$H,">="&S$10+1) -> 13 | T14: =AT14 -> 13 | U14: =COUNTIFS(人员状况!$C:$C,$E14,人员状况!$D:$D,$F14,人员状况!$G:$G,"<="&U$10,人员状况!$H:$H,">="&U$10+1) -> 13 | V14: =IF(MONTH($G$3)>=V$8,COUNTIFS(人员状况!$C:$C,$E14,人员状况!$D:$D,$F14,人员状况!$G:$G,"<="&V$10,人员状况!$H:$H,">="&V$10+1),0) -> 13 | W14: =IF(MONTH($G$3)>=W$8,COUNTIFS(人员状况!$C:$C,$E14,人员状况!$D:$D,$F14,人员状况!$G:$G,"<="&W$10,人员状况!$H:$H,">="&W$10+1),0) -> 13 | X14: =IF(MONTH($G$3)>=X$8,COUNTIFS(人员状况!$C:$C,$E14,人员状况!$D:$D,$F14,人员状况!$G:$G,"<="&X$10,人员状况!$H:$H,">="&X$10+1),0) -> 13 | Y14: =IF(MONTH($G$3)>=Y$8,COUNTIFS(人员状况!$C:$C,$E14,人员状况!$D:$D,$F14,人员状况!$G:$G,"<="&Y$10,人员状况!$H:$H,">="&Y$10+1),0) -> 13 | Z14: =IF(MONTH($G$3)>=Z$8,COUNTIFS(人员状况!$C:$C,$E14,人员状况!$D:$D,$F14,人员状况!$G:$G,"<="&Z$10,人员状况!$H:$H,">="&Z$10+1),0) -> 14 | AA14: =IF(MONTH($G$3)>=AA$8,COUNTIFS(人员状况!$C:$C,$E14,人员状况!$D:$D,$F14,人员状况!$G:$G,"<="&AA$10,人员状况!$H:$H,">="&AA$10+1),0) -> 14 | AB14: =IF(MONTH($G$3)>=AB$8,COUNTIFS(人员状况!$C:$C,$E14,人员状况!$D:$D,$F14,人员状况!$G:$G,"<="&AB$10,人员状况!$H:$H,">="&AB$10+1),0) -> 14 | AC14: =IF(MONTH($G$3)>=AC$8,COUNTIFS(人员状况!$C:$C,$E14,人员状况!$D:$D,$F14,人员状况!$G:$G,"<="&AC$10,人员状况!$H:$H,">="&AC$10+1),0) -> 13 | ... AG14: =IF(MONTH($G$3)>=AG$8,COUNTIFS(人员状况!$C:$C,$E14,人员状况!$D:$D,$F14,人员状况!$G:$G,"<="&AG$10,人员状况!$H:$H,">="&AG$10+1),0) -> 0 | AH14: =AT14 -> 13 | AI14: =IF(MONTH($G$3)>=AI$8,0,S14+SUMIFS(预计变动!$F:$F,预计变动!$A:$A,$E14,预计变动!$B:$B,$F14,预计变动!$I:$I,">="&AI$9,预计变动!$I:$I,"<="&AI$10)) -> 0 | AJ14: =IF(MONTH($G$3)>=AJ$8,0,IF(V14=0,AI14,V14)+SUMIFS(预计变动!$F:$F,预计变动!$A:$A,$E14,预计变动!$B:$B,$F14,预计变动!$I:$I,">="&AJ$9,预计变动!$I:$I,"<="&AJ$10)) -> 0 | AK14: =IF(MONTH($G$3)>=AK$8,0,IF(W14=0,AJ14,W14)+SUMIFS(预计变动!$F:$F,预计变动!$A:$A,$E14,预计变动!$B:$B,$F14,预计变动!$I:$I,">="&AK$9,预计变动!$I:$I,"<="&AK$10)) -> 0 | AL14: =IF(MONTH($G$3)>=AL$8,0,IF(X14=0,AK14,X14)+SUMIFS(预计变动!$F:$F,预计变动!$A:$A,$E14,预计变动!$B:$B,$F14,预计变动!$I:$I,">="&AL$9,预计变动!$I:$I,"<="&AL$10)) -> 0 | AM14: =IF(MONTH($G$3)>=AM$8,0,IF(Y14=0,AL14,Y14)+SUMIFS(预计变动!$F:$F,预计变动!$A:$A,$E14,预计变动!$B:$B,$F14,预计变动!$I:$I,">="&AM$9,预计变动!$I:$I,"<="&AM$10)) -> 0 | AN14: =IF(MONTH($G$3)>=AN$8,0,IF(Z14=0,AM14,Z14)+SUMIFS(预计变动!$F:$F,预计变动!$A:$A,$E14,预计变动!$B:$B,$F14,预计变动!$I:$I,">="&AN$9,预计变动!$I:$I,"<="&AN$10)) -> 0 | AO14: =IF(MONTH($G$3)>=AO$8,0,IF(AA14=0,AN14,AA14)+SUMIFS(预计变动!$F:$F,预计变动!$A:$A,$E14,预计变动!$B:$B,$F14,预计变动!$I:$I,">="&AO$9,预计变动!$I:$I,"<="&AO$10)) -> 0 | AP14: =IF(MONTH($G$3)>=AP$8,0,IF(AB14=0,AO14,AB14)+SUMIFS(预计变动!$F:$F,预计变动!$A:$A,$E14,预计变动!$B:$B,$F14,预计变动!$I:$I,">="&AP$9,预计变动!$I:$I,"<="&AP$10)) -> 0 | AQ14: =IF(MONTH($G$3)>=AQ$8,0,IF(AC14=0,AP14,AC14)+SUMIFS(预计变动!$F:$F,预计变动!$A:$A,$E14,预计变动!$B:$B,$F14,预计变动!$I:$I,">="&AQ$9,预计变动!$I:$I,"<="&AQ$10)) -> 0 | AR14: =IF(MONTH($G$3)>AR$8,0,IF(AD14=0,AQ14,AD14)+SUMIFS(预计变动!$F:$F,预计变动!$A:$A,$E14,预计变动!$B:$B,$F14,预计变动!$I:$I,">="&AR$9,预计变动!$I:$I,"<="&AR$10)) -> 13 | AS14: =IF(MONTH($G$3)>AS$8,0,IF(AE14=0,AR14,AE14)+SUMIFS(预计变动!$F:$F,预计变动!$A:$A,$E14,预计变动!$B:$B,$F14,预计变动!$I:$I,">="&AS$9,预计变动!$I:$I,"<="&AS$10)) -> 13 | AT14: =IF(MONTH($G$3)>AT$8,0,IF(AF14=0,AS14,AF14)+SUMIFS(预计变动!$F:$F,预计变动!$A:$A,$E14,预计变动!$B:$B,$F14,预计变动!$I:$I,">="&AT$9,预计变动!$I:$I,"<="&AT$10)) -> 13 | AU14: =BG14 -> 14 | AV14: =AT14+SUMIFS(预计变动!$F:$F,预计变动!$A:$A,$E14,预计变动!$B:$B,$F14,预计变动!$I:$I,">="&AV$9,预计变动!$I:$I,"<="&AV$10) -> 13 | AW14: =AV14+SUMIFS(预计变动!$F:$F,预计变动!$A:$A,$E14,预计变动!$B:$B,$F14,预计变动!$I:$I,">="&AW$9,预计变动!$I:$I,"<="&AW$10) -> 13 | AX14: =AW14+SUMIFS(预计变动!$F:$F,预计变动!$A:$A,$E14,预计变动!$B:$B,$F14,预计变动!$I:$I,">="&AX$9,预计变动!$I:$I,"<="&AX$10) -> 13 | AY14: =AX14+SUMIFS(预计变动!$F:$F,预计变动!$A:$A,$E14,预计变动!$B:$B,$F14,预计变动!$I:$I,">="&AY$9,预计变动!$I:$I,"<="&AY$10) -> 13 | AZ14: =AY14+SUMIFS(预计变动!$F:$F,预计变动!$A:$A,$E14,预计变动!$B:$B,$F14,预计变动!$I:$I,">="&AZ$9,预计变动!$I:$I,"<="&AZ$10) -> 14 | BA14: =AZ14+SUMIFS(预计变动!$F:$F,预计变动!$A:$A,$E14,预计变动!$B:$B,$F14,预计变动!$I:$I,">="&BA$9,预计变动!$I:$I,"<="&BA$10) -> 14 | BB14: =BA14+SUMIFS(预计变动!$F:$F,预计变动!$A:$A,$E14,预计变动!$B:$B,$F14,预计变动!$I:$I,">="&BB$9,预计变动!$I:$I,"<="&BB$10) -> 14 | BC14: =BB14+SUMIFS(预计变动!$F:$F,预计变动!$A:$A,$E14,预计变动!$B:$B,$F14,预计变动!$I:$I,">="&BC$9,预计变动!$I:$I,"<="&BC$10) -> 14 | BD14: =BC14+SUMIFS(预计变动!$F:$F,预计变动!$A:$A,$E14,预计变动!$B:$B,$F14,预计变动!$I:$I,">="&BD$9,预计变动!$I:$I,"<="&BD$10) -> 14 | ... BG14: =BF14+SUMIFS(预计变动!$F:$F,预计变动!$A:$A,$E14,预计变动!$B:$B,$F14,预计变动!$I:$I,">="&BG$9,预计变动!$I:$I,"<="&BG$10) -> 14
D15: 制造中心 | E15: =IF(C15<>"",C15,E14) -> 流程中心 | F15: =IF(D15<>"",D15,"*") -> 制造中心 | G15: =COUNTIFS(人员状况!$C:$C,$E15,人员状况!$D:$D,$F15,人员状况!$G:$G,"<="&G$10,人员状况!$H:$H,">="&G$10+1) -> 21 | H15: =COUNTIFS(人员状况!$C:$C,$E15,人员状况!$D:$D,$F15,人员状况!$G:$G,"<="&H$10,人员状况!$H:$H,">="&H$10+1) -> 22 | I15: =COUNTIFS(人员状况!$C:$C,$E15,人员状况!$D:$D,$F15,人员状况!$G:$G,"<="&I$10,人员状况!$H:$H,">="&I$10+1) -> 22 | J15: =COUNTIFS(人员状况!$C:$C,$E15,人员状况!$D:$D,$F15,人员状况!$G:$G,"<="&J$10,人员状况!$H:$H,">="&J$10+1) -> 22 | K15: =COUNTIFS(人员状况!$C:$C,$E15,人员状况!$D:$D,$F15,人员状况!$G:$G,"<="&K$10,人员状况!$H:$H,">="&K$10+1) -> 22 | L15: =COUNTIFS(人员状况!$C:$C,$E15,人员状况!$D:$D,$F15,人员状况!$G:$G,"<="&L$10,人员状况!$H:$H,">="&L$10+1) -> 22 | M15: =COUNTIFS(人员状况!$C:$C,$E15,人员状况!$D:$D,$F15,人员状况!$G:$G,"<="&M$10,人员状况!$H:$H,">="&M$10+1) -> 22 | N15: =COUNTIFS(人员状况!$C:$C,$E15,人员状况!$D:$D,$F15,人员状况!$G:$G,"<="&N$10,人员状况!$H:$H,">="&N$10+1) -> 22 | ... S15: =COUNTIFS(人员状况!$C:$C,$E15,人员状况!$D:$D,$F15,人员状况!$G:$G,"<="&S$10,人员状况!$H:$H,">="&S$10+1) -> 21 | T15: =AT15 -> 18 | U15: =COUNTIFS(人员状况!$C:$C,$E15,人员状况!$D:$D,$F15,人员状况!$G:$G,"<="&U$10,人员状况!$H:$H,">="&U$10+1) -> 19 | V15: =IF(MONTH($G$3)>=V$8,COUNTIFS(人员状况!$C:$C,$E15,人员状况!$D:$D,$F15,人员状况!$G:$G,"<="&V$10,人员状况!$H:$H,">="&V$10+1),0) -> 21 | W15: =IF(MONTH($G$3)>=W$8,COUNTIFS(人员状况!$C:$C,$E15,人员状况!$D:$D,$F15,人员状况!$G:$G,"<="&W$10,人员状况!$H:$H,">="&W$10+1),0) -> 21 | X15: =IF(MONTH($G$3)>=X$8,COUNTIFS(人员状况!$C:$C,$E15,人员状况!$D:$D,$F15,人员状况!$G:$G,"<="&X$10,人员状况!$H:$H,">="&X$10+1),0) -> 21 | Y15: =IF(MONTH($G$3)>=Y$8,COUNTIFS(人员状况!$C:$C,$E15,人员状况!$D:$D,$F15,人员状况!$G:$G,"<="&Y$10,人员状况!$H:$H,">="&Y$10+1),0) -> 19 | Z15: =IF(MONTH($G$3)>=Z$8,COUNTIFS(人员状况!$C:$C,$E15,人员状况!$D:$D,$F15,人员状况!$G:$G,"<="&Z$10,人员状况!$H:$H,">="&Z$10+1),0) -> 19 | AA15: =IF(MONTH($G$3)>=AA$8,COUNTIFS(人员状况!$C:$C,$E15,人员状况!$D:$D,$F15,人员状况!$G:$G,"<="&AA$10,人员状况!$H:$H,">="&AA$10+1),0) -> 19 | AB15: =IF(MONTH($G$3)>=AB$8,COUNTIFS(人员状况!$C:$C,$E15,人员状况!$D:$D,$F15,人员状况!$G:$G,"<="&AB$10,人员状况!$H:$H,">="&AB$10+1),0) -> 19 | AC15: =IF(MONTH($G$3)>=AC$8,COUNTIFS(人员状况!$C:$C,$E15,人员状况!$D:$D,$F15,人员状况!$G:$G,"<="&AC$10,人员状况!$H:$H,">="&AC$10+1),0) -> 19 | ... AG15: =IF(MONTH($G$3)>=AG$8,COUNTIFS(人员状况!$C:$C,$E15,人员状况!$D:$D,$F15,人员状况!$G:$G,"<="&AG$10,人员状况!$H:$H,">="&AG$10+1),0) -> 0 | AH15: =AT15 -> 18 | AI15: =IF(MONTH($G$3)>=AI$8,0,S15+SUMIFS(预计变动!$F:$F,预计变动!$A:$A,$E15,预计变动!$B:$B,$F15,预计变动!$I:$I,">="&AI$9,预计变动!$I:$I,"<="&AI$10)) -> 0 | AJ15: =IF(MONTH($G$3)>=AJ$8,0,IF(V15=0,AI15,V15)+SUMIFS(预计变动!$F:$F,预计变动!$A:$A,$E15,预计变动!$B:$B,$F15,预计变动!$I:$I,">="&AJ$9,预计变动!$I:$I,"<="&AJ$10)) -> 0 | AK15: =IF(MONTH($G$3)>=AK$8,0,IF(W15=0,AJ15,W15)+SUMIFS(预计变动!$F:$F,预计变动!$A:$A,$E15,预计变动!$B:$B,$F15,预计变动!$I:$I,">="&AK$9,预计变动!$I:$I,"<="&AK$10)) -> 0 | AL15: =IF(MONTH($G$3)>=AL$8,0,IF(X15=0,AK15,X15)+SUMIFS(预计变动!$F:$F,预计变动!$A:$A,$E15,预计变动!$B:$B,$F15,预计变动!$I:$I,">="&AL$9,预计变动!$I:$I,"<="&AL$10)) -> 0 | AM15: =IF(MONTH($G$3)>=AM$8,0,IF(Y15=0,AL15,Y15)+SUMIFS(预计变动!$F:$F,预计变动!$A:$A,$E15,预计变动!$B:$B,$F15,预计变动!$I:$I,">="&AM$9,预计变动!$I:$I,"<="&AM$10)) -> 0 | AN15: =IF(MONTH($G$3)>=AN$8,0,IF(Z15=0,AM15,Z15)+SUMIFS(预计变动!$F:$F,预计变动!$A:$A,$E15,预计变动!$B:$B,$F15,预计变动!$I:$I,">="&AN$9,预计变动!$I:$I,"<="&AN$10)) -> 0 | AO15: =IF(MONTH($G$3)>=AO$8,0,IF(AA15=0,AN15,AA15)+SUMIFS(预计变动!$F:$F,预计变动!$A:$A,$E15,预计变动!$B:$B,$F15,预计变动!$I:$I,">="&AO$9,预计变动!$I:$I,"<="&AO$10)) -> 0 | AP15: =IF(MONTH($G$3)>=AP$8,0,IF(AB15=0,AO15,AB15)+SUMIFS(预计变动!$F:$F,预计变动!$A:$A,$E15,预计变动!$B:$B,$F15,预计变动!$I:$I,">="&AP$9,预计变动!$I:$I,"<="&AP$10)) -> 0 | AQ15: =IF(MONTH($G$3)>=AQ$8,0,IF(AC15=0,AP15,AC15)+SUMIFS(预计变动!$F:$F,预计变动!$A:$A,$E15,预计变动!$B:$B,$F15,预计变动!$I:$I,">="&AQ$9,预计变动!$I:$I,"<="&AQ$10)) -> 0 | AR15: =IF(MONTH($G$3)>AR$8,0,IF(AD15=0,AQ15,AD15)+SUMIFS(预计变动!$F:$F,预计变动!$A:$A,$E15,预计变动!$B:$B,$F15,预计变动!$I:$I,">="&AR$9,预计变动!$I:$I,"<="&AR$10)) -> 19 | AS15: =IF(MONTH($G$3)>AS$8,0,IF(AE15=0,AR15,AE15)+SUMIFS(预计变动!$F:$F,预计变动!$A:$A,$E15,预计变动!$B:$B,$F15,预计变动!$I:$I,">="&AS$9,预计变动!$I:$I,"<="&AS$10)) -> 20 | AT15: =IF(MONTH($G$3)>AT$8,0,IF(AF15=0,AS15,AF15)+SUMIFS(预计变动!$F:$F,预计变动!$A:$A,$E15,预计变动!$B:$B,$F15,预计变动!$I:$I,">="&AT$9,预计变动!$I:$I,"<="&AT$10)) -> 18 | AU15: =BG15 -> 23 | AV15: =AT15+SUMIFS(预计变动!$F:$F,预计变动!$A:$A,$E15,预计变动!$B:$B,$F15,预计变动!$I:$I,">="&AV$9,预计变动!$I:$I,"<="&AV$10) -> 18 | AW15: =AV15+SUMIFS(预计变动!$F:$F,预计变动!$A:$A,$E15,预计变动!$B:$B,$F15,预计变动!$I:$I,">="&AW$9,预计变动!$I:$I,"<="&AW$10) -> 18 | AX15: =AW15+SUMIFS(预计变动!$F:$F,预计变动!$A:$A,$E15,预计变动!$B:$B,$F15,预计变动!$I:$I,">="&AX$9,预计变动!$I:$I,"<="&AX$10) -> 23 | AY15: =AX15+SUMIFS(预计变动!$F:$F,预计变动!$A:$A,$E15,预计变动!$B:$B,$F15,预计变动!$I:$I,">="&AY$9,预计变动!$I:$I,"<="&AY$10) -> 23 | AZ15: =AY15+SUMIFS(预计变动!$F:$F,预计变动!$A:$A,$E15,预计变动!$B:$B,$F15,预计变动!$I:$I,">="&AZ$9,预计变动!$I:$I,"<="&AZ$10) -> 23 | BA15: =AZ15+SUMIFS(预计变动!$F:$F,预计变动!$A:$A,$E15,预计变动!$B:$B,$F15,预计变动!$I:$I,">="&BA$9,预计变动!$I:$I,"<="&BA$10) -> 23 | BB15: =BA15+SUMIFS(预计变动!$F:$F,预计变动!$A:$A,$E15,预计变动!$B:$B,$F15,预计变动!$I:$I,">="&BB$9,预计变动!$I:$I,"<="&BB$10) -> 23 | BC15: =BB15+SUMIFS(预计变动!$F:$F,预计变动!$A:$A,$E15,预计变动!$B:$B,$F15,预计变动!$I:$I,">="&BC$9,预计变动!$I:$I,"<="&BC$10) -> 23 | BD15: =BC15+SUMIFS(预计变动!$F:$F,预计变动!$A:$A,$E15,预计变动!$B:$B,$F15,预计变动!$I:$I,">="&BD$9,预计变动!$I:$I,"<="&BD$10) -> 23 | ... BG15: =BF15+SUMIFS(预计变动!$F:$F,预计变动!$A:$A,$E15,预计变动!$B:$B,$F15,预计变动!$I:$I,">="&BG$9,预计变动!$I:$I,"<="&BG$10) -> 23
C16: 创新中心 | E16: =IF(C16<>"",C16,E15) -> 创新中心 | F16: =IF(D16<>"",D16,"*") -> * | G16: =COUNTIFS(人员状况!$C:$C,$E16,人员状况!$D:$D,$F16,人员状况!$G:$G,"<="&G$10,人员状况!$H:$H,">="&G$10+1) -> 19 | H16: =COUNTIFS(人员状况!$C:$C,$E16,人员状况!$D:$D,$F16,人员状况!$G:$G,"<="&H$10,人员状况!$H:$H,">="&H$10+1) -> 19 | I16: =COUNTIFS(人员状况!$C:$C,$E16,人员状况!$D:$D,$F16,人员状况!$G:$G,"<="&I$10,人员状况!$H:$H,">="&I$10+1) -> 19 | J16: =COUNTIFS(人员状况!$C:$C,$E16,人员状况!$D:$D,$F16,人员状况!$G:$G,"<="&J$10,人员状况!$H:$H,">="&J$10+1) -> 19 | K16: =COUNTIFS(人员状况!$C:$C,$E16,人员状况!$D:$D,$F16,人员状况!$G:$G,"<="&K$10,人员状况!$H:$H,">="&K$10+1) -> 19 | L16: =COUNTIFS(人员状况!$C:$C,$E16,人员状况!$D:$D,$F16,人员状况!$G:$G,"<="&L$10,人员状况!$H:$H,">="&L$10+1) -> 19 | M16: =COUNTIFS(人员状况!$C:$C,$E16,人员状况!$D:$D,$F16,人员状况!$G:$G,"<="&M$10,人员状况!$H:$H,">="&M$10+1) -> 19 | N16: =COUNTIFS(人员状况!$C:$C,$E16,人员状况!$D:$D,$F16,人员状况!$G:$G,"<="&N$10,人员状况!$H:$H,">="&N$10+1) -> 19 | ... S16: =COUNTIFS(人员状况!$C:$C,$E16,人员状况!$D:$D,$F16,人员状况!$G:$G,"<="&S$10,人员状况!$H:$H,">="&S$10+1) -> 19 | T16: =AT16 -> 20 | U16: =COUNTIFS(人员状况!$C:$C,$E16,人员状况!$D:$D,$F16,人员状况!$G:$G,"<="&U$10,人员状况!$H:$H,">="&U$10+1) -> 20 | V16: =IF(MONTH($G$3)>=V$8,COUNTIFS(人员状况!$C:$C,$E16,人员状况!$D:$D,$F16,人员状况!$G:$G,"<="&V$10,人员状况!$H:$H,">="&V$10+1),0) -> 19 | W16: =IF(MONTH($G$3)>=W$8,COUNTIFS(人员状况!$C:$C,$E16,人员状况!$D:$D,$F16,人员状况!$G:$G,"<="&W$10,人员状况!$H:$H,">="&W$10+1),0) -> 19 | X16: =IF(MONTH($G$3)>=X$8,COUNTIFS(人员状况!$C:$C,$E16,人员状况!$D:$D,$F16,人员状况!$G:$G,"<="&X$10,人员状况!$H:$H,">="&X$10+1),0) -> 19 | Y16: =IF(MONTH($G$3)>=Y$8,COUNTIFS(人员状况!$C:$C,$E16,人员状况!$D:$D,$F16,人员状况!$G:$G,"<="&Y$10,人员状况!$H:$H,">="&Y$10+1),0) -> 19 | Z16: =IF(MONTH($G$3)>=Z$8,COUNTIFS(人员状况!$C:$C,$E16,人员状况!$D:$D,$F16,人员状况!$G:$G,"<="&Z$10,人员状况!$H:$H,">="&Z$10+1),0) -> 19 | AA16: =IF(MONTH($G$3)>=AA$8,COUNTIFS(人员状况!$C:$C,$E16,人员状况!$D:$D,$F16,人员状况!$G:$G,"<="&AA$10,人员状况!$H:$H,">="&AA$10+1),0) -> 19 | AB16: =IF(MONTH($G$3)>=AB$8,COUNTIFS(人员状况!$C:$C,$E16,人员状况!$D:$D,$F16,人员状况!$G:$G,"<="&AB$10,人员状况!$H:$H,">="&AB$10+1),0) -> 20 | AC16: =IF(MONTH($G$3)>=AC$8,COUNTIFS(人员状况!$C:$C,$E16,人员状况!$D:$D,$F16,人员状况!$G:$G,"<="&AC$10,人员状况!$H:$H,">="&AC$10+1),0) -> 20 | ... AG16: =IF(MONTH($G$3)>=AG$8,COUNTIFS(人员状况!$C:$C,$E16,人员状况!$D:$D,$F16,人员状况!$G:$G,"<="&AG$10,人员状况!$H:$H,">="&AG$10+1),0) -> 0 | AH16: =AT16 -> 20 | AI16: =IF(MONTH($G$3)>=AI$8,0,S16+SUMIFS(预计变动!$F:$F,预计变动!$A:$A,$E16,预计变动!$B:$B,$F16,预计变动!$I:$I,">="&AI$9,预计变动!$I:$I,"<="&AI$10)) -> 0 | AJ16: =IF(MONTH($G$3)>=AJ$8,0,IF(V16=0,AI16,V16)+SUMIFS(预计变动!$F:$F,预计变动!$A:$A,$E16,预计变动!$B:$B,$F16,预计变动!$I:$I,">="&AJ$9,预计变动!$I:$I,"<="&AJ$10)) -> 0 | AK16: =IF(MONTH($G$3)>=AK$8,0,IF(W16=0,AJ16,W16)+SUMIFS(预计变动!$F:$F,预计变动!$A:$A,$E16,预计变动!$B:$B,$F16,预计变动!$I:$I,">="&AK$9,预计变动!$I:$I,"<="&AK$10)) -> 0 | AL16: =IF(MONTH($G$3)>=AL$8,0,IF(X16=0,AK16,X16)+SUMIFS(预计变动!$F:$F,预计变动!$A:$A,$E16,预计变动!$B:$B,$F16,预计变动!$I:$I,">="&AL$9,预计变动!$I:$I,"<="&AL$10)) -> 0 | AM16: =IF(MONTH($G$3)>=AM$8,0,IF(Y16=0,AL16,Y16)+SUMIFS(预计变动!$F:$F,预计变动!$A:$A,$E16,预计变动!$B:$B,$F16,预计变动!$I:$I,">="&AM$9,预计变动!$I:$I,"<="&AM$10)) -> 0 | AN16: =IF(MONTH($G$3)>=AN$8,0,IF(Z16=0,AM16,Z16)+SUMIFS(预计变动!$F:$F,预计变动!$A:$A,$E16,预计变动!$B:$B,$F16,预计变动!$I:$I,">="&AN$9,预计变动!$I:$I,"<="&AN$10)) -> 0 | AO16: =IF(MONTH($G$3)>=AO$8,0,IF(AA16=0,AN16,AA16)+SUMIFS(预计变动!$F:$F,预计变动!$A:$A,$E16,预计变动!$B:$B,$F16,预计变动!$I:$I,">="&AO$9,预计变动!$I:$I,"<="&AO$10)) -> 0 | AP16: =IF(MONTH($G$3)>=AP$8,0,IF(AB16=0,AO16,AB16)+SUMIFS(预计变动!$F:$F,预计变动!$A:$A,$E16,预计变动!$B:$B,$F16,预计变动!$I:$I,">="&AP$9,预计变动!$I:$I,"<="&AP$10)) -> 0 | AQ16: =IF(MONTH($G$3)>=AQ$8,0,IF(AC16=0,AP16,AC16)+SUMIFS(预计变动!$F:$F,预计变动!$A:$A,$E16,预计变动!$B:$B,$F16,预计变动!$I:$I,">="&AQ$9,预计变动!$I:$I,"<="&AQ$10)) -> 0 | AR16: =IF(MONTH($G$3)>AR$8,0,IF(AD16=0,AQ16,AD16)+SUMIFS(预计变动!$F:$F,预计变动!$A:$A,$E16,预计变动!$B:$B,$F16,预计变动!$I:$I,">="&AR$9,预计变动!$I:$I,"<="&AR$10)) -> 20 | AS16: =IF(MONTH($G$3)>AS$8,0,IF(AE16=0,AR16,AE16)+SUMIFS(预计变动!$F:$F,预计变动!$A:$A,$E16,预计变动!$B:$B,$F16,预计变动!$I:$I,">="&AS$9,预计变动!$I:$I,"<="&AS$10)) -> 20 | AT16: =IF(MONTH($G$3)>AT$8,0,IF(AF16=0,AS16,AF16)+SUMIFS(预计变动!$F:$F,预计变动!$A:$A,$E16,预计变动!$B:$B,$F16,预计变动!$I:$I,">="&AT$9,预计变动!$I:$I,"<="&AT$10)) -> 20 | AU16: =BG16 -> 20 | AV16: =AT16+SUMIFS(预计变动!$F:$F,预计变动!$A:$A,$E16,预计变动!$B:$B,$F16,预计变动!$I:$I,">="&AV$9,预计变动!$I:$I,"<="&AV$10) -> 20 | AW16: =AV16+SUMIFS(预计变动!$F:$F,预计变动!$A:$A,$E16,预计变动!$B:$B,$F16,预计变动!$I:$I,">="&AW$9,预计变动!$I:$I,"<="&AW$10) -> 20 | AX16: =AW16+SUMIFS(预计变动!$F:$F,预计变动!$A:$A,$E16,预计变动!$B:$B,$F16,预计变动!$I:$I,">="&AX$9,预计变动!$I:$I,"<="&AX$10) -> 20 | AY16: =AX16+SUMIFS(预计变动!$F:$F,预计变动!$A:$A,$E16,预计变动!$B:$B,$F16,预计变动!$I:$I,">="&AY$9,预计变动!$I:$I,"<="&AY$10) -> 20 | AZ16: =AY16+SUMIFS(预计变动!$F:$F,预计变动!$A:$A,$E16,预计变动!$B:$B,$F16,预计变动!$I:$I,">="&AZ$9,预计变动!$I:$I,"<="&AZ$10) -> 20 | BA16: =AZ16+SUMIFS(预计变动!$F:$F,预计变动!$A:$A,$E16,预计变动!$B:$B,$F16,预计变动!$I:$I,">="&BA$9,预计变动!$I:$I,"<="&BA$10) -> 20 | BB16: =BA16+SUMIFS(预计变动!$F:$F,预计变动!$A:$A,$E16,预计变动!$B:$B,$F16,预计变动!$I:$I,">="&BB$9,预计变动!$I:$I,"<="&BB$10) -> 20 | BC16: =BB16+SUMIFS(预计变动!$F:$F,预计变动!$A:$A,$E16,预计变动!$B:$B,$F16,预计变动!$I:$I,">="&BC$9,预计变动!$I:$I,"<="&BC$10) -> 20 | BD16: =BC16+SUMIFS(预计变动!$F:$F,预计变动!$A:$A,$E16,预计变动!$B:$B,$F16,预计变动!$I:$I,">="&BD$9,预计变动!$I:$I,"<="&BD$10) -> 20 | ... BG16: =BF16+SUMIFS(预计变动!$F:$F,预计变动!$A:$A,$E16,预计变动!$B:$B,$F16,预计变动!$I:$I,">="&BG$9,预计变动!$I:$I,"<="&BG$10) -> 20
D17: 产品 研发部 | E17: =IF(C17<>"",C17,E16) -> 创新中心 | F17: =IF(D17<>"",D17,"*") -> 产品 研发部 | G17: =COUNTIFS(人员状况!$C:$C,$E17,人员状况!$D:$D,$F17,人员状况!$G:$G,"<="&G$10,人员状况!$H:$H,">="&G$10+1) -> 8 | H17: =COUNTIFS(人员状况!$C:$C,$E17,人员状况!$D:$D,$F17,人员状况!$G:$G,"<="&H$10,人员状况!$H:$H,">="&H$10+1) -> 8 | I17: =COUNTIFS(人员状况!$C:$C,$E17,人员状况!$D:$D,$F17,人员状况!$G:$G,"<="&I$10,人员状况!$H:$H,">="&I$10+1) -> 8 | J17: =COUNTIFS(人员状况!$C:$C,$E17,人员状况!$D:$D,$F17,人员状况!$G:$G,"<="&J$10,人员状况!$H:$H,">="&J$10+1) -> 8 | K17: =COUNTIFS(人员状况!$C:$C,$E17,人员状况!$D:$D,$F17,人员状况!$G:$G,"<="&K$10,人员状况!$H:$H,">="&K$10+1) -> 8 | L17: =COUNTIFS(人员状况!$C:$C,$E17,人员状况!$D:$D,$F17,人员状况!$G:$G,"<="&L$10,人员状况!$H:$H,">="&L$10+1) -> 8 | M17: =COUNTIFS(人员状况!$C:$C,$E17,人员状况!$D:$D,$F17,人员状况!$G:$G,"<="&M$10,人员状况!$H:$H,">="&M$10+1) -> 8 | N17: =COUNTIFS(人员状况!$C:$C,$E17,人员状况!$D:$D,$F17,人员状况!$G:$G,"<="&N$10,人员状况!$H:$H,">="&N$10+1) -> 8 | ... S17: =COUNTIFS(人员状况!$C:$C,$E17,人员状况!$D:$D,$F17,人员状况!$G:$G,"<="&S$10,人员状况!$H:$H,">="&S$10+1) -> 8 | T17: =AT17 -> 8 | U17: =COUNTIFS(人员状况!$C:$C,$E17,人员状况!$D:$D,$F17,人员状况!$G:$G,"<="&U$10,人员状况!$H:$H,">="&U$10+1) -> 8 | V17: =IF(MONTH($G$3)>=V$8,COUNTIFS(人员状况!$C:$C,$E17,人员状况!$D:$D,$F17,人员状况!$G:$G,"<="&V$10,人员状况!$H:$H,">="&V$10+1),0) -> 8 | W17: =IF(MONTH($G$3)>=W$8,COUNTIFS(人员状况!$C:$C,$E17,人员状况!$D:$D,$F17,人员状况!$G:$G,"<="&W$10,人员状况!$H:$H,">="&W$10+1),0) -> 8 | X17: =IF(MONTH($G$3)>=X$8,COUNTIFS(人员状况!$C:$C,$E17,人员状况!$D:$D,$F17,人员状况!$G:$G,"<="&X$10,人员状况!$H:$H,">="&X$10+1),0) -> 8 | Y17: =IF(MONTH($G$3)>=Y$8,COUNTIFS(人员状况!$C:$C,$E17,人员状况!$D:$D,$F17,人员状况!$G:$G,"<="&Y$10,人员状况!$H:$H,">="&Y$10+1),0) -> 8 | Z17: =IF(MONTH($G$3)>=Z$8,COUNTIFS(人员状况!$C:$C,$E17,人员状况!$D:$D,$F17,人员状况!$G:$G,"<="&Z$10,人员状况!$H:$H,">="&Z$10+1),0) -> 8 | AA17: =IF(MONTH($G$3)>=AA$8,COUNTIFS(人员状况!$C:$C,$E17,人员状况!$D:$D,$F17,人员状况!$G:$G,"<="&AA$10,人员状况!$H:$H,">="&AA$10+1),0) -> 8 | AB17: =IF(MONTH($G$3)>=AB$8,COUNTIFS(人员状况!$C:$C,$E17,人员状况!$D:$D,$F17,人员状况!$G:$G,"<="&AB$10,人员状况!$H:$H,">="&AB$10+1),0) -> 8 | AC17: =IF(MONTH($G$3)>=AC$8,COUNTIFS(人员状况!$C:$C,$E17,人员状况!$D:$D,$F17,人员状况!$G:$G,"<="&AC$10,人员状况!$H:$H,">="&AC$10+1),0) -> 8 | ... AG17: =IF(MONTH($G$3)>=AG$8,COUNTIFS(人员状况!$C:$C,$E17,人员状况!$D:$D,$F17,人员状况!$G:$G,"<="&AG$10,人员状况!$H:$H,">="&AG$10+1),0) -> 0 | AH17: =AT17 -> 8 | AI17: =IF(MONTH($G$3)>=AI$8,0,S17+SUMIFS(预计变动!$F:$F,预计变动!$A:$A,$E17,预计变动!$B:$B,$F17,预计变动!$I:$I,">="&AI$9,预计变动!$I:$I,"<="&AI$10)) -> 0 | AJ17: =IF(MONTH($G$3)>=AJ$8,0,IF(V17=0,AI17,V17)+SUMIFS(预计变动!$F:$F,预计变动!$A:$A,$E17,预计变动!$B:$B,$F17,预计变动!$I:$I,">="&AJ$9,预计变动!$I:$I,"<="&AJ$10)) -> 0 | AK17: =IF(MONTH($G$3)>=AK$8,0,IF(W17=0,AJ17,W17)+SUMIFS(预计变动!$F:$F,预计变动!$A:$A,$E17,预计变动!$B:$B,$F17,预计变动!$I:$I,">="&AK$9,预计变动!$I:$I,"<="&AK$10)) -> 0 | AL17: =IF(MONTH($G$3)>=AL$8,0,IF(X17=0,AK17,X17)+SUMIFS(预计变动!$F:$F,预计变动!$A:$A,$E17,预计变动!$B:$B,$F17,预计变动!$I:$I,">="&AL$9,预计变动!$I:$I,"<="&AL$10)) -> 0 | AM17: =IF(MONTH($G$3)>=AM$8,0,IF(Y17=0,AL17,Y17)+SUMIFS(预计变动!$F:$F,预计变动!$A:$A,$E17,预计变动!$B:$B,$F17,预计变动!$I:$I,">="&AM$9,预计变动!$I:$I,"<="&AM$10)) -> 0 | AN17: =IF(MONTH($G$3)>=AN$8,0,IF(Z17=0,AM17,Z17)+SUMIFS(预计变动!$F:$F,预计变动!$A:$A,$E17,预计变动!$B:$B,$F17,预计变动!$I:$I,">="&AN$9,预计变动!$I:$I,"<="&AN$10)) -> 0 | AO17: =IF(MONTH($G$3)>=AO$8,0,IF(AA17=0,AN17,AA17)+SUMIFS(预计变动!$F:$F,预计变动!$A:$A,$E17,预计变动!$B:$B,$F17,预计变动!$I:$I,">="&AO$9,预计变动!$I:$I,"<="&AO$10)) -> 0 | AP17: =IF(MONTH($G$3)>=AP$8,0,IF(AB17=0,AO17,AB17)+SUMIFS(预计变动!$F:$F,预计变动!$A:$A,$E17,预计变动!$B:$B,$F17,预计变动!$I:$I,">="&AP$9,预计变动!$I:$I,"<="&AP$10)) -> 0 | AQ17: =IF(MONTH($G$3)>=AQ$8,0,IF(AC17=0,AP17,AC17)+SUMIFS(预计变动!$F:$F,预计变动!$A:$A,$E17,预计变动!$B:$B,$F17,预计变动!$I:$I,">="&AQ$9,预计变动!$I:$I,"<="&AQ$10)) -> 0 | AR17: =IF(MONTH($G$3)>AR$8,0,IF(AD17=0,AQ17,AD17)+SUMIFS(预计变动!$F:$F,预计变动!$A:$A,$E17,预计变动!$B:$B,$F17,预计变动!$I:$I,">="&AR$9,预计变动!$I:$I,"<="&AR$10)) -> 8 | AS17: =IF(MONTH($G$3)>AS$8,0,IF(AE17=0,AR17,AE17)+SUMIFS(预计变动!$F:$F,预计变动!$A:$A,$E17,预计变动!$B:$B,$F17,预计变动!$I:$I,">="&AS$9,预计变动!$I:$I,"<="&AS$10)) -> 8 | AT17: =IF(MONTH($G$3)>AT$8,0,IF(AF17=0,AS17,AF17)+SUMIFS(预计变动!$F:$F,预计变动!$A:$A,$E17,预计变动!$B:$B,$F17,预计变动!$I:$I,">="&AT$9,预计变动!$I:$I,"<="&AT$10)) -> 8 | AU17: =BG17 -> 8 | AV17: =AT17+SUMIFS(预计变动!$F:$F,预计变动!$A:$A,$E17,预计变动!$B:$B,$F17,预计变动!$I:$I,">="&AV$9,预计变动!$I:$I,"<="&AV$10) -> 8 | AW17: =AV17+SUMIFS(预计变动!$F:$F,预计变动!$A:$A,$E17,预计变动!$B:$B,$F17,预计变动!$I:$I,">="&AW$9,预计变动!$I:$I,"<="&AW$10) -> 8 | AX17: =AW17+SUMIFS(预计变动!$F:$F,预计变动!$A:$A,$E17,预计变动!$B:$B,$F17,预计变动!$I:$I,">="&AX$9,预计变动!$I:$I,"<="&AX$10) -> 8 | AY17: =AX17+SUMIFS(预计变动!$F:$F,预计变动!$A:$A,$E17,预计变动!$B:$B,$F17,预计变动!$I:$I,">="&AY$9,预计变动!$I:$I,"<="&AY$10) -> 8 | AZ17: =AY17+SUMIFS(预计变动!$F:$F,预计变动!$A:$A,$E17,预计变动!$B:$B,$F17,预计变动!$I:$I,">="&AZ$9,预计变动!$I:$I,"<="&AZ$10) -> 8 | BA17: =AZ17+SUMIFS(预计变动!$F:$F,预计变动!$A:$A,$E17,预计变动!$B:$B,$F17,预计变动!$I:$I,">="&BA$9,预计变动!$I:$I,"<="&BA$10) -> 8 | BB17: =BA17+SUMIFS(预计变动!$F:$F,预计变动!$A:$A,$E17,预计变动!$B:$B,$F17,预计变动!$I:$I,">="&BB$9,预计变动!$I:$I,"<="&BB$10) -> 8 | BC17: =BB17+SUMIFS(预计变动!$F:$F,预计变动!$A:$A,$E17,预计变动!$B:$B,$F17,预计变动!$I:$I,">="&BC$9,预计变动!$I:$I,"<="&BC$10) -> 8 | BD17: =BC17+SUMIFS(预计变动!$F:$F,预计变动!$A:$A,$E17,预计变动!$B:$B,$F17,预计变动!$I:$I,">="&BD$9,预计变动!$I:$I,"<="&BD$10) -> 8 | ... BG17: =BF17+SUMIFS(预计变动!$F:$F,预计变动!$A:$A,$E17,预计变动!$B:$B,$F17,预计变动!$I:$I,">="&BG$9,预计变动!$I:$I,"<="&BG$10) -> 8
D18: XX 试验室 | E18: =IF(C18<>"",C18,E17) -> 创新中心 | F18: =IF(D18<>"",D18,"*") -> XX 试验室 | G18: =COUNTIFS(人员状况!$C:$C,$E18,人员状况!$D:$D,$F18,人员状况!$G:$G,"<="&G$10,人员状况!$H:$H,">="&G$10+1) -> 5 | H18: =COUNTIFS(人员状况!$C:$C,$E18,人员状况!$D:$D,$F18,人员状况!$G:$G,"<="&H$10,人员状况!$H:$H,">="&H$10+1) -> 5 | I18: =COUNTIFS(人员状况!$C:$C,$E18,人员状况!$D:$D,$F18,人员状况!$G:$G,"<="&I$10,人员状况!$H:$H,">="&I$10+1) -> 5 | J18: =COUNTIFS(人员状况!$C:$C,$E18,人员状况!$D:$D,$F18,人员状况!$G:$G,"<="&J$10,人员状况!$H:$H,">="&J$10+1) -> 5 | K18: =COUNTIFS(人员状况!$C:$C,$E18,人员状况!$D:$D,$F18,人员状况!$G:$G,"<="&K$10,人员状况!$H:$H,">="&K$10+1) -> 5 | L18: =COUNTIFS(人员状况!$C:$C,$E18,人员状况!$D:$D,$F18,人员状况!$G:$G,"<="&L$10,人员状况!$H:$H,">="&L$10+1) -> 5 | M18: =COUNTIFS(人员状况!$C:$C,$E18,人员状况!$D:$D,$F18,人员状况!$G:$G,"<="&M$10,人员状况!$H:$H,">="&M$10+1) -> 5 | N18: =COUNTIFS(人员状况!$C:$C,$E18,人员状况!$D:$D,$F18,人员状况!$G:$G,"<="&N$10,人员状况!$H:$H,">="&N$10+1) -> 5 | ... S18: =COUNTIFS(人员状况!$C:$C,$E18,人员状况!$D:$D,$F18,人员状况!$G:$G,"<="&S$10,人员状况!$H:$H,">="&S$10+1) -> 5 | T18: =AT18 -> 5 | U18: =COUNTIFS(人员状况!$C:$C,$E18,人员状况!$D:$D,$F18,人员状况!$G:$G,"<="&U$10,人员状况!$H:$H,">="&U$10+1) -> 5 | V18: =IF(MONTH($G$3)>=V$8,COUNTIFS(人员状况!$C:$C,$E18,人员状况!$D:$D,$F18,人员状况!$G:$G,"<="&V$10,人员状况!$H:$H,">="&V$10+1),0) -> 5 | W18: =IF(MONTH($G$3)>=W$8,COUNTIFS(人员状况!$C:$C,$E18,人员状况!$D:$D,$F18,人员状况!$G:$G,"<="&W$10,人员状况!$H:$H,">="&W$10+1),0) -> 5 | X18: =IF(MONTH($G$3)>=X$8,COUNTIFS(人员状况!$C:$C,$E18,人员状况!$D:$D,$F18,人员状况!$G:$G,"<="&X$10,人员状况!$H:$H,">="&X$10+1),0) -> 5 | Y18: =IF(MONTH($G$3)>=Y$8,COUNTIFS(人员状况!$C:$C,$E18,人员状况!$D:$D,$F18,人员状况!$G:$G,"<="&Y$10,人员状况!$H:$H,">="&Y$10+1),0) -> 5 | Z18: =IF(MONTH($G$3)>=Z$8,COUNTIFS(人员状况!$C:$C,$E18,人员状况!$D:$D,$F18,人员状况!$G:$G,"<="&Z$10,人员状况!$H:$H,">="&Z$10+1),0) -> 5 | AA18: =IF(MONTH($G$3)>=AA$8,COUNTIFS(人员状况!$C:$C,$E18,人员状况!$D:$D,$F18,人员状况!$G:$G,"<="&AA$10,人员状况!$H:$H,">="&AA$10+1),0) -> 5 | AB18: =IF(MONTH($G$3)>=AB$8,COUNTIFS(人员状况!$C:$C,$E18,人员状况!$D:$D,$F18,人员状况!$G:$G,"<="&AB$10,人员状况!$H:$H,">="&AB$10+1),0) -> 5 | AC18: =IF(MONTH($G$3)>=AC$8,COUNTIFS(人员状况!$C:$C,$E18,人员状况!$D:$D,$F18,人员状况!$G:$G,"<="&AC$10,人员状况!$H:$H,">="&AC$10+1),0) -> 5 | ... AG18: =IF(MONTH($G$3)>=AG$8,COUNTIFS(人员状况!$C:$C,$E18,人员状况!$D:$D,$F18,人员状况!$G:$G,"<="&AG$10,人员状况!$H:$H,">="&AG$10+1),0) -> 0 | AH18: =AT18 -> 5 | AI18: =IF(MONTH($G$3)>=AI$8,0,S18+SUMIFS(预计变动!$F:$F,预计变动!$A:$A,$E18,预计变动!$B:$B,$F18,预计变动!$I:$I,">="&AI$9,预计变动!$I:$I,"<="&AI$10)) -> 0 | AJ18: =IF(MONTH($G$3)>=AJ$8,0,IF(V18=0,AI18,V18)+SUMIFS(预计变动!$F:$F,预计变动!$A:$A,$E18,预计变动!$B:$B,$F18,预计变动!$I:$I,">="&AJ$9,预计变动!$I:$I,"<="&AJ$10)) -> 0 | AK18: =IF(MONTH($G$3)>=AK$8,0,IF(W18=0,AJ18,W18)+SUMIFS(预计变动!$F:$F,预计变动!$A:$A,$E18,预计变动!$B:$B,$F18,预计变动!$I:$I,">="&AK$9,预计变动!$I:$I,"<="&AK$10)) -> 0 | AL18: =IF(MONTH($G$3)>=AL$8,0,IF(X18=0,AK18,X18)+SUMIFS(预计变动!$F:$F,预计变动!$A:$A,$E18,预计变动!$B:$B,$F18,预计变动!$I:$I,">="&AL$9,预计变动!$I:$I,"<="&AL$10)) -> 0 | AM18: =IF(MONTH($G$3)>=AM$8,0,IF(Y18=0,AL18,Y18)+SUMIFS(预计变动!$F:$F,预计变动!$A:$A,$E18,预计变动!$B:$B,$F18,预计变动!$I:$I,">="&AM$9,预计变动!$I:$I,"<="&AM$10)) -> 0 | AN18: =IF(MONTH($G$3)>=AN$8,0,IF(Z18=0,AM18,Z18)+SUMIFS(预计变动!$F:$F,预计变动!$A:$A,$E18,预计变动!$B:$B,$F18,预计变动!$I:$I,">="&AN$9,预计变动!$I:$I,"<="&AN$10)) -> 0 | AO18: =IF(MONTH($G$3)>=AO$8,0,IF(AA18=0,AN18,AA18)+SUMIFS(预计变动!$F:$F,预计变动!$A:$A,$E18,预计变动!$B:$B,$F18,预计变动!$I:$I,">="&AO$9,预计变动!$I:$I,"<="&AO$10)) -> 0 | AP18: =IF(MONTH($G$3)>=AP$8,0,IF(AB18=0,AO18,AB18)+SUMIFS(预计变动!$F:$F,预计变动!$A:$A,$E18,预计变动!$B:$B,$F18,预计变动!$I:$I,">="&AP$9,预计变动!$I:$I,"<="&AP$10)) -> 0 | AQ18: =IF(MONTH($G$3)>=AQ$8,0,IF(AC18=0,AP18,AC18)+SUMIFS(预计变动!$F:$F,预计变动!$A:$A,$E18,预计变动!$B:$B,$F18,预计变动!$I:$I,">="&AQ$9,预计变动!$I:$I,"<="&AQ$10)) -> 0 | AR18: =IF(MONTH($G$3)>AR$8,0,IF(AD18=0,AQ18,AD18)+SUMIFS(预计变动!$F:$F,预计变动!$A:$A,$E18,预计变动!$B:$B,$F18,预计变动!$I:$I,">="&AR$9,预计变动!$I:$I,"<="&AR$10)) -> 5 | AS18: =IF(MONTH($G$3)>AS$8,0,IF(AE18=0,AR18,AE18)+SUMIFS(预计变动!$F:$F,预计变动!$A:$A,$E18,预计变动!$B:$B,$F18,预计变动!$I:$I,">="&AS$9,预计变动!$I:$I,"<="&AS$10)) -> 5 | AT18: =IF(MONTH($G$3)>AT$8,0,IF(AF18=0,AS18,AF18)+SUMIFS(预计变动!$F:$F,预计变动!$A:$A,$E18,预计变动!$B:$B,$F18,预计变动!$I:$I,">="&AT$9,预计变动!$I:$I,"<="&AT$10)) -> 5 | AU18: =BG18 -> 5 | AV18: =AT18+SUMIFS(预计变动!$F:$F,预计变动!$A:$A,$E18,预计变动!$B:$B,$F18,预计变动!$I:$I,">="&AV$9,预计变动!$I:$I,"<="&AV$10) -> 5 | AW18: =AV18+SUMIFS(预计变动!$F:$F,预计变动!$A:$A,$E18,预计变动!$B:$B,$F18,预计变动!$I:$I,">="&AW$9,预计变动!$I:$I,"<="&AW$10) -> 5 | AX18: =AW18+SUMIFS(预计变动!$F:$F,预计变动!$A:$A,$E18,预计变动!$B:$B,$F18,预计变动!$I:$I,">="&AX$9,预计变动!$I:$I,"<="&AX$10) -> 5 | AY18: =AX18+SUMIFS(预计变动!$F:$F,预计变动!$A:$A,$E18,预计变动!$B:$B,$F18,预计变动!$I:$I,">="&AY$9,预计变动!$I:$I,"<="&AY$10) -> 5 | AZ18: =AY18+SUMIFS(预计变动!$F:$F,预计变动!$A:$A,$E18,预计变动!$B:$B,$F18,预计变动!$I:$I,">="&AZ$9,预计变动!$I:$I,"<="&AZ$10) -> 5 | BA18: =AZ18+SUMIFS(预计变动!$F:$F,预计变动!$A:$A,$E18,预计变动!$B:$B,$F18,预计变动!$I:$I,">="&BA$9,预计变动!$I:$I,"<="&BA$10) -> 5 | BB18: =BA18+SUMIFS(预计变动!$F:$F,预计变动!$A:$A,$E18,预计变动!$B:$B,$F18,预计变动!$I:$I,">="&BB$9,预计变动!$I:$I,"<="&BB$10) -> 5 | BC18: =BB18+SUMIFS(预计变动!$F:$F,预计变动!$A:$A,$E18,预计变动!$B:$B,$F18,预计变动!$I:$I,">="&BC$9,预计变动!$I:$I,"<="&BC$10) -> 5 | BD18: =BC18+SUMIFS(预计变动!$F:$F,预计变动!$A:$A,$E18,预计变动!$B:$B,$F18,预计变动!$I:$I,">="&BD$9,预计变动!$I:$I,"<="&BD$10) -> 5 | ... BG18: =BF18+SUMIFS(预计变动!$F:$F,预计变动!$A:$A,$E18,预计变动!$B:$B,$F18,预计变动!$I:$I,">="&BG$9,预计变动!$I:$I,"<="&BG$10) -> 5
D19: XX 孵化业务 | E19: =IF(C19<>"",C19,E18) -> 创新中心 | F19: =IF(D19<>"",D19,"*") -> XX 孵化业务 | G19: =COUNTIFS(人员状况!$C:$C,$E19,人员状况!$D:$D,$F19,人员状况!$G:$G,"<="&G$10,人员状况!$H:$H,">="&G$10+1) -> 6 | H19: =COUNTIFS(人员状况!$C:$C,$E19,人员状况!$D:$D,$F19,人员状况!$G:$G,"<="&H$10,人员状况!$H:$H,">="&H$10+1) -> 6 | I19: =COUNTIFS(人员状况!$C:$C,$E19,人员状况!$D:$D,$F19,人员状况!$G:$G,"<="&I$10,人员状况!$H:$H,">="&I$10+1) -> 6 | J19: =COUNTIFS(人员状况!$C:$C,$E19,人员状况!$D:$D,$F19,人员状况!$G:$G,"<="&J$10,人员状况!$H:$H,">="&J$10+1) -> 6 | K19: =COUNTIFS(人员状况!$C:$C,$E19,人员状况!$D:$D,$F19,人员状况!$G:$G,"<="&K$10,人员状况!$H:$H,">="&K$10+1) -> 6 | L19: =COUNTIFS(人员状况!$C:$C,$E19,人员状况!$D:$D,$F19,人员状况!$G:$G,"<="&L$10,人员状况!$H:$H,">="&L$10+1) -> 6 | M19: =COUNTIFS(人员状况!$C:$C,$E19,人员状况!$D:$D,$F19,人员状况!$G:$G,"<="&M$10,人员状况!$H:$H,">="&M$10+1) -> 6 | N19: =COUNTIFS(人员状况!$C:$C,$E19,人员状况!$D:$D,$F19,人员状况!$G:$G,"<="&N$10,人员状况!$H:$H,">="&N$10+1) -> 6 | ... S19: =COUNTIFS(人员状况!$C:$C,$E19,人员状况!$D:$D,$F19,人员状况!$G:$G,"<="&S$10,人员状况!$H:$H,">="&S$10+1) -> 6 | T19: =AT19 -> 7 | U19: =COUNTIFS(人员状况!$C:$C,$E19,人员状况!$D:$D,$F19,人员状况!$G:$G,"<="&U$10,人员状况!$H:$H,">="&U$10+1) -> 7 | V19: =IF(MONTH($G$3)>=V$8,COUNTIFS(人员状况!$C:$C,$E19,人员状况!$D:$D,$F19,人员状况!$G:$G,"<="&V$10,人员状况!$H:$H,">="&V$10+1),0) -> 6 | W19: =IF(MONTH($G$3)>=W$8,COUNTIFS(人员状况!$C:$C,$E19,人员状况!$D:$D,$F19,人员状况!$G:$G,"<="&W$10,人员状况!$H:$H,">="&W$10+1),0) -> 6 | X19: =IF(MONTH($G$3)>=X$8,COUNTIFS(人员状况!$C:$C,$E19,人员状况!$D:$D,$F19,人员状况!$G:$G,"<="&X$10,人员状况!$H:$H,">="&X$10+1),0) -> 6 | Y19: =IF(MONTH($G$3)>=Y$8,COUNTIFS(人员状况!$C:$C,$E19,人员状况!$D:$D,$F19,人员状况!$G:$G,"<="&Y$10,人员状况!$H:$H,">="&Y$10+1),0) -> 6 | Z19: =IF(MONTH($G$3)>=Z$8,COUNTIFS(人员状况!$C:$C,$E19,人员状况!$D:$D,$F19,人员状况!$G:$G,"<="&Z$10,人员状况!$H:$H,">="&Z$10+1),0) -> 6 | AA19: =IF(MONTH($G$3)>=AA$8,COUNTIFS(人员状况!$C:$C,$E19,人员状况!$D:$D,$F19,人员状况!$G:$G,"<="&AA$10,人员状况!$H:$H,">="&AA$10+1),0) -> 6 | AB19: =IF(MONTH($G$3)>=AB$8,COUNTIFS(人员状况!$C:$C,$E19,人员状况!$D:$D,$F19,人员状况!$G:$G,"<="&AB$10,人员状况!$H:$H,">="&AB$10+1),0) -> 7 | AC19: =IF(MONTH($G$3)>=AC$8,COUNTIFS(人员状况!$C:$C,$E19,人员状况!$D:$D,$F19,人员状况!$G:$G,"<="&AC$10,人员状况!$H:$H,">="&AC$10+1),0) -> 7 | ... AG19: =IF(MONTH($G$3)>=AG$8,COUNTIFS(人员状况!$C:$C,$E19,人员状况!$D:$D,$F19,人员状况!$G:$G,"<="&AG$10,人员状况!$H:$H,">="&AG$10+1),0) -> 0 | AH19: =AT19 -> 7 | AI19: =IF(MONTH($G$3)>=AI$8,0,S19+SUMIFS(预计变动!$F:$F,预计变动!$A:$A,$E19,预计变动!$B:$B,$F19,预计变动!$I:$I,">="&AI$9,预计变动!$I:$I,"<="&AI$10)) -> 0 | AJ19: =IF(MONTH($G$3)>=AJ$8,0,IF(V19=0,AI19,V19)+SUMIFS(预计变动!$F:$F,预计变动!$A:$A,$E19,预计变动!$B:$B,$F19,预计变动!$I:$I,">="&AJ$9,预计变动!$I:$I,"<="&AJ$10)) -> 0 | AK19: =IF(MONTH($G$3)>=AK$8,0,IF(W19=0,AJ19,W19)+SUMIFS(预计变动!$F:$F,预计变动!$A:$A,$E19,预计变动!$B:$B,$F19,预计变动!$I:$I,">="&AK$9,预计变动!$I:$I,"<="&AK$10)) -> 0 | AL19: =IF(MONTH($G$3)>=AL$8,0,IF(X19=0,AK19,X19)+SUMIFS(预计变动!$F:$F,预计变动!$A:$A,$E19,预计变动!$B:$B,$F19,预计变动!$I:$I,">="&AL$9,预计变动!$I:$I,"<="&AL$10)) -> 0 | AM19: =IF(MONTH($G$3)>=AM$8,0,IF(Y19=0,AL19,Y19)+SUMIFS(预计变动!$F:$F,预计变动!$A:$A,$E19,预计变动!$B:$B,$F19,预计变动!$I:$I,">="&AM$9,预计变动!$I:$I,"<="&AM$10)) -> 0 | AN19: =IF(MONTH($G$3)>=AN$8,0,IF(Z19=0,AM19,Z19)+SUMIFS(预计变动!$F:$F,预计变动!$A:$A,$E19,预计变动!$B:$B,$F19,预计变动!$I:$I,">="&AN$9,预计变动!$I:$I,"<="&AN$10)) -> 0 | AO19: =IF(MONTH($G$3)>=AO$8,0,IF(AA19=0,AN19,AA19)+SUMIFS(预计变动!$F:$F,预计变动!$A:$A,$E19,预计变动!$B:$B,$F19,预计变动!$I:$I,">="&AO$9,预计变动!$I:$I,"<="&AO$10)) -> 0 | AP19: =IF(MONTH($G$3)>=AP$8,0,IF(AB19=0,AO19,AB19)+SUMIFS(预计变动!$F:$F,预计变动!$A:$A,$E19,预计变动!$B:$B,$F19,预计变动!$I:$I,">="&AP$9,预计变动!$I:$I,"<="&AP$10)) -> 0 | AQ19: =IF(MONTH($G$3)>=AQ$8,0,IF(AC19=0,AP19,AC19)+SUMIFS(预计变动!$F:$F,预计变动!$A:$A,$E19,预计变动!$B:$B,$F19,预计变动!$I:$I,">="&AQ$9,预计变动!$I:$I,"<="&AQ$10)) -> 0 | AR19: =IF(MONTH($G$3)>AR$8,0,IF(AD19=0,AQ19,AD19)+SUMIFS(预计变动!$F:$F,预计变动!$A:$A,$E19,预计变动!$B:$B,$F19,预计变动!$I:$I,">="&AR$9,预计变动!$I:$I,"<="&AR$10)) -> 7 | AS19: =IF(MONTH($G$3)>AS$8,0,IF(AE19=0,AR19,AE19)+SUMIFS(预计变动!$F:$F,预计变动!$A:$A,$E19,预计变动!$B:$B,$F19,预计变动!$I:$I,">="&AS$9,预计变动!$I:$I,"<="&AS$10)) -> 7 | AT19: =IF(MONTH($G$3)>AT$8,0,IF(AF19=0,AS19,AF19)+SUMIFS(预计变动!$F:$F,预计变动!$A:$A,$E19,预计变动!$B:$B,$F19,预计变动!$I:$I,">="&AT$9,预计变动!$I:$I,"<="&AT$10)) -> 7 | AU19: =BG19 -> 7 | AV19: =AT19+SUMIFS(预计变动!$F:$F,预计变动!$A:$A,$E19,预计变动!$B:$B,$F19,预计变动!$I:$I,">="&AV$9,预计变动!$I:$I,"<="&AV$10) -> 7 | AW19: =AV19+SUMIFS(预计变动!$F:$F,预计变动!$A:$A,$E19,预计变动!$B:$B,$F19,预计变动!$I:$I,">="&AW$9,预计变动!$I:$I,"<="&AW$10) -> 7 | AX19: =AW19+SUMIFS(预计变动!$F:$F,预计变动!$A:$A,$E19,预计变动!$B:$B,$F19,预计变动!$I:$I,">="&AX$9,预计变动!$I:$I,"<="&AX$10) -> 7 | AY19: =AX19+SUMIFS(预计变动!$F:$F,预计变动!$A:$A,$E19,预计变动!$B:$B,$F19,预计变动!$I:$I,">="&AY$9,预计变动!$I:$I,"<="&AY$10) -> 7 | AZ19: =AY19+SUMIFS(预计变动!$F:$F,预计变动!$A:$A,$E19,预计变动!$B:$B,$F19,预计变动!$I:$I,">="&AZ$9,预计变动!$I:$I,"<="&AZ$10) -> 7 | BA19: =AZ19+SUMIFS(预计变动!$F:$F,预计变动!$A:$A,$E19,预计变动!$B:$B,$F19,预计变动!$I:$I,">="&BA$9,预计变动!$I:$I,"<="&BA$10) -> 7 | BB19: =BA19+SUMIFS(预计变动!$F:$F,预计变动!$A:$A,$E19,预计变动!$B:$B,$F19,预计变动!$I:$I,">="&BB$9,预计变动!$I:$I,"<="&BB$10) -> 7 | BC19: =BB19+SUMIFS(预计变动!$F:$F,预计变动!$A:$A,$E19,预计变动!$B:$B,$F19,预计变动!$I:$I,">="&BC$9,预计变动!$I:$I,"<="&BC$10) -> 7 | BD19: =BC19+SUMIFS(预计变动!$F:$F,预计变动!$A:$A,$E19,预计变动!$B:$B,$F19,预计变动!$I:$I,">="&BD$9,预计变动!$I:$I,"<="&BD$10) -> 7 | ... BG19: =BF19+SUMIFS(预计变动!$F:$F,预计变动!$A:$A,$E19,预计变动!$B:$B,$F19,预计变动!$I:$I,">="&BG$9,预计变动!$I:$I,"<="&BG$10) -> 7
C20: 支持中心 | E20: =IF(C20<>"",C20,E19) -> 支持中心 | F20: =IF(D20<>"",D20,"*") -> * | G20: =COUNTIFS(人员状况!$C:$C,$E20,人员状况!$D:$D,$F20,人员状况!$G:$G,"<="&G$10,人员状况!$H:$H,">="&G$10+1) -> 17 | H20: =COUNTIFS(人员状况!$C:$C,$E20,人员状况!$D:$D,$F20,人员状况!$G:$G,"<="&H$10,人员状况!$H:$H,">="&H$10+1) -> 17 | I20: =COUNTIFS(人员状况!$C:$C,$E20,人员状况!$D:$D,$F20,人员状况!$G:$G,"<="&I$10,人员状况!$H:$H,">="&I$10+1) -> 17 | J20: =COUNTIFS(人员状况!$C:$C,$E20,人员状况!$D:$D,$F20,人员状况!$G:$G,"<="&J$10,人员状况!$H:$H,">="&J$10+1) -> 17 | K20: =COUNTIFS(人员状况!$C:$C,$E20,人员状况!$D:$D,$F20,人员状况!$G:$G,"<="&K$10,人员状况!$H:$H,">="&K$10+1) -> 17 | L20: =COUNTIFS(人员状况!$C:$C,$E20,人员状况!$D:$D,$F20,人员状况!$G:$G,"<="&L$10,人员状况!$H:$H,">="&L$10+1) -> 17 | M20: =COUNTIFS(人员状况!$C:$C,$E20,人员状况!$D:$D,$F20,人员状况!$G:$G,"<="&M$10,人员状况!$H:$H,">="&M$10+1) -> 17 | N20: =COUNTIFS(人员状况!$C:$C,$E20,人员状况!$D:$D,$F20,人员状况!$G:$G,"<="&N$10,人员状况!$H:$H,">="&N$10+1) -> 17 | ... S20: =COUNTIFS(人员状况!$C:$C,$E20,人员状况!$D:$D,$F20,人员状况!$G:$G,"<="&S$10,人员状况!$H:$H,">="&S$10+1) -> 17 | T20: =AT20 -> 17 | U20: =COUNTIFS(人员状况!$C:$C,$E20,人员状况!$D:$D,$F20,人员状况!$G:$G,"<="&U$10,人员状况!$H:$H,">="&U$10+1) -> 17 | V20: =IF(MONTH($G$3)>=V$8,COUNTIFS(人员状况!$C:$C,$E20,人员状况!$D:$D,$F20,人员状况!$G:$G,"<="&V$10,人员状况!$H:$H,">="&V$10+1),0) -> 17 | W20: =IF(MONTH($G$3)>=W$8,COUNTIFS(人员状况!$C:$C,$E20,人员状况!$D:$D,$F20,人员状况!$G:$G,"<="&W$10,人员状况!$H:$H,">="&W$10+1),0) -> 17 | X20: =IF(MONTH($G$3)>=X$8,COUNTIFS(人员状况!$C:$C,$E20,人员状况!$D:$D,$F20,人员状况!$G:$G,"<="&X$10,人员状况!$H:$H,">="&X$10+1),0) -> 17 | Y20: =IF(MONTH($G$3)>=Y$8,COUNTIFS(人员状况!$C:$C,$E20,人员状况!$D:$D,$F20,人员状况!$G:$G,"<="&Y$10,人员状况!$H:$H,">="&Y$10+1),0) -> 17 | Z20: =IF(MONTH($G$3)>=Z$8,COUNTIFS(人员状况!$C:$C,$E20,人员状况!$D:$D,$F20,人员状况!$G:$G,"<="&Z$10,人员状况!$H:$H,">="&Z$10+1),0) -> 17 | AA20: =IF(MONTH($G$3)>=AA$8,COUNTIFS(人员状况!$C:$C,$E20,人员状况!$D:$D,$F20,人员状况!$G:$G,"<="&AA$10,人员状况!$H:$H,">="&AA$10+1),0) -> 17 | AB20: =IF(MONTH($G$3)>=AB$8,COUNTIFS(人员状况!$C:$C,$E20,人员状况!$D:$D,$F20,人员状况!$G:$G,"<="&AB$10,人员状况!$H:$H,">="&AB$10+1),0) -> 17 | AC20: =IF(MONTH($G$3)>=AC$8,COUNTIFS(人员状况!$C:$C,$E20,人员状况!$D:$D,$F20,人员状况!$G:$G,"<="&AC$10,人员状况!$H:$H,">="&AC$10+1),0) -> 17 | ... AG20: =IF(MONTH($G$3)>=AG$8,COUNTIFS(人员状况!$C:$C,$E20,人员状况!$D:$D,$F20,人员状况!$G:$G,"<="&AG$10,人员状况!$H:$H,">="&AG$10+1),0) -> 0 | AH20: =AT20 -> 17 | AI20: =IF(MONTH($G$3)>=AI$8,0,S20+SUMIFS(预计变动!$F:$F,预计变动!$A:$A,$E20,预计变动!$B:$B,$F20,预计变动!$I:$I,">="&AI$9,预计变动!$I:$I,"<="&AI$10)) -> 0 | AJ20: =IF(MONTH($G$3)>=AJ$8,0,IF(V20=0,AI20,V20)+SUMIFS(预计变动!$F:$F,预计变动!$A:$A,$E20,预计变动!$B:$B,$F20,预计变动!$I:$I,">="&AJ$9,预计变动!$I:$I,"<="&AJ$10)) -> 0 | AK20: =IF(MONTH($G$3)>=AK$8,0,IF(W20=0,AJ20,W20)+SUMIFS(预计变动!$F:$F,预计变动!$A:$A,$E20,预计变动!$B:$B,$F20,预计变动!$I:$I,">="&AK$9,预计变动!$I:$I,"<="&AK$10)) -> 0 | AL20: =IF(MONTH($G$3)>=AL$8,0,IF(X20=0,AK20,X20)+SUMIFS(预计变动!$F:$F,预计变动!$A:$A,$E20,预计变动!$B:$B,$F20,预计变动!$I:$I,">="&AL$9,预计变动!$I:$I,"<="&AL$10)) -> 0 | AM20: =IF(MONTH($G$3)>=AM$8,0,IF(Y20=0,AL20,Y20)+SUMIFS(预计变动!$F:$F,预计变动!$A:$A,$E20,预计变动!$B:$B,$F20,预计变动!$I:$I,">="&AM$9,预计变动!$I:$I,"<="&AM$10)) -> 0 | AN20: =IF(MONTH($G$3)>=AN$8,0,IF(Z20=0,AM20,Z20)+SUMIFS(预计变动!$F:$F,预计变动!$A:$A,$E20,预计变动!$B:$B,$F20,预计变动!$I:$I,">="&AN$9,预计变动!$I:$I,"<="&AN$10)) -> 0 | AO20: =IF(MONTH($G$3)>=AO$8,0,IF(AA20=0,AN20,AA20)+SUMIFS(预计变动!$F:$F,预计变动!$A:$A,$E20,预计变动!$B:$B,$F20,预计变动!$I:$I,">="&AO$9,预计变动!$I:$I,"<="&AO$10)) -> 0 | AP20: =IF(MONTH($G$3)>=AP$8,0,IF(AB20=0,AO20,AB20)+SUMIFS(预计变动!$F:$F,预计变动!$A:$A,$E20,预计变动!$B:$B,$F20,预计变动!$I:$I,">="&AP$9,预计变动!$I:$I,"<="&AP$10)) -> 0 | AQ20: =IF(MONTH($G$3)>=AQ$8,0,IF(AC20=0,AP20,AC20)+SUMIFS(预计变动!$F:$F,预计变动!$A:$A,$E20,预计变动!$B:$B,$F20,预计变动!$I:$I,">="&AQ$9,预计变动!$I:$I,"<="&AQ$10)) -> 0 | AR20: =IF(MONTH($G$3)>AR$8,0,IF(AD20=0,AQ20,AD20)+SUMIFS(预计变动!$F:$F,预计变动!$A:$A,$E20,预计变动!$B:$B,$F20,预计变动!$I:$I,">="&AR$9,预计变动!$I:$I,"<="&AR$10)) -> 17 | AS20: =IF(MONTH($G$3)>AS$8,0,IF(AE20=0,AR20,AE20)+SUMIFS(预计变动!$F:$F,预计变动!$A:$A,$E20,预计变动!$B:$B,$F20,预计变动!$I:$I,">="&AS$9,预计变动!$I:$I,"<="&AS$10)) -> 17 | AT20: =IF(MONTH($G$3)>AT$8,0,IF(AF20=0,AS20,AF20)+SUMIFS(预计变动!$F:$F,预计变动!$A:$A,$E20,预计变动!$B:$B,$F20,预计变动!$I:$I,">="&AT$9,预计变动!$I:$I,"<="&AT$10)) -> 17 | AU20: =BG20 -> 17 | AV20: =AT20+SUMIFS(预计变动!$F:$F,预计变动!$A:$A,$E20,预计变动!$B:$B,$F20,预计变动!$I:$I,">="&AV$9,预计变动!$I:$I,"<="&AV$10) -> 17 | AW20: =AV20+SUMIFS(预计变动!$F:$F,预计变动!$A:$A,$E20,预计变动!$B:$B,$F20,预计变动!$I:$I,">="&AW$9,预计变动!$I:$I,"<="&AW$10) -> 17 | AX20: =AW20+SUMIFS(预计变动!$F:$F,预计变动!$A:$A,$E20,预计变动!$B:$B,$F20,预计变动!$I:$I,">="&AX$9,预计变动!$I:$I,"<="&AX$10) -> 17 | AY20: =AX20+SUMIFS(预计变动!$F:$F,预计变动!$A:$A,$E20,预计变动!$B:$B,$F20,预计变动!$I:$I,">="&AY$9,预计变动!$I:$I,"<="&AY$10) -> 17 | AZ20: =AY20+SUMIFS(预计变动!$F:$F,预计变动!$A:$A,$E20,预计变动!$B:$B,$F20,预计变动!$I:$I,">="&AZ$9,预计变动!$I:$I,"<="&AZ$10) -> 17 | BA20: =AZ20+SUMIFS(预计变动!$F:$F,预计变动!$A:$A,$E20,预计变动!$B:$B,$F20,预计变动!$I:$I,">="&BA$9,预计变动!$I:$I,"<="&BA$10) -> 17 | BB20: =BA20+SUMIFS(预计变动!$F:$F,预计变动!$A:$A,$E20,预计变动!$B:$B,$F20,预计变动!$I:$I,">="&BB$9,预计变动!$I:$I,"<="&BB$10) -> 17 | BC20: =BB20+SUMIFS(预计变动!$F:$F,预计变动!$A:$A,$E20,预计变动!$B:$B,$F20,预计变动!$I:$I,">="&BC$9,预计变动!$I:$I,"<="&BC$10) -> 17 | BD20: =BC20+SUMIFS(预计变动!$F:$F,预计变动!$A:$A,$E20,预计变动!$B:$B,$F20,预计变动!$I:$I,">="&BD$9,预计变动!$I:$I,"<="&BD$10) -> 17 | ... BG20: =BF20+SUMIFS(预计变动!$F:$F,预计变动!$A:$A,$E20,预计变动!$B:$B,$F20,预计变动!$I:$I,">="&BG$9,预计变动!$I:$I,"<="&BG$10) -> 17
D21: 财务部 | E21: =IF(C21<>"",C21,E20) -> 支持中心 | F21: =IF(D21<>"",D21,"*") -> 财务部 | G21: =COUNTIFS(人员状况!$C:$C,$E21,人员状况!$D:$D,$F21,人员状况!$G:$G,"<="&G$10,人员状况!$H:$H,">="&G$10+1) -> 7 | H21: =COUNTIFS(人员状况!$C:$C,$E21,人员状况!$D:$D,$F21,人员状况!$G:$G,"<="&H$10,人员状况!$H:$H,">="&H$10+1) -> 7 | I21: =COUNTIFS(人员状况!$C:$C,$E21,人员状况!$D:$D,$F21,人员状况!$G:$G,"<="&I$10,人员状况!$H:$H,">="&I$10+1) -> 7 | J21: =COUNTIFS(人员状况!$C:$C,$E21,人员状况!$D:$D,$F21,人员状况!$G:$G,"<="&J$10,人员状况!$H:$H,">="&J$10+1) -> 7 | K21: =COUNTIFS(人员状况!$C:$C,$E21,人员状况!$D:$D,$F21,人员状况!$G:$G,"<="&K$10,人员状况!$H:$H,">="&K$10+1) -> 7 | L21: =COUNTIFS(人员状况!$C:$C,$E21,人员状况!$D:$D,$F21,人员状况!$G:$G,"<="&L$10,人员状况!$H:$H,">="&L$10+1) -> 7 | M21: =COUNTIFS(人员状况!$C:$C,$E21,人员状况!$D:$D,$F21,人员状况!$G:$G,"<="&M$10,人员状况!$H:$H,">="&M$10+1) -> 7 | N21: =COUNTIFS(人员状况!$C:$C,$E21,人员状况!$D:$D,$F21,人员状况!$G:$G,"<="&N$10,人员状况!$H:$H,">="&N$10+1) -> 7 | ... S21: =COUNTIFS(人员状况!$C:$C,$E21,人员状况!$D:$D,$F21,人员状况!$G:$G,"<="&S$10,人员状况!$H:$H,">="&S$10+1) -> 7 | T21: =AT21 -> 7 | U21: =COUNTIFS(人员状况!$C:$C,$E21,人员状况!$D:$D,$F21,人员状况!$G:$G,"<="&U$10,人员状况!$H:$H,">="&U$10+1) -> 7 | V21: =IF(MONTH($G$3)>=V$8,COUNTIFS(人员状况!$C:$C,$E21,人员状况!$D:$D,$F21,人员状况!$G:$G,"<="&V$10,人员状况!$H:$H,">="&V$10+1),0) -> 7 | W21: =IF(MONTH($G$3)>=W$8,COUNTIFS(人员状况!$C:$C,$E21,人员状况!$D:$D,$F21,人员状况!$G:$G,"<="&W$10,人员状况!$H:$H,">="&W$10+1),0) -> 7 | X21: =IF(MONTH($G$3)>=X$8,COUNTIFS(人员状况!$C:$C,$E21,人员状况!$D:$D,$F21,人员状况!$G:$G,"<="&X$10,人员状况!$H:$H,">="&X$10+1),0) -> 7 | Y21: =IF(MONTH($G$3)>=Y$8,COUNTIFS(人员状况!$C:$C,$E21,人员状况!$D:$D,$F21,人员状况!$G:$G,"<="&Y$10,人员状况!$H:$H,">="&Y$10+1),0) -> 7 | Z21: =IF(MONTH($G$3)>=Z$8,COUNTIFS(人员状况!$C:$C,$E21,人员状况!$D:$D,$F21,人员状况!$G:$G,"<="&Z$10,人员状况!$H:$H,">="&Z$10+1),0) -> 7 | AA21: =IF(MONTH($G$3)>=AA$8,COUNTIFS(人员状况!$C:$C,$E21,人员状况!$D:$D,$F21,人员状况!$G:$G,"<="&AA$10,人员状况!$H:$H,">="&AA$10+1),0) -> 7 | AB21: =IF(MONTH($G$3)>=AB$8,COUNTIFS(人员状况!$C:$C,$E21,人员状况!$D:$D,$F21,人员状况!$G:$G,"<="&AB$10,人员状况!$H:$H,">="&AB$10+1),0) -> 7 | AC21: =IF(MONTH($G$3)>=AC$8,COUNTIFS(人员状况!$C:$C,$E21,人员状况!$D:$D,$F21,人员状况!$G:$G,"<="&AC$10,人员状况!$H:$H,">="&AC$10+1),0) -> 7 | ... AG21: =IF(MONTH($G$3)>=AG$8,COUNTIFS(人员状况!$C:$C,$E21,人员状况!$D:$D,$F21,人员状况!$G:$G,"<="&AG$10,人员状况!$H:$H,">="&AG$10+1),0) -> 0 | AH21: =AT21 -> 7 | AI21: =IF(MONTH($G$3)>=AI$8,0,S21+SUMIFS(预计变动!$F:$F,预计变动!$A:$A,$E21,预计变动!$B:$B,$F21,预计变动!$I:$I,">="&AI$9,预计变动!$I:$I,"<="&AI$10)) -> 0 | AJ21: =IF(MONTH($G$3)>=AJ$8,0,IF(V21=0,AI21,V21)+SUMIFS(预计变动!$F:$F,预计变动!$A:$A,$E21,预计变动!$B:$B,$F21,预计变动!$I:$I,">="&AJ$9,预计变动!$I:$I,"<="&AJ$10)) -> 0 | AK21: =IF(MONTH($G$3)>=AK$8,0,IF(W21=0,AJ21,W21)+SUMIFS(预计变动!$F:$F,预计变动!$A:$A,$E21,预计变动!$B:$B,$F21,预计变动!$I:$I,">="&AK$9,预计变动!$I:$I,"<="&AK$10)) -> 0 | AL21: =IF(MONTH($G$3)>=AL$8,0,IF(X21=0,AK21,X21)+SUMIFS(预计变动!$F:$F,预计变动!$A:$A,$E21,预计变动!$B:$B,$F21,预计变动!$I:$I,">="&AL$9,预计变动!$I:$I,"<="&AL$10)) -> 0 | AM21: =IF(MONTH($G$3)>=AM$8,0,IF(Y21=0,AL21,Y21)+SUMIFS(预计变动!$F:$F,预计变动!$A:$A,$E21,预计变动!$B:$B,$F21,预计变动!$I:$I,">="&AM$9,预计变动!$I:$I,"<="&AM$10)) -> 0 | AN21: =IF(MONTH($G$3)>=AN$8,0,IF(Z21=0,AM21,Z21)+SUMIFS(预计变动!$F:$F,预计变动!$A:$A,$E21,预计变动!$B:$B,$F21,预计变动!$I:$I,">="&AN$9,预计变动!$I:$I,"<="&AN$10)) -> 0 | AO21: =IF(MONTH($G$3)>=AO$8,0,IF(AA21=0,AN21,AA21)+SUMIFS(预计变动!$F:$F,预计变动!$A:$A,$E21,预计变动!$B:$B,$F21,预计变动!$I:$I,">="&AO$9,预计变动!$I:$I,"<="&AO$10)) -> 0 | AP21: =IF(MONTH($G$3)>=AP$8,0,IF(AB21=0,AO21,AB21)+SUMIFS(预计变动!$F:$F,预计变动!$A:$A,$E21,预计变动!$B:$B,$F21,预计变动!$I:$I,">="&AP$9,预计变动!$I:$I,"<="&AP$10)) -> 0 | AQ21: =IF(MONTH($G$3)>=AQ$8,0,IF(AC21=0,AP21,AC21)+SUMIFS(预计变动!$F:$F,预计变动!$A:$A,$E21,预计变动!$B:$B,$F21,预计变动!$I:$I,">="&AQ$9,预计变动!$I:$I,"<="&AQ$10)) -> 0 | AR21: =IF(MONTH($G$3)>AR$8,0,IF(AD21=0,AQ21,AD21)+SUMIFS(预计变动!$F:$F,预计变动!$A:$A,$E21,预计变动!$B:$B,$F21,预计变动!$I:$I,">="&AR$9,预计变动!$I:$I,"<="&AR$10)) -> 7 | AS21: =IF(MONTH($G$3)>AS$8,0,IF(AE21=0,AR21,AE21)+SUMIFS(预计变动!$F:$F,预计变动!$A:$A,$E21,预计变动!$B:$B,$F21,预计变动!$I:$I,">="&AS$9,预计变动!$I:$I,"<="&AS$10)) -> 7 | AT21: =IF(MONTH($G$3)>AT$8,0,IF(AF21=0,AS21,AF21)+SUMIFS(预计变动!$F:$F,预计变动!$A:$A,$E21,预计变动!$B:$B,$F21,预计变动!$I:$I,">="&AT$9,预计变动!$I:$I,"<="&AT$10)) -> 7 | AU21: =BG21 -> 7 | AV21: =AT21+SUMIFS(预计变动!$F:$F,预计变动!$A:$A,$E21,预计变动!$B:$B,$F21,预计变动!$I:$I,">="&AV$9,预计变动!$I:$I,"<="&AV$10) -> 7 | AW21: =AV21+SUMIFS(预计变动!$F:$F,预计变动!$A:$A,$E21,预计变动!$B:$B,$F21,预计变动!$I:$I,">="&AW$9,预计变动!$I:$I,"<="&AW$10) -> 7 | AX21: =AW21+SUMIFS(预计变动!$F:$F,预计变动!$A:$A,$E21,预计变动!$B:$B,$F21,预计变动!$I:$I,">="&AX$9,预计变动!$I:$I,"<="&AX$10) -> 7 | AY21: =AX21+SUMIFS(预计变动!$F:$F,预计变动!$A:$A,$E21,预计变动!$B:$B,$F21,预计变动!$I:$I,">="&AY$9,预计变动!$I:$I,"<="&AY$10) -> 7 | AZ21: =AY21+SUMIFS(预计变动!$F:$F,预计变动!$A:$A,$E21,预计变动!$B:$B,$F21,预计变动!$I:$I,">="&AZ$9,预计变动!$I:$I,"<="&AZ$10) -> 7 | BA21: =AZ21+SUMIFS(预计变动!$F:$F,预计变动!$A:$A,$E21,预计变动!$B:$B,$F21,预计变动!$I:$I,">="&BA$9,预计变动!$I:$I,"<="&BA$10) -> 7 | BB21: =BA21+SUMIFS(预计变动!$F:$F,预计变动!$A:$A,$E21,预计变动!$B:$B,$F21,预计变动!$I:$I,">="&BB$9,预计变动!$I:$I,"<="&BB$10) -> 7 | BC21: =BB21+SUMIFS(预计变动!$F:$F,预计变动!$A:$A,$E21,预计变动!$B:$B,$F21,预计变动!$I:$I,">="&BC$9,预计变动!$I:$I,"<="&BC$10) -> 7 | BD21: =BC21+SUMIFS(预计变动!$F:$F,预计变动!$A:$A,$E21,预计变动!$B:$B,$F21,预计变动!$I:$I,">="&BD$9,预计变动!$I:$I,"<="&BD$10) -> 7 | ... BG21: =BF21+SUMIFS(预计变动!$F:$F,预计变动!$A:$A,$E21,预计变动!$B:$B,$F21,预计变动!$I:$I,">="&BG$9,预计变动!$I:$I,"<="&BG$10) -> 7
D22: 人力资源部 | E22: =IF(C22<>"",C22,E21) -> 支持中心 | F22: =IF(D22<>"",D22,"*") -> 人力资源部 | G22: =COUNTIFS(人员状况!$C:$C,$E22,人员状况!$D:$D,$F22,人员状况!$G:$G,"<="&G$10,人员状况!$H:$H,">="&G$10+1) -> 6 | H22: =COUNTIFS(人员状况!$C:$C,$E22,人员状况!$D:$D,$F22,人员状况!$G:$G,"<="&H$10,人员状况!$H:$H,">="&H$10+1) -> 6 | I22: =COUNTIFS(人员状况!$C:$C,$E22,人员状况!$D:$D,$F22,人员状况!$G:$G,"<="&I$10,人员状况!$H:$H,">="&I$10+1) -> 6 | J22: =COUNTIFS(人员状况!$C:$C,$E22,人员状况!$D:$D,$F22,人员状况!$G:$G,"<="&J$10,人员状况!$H:$H,">="&J$10+1) -> 6 | K22: =COUNTIFS(人员状况!$C:$C,$E22,人员状况!$D:$D,$F22,人员状况!$G:$G,"<="&K$10,人员状况!$H:$H,">="&K$10+1) -> 6 | L22: =COUNTIFS(人员状况!$C:$C,$E22,人员状况!$D:$D,$F22,人员状况!$G:$G,"<="&L$10,人员状况!$H:$H,">="&L$10+1) -> 6 | M22: =COUNTIFS(人员状况!$C:$C,$E22,人员状况!$D:$D,$F22,人员状况!$G:$G,"<="&M$10,人员状况!$H:$H,">="&M$10+1) -> 6 | N22: =COUNTIFS(人员状况!$C:$C,$E22,人员状况!$D:$D,$F22,人员状况!$G:$G,"<="&N$10,人员状况!$H:$H,">="&N$10+1) -> 6 | ... S22: =COUNTIFS(人员状况!$C:$C,$E22,人员状况!$D:$D,$F22,人员状况!$G:$G,"<="&S$10,人员状况!$H:$H,">="&S$10+1) -> 6 | T22: =AT22 -> 6 | U22: =COUNTIFS(人员状况!$C:$C,$E22,人员状况!$D:$D,$F22,人员状况!$G:$G,"<="&U$10,人员状况!$H:$H,">="&U$10+1) -> 6 | V22: =IF(MONTH($G$3)>=V$8,COUNTIFS(人员状况!$C:$C,$E22,人员状况!$D:$D,$F22,人员状况!$G:$G,"<="&V$10,人员状况!$H:$H,">="&V$10+1),0) -> 6 | W22: =IF(MONTH($G$3)>=W$8,COUNTIFS(人员状况!$C:$C,$E22,人员状况!$D:$D,$F22,人员状况!$G:$G,"<="&W$10,人员状况!$H:$H,">="&W$10+1),0) -> 6 | X22: =IF(MONTH($G$3)>=X$8,COUNTIFS(人员状况!$C:$C,$E22,人员状况!$D:$D,$F22,人员状况!$G:$G,"<="&X$10,人员状况!$H:$H,">="&X$10+1),0) -> 6 | Y22: =IF(MONTH($G$3)>=Y$8,COUNTIFS(人员状况!$C:$C,$E22,人员状况!$D:$D,$F22,人员状况!$G:$G,"<="&Y$10,人员状况!$H:$H,">="&Y$10+1),0) -> 6 | Z22: =IF(MONTH($G$3)>=Z$8,COUNTIFS(人员状况!$C:$C,$E22,人员状况!$D:$D,$F22,人员状况!$G:$G,"<="&Z$10,人员状况!$H:$H,">="&Z$10+1),0) -> 6 | AA22: =IF(MONTH($G$3)>=AA$8,COUNTIFS(人员状况!$C:$C,$E22,人员状况!$D:$D,$F22,人员状况!$G:$G,"<="&AA$10,人员状况!$H:$H,">="&AA$10+1),0) -> 6 | AB22: =IF(MONTH($G$3)>=AB$8,COUNTIFS(人员状况!$C:$C,$E22,人员状况!$D:$D,$F22,人员状况!$G:$G,"<="&AB$10,人员状况!$H:$H,">="&AB$10+1),0) -> 6 | AC22: =IF(MONTH($G$3)>=AC$8,COUNTIFS(人员状况!$C:$C,$E22,人员状况!$D:$D,$F22,人员状况!$G:$G,"<="&AC$10,人员状况!$H:$H,">="&AC$10+1),0) -> 6 | ... AG22: =IF(MONTH($G$3)>=AG$8,COUNTIFS(人员状况!$C:$C,$E22,人员状况!$D:$D,$F22,人员状况!$G:$G,"<="&AG$10,人员状况!$H:$H,">="&AG$10+1),0) -> 0 | AH22: =AT22 -> 6 | AI22: =IF(MONTH($G$3)>=AI$8,0,S22+SUMIFS(预计变动!$F:$F,预计变动!$A:$A,$E22,预计变动!$B:$B,$F22,预计变动!$I:$I,">="&AI$9,预计变动!$I:$I,"<="&AI$10)) -> 0 | AJ22: =IF(MONTH($G$3)>=AJ$8,0,IF(V22=0,AI22,V22)+SUMIFS(预计变动!$F:$F,预计变动!$A:$A,$E22,预计变动!$B:$B,$F22,预计变动!$I:$I,">="&AJ$9,预计变动!$I:$I,"<="&AJ$10)) -> 0 | AK22: =IF(MONTH($G$3)>=AK$8,0,IF(W22=0,AJ22,W22)+SUMIFS(预计变动!$F:$F,预计变动!$A:$A,$E22,预计变动!$B:$B,$F22,预计变动!$I:$I,">="&AK$9,预计变动!$I:$I,"<="&AK$10)) -> 0 | AL22: =IF(MONTH($G$3)>=AL$8,0,IF(X22=0,AK22,X22)+SUMIFS(预计变动!$F:$F,预计变动!$A:$A,$E22,预计变动!$B:$B,$F22,预计变动!$I:$I,">="&AL$9,预计变动!$I:$I,"<="&AL$10)) -> 0 | AM22: =IF(MONTH($G$3)>=AM$8,0,IF(Y22=0,AL22,Y22)+SUMIFS(预计变动!$F:$F,预计变动!$A:$A,$E22,预计变动!$B:$B,$F22,预计变动!$I:$I,">="&AM$9,预计变动!$I:$I,"<="&AM$10)) -> 0 | AN22: =IF(MONTH($G$3)>=AN$8,0,IF(Z22=0,AM22,Z22)+SUMIFS(预计变动!$F:$F,预计变动!$A:$A,$E22,预计变动!$B:$B,$F22,预计变动!$I:$I,">="&AN$9,预计变动!$I:$I,"<="&AN$10)) -> 0 | AO22: =IF(MONTH($G$3)>=AO$8,0,IF(AA22=0,AN22,AA22)+SUMIFS(预计变动!$F:$F,预计变动!$A:$A,$E22,预计变动!$B:$B,$F22,预计变动!$I:$I,">="&AO$9,预计变动!$I:$I,"<="&AO$10)) -> 0 | AP22: =IF(MONTH($G$3)>=AP$8,0,IF(AB22=0,AO22,AB22)+SUMIFS(预计变动!$F:$F,预计变动!$A:$A,$E22,预计变动!$B:$B,$F22,预计变动!$I:$I,">="&AP$9,预计变动!$I:$I,"<="&AP$10)) -> 0 | AQ22: =IF(MONTH($G$3)>=AQ$8,0,IF(AC22=0,AP22,AC22)+SUMIFS(预计变动!$F:$F,预计变动!$A:$A,$E22,预计变动!$B:$B,$F22,预计变动!$I:$I,">="&AQ$9,预计变动!$I:$I,"<="&AQ$10)) -> 0 | AR22: =IF(MONTH($G$3)>AR$8,0,IF(AD22=0,AQ22,AD22)+SUMIFS(预计变动!$F:$F,预计变动!$A:$A,$E22,预计变动!$B:$B,$F22,预计变动!$I:$I,">="&AR$9,预计变动!$I:$I,"<="&AR$10)) -> 6 | AS22: =IF(MONTH($G$3)>AS$8,0,IF(AE22=0,AR22,AE22)+SUMIFS(预计变动!$F:$F,预计变动!$A:$A,$E22,预计变动!$B:$B,$F22,预计变动!$I:$I,">="&AS$9,预计变动!$I:$I,"<="&AS$10)) -> 6 | AT22: =IF(MONTH($G$3)>AT$8,0,IF(AF22=0,AS22,AF22)+SUMIFS(预计变动!$F:$F,预计变动!$A:$A,$E22,预计变动!$B:$B,$F22,预计变动!$I:$I,">="&AT$9,预计变动!$I:$I,"<="&AT$10)) -> 6 | AU22: =BG22 -> 6 | AV22: =AT22+SUMIFS(预计变动!$F:$F,预计变动!$A:$A,$E22,预计变动!$B:$B,$F22,预计变动!$I:$I,">="&AV$9,预计变动!$I:$I,"<="&AV$10) -> 6 | AW22: =AV22+SUMIFS(预计变动!$F:$F,预计变动!$A:$A,$E22,预计变动!$B:$B,$F22,预计变动!$I:$I,">="&AW$9,预计变动!$I:$I,"<="&AW$10) -> 6 | AX22: =AW22+SUMIFS(预计变动!$F:$F,预计变动!$A:$A,$E22,预计变动!$B:$B,$F22,预计变动!$I:$I,">="&AX$9,预计变动!$I:$I,"<="&AX$10) -> 6 | AY22: =AX22+SUMIFS(预计变动!$F:$F,预计变动!$A:$A,$E22,预计变动!$B:$B,$F22,预计变动!$I:$I,">="&AY$9,预计变动!$I:$I,"<="&AY$10) -> 6 | AZ22: =AY22+SUMIFS(预计变动!$F:$F,预计变动!$A:$A,$E22,预计变动!$B:$B,$F22,预计变动!$I:$I,">="&AZ$9,预计变动!$I:$I,"<="&AZ$10) -> 6 | BA22: =AZ22+SUMIFS(预计变动!$F:$F,预计变动!$A:$A,$E22,预计变动!$B:$B,$F22,预计变动!$I:$I,">="&BA$9,预计变动!$I:$I,"<="&BA$10) -> 6 | BB22: =BA22+SUMIFS(预计变动!$F:$F,预计变动!$A:$A,$E22,预计变动!$B:$B,$F22,预计变动!$I:$I,">="&BB$9,预计变动!$I:$I,"<="&BB$10) -> 6 | BC22: =BB22+SUMIFS(预计变动!$F:$F,预计变动!$A:$A,$E22,预计变动!$B:$B,$F22,预计变动!$I:$I,">="&BC$9,预计变动!$I:$I,"<="&BC$10) -> 6 | BD22: =BC22+SUMIFS(预计变动!$F:$F,预计变动!$A:$A,$E22,预计变动!$B:$B,$F22,预计变动!$I:$I,">="&BD$9,预计变动!$I:$I,"<="&BD$10) -> 6 | ... BG22: =BF22+SUMIFS(预计变动!$F:$F,预计变动!$A:$A,$E22,预计变动!$B:$B,$F22,预计变动!$I:$I,">="&BG$9,预计变动!$I:$I,"<="&BG$10) -> 6
D23: IT部 | E23: =IF(C23<>"",C23,E22) -> 支持中心 | F23: =IF(D23<>"",D23,"*") -> IT部 | G23: =COUNTIFS(人员状况!$C:$C,$E23,人员状况!$D:$D,$F23,人员状况!$G:$G,"<="&G$10,人员状况!$H:$H,">="&G$10+1) -> 3 | H23: =COUNTIFS(人员状况!$C:$C,$E23,人员状况!$D:$D,$F23,人员状况!$G:$G,"<="&H$10,人员状况!$H:$H,">="&H$10+1) -> 3 | I23: =COUNTIFS(人员状况!$C:$C,$E23,人员状况!$D:$D,$F23,人员状况!$G:$G,"<="&I$10,人员状况!$H:$H,">="&I$10+1) -> 3 | J23: =COUNTIFS(人员状况!$C:$C,$E23,人员状况!$D:$D,$F23,人员状况!$G:$G,"<="&J$10,人员状况!$H:$H,">="&J$10+1) -> 3 | K23: =COUNTIFS(人员状况!$C:$C,$E23,人员状况!$D:$D,$F23,人员状况!$G:$G,"<="&K$10,人员状况!$H:$H,">="&K$10+1) -> 3 | L23: =COUNTIFS(人员状况!$C:$C,$E23,人员状况!$D:$D,$F23,人员状况!$G:$G,"<="&L$10,人员状况!$H:$H,">="&L$10+1) -> 3 | M23: =COUNTIFS(人员状况!$C:$C,$E23,人员状况!$D:$D,$F23,人员状况!$G:$G,"<="&M$10,人员状况!$H:$H,">="&M$10+1) -> 3 | N23: =COUNTIFS(人员状况!$C:$C,$E23,人员状况!$D:$D,$F23,人员状况!$G:$G,"<="&N$10,人员状况!$H:$H,">="&N$10+1) -> 3 | ... S23: =COUNTIFS(人员状况!$C:$C,$E23,人员状况!$D:$D,$F23,人员状况!$G:$G,"<="&S$10,人员状况!$H:$H,">="&S$10+1) -> 3 | T23: =AT23 -> 3 | U23: =COUNTIFS(人员状况!$C:$C,$E23,人员状况!$D:$D,$F23,人员状况!$G:$G,"<="&U$10,人员状况!$H:$H,">="&U$10+1) -> 3 | V23: =IF(MONTH($G$3)>=V$8,COUNTIFS(人员状况!$C:$C,$E23,人员状况!$D:$D,$F23,人员状况!$G:$G,"<="&V$10,人员状况!$H:$H,">="&V$10+1),0) -> 3 | W23: =IF(MONTH($G$3)>=W$8,COUNTIFS(人员状况!$C:$C,$E23,人员状况!$D:$D,$F23,人员状况!$G:$G,"<="&W$10,人员状况!$H:$H,">="&W$10+1),0) -> 3 | X23: =IF(MONTH($G$3)>=X$8,COUNTIFS(人员状况!$C:$C,$E23,人员状况!$D:$D,$F23,人员状况!$G:$G,"<="&X$10,人员状况!$H:$H,">="&X$10+1),0) -> 3 | Y23: =IF(MONTH($G$3)>=Y$8,COUNTIFS(人员状况!$C:$C,$E23,人员状况!$D:$D,$F23,人员状况!$G:$G,"<="&Y$10,人员状况!$H:$H,">="&Y$10+1),0) -> 3 | Z23: =IF(MONTH($G$3)>=Z$8,COUNTIFS(人员状况!$C:$C,$E23,人员状况!$D:$D,$F23,人员状况!$G:$G,"<="&Z$10,人员状况!$H:$H,">="&Z$10+1),0) -> 3 | AA23: =IF(MONTH($G$3)>=AA$8,COUNTIFS(人员状况!$C:$C,$E23,人员状况!$D:$D,$F23,人员状况!$G:$G,"<="&AA$10,人员状况!$H:$H,">="&AA$10+1),0) -> 3 | AB23: =IF(MONTH($G$3)>=AB$8,COUNTIFS(人员状况!$C:$C,$E23,人员状况!$D:$D,$F23,人员状况!$G:$G,"<="&AB$10,人员状况!$H:$H,">="&AB$10+1),0) -> 3 | AC23: =IF(MONTH($G$3)>=AC$8,COUNTIFS(人员状况!$C:$C,$E23,人员状况!$D:$D,$F23,人员状况!$G:$G,"<="&AC$10,人员状况!$H:$H,">="&AC$10+1),0) -> 3 | ... AG23: =IF(MONTH($G$3)>=AG$8,COUNTIFS(人员状况!$C:$C,$E23,人员状况!$D:$D,$F23,人员状况!$G:$G,"<="&AG$10,人员状况!$H:$H,">="&AG$10+1),0) -> 0 | AH23: =AT23 -> 3 | AI23: =IF(MONTH($G$3)>=AI$8,0,S23+SUMIFS(预计变动!$F:$F,预计变动!$A:$A,$E23,预计变动!$B:$B,$F23,预计变动!$I:$I,">="&AI$9,预计变动!$I:$I,"<="&AI$10)) -> 0 | AJ23: =IF(MONTH($G$3)>=AJ$8,0,IF(V23=0,AI23,V23)+SUMIFS(预计变动!$F:$F,预计变动!$A:$A,$E23,预计变动!$B:$B,$F23,预计变动!$I:$I,">="&AJ$9,预计变动!$I:$I,"<="&AJ$10)) -> 0 | AK23: =IF(MONTH($G$3)>=AK$8,0,IF(W23=0,AJ23,W23)+SUMIFS(预计变动!$F:$F,预计变动!$A:$A,$E23,预计变动!$B:$B,$F23,预计变动!$I:$I,">="&AK$9,预计变动!$I:$I,"<="&AK$10)) -> 0 | AL23: =IF(MONTH($G$3)>=AL$8,0,IF(X23=0,AK23,X23)+SUMIFS(预计变动!$F:$F,预计变动!$A:$A,$E23,预计变动!$B:$B,$F23,预计变动!$I:$I,">="&AL$9,预计变动!$I:$I,"<="&AL$10)) -> 0 | AM23: =IF(MONTH($G$3)>=AM$8,0,IF(Y23=0,AL23,Y23)+SUMIFS(预计变动!$F:$F,预计变动!$A:$A,$E23,预计变动!$B:$B,$F23,预计变动!$I:$I,">="&AM$9,预计变动!$I:$I,"<="&AM$10)) -> 0 | AN23: =IF(MONTH($G$3)>=AN$8,0,IF(Z23=0,AM23,Z23)+SUMIFS(预计变动!$F:$F,预计变动!$A:$A,$E23,预计变动!$B:$B,$F23,预计变动!$I:$I,">="&AN$9,预计变动!$I:$I,"<="&AN$10)) -> 0 | AO23: =IF(MONTH($G$3)>=AO$8,0,IF(AA23=0,AN23,AA23)+SUMIFS(预计变动!$F:$F,预计变动!$A:$A,$E23,预计变动!$B:$B,$F23,预计变动!$I:$I,">="&AO$9,预计变动!$I:$I,"<="&AO$10)) -> 0 | AP23: =IF(MONTH($G$3)>=AP$8,0,IF(AB23=0,AO23,AB23)+SUMIFS(预计变动!$F:$F,预计变动!$A:$A,$E23,预计变动!$B:$B,$F23,预计变动!$I:$I,">="&AP$9,预计变动!$I:$I,"<="&AP$10)) -> 0 | AQ23: =IF(MONTH($G$3)>=AQ$8,0,IF(AC23=0,AP23,AC23)+SUMIFS(预计变动!$F:$F,预计变动!$A:$A,$E23,预计变动!$B:$B,$F23,预计变动!$I:$I,">="&AQ$9,预计变动!$I:$I,"<="&AQ$10)) -> 0 | AR23: =IF(MONTH($G$3)>AR$8,0,IF(AD23=0,AQ23,AD23)+SUMIFS(预计变动!$F:$F,预计变动!$A:$A,$E23,预计变动!$B:$B,$F23,预计变动!$I:$I,">="&AR$9,预计变动!$I:$I,"<="&AR$10)) -> 3 | AS23: =IF(MONTH($G$3)>AS$8,0,IF(AE23=0,AR23,AE23)+SUMIFS(预计变动!$F:$F,预计变动!$A:$A,$E23,预计变动!$B:$B,$F23,预计变动!$I:$I,">="&AS$9,预计变动!$I:$I,"<="&AS$10)) -> 3 | AT23: =IF(MONTH($G$3)>AT$8,0,IF(AF23=0,AS23,AF23)+SUMIFS(预计变动!$F:$F,预计变动!$A:$A,$E23,预计变动!$B:$B,$F23,预计变动!$I:$I,">="&AT$9,预计变动!$I:$I,"<="&AT$10)) -> 3 | AU23: =BG23 -> 3 | AV23: =AT23+SUMIFS(预计变动!$F:$F,预计变动!$A:$A,$E23,预计变动!$B:$B,$F23,预计变动!$I:$I,">="&AV$9,预计变动!$I:$I,"<="&AV$10) -> 3 | AW23: =AV23+SUMIFS(预计变动!$F:$F,预计变动!$A:$A,$E23,预计变动!$B:$B,$F23,预计变动!$I:$I,">="&AW$9,预计变动!$I:$I,"<="&AW$10) -> 3 | AX23: =AW23+SUMIFS(预计变动!$F:$F,预计变动!$A:$A,$E23,预计变动!$B:$B,$F23,预计变动!$I:$I,">="&AX$9,预计变动!$I:$I,"<="&AX$10) -> 3 | AY23: =AX23+SUMIFS(预计变动!$F:$F,预计变动!$A:$A,$E23,预计变动!$B:$B,$F23,预计变动!$I:$I,">="&AY$9,预计变动!$I:$I,"<="&AY$10) -> 3 | AZ23: =AY23+SUMIFS(预计变动!$F:$F,预计变动!$A:$A,$E23,预计变动!$B:$B,$F23,预计变动!$I:$I,">="&AZ$9,预计变动!$I:$I,"<="&AZ$10) -> 3 | BA23: =AZ23+SUMIFS(预计变动!$F:$F,预计变动!$A:$A,$E23,预计变动!$B:$B,$F23,预计变动!$I:$I,">="&BA$9,预计变动!$I:$I,"<="&BA$10) -> 3 | BB23: =BA23+SUMIFS(预计变动!$F:$F,预计变动!$A:$A,$E23,预计变动!$B:$B,$F23,预计变动!$I:$I,">="&BB$9,预计变动!$I:$I,"<="&BB$10) -> 3 | BC23: =BB23+SUMIFS(预计变动!$F:$F,预计变动!$A:$A,$E23,预计变动!$B:$B,$F23,预计变动!$I:$I,">="&BC$9,预计变动!$I:$I,"<="&BC$10) -> 3 | BD23: =BC23+SUMIFS(预计变动!$F:$F,预计变动!$A:$A,$E23,预计变动!$B:$B,$F23,预计变动!$I:$I,">="&BD$9,预计变动!$I:$I,"<="&BD$10) -> 3 | ... BG23: =BF23+SUMIFS(预计变动!$F:$F,预计变动!$A:$A,$E23,预计变动!$B:$B,$F23,预计变动!$I:$I,">="&BG$9,预计变动!$I:$I,"<="&BG$10) -> 3
D24: 总经办 | E24: =IF(C24<>"",C24,E23) -> 支持中心 | F24: =IF(D24<>"",D24,"*") -> 总经办 | G24: =COUNTIFS(人员状况!$C:$C,$E24,人员状况!$D:$D,$F24,人员状况!$G:$G,"<="&G$10,人员状况!$H:$H,">="&G$10+1) -> 1 | H24: =COUNTIFS(人员状况!$C:$C,$E24,人员状况!$D:$D,$F24,人员状况!$G:$G,"<="&H$10,人员状况!$H:$H,">="&H$10+1) -> 1 | I24: =COUNTIFS(人员状况!$C:$C,$E24,人员状况!$D:$D,$F24,人员状况!$G:$G,"<="&I$10,人员状况!$H:$H,">="&I$10+1) -> 1 | J24: =COUNTIFS(人员状况!$C:$C,$E24,人员状况!$D:$D,$F24,人员状况!$G:$G,"<="&J$10,人员状况!$H:$H,">="&J$10+1) -> 1 | K24: =COUNTIFS(人员状况!$C:$C,$E24,人员状况!$D:$D,$F24,人员状况!$G:$G,"<="&K$10,人员状况!$H:$H,">="&K$10+1) -> 1 | L24: =COUNTIFS(人员状况!$C:$C,$E24,人员状况!$D:$D,$F24,人员状况!$G:$G,"<="&L$10,人员状况!$H:$H,">="&L$10+1) -> 1 | M24: =COUNTIFS(人员状况!$C:$C,$E24,人员状况!$D:$D,$F24,人员状况!$G:$G,"<="&M$10,人员状况!$H:$H,">="&M$10+1) -> 1 | N24: =COUNTIFS(人员状况!$C:$C,$E24,人员状况!$D:$D,$F24,人员状况!$G:$G,"<="&N$10,人员状况!$H:$H,">="&N$10+1) -> 1 | ... S24: =COUNTIFS(人员状况!$C:$C,$E24,人员状况!$D:$D,$F24,人员状况!$G:$G,"<="&S$10,人员状况!$H:$H,">="&S$10+1) -> 1 | T24: =AT24 -> 1 | U24: =COUNTIFS(人员状况!$C:$C,$E24,人员状况!$D:$D,$F24,人员状况!$G:$G,"<="&U$10,人员状况!$H:$H,">="&U$10+1) -> 1 | V24: =IF(MONTH($G$3)>=V$8,COUNTIFS(人员状况!$C:$C,$E24,人员状况!$D:$D,$F24,人员状况!$G:$G,"<="&V$10,人员状况!$H:$H,">="&V$10+1),0) -> 1 | W24: =IF(MONTH($G$3)>=W$8,COUNTIFS(人员状况!$C:$C,$E24,人员状况!$D:$D,$F24,人员状况!$G:$G,"<="&W$10,人员状况!$H:$H,">="&W$10+1),0) -> 1 | X24: =IF(MONTH($G$3)>=X$8,COUNTIFS(人员状况!$C:$C,$E24,人员状况!$D:$D,$F24,人员状况!$G:$G,"<="&X$10,人员状况!$H:$H,">="&X$10+1),0) -> 1 | Y24: =IF(MONTH($G$3)>=Y$8,COUNTIFS(人员状况!$C:$C,$E24,人员状况!$D:$D,$F24,人员状况!$G:$G,"<="&Y$10,人员状况!$H:$H,">="&Y$10+1),0) -> 1 | Z24: =IF(MONTH($G$3)>=Z$8,COUNTIFS(人员状况!$C:$C,$E24,人员状况!$D:$D,$F24,人员状况!$G:$G,"<="&Z$10,人员状况!$H:$H,">="&Z$10+1),0) -> 1 | AA24: =IF(MONTH($G$3)>=AA$8,COUNTIFS(人员状况!$C:$C,$E24,人员状况!$D:$D,$F24,人员状况!$G:$G,"<="&AA$10,人员状况!$H:$H,">="&AA$10+1),0) -> 1 | AB24: =IF(MONTH($G$3)>=AB$8,COUNTIFS(人员状况!$C:$C,$E24,人员状况!$D:$D,$F24,人员状况!$G:$G,"<="&AB$10,人员状况!$H:$H,">="&AB$10+1),0) -> 1 | AC24: =IF(MONTH($G$3)>=AC$8,COUNTIFS(人员状况!$C:$C,$E24,人员状况!$D:$D,$F24,人员状况!$G:$G,"<="&AC$10,人员状况!$H:$H,">="&AC$10+1),0) -> 1 | ... AG24: =IF(MONTH($G$3)>=AG$8,COUNTIFS(人员状况!$C:$C,$E24,人员状况!$D:$D,$F24,人员状况!$G:$G,"<="&AG$10,人员状况!$H:$H,">="&AG$10+1),0) -> 0 | AH24: =AT24 -> 1 | AI24: =IF(MONTH($G$3)>=AI$8,0,S24+SUMIFS(预计变动!$F:$F,预计变动!$A:$A,$E24,预计变动!$B:$B,$F24,预计变动!$I:$I,">="&AI$9,预计变动!$I:$I,"<="&AI$10)) -> 0 | AJ24: =IF(MONTH($G$3)>=AJ$8,0,IF(V24=0,AI24,V24)+SUMIFS(预计变动!$F:$F,预计变动!$A:$A,$E24,预计变动!$B:$B,$F24,预计变动!$I:$I,">="&AJ$9,预计变动!$I:$I,"<="&AJ$10)) -> 0 | AK24: =IF(MONTH($G$3)>=AK$8,0,IF(W24=0,AJ24,W24)+SUMIFS(预计变动!$F:$F,预计变动!$A:$A,$E24,预计变动!$B:$B,$F24,预计变动!$I:$I,">="&AK$9,预计变动!$I:$I,"<="&AK$10)) -> 0 | AL24: =IF(MONTH($G$3)>=AL$8,0,IF(X24=0,AK24,X24)+SUMIFS(预计变动!$F:$F,预计变动!$A:$A,$E24,预计变动!$B:$B,$F24,预计变动!$I:$I,">="&AL$9,预计变动!$I:$I,"<="&AL$10)) -> 0 | AM24: =IF(MONTH($G$3)>=AM$8,0,IF(Y24=0,AL24,Y24)+SUMIFS(预计变动!$F:$F,预计变动!$A:$A,$E24,预计变动!$B:$B,$F24,预计变动!$I:$I,">="&AM$9,预计变动!$I:$I,"<="&AM$10)) -> 0 | AN24: =IF(MONTH($G$3)>=AN$8,0,IF(Z24=0,AM24,Z24)+SUMIFS(预计变动!$F:$F,预计变动!$A:$A,$E24,预计变动!$B:$B,$F24,预计变动!$I:$I,">="&AN$9,预计变动!$I:$I,"<="&AN$10)) -> 0 | AO24: =IF(MONTH($G$3)>=AO$8,0,IF(AA24=0,AN24,AA24)+SUMIFS(预计变动!$F:$F,预计变动!$A:$A,$E24,预计变动!$B:$B,$F24,预计变动!$I:$I,">="&AO$9,预计变动!$I:$I,"<="&AO$10)) -> 0 | AP24: =IF(MONTH($G$3)>=AP$8,0,IF(AB24=0,AO24,AB24)+SUMIFS(预计变动!$F:$F,预计变动!$A:$A,$E24,预计变动!$B:$B,$F24,预计变动!$I:$I,">="&AP$9,预计变动!$I:$I,"<="&AP$10)) -> 0 | AQ24: =IF(MONTH($G$3)>=AQ$8,0,IF(AC24=0,AP24,AC24)+SUMIFS(预计变动!$F:$F,预计变动!$A:$A,$E24,预计变动!$B:$B,$F24,预计变动!$I:$I,">="&AQ$9,预计变动!$I:$I,"<="&AQ$10)) -> 0 | AR24: =IF(MONTH($G$3)>AR$8,0,IF(AD24=0,AQ24,AD24)+SUMIFS(预计变动!$F:$F,预计变动!$A:$A,$E24,预计变动!$B:$B,$F24,预计变动!$I:$I,">="&AR$9,预计变动!$I:$I,"<="&AR$10)) -> 1 | AS24: =IF(MONTH($G$3)>AS$8,0,IF(AE24=0,AR24,AE24)+SUMIFS(预计变动!$F:$F,预计变动!$A:$A,$E24,预计变动!$B:$B,$F24,预计变动!$I:$I,">="&AS$9,预计变动!$I:$I,"<="&AS$10)) -> 1 | AT24: =IF(MONTH($G$3)>AT$8,0,IF(AF24=0,AS24,AF24)+SUMIFS(预计变动!$F:$F,预计变动!$A:$A,$E24,预计变动!$B:$B,$F24,预计变动!$I:$I,">="&AT$9,预计变动!$I:$I,"<="&AT$10)) -> 1 | AU24: =BG24 -> 1 | AV24: =AT24+SUMIFS(预计变动!$F:$F,预计变动!$A:$A,$E24,预计变动!$B:$B,$F24,预计变动!$I:$I,">="&AV$9,预计变动!$I:$I,"<="&AV$10) -> 1 | AW24: =AV24+SUMIFS(预计变动!$F:$F,预计变动!$A:$A,$E24,预计变动!$B:$B,$F24,预计变动!$I:$I,">="&AW$9,预计变动!$I:$I,"<="&AW$10) -> 1 | AX24: =AW24+SUMIFS(预计变动!$F:$F,预计变动!$A:$A,$E24,预计变动!$B:$B,$F24,预计变动!$I:$I,">="&AX$9,预计变动!$I:$I,"<="&AX$10) -> 1 | AY24: =AX24+SUMIFS(预计变动!$F:$F,预计变动!$A:$A,$E24,预计变动!$B:$B,$F24,预计变动!$I:$I,">="&AY$9,预计变动!$I:$I,"<="&AY$10) -> 1 | AZ24: =AY24+SUMIFS(预计变动!$F:$F,预计变动!$A:$A,$E24,预计变动!$B:$B,$F24,预计变动!$I:$I,">="&AZ$9,预计变动!$I:$I,"<="&AZ$10) -> 1 | BA24: =AZ24+SUMIFS(预计变动!$F:$F,预计变动!$A:$A,$E24,预计变动!$B:$B,$F24,预计变动!$I:$I,">="&BA$9,预计变动!$I:$I,"<="&BA$10) -> 1 | BB24: =BA24+SUMIFS(预计变动!$F:$F,预计变动!$A:$A,$E24,预计变动!$B:$B,$F24,预计变动!$I:$I,">="&BB$9,预计变动!$I:$I,"<="&BB$10) -> 1 | BC24: =BB24+SUMIFS(预计变动!$F:$F,预计变动!$A:$A,$E24,预计变动!$B:$B,$F24,预计变动!$I:$I,">="&BC$9,预计变动!$I:$I,"<="&BC$10) -> 1 | BD24: =BC24+SUMIFS(预计变动!$F:$F,预计变动!$A:$A,$E24,预计变动!$B:$B,$F24,预计变动!$I:$I,">="&BD$9,预计变动!$I:$I,"<="&BD$10) -> 1 | ... BG24: =BF24+SUMIFS(预计变动!$F:$F,预计变动!$A:$A,$E24,预计变动!$B:$B,$F24,预计变动!$I:$I,">="&BG$9,预计变动!$I:$I,"<="&BG$10) -> 1
B26: 平均人数
B27: 合计 | E27: * | F27: * | G27: =SUMIFS(薪酬明细!$K:$K,薪酬明细!$D:$D,$E27,薪酬明细!$E:$E,$F27,薪酬明细!$H:$H,">="&G$9,薪酬明细!$H:$H,"<="&G$10,薪酬明细!$A:$A,G$6)/12 -> 73 | H27: =SUMIFS(薪酬明细!$K:$K,薪酬明细!$D:$D,$E27,薪酬明细!$E:$E,$F27,薪酬明细!$H:$H,">="&H$9,薪酬明细!$H:$H,"<="&H$10,薪酬明细!$A:$A,H$6) -> 73 | I27: =SUMIFS(薪酬明细!$K:$K,薪酬明细!$D:$D,$E27,薪酬明细!$E:$E,$F27,薪酬明细!$H:$H,">="&I$9,薪酬明细!$H:$H,"<="&I$10,薪酬明细!$A:$A,I$6) -> 73 | J27: =SUMIFS(薪酬明细!$K:$K,薪酬明细!$D:$D,$E27,薪酬明细!$E:$E,$F27,薪酬明细!$H:$H,">="&J$9,薪酬明细!$H:$H,"<="&J$10,薪酬明细!$A:$A,J$6) -> 73 | K27: =SUMIFS(薪酬明细!$K:$K,薪酬明细!$D:$D,$E27,薪酬明细!$E:$E,$F27,薪酬明细!$H:$H,">="&K$9,薪酬明细!$H:$H,"<="&K$10,薪酬明细!$A:$A,K$6) -> 73 | L27: =SUMIFS(薪酬明细!$K:$K,薪酬明细!$D:$D,$E27,薪酬明细!$E:$E,$F27,薪酬明细!$H:$H,">="&L$9,薪酬明细!$H:$H,"<="&L$10,薪酬明细!$A:$A,L$6) -> 73 | M27: =SUMIFS(薪酬明细!$K:$K,薪酬明细!$D:$D,$E27,薪酬明细!$E:$E,$F27,薪酬明细!$H:$H,">="&M$9,薪酬明细!$H:$H,"<="&M$10,薪酬明细!$A:$A,M$6) -> 73 | N27: =SUMIFS(薪酬明细!$K:$K,薪酬明细!$D:$D,$E27,薪酬明细!$E:$E,$F27,薪酬明细!$H:$H,">="&N$9,薪酬明细!$H:$H,"<="&N$10,薪酬明细!$A:$A,N$6) -> 73 | O27: =SUMIFS(薪酬明细!$K:$K,薪酬明细!$D:$D,$E27,薪酬明细!$E:$E,$F27,薪酬明细!$H:$H,">="&O$9,薪酬明细!$H:$H,"<="&O$10,薪酬明细!$A:$A,O$6) -> 73 | ... S27: =SUMIFS(薪酬明细!$K:$K,薪酬明细!$D:$D,$E27,薪酬明细!$E:$E,$F27,薪酬明细!$H:$H,">="&S$9,薪酬明细!$H:$H,"<="&S$10,薪酬明细!$A:$A,S$6) -> 73 | T27: =(U27*MONTH($G$3)+AH27*(12-MONTH($G$3)))/12 -> 73 | U27: =SUMIFS(薪酬明细!$K:$K,薪酬明细!$D:$D,$E27,薪酬明细!$E:$E,$F27,薪酬明细!$H:$H,">="&U$9,薪酬明细!$H:$H,"<="&U$10,薪酬明细!$A:$A,U$6)/MONTH($G$3) -> 73 | V27: =SUMIFS(薪酬明细!$K:$K,薪酬明细!$D:$D,$E27,薪酬明细!$E:$E,$F27,薪酬明细!$H:$H,">="&V$9,薪酬明细!$H:$H,"<="&V$10,薪酬明细!$A:$A,V$6) -> 73 | W27: =SUMIFS(薪酬明细!$K:$K,薪酬明细!$D:$D,$E27,薪酬明细!$E:$E,$F27,薪酬明细!$H:$H,">="&W$9,薪酬明细!$H:$H,"<="&W$10,薪酬明细!$A:$A,W$6) -> 73 | X27: =SUMIFS(薪酬明细!$K:$K,薪酬明细!$D:$D,$E27,薪酬明细!$E:$E,$F27,薪酬明细!$H:$H,">="&X$9,薪酬明细!$H:$H,"<="&X$10,薪酬明细!$A:$A,X$6) -> 73 | Y27: =SUMIFS(薪酬明细!$K:$K,薪酬明细!$D:$D,$E27,薪酬明细!$E:$E,$F27,薪酬明细!$H:$H,">="&Y$9,薪酬明细!$H:$H,"<="&Y$10,薪酬明细!$A:$A,Y$6) -> 73 | Z27: =SUMIFS(薪酬明细!$K:$K,薪酬明细!$D:$D,$E27,薪酬明细!$E:$E,$F27,薪酬明细!$H:$H,">="&Z$9,薪酬明细!$H:$H,"<="&Z$10,薪酬明细!$A:$A,Z$6) -> 73 | AA27: =SUMIFS(薪酬明细!$K:$K,薪酬明细!$D:$D,$E27,薪酬明细!$E:$E,$F27,薪酬明细!$H:$H,">="&AA$9,薪酬明细!$H:$H,"<="&AA$10,薪酬明细!$A:$A,AA$6) -> 73 | AB27: =SUMIFS(薪酬明细!$K:$K,薪酬明细!$D:$D,$E27,薪酬明细!$E:$E,$F27,薪酬明细!$H:$H,">="&AB$9,薪酬明细!$H:$H,"<="&AB$10,薪酬明细!$A:$A,AB$6) -> 73 | AC27: =SUMIFS(薪酬明细!$K:$K,薪酬明细!$D:$D,$E27,薪酬明细!$E:$E,$F27,薪酬明细!$H:$H,">="&AC$9,薪酬明细!$H:$H,"<="&AC$10,薪酬明细!$A:$A,AC$6) -> 73 | ... AG27: =SUMIFS(薪酬明细!$K:$K,薪酬明细!$D:$D,$E27,薪酬明细!$E:$E,$F27,薪酬明细!$H:$H,">="&AG$9,薪酬明细!$H:$H,"<="&AG$10,薪酬明细!$A:$A,AG$6) -> 0 | AH27: =SUMIFS(薪酬明细!$K:$K,薪酬明细!$D:$D,$E27,薪酬明细!$E:$E,$F27,薪酬明细!$H:$H,">="&AH$9,薪酬明细!$H:$H,"<="&AH$10,薪酬明细!$A:$A,AH$6)/(12-MONTH($G$3)) -> 73 | AI27: =SUMIFS(薪酬明细!$K:$K,薪酬明细!$D:$D,$E27,薪酬明细!$E:$E,$F27,薪酬明细!$H:$H,">="&AI$9,薪酬明细!$H:$H,"<="&AI$10,薪酬明细!$A:$A,AI$6) -> 0 | AJ27: =SUMIFS(薪酬明细!$K:$K,薪酬明细!$D:$D,$E27,薪酬明细!$E:$E,$F27,薪酬明细!$H:$H,">="&AJ$9,薪酬明细!$H:$H,"<="&AJ$10,薪酬明细!$A:$A,AJ$6) -> 0 | AK27: =SUMIFS(薪酬明细!$K:$K,薪酬明细!$D:$D,$E27,薪酬明细!$E:$E,$F27,薪酬明细!$H:$H,">="&AK$9,薪酬明细!$H:$H,"<="&AK$10,薪酬明细!$A:$A,AK$6) -> 0 | AL27: =SUMIFS(薪酬明细!$K:$K,薪酬明细!$D:$D,$E27,薪酬明细!$E:$E,$F27,薪酬明细!$H:$H,">="&AL$9,薪酬明细!$H:$H,"<="&AL$10,薪酬明细!$A:$A,AL$6) -> 0 | AM27: =SUMIFS(薪酬明细!$K:$K,薪酬明细!$D:$D,$E27,薪酬明细!$E:$E,$F27,薪酬明细!$H:$H,">="&AM$9,薪酬明细!$H:$H,"<="&AM$10,薪酬明细!$A:$A,AM$6) -> 0 | AN27: =SUMIFS(薪酬明细!$K:$K,薪酬明细!$D:$D,$E27,薪酬明细!$E:$E,$F27,薪酬明细!$H:$H,">="&AN$9,薪酬明细!$H:$H,"<="&AN$10,薪酬明细!$A:$A,AN$6) -> 0 | AO27: =SUMIFS(薪酬明细!$K:$K,薪酬明细!$D:$D,$E27,薪酬明细!$E:$E,$F27,薪酬明细!$H:$H,">="&AO$9,薪酬明细!$H:$H,"<="&AO$10,薪酬明细!$A:$A,AO$6) -> 0 | AP27: =SUMIFS(薪酬明细!$K:$K,薪酬明细!$D:$D,$E27,薪酬明细!$E:$E,$F27,薪酬明细!$H:$H,">="&AP$9,薪酬明细!$H:$H,"<="&AP$10,薪酬明细!$A:$A,AP$6) -> 0 | ... AT27: =SUMIFS(薪酬明细!$K:$K,薪酬明细!$D:$D,$E27,薪酬明细!$E:$E,$F27,薪酬明细!$H:$H,">="&AT$9,薪酬明细!$H:$H,"<="&AT$10,薪酬明细!$A:$A,AT$6) -> 73 | AU27: =SUMIFS(薪酬明细!$K:$K,薪酬明细!$D:$D,$E27,薪酬明细!$E:$E,$F27,薪酬明细!$H:$H,">="&AU$9,薪酬明细!$H:$H,"<="&AU$10,薪酬明细!$A:$A,AU$6)/12 -> 73 | AV27: =SUMIFS(薪酬明细!$K:$K,薪酬明细!$D:$D,$E27,薪酬明细!$E:$E,$F27,薪酬明细!$H:$H,">="&AV$9,薪酬明细!$H:$H,"<="&AV$10,薪酬明细!$A:$A,AV$6) -> 73 | AW27: =SUMIFS(薪酬明细!$K:$K,薪酬明细!$D:$D,$E27,薪酬明细!$E:$E,$F27,薪酬明细!$H:$H,">="&AW$9,薪酬明细!$H:$H,"<="&AW$10,薪酬明细!$A:$A,AW$6) -> 73 | AX27: =SUMIFS(薪酬明细!$K:$K,薪酬明细!$D:$D,$E27,薪酬明细!$E:$E,$F27,薪酬明细!$H:$H,">="&AX$9,薪酬明细!$H:$H,"<="&AX$10,薪酬明细!$A:$A,AX$6) -> 73 | AY27: =SUMIFS(薪酬明细!$K:$K,薪酬明细!$D:$D,$E27,薪酬明细!$E:$E,$F27,薪酬明细!$H:$H,">="&AY$9,薪酬明细!$H:$H,"<="&AY$10,薪酬明细!$A:$A,AY$6) -> 73 | AZ27: =SUMIFS(薪酬明细!$K:$K,薪酬明细!$D:$D,$E27,薪酬明细!$E:$E,$F27,薪酬明细!$H:$H,">="&AZ$9,薪酬明细!$H:$H,"<="&AZ$10,薪酬明细!$A:$A,AZ$6) -> 73 | BA27: =SUMIFS(薪酬明细!$K:$K,薪酬明细!$D:$D,$E27,薪酬明细!$E:$E,$F27,薪酬明细!$H:$H,">="&BA$9,薪酬明细!$H:$H,"<="&BA$10,薪酬明细!$A:$A,BA$6) -> 73 | BB27: =SUMIFS(薪酬明细!$K:$K,薪酬明细!$D:$D,$E27,薪酬明细!$E:$E,$F27,薪酬明细!$H:$H,">="&BB$9,薪酬明细!$H:$H,"<="&BB$10,薪酬明细!$A:$A,BB$6) -> 73 | BC27: =SUMIFS(薪酬明细!$K:$K,薪酬明细!$D:$D,$E27,薪酬明细!$E:$E,$F27,薪酬明细!$H:$H,">="&BC$9,薪酬明细!$H:$H,"<="&BC$10,薪酬明细!$A:$A,BC$6) -> 73 | ... BG27: =SUMIFS(薪酬明细!$K:$K,薪酬明细!$D:$D,$E27,薪酬明细!$E:$E,$F27,薪酬明细!$H:$H,">="&BG$9,薪酬明细!$H:$H,"<="&BG$10,薪酬明细!$A:$A,BG$6) -> 73
C28: 流程中心 | E28: =IF(C28<>"",C28,E27) -> 流程中心 | F28: =IF(D28<>"",D28,"*") -> * | G28: =SUMIFS(薪酬明细!$K:$K,薪酬明细!$D:$D,$E28,薪酬明细!$E:$E,$F28,薪酬明细!$H:$H,">="&G$9,薪酬明细!$H:$H,"<="&G$10,薪酬明细!$A:$A,G$6)/12 -> 36 | H28: =SUMIFS(薪酬明细!$K:$K,薪酬明细!$D:$D,$E28,薪酬明细!$E:$E,$F28,薪酬明细!$H:$H,">="&H$9,薪酬明细!$H:$H,"<="&H$10,薪酬明细!$A:$A,H$6) -> 36 | I28: =SUMIFS(薪酬明细!$K:$K,薪酬明细!$D:$D,$E28,薪酬明细!$E:$E,$F28,薪酬明细!$H:$H,">="&I$9,薪酬明细!$H:$H,"<="&I$10,薪酬明细!$A:$A,I$6) -> 36 | J28: =SUMIFS(薪酬明细!$K:$K,薪酬明细!$D:$D,$E28,薪酬明细!$E:$E,$F28,薪酬明细!$H:$H,">="&J$9,薪酬明细!$H:$H,"<="&J$10,薪酬明细!$A:$A,J$6) -> 36 | K28: =SUMIFS(薪酬明细!$K:$K,薪酬明细!$D:$D,$E28,薪酬明细!$E:$E,$F28,薪酬明细!$H:$H,">="&K$9,薪酬明细!$H:$H,"<="&K$10,薪酬明细!$A:$A,K$6) -> 36 | L28: =SUMIFS(薪酬明细!$K:$K,薪酬明细!$D:$D,$E28,薪酬明细!$E:$E,$F28,薪酬明细!$H:$H,">="&L$9,薪酬明细!$H:$H,"<="&L$10,薪酬明细!$A:$A,L$6) -> 36 | M28: =SUMIFS(薪酬明细!$K:$K,薪酬明细!$D:$D,$E28,薪酬明细!$E:$E,$F28,薪酬明细!$H:$H,">="&M$9,薪酬明细!$H:$H,"<="&M$10,薪酬明细!$A:$A,M$6) -> 36 | N28: =SUMIFS(薪酬明细!$K:$K,薪酬明细!$D:$D,$E28,薪酬明细!$E:$E,$F28,薪酬明细!$H:$H,">="&N$9,薪酬明细!$H:$H,"<="&N$10,薪酬明细!$A:$A,N$6) -> 36 | O28: =SUMIFS(薪酬明细!$K:$K,薪酬明细!$D:$D,$E28,薪酬明细!$E:$E,$F28,薪酬明细!$H:$H,">="&O$9,薪酬明细!$H:$H,"<="&O$10,薪酬明细!$A:$A,O$6) -> 36 | ... S28: =SUMIFS(薪酬明细!$K:$K,薪酬明细!$D:$D,$E28,薪酬明细!$E:$E,$F28,薪酬明细!$H:$H,">="&S$9,薪酬明细!$H:$H,"<="&S$10,薪酬明细!$A:$A,S$6) -> 36 | T28: =(U28*MONTH($G$3)+AH28*(12-MONTH($G$3)))/12 -> 36 | U28: =SUMIFS(薪酬明细!$K:$K,薪酬明细!$D:$D,$E28,薪酬明细!$E:$E,$F28,薪酬明细!$H:$H,">="&U$9,薪酬明细!$H:$H,"<="&U$10,薪酬明细!$A:$A,U$6)/MONTH($G$3) -> 36 | V28: =SUMIFS(薪酬明细!$K:$K,薪酬明细!$D:$D,$E28,薪酬明细!$E:$E,$F28,薪酬明细!$H:$H,">="&V$9,薪酬明细!$H:$H,"<="&V$10,薪酬明细!$A:$A,V$6) -> 36 | W28: =SUMIFS(薪酬明细!$K:$K,薪酬明细!$D:$D,$E28,薪酬明细!$E:$E,$F28,薪酬明细!$H:$H,">="&W$9,薪酬明细!$H:$H,"<="&W$10,薪酬明细!$A:$A,W$6) -> 36 | X28: =SUMIFS(薪酬明细!$K:$K,薪酬明细!$D:$D,$E28,薪酬明细!$E:$E,$F28,薪酬明细!$H:$H,">="&X$9,薪酬明细!$H:$H,"<="&X$10,薪酬明细!$A:$A,X$6) -> 36 | Y28: =SUMIFS(薪酬明细!$K:$K,薪酬明细!$D:$D,$E28,薪酬明细!$E:$E,$F28,薪酬明细!$H:$H,">="&Y$9,薪酬明细!$H:$H,"<="&Y$10,薪酬明细!$A:$A,Y$6) -> 36 | Z28: =SUMIFS(薪酬明细!$K:$K,薪酬明细!$D:$D,$E28,薪酬明细!$E:$E,$F28,薪酬明细!$H:$H,">="&Z$9,薪酬明细!$H:$H,"<="&Z$10,薪酬明细!$A:$A,Z$6) -> 36 | AA28: =SUMIFS(薪酬明细!$K:$K,薪酬明细!$D:$D,$E28,薪酬明细!$E:$E,$F28,薪酬明细!$H:$H,">="&AA$9,薪酬明细!$H:$H,"<="&AA$10,薪酬明细!$A:$A,AA$6) -> 36 | AB28: =SUMIFS(薪酬明细!$K:$K,薪酬明细!$D:$D,$E28,薪酬明细!$E:$E,$F28,薪酬明细!$H:$H,">="&AB$9,薪酬明细!$H:$H,"<="&AB$10,薪酬明细!$A:$A,AB$6) -> 36 | AC28: =SUMIFS(薪酬明细!$K:$K,薪酬明细!$D:$D,$E28,薪酬明细!$E:$E,$F28,薪酬明细!$H:$H,">="&AC$9,薪酬明细!$H:$H,"<="&AC$10,薪酬明细!$A:$A,AC$6) -> 36 | ... AG28: =SUMIFS(薪酬明细!$K:$K,薪酬明细!$D:$D,$E28,薪酬明细!$E:$E,$F28,薪酬明细!$H:$H,">="&AG$9,薪酬明细!$H:$H,"<="&AG$10,薪酬明细!$A:$A,AG$6) -> 0 | AH28: =SUMIFS(薪酬明细!$K:$K,薪酬明细!$D:$D,$E28,薪酬明细!$E:$E,$F28,薪酬明细!$H:$H,">="&AH$9,薪酬明细!$H:$H,"<="&AH$10,薪酬明细!$A:$A,AH$6)/(12-MONTH($G$3)) -> 36 | AI28: =SUMIFS(薪酬明细!$K:$K,薪酬明细!$D:$D,$E28,薪酬明细!$E:$E,$F28,薪酬明细!$H:$H,">="&AI$9,薪酬明细!$H:$H,"<="&AI$10,薪酬明细!$A:$A,AI$6) -> 0 | AJ28: =SUMIFS(薪酬明细!$K:$K,薪酬明细!$D:$D,$E28,薪酬明细!$E:$E,$F28,薪酬明细!$H:$H,">="&AJ$9,薪酬明细!$H:$H,"<="&AJ$10,薪酬明细!$A:$A,AJ$6) -> 0 | AK28: =SUMIFS(薪酬明细!$K:$K,薪酬明细!$D:$D,$E28,薪酬明细!$E:$E,$F28,薪酬明细!$H:$H,">="&AK$9,薪酬明细!$H:$H,"<="&AK$10,薪酬明细!$A:$A,AK$6) -> 0 | AL28: =SUMIFS(薪酬明细!$K:$K,薪酬明细!$D:$D,$E28,薪酬明细!$E:$E,$F28,薪酬明细!$H:$H,">="&AL$9,薪酬明细!$H:$H,"<="&AL$10,薪酬明细!$A:$A,AL$6) -> 0 | AM28: =SUMIFS(薪酬明细!$K:$K,薪酬明细!$D:$D,$E28,薪酬明细!$E:$E,$F28,薪酬明细!$H:$H,">="&AM$9,薪酬明细!$H:$H,"<="&AM$10,薪酬明细!$A:$A,AM$6) -> 0 | AN28: =SUMIFS(薪酬明细!$K:$K,薪酬明细!$D:$D,$E28,薪酬明细!$E:$E,$F28,薪酬明细!$H:$H,">="&AN$9,薪酬明细!$H:$H,"<="&AN$10,薪酬明细!$A:$A,AN$6) -> 0 | AO28: =SUMIFS(薪酬明细!$K:$K,薪酬明细!$D:$D,$E28,薪酬明细!$E:$E,$F28,薪酬明细!$H:$H,">="&AO$9,薪酬明细!$H:$H,"<="&AO$10,薪酬明细!$A:$A,AO$6) -> 0 | AP28: =SUMIFS(薪酬明细!$K:$K,薪酬明细!$D:$D,$E28,薪酬明细!$E:$E,$F28,薪酬明细!$H:$H,">="&AP$9,薪酬明细!$H:$H,"<="&AP$10,薪酬明细!$A:$A,AP$6) -> 0 | ... AT28: =SUMIFS(薪酬明细!$K:$K,薪酬明细!$D:$D,$E28,薪酬明细!$E:$E,$F28,薪酬明细!$H:$H,">="&AT$9,薪酬明细!$H:$H,"<="&AT$10,薪酬明细!$A:$A,AT$6) -> 36 | AU28: =SUMIFS(薪酬明细!$K:$K,薪酬明细!$D:$D,$E28,薪酬明细!$E:$E,$F28,薪酬明细!$H:$H,">="&AU$9,薪酬明细!$H:$H,"<="&AU$10,薪酬明细!$A:$A,AU$6)/12 -> 36 | AV28: =SUMIFS(薪酬明细!$K:$K,薪酬明细!$D:$D,$E28,薪酬明细!$E:$E,$F28,薪酬明细!$H:$H,">="&AV$9,薪酬明细!$H:$H,"<="&AV$10,薪酬明细!$A:$A,AV$6) -> 36 | AW28: =SUMIFS(薪酬明细!$K:$K,薪酬明细!$D:$D,$E28,薪酬明细!$E:$E,$F28,薪酬明细!$H:$H,">="&AW$9,薪酬明细!$H:$H,"<="&AW$10,薪酬明细!$A:$A,AW$6) -> 36 | AX28: =SUMIFS(薪酬明细!$K:$K,薪酬明细!$D:$D,$E28,薪酬明细!$E:$E,$F28,薪酬明细!$H:$H,">="&AX$9,薪酬明细!$H:$H,"<="&AX$10,薪酬明细!$A:$A,AX$6) -> 36 | AY28: =SUMIFS(薪酬明细!$K:$K,薪酬明细!$D:$D,$E28,薪酬明细!$E:$E,$F28,薪酬明细!$H:$H,">="&AY$9,薪酬明细!$H:$H,"<="&AY$10,薪酬明细!$A:$A,AY$6) -> 36 | AZ28: =SUMIFS(薪酬明细!$K:$K,薪酬明细!$D:$D,$E28,薪酬明细!$E:$E,$F28,薪酬明细!$H:$H,">="&AZ$9,薪酬明细!$H:$H,"<="&AZ$10,薪酬明细!$A:$A,AZ$6) -> 36 | BA28: =SUMIFS(薪酬明细!$K:$K,薪酬明细!$D:$D,$E28,薪酬明细!$E:$E,$F28,薪酬明细!$H:$H,">="&BA$9,薪酬明细!$H:$H,"<="&BA$10,薪酬明细!$A:$A,BA$6) -> 36 | BB28: =SUMIFS(薪酬明细!$K:$K,薪酬明细!$D:$D,$E28,薪酬明细!$E:$E,$F28,薪酬明细!$H:$H,">="&BB$9,薪酬明细!$H:$H,"<="&BB$10,薪酬明细!$A:$A,BB$6) -> 36 | BC28: =SUMIFS(薪酬明细!$K:$K,薪酬明细!$D:$D,$E28,薪酬明细!$E:$E,$F28,薪酬明细!$H:$H,">="&BC$9,薪酬明细!$H:$H,"<="&BC$10,薪酬明细!$A:$A,BC$6) -> 36 | ... BG28: =SUMIFS(薪酬明细!$K:$K,薪酬明细!$D:$D,$E28,薪酬明细!$E:$E,$F28,薪酬明细!$H:$H,">="&BG$9,薪酬明细!$H:$H,"<="&BG$10,薪酬明细!$A:$A,BG$6) -> 36
D29: 销售中心 | E29: =IF(C29<>"",C29,E28) -> 流程中心 | F29: =IF(D29<>"",D29,"*") -> 销售中心 | G29: =SUMIFS(薪酬明细!$K:$K,薪酬明细!$D:$D,$E29,薪酬明细!$E:$E,$F29,薪酬明细!$H:$H,">="&G$9,薪酬明细!$H:$H,"<="&G$10,薪酬明细!$A:$A,G$6)/12 -> 14 | H29: =SUMIFS(薪酬明细!$K:$K,薪酬明细!$D:$D,$E29,薪酬明细!$E:$E,$F29,薪酬明细!$H:$H,">="&H$9,薪酬明细!$H:$H,"<="&H$10,薪酬明细!$A:$A,H$6) -> 14 | I29: =SUMIFS(薪酬明细!$K:$K,薪酬明细!$D:$D,$E29,薪酬明细!$E:$E,$F29,薪酬明细!$H:$H,">="&I$9,薪酬明细!$H:$H,"<="&I$10,薪酬明细!$A:$A,I$6) -> 14 | J29: =SUMIFS(薪酬明细!$K:$K,薪酬明细!$D:$D,$E29,薪酬明细!$E:$E,$F29,薪酬明细!$H:$H,">="&J$9,薪酬明细!$H:$H,"<="&J$10,薪酬明细!$A:$A,J$6) -> 14 | K29: =SUMIFS(薪酬明细!$K:$K,薪酬明细!$D:$D,$E29,薪酬明细!$E:$E,$F29,薪酬明细!$H:$H,">="&K$9,薪酬明细!$H:$H,"<="&K$10,薪酬明细!$A:$A,K$6) -> 14 | L29: =SUMIFS(薪酬明细!$K:$K,薪酬明细!$D:$D,$E29,薪酬明细!$E:$E,$F29,薪酬明细!$H:$H,">="&L$9,薪酬明细!$H:$H,"<="&L$10,薪酬明细!$A:$A,L$6) -> 14 | M29: =SUMIFS(薪酬明细!$K:$K,薪酬明细!$D:$D,$E29,薪酬明细!$E:$E,$F29,薪酬明细!$H:$H,">="&M$9,薪酬明细!$H:$H,"<="&M$10,薪酬明细!$A:$A,M$6) -> 14 | N29: =SUMIFS(薪酬明细!$K:$K,薪酬明细!$D:$D,$E29,薪酬明细!$E:$E,$F29,薪酬明细!$H:$H,">="&N$9,薪酬明细!$H:$H,"<="&N$10,薪酬明细!$A:$A,N$6) -> 14 | O29: =SUMIFS(薪酬明细!$K:$K,薪酬明细!$D:$D,$E29,薪酬明细!$E:$E,$F29,薪酬明细!$H:$H,">="&O$9,薪酬明细!$H:$H,"<="&O$10,薪酬明细!$A:$A,O$6) -> 14 | ... S29: =SUMIFS(薪酬明细!$K:$K,薪酬明细!$D:$D,$E29,薪酬明细!$E:$E,$F29,薪酬明细!$H:$H,">="&S$9,薪酬明细!$H:$H,"<="&S$10,薪酬明细!$A:$A,S$6) -> 14 | T29: =(U29*MONTH($G$3)+AH29*(12-MONTH($G$3)))/12 -> 14 | U29: =SUMIFS(薪酬明细!$K:$K,薪酬明细!$D:$D,$E29,薪酬明细!$E:$E,$F29,薪酬明细!$H:$H,">="&U$9,薪酬明细!$H:$H,"<="&U$10,薪酬明细!$A:$A,U$6)/MONTH($G$3) -> 14 | V29: =SUMIFS(薪酬明细!$K:$K,薪酬明细!$D:$D,$E29,薪酬明细!$E:$E,$F29,薪酬明细!$H:$H,">="&V$9,薪酬明细!$H:$H,"<="&V$10,薪酬明细!$A:$A,V$6) -> 14 | W29: =SUMIFS(薪酬明细!$K:$K,薪酬明细!$D:$D,$E29,薪酬明细!$E:$E,$F29,薪酬明细!$H:$H,">="&W$9,薪酬明细!$H:$H,"<="&W$10,薪酬明细!$A:$A,W$6) -> 14 | X29: =SUMIFS(薪酬明细!$K:$K,薪酬明细!$D:$D,$E29,薪酬明细!$E:$E,$F29,薪酬明细!$H:$H,">="&X$9,薪酬明细!$H:$H,"<="&X$10,薪酬明细!$A:$A,X$6) -> 14 | Y29: =SUMIFS(薪酬明细!$K:$K,薪酬明细!$D:$D,$E29,薪酬明细!$E:$E,$F29,薪酬明细!$H:$H,">="&Y$9,薪酬明细!$H:$H,"<="&Y$10,薪酬明细!$A:$A,Y$6) -> 14 | Z29: =SUMIFS(薪酬明细!$K:$K,薪酬明细!$D:$D,$E29,薪酬明细!$E:$E,$F29,薪酬明细!$H:$H,">="&Z$9,薪酬明细!$H:$H,"<="&Z$10,薪酬明细!$A:$A,Z$6) -> 14 | AA29: =SUMIFS(薪酬明细!$K:$K,薪酬明细!$D:$D,$E29,薪酬明细!$E:$E,$F29,薪酬明细!$H:$H,">="&AA$9,薪酬明细!$H:$H,"<="&AA$10,薪酬明细!$A:$A,AA$6) -> 14 | AB29: =SUMIFS(薪酬明细!$K:$K,薪酬明细!$D:$D,$E29,薪酬明细!$E:$E,$F29,薪酬明细!$H:$H,">="&AB$9,薪酬明细!$H:$H,"<="&AB$10,薪酬明细!$A:$A,AB$6) -> 14 | AC29: =SUMIFS(薪酬明细!$K:$K,薪酬明细!$D:$D,$E29,薪酬明细!$E:$E,$F29,薪酬明细!$H:$H,">="&AC$9,薪酬明细!$H:$H,"<="&AC$10,薪酬明细!$A:$A,AC$6) -> 14 | ... AG29: =SUMIFS(薪酬明细!$K:$K,薪酬明细!$D:$D,$E29,薪酬明细!$E:$E,$F29,薪酬明细!$H:$H,">="&AG$9,薪酬明细!$H:$H,"<="&AG$10,薪酬明细!$A:$A,AG$6) -> 0 | AH29: =SUMIFS(薪酬明细!$K:$K,薪酬明细!$D:$D,$E29,薪酬明细!$E:$E,$F29,薪酬明细!$H:$H,">="&AH$9,薪酬明细!$H:$H,"<="&AH$10,薪酬明细!$A:$A,AH$6)/(12-MONTH($G$3)) -> 14 | AI29: =SUMIFS(薪酬明细!$K:$K,薪酬明细!$D:$D,$E29,薪酬明细!$E:$E,$F29,薪酬明细!$H:$H,">="&AI$9,薪酬明细!$H:$H,"<="&AI$10,薪酬明细!$A:$A,AI$6) -> 0 | AJ29: =SUMIFS(薪酬明细!$K:$K,薪酬明细!$D:$D,$E29,薪酬明细!$E:$E,$F29,薪酬明细!$H:$H,">="&AJ$9,薪酬明细!$H:$H,"<="&AJ$10,薪酬明细!$A:$A,AJ$6) -> 0 | AK29: =SUMIFS(薪酬明细!$K:$K,薪酬明细!$D:$D,$E29,薪酬明细!$E:$E,$F29,薪酬明细!$H:$H,">="&AK$9,薪酬明细!$H:$H,"<="&AK$10,薪酬明细!$A:$A,AK$6) -> 0 | AL29: =SUMIFS(薪酬明细!$K:$K,薪酬明细!$D:$D,$E29,薪酬明细!$E:$E,$F29,薪酬明细!$H:$H,">="&AL$9,薪酬明细!$H:$H,"<="&AL$10,薪酬明细!$A:$A,AL$6) -> 0 | AM29: =SUMIFS(薪酬明细!$K:$K,薪酬明细!$D:$D,$E29,薪酬明细!$E:$E,$F29,薪酬明细!$H:$H,">="&AM$9,薪酬明细!$H:$H,"<="&AM$10,薪酬明细!$A:$A,AM$6) -> 0 | AN29: =SUMIFS(薪酬明细!$K:$K,薪酬明细!$D:$D,$E29,薪酬明细!$E:$E,$F29,薪酬明细!$H:$H,">="&AN$9,薪酬明细!$H:$H,"<="&AN$10,薪酬明细!$A:$A,AN$6) -> 0 | AO29: =SUMIFS(薪酬明细!$K:$K,薪酬明细!$D:$D,$E29,薪酬明细!$E:$E,$F29,薪酬明细!$H:$H,">="&AO$9,薪酬明细!$H:$H,"<="&AO$10,薪酬明细!$A:$A,AO$6) -> 0 | AP29: =SUMIFS(薪酬明细!$K:$K,薪酬明细!$D:$D,$E29,薪酬明细!$E:$E,$F29,薪酬明细!$H:$H,">="&AP$9,薪酬明细!$H:$H,"<="&AP$10,薪酬明细!$A:$A,AP$6) -> 0 | ... AT29: =SUMIFS(薪酬明细!$K:$K,薪酬明细!$D:$D,$E29,薪酬明细!$E:$E,$F29,薪酬明细!$H:$H,">="&AT$9,薪酬明细!$H:$H,"<="&AT$10,薪酬明细!$A:$A,AT$6) -> 14 | AU29: =SUMIFS(薪酬明细!$K:$K,薪酬明细!$D:$D,$E29,薪酬明细!$E:$E,$F29,薪酬明细!$H:$H,">="&AU$9,薪酬明细!$H:$H,"<="&AU$10,薪酬明细!$A:$A,AU$6)/12 -> 14 | AV29: =SUMIFS(薪酬明细!$K:$K,薪酬明细!$D:$D,$E29,薪酬明细!$E:$E,$F29,薪酬明细!$H:$H,">="&AV$9,薪酬明细!$H:$H,"<="&AV$10,薪酬明细!$A:$A,AV$6) -> 14 | AW29: =SUMIFS(薪酬明细!$K:$K,薪酬明细!$D:$D,$E29,薪酬明细!$E:$E,$F29,薪酬明细!$H:$H,">="&AW$9,薪酬明细!$H:$H,"<="&AW$10,薪酬明细!$A:$A,AW$6) -> 14 | AX29: =SUMIFS(薪酬明细!$K:$K,薪酬明细!$D:$D,$E29,薪酬明细!$E:$E,$F29,薪酬明细!$H:$H,">="&AX$9,薪酬明细!$H:$H,"<="&AX$10,薪酬明细!$A:$A,AX$6) -> 14 | AY29: =SUMIFS(薪酬明细!$K:$K,薪酬明细!$D:$D,$E29,薪酬明细!$E:$E,$F29,薪酬明细!$H:$H,">="&AY$9,薪酬明细!$H:$H,"<="&AY$10,薪酬明细!$A:$A,AY$6) -> 14 | AZ29: =SUMIFS(薪酬明细!$K:$K,薪酬明细!$D:$D,$E29,薪酬明细!$E:$E,$F29,薪酬明细!$H:$H,">="&AZ$9,薪酬明细!$H:$H,"<="&AZ$10,薪酬明细!$A:$A,AZ$6) -> 14 | BA29: =SUMIFS(薪酬明细!$K:$K,薪酬明细!$D:$D,$E29,薪酬明细!$E:$E,$F29,薪酬明细!$H:$H,">="&BA$9,薪酬明细!$H:$H,"<="&BA$10,薪酬明细!$A:$A,BA$6) -> 14 | BB29: =SUMIFS(薪酬明细!$K:$K,薪酬明细!$D:$D,$E29,薪酬明细!$E:$E,$F29,薪酬明细!$H:$H,">="&BB$9,薪酬明细!$H:$H,"<="&BB$10,薪酬明细!$A:$A,BB$6) -> 14 | BC29: =SUMIFS(薪酬明细!$K:$K,薪酬明细!$D:$D,$E29,薪酬明细!$E:$E,$F29,薪酬明细!$H:$H,">="&BC$9,薪酬明细!$H:$H,"<="&BC$10,薪酬明细!$A:$A,BC$6) -> 14 | ... BG29: =SUMIFS(薪酬明细!$K:$K,薪酬明细!$D:$D,$E29,薪酬明细!$E:$E,$F29,薪酬明细!$H:$H,">="&BG$9,薪酬明细!$H:$H,"<="&BG$10,薪酬明细!$A:$A,BG$6) -> 14
D30: 制造中心 | E30: =IF(C30<>"",C30,E29) -> 流程中心 | F30: =IF(D30<>"",D30,"*") -> 制造中心 | G30: =SUMIFS(薪酬明细!$K:$K,薪酬明细!$D:$D,$E30,薪酬明细!$E:$E,$F30,薪酬明细!$H:$H,">="&G$9,薪酬明细!$H:$H,"<="&G$10,薪酬明细!$A:$A,G$6)/12 -> 22 | H30: =SUMIFS(薪酬明细!$K:$K,薪酬明细!$D:$D,$E30,薪酬明细!$E:$E,$F30,薪酬明细!$H:$H,">="&H$9,薪酬明细!$H:$H,"<="&H$10,薪酬明细!$A:$A,H$6) -> 22 | I30: =SUMIFS(薪酬明细!$K:$K,薪酬明细!$D:$D,$E30,薪酬明细!$E:$E,$F30,薪酬明细!$H:$H,">="&I$9,薪酬明细!$H:$H,"<="&I$10,薪酬明细!$A:$A,I$6) -> 22 | J30: =SUMIFS(薪酬明细!$K:$K,薪酬明细!$D:$D,$E30,薪酬明细!$E:$E,$F30,薪酬明细!$H:$H,">="&J$9,薪酬明细!$H:$H,"<="&J$10,薪酬明细!$A:$A,J$6) -> 22 | K30: =SUMIFS(薪酬明细!$K:$K,薪酬明细!$D:$D,$E30,薪酬明细!$E:$E,$F30,薪酬明细!$H:$H,">="&K$9,薪酬明细!$H:$H,"<="&K$10,薪酬明细!$A:$A,K$6) -> 22 | L30: =SUMIFS(薪酬明细!$K:$K,薪酬明细!$D:$D,$E30,薪酬明细!$E:$E,$F30,薪酬明细!$H:$H,">="&L$9,薪酬明细!$H:$H,"<="&L$10,薪酬明细!$A:$A,L$6) -> 22 | M30: =SUMIFS(薪酬明细!$K:$K,薪酬明细!$D:$D,$E30,薪酬明细!$E:$E,$F30,薪酬明细!$H:$H,">="&M$9,薪酬明细!$H:$H,"<="&M$10,薪酬明细!$A:$A,M$6) -> 22 | N30: =SUMIFS(薪酬明细!$K:$K,薪酬明细!$D:$D,$E30,薪酬明细!$E:$E,$F30,薪酬明细!$H:$H,">="&N$9,薪酬明细!$H:$H,"<="&N$10,薪酬明细!$A:$A,N$6) -> 22 | O30: =SUMIFS(薪酬明细!$K:$K,薪酬明细!$D:$D,$E30,薪酬明细!$E:$E,$F30,薪酬明细!$H:$H,">="&O$9,薪酬明细!$H:$H,"<="&O$10,薪酬明细!$A:$A,O$6) -> 22 | ... S30: =SUMIFS(薪酬明细!$K:$K,薪酬明细!$D:$D,$E30,薪酬明细!$E:$E,$F30,薪酬明细!$H:$H,">="&S$9,薪酬明细!$H:$H,"<="&S$10,薪酬明细!$A:$A,S$6) -> 22 | T30: =(U30*MONTH($G$3)+AH30*(12-MONTH($G$3)))/12 -> 22 | U30: =SUMIFS(薪酬明细!$K:$K,薪酬明细!$D:$D,$E30,薪酬明细!$E:$E,$F30,薪酬明细!$H:$H,">="&U$9,薪酬明细!$H:$H,"<="&U$10,薪酬明细!$A:$A,U$6)/MONTH($G$3) -> 22 | V30: =SUMIFS(薪酬明细!$K:$K,薪酬明细!$D:$D,$E30,薪酬明细!$E:$E,$F30,薪酬明细!$H:$H,">="&V$9,薪酬明细!$H:$H,"<="&V$10,薪酬明细!$A:$A,V$6) -> 22 | W30: =SUMIFS(薪酬明细!$K:$K,薪酬明细!$D:$D,$E30,薪酬明细!$E:$E,$F30,薪酬明细!$H:$H,">="&W$9,薪酬明细!$H:$H,"<="&W$10,薪酬明细!$A:$A,W$6) -> 22 | X30: =SUMIFS(薪酬明细!$K:$K,薪酬明细!$D:$D,$E30,薪酬明细!$E:$E,$F30,薪酬明细!$H:$H,">="&X$9,薪酬明细!$H:$H,"<="&X$10,薪酬明细!$A:$A,X$6) -> 22 | Y30: =SUMIFS(薪酬明细!$K:$K,薪酬明细!$D:$D,$E30,薪酬明细!$E:$E,$F30,薪酬明细!$H:$H,">="&Y$9,薪酬明细!$H:$H,"<="&Y$10,薪酬明细!$A:$A,Y$6) -> 22 | Z30: =SUMIFS(薪酬明细!$K:$K,薪酬明细!$D:$D,$E30,薪酬明细!$E:$E,$F30,薪酬明细!$H:$H,">="&Z$9,薪酬明细!$H:$H,"<="&Z$10,薪酬明细!$A:$A,Z$6) -> 22 | AA30: =SUMIFS(薪酬明细!$K:$K,薪酬明细!$D:$D,$E30,薪酬明细!$E:$E,$F30,薪酬明细!$H:$H,">="&AA$9,薪酬明细!$H:$H,"<="&AA$10,薪酬明细!$A:$A,AA$6) -> 22 | AB30: =SUMIFS(薪酬明细!$K:$K,薪酬明细!$D:$D,$E30,薪酬明细!$E:$E,$F30,薪酬明细!$H:$H,">="&AB$9,薪酬明细!$H:$H,"<="&AB$10,薪酬明细!$A:$A,AB$6) -> 22 | AC30: =SUMIFS(薪酬明细!$K:$K,薪酬明细!$D:$D,$E30,薪酬明细!$E:$E,$F30,薪酬明细!$H:$H,">="&AC$9,薪酬明细!$H:$H,"<="&AC$10,薪酬明细!$A:$A,AC$6) -> 22 | ... AG30: =SUMIFS(薪酬明细!$K:$K,薪酬明细!$D:$D,$E30,薪酬明细!$E:$E,$F30,薪酬明细!$H:$H,">="&AG$9,薪酬明细!$H:$H,"<="&AG$10,薪酬明细!$A:$A,AG$6) -> 0 | AH30: =SUMIFS(薪酬明细!$K:$K,薪酬明细!$D:$D,$E30,薪酬明细!$E:$E,$F30,薪酬明细!$H:$H,">="&AH$9,薪酬明细!$H:$H,"<="&AH$10,薪酬明细!$A:$A,AH$6)/(12-MONTH($G$3)) -> 22 | AI30: =SUMIFS(薪酬明细!$K:$K,薪酬明细!$D:$D,$E30,薪酬明细!$E:$E,$F30,薪酬明细!$H:$H,">="&AI$9,薪酬明细!$H:$H,"<="&AI$10,薪酬明细!$A:$A,AI$6) -> 0 | AJ30: =SUMIFS(薪酬明细!$K:$K,薪酬明细!$D:$D,$E30,薪酬明细!$E:$E,$F30,薪酬明细!$H:$H,">="&AJ$9,薪酬明细!$H:$H,"<="&AJ$10,薪酬明细!$A:$A,AJ$6) -> 0 | AK30: =SUMIFS(薪酬明细!$K:$K,薪酬明细!$D:$D,$E30,薪酬明细!$E:$E,$F30,薪酬明细!$H:$H,">="&AK$9,薪酬明细!$H:$H,"<="&AK$10,薪酬明细!$A:$A,AK$6) -> 0 | AL30: =SUMIFS(薪酬明细!$K:$K,薪酬明细!$D:$D,$E30,薪酬明细!$E:$E,$F30,薪酬明细!$H:$H,">="&AL$9,薪酬明细!$H:$H,"<="&AL$10,薪酬明细!$A:$A,AL$6) -> 0 | AM30: =SUMIFS(薪酬明细!$K:$K,薪酬明细!$D:$D,$E30,薪酬明细!$E:$E,$F30,薪酬明细!$H:$H,">="&AM$9,薪酬明细!$H:$H,"<="&AM$10,薪酬明细!$A:$A,AM$6) -> 0 | AN30: =SUMIFS(薪酬明细!$K:$K,薪酬明细!$D:$D,$E30,薪酬明细!$E:$E,$F30,薪酬明细!$H:$H,">="&AN$9,薪酬明细!$H:$H,"<="&AN$10,薪酬明细!$A:$A,AN$6) -> 0 | AO30: =SUMIFS(薪酬明细!$K:$K,薪酬明细!$D:$D,$E30,薪酬明细!$E:$E,$F30,薪酬明细!$H:$H,">="&AO$9,薪酬明细!$H:$H,"<="&AO$10,薪酬明细!$A:$A,AO$6) -> 0 | AP30: =SUMIFS(薪酬明细!$K:$K,薪酬明细!$D:$D,$E30,薪酬明细!$E:$E,$F30,薪酬明细!$H:$H,">="&AP$9,薪酬明细!$H:$H,"<="&AP$10,薪酬明细!$A:$A,AP$6) -> 0 | ... AT30: =SUMIFS(薪酬明细!$K:$K,薪酬明细!$D:$D,$E30,薪酬明细!$E:$E,$F30,薪酬明细!$H:$H,">="&AT$9,薪酬明细!$H:$H,"<="&AT$10,薪酬明细!$A:$A,AT$6) -> 22 | AU30: =SUMIFS(薪酬明细!$K:$K,薪酬明细!$D:$D,$E30,薪酬明细!$E:$E,$F30,薪酬明细!$H:$H,">="&AU$9,薪酬明细!$H:$H,"<="&AU$10,薪酬明细!$A:$A,AU$6)/12 -> 22 | AV30: =SUMIFS(薪酬明细!$K:$K,薪酬明细!$D:$D,$E30,薪酬明细!$E:$E,$F30,薪酬明细!$H:$H,">="&AV$9,薪酬明细!$H:$H,"<="&AV$10,薪酬明细!$A:$A,AV$6) -> 22 | AW30: =SUMIFS(薪酬明细!$K:$K,薪酬明细!$D:$D,$E30,薪酬明细!$E:$E,$F30,薪酬明细!$H:$H,">="&AW$9,薪酬明细!$H:$H,"<="&AW$10,薪酬明细!$A:$A,AW$6) -> 22 | AX30: =SUMIFS(薪酬明细!$K:$K,薪酬明细!$D:$D,$E30,薪酬明细!$E:$E,$F30,薪酬明细!$H:$H,">="&AX$9,薪酬明细!$H:$H,"<="&AX$10,薪酬明细!$A:$A,AX$6) -> 22 | AY30: =SUMIFS(薪酬明细!$K:$K,薪酬明细!$D:$D,$E30,薪酬明细!$E:$E,$F30,薪酬明细!$H:$H,">="&AY$9,薪酬明细!$H:$H,"<="&AY$10,薪酬明细!$A:$A,AY$6) -> 22 | AZ30: =SUMIFS(薪酬明细!$K:$K,薪酬明细!$D:$D,$E30,薪酬明细!$E:$E,$F30,薪酬明细!$H:$H,">="&AZ$9,薪酬明细!$H:$H,"<="&AZ$10,薪酬明细!$A:$A,AZ$6) -> 22 | BA30: =SUMIFS(薪酬明细!$K:$K,薪酬明细!$D:$D,$E30,薪酬明细!$E:$E,$F30,薪酬明细!$H:$H,">="&BA$9,薪酬明细!$H:$H,"<="&BA$10,薪酬明细!$A:$A,BA$6) -> 22 | BB30: =SUMIFS(薪酬明细!$K:$K,薪酬明细!$D:$D,$E30,薪酬明细!$E:$E,$F30,薪酬明细!$H:$H,">="&BB$9,薪酬明细!$H:$H,"<="&BB$10,薪酬明细!$A:$A,BB$6) -> 22 | BC30: =SUMIFS(薪酬明细!$K:$K,薪酬明细!$D:$D,$E30,薪酬明细!$E:$E,$F30,薪酬明细!$H:$H,">="&BC$9,薪酬明细!$H:$H,"<="&BC$10,薪酬明细!$A:$A,BC$6) -> 22 | ... BG30: =SUMIFS(薪酬明细!$K:$K,薪酬明细!$D:$D,$E30,薪酬明细!$E:$E,$F30,薪酬明细!$H:$H,">="&BG$9,薪酬明细!$H:$H,"<="&BG$10,薪酬明细!$A:$A,BG$6) -> 22
C31: 创新中心 | E31: =IF(C31<>"",C31,E30) -> 创新中心 | F31: =IF(D31<>"",D31,"*") -> * | G31: =SUMIFS(薪酬明细!$K:$K,薪酬明细!$D:$D,$E31,薪酬明细!$E:$E,$F31,薪酬明细!$H:$H,">="&G$9,薪酬明细!$H:$H,"<="&G$10,薪酬明细!$A:$A,G$6)/12 -> 20 | H31: =SUMIFS(薪酬明细!$K:$K,薪酬明细!$D:$D,$E31,薪酬明细!$E:$E,$F31,薪酬明细!$H:$H,">="&H$9,薪酬明细!$H:$H,"<="&H$10,薪酬明细!$A:$A,H$6) -> 20 | I31: =SUMIFS(薪酬明细!$K:$K,薪酬明细!$D:$D,$E31,薪酬明细!$E:$E,$F31,薪酬明细!$H:$H,">="&I$9,薪酬明细!$H:$H,"<="&I$10,薪酬明细!$A:$A,I$6) -> 20 | J31: =SUMIFS(薪酬明细!$K:$K,薪酬明细!$D:$D,$E31,薪酬明细!$E:$E,$F31,薪酬明细!$H:$H,">="&J$9,薪酬明细!$H:$H,"<="&J$10,薪酬明细!$A:$A,J$6) -> 20 | K31: =SUMIFS(薪酬明细!$K:$K,薪酬明细!$D:$D,$E31,薪酬明细!$E:$E,$F31,薪酬明细!$H:$H,">="&K$9,薪酬明细!$H:$H,"<="&K$10,薪酬明细!$A:$A,K$6) -> 20 | L31: =SUMIFS(薪酬明细!$K:$K,薪酬明细!$D:$D,$E31,薪酬明细!$E:$E,$F31,薪酬明细!$H:$H,">="&L$9,薪酬明细!$H:$H,"<="&L$10,薪酬明细!$A:$A,L$6) -> 20 | M31: =SUMIFS(薪酬明细!$K:$K,薪酬明细!$D:$D,$E31,薪酬明细!$E:$E,$F31,薪酬明细!$H:$H,">="&M$9,薪酬明细!$H:$H,"<="&M$10,薪酬明细!$A:$A,M$6) -> 20 | N31: =SUMIFS(薪酬明细!$K:$K,薪酬明细!$D:$D,$E31,薪酬明细!$E:$E,$F31,薪酬明细!$H:$H,">="&N$9,薪酬明细!$H:$H,"<="&N$10,薪酬明细!$A:$A,N$6) -> 20 | O31: =SUMIFS(薪酬明细!$K:$K,薪酬明细!$D:$D,$E31,薪酬明细!$E:$E,$F31,薪酬明细!$H:$H,">="&O$9,薪酬明细!$H:$H,"<="&O$10,薪酬明细!$A:$A,O$6) -> 20 | ... S31: =SUMIFS(薪酬明细!$K:$K,薪酬明细!$D:$D,$E31,薪酬明细!$E:$E,$F31,薪酬明细!$H:$H,">="&S$9,薪酬明细!$H:$H,"<="&S$10,薪酬明细!$A:$A,S$6) -> 20 | T31: =(U31*MONTH($G$3)+AH31*(12-MONTH($G$3)))/12 -> 20 | U31: =SUMIFS(薪酬明细!$K:$K,薪酬明细!$D:$D,$E31,薪酬明细!$E:$E,$F31,薪酬明细!$H:$H,">="&U$9,薪酬明细!$H:$H,"<="&U$10,薪酬明细!$A:$A,U$6)/MONTH($G$3) -> 20 | V31: =SUMIFS(薪酬明细!$K:$K,薪酬明细!$D:$D,$E31,薪酬明细!$E:$E,$F31,薪酬明细!$H:$H,">="&V$9,薪酬明细!$H:$H,"<="&V$10,薪酬明细!$A:$A,V$6) -> 20 | W31: =SUMIFS(薪酬明细!$K:$K,薪酬明细!$D:$D,$E31,薪酬明细!$E:$E,$F31,薪酬明细!$H:$H,">="&W$9,薪酬明细!$H:$H,"<="&W$10,薪酬明细!$A:$A,W$6) -> 20 | X31: =SUMIFS(薪酬明细!$K:$K,薪酬明细!$D:$D,$E31,薪酬明细!$E:$E,$F31,薪酬明细!$H:$H,">="&X$9,薪酬明细!$H:$H,"<="&X$10,薪酬明细!$A:$A,X$6) -> 20 | Y31: =SUMIFS(薪酬明细!$K:$K,薪酬明细!$D:$D,$E31,薪酬明细!$E:$E,$F31,薪酬明细!$H:$H,">="&Y$9,薪酬明细!$H:$H,"<="&Y$10,薪酬明细!$A:$A,Y$6) -> 20 | Z31: =SUMIFS(薪酬明细!$K:$K,薪酬明细!$D:$D,$E31,薪酬明细!$E:$E,$F31,薪酬明细!$H:$H,">="&Z$9,薪酬明细!$H:$H,"<="&Z$10,薪酬明细!$A:$A,Z$6) -> 20 | AA31: =SUMIFS(薪酬明细!$K:$K,薪酬明细!$D:$D,$E31,薪酬明细!$E:$E,$F31,薪酬明细!$H:$H,">="&AA$9,薪酬明细!$H:$H,"<="&AA$10,薪酬明细!$A:$A,AA$6) -> 20 | AB31: =SUMIFS(薪酬明细!$K:$K,薪酬明细!$D:$D,$E31,薪酬明细!$E:$E,$F31,薪酬明细!$H:$H,">="&AB$9,薪酬明细!$H:$H,"<="&AB$10,薪酬明细!$A:$A,AB$6) -> 20 | AC31: =SUMIFS(薪酬明细!$K:$K,薪酬明细!$D:$D,$E31,薪酬明细!$E:$E,$F31,薪酬明细!$H:$H,">="&AC$9,薪酬明细!$H:$H,"<="&AC$10,薪酬明细!$A:$A,AC$6) -> 20 | ... AG31: =SUMIFS(薪酬明细!$K:$K,薪酬明细!$D:$D,$E31,薪酬明细!$E:$E,$F31,薪酬明细!$H:$H,">="&AG$9,薪酬明细!$H:$H,"<="&AG$10,薪酬明细!$A:$A,AG$6) -> 0 | AH31: =SUMIFS(薪酬明细!$K:$K,薪酬明细!$D:$D,$E31,薪酬明细!$E:$E,$F31,薪酬明细!$H:$H,">="&AH$9,薪酬明细!$H:$H,"<="&AH$10,薪酬明细!$A:$A,AH$6)/(12-MONTH($G$3)) -> 20 | AI31: =SUMIFS(薪酬明细!$K:$K,薪酬明细!$D:$D,$E31,薪酬明细!$E:$E,$F31,薪酬明细!$H:$H,">="&AI$9,薪酬明细!$H:$H,"<="&AI$10,薪酬明细!$A:$A,AI$6) -> 0 | AJ31: =SUMIFS(薪酬明细!$K:$K,薪酬明细!$D:$D,$E31,薪酬明细!$E:$E,$F31,薪酬明细!$H:$H,">="&AJ$9,薪酬明细!$H:$H,"<="&AJ$10,薪酬明细!$A:$A,AJ$6) -> 0 | AK31: =SUMIFS(薪酬明细!$K:$K,薪酬明细!$D:$D,$E31,薪酬明细!$E:$E,$F31,薪酬明细!$H:$H,">="&AK$9,薪酬明细!$H:$H,"<="&AK$10,薪酬明细!$A:$A,AK$6) -> 0 | AL31: =SUMIFS(薪酬明细!$K:$K,薪酬明细!$D:$D,$E31,薪酬明细!$E:$E,$F31,薪酬明细!$H:$H,">="&AL$9,薪酬明细!$H:$H,"<="&AL$10,薪酬明细!$A:$A,AL$6) -> 0 | AM31: =SUMIFS(薪酬明细!$K:$K,薪酬明细!$D:$D,$E31,薪酬明细!$E:$E,$F31,薪酬明细!$H:$H,">="&AM$9,薪酬明细!$H:$H,"<="&AM$10,薪酬明细!$A:$A,AM$6) -> 0 | AN31: =SUMIFS(薪酬明细!$K:$K,薪酬明细!$D:$D,$E31,薪酬明细!$E:$E,$F31,薪酬明细!$H:$H,">="&AN$9,薪酬明细!$H:$H,"<="&AN$10,薪酬明细!$A:$A,AN$6) -> 0 | AO31: =SUMIFS(薪酬明细!$K:$K,薪酬明细!$D:$D,$E31,薪酬明细!$E:$E,$F31,薪酬明细!$H:$H,">="&AO$9,薪酬明细!$H:$H,"<="&AO$10,薪酬明细!$A:$A,AO$6) -> 0 | AP31: =SUMIFS(薪酬明细!$K:$K,薪酬明细!$D:$D,$E31,薪酬明细!$E:$E,$F31,薪酬明细!$H:$H,">="&AP$9,薪酬明细!$H:$H,"<="&AP$10,薪酬明细!$A:$A,AP$6) -> 0 | ... AT31: =SUMIFS(薪酬明细!$K:$K,薪酬明细!$D:$D,$E31,薪酬明细!$E:$E,$F31,薪酬明细!$H:$H,">="&AT$9,薪酬明细!$H:$H,"<="&AT$10,薪酬明细!$A:$A,AT$6) -> 20 | AU31: =SUMIFS(薪酬明细!$K:$K,薪酬明细!$D:$D,$E31,薪酬明细!$E:$E,$F31,薪酬明细!$H:$H,">="&AU$9,薪酬明细!$H:$H,"<="&AU$10,薪酬明细!$A:$A,AU$6)/12 -> 20 | AV31: =SUMIFS(薪酬明细!$K:$K,薪酬明细!$D:$D,$E31,薪酬明细!$E:$E,$F31,薪酬明细!$H:$H,">="&AV$9,薪酬明细!$H:$H,"<="&AV$10,薪酬明细!$A:$A,AV$6) -> 20 | AW31: =SUMIFS(薪酬明细!$K:$K,薪酬明细!$D:$D,$E31,薪酬明细!$E:$E,$F31,薪酬明细!$H:$H,">="&AW$9,薪酬明细!$H:$H,"<="&AW$10,薪酬明细!$A:$A,AW$6) -> 20 | AX31: =SUMIFS(薪酬明细!$K:$K,薪酬明细!$D:$D,$E31,薪酬明细!$E:$E,$F31,薪酬明细!$H:$H,">="&AX$9,薪酬明细!$H:$H,"<="&AX$10,薪酬明细!$A:$A,AX$6) -> 20 | AY31: =SUMIFS(薪酬明细!$K:$K,薪酬明细!$D:$D,$E31,薪酬明细!$E:$E,$F31,薪酬明细!$H:$H,">="&AY$9,薪酬明细!$H:$H,"<="&AY$10,薪酬明细!$A:$A,AY$6) -> 20 | AZ31: =SUMIFS(薪酬明细!$K:$K,薪酬明细!$D:$D,$E31,薪酬明细!$E:$E,$F31,薪酬明细!$H:$H,">="&AZ$9,薪酬明细!$H:$H,"<="&AZ$10,薪酬明细!$A:$A,AZ$6) -> 20 | BA31: =SUMIFS(薪酬明细!$K:$K,薪酬明细!$D:$D,$E31,薪酬明细!$E:$E,$F31,薪酬明细!$H:$H,">="&BA$9,薪酬明细!$H:$H,"<="&BA$10,薪酬明细!$A:$A,BA$6) -> 20 | BB31: =SUMIFS(薪酬明细!$K:$K,薪酬明细!$D:$D,$E31,薪酬明细!$E:$E,$F31,薪酬明细!$H:$H,">="&BB$9,薪酬明细!$H:$H,"<="&BB$10,薪酬明细!$A:$A,BB$6) -> 20 | BC31: =SUMIFS(薪酬明细!$K:$K,薪酬明细!$D:$D,$E31,薪酬明细!$E:$E,$F31,薪酬明细!$H:$H,">="&BC$9,薪酬明细!$H:$H,"<="&BC$10,薪酬明细!$A:$A,BC$6) -> 20 | ... BG31: =SUMIFS(薪酬明细!$K:$K,薪酬明细!$D:$D,$E31,薪酬明细!$E:$E,$F31,薪酬明细!$H:$H,">="&BG$9,薪酬明细!$H:$H,"<="&BG$10,薪酬明细!$A:$A,BG$6) -> 20
D32: 产品 研发部 | E32: =IF(C32<>"",C32,E31) -> 创新中心 | F32: =IF(D32<>"",D32,"*") -> 产品 研发部 | G32: =SUMIFS(薪酬明细!$K:$K,薪酬明细!$D:$D,$E32,薪酬明细!$E:$E,$F32,薪酬明细!$H:$H,">="&G$9,薪酬明细!$H:$H,"<="&G$10,薪酬明细!$A:$A,G$6)/12 -> 8 | H32: =SUMIFS(薪酬明细!$K:$K,薪酬明细!$D:$D,$E32,薪酬明细!$E:$E,$F32,薪酬明细!$H:$H,">="&H$9,薪酬明细!$H:$H,"<="&H$10,薪酬明细!$A:$A,H$6) -> 8 | I32: =SUMIFS(薪酬明细!$K:$K,薪酬明细!$D:$D,$E32,薪酬明细!$E:$E,$F32,薪酬明细!$H:$H,">="&I$9,薪酬明细!$H:$H,"<="&I$10,薪酬明细!$A:$A,I$6) -> 8 | J32: =SUMIFS(薪酬明细!$K:$K,薪酬明细!$D:$D,$E32,薪酬明细!$E:$E,$F32,薪酬明细!$H:$H,">="&J$9,薪酬明细!$H:$H,"<="&J$10,薪酬明细!$A:$A,J$6) -> 8 | K32: =SUMIFS(薪酬明细!$K:$K,薪酬明细!$D:$D,$E32,薪酬明细!$E:$E,$F32,薪酬明细!$H:$H,">="&K$9,薪酬明细!$H:$H,"<="&K$10,薪酬明细!$A:$A,K$6) -> 8 | L32: =SUMIFS(薪酬明细!$K:$K,薪酬明细!$D:$D,$E32,薪酬明细!$E:$E,$F32,薪酬明细!$H:$H,">="&L$9,薪酬明细!$H:$H,"<="&L$10,薪酬明细!$A:$A,L$6) -> 8 | M32: =SUMIFS(薪酬明细!$K:$K,薪酬明细!$D:$D,$E32,薪酬明细!$E:$E,$F32,薪酬明细!$H:$H,">="&M$9,薪酬明细!$H:$H,"<="&M$10,薪酬明细!$A:$A,M$6) -> 8 | N32: =SUMIFS(薪酬明细!$K:$K,薪酬明细!$D:$D,$E32,薪酬明细!$E:$E,$F32,薪酬明细!$H:$H,">="&N$9,薪酬明细!$H:$H,"<="&N$10,薪酬明细!$A:$A,N$6) -> 8 | O32: =SUMIFS(薪酬明细!$K:$K,薪酬明细!$D:$D,$E32,薪酬明细!$E:$E,$F32,薪酬明细!$H:$H,">="&O$9,薪酬明细!$H:$H,"<="&O$10,薪酬明细!$A:$A,O$6) -> 8 | ... S32: =SUMIFS(薪酬明细!$K:$K,薪酬明细!$D:$D,$E32,薪酬明细!$E:$E,$F32,薪酬明细!$H:$H,">="&S$9,薪酬明细!$H:$H,"<="&S$10,薪酬明细!$A:$A,S$6) -> 8 | T32: =(U32*MONTH($G$3)+AH32*(12-MONTH($G$3)))/12 -> 8 | U32: =SUMIFS(薪酬明细!$K:$K,薪酬明细!$D:$D,$E32,薪酬明细!$E:$E,$F32,薪酬明细!$H:$H,">="&U$9,薪酬明细!$H:$H,"<="&U$10,薪酬明细!$A:$A,U$6)/MONTH($G$3) -> 8 | V32: =SUMIFS(薪酬明细!$K:$K,薪酬明细!$D:$D,$E32,薪酬明细!$E:$E,$F32,薪酬明细!$H:$H,">="&V$9,薪酬明细!$H:$H,"<="&V$10,薪酬明细!$A:$A,V$6) -> 8 | W32: =SUMIFS(薪酬明细!$K:$K,薪酬明细!$D:$D,$E32,薪酬明细!$E:$E,$F32,薪酬明细!$H:$H,">="&W$9,薪酬明细!$H:$H,"<="&W$10,薪酬明细!$A:$A,W$6) -> 8 | X32: =SUMIFS(薪酬明细!$K:$K,薪酬明细!$D:$D,$E32,薪酬明细!$E:$E,$F32,薪酬明细!$H:$H,">="&X$9,薪酬明细!$H:$H,"<="&X$10,薪酬明细!$A:$A,X$6) -> 8 | Y32: =SUMIFS(薪酬明细!$K:$K,薪酬明细!$D:$D,$E32,薪酬明细!$E:$E,$F32,薪酬明细!$H:$H,">="&Y$9,薪酬明细!$H:$H,"<="&Y$10,薪酬明细!$A:$A,Y$6) -> 8 | Z32: =SUMIFS(薪酬明细!$K:$K,薪酬明细!$D:$D,$E32,薪酬明细!$E:$E,$F32,薪酬明细!$H:$H,">="&Z$9,薪酬明细!$H:$H,"<="&Z$10,薪酬明细!$A:$A,Z$6) -> 8 | AA32: =SUMIFS(薪酬明细!$K:$K,薪酬明细!$D:$D,$E32,薪酬明细!$E:$E,$F32,薪酬明细!$H:$H,">="&AA$9,薪酬明细!$H:$H,"<="&AA$10,薪酬明细!$A:$A,AA$6) -> 8 | AB32: =SUMIFS(薪酬明细!$K:$K,薪酬明细!$D:$D,$E32,薪酬明细!$E:$E,$F32,薪酬明细!$H:$H,">="&AB$9,薪酬明细!$H:$H,"<="&AB$10,薪酬明细!$A:$A,AB$6) -> 8 | AC32: =SUMIFS(薪酬明细!$K:$K,薪酬明细!$D:$D,$E32,薪酬明细!$E:$E,$F32,薪酬明细!$H:$H,">="&AC$9,薪酬明细!$H:$H,"<="&AC$10,薪酬明细!$A:$A,AC$6) -> 8 | ... AG32: =SUMIFS(薪酬明细!$K:$K,薪酬明细!$D:$D,$E32,薪酬明细!$E:$E,$F32,薪酬明细!$H:$H,">="&AG$9,薪酬明细!$H:$H,"<="&AG$10,薪酬明细!$A:$A,AG$6) -> 0 | AH32: =SUMIFS(薪酬明细!$K:$K,薪酬明细!$D:$D,$E32,薪酬明细!$E:$E,$F32,薪酬明细!$H:$H,">="&AH$9,薪酬明细!$H:$H,"<="&AH$10,薪酬明细!$A:$A,AH$6)/(12-MONTH($G$3)) -> 8 | AI32: =SUMIFS(薪酬明细!$K:$K,薪酬明细!$D:$D,$E32,薪酬明细!$E:$E,$F32,薪酬明细!$H:$H,">="&AI$9,薪酬明细!$H:$H,"<="&AI$10,薪酬明细!$A:$A,AI$6) -> 0 | AJ32: =SUMIFS(薪酬明细!$K:$K,薪酬明细!$D:$D,$E32,薪酬明细!$E:$E,$F32,薪酬明细!$H:$H,">="&AJ$9,薪酬明细!$H:$H,"<="&AJ$10,薪酬明细!$A:$A,AJ$6) -> 0 | AK32: =SUMIFS(薪酬明细!$K:$K,薪酬明细!$D:$D,$E32,薪酬明细!$E:$E,$F32,薪酬明细!$H:$H,">="&AK$9,薪酬明细!$H:$H,"<="&AK$10,薪酬明细!$A:$A,AK$6) -> 0 | AL32: =SUMIFS(薪酬明细!$K:$K,薪酬明细!$D:$D,$E32,薪酬明细!$E:$E,$F32,薪酬明细!$H:$H,">="&AL$9,薪酬明细!$H:$H,"<="&AL$10,薪酬明细!$A:$A,AL$6) -> 0 | AM32: =SUMIFS(薪酬明细!$K:$K,薪酬明细!$D:$D,$E32,薪酬明细!$E:$E,$F32,薪酬明细!$H:$H,">="&AM$9,薪酬明细!$H:$H,"<="&AM$10,薪酬明细!$A:$A,AM$6) -> 0 | AN32: =SUMIFS(薪酬明细!$K:$K,薪酬明细!$D:$D,$E32,薪酬明细!$E:$E,$F32,薪酬明细!$H:$H,">="&AN$9,薪酬明细!$H:$H,"<="&AN$10,薪酬明细!$A:$A,AN$6) -> 0 | AO32: =SUMIFS(薪酬明细!$K:$K,薪酬明细!$D:$D,$E32,薪酬明细!$E:$E,$F32,薪酬明细!$H:$H,">="&AO$9,薪酬明细!$H:$H,"<="&AO$10,薪酬明细!$A:$A,AO$6) -> 0 | AP32: =SUMIFS(薪酬明细!$K:$K,薪酬明细!$D:$D,$E32,薪酬明细!$E:$E,$F32,薪酬明细!$H:$H,">="&AP$9,薪酬明细!$H:$H,"<="&AP$10,薪酬明细!$A:$A,AP$6) -> 0 | ... AT32: =SUMIFS(薪酬明细!$K:$K,薪酬明细!$D:$D,$E32,薪酬明细!$E:$E,$F32,薪酬明细!$H:$H,">="&AT$9,薪酬明细!$H:$H,"<="&AT$10,薪酬明细!$A:$A,AT$6) -> 8 | AU32: =SUMIFS(薪酬明细!$K:$K,薪酬明细!$D:$D,$E32,薪酬明细!$E:$E,$F32,薪酬明细!$H:$H,">="&AU$9,薪酬明细!$H:$H,"<="&AU$10,薪酬明细!$A:$A,AU$6)/12 -> 8 | AV32: =SUMIFS(薪酬明细!$K:$K,薪酬明细!$D:$D,$E32,薪酬明细!$E:$E,$F32,薪酬明细!$H:$H,">="&AV$9,薪酬明细!$H:$H,"<="&AV$10,薪酬明细!$A:$A,AV$6) -> 8 | AW32: =SUMIFS(薪酬明细!$K:$K,薪酬明细!$D:$D,$E32,薪酬明细!$E:$E,$F32,薪酬明细!$H:$H,">="&AW$9,薪酬明细!$H:$H,"<="&AW$10,薪酬明细!$A:$A,AW$6) -> 8 | AX32: =SUMIFS(薪酬明细!$K:$K,薪酬明细!$D:$D,$E32,薪酬明细!$E:$E,$F32,薪酬明细!$H:$H,">="&AX$9,薪酬明细!$H:$H,"<="&AX$10,薪酬明细!$A:$A,AX$6) -> 8 | AY32: =SUMIFS(薪酬明细!$K:$K,薪酬明细!$D:$D,$E32,薪酬明细!$E:$E,$F32,薪酬明细!$H:$H,">="&AY$9,薪酬明细!$H:$H,"<="&AY$10,薪酬明细!$A:$A,AY$6) -> 8 | AZ32: =SUMIFS(薪酬明细!$K:$K,薪酬明细!$D:$D,$E32,薪酬明细!$E:$E,$F32,薪酬明细!$H:$H,">="&AZ$9,薪酬明细!$H:$H,"<="&AZ$10,薪酬明细!$A:$A,AZ$6) -> 8 | BA32: =SUMIFS(薪酬明细!$K:$K,薪酬明细!$D:$D,$E32,薪酬明细!$E:$E,$F32,薪酬明细!$H:$H,">="&BA$9,薪酬明细!$H:$H,"<="&BA$10,薪酬明细!$A:$A,BA$6) -> 8 | BB32: =SUMIFS(薪酬明细!$K:$K,薪酬明细!$D:$D,$E32,薪酬明细!$E:$E,$F32,薪酬明细!$H:$H,">="&BB$9,薪酬明细!$H:$H,"<="&BB$10,薪酬明细!$A:$A,BB$6) -> 8 | BC32: =SUMIFS(薪酬明细!$K:$K,薪酬明细!$D:$D,$E32,薪酬明细!$E:$E,$F32,薪酬明细!$H:$H,">="&BC$9,薪酬明细!$H:$H,"<="&BC$10,薪酬明细!$A:$A,BC$6) -> 8 | ... BG32: =SUMIFS(薪酬明细!$K:$K,薪酬明细!$D:$D,$E32,薪酬明细!$E:$E,$F32,薪酬明细!$H:$H,">="&BG$9,薪酬明细!$H:$H,"<="&BG$10,薪酬明细!$A:$A,BG$6) -> 8
D33: XX 试验室 | E33: =IF(C33<>"",C33,E32) -> 创新中心 | F33: =IF(D33<>"",D33,"*") -> XX 试验室 | G33: =SUMIFS(薪酬明细!$K:$K,薪酬明细!$D:$D,$E33,薪酬明细!$E:$E,$F33,薪酬明细!$H:$H,">="&G$9,薪酬明细!$H:$H,"<="&G$10,薪酬明细!$A:$A,G$6)/12 -> 5 | H33: =SUMIFS(薪酬明细!$K:$K,薪酬明细!$D:$D,$E33,薪酬明细!$E:$E,$F33,薪酬明细!$H:$H,">="&H$9,薪酬明细!$H:$H,"<="&H$10,薪酬明细!$A:$A,H$6) -> 5 | I33: =SUMIFS(薪酬明细!$K:$K,薪酬明细!$D:$D,$E33,薪酬明细!$E:$E,$F33,薪酬明细!$H:$H,">="&I$9,薪酬明细!$H:$H,"<="&I$10,薪酬明细!$A:$A,I$6) -> 5 | J33: =SUMIFS(薪酬明细!$K:$K,薪酬明细!$D:$D,$E33,薪酬明细!$E:$E,$F33,薪酬明细!$H:$H,">="&J$9,薪酬明细!$H:$H,"<="&J$10,薪酬明细!$A:$A,J$6) -> 5 | K33: =SUMIFS(薪酬明细!$K:$K,薪酬明细!$D:$D,$E33,薪酬明细!$E:$E,$F33,薪酬明细!$H:$H,">="&K$9,薪酬明细!$H:$H,"<="&K$10,薪酬明细!$A:$A,K$6) -> 5 | L33: =SUMIFS(薪酬明细!$K:$K,薪酬明细!$D:$D,$E33,薪酬明细!$E:$E,$F33,薪酬明细!$H:$H,">="&L$9,薪酬明细!$H:$H,"<="&L$10,薪酬明细!$A:$A,L$6) -> 5 | M33: =SUMIFS(薪酬明细!$K:$K,薪酬明细!$D:$D,$E33,薪酬明细!$E:$E,$F33,薪酬明细!$H:$H,">="&M$9,薪酬明细!$H:$H,"<="&M$10,薪酬明细!$A:$A,M$6) -> 5 | N33: =SUMIFS(薪酬明细!$K:$K,薪酬明细!$D:$D,$E33,薪酬明细!$E:$E,$F33,薪酬明细!$H:$H,">="&N$9,薪酬明细!$H:$H,"<="&N$10,薪酬明细!$A:$A,N$6) -> 5 | O33: =SUMIFS(薪酬明细!$K:$K,薪酬明细!$D:$D,$E33,薪酬明细!$E:$E,$F33,薪酬明细!$H:$H,">="&O$9,薪酬明细!$H:$H,"<="&O$10,薪酬明细!$A:$A,O$6) -> 5 | ... S33: =SUMIFS(薪酬明细!$K:$K,薪酬明细!$D:$D,$E33,薪酬明细!$E:$E,$F33,薪酬明细!$H:$H,">="&S$9,薪酬明细!$H:$H,"<="&S$10,薪酬明细!$A:$A,S$6) -> 5 | T33: =(U33*MONTH($G$3)+AH33*(12-MONTH($G$3)))/12 -> 5 | U33: =SUMIFS(薪酬明细!$K:$K,薪酬明细!$D:$D,$E33,薪酬明细!$E:$E,$F33,薪酬明细!$H:$H,">="&U$9,薪酬明细!$H:$H,"<="&U$10,薪酬明细!$A:$A,U$6)/MONTH($G$3) -> 5 | V33: =SUMIFS(薪酬明细!$K:$K,薪酬明细!$D:$D,$E33,薪酬明细!$E:$E,$F33,薪酬明细!$H:$H,">="&V$9,薪酬明细!$H:$H,"<="&V$10,薪酬明细!$A:$A,V$6) -> 5 | W33: =SUMIFS(薪酬明细!$K:$K,薪酬明细!$D:$D,$E33,薪酬明细!$E:$E,$F33,薪酬明细!$H:$H,">="&W$9,薪酬明细!$H:$H,"<="&W$10,薪酬明细!$A:$A,W$6) -> 5 | X33: =SUMIFS(薪酬明细!$K:$K,薪酬明细!$D:$D,$E33,薪酬明细!$E:$E,$F33,薪酬明细!$H:$H,">="&X$9,薪酬明细!$H:$H,"<="&X$10,薪酬明细!$A:$A,X$6) -> 5 | Y33: =SUMIFS(薪酬明细!$K:$K,薪酬明细!$D:$D,$E33,薪酬明细!$E:$E,$F33,薪酬明细!$H:$H,">="&Y$9,薪酬明细!$H:$H,"<="&Y$10,薪酬明细!$A:$A,Y$6) -> 5 | Z33: =SUMIFS(薪酬明细!$K:$K,薪酬明细!$D:$D,$E33,薪酬明细!$E:$E,$F33,薪酬明细!$H:$H,">="&Z$9,薪酬明细!$H:$H,"<="&Z$10,薪酬明细!$A:$A,Z$6) -> 5 | AA33: =SUMIFS(薪酬明细!$K:$K,薪酬明细!$D:$D,$E33,薪酬明细!$E:$E,$F33,薪酬明细!$H:$H,">="&AA$9,薪酬明细!$H:$H,"<="&AA$10,薪酬明细!$A:$A,AA$6) -> 5 | AB33: =SUMIFS(薪酬明细!$K:$K,薪酬明细!$D:$D,$E33,薪酬明细!$E:$E,$F33,薪酬明细!$H:$H,">="&AB$9,薪酬明细!$H:$H,"<="&AB$10,薪酬明细!$A:$A,AB$6) -> 5 | AC33: =SUMIFS(薪酬明细!$K:$K,薪酬明细!$D:$D,$E33,薪酬明细!$E:$E,$F33,薪酬明细!$H:$H,">="&AC$9,薪酬明细!$H:$H,"<="&AC$10,薪酬明细!$A:$A,AC$6) -> 5 | ... AG33: =SUMIFS(薪酬明细!$K:$K,薪酬明细!$D:$D,$E33,薪酬明细!$E:$E,$F33,薪酬明细!$H:$H,">="&AG$9,薪酬明细!$H:$H,"<="&AG$10,薪酬明细!$A:$A,AG$6) -> 0 | AH33: =SUMIFS(薪酬明细!$K:$K,薪酬明细!$D:$D,$E33,薪酬明细!$E:$E,$F33,薪酬明细!$H:$H,">="&AH$9,薪酬明细!$H:$H,"<="&AH$10,薪酬明细!$A:$A,AH$6)/(12-MONTH($G$3)) -> 5 | AI33: =SUMIFS(薪酬明细!$K:$K,薪酬明细!$D:$D,$E33,薪酬明细!$E:$E,$F33,薪酬明细!$H:$H,">="&AI$9,薪酬明细!$H:$H,"<="&AI$10,薪酬明细!$A:$A,AI$6) -> 0 | AJ33: =SUMIFS(薪酬明细!$K:$K,薪酬明细!$D:$D,$E33,薪酬明细!$E:$E,$F33,薪酬明细!$H:$H,">="&AJ$9,薪酬明细!$H:$H,"<="&AJ$10,薪酬明细!$A:$A,AJ$6) -> 0 | AK33: =SUMIFS(薪酬明细!$K:$K,薪酬明细!$D:$D,$E33,薪酬明细!$E:$E,$F33,薪酬明细!$H:$H,">="&AK$9,薪酬明细!$H:$H,"<="&AK$10,薪酬明细!$A:$A,AK$6) -> 0 | AL33: =SUMIFS(薪酬明细!$K:$K,薪酬明细!$D:$D,$E33,薪酬明细!$E:$E,$F33,薪酬明细!$H:$H,">="&AL$9,薪酬明细!$H:$H,"<="&AL$10,薪酬明细!$A:$A,AL$6) -> 0 | AM33: =SUMIFS(薪酬明细!$K:$K,薪酬明细!$D:$D,$E33,薪酬明细!$E:$E,$F33,薪酬明细!$H:$H,">="&AM$9,薪酬明细!$H:$H,"<="&AM$10,薪酬明细!$A:$A,AM$6) -> 0 | AN33: =SUMIFS(薪酬明细!$K:$K,薪酬明细!$D:$D,$E33,薪酬明细!$E:$E,$F33,薪酬明细!$H:$H,">="&AN$9,薪酬明细!$H:$H,"<="&AN$10,薪酬明细!$A:$A,AN$6) -> 0 | AO33: =SUMIFS(薪酬明细!$K:$K,薪酬明细!$D:$D,$E33,薪酬明细!$E:$E,$F33,薪酬明细!$H:$H,">="&AO$9,薪酬明细!$H:$H,"<="&AO$10,薪酬明细!$A:$A,AO$6) -> 0 | AP33: =SUMIFS(薪酬明细!$K:$K,薪酬明细!$D:$D,$E33,薪酬明细!$E:$E,$F33,薪酬明细!$H:$H,">="&AP$9,薪酬明细!$H:$H,"<="&AP$10,薪酬明细!$A:$A,AP$6) -> 0 | ... AT33: =SUMIFS(薪酬明细!$K:$K,薪酬明细!$D:$D,$E33,薪酬明细!$E:$E,$F33,薪酬明细!$H:$H,">="&AT$9,薪酬明细!$H:$H,"<="&AT$10,薪酬明细!$A:$A,AT$6) -> 5 | AU33: =SUMIFS(薪酬明细!$K:$K,薪酬明细!$D:$D,$E33,薪酬明细!$E:$E,$F33,薪酬明细!$H:$H,">="&AU$9,薪酬明细!$H:$H,"<="&AU$10,薪酬明细!$A:$A,AU$6)/12 -> 5 | AV33: =SUMIFS(薪酬明细!$K:$K,薪酬明细!$D:$D,$E33,薪酬明细!$E:$E,$F33,薪酬明细!$H:$H,">="&AV$9,薪酬明细!$H:$H,"<="&AV$10,薪酬明细!$A:$A,AV$6) -> 5 | AW33: =SUMIFS(薪酬明细!$K:$K,薪酬明细!$D:$D,$E33,薪酬明细!$E:$E,$F33,薪酬明细!$H:$H,">="&AW$9,薪酬明细!$H:$H,"<="&AW$10,薪酬明细!$A:$A,AW$6) -> 5 | AX33: =SUMIFS(薪酬明细!$K:$K,薪酬明细!$D:$D,$E33,薪酬明细!$E:$E,$F33,薪酬明细!$H:$H,">="&AX$9,薪酬明细!$H:$H,"<="&AX$10,薪酬明细!$A:$A,AX$6) -> 5 | AY33: =SUMIFS(薪酬明细!$K:$K,薪酬明细!$D:$D,$E33,薪酬明细!$E:$E,$F33,薪酬明细!$H:$H,">="&AY$9,薪酬明细!$H:$H,"<="&AY$10,薪酬明细!$A:$A,AY$6) -> 5 | AZ33: =SUMIFS(薪酬明细!$K:$K,薪酬明细!$D:$D,$E33,薪酬明细!$E:$E,$F33,薪酬明细!$H:$H,">="&AZ$9,薪酬明细!$H:$H,"<="&AZ$10,薪酬明细!$A:$A,AZ$6) -> 5 | BA33: =SUMIFS(薪酬明细!$K:$K,薪酬明细!$D:$D,$E33,薪酬明细!$E:$E,$F33,薪酬明细!$H:$H,">="&BA$9,薪酬明细!$H:$H,"<="&BA$10,薪酬明细!$A:$A,BA$6) -> 5 | BB33: =SUMIFS(薪酬明细!$K:$K,薪酬明细!$D:$D,$E33,薪酬明细!$E:$E,$F33,薪酬明细!$H:$H,">="&BB$9,薪酬明细!$H:$H,"<="&BB$10,薪酬明细!$A:$A,BB$6) -> 5 | BC33: =SUMIFS(薪酬明细!$K:$K,薪酬明细!$D:$D,$E33,薪酬明细!$E:$E,$F33,薪酬明细!$H:$H,">="&BC$9,薪酬明细!$H:$H,"<="&BC$10,薪酬明细!$A:$A,BC$6) -> 5 | ... BG33: =SUMIFS(薪酬明细!$K:$K,薪酬明细!$D:$D,$E33,薪酬明细!$E:$E,$F33,薪酬明细!$H:$H,">="&BG$9,薪酬明细!$H:$H,"<="&BG$10,薪酬明细!$A:$A,BG$6) -> 5
D34: XX 孵化业务 | E34: =IF(C34<>"",C34,E33) -> 创新中心 | F34: =IF(D34<>"",D34,"*") -> XX 孵化业务 | G34: =SUMIFS(薪酬明细!$K:$K,薪酬明细!$D:$D,$E34,薪酬明细!$E:$E,$F34,薪酬明细!$H:$H,">="&G$9,薪酬明细!$H:$H,"<="&G$10,薪酬明细!$A:$A,G$6)/12 -> 7 | H34: =SUMIFS(薪酬明细!$K:$K,薪酬明细!$D:$D,$E34,薪酬明细!$E:$E,$F34,薪酬明细!$H:$H,">="&H$9,薪酬明细!$H:$H,"<="&H$10,薪酬明细!$A:$A,H$6) -> 7 | I34: =SUMIFS(薪酬明细!$K:$K,薪酬明细!$D:$D,$E34,薪酬明细!$E:$E,$F34,薪酬明细!$H:$H,">="&I$9,薪酬明细!$H:$H,"<="&I$10,薪酬明细!$A:$A,I$6) -> 7 | J34: =SUMIFS(薪酬明细!$K:$K,薪酬明细!$D:$D,$E34,薪酬明细!$E:$E,$F34,薪酬明细!$H:$H,">="&J$9,薪酬明细!$H:$H,"<="&J$10,薪酬明细!$A:$A,J$6) -> 7 | K34: =SUMIFS(薪酬明细!$K:$K,薪酬明细!$D:$D,$E34,薪酬明细!$E:$E,$F34,薪酬明细!$H:$H,">="&K$9,薪酬明细!$H:$H,"<="&K$10,薪酬明细!$A:$A,K$6) -> 7 | L34: =SUMIFS(薪酬明细!$K:$K,薪酬明细!$D:$D,$E34,薪酬明细!$E:$E,$F34,薪酬明细!$H:$H,">="&L$9,薪酬明细!$H:$H,"<="&L$10,薪酬明细!$A:$A,L$6) -> 7 | M34: =SUMIFS(薪酬明细!$K:$K,薪酬明细!$D:$D,$E34,薪酬明细!$E:$E,$F34,薪酬明细!$H:$H,">="&M$9,薪酬明细!$H:$H,"<="&M$10,薪酬明细!$A:$A,M$6) -> 7 | N34: =SUMIFS(薪酬明细!$K:$K,薪酬明细!$D:$D,$E34,薪酬明细!$E:$E,$F34,薪酬明细!$H:$H,">="&N$9,薪酬明细!$H:$H,"<="&N$10,薪酬明细!$A:$A,N$6) -> 7 | O34: =SUMIFS(薪酬明细!$K:$K,薪酬明细!$D:$D,$E34,薪酬明细!$E:$E,$F34,薪酬明细!$H:$H,">="&O$9,薪酬明细!$H:$H,"<="&O$10,薪酬明细!$A:$A,O$6) -> 7 | ... S34: =SUMIFS(薪酬明细!$K:$K,薪酬明细!$D:$D,$E34,薪酬明细!$E:$E,$F34,薪酬明细!$H:$H,">="&S$9,薪酬明细!$H:$H,"<="&S$10,薪酬明细!$A:$A,S$6) -> 7 | T34: =(U34*MONTH($G$3)+AH34*(12-MONTH($G$3)))/12 -> 7 | U34: =SUMIFS(薪酬明细!$K:$K,薪酬明细!$D:$D,$E34,薪酬明细!$E:$E,$F34,薪酬明细!$H:$H,">="&U$9,薪酬明细!$H:$H,"<="&U$10,薪酬明细!$A:$A,U$6)/MONTH($G$3) -> 7 | V34: =SUMIFS(薪酬明细!$K:$K,薪酬明细!$D:$D,$E34,薪酬明细!$E:$E,$F34,薪酬明细!$H:$H,">="&V$9,薪酬明细!$H:$H,"<="&V$10,薪酬明细!$A:$A,V$6) -> 7 | W34: =SUMIFS(薪酬明细!$K:$K,薪酬明细!$D:$D,$E34,薪酬明细!$E:$E,$F34,薪酬明细!$H:$H,">="&W$9,薪酬明细!$H:$H,"<="&W$10,薪酬明细!$A:$A,W$6) -> 7 | X34: =SUMIFS(薪酬明细!$K:$K,薪酬明细!$D:$D,$E34,薪酬明细!$E:$E,$F34,薪酬明细!$H:$H,">="&X$9,薪酬明细!$H:$H,"<="&X$10,薪酬明细!$A:$A,X$6) -> 7 | Y34: =SUMIFS(薪酬明细!$K:$K,薪酬明细!$D:$D,$E34,薪酬明细!$E:$E,$F34,薪酬明细!$H:$H,">="&Y$9,薪酬明细!$H:$H,"<="&Y$10,薪酬明细!$A:$A,Y$6) -> 7 | Z34: =SUMIFS(薪酬明细!$K:$K,薪酬明细!$D:$D,$E34,薪酬明细!$E:$E,$F34,薪酬明细!$H:$H,">="&Z$9,薪酬明细!$H:$H,"<="&Z$10,薪酬明细!$A:$A,Z$6) -> 7 | AA34: =SUMIFS(薪酬明细!$K:$K,薪酬明细!$D:$D,$E34,薪酬明细!$E:$E,$F34,薪酬明细!$H:$H,">="&AA$9,薪酬明细!$H:$H,"<="&AA$10,薪酬明细!$A:$A,AA$6) -> 7 | AB34: =SUMIFS(薪酬明细!$K:$K,薪酬明细!$D:$D,$E34,薪酬明细!$E:$E,$F34,薪酬明细!$H:$H,">="&AB$9,薪酬明细!$H:$H,"<="&AB$10,薪酬明细!$A:$A,AB$6) -> 7 | AC34: =SUMIFS(薪酬明细!$K:$K,薪酬明细!$D:$D,$E34,薪酬明细!$E:$E,$F34,薪酬明细!$H:$H,">="&AC$9,薪酬明细!$H:$H,"<="&AC$10,薪酬明细!$A:$A,AC$6) -> 7 | ... AG34: =SUMIFS(薪酬明细!$K:$K,薪酬明细!$D:$D,$E34,薪酬明细!$E:$E,$F34,薪酬明细!$H:$H,">="&AG$9,薪酬明细!$H:$H,"<="&AG$10,薪酬明细!$A:$A,AG$6) -> 0 | AH34: =SUMIFS(薪酬明细!$K:$K,薪酬明细!$D:$D,$E34,薪酬明细!$E:$E,$F34,薪酬明细!$H:$H,">="&AH$9,薪酬明细!$H:$H,"<="&AH$10,薪酬明细!$A:$A,AH$6)/(12-MONTH($G$3)) -> 7 | AI34: =SUMIFS(薪酬明细!$K:$K,薪酬明细!$D:$D,$E34,薪酬明细!$E:$E,$F34,薪酬明细!$H:$H,">="&AI$9,薪酬明细!$H:$H,"<="&AI$10,薪酬明细!$A:$A,AI$6) -> 0 | AJ34: =SUMIFS(薪酬明细!$K:$K,薪酬明细!$D:$D,$E34,薪酬明细!$E:$E,$F34,薪酬明细!$H:$H,">="&AJ$9,薪酬明细!$H:$H,"<="&AJ$10,薪酬明细!$A:$A,AJ$6) -> 0 | AK34: =SUMIFS(薪酬明细!$K:$K,薪酬明细!$D:$D,$E34,薪酬明细!$E:$E,$F34,薪酬明细!$H:$H,">="&AK$9,薪酬明细!$H:$H,"<="&AK$10,薪酬明细!$A:$A,AK$6) -> 0 | AL34: =SUMIFS(薪酬明细!$K:$K,薪酬明细!$D:$D,$E34,薪酬明细!$E:$E,$F34,薪酬明细!$H:$H,">="&AL$9,薪酬明细!$H:$H,"<="&AL$10,薪酬明细!$A:$A,AL$6) -> 0 | AM34: =SUMIFS(薪酬明细!$K:$K,薪酬明细!$D:$D,$E34,薪酬明细!$E:$E,$F34,薪酬明细!$H:$H,">="&AM$9,薪酬明细!$H:$H,"<="&AM$10,薪酬明细!$A:$A,AM$6) -> 0 | AN34: =SUMIFS(薪酬明细!$K:$K,薪酬明细!$D:$D,$E34,薪酬明细!$E:$E,$F34,薪酬明细!$H:$H,">="&AN$9,薪酬明细!$H:$H,"<="&AN$10,薪酬明细!$A:$A,AN$6) -> 0 | AO34: =SUMIFS(薪酬明细!$K:$K,薪酬明细!$D:$D,$E34,薪酬明细!$E:$E,$F34,薪酬明细!$H:$H,">="&AO$9,薪酬明细!$H:$H,"<="&AO$10,薪酬明细!$A:$A,AO$6) -> 0 | AP34: =SUMIFS(薪酬明细!$K:$K,薪酬明细!$D:$D,$E34,薪酬明细!$E:$E,$F34,薪酬明细!$H:$H,">="&AP$9,薪酬明细!$H:$H,"<="&AP$10,薪酬明细!$A:$A,AP$6) -> 0 | ... AT34: =SUMIFS(薪酬明细!$K:$K,薪酬明细!$D:$D,$E34,薪酬明细!$E:$E,$F34,薪酬明细!$H:$H,">="&AT$9,薪酬明细!$H:$H,"<="&AT$10,薪酬明细!$A:$A,AT$6) -> 7 | AU34: =SUMIFS(薪酬明细!$K:$K,薪酬明细!$D:$D,$E34,薪酬明细!$E:$E,$F34,薪酬明细!$H:$H,">="&AU$9,薪酬明细!$H:$H,"<="&AU$10,薪酬明细!$A:$A,AU$6)/12 -> 7 | AV34: =SUMIFS(薪酬明细!$K:$K,薪酬明细!$D:$D,$E34,薪酬明细!$E:$E,$F34,薪酬明细!$H:$H,">="&AV$9,薪酬明细!$H:$H,"<="&AV$10,薪酬明细!$A:$A,AV$6) -> 7 | AW34: =SUMIFS(薪酬明细!$K:$K,薪酬明细!$D:$D,$E34,薪酬明细!$E:$E,$F34,薪酬明细!$H:$H,">="&AW$9,薪酬明细!$H:$H,"<="&AW$10,薪酬明细!$A:$A,AW$6) -> 7 | AX34: =SUMIFS(薪酬明细!$K:$K,薪酬明细!$D:$D,$E34,薪酬明细!$E:$E,$F34,薪酬明细!$H:$H,">="&AX$9,薪酬明细!$H:$H,"<="&AX$10,薪酬明细!$A:$A,AX$6) -> 7 | AY34: =SUMIFS(薪酬明细!$K:$K,薪酬明细!$D:$D,$E34,薪酬明细!$E:$E,$F34,薪酬明细!$H:$H,">="&AY$9,薪酬明细!$H:$H,"<="&AY$10,薪酬明细!$A:$A,AY$6) -> 7 | AZ34: =SUMIFS(薪酬明细!$K:$K,薪酬明细!$D:$D,$E34,薪酬明细!$E:$E,$F34,薪酬明细!$H:$H,">="&AZ$9,薪酬明细!$H:$H,"<="&AZ$10,薪酬明细!$A:$A,AZ$6) -> 7 | BA34: =SUMIFS(薪酬明细!$K:$K,薪酬明细!$D:$D,$E34,薪酬明细!$E:$E,$F34,薪酬明细!$H:$H,">="&BA$9,薪酬明细!$H:$H,"<="&BA$10,薪酬明细!$A:$A,BA$6) -> 7 | BB34: =SUMIFS(薪酬明细!$K:$K,薪酬明细!$D:$D,$E34,薪酬明细!$E:$E,$F34,薪酬明细!$H:$H,">="&BB$9,薪酬明细!$H:$H,"<="&BB$10,薪酬明细!$A:$A,BB$6) -> 7 | BC34: =SUMIFS(薪酬明细!$K:$K,薪酬明细!$D:$D,$E34,薪酬明细!$E:$E,$F34,薪酬明细!$H:$H,">="&BC$9,薪酬明细!$H:$H,"<="&BC$10,薪酬明细!$A:$A,BC$6) -> 7 | ... BG34: =SUMIFS(薪酬明细!$K:$K,薪酬明细!$D:$D,$E34,薪酬明细!$E:$E,$F34,薪酬明细!$H:$H,">="&BG$9,薪酬明细!$H:$H,"<="&BG$10,薪酬明细!$A:$A,BG$6) -> 7
C35: 支持中心 | E35: =IF(C35<>"",C35,E34) -> 支持中心 | F35: =IF(D35<>"",D35,"*") -> * | G35: =SUMIFS(薪酬明细!$K:$K,薪酬明细!$D:$D,$E35,薪酬明细!$E:$E,$F35,薪酬明细!$H:$H,">="&G$9,薪酬明细!$H:$H,"<="&G$10,薪酬明细!$A:$A,G$6)/12 -> 17 | H35: =SUMIFS(薪酬明细!$K:$K,薪酬明细!$D:$D,$E35,薪酬明细!$E:$E,$F35,薪酬明细!$H:$H,">="&H$9,薪酬明细!$H:$H,"<="&H$10,薪酬明细!$A:$A,H$6) -> 17 | I35: =SUMIFS(薪酬明细!$K:$K,薪酬明细!$D:$D,$E35,薪酬明细!$E:$E,$F35,薪酬明细!$H:$H,">="&I$9,薪酬明细!$H:$H,"<="&I$10,薪酬明细!$A:$A,I$6) -> 17 | J35: =SUMIFS(薪酬明细!$K:$K,薪酬明细!$D:$D,$E35,薪酬明细!$E:$E,$F35,薪酬明细!$H:$H,">="&J$9,薪酬明细!$H:$H,"<="&J$10,薪酬明细!$A:$A,J$6) -> 17 | K35: =SUMIFS(薪酬明细!$K:$K,薪酬明细!$D:$D,$E35,薪酬明细!$E:$E,$F35,薪酬明细!$H:$H,">="&K$9,薪酬明细!$H:$H,"<="&K$10,薪酬明细!$A:$A,K$6) -> 17 | L35: =SUMIFS(薪酬明细!$K:$K,薪酬明细!$D:$D,$E35,薪酬明细!$E:$E,$F35,薪酬明细!$H:$H,">="&L$9,薪酬明细!$H:$H,"<="&L$10,薪酬明细!$A:$A,L$6) -> 17 | M35: =SUMIFS(薪酬明细!$K:$K,薪酬明细!$D:$D,$E35,薪酬明细!$E:$E,$F35,薪酬明细!$H:$H,">="&M$9,薪酬明细!$H:$H,"<="&M$10,薪酬明细!$A:$A,M$6) -> 17 | N35: =SUMIFS(薪酬明细!$K:$K,薪酬明细!$D:$D,$E35,薪酬明细!$E:$E,$F35,薪酬明细!$H:$H,">="&N$9,薪酬明细!$H:$H,"<="&N$10,薪酬明细!$A:$A,N$6) -> 17 | O35: =SUMIFS(薪酬明细!$K:$K,薪酬明细!$D:$D,$E35,薪酬明细!$E:$E,$F35,薪酬明细!$H:$H,">="&O$9,薪酬明细!$H:$H,"<="&O$10,薪酬明细!$A:$A,O$6) -> 17 | ... S35: =SUMIFS(薪酬明细!$K:$K,薪酬明细!$D:$D,$E35,薪酬明细!$E:$E,$F35,薪酬明细!$H:$H,">="&S$9,薪酬明细!$H:$H,"<="&S$10,薪酬明细!$A:$A,S$6) -> 17 | T35: =(U35*MONTH($G$3)+AH35*(12-MONTH($G$3)))/12 -> 17 | U35: =SUMIFS(薪酬明细!$K:$K,薪酬明细!$D:$D,$E35,薪酬明细!$E:$E,$F35,薪酬明细!$H:$H,">="&U$9,薪酬明细!$H:$H,"<="&U$10,薪酬明细!$A:$A,U$6)/MONTH($G$3) -> 17 | V35: =SUMIFS(薪酬明细!$K:$K,薪酬明细!$D:$D,$E35,薪酬明细!$E:$E,$F35,薪酬明细!$H:$H,">="&V$9,薪酬明细!$H:$H,"<="&V$10,薪酬明细!$A:$A,V$6) -> 17 | W35: =SUMIFS(薪酬明细!$K:$K,薪酬明细!$D:$D,$E35,薪酬明细!$E:$E,$F35,薪酬明细!$H:$H,">="&W$9,薪酬明细!$H:$H,"<="&W$10,薪酬明细!$A:$A,W$6) -> 17 | X35: =SUMIFS(薪酬明细!$K:$K,薪酬明细!$D:$D,$E35,薪酬明细!$E:$E,$F35,薪酬明细!$H:$H,">="&X$9,薪酬明细!$H:$H,"<="&X$10,薪酬明细!$A:$A,X$6) -> 17 | Y35: =SUMIFS(薪酬明细!$K:$K,薪酬明细!$D:$D,$E35,薪酬明细!$E:$E,$F35,薪酬明细!$H:$H,">="&Y$9,薪酬明细!$H:$H,"<="&Y$10,薪酬明细!$A:$A,Y$6) -> 17 | Z35: =SUMIFS(薪酬明细!$K:$K,薪酬明细!$D:$D,$E35,薪酬明细!$E:$E,$F35,薪酬明细!$H:$H,">="&Z$9,薪酬明细!$H:$H,"<="&Z$10,薪酬明细!$A:$A,Z$6) -> 17 | AA35: =SUMIFS(薪酬明细!$K:$K,薪酬明细!$D:$D,$E35,薪酬明细!$E:$E,$F35,薪酬明细!$H:$H,">="&AA$9,薪酬明细!$H:$H,"<="&AA$10,薪酬明细!$A:$A,AA$6) -> 17 | AB35: =SUMIFS(薪酬明细!$K:$K,薪酬明细!$D:$D,$E35,薪酬明细!$E:$E,$F35,薪酬明细!$H:$H,">="&AB$9,薪酬明细!$H:$H,"<="&AB$10,薪酬明细!$A:$A,AB$6) -> 17 | AC35: =SUMIFS(薪酬明细!$K:$K,薪酬明细!$D:$D,$E35,薪酬明细!$E:$E,$F35,薪酬明细!$H:$H,">="&AC$9,薪酬明细!$H:$H,"<="&AC$10,薪酬明细!$A:$A,AC$6) -> 17 | ... AG35: =SUMIFS(薪酬明细!$K:$K,薪酬明细!$D:$D,$E35,薪酬明细!$E:$E,$F35,薪酬明细!$H:$H,">="&AG$9,薪酬明细!$H:$H,"<="&AG$10,薪酬明细!$A:$A,AG$6) -> 0 | AH35: =SUMIFS(薪酬明细!$K:$K,薪酬明细!$D:$D,$E35,薪酬明细!$E:$E,$F35,薪酬明细!$H:$H,">="&AH$9,薪酬明细!$H:$H,"<="&AH$10,薪酬明细!$A:$A,AH$6)/(12-MONTH($G$3)) -> 17 | AI35: =SUMIFS(薪酬明细!$K:$K,薪酬明细!$D:$D,$E35,薪酬明细!$E:$E,$F35,薪酬明细!$H:$H,">="&AI$9,薪酬明细!$H:$H,"<="&AI$10,薪酬明细!$A:$A,AI$6) -> 0 | AJ35: =SUMIFS(薪酬明细!$K:$K,薪酬明细!$D:$D,$E35,薪酬明细!$E:$E,$F35,薪酬明细!$H:$H,">="&AJ$9,薪酬明细!$H:$H,"<="&AJ$10,薪酬明细!$A:$A,AJ$6) -> 0 | AK35: =SUMIFS(薪酬明细!$K:$K,薪酬明细!$D:$D,$E35,薪酬明细!$E:$E,$F35,薪酬明细!$H:$H,">="&AK$9,薪酬明细!$H:$H,"<="&AK$10,薪酬明细!$A:$A,AK$6) -> 0 | AL35: =SUMIFS(薪酬明细!$K:$K,薪酬明细!$D:$D,$E35,薪酬明细!$E:$E,$F35,薪酬明细!$H:$H,">="&AL$9,薪酬明细!$H:$H,"<="&AL$10,薪酬明细!$A:$A,AL$6) -> 0 | AM35: =SUMIFS(薪酬明细!$K:$K,薪酬明细!$D:$D,$E35,薪酬明细!$E:$E,$F35,薪酬明细!$H:$H,">="&AM$9,薪酬明细!$H:$H,"<="&AM$10,薪酬明细!$A:$A,AM$6) -> 0 | AN35: =SUMIFS(薪酬明细!$K:$K,薪酬明细!$D:$D,$E35,薪酬明细!$E:$E,$F35,薪酬明细!$H:$H,">="&AN$9,薪酬明细!$H:$H,"<="&AN$10,薪酬明细!$A:$A,AN$6) -> 0 | AO35: =SUMIFS(薪酬明细!$K:$K,薪酬明细!$D:$D,$E35,薪酬明细!$E:$E,$F35,薪酬明细!$H:$H,">="&AO$9,薪酬明细!$H:$H,"<="&AO$10,薪酬明细!$A:$A,AO$6) -> 0 | AP35: =SUMIFS(薪酬明细!$K:$K,薪酬明细!$D:$D,$E35,薪酬明细!$E:$E,$F35,薪酬明细!$H:$H,">="&AP$9,薪酬明细!$H:$H,"<="&AP$10,薪酬明细!$A:$A,AP$6) -> 0 | ... AT35: =SUMIFS(薪酬明细!$K:$K,薪酬明细!$D:$D,$E35,薪酬明细!$E:$E,$F35,薪酬明细!$H:$H,">="&AT$9,薪酬明细!$H:$H,"<="&AT$10,薪酬明细!$A:$A,AT$6) -> 17 | AU35: =SUMIFS(薪酬明细!$K:$K,薪酬明细!$D:$D,$E35,薪酬明细!$E:$E,$F35,薪酬明细!$H:$H,">="&AU$9,薪酬明细!$H:$H,"<="&AU$10,薪酬明细!$A:$A,AU$6)/12 -> 17 | AV35: =SUMIFS(薪酬明细!$K:$K,薪酬明细!$D:$D,$E35,薪酬明细!$E:$E,$F35,薪酬明细!$H:$H,">="&AV$9,薪酬明细!$H:$H,"<="&AV$10,薪酬明细!$A:$A,AV$6) -> 17 | AW35: =SUMIFS(薪酬明细!$K:$K,薪酬明细!$D:$D,$E35,薪酬明细!$E:$E,$F35,薪酬明细!$H:$H,">="&AW$9,薪酬明细!$H:$H,"<="&AW$10,薪酬明细!$A:$A,AW$6) -> 17 | AX35: =SUMIFS(薪酬明细!$K:$K,薪酬明细!$D:$D,$E35,薪酬明细!$E:$E,$F35,薪酬明细!$H:$H,">="&AX$9,薪酬明细!$H:$H,"<="&AX$10,薪酬明细!$A:$A,AX$6) -> 17 | AY35: =SUMIFS(薪酬明细!$K:$K,薪酬明细!$D:$D,$E35,薪酬明细!$E:$E,$F35,薪酬明细!$H:$H,">="&AY$9,薪酬明细!$H:$H,"<="&AY$10,薪酬明细!$A:$A,AY$6) -> 17 | AZ35: =SUMIFS(薪酬明细!$K:$K,薪酬明细!$D:$D,$E35,薪酬明细!$E:$E,$F35,薪酬明细!$H:$H,">="&AZ$9,薪酬明细!$H:$H,"<="&AZ$10,薪酬明细!$A:$A,AZ$6) -> 17 | BA35: =SUMIFS(薪酬明细!$K:$K,薪酬明细!$D:$D,$E35,薪酬明细!$E:$E,$F35,薪酬明细!$H:$H,">="&BA$9,薪酬明细!$H:$H,"<="&BA$10,薪酬明细!$A:$A,BA$6) -> 17 | BB35: =SUMIFS(薪酬明细!$K:$K,薪酬明细!$D:$D,$E35,薪酬明细!$E:$E,$F35,薪酬明细!$H:$H,">="&BB$9,薪酬明细!$H:$H,"<="&BB$10,薪酬明细!$A:$A,BB$6) -> 17 | BC35: =SUMIFS(薪酬明细!$K:$K,薪酬明细!$D:$D,$E35,薪酬明细!$E:$E,$F35,薪酬明细!$H:$H,">="&BC$9,薪酬明细!$H:$H,"<="&BC$10,薪酬明细!$A:$A,BC$6) -> 17 | ... BG35: =SUMIFS(薪酬明细!$K:$K,薪酬明细!$D:$D,$E35,薪酬明细!$E:$E,$F35,薪酬明细!$H:$H,">="&BG$9,薪酬明细!$H:$H,"<="&BG$10,薪酬明细!$A:$A,BG$6) -> 17
D36: 财务部 | E36: =IF(C36<>"",C36,E35) -> 支持中心 | F36: =IF(D36<>"",D36,"*") -> 财务部 | G36: =SUMIFS(薪酬明细!$K:$K,薪酬明细!$D:$D,$E36,薪酬明细!$E:$E,$F36,薪酬明细!$H:$H,">="&G$9,薪酬明细!$H:$H,"<="&G$10,薪酬明细!$A:$A,G$6)/12 -> 7 | H36: =SUMIFS(薪酬明细!$K:$K,薪酬明细!$D:$D,$E36,薪酬明细!$E:$E,$F36,薪酬明细!$H:$H,">="&H$9,薪酬明细!$H:$H,"<="&H$10,薪酬明细!$A:$A,H$6) -> 7 | I36: =SUMIFS(薪酬明细!$K:$K,薪酬明细!$D:$D,$E36,薪酬明细!$E:$E,$F36,薪酬明细!$H:$H,">="&I$9,薪酬明细!$H:$H,"<="&I$10,薪酬明细!$A:$A,I$6) -> 7 | J36: =SUMIFS(薪酬明细!$K:$K,薪酬明细!$D:$D,$E36,薪酬明细!$E:$E,$F36,薪酬明细!$H:$H,">="&J$9,薪酬明细!$H:$H,"<="&J$10,薪酬明细!$A:$A,J$6) -> 7 | K36: =SUMIFS(薪酬明细!$K:$K,薪酬明细!$D:$D,$E36,薪酬明细!$E:$E,$F36,薪酬明细!$H:$H,">="&K$9,薪酬明细!$H:$H,"<="&K$10,薪酬明细!$A:$A,K$6) -> 7 | L36: =SUMIFS(薪酬明细!$K:$K,薪酬明细!$D:$D,$E36,薪酬明细!$E:$E,$F36,薪酬明细!$H:$H,">="&L$9,薪酬明细!$H:$H,"<="&L$10,薪酬明细!$A:$A,L$6) -> 7 | M36: =SUMIFS(薪酬明细!$K:$K,薪酬明细!$D:$D,$E36,薪酬明细!$E:$E,$F36,薪酬明细!$H:$H,">="&M$9,薪酬明细!$H:$H,"<="&M$10,薪酬明细!$A:$A,M$6) -> 7 | N36: =SUMIFS(薪酬明细!$K:$K,薪酬明细!$D:$D,$E36,薪酬明细!$E:$E,$F36,薪酬明细!$H:$H,">="&N$9,薪酬明细!$H:$H,"<="&N$10,薪酬明细!$A:$A,N$6) -> 7 | O36: =SUMIFS(薪酬明细!$K:$K,薪酬明细!$D:$D,$E36,薪酬明细!$E:$E,$F36,薪酬明细!$H:$H,">="&O$9,薪酬明细!$H:$H,"<="&O$10,薪酬明细!$A:$A,O$6) -> 7 | ... S36: =SUMIFS(薪酬明细!$K:$K,薪酬明细!$D:$D,$E36,薪酬明细!$E:$E,$F36,薪酬明细!$H:$H,">="&S$9,薪酬明细!$H:$H,"<="&S$10,薪酬明细!$A:$A,S$6) -> 7 | T36: =(U36*MONTH($G$3)+AH36*(12-MONTH($G$3)))/12 -> 7 | U36: =SUMIFS(薪酬明细!$K:$K,薪酬明细!$D:$D,$E36,薪酬明细!$E:$E,$F36,薪酬明细!$H:$H,">="&U$9,薪酬明细!$H:$H,"<="&U$10,薪酬明细!$A:$A,U$6)/MONTH($G$3) -> 7 | V36: =SUMIFS(薪酬明细!$K:$K,薪酬明细!$D:$D,$E36,薪酬明细!$E:$E,$F36,薪酬明细!$H:$H,">="&V$9,薪酬明细!$H:$H,"<="&V$10,薪酬明细!$A:$A,V$6) -> 7 | W36: =SUMIFS(薪酬明细!$K:$K,薪酬明细!$D:$D,$E36,薪酬明细!$E:$E,$F36,薪酬明细!$H:$H,">="&W$9,薪酬明细!$H:$H,"<="&W$10,薪酬明细!$A:$A,W$6) -> 7 | X36: =SUMIFS(薪酬明细!$K:$K,薪酬明细!$D:$D,$E36,薪酬明细!$E:$E,$F36,薪酬明细!$H:$H,">="&X$9,薪酬明细!$H:$H,"<="&X$10,薪酬明细!$A:$A,X$6) -> 7 | Y36: =SUMIFS(薪酬明细!$K:$K,薪酬明细!$D:$D,$E36,薪酬明细!$E:$E,$F36,薪酬明细!$H:$H,">="&Y$9,薪酬明细!$H:$H,"<="&Y$10,薪酬明细!$A:$A,Y$6) -> 7 | Z36: =SUMIFS(薪酬明细!$K:$K,薪酬明细!$D:$D,$E36,薪酬明细!$E:$E,$F36,薪酬明细!$H:$H,">="&Z$9,薪酬明细!$H:$H,"<="&Z$10,薪酬明细!$A:$A,Z$6) -> 7 | AA36: =SUMIFS(薪酬明细!$K:$K,薪酬明细!$D:$D,$E36,薪酬明细!$E:$E,$F36,薪酬明细!$H:$H,">="&AA$9,薪酬明细!$H:$H,"<="&AA$10,薪酬明细!$A:$A,AA$6) -> 7 | AB36: =SUMIFS(薪酬明细!$K:$K,薪酬明细!$D:$D,$E36,薪酬明细!$E:$E,$F36,薪酬明细!$H:$H,">="&AB$9,薪酬明细!$H:$H,"<="&AB$10,薪酬明细!$A:$A,AB$6) -> 7 | AC36: =SUMIFS(薪酬明细!$K:$K,薪酬明细!$D:$D,$E36,薪酬明细!$E:$E,$F36,薪酬明细!$H:$H,">="&AC$9,薪酬明细!$H:$H,"<="&AC$10,薪酬明细!$A:$A,AC$6) -> 7 | ... AG36: =SUMIFS(薪酬明细!$K:$K,薪酬明细!$D:$D,$E36,薪酬明细!$E:$E,$F36,薪酬明细!$H:$H,">="&AG$9,薪酬明细!$H:$H,"<="&AG$10,薪酬明细!$A:$A,AG$6) -> 0 | AH36: =SUMIFS(薪酬明细!$K:$K,薪酬明细!$D:$D,$E36,薪酬明细!$E:$E,$F36,薪酬明细!$H:$H,">="&AH$9,薪酬明细!$H:$H,"<="&AH$10,薪酬明细!$A:$A,AH$6)/(12-MONTH($G$3)) -> 7 | AI36: =SUMIFS(薪酬明细!$K:$K,薪酬明细!$D:$D,$E36,薪酬明细!$E:$E,$F36,薪酬明细!$H:$H,">="&AI$9,薪酬明细!$H:$H,"<="&AI$10,薪酬明细!$A:$A,AI$6) -> 0 | AJ36: =SUMIFS(薪酬明细!$K:$K,薪酬明细!$D:$D,$E36,薪酬明细!$E:$E,$F36,薪酬明细!$H:$H,">="&AJ$9,薪酬明细!$H:$H,"<="&AJ$10,薪酬明细!$A:$A,AJ$6) -> 0 | AK36: =SUMIFS(薪酬明细!$K:$K,薪酬明细!$D:$D,$E36,薪酬明细!$E:$E,$F36,薪酬明细!$H:$H,">="&AK$9,薪酬明细!$H:$H,"<="&AK$10,薪酬明细!$A:$A,AK$6) -> 0 | AL36: =SUMIFS(薪酬明细!$K:$K,薪酬明细!$D:$D,$E36,薪酬明细!$E:$E,$F36,薪酬明细!$H:$H,">="&AL$9,薪酬明细!$H:$H,"<="&AL$10,薪酬明细!$A:$A,AL$6) -> 0 | AM36: =SUMIFS(薪酬明细!$K:$K,薪酬明细!$D:$D,$E36,薪酬明细!$E:$E,$F36,薪酬明细!$H:$H,">="&AM$9,薪酬明细!$H:$H,"<="&AM$10,薪酬明细!$A:$A,AM$6) -> 0 | AN36: =SUMIFS(薪酬明细!$K:$K,薪酬明细!$D:$D,$E36,薪酬明细!$E:$E,$F36,薪酬明细!$H:$H,">="&AN$9,薪酬明细!$H:$H,"<="&AN$10,薪酬明细!$A:$A,AN$6) -> 0 | AO36: =SUMIFS(薪酬明细!$K:$K,薪酬明细!$D:$D,$E36,薪酬明细!$E:$E,$F36,薪酬明细!$H:$H,">="&AO$9,薪酬明细!$H:$H,"<="&AO$10,薪酬明细!$A:$A,AO$6) -> 0 | AP36: =SUMIFS(薪酬明细!$K:$K,薪酬明细!$D:$D,$E36,薪酬明细!$E:$E,$F36,薪酬明细!$H:$H,">="&AP$9,薪酬明细!$H:$H,"<="&AP$10,薪酬明细!$A:$A,AP$6) -> 0 | ... AT36: =SUMIFS(薪酬明细!$K:$K,薪酬明细!$D:$D,$E36,薪酬明细!$E:$E,$F36,薪酬明细!$H:$H,">="&AT$9,薪酬明细!$H:$H,"<="&AT$10,薪酬明细!$A:$A,AT$6) -> 7 | AU36: =SUMIFS(薪酬明细!$K:$K,薪酬明细!$D:$D,$E36,薪酬明细!$E:$E,$F36,薪酬明细!$H:$H,">="&AU$9,薪酬明细!$H:$H,"<="&AU$10,薪酬明细!$A:$A,AU$6)/12 -> 7 | AV36: =SUMIFS(薪酬明细!$K:$K,薪酬明细!$D:$D,$E36,薪酬明细!$E:$E,$F36,薪酬明细!$H:$H,">="&AV$9,薪酬明细!$H:$H,"<="&AV$10,薪酬明细!$A:$A,AV$6) -> 7 | AW36: =SUMIFS(薪酬明细!$K:$K,薪酬明细!$D:$D,$E36,薪酬明细!$E:$E,$F36,薪酬明细!$H:$H,">="&AW$9,薪酬明细!$H:$H,"<="&AW$10,薪酬明细!$A:$A,AW$6) -> 7 | AX36: =SUMIFS(薪酬明细!$K:$K,薪酬明细!$D:$D,$E36,薪酬明细!$E:$E,$F36,薪酬明细!$H:$H,">="&AX$9,薪酬明细!$H:$H,"<="&AX$10,薪酬明细!$A:$A,AX$6) -> 7 | AY36: =SUMIFS(薪酬明细!$K:$K,薪酬明细!$D:$D,$E36,薪酬明细!$E:$E,$F36,薪酬明细!$H:$H,">="&AY$9,薪酬明细!$H:$H,"<="&AY$10,薪酬明细!$A:$A,AY$6) -> 7 | AZ36: =SUMIFS(薪酬明细!$K:$K,薪酬明细!$D:$D,$E36,薪酬明细!$E:$E,$F36,薪酬明细!$H:$H,">="&AZ$9,薪酬明细!$H:$H,"<="&AZ$10,薪酬明细!$A:$A,AZ$6) -> 7 | BA36: =SUMIFS(薪酬明细!$K:$K,薪酬明细!$D:$D,$E36,薪酬明细!$E:$E,$F36,薪酬明细!$H:$H,">="&BA$9,薪酬明细!$H:$H,"<="&BA$10,薪酬明细!$A:$A,BA$6) -> 7 | BB36: =SUMIFS(薪酬明细!$K:$K,薪酬明细!$D:$D,$E36,薪酬明细!$E:$E,$F36,薪酬明细!$H:$H,">="&BB$9,薪酬明细!$H:$H,"<="&BB$10,薪酬明细!$A:$A,BB$6) -> 7 | BC36: =SUMIFS(薪酬明细!$K:$K,薪酬明细!$D:$D,$E36,薪酬明细!$E:$E,$F36,薪酬明细!$H:$H,">="&BC$9,薪酬明细!$H:$H,"<="&BC$10,薪酬明细!$A:$A,BC$6) -> 7 | ... BG36: =SUMIFS(薪酬明细!$K:$K,薪酬明细!$D:$D,$E36,薪酬明细!$E:$E,$F36,薪酬明细!$H:$H,">="&BG$9,薪酬明细!$H:$H,"<="&BG$10,薪酬明细!$A:$A,BG$6) -> 7
D37: 人力资源部 | E37: =IF(C37<>"",C37,E36) -> 支持中心 | F37: =IF(D37<>"",D37,"*") -> 人力资源部 | G37: =SUMIFS(薪酬明细!$K:$K,薪酬明细!$D:$D,$E37,薪酬明细!$E:$E,$F37,薪酬明细!$H:$H,">="&G$9,薪酬明细!$H:$H,"<="&G$10,薪酬明细!$A:$A,G$6)/12 -> 6 | H37: =SUMIFS(薪酬明细!$K:$K,薪酬明细!$D:$D,$E37,薪酬明细!$E:$E,$F37,薪酬明细!$H:$H,">="&H$9,薪酬明细!$H:$H,"<="&H$10,薪酬明细!$A:$A,H$6) -> 6 | I37: =SUMIFS(薪酬明细!$K:$K,薪酬明细!$D:$D,$E37,薪酬明细!$E:$E,$F37,薪酬明细!$H:$H,">="&I$9,薪酬明细!$H:$H,"<="&I$10,薪酬明细!$A:$A,I$6) -> 6 | J37: =SUMIFS(薪酬明细!$K:$K,薪酬明细!$D:$D,$E37,薪酬明细!$E:$E,$F37,薪酬明细!$H:$H,">="&J$9,薪酬明细!$H:$H,"<="&J$10,薪酬明细!$A:$A,J$6) -> 6 | K37: =SUMIFS(薪酬明细!$K:$K,薪酬明细!$D:$D,$E37,薪酬明细!$E:$E,$F37,薪酬明细!$H:$H,">="&K$9,薪酬明细!$H:$H,"<="&K$10,薪酬明细!$A:$A,K$6) -> 6 | L37: =SUMIFS(薪酬明细!$K:$K,薪酬明细!$D:$D,$E37,薪酬明细!$E:$E,$F37,薪酬明细!$H:$H,">="&L$9,薪酬明细!$H:$H,"<="&L$10,薪酬明细!$A:$A,L$6) -> 6 | M37: =SUMIFS(薪酬明细!$K:$K,薪酬明细!$D:$D,$E37,薪酬明细!$E:$E,$F37,薪酬明细!$H:$H,">="&M$9,薪酬明细!$H:$H,"<="&M$10,薪酬明细!$A:$A,M$6) -> 6 | N37: =SUMIFS(薪酬明细!$K:$K,薪酬明细!$D:$D,$E37,薪酬明细!$E:$E,$F37,薪酬明细!$H:$H,">="&N$9,薪酬明细!$H:$H,"<="&N$10,薪酬明细!$A:$A,N$6) -> 6 | O37: =SUMIFS(薪酬明细!$K:$K,薪酬明细!$D:$D,$E37,薪酬明细!$E:$E,$F37,薪酬明细!$H:$H,">="&O$9,薪酬明细!$H:$H,"<="&O$10,薪酬明细!$A:$A,O$6) -> 6 | ... S37: =SUMIFS(薪酬明细!$K:$K,薪酬明细!$D:$D,$E37,薪酬明细!$E:$E,$F37,薪酬明细!$H:$H,">="&S$9,薪酬明细!$H:$H,"<="&S$10,薪酬明细!$A:$A,S$6) -> 6 | T37: =(U37*MONTH($G$3)+AH37*(12-MONTH($G$3)))/12 -> 6 | U37: =SUMIFS(薪酬明细!$K:$K,薪酬明细!$D:$D,$E37,薪酬明细!$E:$E,$F37,薪酬明细!$H:$H,">="&U$9,薪酬明细!$H:$H,"<="&U$10,薪酬明细!$A:$A,U$6)/MONTH($G$3) -> 6 | V37: =SUMIFS(薪酬明细!$K:$K,薪酬明细!$D:$D,$E37,薪酬明细!$E:$E,$F37,薪酬明细!$H:$H,">="&V$9,薪酬明细!$H:$H,"<="&V$10,薪酬明细!$A:$A,V$6) -> 6 | W37: =SUMIFS(薪酬明细!$K:$K,薪酬明细!$D:$D,$E37,薪酬明细!$E:$E,$F37,薪酬明细!$H:$H,">="&W$9,薪酬明细!$H:$H,"<="&W$10,薪酬明细!$A:$A,W$6) -> 6 | X37: =SUMIFS(薪酬明细!$K:$K,薪酬明细!$D:$D,$E37,薪酬明细!$E:$E,$F37,薪酬明细!$H:$H,">="&X$9,薪酬明细!$H:$H,"<="&X$10,薪酬明细!$A:$A,X$6) -> 6 | Y37: =SUMIFS(薪酬明细!$K:$K,薪酬明细!$D:$D,$E37,薪酬明细!$E:$E,$F37,薪酬明细!$H:$H,">="&Y$9,薪酬明细!$H:$H,"<="&Y$10,薪酬明细!$A:$A,Y$6) -> 6 | Z37: =SUMIFS(薪酬明细!$K:$K,薪酬明细!$D:$D,$E37,薪酬明细!$E:$E,$F37,薪酬明细!$H:$H,">="&Z$9,薪酬明细!$H:$H,"<="&Z$10,薪酬明细!$A:$A,Z$6) -> 6 | AA37: =SUMIFS(薪酬明细!$K:$K,薪酬明细!$D:$D,$E37,薪酬明细!$E:$E,$F37,薪酬明细!$H:$H,">="&AA$9,薪酬明细!$H:$H,"<="&AA$10,薪酬明细!$A:$A,AA$6) -> 6 | AB37: =SUMIFS(薪酬明细!$K:$K,薪酬明细!$D:$D,$E37,薪酬明细!$E:$E,$F37,薪酬明细!$H:$H,">="&AB$9,薪酬明细!$H:$H,"<="&AB$10,薪酬明细!$A:$A,AB$6) -> 6 | AC37: =SUMIFS(薪酬明细!$K:$K,薪酬明细!$D:$D,$E37,薪酬明细!$E:$E,$F37,薪酬明细!$H:$H,">="&AC$9,薪酬明细!$H:$H,"<="&AC$10,薪酬明细!$A:$A,AC$6) -> 6 | ... AG37: =SUMIFS(薪酬明细!$K:$K,薪酬明细!$D:$D,$E37,薪酬明细!$E:$E,$F37,薪酬明细!$H:$H,">="&AG$9,薪酬明细!$H:$H,"<="&AG$10,薪酬明细!$A:$A,AG$6) -> 0 | AH37: =SUMIFS(薪酬明细!$K:$K,薪酬明细!$D:$D,$E37,薪酬明细!$E:$E,$F37,薪酬明细!$H:$H,">="&AH$9,薪酬明细!$H:$H,"<="&AH$10,薪酬明细!$A:$A,AH$6)/(12-MONTH($G$3)) -> 6 | AI37: =SUMIFS(薪酬明细!$K:$K,薪酬明细!$D:$D,$E37,薪酬明细!$E:$E,$F37,薪酬明细!$H:$H,">="&AI$9,薪酬明细!$H:$H,"<="&AI$10,薪酬明细!$A:$A,AI$6) -> 0 | AJ37: =SUMIFS(薪酬明细!$K:$K,薪酬明细!$D:$D,$E37,薪酬明细!$E:$E,$F37,薪酬明细!$H:$H,">="&AJ$9,薪酬明细!$H:$H,"<="&AJ$10,薪酬明细!$A:$A,AJ$6) -> 0 | AK37: =SUMIFS(薪酬明细!$K:$K,薪酬明细!$D:$D,$E37,薪酬明细!$E:$E,$F37,薪酬明细!$H:$H,">="&AK$9,薪酬明细!$H:$H,"<="&AK$10,薪酬明细!$A:$A,AK$6) -> 0 | AL37: =SUMIFS(薪酬明细!$K:$K,薪酬明细!$D:$D,$E37,薪酬明细!$E:$E,$F37,薪酬明细!$H:$H,">="&AL$9,薪酬明细!$H:$H,"<="&AL$10,薪酬明细!$A:$A,AL$6) -> 0 | AM37: =SUMIFS(薪酬明细!$K:$K,薪酬明细!$D:$D,$E37,薪酬明细!$E:$E,$F37,薪酬明细!$H:$H,">="&AM$9,薪酬明细!$H:$H,"<="&AM$10,薪酬明细!$A:$A,AM$6) -> 0 | AN37: =SUMIFS(薪酬明细!$K:$K,薪酬明细!$D:$D,$E37,薪酬明细!$E:$E,$F37,薪酬明细!$H:$H,">="&AN$9,薪酬明细!$H:$H,"<="&AN$10,薪酬明细!$A:$A,AN$6) -> 0 | AO37: =SUMIFS(薪酬明细!$K:$K,薪酬明细!$D:$D,$E37,薪酬明细!$E:$E,$F37,薪酬明细!$H:$H,">="&AO$9,薪酬明细!$H:$H,"<="&AO$10,薪酬明细!$A:$A,AO$6) -> 0 | AP37: =SUMIFS(薪酬明细!$K:$K,薪酬明细!$D:$D,$E37,薪酬明细!$E:$E,$F37,薪酬明细!$H:$H,">="&AP$9,薪酬明细!$H:$H,"<="&AP$10,薪酬明细!$A:$A,AP$6) -> 0 | ... AT37: =SUMIFS(薪酬明细!$K:$K,薪酬明细!$D:$D,$E37,薪酬明细!$E:$E,$F37,薪酬明细!$H:$H,">="&AT$9,薪酬明细!$H:$H,"<="&AT$10,薪酬明细!$A:$A,AT$6) -> 6 | AU37: =SUMIFS(薪酬明细!$K:$K,薪酬明细!$D:$D,$E37,薪酬明细!$E:$E,$F37,薪酬明细!$H:$H,">="&AU$9,薪酬明细!$H:$H,"<="&AU$10,薪酬明细!$A:$A,AU$6)/12 -> 6 | AV37: =SUMIFS(薪酬明细!$K:$K,薪酬明细!$D:$D,$E37,薪酬明细!$E:$E,$F37,薪酬明细!$H:$H,">="&AV$9,薪酬明细!$H:$H,"<="&AV$10,薪酬明细!$A:$A,AV$6) -> 6 | AW37: =SUMIFS(薪酬明细!$K:$K,薪酬明细!$D:$D,$E37,薪酬明细!$E:$E,$F37,薪酬明细!$H:$H,">="&AW$9,薪酬明细!$H:$H,"<="&AW$10,薪酬明细!$A:$A,AW$6) -> 6 | AX37: =SUMIFS(薪酬明细!$K:$K,薪酬明细!$D:$D,$E37,薪酬明细!$E:$E,$F37,薪酬明细!$H:$H,">="&AX$9,薪酬明细!$H:$H,"<="&AX$10,薪酬明细!$A:$A,AX$6) -> 6 | AY37: =SUMIFS(薪酬明细!$K:$K,薪酬明细!$D:$D,$E37,薪酬明细!$E:$E,$F37,薪酬明细!$H:$H,">="&AY$9,薪酬明细!$H:$H,"<="&AY$10,薪酬明细!$A:$A,AY$6) -> 6 | AZ37: =SUMIFS(薪酬明细!$K:$K,薪酬明细!$D:$D,$E37,薪酬明细!$E:$E,$F37,薪酬明细!$H:$H,">="&AZ$9,薪酬明细!$H:$H,"<="&AZ$10,薪酬明细!$A:$A,AZ$6) -> 6 | BA37: =SUMIFS(薪酬明细!$K:$K,薪酬明细!$D:$D,$E37,薪酬明细!$E:$E,$F37,薪酬明细!$H:$H,">="&BA$9,薪酬明细!$H:$H,"<="&BA$10,薪酬明细!$A:$A,BA$6) -> 6 | BB37: =SUMIFS(薪酬明细!$K:$K,薪酬明细!$D:$D,$E37,薪酬明细!$E:$E,$F37,薪酬明细!$H:$H,">="&BB$9,薪酬明细!$H:$H,"<="&BB$10,薪酬明细!$A:$A,BB$6) -> 6 | BC37: =SUMIFS(薪酬明细!$K:$K,薪酬明细!$D:$D,$E37,薪酬明细!$E:$E,$F37,薪酬明细!$H:$H,">="&BC$9,薪酬明细!$H:$H,"<="&BC$10,薪酬明细!$A:$A,BC$6) -> 6 | ... BG37: =SUMIFS(薪酬明细!$K:$K,薪酬明细!$D:$D,$E37,薪酬明细!$E:$E,$F37,薪酬明细!$H:$H,">="&BG$9,薪酬明细!$H:$H,"<="&BG$10,薪酬明细!$A:$A,BG$6) -> 6
D38: IT部 | E38: =IF(C38<>"",C38,E37) -> 支持中心 | F38: =IF(D38<>"",D38,"*") -> IT部 | G38: =SUMIFS(薪酬明细!$K:$K,薪酬明细!$D:$D,$E38,薪酬明细!$E:$E,$F38,薪酬明细!$H:$H,">="&G$9,薪酬明细!$H:$H,"<="&G$10,薪酬明细!$A:$A,G$6)/12 -> 3 | H38: =SUMIFS(薪酬明细!$K:$K,薪酬明细!$D:$D,$E38,薪酬明细!$E:$E,$F38,薪酬明细!$H:$H,">="&H$9,薪酬明细!$H:$H,"<="&H$10,薪酬明细!$A:$A,H$6) -> 3 | I38: =SUMIFS(薪酬明细!$K:$K,薪酬明细!$D:$D,$E38,薪酬明细!$E:$E,$F38,薪酬明细!$H:$H,">="&I$9,薪酬明细!$H:$H,"<="&I$10,薪酬明细!$A:$A,I$6) -> 3 | J38: =SUMIFS(薪酬明细!$K:$K,薪酬明细!$D:$D,$E38,薪酬明细!$E:$E,$F38,薪酬明细!$H:$H,">="&J$9,薪酬明细!$H:$H,"<="&J$10,薪酬明细!$A:$A,J$6) -> 3 | K38: =SUMIFS(薪酬明细!$K:$K,薪酬明细!$D:$D,$E38,薪酬明细!$E:$E,$F38,薪酬明细!$H:$H,">="&K$9,薪酬明细!$H:$H,"<="&K$10,薪酬明细!$A:$A,K$6) -> 3 | L38: =SUMIFS(薪酬明细!$K:$K,薪酬明细!$D:$D,$E38,薪酬明细!$E:$E,$F38,薪酬明细!$H:$H,">="&L$9,薪酬明细!$H:$H,"<="&L$10,薪酬明细!$A:$A,L$6) -> 3 | M38: =SUMIFS(薪酬明细!$K:$K,薪酬明细!$D:$D,$E38,薪酬明细!$E:$E,$F38,薪酬明细!$H:$H,">="&M$9,薪酬明细!$H:$H,"<="&M$10,薪酬明细!$A:$A,M$6) -> 3 | N38: =SUMIFS(薪酬明细!$K:$K,薪酬明细!$D:$D,$E38,薪酬明细!$E:$E,$F38,薪酬明细!$H:$H,">="&N$9,薪酬明细!$H:$H,"<="&N$10,薪酬明细!$A:$A,N$6) -> 3 | O38: =SUMIFS(薪酬明细!$K:$K,薪酬明细!$D:$D,$E38,薪酬明细!$E:$E,$F38,薪酬明细!$H:$H,">="&O$9,薪酬明细!$H:$H,"<="&O$10,薪酬明细!$A:$A,O$6) -> 3 | ... S38: =SUMIFS(薪酬明细!$K:$K,薪酬明细!$D:$D,$E38,薪酬明细!$E:$E,$F38,薪酬明细!$H:$H,">="&S$9,薪酬明细!$H:$H,"<="&S$10,薪酬明细!$A:$A,S$6) -> 3 | T38: =(U38*MONTH($G$3)+AH38*(12-MONTH($G$3)))/12 -> 3 | U38: =SUMIFS(薪酬明细!$K:$K,薪酬明细!$D:$D,$E38,薪酬明细!$E:$E,$F38,薪酬明细!$H:$H,">="&U$9,薪酬明细!$H:$H,"<="&U$10,薪酬明细!$A:$A,U$6)/MONTH($G$3) -> 3 | V38: =SUMIFS(薪酬明细!$K:$K,薪酬明细!$D:$D,$E38,薪酬明细!$E:$E,$F38,薪酬明细!$H:$H,">="&V$9,薪酬明细!$H:$H,"<="&V$10,薪酬明细!$A:$A,V$6) -> 3 | W38: =SUMIFS(薪酬明细!$K:$K,薪酬明细!$D:$D,$E38,薪酬明细!$E:$E,$F38,薪酬明细!$H:$H,">="&W$9,薪酬明细!$H:$H,"<="&W$10,薪酬明细!$A:$A,W$6) -> 3 | X38: =SUMIFS(薪酬明细!$K:$K,薪酬明细!$D:$D,$E38,薪酬明细!$E:$E,$F38,薪酬明细!$H:$H,">="&X$9,薪酬明细!$H:$H,"<="&X$10,薪酬明细!$A:$A,X$6) -> 3 | Y38: =SUMIFS(薪酬明细!$K:$K,薪酬明细!$D:$D,$E38,薪酬明细!$E:$E,$F38,薪酬明细!$H:$H,">="&Y$9,薪酬明细!$H:$H,"<="&Y$10,薪酬明细!$A:$A,Y$6) -> 3 | Z38: =SUMIFS(薪酬明细!$K:$K,薪酬明细!$D:$D,$E38,薪酬明细!$E:$E,$F38,薪酬明细!$H:$H,">="&Z$9,薪酬明细!$H:$H,"<="&Z$10,薪酬明细!$A:$A,Z$6) -> 3 | AA38: =SUMIFS(薪酬明细!$K:$K,薪酬明细!$D:$D,$E38,薪酬明细!$E:$E,$F38,薪酬明细!$H:$H,">="&AA$9,薪酬明细!$H:$H,"<="&AA$10,薪酬明细!$A:$A,AA$6) -> 3 | AB38: =SUMIFS(薪酬明细!$K:$K,薪酬明细!$D:$D,$E38,薪酬明细!$E:$E,$F38,薪酬明细!$H:$H,">="&AB$9,薪酬明细!$H:$H,"<="&AB$10,薪酬明细!$A:$A,AB$6) -> 3 | AC38: =SUMIFS(薪酬明细!$K:$K,薪酬明细!$D:$D,$E38,薪酬明细!$E:$E,$F38,薪酬明细!$H:$H,">="&AC$9,薪酬明细!$H:$H,"<="&AC$10,薪酬明细!$A:$A,AC$6) -> 3 | ... AG38: =SUMIFS(薪酬明细!$K:$K,薪酬明细!$D:$D,$E38,薪酬明细!$E:$E,$F38,薪酬明细!$H:$H,">="&AG$9,薪酬明细!$H:$H,"<="&AG$10,薪酬明细!$A:$A,AG$6) -> 0 | AH38: =SUMIFS(薪酬明细!$K:$K,薪酬明细!$D:$D,$E38,薪酬明细!$E:$E,$F38,薪酬明细!$H:$H,">="&AH$9,薪酬明细!$H:$H,"<="&AH$10,薪酬明细!$A:$A,AH$6)/(12-MONTH($G$3)) -> 3 | AI38: =SUMIFS(薪酬明细!$K:$K,薪酬明细!$D:$D,$E38,薪酬明细!$E:$E,$F38,薪酬明细!$H:$H,">="&AI$9,薪酬明细!$H:$H,"<="&AI$10,薪酬明细!$A:$A,AI$6) -> 0 | AJ38: =SUMIFS(薪酬明细!$K:$K,薪酬明细!$D:$D,$E38,薪酬明细!$E:$E,$F38,薪酬明细!$H:$H,">="&AJ$9,薪酬明细!$H:$H,"<="&AJ$10,薪酬明细!$A:$A,AJ$6) -> 0 | AK38: =SUMIFS(薪酬明细!$K:$K,薪酬明细!$D:$D,$E38,薪酬明细!$E:$E,$F38,薪酬明细!$H:$H,">="&AK$9,薪酬明细!$H:$H,"<="&AK$10,薪酬明细!$A:$A,AK$6) -> 0 | AL38: =SUMIFS(薪酬明细!$K:$K,薪酬明细!$D:$D,$E38,薪酬明细!$E:$E,$F38,薪酬明细!$H:$H,">="&AL$9,薪酬明细!$H:$H,"<="&AL$10,薪酬明细!$A:$A,AL$6) -> 0 | AM38: =SUMIFS(薪酬明细!$K:$K,薪酬明细!$D:$D,$E38,薪酬明细!$E:$E,$F38,薪酬明细!$H:$H,">="&AM$9,薪酬明细!$H:$H,"<="&AM$10,薪酬明细!$A:$A,AM$6) -> 0 | AN38: =SUMIFS(薪酬明细!$K:$K,薪酬明细!$D:$D,$E38,薪酬明细!$E:$E,$F38,薪酬明细!$H:$H,">="&AN$9,薪酬明细!$H:$H,"<="&AN$10,薪酬明细!$A:$A,AN$6) -> 0 | AO38: =SUMIFS(薪酬明细!$K:$K,薪酬明细!$D:$D,$E38,薪酬明细!$E:$E,$F38,薪酬明细!$H:$H,">="&AO$9,薪酬明细!$H:$H,"<="&AO$10,薪酬明细!$A:$A,AO$6) -> 0 | AP38: =SUMIFS(薪酬明细!$K:$K,薪酬明细!$D:$D,$E38,薪酬明细!$E:$E,$F38,薪酬明细!$H:$H,">="&AP$9,薪酬明细!$H:$H,"<="&AP$10,薪酬明细!$A:$A,AP$6) -> 0 | ... AT38: =SUMIFS(薪酬明细!$K:$K,薪酬明细!$D:$D,$E38,薪酬明细!$E:$E,$F38,薪酬明细!$H:$H,">="&AT$9,薪酬明细!$H:$H,"<="&AT$10,薪酬明细!$A:$A,AT$6) -> 3 | AU38: =SUMIFS(薪酬明细!$K:$K,薪酬明细!$D:$D,$E38,薪酬明细!$E:$E,$F38,薪酬明细!$H:$H,">="&AU$9,薪酬明细!$H:$H,"<="&AU$10,薪酬明细!$A:$A,AU$6)/12 -> 3 | AV38: =SUMIFS(薪酬明细!$K:$K,薪酬明细!$D:$D,$E38,薪酬明细!$E:$E,$F38,薪酬明细!$H:$H,">="&AV$9,薪酬明细!$H:$H,"<="&AV$10,薪酬明细!$A:$A,AV$6) -> 3 | AW38: =SUMIFS(薪酬明细!$K:$K,薪酬明细!$D:$D,$E38,薪酬明细!$E:$E,$F38,薪酬明细!$H:$H,">="&AW$9,薪酬明细!$H:$H,"<="&AW$10,薪酬明细!$A:$A,AW$6) -> 3 | AX38: =SUMIFS(薪酬明细!$K:$K,薪酬明细!$D:$D,$E38,薪酬明细!$E:$E,$F38,薪酬明细!$H:$H,">="&AX$9,薪酬明细!$H:$H,"<="&AX$10,薪酬明细!$A:$A,AX$6) -> 3 | AY38: =SUMIFS(薪酬明细!$K:$K,薪酬明细!$D:$D,$E38,薪酬明细!$E:$E,$F38,薪酬明细!$H:$H,">="&AY$9,薪酬明细!$H:$H,"<="&AY$10,薪酬明细!$A:$A,AY$6) -> 3 | AZ38: =SUMIFS(薪酬明细!$K:$K,薪酬明细!$D:$D,$E38,薪酬明细!$E:$E,$F38,薪酬明细!$H:$H,">="&AZ$9,薪酬明细!$H:$H,"<="&AZ$10,薪酬明细!$A:$A,AZ$6) -> 3 | BA38: =SUMIFS(薪酬明细!$K:$K,薪酬明细!$D:$D,$E38,薪酬明细!$E:$E,$F38,薪酬明细!$H:$H,">="&BA$9,薪酬明细!$H:$H,"<="&BA$10,薪酬明细!$A:$A,BA$6) -> 3 | BB38: =SUMIFS(薪酬明细!$K:$K,薪酬明细!$D:$D,$E38,薪酬明细!$E:$E,$F38,薪酬明细!$H:$H,">="&BB$9,薪酬明细!$H:$H,"<="&BB$10,薪酬明细!$A:$A,BB$6) -> 3 | BC38: =SUMIFS(薪酬明细!$K:$K,薪酬明细!$D:$D,$E38,薪酬明细!$E:$E,$F38,薪酬明细!$H:$H,">="&BC$9,薪酬明细!$H:$H,"<="&BC$10,薪酬明细!$A:$A,BC$6) -> 3 | ... BG38: =SUMIFS(薪酬明细!$K:$K,薪酬明细!$D:$D,$E38,薪酬明细!$E:$E,$F38,薪酬明细!$H:$H,">="&BG$9,薪酬明细!$H:$H,"<="&BG$10,薪酬明细!$A:$A,BG$6) -> 3
D39: 总经办 | E39: =IF(C39<>"",C39,E38) -> 支持中心 | F39: =IF(D39<>"",D39,"*") -> 总经办 | G39: =SUMIFS(薪酬明细!$K:$K,薪酬明细!$D:$D,$E39,薪酬明细!$E:$E,$F39,薪酬明细!$H:$H,">="&G$9,薪酬明细!$H:$H,"<="&G$10,薪酬明细!$A:$A,G$6)/12 -> 1 | H39: =SUMIFS(薪酬明细!$K:$K,薪酬明细!$D:$D,$E39,薪酬明细!$E:$E,$F39,薪酬明细!$H:$H,">="&H$9,薪酬明细!$H:$H,"<="&H$10,薪酬明细!$A:$A,H$6) -> 1 | I39: =SUMIFS(薪酬明细!$K:$K,薪酬明细!$D:$D,$E39,薪酬明细!$E:$E,$F39,薪酬明细!$H:$H,">="&I$9,薪酬明细!$H:$H,"<="&I$10,薪酬明细!$A:$A,I$6) -> 1 | J39: =SUMIFS(薪酬明细!$K:$K,薪酬明细!$D:$D,$E39,薪酬明细!$E:$E,$F39,薪酬明细!$H:$H,">="&J$9,薪酬明细!$H:$H,"<="&J$10,薪酬明细!$A:$A,J$6) -> 1 | K39: =SUMIFS(薪酬明细!$K:$K,薪酬明细!$D:$D,$E39,薪酬明细!$E:$E,$F39,薪酬明细!$H:$H,">="&K$9,薪酬明细!$H:$H,"<="&K$10,薪酬明细!$A:$A,K$6) -> 1 | L39: =SUMIFS(薪酬明细!$K:$K,薪酬明细!$D:$D,$E39,薪酬明细!$E:$E,$F39,薪酬明细!$H:$H,">="&L$9,薪酬明细!$H:$H,"<="&L$10,薪酬明细!$A:$A,L$6) -> 1 | M39: =SUMIFS(薪酬明细!$K:$K,薪酬明细!$D:$D,$E39,薪酬明细!$E:$E,$F39,薪酬明细!$H:$H,">="&M$9,薪酬明细!$H:$H,"<="&M$10,薪酬明细!$A:$A,M$6) -> 1 | N39: =SUMIFS(薪酬明细!$K:$K,薪酬明细!$D:$D,$E39,薪酬明细!$E:$E,$F39,薪酬明细!$H:$H,">="&N$9,薪酬明细!$H:$H,"<="&N$10,薪酬明细!$A:$A,N$6) -> 1 | O39: =SUMIFS(薪酬明细!$K:$K,薪酬明细!$D:$D,$E39,薪酬明细!$E:$E,$F39,薪酬明细!$H:$H,">="&O$9,薪酬明细!$H:$H,"<="&O$10,薪酬明细!$A:$A,O$6) -> 1 | ... S39: =SUMIFS(薪酬明细!$K:$K,薪酬明细!$D:$D,$E39,薪酬明细!$E:$E,$F39,薪酬明细!$H:$H,">="&S$9,薪酬明细!$H:$H,"<="&S$10,薪酬明细!$A:$A,S$6) -> 1 | T39: =(U39*MONTH($G$3)+AH39*(12-MONTH($G$3)))/12 -> 1 | U39: =SUMIFS(薪酬明细!$K:$K,薪酬明细!$D:$D,$E39,薪酬明细!$E:$E,$F39,薪酬明细!$H:$H,">="&U$9,薪酬明细!$H:$H,"<="&U$10,薪酬明细!$A:$A,U$6)/MONTH($G$3) -> 1 | V39: =SUMIFS(薪酬明细!$K:$K,薪酬明细!$D:$D,$E39,薪酬明细!$E:$E,$F39,薪酬明细!$H:$H,">="&V$9,薪酬明细!$H:$H,"<="&V$10,薪酬明细!$A:$A,V$6) -> 1 | W39: =SUMIFS(薪酬明细!$K:$K,薪酬明细!$D:$D,$E39,薪酬明细!$E:$E,$F39,薪酬明细!$H:$H,">="&W$9,薪酬明细!$H:$H,"<="&W$10,薪酬明细!$A:$A,W$6) -> 1 | X39: =SUMIFS(薪酬明细!$K:$K,薪酬明细!$D:$D,$E39,薪酬明细!$E:$E,$F39,薪酬明细!$H:$H,">="&X$9,薪酬明细!$H:$H,"<="&X$10,薪酬明细!$A:$A,X$6) -> 1 | Y39: =SUMIFS(薪酬明细!$K:$K,薪酬明细!$D:$D,$E39,薪酬明细!$E:$E,$F39,薪酬明细!$H:$H,">="&Y$9,薪酬明细!$H:$H,"<="&Y$10,薪酬明细!$A:$A,Y$6) -> 1 | Z39: =SUMIFS(薪酬明细!$K:$K,薪酬明细!$D:$D,$E39,薪酬明细!$E:$E,$F39,薪酬明细!$H:$H,">="&Z$9,薪酬明细!$H:$H,"<="&Z$10,薪酬明细!$A:$A,Z$6) -> 1 | AA39: =SUMIFS(薪酬明细!$K:$K,薪酬明细!$D:$D,$E39,薪酬明细!$E:$E,$F39,薪酬明细!$H:$H,">="&AA$9,薪酬明细!$H:$H,"<="&AA$10,薪酬明细!$A:$A,AA$6) -> 1 | AB39: =SUMIFS(薪酬明细!$K:$K,薪酬明细!$D:$D,$E39,薪酬明细!$E:$E,$F39,薪酬明细!$H:$H,">="&AB$9,薪酬明细!$H:$H,"<="&AB$10,薪酬明细!$A:$A,AB$6) -> 1 | AC39: =SUMIFS(薪酬明细!$K:$K,薪酬明细!$D:$D,$E39,薪酬明细!$E:$E,$F39,薪酬明细!$H:$H,">="&AC$9,薪酬明细!$H:$H,"<="&AC$10,薪酬明细!$A:$A,AC$6) -> 1 | ... AG39: =SUMIFS(薪酬明细!$K:$K,薪酬明细!$D:$D,$E39,薪酬明细!$E:$E,$F39,薪酬明细!$H:$H,">="&AG$9,薪酬明细!$H:$H,"<="&AG$10,薪酬明细!$A:$A,AG$6) -> 0 | AH39: =SUMIFS(薪酬明细!$K:$K,薪酬明细!$D:$D,$E39,薪酬明细!$E:$E,$F39,薪酬明细!$H:$H,">="&AH$9,薪酬明细!$H:$H,"<="&AH$10,薪酬明细!$A:$A,AH$6)/(12-MONTH($G$3)) -> 1 | AI39: =SUMIFS(薪酬明细!$K:$K,薪酬明细!$D:$D,$E39,薪酬明细!$E:$E,$F39,薪酬明细!$H:$H,">="&AI$9,薪酬明细!$H:$H,"<="&AI$10,薪酬明细!$A:$A,AI$6) -> 0 | AJ39: =SUMIFS(薪酬明细!$K:$K,薪酬明细!$D:$D,$E39,薪酬明细!$E:$E,$F39,薪酬明细!$H:$H,">="&AJ$9,薪酬明细!$H:$H,"<="&AJ$10,薪酬明细!$A:$A,AJ$6) -> 0 | AK39: =SUMIFS(薪酬明细!$K:$K,薪酬明细!$D:$D,$E39,薪酬明细!$E:$E,$F39,薪酬明细!$H:$H,">="&AK$9,薪酬明细!$H:$H,"<="&AK$10,薪酬明细!$A:$A,AK$6) -> 0 | AL39: =SUMIFS(薪酬明细!$K:$K,薪酬明细!$D:$D,$E39,薪酬明细!$E:$E,$F39,薪酬明细!$H:$H,">="&AL$9,薪酬明细!$H:$H,"<="&AL$10,薪酬明细!$A:$A,AL$6) -> 0 | AM39: =SUMIFS(薪酬明细!$K:$K,薪酬明细!$D:$D,$E39,薪酬明细!$E:$E,$F39,薪酬明细!$H:$H,">="&AM$9,薪酬明细!$H:$H,"<="&AM$10,薪酬明细!$A:$A,AM$6) -> 0 | AN39: =SUMIFS(薪酬明细!$K:$K,薪酬明细!$D:$D,$E39,薪酬明细!$E:$E,$F39,薪酬明细!$H:$H,">="&AN$9,薪酬明细!$H:$H,"<="&AN$10,薪酬明细!$A:$A,AN$6) -> 0 | AO39: =SUMIFS(薪酬明细!$K:$K,薪酬明细!$D:$D,$E39,薪酬明细!$E:$E,$F39,薪酬明细!$H:$H,">="&AO$9,薪酬明细!$H:$H,"<="&AO$10,薪酬明细!$A:$A,AO$6) -> 0 | AP39: =SUMIFS(薪酬明细!$K:$K,薪酬明细!$D:$D,$E39,薪酬明细!$E:$E,$F39,薪酬明细!$H:$H,">="&AP$9,薪酬明细!$H:$H,"<="&AP$10,薪酬明细!$A:$A,AP$6) -> 0 | ... AT39: =SUMIFS(薪酬明细!$K:$K,薪酬明细!$D:$D,$E39,薪酬明细!$E:$E,$F39,薪酬明细!$H:$H,">="&AT$9,薪酬明细!$H:$H,"<="&AT$10,薪酬明细!$A:$A,AT$6) -> 1 | AU39: =SUMIFS(薪酬明细!$K:$K,薪酬明细!$D:$D,$E39,薪酬明细!$E:$E,$F39,薪酬明细!$H:$H,">="&AU$9,薪酬明细!$H:$H,"<="&AU$10,薪酬明细!$A:$A,AU$6)/12 -> 1 | AV39: =SUMIFS(薪酬明细!$K:$K,薪酬明细!$D:$D,$E39,薪酬明细!$E:$E,$F39,薪酬明细!$H:$H,">="&AV$9,薪酬明细!$H:$H,"<="&AV$10,薪酬明细!$A:$A,AV$6) -> 1 | AW39: =SUMIFS(薪酬明细!$K:$K,薪酬明细!$D:$D,$E39,薪酬明细!$E:$E,$F39,薪酬明细!$H:$H,">="&AW$9,薪酬明细!$H:$H,"<="&AW$10,薪酬明细!$A:$A,AW$6) -> 1 | AX39: =SUMIFS(薪酬明细!$K:$K,薪酬明细!$D:$D,$E39,薪酬明细!$E:$E,$F39,薪酬明细!$H:$H,">="&AX$9,薪酬明细!$H:$H,"<="&AX$10,薪酬明细!$A:$A,AX$6) -> 1 | AY39: =SUMIFS(薪酬明细!$K:$K,薪酬明细!$D:$D,$E39,薪酬明细!$E:$E,$F39,薪酬明细!$H:$H,">="&AY$9,薪酬明细!$H:$H,"<="&AY$10,薪酬明细!$A:$A,AY$6) -> 1 | AZ39: =SUMIFS(薪酬明细!$K:$K,薪酬明细!$D:$D,$E39,薪酬明细!$E:$E,$F39,薪酬明细!$H:$H,">="&AZ$9,薪酬明细!$H:$H,"<="&AZ$10,薪酬明细!$A:$A,AZ$6) -> 1 | BA39: =SUMIFS(薪酬明细!$K:$K,薪酬明细!$D:$D,$E39,薪酬明细!$E:$E,$F39,薪酬明细!$H:$H,">="&BA$9,薪酬明细!$H:$H,"<="&BA$10,薪酬明细!$A:$A,BA$6) -> 1 | BB39: =SUMIFS(薪酬明细!$K:$K,薪酬明细!$D:$D,$E39,薪酬明细!$E:$E,$F39,薪酬明细!$H:$H,">="&BB$9,薪酬明细!$H:$H,"<="&BB$10,薪酬明细!$A:$A,BB$6) -> 1 | BC39: =SUMIFS(薪酬明细!$K:$K,薪酬明细!$D:$D,$E39,薪酬明细!$E:$E,$F39,薪酬明细!$H:$H,">="&BC$9,薪酬明细!$H:$H,"<="&BC$10,薪酬明细!$A:$A,BC$6) -> 1 | ... BG39: =SUMIFS(薪酬明细!$K:$K,薪酬明细!$D:$D,$E39,薪酬明细!$E:$E,$F39,薪酬明细!$H:$H,">="&BG$9,薪酬明细!$H:$H,"<="&BG$10,薪酬明细!$A:$A,BG$6) -> 1
B41: 固定工资
B42: 合计 | E42: * | F42: * | G42: =SUMIFS(薪酬明细!$L:$L,薪酬明细!$D:$D,$E42,薪酬明细!$E:$E,$F42,薪酬明细!$H:$H,">="&G$9,薪酬明细!$H:$H,"<="&G$10,薪酬明细!$A:$A,G$6)/10000 -> 710.1 | H42: =SUMIFS(薪酬明细!$L:$L,薪酬明细!$D:$D,$E42,薪酬明细!$E:$E,$F42,薪酬明细!$H:$H,">="&H$9,薪酬明细!$H:$H,"<="&H$10,薪酬明细!$A:$A,H$6)/10000 -> 59.3 | I42: =SUMIFS(薪酬明细!$L:$L,薪酬明细!$D:$D,$E42,薪酬明细!$E:$E,$F42,薪酬明细!$H:$H,">="&I$9,薪酬明细!$H:$H,"<="&I$10,薪酬明细!$A:$A,I$6)/10000 -> 59.1 | J42: =SUMIFS(薪酬明细!$L:$L,薪酬明细!$D:$D,$E42,薪酬明细!$E:$E,$F42,薪酬明细!$H:$H,">="&J$9,薪酬明细!$H:$H,"<="&J$10,薪酬明细!$A:$A,J$6)/10000 -> 59.1 | K42: =SUMIFS(薪酬明细!$L:$L,薪酬明细!$D:$D,$E42,薪酬明细!$E:$E,$F42,薪酬明细!$H:$H,">="&K$9,薪酬明细!$H:$H,"<="&K$10,薪酬明细!$A:$A,K$6)/10000 -> 59.1 | L42: =SUMIFS(薪酬明细!$L:$L,薪酬明细!$D:$D,$E42,薪酬明细!$E:$E,$F42,薪酬明细!$H:$H,">="&L$9,薪酬明细!$H:$H,"<="&L$10,薪酬明细!$A:$A,L$6)/10000 -> 59.1 | M42: =SUMIFS(薪酬明细!$L:$L,薪酬明细!$D:$D,$E42,薪酬明细!$E:$E,$F42,薪酬明细!$H:$H,">="&M$9,薪酬明细!$H:$H,"<="&M$10,薪酬明细!$A:$A,M$6)/10000 -> 59.3 | N42: =SUMIFS(薪酬明细!$L:$L,薪酬明细!$D:$D,$E42,薪酬明细!$E:$E,$F42,薪酬明细!$H:$H,">="&N$9,薪酬明细!$H:$H,"<="&N$10,薪酬明细!$A:$A,N$6)/10000 -> 59.4 | ... S42: =SUMIFS(薪酬明细!$L:$L,薪酬明细!$D:$D,$E42,薪酬明细!$E:$E,$F42,薪酬明细!$H:$H,">="&S$9,薪酬明细!$H:$H,"<="&S$10,薪酬明细!$A:$A,S$6)/10000 -> 59.1 | T42: =U42+AH42 -> 710.1 | U42: =SUMIFS(薪酬明细!$L:$L,薪酬明细!$D:$D,$E42,薪酬明细!$E:$E,$F42,薪酬明细!$H:$H,">="&U$9,薪酬明细!$H:$H,"<="&U$10,薪酬明细!$A:$A,U$6)/10000 -> 532.4 | V42: =SUMIFS(薪酬明细!$L:$L,薪酬明细!$D:$D,$E42,薪酬明细!$E:$E,$F42,薪酬明细!$H:$H,">="&V$9,薪酬明细!$H:$H,"<="&V$10,薪酬明细!$A:$A,V$6)/10000 -> 59.3 | W42: =SUMIFS(薪酬明细!$L:$L,薪酬明细!$D:$D,$E42,薪酬明细!$E:$E,$F42,薪酬明细!$H:$H,">="&W$9,薪酬明细!$H:$H,"<="&W$10,薪酬明细!$A:$A,W$6)/10000 -> 59.2 | X42: =SUMIFS(薪酬明细!$L:$L,薪酬明细!$D:$D,$E42,薪酬明细!$E:$E,$F42,薪酬明细!$H:$H,">="&X$9,薪酬明细!$H:$H,"<="&X$10,薪酬明细!$A:$A,X$6)/10000 -> 59.2 | Y42: =SUMIFS(薪酬明细!$L:$L,薪酬明细!$D:$D,$E42,薪酬明细!$E:$E,$F42,薪酬明细!$H:$H,">="&Y$9,薪酬明细!$H:$H,"<="&Y$10,薪酬明细!$A:$A,Y$6)/10000 -> 59.2 | Z42: =SUMIFS(薪酬明细!$L:$L,薪酬明细!$D:$D,$E42,薪酬明细!$E:$E,$F42,薪酬明细!$H:$H,">="&Z$9,薪酬明细!$H:$H,"<="&Z$10,薪酬明细!$A:$A,Z$6)/10000 -> 58.8 | AA42: =SUMIFS(薪酬明细!$L:$L,薪酬明细!$D:$D,$E42,薪酬明细!$E:$E,$F42,薪酬明细!$H:$H,">="&AA$9,薪酬明细!$H:$H,"<="&AA$10,薪酬明细!$A:$A,AA$6)/10000 -> 59.1 | AB42: =SUMIFS(薪酬明细!$L:$L,薪酬明细!$D:$D,$E42,薪酬明细!$E:$E,$F42,薪酬明细!$H:$H,">="&AB$9,薪酬明细!$H:$H,"<="&AB$10,薪酬明细!$A:$A,AB$6)/10000 -> 59.1 | ... BG42: =SUMIFS(薪酬明细!$L:$L,薪酬明细!$D:$D,$E42,薪酬明细!$E:$E,$F42,薪酬明细!$H:$H,">="&BG$9,薪酬明细!$H:$H,"<="&BG$10,薪酬明细!$A:$A,BG$6)/10000 -> 58.9
C43: 流程中心 | E43: =IF(C43<>"",C43,E10) -> 流程中心 | F43: =IF(D43<>"",D43,"*") -> * | G43: =SUMIFS(薪酬明细!$L:$L,薪酬明细!$D:$D,$E43,薪酬明细!$E:$E,$F43,薪酬明细!$H:$H,">="&G$9,薪酬明细!$H:$H,"<="&G$10,薪酬明细!$A:$A,G$6)/10000 -> 261.5 | H43: =SUMIFS(薪酬明细!$L:$L,薪酬明细!$D:$D,$E43,薪酬明细!$E:$E,$F43,薪酬明细!$H:$H,">="&H$9,薪酬明细!$H:$H,"<="&H$10,薪酬明细!$A:$A,H$6)/10000 -> 21.7 | I43: =SUMIFS(薪酬明细!$L:$L,薪酬明细!$D:$D,$E43,薪酬明细!$E:$E,$F43,薪酬明细!$H:$H,">="&I$9,薪酬明细!$H:$H,"<="&I$10,薪酬明细!$A:$A,I$6)/10000 -> 21.7 | J43: =SUMIFS(薪酬明细!$L:$L,薪酬明细!$D:$D,$E43,薪酬明细!$E:$E,$F43,薪酬明细!$H:$H,">="&J$9,薪酬明细!$H:$H,"<="&J$10,薪酬明细!$A:$A,J$6)/10000 -> 21.9 | K43: =SUMIFS(薪酬明细!$L:$L,薪酬明细!$D:$D,$E43,薪酬明细!$E:$E,$F43,薪酬明细!$H:$H,">="&K$9,薪酬明细!$H:$H,"<="&K$10,薪酬明细!$A:$A,K$6)/10000 -> 21.7 | L43: =SUMIFS(薪酬明细!$L:$L,薪酬明细!$D:$D,$E43,薪酬明细!$E:$E,$F43,薪酬明细!$H:$H,">="&L$9,薪酬明细!$H:$H,"<="&L$10,薪酬明细!$A:$A,L$6)/10000 -> 21.9 | M43: =SUMIFS(薪酬明细!$L:$L,薪酬明细!$D:$D,$E43,薪酬明细!$E:$E,$F43,薪酬明细!$H:$H,">="&M$9,薪酬明细!$H:$H,"<="&M$10,薪酬明细!$A:$A,M$6)/10000 -> 21.7 | N43: =SUMIFS(薪酬明细!$L:$L,薪酬明细!$D:$D,$E43,薪酬明细!$E:$E,$F43,薪酬明细!$H:$H,">="&N$9,薪酬明细!$H:$H,"<="&N$10,薪酬明细!$A:$A,N$6)/10000 -> 21.9 | ... S43: =SUMIFS(薪酬明细!$L:$L,薪酬明细!$D:$D,$E43,薪酬明细!$E:$E,$F43,薪酬明细!$H:$H,">="&S$9,薪酬明细!$H:$H,"<="&S$10,薪酬明细!$A:$A,S$6)/10000 -> 21.7 | T43: =U43+AH43 -> 260.5 | U43: =SUMIFS(薪酬明细!$L:$L,薪酬明细!$D:$D,$E43,薪酬明细!$E:$E,$F43,薪酬明细!$H:$H,">="&U$9,薪酬明细!$H:$H,"<="&U$10,薪酬明细!$A:$A,U$6)/10000 -> 195.4 | V43: =SUMIFS(薪酬明细!$L:$L,薪酬明细!$D:$D,$E43,薪酬明细!$E:$E,$F43,薪酬明细!$H:$H,">="&V$9,薪酬明细!$H:$H,"<="&V$10,薪酬明细!$A:$A,V$6)/10000 -> 21.9 | W43: =SUMIFS(薪酬明细!$L:$L,薪酬明细!$D:$D,$E43,薪酬明细!$E:$E,$F43,薪酬明细!$H:$H,">="&W$9,薪酬明细!$H:$H,"<="&W$10,薪酬明细!$A:$A,W$6)/10000 -> 21.7 | X43: =SUMIFS(薪酬明细!$L:$L,薪酬明细!$D:$D,$E43,薪酬明细!$E:$E,$F43,薪酬明细!$H:$H,">="&X$9,薪酬明细!$H:$H,"<="&X$10,薪酬明细!$A:$A,X$6)/10000 -> 21.6 | Y43: =SUMIFS(薪酬明细!$L:$L,薪酬明细!$D:$D,$E43,薪酬明细!$E:$E,$F43,薪酬明细!$H:$H,">="&Y$9,薪酬明细!$H:$H,"<="&Y$10,薪酬明细!$A:$A,Y$6)/10000 -> 21.8 | Z43: =SUMIFS(薪酬明细!$L:$L,薪酬明细!$D:$D,$E43,薪酬明细!$E:$E,$F43,薪酬明细!$H:$H,">="&Z$9,薪酬明细!$H:$H,"<="&Z$10,薪酬明细!$A:$A,Z$6)/10000 -> 21.5 | AA43: =SUMIFS(薪酬明细!$L:$L,薪酬明细!$D:$D,$E43,薪酬明细!$E:$E,$F43,薪酬明细!$H:$H,">="&AA$9,薪酬明细!$H:$H,"<="&AA$10,薪酬明细!$A:$A,AA$6)/10000 -> 21.6 | AB43: =SUMIFS(薪酬明细!$L:$L,薪酬明细!$D:$D,$E43,薪酬明细!$E:$E,$F43,薪酬明细!$H:$H,">="&AB$9,薪酬明细!$H:$H,"<="&AB$10,薪酬明细!$A:$A,AB$6)/10000 -> 21.6 | ... BG43: =SUMIFS(薪酬明细!$L:$L,薪酬明细!$D:$D,$E43,薪酬明细!$E:$E,$F43,薪酬明细!$H:$H,">="&BG$9,薪酬明细!$H:$H,"<="&BG$10,薪酬明细!$A:$A,BG$6)/10000 -> 21.7
D44: 销售中心 | E44: =IF(C44<>"",C44,E43) -> 流程中心 | F44: =IF(D44<>"",D44,"*") -> 销售中心 | G44: =SUMIFS(薪酬明细!$L:$L,薪酬明细!$D:$D,$E44,薪酬明细!$E:$E,$F44,薪酬明细!$H:$H,">="&G$9,薪酬明细!$H:$H,"<="&G$10,薪酬明细!$A:$A,G$6)/10000 -> 151.6 | H44: =SUMIFS(薪酬明细!$L:$L,薪酬明细!$D:$D,$E44,薪酬明细!$E:$E,$F44,薪酬明细!$H:$H,">="&H$9,薪酬明细!$H:$H,"<="&H$10,薪酬明细!$A:$A,H$6)/10000 -> 12.5 | I44: =SUMIFS(薪酬明细!$L:$L,薪酬明细!$D:$D,$E44,薪酬明细!$E:$E,$F44,薪酬明细!$H:$H,">="&I$9,薪酬明细!$H:$H,"<="&I$10,薪酬明细!$A:$A,I$6)/10000 -> 12.5 | J44: =SUMIFS(薪酬明细!$L:$L,薪酬明细!$D:$D,$E44,薪酬明细!$E:$E,$F44,薪酬明细!$H:$H,">="&J$9,薪酬明细!$H:$H,"<="&J$10,薪酬明细!$A:$A,J$6)/10000 -> 12.7 | K44: =SUMIFS(薪酬明细!$L:$L,薪酬明细!$D:$D,$E44,薪酬明细!$E:$E,$F44,薪酬明细!$H:$H,">="&K$9,薪酬明细!$H:$H,"<="&K$10,薪酬明细!$A:$A,K$6)/10000 -> 12.5 | L44: =SUMIFS(薪酬明细!$L:$L,薪酬明细!$D:$D,$E44,薪酬明细!$E:$E,$F44,薪酬明细!$H:$H,">="&L$9,薪酬明细!$H:$H,"<="&L$10,薪酬明细!$A:$A,L$6)/10000 -> 12.7 | M44: =SUMIFS(薪酬明细!$L:$L,薪酬明细!$D:$D,$E44,薪酬明细!$E:$E,$F44,薪酬明细!$H:$H,">="&M$9,薪酬明细!$H:$H,"<="&M$10,薪酬明细!$A:$A,M$6)/10000 -> 12.6 | N44: =SUMIFS(薪酬明细!$L:$L,薪酬明细!$D:$D,$E44,薪酬明细!$E:$E,$F44,薪酬明细!$H:$H,">="&N$9,薪酬明细!$H:$H,"<="&N$10,薪酬明细!$A:$A,N$6)/10000 -> 12.6 | ... S44: =SUMIFS(薪酬明细!$L:$L,薪酬明细!$D:$D,$E44,薪酬明细!$E:$E,$F44,薪酬明细!$H:$H,">="&S$9,薪酬明细!$H:$H,"<="&S$10,薪酬明细!$A:$A,S$6)/10000 -> 12.6 | T44: =U44+AH44 -> 151.1 | U44: =SUMIFS(薪酬明细!$L:$L,薪酬明细!$D:$D,$E44,薪酬明细!$E:$E,$F44,薪酬明细!$H:$H,">="&U$9,薪酬明细!$H:$H,"<="&U$10,薪酬明细!$A:$A,U$6)/10000 -> 113.1 | V44: =SUMIFS(薪酬明细!$L:$L,薪酬明细!$D:$D,$E44,薪酬明细!$E:$E,$F44,薪酬明细!$H:$H,">="&V$9,薪酬明细!$H:$H,"<="&V$10,薪酬明细!$A:$A,V$6)/10000 -> 12.8 | W44: =SUMIFS(薪酬明细!$L:$L,薪酬明细!$D:$D,$E44,薪酬明细!$E:$E,$F44,薪酬明细!$H:$H,">="&W$9,薪酬明细!$H:$H,"<="&W$10,薪酬明细!$A:$A,W$6)/10000 -> 12.6 | X44: =SUMIFS(薪酬明细!$L:$L,薪酬明细!$D:$D,$E44,薪酬明细!$E:$E,$F44,薪酬明细!$H:$H,">="&X$9,薪酬明细!$H:$H,"<="&X$10,薪酬明细!$A:$A,X$6)/10000 -> 12.4 | Y44: =SUMIFS(薪酬明细!$L:$L,薪酬明细!$D:$D,$E44,薪酬明细!$E:$E,$F44,薪酬明细!$H:$H,">="&Y$9,薪酬明细!$H:$H,"<="&Y$10,薪酬明细!$A:$A,Y$6)/10000 -> 12.6 | Z44: =SUMIFS(薪酬明细!$L:$L,薪酬明细!$D:$D,$E44,薪酬明细!$E:$E,$F44,薪酬明细!$H:$H,">="&Z$9,薪酬明细!$H:$H,"<="&Z$10,薪酬明细!$A:$A,Z$6)/10000 -> 12.5 | AA44: =SUMIFS(薪酬明细!$L:$L,薪酬明细!$D:$D,$E44,薪酬明细!$E:$E,$F44,薪酬明细!$H:$H,">="&AA$9,薪酬明细!$H:$H,"<="&AA$10,薪酬明细!$A:$A,AA$6)/10000 -> 12.6 | AB44: =SUMIFS(薪酬明细!$L:$L,薪酬明细!$D:$D,$E44,薪酬明细!$E:$E,$F44,薪酬明细!$H:$H,">="&AB$9,薪酬明细!$H:$H,"<="&AB$10,薪酬明细!$A:$A,AB$6)/10000 -> 12.4 | ... BG44: =SUMIFS(薪酬明细!$L:$L,薪酬明细!$D:$D,$E44,薪酬明细!$E:$E,$F44,薪酬明细!$H:$H,">="&BG$9,薪酬明细!$H:$H,"<="&BG$10,薪酬明细!$A:$A,BG$6)/10000 -> 12.5
D45: 制造中心 | E45: =IF(C45<>"",C45,E44) -> 流程中心 | F45: =IF(D45<>"",D45,"*") -> 制造中心 | G45: =SUMIFS(薪酬明细!$L:$L,薪酬明细!$D:$D,$E45,薪酬明细!$E:$E,$F45,薪酬明细!$H:$H,">="&G$9,薪酬明细!$H:$H,"<="&G$10,薪酬明细!$A:$A,G$6)/10000 -> 109.9 | H45: =SUMIFS(薪酬明细!$L:$L,薪酬明细!$D:$D,$E45,薪酬明细!$E:$E,$F45,薪酬明细!$H:$H,">="&H$9,薪酬明细!$H:$H,"<="&H$10,薪酬明细!$A:$A,H$6)/10000 -> 9.2 | I45: =SUMIFS(薪酬明细!$L:$L,薪酬明细!$D:$D,$E45,薪酬明细!$E:$E,$F45,薪酬明细!$H:$H,">="&I$9,薪酬明细!$H:$H,"<="&I$10,薪酬明细!$A:$A,I$6)/10000 -> 9.2 | J45: =SUMIFS(薪酬明细!$L:$L,薪酬明细!$D:$D,$E45,薪酬明细!$E:$E,$F45,薪酬明细!$H:$H,">="&J$9,薪酬明细!$H:$H,"<="&J$10,薪酬明细!$A:$A,J$6)/10000 -> 9.2 | K45: =SUMIFS(薪酬明细!$L:$L,薪酬明细!$D:$D,$E45,薪酬明细!$E:$E,$F45,薪酬明细!$H:$H,">="&K$9,薪酬明细!$H:$H,"<="&K$10,薪酬明细!$A:$A,K$6)/10000 -> 9.1 | L45: =SUMIFS(薪酬明细!$L:$L,薪酬明细!$D:$D,$E45,薪酬明细!$E:$E,$F45,薪酬明细!$H:$H,">="&L$9,薪酬明细!$H:$H,"<="&L$10,薪酬明细!$A:$A,L$6)/10000 -> 9.2 | M45: =SUMIFS(薪酬明细!$L:$L,薪酬明细!$D:$D,$E45,薪酬明细!$E:$E,$F45,薪酬明细!$H:$H,">="&M$9,薪酬明细!$H:$H,"<="&M$10,薪酬明细!$A:$A,M$6)/10000 -> 9.1 | N45: =SUMIFS(薪酬明细!$L:$L,薪酬明细!$D:$D,$E45,薪酬明细!$E:$E,$F45,薪酬明细!$H:$H,">="&N$9,薪酬明细!$H:$H,"<="&N$10,薪酬明细!$A:$A,N$6)/10000 -> 9.3 | ... S45: =SUMIFS(薪酬明细!$L:$L,薪酬明细!$D:$D,$E45,薪酬明细!$E:$E,$F45,薪酬明细!$H:$H,">="&S$9,薪酬明细!$H:$H,"<="&S$10,薪酬明细!$A:$A,S$6)/10000 -> 9.1 | T45: =U45+AH45 -> 109.4 | U45: =SUMIFS(薪酬明细!$L:$L,薪酬明细!$D:$D,$E45,薪酬明细!$E:$E,$F45,薪酬明细!$H:$H,">="&U$9,薪酬明细!$H:$H,"<="&U$10,薪酬明细!$A:$A,U$6)/10000 -> 82.3 | V45: =SUMIFS(薪酬明细!$L:$L,薪酬明细!$D:$D,$E45,薪酬明细!$E:$E,$F45,薪酬明细!$H:$H,">="&V$9,薪酬明细!$H:$H,"<="&V$10,薪酬明细!$A:$A,V$6)/10000 -> 9.1 | W45: =SUMIFS(薪酬明细!$L:$L,薪酬明细!$D:$D,$E45,薪酬明细!$E:$E,$F45,薪酬明细!$H:$H,">="&W$9,薪酬明细!$H:$H,"<="&W$10,薪酬明细!$A:$A,W$6)/10000 -> 9.1 | X45: =SUMIFS(薪酬明细!$L:$L,薪酬明细!$D:$D,$E45,薪酬明细!$E:$E,$F45,薪酬明细!$H:$H,">="&X$9,薪酬明细!$H:$H,"<="&X$10,薪酬明细!$A:$A,X$6)/10000 -> 9.2 | Y45: =SUMIFS(薪酬明细!$L:$L,薪酬明细!$D:$D,$E45,薪酬明细!$E:$E,$F45,薪酬明细!$H:$H,">="&Y$9,薪酬明细!$H:$H,"<="&Y$10,薪酬明细!$A:$A,Y$6)/10000 -> 9.2 | Z45: =SUMIFS(薪酬明细!$L:$L,薪酬明细!$D:$D,$E45,薪酬明细!$E:$E,$F45,薪酬明细!$H:$H,">="&Z$9,薪酬明细!$H:$H,"<="&Z$10,薪酬明细!$A:$A,Z$6)/10000 -> 9 | AA45: =SUMIFS(薪酬明细!$L:$L,薪酬明细!$D:$D,$E45,薪酬明细!$E:$E,$F45,薪酬明细!$H:$H,">="&AA$9,薪酬明细!$H:$H,"<="&AA$10,薪酬明细!$A:$A,AA$6)/10000 -> 9 | AB45: =SUMIFS(薪酬明细!$L:$L,薪酬明细!$D:$D,$E45,薪酬明细!$E:$E,$F45,薪酬明细!$H:$H,">="&AB$9,薪酬明细!$H:$H,"<="&AB$10,薪酬明细!$A:$A,AB$6)/10000 -> 9.2 | ... BG45: =SUMIFS(薪酬明细!$L:$L,薪酬明细!$D:$D,$E45,薪酬明细!$E:$E,$F45,薪酬明细!$H:$H,">="&BG$9,薪酬明细!$H:$H,"<="&BG$10,薪酬明细!$A:$A,BG$6)/10000 -> 9.2
C46: 创新中心 | E46: =IF(C46<>"",C46,E45) -> 创新中心 | F46: =IF(D46<>"",D46,"*") -> * | G46: =SUMIFS(薪酬明细!$L:$L,薪酬明细!$D:$D,$E46,薪酬明细!$E:$E,$F46,薪酬明细!$H:$H,">="&G$9,薪酬明细!$H:$H,"<="&G$10,薪酬明细!$A:$A,G$6)/10000 -> 240 | H46: =SUMIFS(薪酬明细!$L:$L,薪酬明细!$D:$D,$E46,薪酬明细!$E:$E,$F46,薪酬明细!$H:$H,">="&H$9,薪酬明细!$H:$H,"<="&H$10,薪酬明细!$A:$A,H$6)/10000 -> 20.1 | I46: =SUMIFS(薪酬明细!$L:$L,薪酬明细!$D:$D,$E46,薪酬明细!$E:$E,$F46,薪酬明细!$H:$H,">="&I$9,薪酬明细!$H:$H,"<="&I$10,薪酬明细!$A:$A,I$6)/10000 -> 20.1 | J46: =SUMIFS(薪酬明细!$L:$L,薪酬明细!$D:$D,$E46,薪酬明细!$E:$E,$F46,薪酬明细!$H:$H,">="&J$9,薪酬明细!$H:$H,"<="&J$10,薪酬明细!$A:$A,J$6)/10000 -> 20 | K46: =SUMIFS(薪酬明细!$L:$L,薪酬明细!$D:$D,$E46,薪酬明细!$E:$E,$F46,薪酬明细!$H:$H,">="&K$9,薪酬明细!$H:$H,"<="&K$10,薪酬明细!$A:$A,K$6)/10000 -> 20 | L46: =SUMIFS(薪酬明细!$L:$L,薪酬明细!$D:$D,$E46,薪酬明细!$E:$E,$F46,薪酬明细!$H:$H,">="&L$9,薪酬明细!$H:$H,"<="&L$10,薪酬明细!$A:$A,L$6)/10000 -> 20 | M46: =SUMIFS(薪酬明细!$L:$L,薪酬明细!$D:$D,$E46,薪酬明细!$E:$E,$F46,薪酬明细!$H:$H,">="&M$9,薪酬明细!$H:$H,"<="&M$10,薪酬明细!$A:$A,M$6)/10000 -> 20.2 | N46: =SUMIFS(薪酬明细!$L:$L,薪酬明细!$D:$D,$E46,薪酬明细!$E:$E,$F46,薪酬明细!$H:$H,">="&N$9,薪酬明细!$H:$H,"<="&N$10,薪酬明细!$A:$A,N$6)/10000 -> 19.9 | ... S46: =SUMIFS(薪酬明细!$L:$L,薪酬明细!$D:$D,$E46,薪酬明细!$E:$E,$F46,薪酬明细!$H:$H,">="&S$9,薪酬明细!$H:$H,"<="&S$10,薪酬明细!$A:$A,S$6)/10000 -> 19.9 | T46: =U46+AH46 -> 240.4 | U46: =SUMIFS(薪酬明细!$L:$L,薪酬明细!$D:$D,$E46,薪酬明细!$E:$E,$F46,薪酬明细!$H:$H,">="&U$9,薪酬明细!$H:$H,"<="&U$10,薪酬明细!$A:$A,U$6)/10000 -> 180.3 | V46: =SUMIFS(薪酬明细!$L:$L,薪酬明细!$D:$D,$E46,薪酬明细!$E:$E,$F46,薪酬明细!$H:$H,">="&V$9,薪酬明细!$H:$H,"<="&V$10,薪酬明细!$A:$A,V$6)/10000 -> 19.9 | W46: =SUMIFS(薪酬明细!$L:$L,薪酬明细!$D:$D,$E46,薪酬明细!$E:$E,$F46,薪酬明细!$H:$H,">="&W$9,薪酬明细!$H:$H,"<="&W$10,薪酬明细!$A:$A,W$6)/10000 -> 20.2 | X46: =SUMIFS(薪酬明细!$L:$L,薪酬明细!$D:$D,$E46,薪酬明细!$E:$E,$F46,薪酬明细!$H:$H,">="&X$9,薪酬明细!$H:$H,"<="&X$10,薪酬明细!$A:$A,X$6)/10000 -> 20.2 | Y46: =SUMIFS(薪酬明细!$L:$L,薪酬明细!$D:$D,$E46,薪酬明细!$E:$E,$F46,薪酬明细!$H:$H,">="&Y$9,薪酬明细!$H:$H,"<="&Y$10,薪酬明细!$A:$A,Y$6)/10000 -> 20 | Z46: =SUMIFS(薪酬明细!$L:$L,薪酬明细!$D:$D,$E46,薪酬明细!$E:$E,$F46,薪酬明细!$H:$H,">="&Z$9,薪酬明细!$H:$H,"<="&Z$10,薪酬明细!$A:$A,Z$6)/10000 -> 19.9 | AA46: =SUMIFS(薪酬明细!$L:$L,薪酬明细!$D:$D,$E46,薪酬明细!$E:$E,$F46,薪酬明细!$H:$H,">="&AA$9,薪酬明细!$H:$H,"<="&AA$10,薪酬明细!$A:$A,AA$6)/10000 -> 20 | AB46: =SUMIFS(薪酬明细!$L:$L,薪酬明细!$D:$D,$E46,薪酬明细!$E:$E,$F46,薪酬明细!$H:$H,">="&AB$9,薪酬明细!$H:$H,"<="&AB$10,薪酬明细!$A:$A,AB$6)/10000 -> 20 | ... BG46: =SUMIFS(薪酬明细!$L:$L,薪酬明细!$D:$D,$E46,薪酬明细!$E:$E,$F46,薪酬明细!$H:$H,">="&BG$9,薪酬明细!$H:$H,"<="&BG$10,薪酬明细!$A:$A,BG$6)/10000 -> 20.1
D47: 产品 研发部 | E47: =IF(C47<>"",C47,E46) -> 创新中心 | F47: =IF(D47<>"",D47,"*") -> 产品 研发部 | G47: =SUMIFS(薪酬明细!$L:$L,薪酬明细!$D:$D,$E47,薪酬明细!$E:$E,$F47,薪酬明细!$H:$H,">="&G$9,薪酬明细!$H:$H,"<="&G$10,薪酬明细!$A:$A,G$6)/10000 -> 82.9 | H47: =SUMIFS(薪酬明细!$L:$L,薪酬明细!$D:$D,$E47,薪酬明细!$E:$E,$F47,薪酬明细!$H:$H,">="&H$9,薪酬明细!$H:$H,"<="&H$10,薪酬明细!$A:$A,H$6)/10000 -> 6.9 | I47: =SUMIFS(薪酬明细!$L:$L,薪酬明细!$D:$D,$E47,薪酬明细!$E:$E,$F47,薪酬明细!$H:$H,">="&I$9,薪酬明细!$H:$H,"<="&I$10,薪酬明细!$A:$A,I$6)/10000 -> 6.9 | J47: =SUMIFS(薪酬明细!$L:$L,薪酬明细!$D:$D,$E47,薪酬明细!$E:$E,$F47,薪酬明细!$H:$H,">="&J$9,薪酬明细!$H:$H,"<="&J$10,薪酬明细!$A:$A,J$6)/10000 -> 6.8 | K47: =SUMIFS(薪酬明细!$L:$L,薪酬明细!$D:$D,$E47,薪酬明细!$E:$E,$F47,薪酬明细!$H:$H,">="&K$9,薪酬明细!$H:$H,"<="&K$10,薪酬明细!$A:$A,K$6)/10000 -> 6.9 | L47: =SUMIFS(薪酬明细!$L:$L,薪酬明细!$D:$D,$E47,薪酬明细!$E:$E,$F47,薪酬明细!$H:$H,">="&L$9,薪酬明细!$H:$H,"<="&L$10,薪酬明细!$A:$A,L$6)/10000 -> 6.9 | M47: =SUMIFS(薪酬明细!$L:$L,薪酬明细!$D:$D,$E47,薪酬明细!$E:$E,$F47,薪酬明细!$H:$H,">="&M$9,薪酬明细!$H:$H,"<="&M$10,薪酬明细!$A:$A,M$6)/10000 -> 7 | N47: =SUMIFS(薪酬明细!$L:$L,薪酬明细!$D:$D,$E47,薪酬明细!$E:$E,$F47,薪酬明细!$H:$H,">="&N$9,薪酬明细!$H:$H,"<="&N$10,薪酬明细!$A:$A,N$6)/10000 -> 6.8 | ... S47: =SUMIFS(薪酬明细!$L:$L,薪酬明细!$D:$D,$E47,薪酬明细!$E:$E,$F47,薪酬明细!$H:$H,">="&S$9,薪酬明细!$H:$H,"<="&S$10,薪酬明细!$A:$A,S$6)/10000 -> 6.8 | T47: =U47+AH47 -> 83.6 | U47: =SUMIFS(薪酬明细!$L:$L,薪酬明细!$D:$D,$E47,薪酬明细!$E:$E,$F47,薪酬明细!$H:$H,">="&U$9,薪酬明细!$H:$H,"<="&U$10,薪酬明细!$A:$A,U$6)/10000 -> 62.6 | V47: =SUMIFS(薪酬明细!$L:$L,薪酬明细!$D:$D,$E47,薪酬明细!$E:$E,$F47,薪酬明细!$H:$H,">="&V$9,薪酬明细!$H:$H,"<="&V$10,薪酬明细!$A:$A,V$6)/10000 -> 6.9 | W47: =SUMIFS(薪酬明细!$L:$L,薪酬明细!$D:$D,$E47,薪酬明细!$E:$E,$F47,薪酬明细!$H:$H,">="&W$9,薪酬明细!$H:$H,"<="&W$10,薪酬明细!$A:$A,W$6)/10000 -> 7 | X47: =SUMIFS(薪酬明细!$L:$L,薪酬明细!$D:$D,$E47,薪酬明细!$E:$E,$F47,薪酬明细!$H:$H,">="&X$9,薪酬明细!$H:$H,"<="&X$10,薪酬明细!$A:$A,X$6)/10000 -> 7 | Y47: =SUMIFS(薪酬明细!$L:$L,薪酬明细!$D:$D,$E47,薪酬明细!$E:$E,$F47,薪酬明细!$H:$H,">="&Y$9,薪酬明细!$H:$H,"<="&Y$10,薪酬明细!$A:$A,Y$6)/10000 -> 6.9 | Z47: =SUMIFS(薪酬明细!$L:$L,薪酬明细!$D:$D,$E47,薪酬明细!$E:$E,$F47,薪酬明细!$H:$H,">="&Z$9,薪酬明细!$H:$H,"<="&Z$10,薪酬明细!$A:$A,Z$6)/10000 -> 6.9 | AA47: =SUMIFS(薪酬明细!$L:$L,薪酬明细!$D:$D,$E47,薪酬明细!$E:$E,$F47,薪酬明细!$H:$H,">="&AA$9,薪酬明细!$H:$H,"<="&AA$10,薪酬明细!$A:$A,AA$6)/10000 -> 6.8 | AB47: =SUMIFS(薪酬明细!$L:$L,薪酬明细!$D:$D,$E47,薪酬明细!$E:$E,$F47,薪酬明细!$H:$H,">="&AB$9,薪酬明细!$H:$H,"<="&AB$10,薪酬明细!$A:$A,AB$6)/10000 -> 7 | ... BG47: =SUMIFS(薪酬明细!$L:$L,薪酬明细!$D:$D,$E47,薪酬明细!$E:$E,$F47,薪酬明细!$H:$H,">="&BG$9,薪酬明细!$H:$H,"<="&BG$10,薪酬明细!$A:$A,BG$6)/10000 -> 6.9
D48: XX 试验室 | E48: =IF(C48<>"",C48,E47) -> 创新中心 | F48: =IF(D48<>"",D48,"*") -> XX 试验室 | G48: =SUMIFS(薪酬明细!$L:$L,薪酬明细!$D:$D,$E48,薪酬明细!$E:$E,$F48,薪酬明细!$H:$H,">="&G$9,薪酬明细!$H:$H,"<="&G$10,薪酬明细!$A:$A,G$6)/10000 -> 56.5 | H48: =SUMIFS(薪酬明细!$L:$L,薪酬明细!$D:$D,$E48,薪酬明细!$E:$E,$F48,薪酬明细!$H:$H,">="&H$9,薪酬明细!$H:$H,"<="&H$10,薪酬明细!$A:$A,H$6)/10000 -> 4.7 | I48: =SUMIFS(薪酬明细!$L:$L,薪酬明细!$D:$D,$E48,薪酬明细!$E:$E,$F48,薪酬明细!$H:$H,">="&I$9,薪酬明细!$H:$H,"<="&I$10,薪酬明细!$A:$A,I$6)/10000 -> 4.7 | J48: =SUMIFS(薪酬明细!$L:$L,薪酬明细!$D:$D,$E48,薪酬明细!$E:$E,$F48,薪酬明细!$H:$H,">="&J$9,薪酬明细!$H:$H,"<="&J$10,薪酬明细!$A:$A,J$6)/10000 -> 4.7 | K48: =SUMIFS(薪酬明细!$L:$L,薪酬明细!$D:$D,$E48,薪酬明细!$E:$E,$F48,薪酬明细!$H:$H,">="&K$9,薪酬明细!$H:$H,"<="&K$10,薪酬明细!$A:$A,K$6)/10000 -> 4.7 | L48: =SUMIFS(薪酬明细!$L:$L,薪酬明细!$D:$D,$E48,薪酬明细!$E:$E,$F48,薪酬明细!$H:$H,">="&L$9,薪酬明细!$H:$H,"<="&L$10,薪酬明细!$A:$A,L$6)/10000 -> 4.8 | M48: =SUMIFS(薪酬明细!$L:$L,薪酬明细!$D:$D,$E48,薪酬明细!$E:$E,$F48,薪酬明细!$H:$H,">="&M$9,薪酬明细!$H:$H,"<="&M$10,薪酬明细!$A:$A,M$6)/10000 -> 4.7 | N48: =SUMIFS(薪酬明细!$L:$L,薪酬明细!$D:$D,$E48,薪酬明细!$E:$E,$F48,薪酬明细!$H:$H,">="&N$9,薪酬明细!$H:$H,"<="&N$10,薪酬明细!$A:$A,N$6)/10000 -> 4.7 | ... S48: =SUMIFS(薪酬明细!$L:$L,薪酬明细!$D:$D,$E48,薪酬明细!$E:$E,$F48,薪酬明细!$H:$H,">="&S$9,薪酬明细!$H:$H,"<="&S$10,薪酬明细!$A:$A,S$6)/10000 -> 4.7 | T48: =U48+AH48 -> 56.2 | U48: =SUMIFS(薪酬明细!$L:$L,薪酬明细!$D:$D,$E48,薪酬明细!$E:$E,$F48,薪酬明细!$H:$H,">="&U$9,薪酬明细!$H:$H,"<="&U$10,薪酬明细!$A:$A,U$6)/10000 -> 42.2 | V48: =SUMIFS(薪酬明细!$L:$L,薪酬明细!$D:$D,$E48,薪酬明细!$E:$E,$F48,薪酬明细!$H:$H,">="&V$9,薪酬明细!$H:$H,"<="&V$10,薪酬明细!$A:$A,V$6)/10000 -> 4.6 | W48: =SUMIFS(薪酬明细!$L:$L,薪酬明细!$D:$D,$E48,薪酬明细!$E:$E,$F48,薪酬明细!$H:$H,">="&W$9,薪酬明细!$H:$H,"<="&W$10,薪酬明细!$A:$A,W$6)/10000 -> 4.8 | X48: =SUMIFS(薪酬明细!$L:$L,薪酬明细!$D:$D,$E48,薪酬明细!$E:$E,$F48,薪酬明细!$H:$H,">="&X$9,薪酬明细!$H:$H,"<="&X$10,薪酬明细!$A:$A,X$6)/10000 -> 4.7 | Y48: =SUMIFS(薪酬明细!$L:$L,薪酬明细!$D:$D,$E48,薪酬明细!$E:$E,$F48,薪酬明细!$H:$H,">="&Y$9,薪酬明细!$H:$H,"<="&Y$10,薪酬明细!$A:$A,Y$6)/10000 -> 4.6 | Z48: =SUMIFS(薪酬明细!$L:$L,薪酬明细!$D:$D,$E48,薪酬明细!$E:$E,$F48,薪酬明细!$H:$H,">="&Z$9,薪酬明细!$H:$H,"<="&Z$10,薪酬明细!$A:$A,Z$6)/10000 -> 4.7 | AA48: =SUMIFS(薪酬明细!$L:$L,薪酬明细!$D:$D,$E48,薪酬明细!$E:$E,$F48,薪酬明细!$H:$H,">="&AA$9,薪酬明细!$H:$H,"<="&AA$10,薪酬明细!$A:$A,AA$6)/10000 -> 4.8 | AB48: =SUMIFS(薪酬明细!$L:$L,薪酬明细!$D:$D,$E48,薪酬明细!$E:$E,$F48,薪酬明细!$H:$H,">="&AB$9,薪酬明细!$H:$H,"<="&AB$10,薪酬明细!$A:$A,AB$6)/10000 -> 4.6 | ... BG48: =SUMIFS(薪酬明细!$L:$L,薪酬明细!$D:$D,$E48,薪酬明细!$E:$E,$F48,薪酬明细!$H:$H,">="&BG$9,薪酬明细!$H:$H,"<="&BG$10,薪酬明细!$A:$A,BG$6)/10000 -> 4.7
D49: XX 孵化业务 | E49: =IF(C49<>"",C49,E48) -> 创新中心 | F49: =IF(D49<>"",D49,"*") -> XX 孵化业务 | G49: =SUMIFS(薪酬明细!$L:$L,薪酬明细!$D:$D,$E49,薪酬明细!$E:$E,$F49,薪酬明细!$H:$H,">="&G$9,薪酬明细!$H:$H,"<="&G$10,薪酬明细!$A:$A,G$6)/10000 -> 100.6 | H49: =SUMIFS(薪酬明细!$L:$L,薪酬明细!$D:$D,$E49,薪酬明细!$E:$E,$F49,薪酬明细!$H:$H,">="&H$9,薪酬明细!$H:$H,"<="&H$10,薪酬明细!$A:$A,H$6)/10000 -> 8.4 | I49: =SUMIFS(薪酬明细!$L:$L,薪酬明细!$D:$D,$E49,薪酬明细!$E:$E,$F49,薪酬明细!$H:$H,">="&I$9,薪酬明细!$H:$H,"<="&I$10,薪酬明细!$A:$A,I$6)/10000 -> 8.5 | J49: =SUMIFS(薪酬明细!$L:$L,薪酬明细!$D:$D,$E49,薪酬明细!$E:$E,$F49,薪酬明细!$H:$H,">="&J$9,薪酬明细!$H:$H,"<="&J$10,薪酬明细!$A:$A,J$6)/10000 -> 8.4 | K49: =SUMIFS(薪酬明细!$L:$L,薪酬明细!$D:$D,$E49,薪酬明细!$E:$E,$F49,薪酬明细!$H:$H,">="&K$9,薪酬明细!$H:$H,"<="&K$10,薪酬明细!$A:$A,K$6)/10000 -> 8.4 | L49: =SUMIFS(薪酬明细!$L:$L,薪酬明细!$D:$D,$E49,薪酬明细!$E:$E,$F49,薪酬明细!$H:$H,">="&L$9,薪酬明细!$H:$H,"<="&L$10,薪酬明细!$A:$A,L$6)/10000 -> 8.3 | M49: =SUMIFS(薪酬明细!$L:$L,薪酬明细!$D:$D,$E49,薪酬明细!$E:$E,$F49,薪酬明细!$H:$H,">="&M$9,薪酬明细!$H:$H,"<="&M$10,薪酬明细!$A:$A,M$6)/10000 -> 8.5 | N49: =SUMIFS(薪酬明细!$L:$L,薪酬明细!$D:$D,$E49,薪酬明细!$E:$E,$F49,薪酬明细!$H:$H,">="&N$9,薪酬明细!$H:$H,"<="&N$10,薪酬明细!$A:$A,N$6)/10000 -> 8.4 | ... S49: =SUMIFS(薪酬明细!$L:$L,薪酬明细!$D:$D,$E49,薪酬明细!$E:$E,$F49,薪酬明细!$H:$H,">="&S$9,薪酬明细!$H:$H,"<="&S$10,薪酬明细!$A:$A,S$6)/10000 -> 8.4 | T49: =U49+AH49 -> 100.6 | U49: =SUMIFS(薪酬明细!$L:$L,薪酬明细!$D:$D,$E49,薪酬明细!$E:$E,$F49,薪酬明细!$H:$H,">="&U$9,薪酬明细!$H:$H,"<="&U$10,薪酬明细!$A:$A,U$6)/10000 -> 75.5 | V49: =SUMIFS(薪酬明细!$L:$L,薪酬明细!$D:$D,$E49,薪酬明细!$E:$E,$F49,薪酬明细!$H:$H,">="&V$9,薪酬明细!$H:$H,"<="&V$10,薪酬明细!$A:$A,V$6)/10000 -> 8.3 | W49: =SUMIFS(薪酬明细!$L:$L,薪酬明细!$D:$D,$E49,薪酬明细!$E:$E,$F49,薪酬明细!$H:$H,">="&W$9,薪酬明细!$H:$H,"<="&W$10,薪酬明细!$A:$A,W$6)/10000 -> 8.3 | X49: =SUMIFS(薪酬明细!$L:$L,薪酬明细!$D:$D,$E49,薪酬明细!$E:$E,$F49,薪酬明细!$H:$H,">="&X$9,薪酬明细!$H:$H,"<="&X$10,薪酬明细!$A:$A,X$6)/10000 -> 8.5 | Y49: =SUMIFS(薪酬明细!$L:$L,薪酬明细!$D:$D,$E49,薪酬明细!$E:$E,$F49,薪酬明细!$H:$H,">="&Y$9,薪酬明细!$H:$H,"<="&Y$10,薪酬明细!$A:$A,Y$6)/10000 -> 8.4 | Z49: =SUMIFS(薪酬明细!$L:$L,薪酬明细!$D:$D,$E49,薪酬明细!$E:$E,$F49,薪酬明细!$H:$H,">="&Z$9,薪酬明细!$H:$H,"<="&Z$10,薪酬明细!$A:$A,Z$6)/10000 -> 8.3 | AA49: =SUMIFS(薪酬明细!$L:$L,薪酬明细!$D:$D,$E49,薪酬明细!$E:$E,$F49,薪酬明细!$H:$H,">="&AA$9,薪酬明细!$H:$H,"<="&AA$10,薪酬明细!$A:$A,AA$6)/10000 -> 8.4 | AB49: =SUMIFS(薪酬明细!$L:$L,薪酬明细!$D:$D,$E49,薪酬明细!$E:$E,$F49,薪酬明细!$H:$H,">="&AB$9,薪酬明细!$H:$H,"<="&AB$10,薪酬明细!$A:$A,AB$6)/10000 -> 8.4 | ... BG49: =SUMIFS(薪酬明细!$L:$L,薪酬明细!$D:$D,$E49,薪酬明细!$E:$E,$F49,薪酬明细!$H:$H,">="&BG$9,薪酬明细!$H:$H,"<="&BG$10,薪酬明细!$A:$A,BG$6)/10000 -> 8.5
C50: 支持中心 | E50: =IF(C50<>"",C50,E49) -> 支持中心 | F50: =IF(D50<>"",D50,"*") -> * | G50: =SUMIFS(薪酬明细!$L:$L,薪酬明细!$D:$D,$E50,薪酬明细!$E:$E,$F50,薪酬明细!$H:$H,">="&G$9,薪酬明细!$H:$H,"<="&G$10,薪酬明细!$A:$A,G$6)/10000 -> 208.6 | H50: =SUMIFS(薪酬明细!$L:$L,薪酬明细!$D:$D,$E50,薪酬明细!$E:$E,$F50,薪酬明细!$H:$H,">="&H$9,薪酬明细!$H:$H,"<="&H$10,薪酬明细!$A:$A,H$6)/10000 -> 17.5 | I50: =SUMIFS(薪酬明细!$L:$L,薪酬明细!$D:$D,$E50,薪酬明细!$E:$E,$F50,薪酬明细!$H:$H,">="&I$9,薪酬明细!$H:$H,"<="&I$10,薪酬明细!$A:$A,I$6)/10000 -> 17.2 | J50: =SUMIFS(薪酬明细!$L:$L,薪酬明细!$D:$D,$E50,薪酬明细!$E:$E,$F50,薪酬明细!$H:$H,">="&J$9,薪酬明细!$H:$H,"<="&J$10,薪酬明细!$A:$A,J$6)/10000 -> 17.3 | K50: =SUMIFS(薪酬明细!$L:$L,薪酬明细!$D:$D,$E50,薪酬明细!$E:$E,$F50,薪酬明细!$H:$H,">="&K$9,薪酬明细!$H:$H,"<="&K$10,薪酬明细!$A:$A,K$6)/10000 -> 17.5 | L50: =SUMIFS(薪酬明细!$L:$L,薪酬明细!$D:$D,$E50,薪酬明细!$E:$E,$F50,薪酬明细!$H:$H,">="&L$9,薪酬明细!$H:$H,"<="&L$10,薪酬明细!$A:$A,L$6)/10000 -> 17.3 | M50: =SUMIFS(薪酬明细!$L:$L,薪酬明细!$D:$D,$E50,薪酬明细!$E:$E,$F50,薪酬明细!$H:$H,">="&M$9,薪酬明细!$H:$H,"<="&M$10,薪酬明细!$A:$A,M$6)/10000 -> 17.4 | N50: =SUMIFS(薪酬明细!$L:$L,薪酬明细!$D:$D,$E50,薪酬明细!$E:$E,$F50,薪酬明细!$H:$H,">="&N$9,薪酬明细!$H:$H,"<="&N$10,薪酬明细!$A:$A,N$6)/10000 -> 17.5 | ... S50: =SUMIFS(薪酬明细!$L:$L,薪酬明细!$D:$D,$E50,薪酬明细!$E:$E,$F50,薪酬明细!$H:$H,">="&S$9,薪酬明细!$H:$H,"<="&S$10,薪酬明细!$A:$A,S$6)/10000 -> 17.4 | T50: =U50+AH50 -> 209.1 | U50: =SUMIFS(薪酬明细!$L:$L,薪酬明细!$D:$D,$E50,薪酬明细!$E:$E,$F50,薪酬明细!$H:$H,">="&U$9,薪酬明细!$H:$H,"<="&U$10,薪酬明细!$A:$A,U$6)/10000 -> 156.7 | V50: =SUMIFS(薪酬明细!$L:$L,薪酬明细!$D:$D,$E50,薪酬明细!$E:$E,$F50,薪酬明细!$H:$H,">="&V$9,薪酬明细!$H:$H,"<="&V$10,薪酬明细!$A:$A,V$6)/10000 -> 17.5 | W50: =SUMIFS(薪酬明细!$L:$L,薪酬明细!$D:$D,$E50,薪酬明细!$E:$E,$F50,薪酬明细!$H:$H,">="&W$9,薪酬明细!$H:$H,"<="&W$10,薪酬明细!$A:$A,W$6)/10000 -> 17.3 | X50: =SUMIFS(薪酬明细!$L:$L,薪酬明细!$D:$D,$E50,薪酬明细!$E:$E,$F50,薪酬明细!$H:$H,">="&X$9,薪酬明细!$H:$H,"<="&X$10,薪酬明细!$A:$A,X$6)/10000 -> 17.4 | Y50: =SUMIFS(薪酬明细!$L:$L,薪酬明细!$D:$D,$E50,薪酬明细!$E:$E,$F50,薪酬明细!$H:$H,">="&Y$9,薪酬明细!$H:$H,"<="&Y$10,薪酬明细!$A:$A,Y$6)/10000 -> 17.5 | Z50: =SUMIFS(薪酬明细!$L:$L,薪酬明细!$D:$D,$E50,薪酬明细!$E:$E,$F50,薪酬明细!$H:$H,">="&Z$9,薪酬明细!$H:$H,"<="&Z$10,薪酬明细!$A:$A,Z$6)/10000 -> 17.4 | AA50: =SUMIFS(薪酬明细!$L:$L,薪酬明细!$D:$D,$E50,薪酬明细!$E:$E,$F50,薪酬明细!$H:$H,">="&AA$9,薪酬明细!$H:$H,"<="&AA$10,薪酬明细!$A:$A,AA$6)/10000 -> 17.5 | AB50: =SUMIFS(薪酬明细!$L:$L,薪酬明细!$D:$D,$E50,薪酬明细!$E:$E,$F50,薪酬明细!$H:$H,">="&AB$9,薪酬明细!$H:$H,"<="&AB$10,薪酬明细!$A:$A,AB$6)/10000 -> 17.5 | ... BG50: =SUMIFS(薪酬明细!$L:$L,薪酬明细!$D:$D,$E50,薪酬明细!$E:$E,$F50,薪酬明细!$H:$H,">="&BG$9,薪酬明细!$H:$H,"<="&BG$10,薪酬明细!$A:$A,BG$6)/10000 -> 17.2
D51: 财务部 | E51: =IF(C51<>"",C51,E50) -> 支持中心 | F51: =IF(D51<>"",D51,"*") -> 财务部 | G51: =SUMIFS(薪酬明细!$L:$L,薪酬明细!$D:$D,$E51,薪酬明细!$E:$E,$F51,薪酬明细!$H:$H,">="&G$9,薪酬明细!$H:$H,"<="&G$10,薪酬明细!$A:$A,G$6)/10000 -> 81.4 | H51: =SUMIFS(薪酬明细!$L:$L,薪酬明细!$D:$D,$E51,薪酬明细!$E:$E,$F51,薪酬明细!$H:$H,">="&H$9,薪酬明细!$H:$H,"<="&H$10,薪酬明细!$A:$A,H$6)/10000 -> 6.8 | I51: =SUMIFS(薪酬明细!$L:$L,薪酬明细!$D:$D,$E51,薪酬明细!$E:$E,$F51,薪酬明细!$H:$H,">="&I$9,薪酬明细!$H:$H,"<="&I$10,薪酬明细!$A:$A,I$6)/10000 -> 6.8 | J51: =SUMIFS(薪酬明细!$L:$L,薪酬明细!$D:$D,$E51,薪酬明细!$E:$E,$F51,薪酬明细!$H:$H,">="&J$9,薪酬明细!$H:$H,"<="&J$10,薪酬明细!$A:$A,J$6)/10000 -> 6.7 | K51: =SUMIFS(薪酬明细!$L:$L,薪酬明细!$D:$D,$E51,薪酬明细!$E:$E,$F51,薪酬明细!$H:$H,">="&K$9,薪酬明细!$H:$H,"<="&K$10,薪酬明细!$A:$A,K$6)/10000 -> 6.8 | L51: =SUMIFS(薪酬明细!$L:$L,薪酬明细!$D:$D,$E51,薪酬明细!$E:$E,$F51,薪酬明细!$H:$H,">="&L$9,薪酬明细!$H:$H,"<="&L$10,薪酬明细!$A:$A,L$6)/10000 -> 6.8 | M51: =SUMIFS(薪酬明细!$L:$L,薪酬明细!$D:$D,$E51,薪酬明细!$E:$E,$F51,薪酬明细!$H:$H,">="&M$9,薪酬明细!$H:$H,"<="&M$10,薪酬明细!$A:$A,M$6)/10000 -> 6.9 | N51: =SUMIFS(薪酬明细!$L:$L,薪酬明细!$D:$D,$E51,薪酬明细!$E:$E,$F51,薪酬明细!$H:$H,">="&N$9,薪酬明细!$H:$H,"<="&N$10,薪酬明细!$A:$A,N$6)/10000 -> 6.7 | ... S51: =SUMIFS(薪酬明细!$L:$L,薪酬明细!$D:$D,$E51,薪酬明细!$E:$E,$F51,薪酬明细!$H:$H,">="&S$9,薪酬明细!$H:$H,"<="&S$10,薪酬明细!$A:$A,S$6)/10000 -> 6.8 | T51: =U51+AH51 -> 81.6 | U51: =SUMIFS(薪酬明细!$L:$L,薪酬明细!$D:$D,$E51,薪酬明细!$E:$E,$F51,薪酬明细!$H:$H,">="&U$9,薪酬明细!$H:$H,"<="&U$10,薪酬明细!$A:$A,U$6)/10000 -> 61.1 | V51: =SUMIFS(薪酬明细!$L:$L,薪酬明细!$D:$D,$E51,薪酬明细!$E:$E,$F51,薪酬明细!$H:$H,">="&V$9,薪酬明细!$H:$H,"<="&V$10,薪酬明细!$A:$A,V$6)/10000 -> 6.8 | W51: =SUMIFS(薪酬明细!$L:$L,薪酬明细!$D:$D,$E51,薪酬明细!$E:$E,$F51,薪酬明细!$H:$H,">="&W$9,薪酬明细!$H:$H,"<="&W$10,薪酬明细!$A:$A,W$6)/10000 -> 6.8 | X51: =SUMIFS(薪酬明细!$L:$L,薪酬明细!$D:$D,$E51,薪酬明细!$E:$E,$F51,薪酬明细!$H:$H,">="&X$9,薪酬明细!$H:$H,"<="&X$10,薪酬明细!$A:$A,X$6)/10000 -> 6.8 | Y51: =SUMIFS(薪酬明细!$L:$L,薪酬明细!$D:$D,$E51,薪酬明细!$E:$E,$F51,薪酬明细!$H:$H,">="&Y$9,薪酬明细!$H:$H,"<="&Y$10,薪酬明细!$A:$A,Y$6)/10000 -> 6.7 | Z51: =SUMIFS(薪酬明细!$L:$L,薪酬明细!$D:$D,$E51,薪酬明细!$E:$E,$F51,薪酬明细!$H:$H,">="&Z$9,薪酬明细!$H:$H,"<="&Z$10,薪酬明细!$A:$A,Z$6)/10000 -> 6.8 | AA51: =SUMIFS(薪酬明细!$L:$L,薪酬明细!$D:$D,$E51,薪酬明细!$E:$E,$F51,薪酬明细!$H:$H,">="&AA$9,薪酬明细!$H:$H,"<="&AA$10,薪酬明细!$A:$A,AA$6)/10000 -> 6.8 | AB51: =SUMIFS(薪酬明细!$L:$L,薪酬明细!$D:$D,$E51,薪酬明细!$E:$E,$F51,薪酬明细!$H:$H,">="&AB$9,薪酬明细!$H:$H,"<="&AB$10,薪酬明细!$A:$A,AB$6)/10000 -> 6.8 | ... BG51: =SUMIFS(薪酬明细!$L:$L,薪酬明细!$D:$D,$E51,薪酬明细!$E:$E,$F51,薪酬明细!$H:$H,">="&BG$9,薪酬明细!$H:$H,"<="&BG$10,薪酬明细!$A:$A,BG$6)/10000 -> 6.7
D52: 人力资源部 | E52: =IF(C52<>"",C52,E51) -> 支持中心 | F52: =IF(D52<>"",D52,"*") -> 人力资源部 | G52: =SUMIFS(薪酬明细!$L:$L,薪酬明细!$D:$D,$E52,薪酬明细!$E:$E,$F52,薪酬明细!$H:$H,">="&G$9,薪酬明细!$H:$H,"<="&G$10,薪酬明细!$A:$A,G$6)/10000 -> 72.5 | H52: =SUMIFS(薪酬明细!$L:$L,薪酬明细!$D:$D,$E52,薪酬明细!$E:$E,$F52,薪酬明细!$H:$H,">="&H$9,薪酬明细!$H:$H,"<="&H$10,薪酬明细!$A:$A,H$6)/10000 -> 6 | I52: =SUMIFS(薪酬明细!$L:$L,薪酬明细!$D:$D,$E52,薪酬明细!$E:$E,$F52,薪酬明细!$H:$H,">="&I$9,薪酬明细!$H:$H,"<="&I$10,薪酬明细!$A:$A,I$6)/10000 -> 5.9 | J52: =SUMIFS(薪酬明细!$L:$L,薪酬明细!$D:$D,$E52,薪酬明细!$E:$E,$F52,薪酬明细!$H:$H,">="&J$9,薪酬明细!$H:$H,"<="&J$10,薪酬明细!$A:$A,J$6)/10000 -> 6 | K52: =SUMIFS(薪酬明细!$L:$L,薪酬明细!$D:$D,$E52,薪酬明细!$E:$E,$F52,薪酬明细!$H:$H,">="&K$9,薪酬明细!$H:$H,"<="&K$10,薪酬明细!$A:$A,K$6)/10000 -> 6.1 | L52: =SUMIFS(薪酬明细!$L:$L,薪酬明细!$D:$D,$E52,薪酬明细!$E:$E,$F52,薪酬明细!$H:$H,">="&L$9,薪酬明细!$H:$H,"<="&L$10,薪酬明细!$A:$A,L$6)/10000 -> 5.9 | M52: =SUMIFS(薪酬明细!$L:$L,薪酬明细!$D:$D,$E52,薪酬明细!$E:$E,$F52,薪酬明细!$H:$H,">="&M$9,薪酬明细!$H:$H,"<="&M$10,薪酬明细!$A:$A,M$6)/10000 -> 6 | N52: =SUMIFS(薪酬明细!$L:$L,薪酬明细!$D:$D,$E52,薪酬明细!$E:$E,$F52,薪酬明细!$H:$H,">="&N$9,薪酬明细!$H:$H,"<="&N$10,薪酬明细!$A:$A,N$6)/10000 -> 6.2 | ... S52: =SUMIFS(薪酬明细!$L:$L,薪酬明细!$D:$D,$E52,薪酬明细!$E:$E,$F52,薪酬明细!$H:$H,">="&S$9,薪酬明细!$H:$H,"<="&S$10,薪酬明细!$A:$A,S$6)/10000 -> 6.1 | T52: =U52+AH52 -> 73 | U52: =SUMIFS(薪酬明细!$L:$L,薪酬明细!$D:$D,$E52,薪酬明细!$E:$E,$F52,薪酬明细!$H:$H,">="&U$9,薪酬明细!$H:$H,"<="&U$10,薪酬明细!$A:$A,U$6)/10000 -> 54.7 | V52: =SUMIFS(薪酬明细!$L:$L,薪酬明细!$D:$D,$E52,薪酬明细!$E:$E,$F52,薪酬明细!$H:$H,">="&V$9,薪酬明细!$H:$H,"<="&V$10,薪酬明细!$A:$A,V$6)/10000 -> 6.1 | W52: =SUMIFS(薪酬明细!$L:$L,薪酬明细!$D:$D,$E52,薪酬明细!$E:$E,$F52,薪酬明细!$H:$H,">="&W$9,薪酬明细!$H:$H,"<="&W$10,薪酬明细!$A:$A,W$6)/10000 -> 6 | X52: =SUMIFS(薪酬明细!$L:$L,薪酬明细!$D:$D,$E52,薪酬明细!$E:$E,$F52,薪酬明细!$H:$H,">="&X$9,薪酬明细!$H:$H,"<="&X$10,薪酬明细!$A:$A,X$6)/10000 -> 6 | Y52: =SUMIFS(薪酬明细!$L:$L,薪酬明细!$D:$D,$E52,薪酬明细!$E:$E,$F52,薪酬明细!$H:$H,">="&Y$9,薪酬明细!$H:$H,"<="&Y$10,薪酬明细!$A:$A,Y$6)/10000 -> 6.2 | Z52: =SUMIFS(薪酬明细!$L:$L,薪酬明细!$D:$D,$E52,薪酬明细!$E:$E,$F52,薪酬明细!$H:$H,">="&Z$9,薪酬明细!$H:$H,"<="&Z$10,薪酬明细!$A:$A,Z$6)/10000 -> 6.1 | AA52: =SUMIFS(薪酬明细!$L:$L,薪酬明细!$D:$D,$E52,薪酬明细!$E:$E,$F52,薪酬明细!$H:$H,">="&AA$9,薪酬明细!$H:$H,"<="&AA$10,薪酬明细!$A:$A,AA$6)/10000 -> 6.2 | AB52: =SUMIFS(薪酬明细!$L:$L,薪酬明细!$D:$D,$E52,薪酬明细!$E:$E,$F52,薪酬明细!$H:$H,">="&AB$9,薪酬明细!$H:$H,"<="&AB$10,薪酬明细!$A:$A,AB$6)/10000 -> 6.1 | ... BG52: =SUMIFS(薪酬明细!$L:$L,薪酬明细!$D:$D,$E52,薪酬明细!$E:$E,$F52,薪酬明细!$H:$H,">="&BG$9,薪酬明细!$H:$H,"<="&BG$10,薪酬明细!$A:$A,BG$6)/10000 -> 6
D53: IT部 | E53: =IF(C53<>"",C53,E52) -> 支持中心 | F53: =IF(D53<>"",D53,"*") -> IT部 | G53: =SUMIFS(薪酬明细!$L:$L,薪酬明细!$D:$D,$E53,薪酬明细!$E:$E,$F53,薪酬明细!$H:$H,">="&G$9,薪酬明细!$H:$H,"<="&G$10,薪酬明细!$A:$A,G$6)/10000 -> 34.2 | H53: =SUMIFS(薪酬明细!$L:$L,薪酬明细!$D:$D,$E53,薪酬明细!$E:$E,$F53,薪酬明细!$H:$H,">="&H$9,薪酬明细!$H:$H,"<="&H$10,薪酬明细!$A:$A,H$6)/10000 -> 2.9 | I53: =SUMIFS(薪酬明细!$L:$L,薪酬明细!$D:$D,$E53,薪酬明细!$E:$E,$F53,薪酬明细!$H:$H,">="&I$9,薪酬明细!$H:$H,"<="&I$10,薪酬明细!$A:$A,I$6)/10000 -> 2.9 | J53: =SUMIFS(薪酬明细!$L:$L,薪酬明细!$D:$D,$E53,薪酬明细!$E:$E,$F53,薪酬明细!$H:$H,">="&J$9,薪酬明细!$H:$H,"<="&J$10,薪酬明细!$A:$A,J$6)/10000 -> 2.8 | K53: =SUMIFS(薪酬明细!$L:$L,薪酬明细!$D:$D,$E53,薪酬明细!$E:$E,$F53,薪酬明细!$H:$H,">="&K$9,薪酬明细!$H:$H,"<="&K$10,薪酬明细!$A:$A,K$6)/10000 -> 2.9 | L53: =SUMIFS(薪酬明细!$L:$L,薪酬明细!$D:$D,$E53,薪酬明细!$E:$E,$F53,薪酬明细!$H:$H,">="&L$9,薪酬明细!$H:$H,"<="&L$10,薪酬明细!$A:$A,L$6)/10000 -> 2.9 | M53: =SUMIFS(薪酬明细!$L:$L,薪酬明细!$D:$D,$E53,薪酬明细!$E:$E,$F53,薪酬明细!$H:$H,">="&M$9,薪酬明细!$H:$H,"<="&M$10,薪酬明细!$A:$A,M$6)/10000 -> 2.8 | N53: =SUMIFS(薪酬明细!$L:$L,薪酬明细!$D:$D,$E53,薪酬明细!$E:$E,$F53,薪酬明细!$H:$H,">="&N$9,薪酬明细!$H:$H,"<="&N$10,薪酬明细!$A:$A,N$6)/10000 -> 2.9 | ... S53: =SUMIFS(薪酬明细!$L:$L,薪酬明细!$D:$D,$E53,薪酬明细!$E:$E,$F53,薪酬明细!$H:$H,">="&S$9,薪酬明细!$H:$H,"<="&S$10,薪酬明细!$A:$A,S$6)/10000 -> 2.8 | T53: =U53+AH53 -> 34.2 | U53: =SUMIFS(薪酬明细!$L:$L,薪酬明细!$D:$D,$E53,薪酬明细!$E:$E,$F53,薪酬明细!$H:$H,">="&U$9,薪酬明细!$H:$H,"<="&U$10,薪酬明细!$A:$A,U$6)/10000 -> 25.6 | V53: =SUMIFS(薪酬明细!$L:$L,薪酬明细!$D:$D,$E53,薪酬明细!$E:$E,$F53,薪酬明细!$H:$H,">="&V$9,薪酬明细!$H:$H,"<="&V$10,薪酬明细!$A:$A,V$6)/10000 -> 2.9 | W53: =SUMIFS(薪酬明细!$L:$L,薪酬明细!$D:$D,$E53,薪酬明细!$E:$E,$F53,薪酬明细!$H:$H,">="&W$9,薪酬明细!$H:$H,"<="&W$10,薪酬明细!$A:$A,W$6)/10000 -> 2.8 | X53: =SUMIFS(薪酬明细!$L:$L,薪酬明细!$D:$D,$E53,薪酬明细!$E:$E,$F53,薪酬明细!$H:$H,">="&X$9,薪酬明细!$H:$H,"<="&X$10,薪酬明细!$A:$A,X$6)/10000 -> 2.9 | Y53: =SUMIFS(薪酬明细!$L:$L,薪酬明细!$D:$D,$E53,薪酬明细!$E:$E,$F53,薪酬明细!$H:$H,">="&Y$9,薪酬明细!$H:$H,"<="&Y$10,薪酬明细!$A:$A,Y$6)/10000 -> 2.8 | Z53: =SUMIFS(薪酬明细!$L:$L,薪酬明细!$D:$D,$E53,薪酬明细!$E:$E,$F53,薪酬明细!$H:$H,">="&Z$9,薪酬明细!$H:$H,"<="&Z$10,薪酬明细!$A:$A,Z$6)/10000 -> 2.8 | AA53: =SUMIFS(薪酬明细!$L:$L,薪酬明细!$D:$D,$E53,薪酬明细!$E:$E,$F53,薪酬明细!$H:$H,">="&AA$9,薪酬明细!$H:$H,"<="&AA$10,薪酬明细!$A:$A,AA$6)/10000 -> 2.9 | AB53: =SUMIFS(薪酬明细!$L:$L,薪酬明细!$D:$D,$E53,薪酬明细!$E:$E,$F53,薪酬明细!$H:$H,">="&AB$9,薪酬明细!$H:$H,"<="&AB$10,薪酬明细!$A:$A,AB$6)/10000 -> 2.9 | ... BG53: =SUMIFS(薪酬明细!$L:$L,薪酬明细!$D:$D,$E53,薪酬明细!$E:$E,$F53,薪酬明细!$H:$H,">="&BG$9,薪酬明细!$H:$H,"<="&BG$10,薪酬明细!$A:$A,BG$6)/10000 -> 2.8
D54: 总经办 | E54: =IF(C54<>"",C54,E53) -> 支持中心 | F54: =IF(D54<>"",D54,"*") -> 总经办 | G54: =SUMIFS(薪酬明细!$L:$L,薪酬明细!$D:$D,$E54,薪酬明细!$E:$E,$F54,薪酬明细!$H:$H,">="&G$9,薪酬明细!$H:$H,"<="&G$10,薪酬明细!$A:$A,G$6)/10000 -> 20.4 | H54: =SUMIFS(薪酬明细!$L:$L,薪酬明细!$D:$D,$E54,薪酬明细!$E:$E,$F54,薪酬明细!$H:$H,">="&H$9,薪酬明细!$H:$H,"<="&H$10,薪酬明细!$A:$A,H$6)/10000 -> 1.7 | I54: =SUMIFS(薪酬明细!$L:$L,薪酬明细!$D:$D,$E54,薪酬明细!$E:$E,$F54,薪酬明细!$H:$H,">="&I$9,薪酬明细!$H:$H,"<="&I$10,薪酬明细!$A:$A,I$6)/10000 -> 1.7 | J54: =SUMIFS(薪酬明细!$L:$L,薪酬明细!$D:$D,$E54,薪酬明细!$E:$E,$F54,薪酬明细!$H:$H,">="&J$9,薪酬明细!$H:$H,"<="&J$10,薪酬明细!$A:$A,J$6)/10000 -> 1.7 | K54: =SUMIFS(薪酬明细!$L:$L,薪酬明细!$D:$D,$E54,薪酬明细!$E:$E,$F54,薪酬明细!$H:$H,">="&K$9,薪酬明细!$H:$H,"<="&K$10,薪酬明细!$A:$A,K$6)/10000 -> 1.7 | L54: =SUMIFS(薪酬明细!$L:$L,薪酬明细!$D:$D,$E54,薪酬明细!$E:$E,$F54,薪酬明细!$H:$H,">="&L$9,薪酬明细!$H:$H,"<="&L$10,薪酬明细!$A:$A,L$6)/10000 -> 1.7 | M54: =SUMIFS(薪酬明细!$L:$L,薪酬明细!$D:$D,$E54,薪酬明细!$E:$E,$F54,薪酬明细!$H:$H,">="&M$9,薪酬明细!$H:$H,"<="&M$10,薪酬明细!$A:$A,M$6)/10000 -> 1.7 | N54: =SUMIFS(薪酬明细!$L:$L,薪酬明细!$D:$D,$E54,薪酬明细!$E:$E,$F54,薪酬明细!$H:$H,">="&N$9,薪酬明细!$H:$H,"<="&N$10,薪酬明细!$A:$A,N$6)/10000 -> 1.7 | ... S54: =SUMIFS(薪酬明细!$L:$L,薪酬明细!$D:$D,$E54,薪酬明细!$E:$E,$F54,薪酬明细!$H:$H,">="&S$9,薪酬明细!$H:$H,"<="&S$10,薪酬明细!$A:$A,S$6)/10000 -> 1.7 | T54: =U54+AH54 -> 20.3 | U54: =SUMIFS(薪酬明细!$L:$L,薪酬明细!$D:$D,$E54,薪酬明细!$E:$E,$F54,薪酬明细!$H:$H,">="&U$9,薪酬明细!$H:$H,"<="&U$10,薪酬明细!$A:$A,U$6)/10000 -> 15.3 | V54: =SUMIFS(薪酬明细!$L:$L,薪酬明细!$D:$D,$E54,薪酬明细!$E:$E,$F54,薪酬明细!$H:$H,">="&V$9,薪酬明细!$H:$H,"<="&V$10,薪酬明细!$A:$A,V$6)/10000 -> 1.7 | W54: =SUMIFS(薪酬明细!$L:$L,薪酬明细!$D:$D,$E54,薪酬明细!$E:$E,$F54,薪酬明细!$H:$H,">="&W$9,薪酬明细!$H:$H,"<="&W$10,薪酬明细!$A:$A,W$6)/10000 -> 1.7 | X54: =SUMIFS(薪酬明细!$L:$L,薪酬明细!$D:$D,$E54,薪酬明细!$E:$E,$F54,薪酬明细!$H:$H,">="&X$9,薪酬明细!$H:$H,"<="&X$10,薪酬明细!$A:$A,X$6)/10000 -> 1.6 | Y54: =SUMIFS(薪酬明细!$L:$L,薪酬明细!$D:$D,$E54,薪酬明细!$E:$E,$F54,薪酬明细!$H:$H,">="&Y$9,薪酬明细!$H:$H,"<="&Y$10,薪酬明细!$A:$A,Y$6)/10000 -> 1.8 | Z54: =SUMIFS(薪酬明细!$L:$L,薪酬明细!$D:$D,$E54,薪酬明细!$E:$E,$F54,薪酬明细!$H:$H,">="&Z$9,薪酬明细!$H:$H,"<="&Z$10,薪酬明细!$A:$A,Z$6)/10000 -> 1.7 | AA54: =SUMIFS(薪酬明细!$L:$L,薪酬明细!$D:$D,$E54,薪酬明细!$E:$E,$F54,薪酬明细!$H:$H,">="&AA$9,薪酬明细!$H:$H,"<="&AA$10,薪酬明细!$A:$A,AA$6)/10000 -> 1.7 | AB54: =SUMIFS(薪酬明细!$L:$L,薪酬明细!$D:$D,$E54,薪酬明细!$E:$E,$F54,薪酬明细!$H:$H,">="&AB$9,薪酬明细!$H:$H,"<="&AB$10,薪酬明细!$A:$A,AB$6)/10000 -> 1.7 | ... BG54: =SUMIFS(薪酬明细!$L:$L,薪酬明细!$D:$D,$E54,薪酬明细!$E:$E,$F54,薪酬明细!$H:$H,">="&BG$9,薪酬明细!$H:$H,"<="&BG$10,薪酬明细!$A:$A,BG$6)/10000 -> 1.7
B56: 变动薪酬
B57: 合计 | E57: * | F57: * | G57: =SUMIFS(薪酬明细!$M:$M,薪酬明细!$D:$D,$E57,薪酬明细!$E:$E,$F57,薪酬明细!$H:$H,">="&G$9,薪酬明细!$H:$H,"<="&G$10,薪酬明细!$A:$A,G$6)/10000 -> 275.6 | H57: =SUMIFS(薪酬明细!$M:$M,薪酬明细!$D:$D,$E57,薪酬明细!$E:$E,$F57,薪酬明细!$H:$H,">="&H$9,薪酬明细!$H:$H,"<="&H$10,薪酬明细!$A:$A,H$6)/10000 -> 23 | I57: =SUMIFS(薪酬明细!$M:$M,薪酬明细!$D:$D,$E57,薪酬明细!$E:$E,$F57,薪酬明细!$H:$H,">="&I$9,薪酬明细!$H:$H,"<="&I$10,薪酬明细!$A:$A,I$6)/10000 -> 23.1 | J57: =SUMIFS(薪酬明细!$M:$M,薪酬明细!$D:$D,$E57,薪酬明细!$E:$E,$F57,薪酬明细!$H:$H,">="&J$9,薪酬明细!$H:$H,"<="&J$10,薪酬明细!$A:$A,J$6)/10000 -> 23.1 | K57: =SUMIFS(薪酬明细!$M:$M,薪酬明细!$D:$D,$E57,薪酬明细!$E:$E,$F57,薪酬明细!$H:$H,">="&K$9,薪酬明细!$H:$H,"<="&K$10,薪酬明细!$A:$A,K$6)/10000 -> 22.9 | L57: =SUMIFS(薪酬明细!$M:$M,薪酬明细!$D:$D,$E57,薪酬明细!$E:$E,$F57,薪酬明细!$H:$H,">="&L$9,薪酬明细!$H:$H,"<="&L$10,薪酬明细!$A:$A,L$6)/10000 -> 22.8 | M57: =SUMIFS(薪酬明细!$M:$M,薪酬明细!$D:$D,$E57,薪酬明细!$E:$E,$F57,薪酬明细!$H:$H,">="&M$9,薪酬明细!$H:$H,"<="&M$10,薪酬明细!$A:$A,M$6)/10000 -> 23 | N57: =SUMIFS(薪酬明细!$M:$M,薪酬明细!$D:$D,$E57,薪酬明细!$E:$E,$F57,薪酬明细!$H:$H,">="&N$9,薪酬明细!$H:$H,"<="&N$10,薪酬明细!$A:$A,N$6)/10000 -> 23 | ... S57: =SUMIFS(薪酬明细!$M:$M,薪酬明细!$D:$D,$E57,薪酬明细!$E:$E,$F57,薪酬明细!$H:$H,">="&S$9,薪酬明细!$H:$H,"<="&S$10,薪酬明细!$A:$A,S$6)/10000 -> 23 | T57: =U57+AH57 -> 276.1 | U57: =SUMIFS(薪酬明细!$M:$M,薪酬明细!$D:$D,$E57,薪酬明细!$E:$E,$F57,薪酬明细!$H:$H,">="&U$9,薪酬明细!$H:$H,"<="&U$10,薪酬明细!$A:$A,U$6)/10000 -> 207 | V57: =SUMIFS(薪酬明细!$M:$M,薪酬明细!$D:$D,$E57,薪酬明细!$E:$E,$F57,薪酬明细!$H:$H,">="&V$9,薪酬明细!$H:$H,"<="&V$10,薪酬明细!$A:$A,V$6)/10000 -> 22.8 | W57: =SUMIFS(薪酬明细!$M:$M,薪酬明细!$D:$D,$E57,薪酬明细!$E:$E,$F57,薪酬明细!$H:$H,">="&W$9,薪酬明细!$H:$H,"<="&W$10,薪酬明细!$A:$A,W$6)/10000 -> 23 | X57: =SUMIFS(薪酬明细!$M:$M,薪酬明细!$D:$D,$E57,薪酬明细!$E:$E,$F57,薪酬明细!$H:$H,">="&X$9,薪酬明细!$H:$H,"<="&X$10,薪酬明细!$A:$A,X$6)/10000 -> 23 | Y57: =SUMIFS(薪酬明细!$M:$M,薪酬明细!$D:$D,$E57,薪酬明细!$E:$E,$F57,薪酬明细!$H:$H,">="&Y$9,薪酬明细!$H:$H,"<="&Y$10,薪酬明细!$A:$A,Y$6)/10000 -> 23 | Z57: =SUMIFS(薪酬明细!$M:$M,薪酬明细!$D:$D,$E57,薪酬明细!$E:$E,$F57,薪酬明细!$H:$H,">="&Z$9,薪酬明细!$H:$H,"<="&Z$10,薪酬明细!$A:$A,Z$6)/10000 -> 23 | AA57: =SUMIFS(薪酬明细!$M:$M,薪酬明细!$D:$D,$E57,薪酬明细!$E:$E,$F57,薪酬明细!$H:$H,">="&AA$9,薪酬明细!$H:$H,"<="&AA$10,薪酬明细!$A:$A,AA$6)/10000 -> 23.1 | AB57: =SUMIFS(薪酬明细!$M:$M,薪酬明细!$D:$D,$E57,薪酬明细!$E:$E,$F57,薪酬明细!$H:$H,">="&AB$9,薪酬明细!$H:$H,"<="&AB$10,薪酬明细!$A:$A,AB$6)/10000 -> 23.1 | ... BG57: =SUMIFS(薪酬明细!$M:$M,薪酬明细!$D:$D,$E57,薪酬明细!$E:$E,$F57,薪酬明细!$H:$H,">="&BG$9,薪酬明细!$H:$H,"<="&BG$10,薪酬明细!$A:$A,BG$6)/10000 -> 22.9
C58: 流程中心 | E58: =IF(C58<>"",C58,E55) -> 流程中心 | F58: =IF(D58<>"",D58,"*") -> * | G58: =SUMIFS(薪酬明细!$M:$M,薪酬明细!$D:$D,$E58,薪酬明细!$E:$E,$F58,薪酬明细!$H:$H,">="&G$9,薪酬明细!$H:$H,"<="&G$10,薪酬明细!$A:$A,G$6)/10000 -> 136 | H58: =SUMIFS(薪酬明细!$M:$M,薪酬明细!$D:$D,$E58,薪酬明细!$E:$E,$F58,薪酬明细!$H:$H,">="&H$9,薪酬明细!$H:$H,"<="&H$10,薪酬明细!$A:$A,H$6)/10000 -> 11.3 | I58: =SUMIFS(薪酬明细!$M:$M,薪酬明细!$D:$D,$E58,薪酬明细!$E:$E,$F58,薪酬明细!$H:$H,">="&I$9,薪酬明细!$H:$H,"<="&I$10,薪酬明细!$A:$A,I$6)/10000 -> 11.4 | J58: =SUMIFS(薪酬明细!$M:$M,薪酬明细!$D:$D,$E58,薪酬明细!$E:$E,$F58,薪酬明细!$H:$H,">="&J$9,薪酬明细!$H:$H,"<="&J$10,薪酬明细!$A:$A,J$6)/10000 -> 11.3 | K58: =SUMIFS(薪酬明细!$M:$M,薪酬明细!$D:$D,$E58,薪酬明细!$E:$E,$F58,薪酬明细!$H:$H,">="&K$9,薪酬明细!$H:$H,"<="&K$10,薪酬明细!$A:$A,K$6)/10000 -> 11.3 | L58: =SUMIFS(薪酬明细!$M:$M,薪酬明细!$D:$D,$E58,薪酬明细!$E:$E,$F58,薪酬明细!$H:$H,">="&L$9,薪酬明细!$H:$H,"<="&L$10,薪酬明细!$A:$A,L$6)/10000 -> 11.3 | M58: =SUMIFS(薪酬明细!$M:$M,薪酬明细!$D:$D,$E58,薪酬明细!$E:$E,$F58,薪酬明细!$H:$H,">="&M$9,薪酬明细!$H:$H,"<="&M$10,薪酬明细!$A:$A,M$6)/10000 -> 11.4 | N58: =SUMIFS(薪酬明细!$M:$M,薪酬明细!$D:$D,$E58,薪酬明细!$E:$E,$F58,薪酬明细!$H:$H,">="&N$9,薪酬明细!$H:$H,"<="&N$10,薪酬明细!$A:$A,N$6)/10000 -> 11.4 | ... S58: =SUMIFS(薪酬明细!$M:$M,薪酬明细!$D:$D,$E58,薪酬明细!$E:$E,$F58,薪酬明细!$H:$H,">="&S$9,薪酬明细!$H:$H,"<="&S$10,薪酬明细!$A:$A,S$6)/10000 -> 11.3 | T58: =U58+AH58 -> 136.2 | U58: =SUMIFS(薪酬明细!$M:$M,薪酬明细!$D:$D,$E58,薪酬明细!$E:$E,$F58,薪酬明细!$H:$H,">="&U$9,薪酬明细!$H:$H,"<="&U$10,薪酬明细!$A:$A,U$6)/10000 -> 102.1 | V58: =SUMIFS(薪酬明细!$M:$M,薪酬明细!$D:$D,$E58,薪酬明细!$E:$E,$F58,薪酬明细!$H:$H,">="&V$9,薪酬明细!$H:$H,"<="&V$10,薪酬明细!$A:$A,V$6)/10000 -> 11.2 | W58: =SUMIFS(薪酬明细!$M:$M,薪酬明细!$D:$D,$E58,薪酬明细!$E:$E,$F58,薪酬明细!$H:$H,">="&W$9,薪酬明细!$H:$H,"<="&W$10,薪酬明细!$A:$A,W$6)/10000 -> 11.3 | X58: =SUMIFS(薪酬明细!$M:$M,薪酬明细!$D:$D,$E58,薪酬明细!$E:$E,$F58,薪酬明细!$H:$H,">="&X$9,薪酬明细!$H:$H,"<="&X$10,薪酬明细!$A:$A,X$6)/10000 -> 11.4 | Y58: =SUMIFS(薪酬明细!$M:$M,薪酬明细!$D:$D,$E58,薪酬明细!$E:$E,$F58,薪酬明细!$H:$H,">="&Y$9,薪酬明细!$H:$H,"<="&Y$10,薪酬明细!$A:$A,Y$6)/10000 -> 11.3 | Z58: =SUMIFS(薪酬明细!$M:$M,薪酬明细!$D:$D,$E58,薪酬明细!$E:$E,$F58,薪酬明细!$H:$H,">="&Z$9,薪酬明细!$H:$H,"<="&Z$10,薪酬明细!$A:$A,Z$6)/10000 -> 11.4 | AA58: =SUMIFS(薪酬明细!$M:$M,薪酬明细!$D:$D,$E58,薪酬明细!$E:$E,$F58,薪酬明细!$H:$H,">="&AA$9,薪酬明细!$H:$H,"<="&AA$10,薪酬明细!$A:$A,AA$6)/10000 -> 11.4 | AB58: =SUMIFS(薪酬明细!$M:$M,薪酬明细!$D:$D,$E58,薪酬明细!$E:$E,$F58,薪酬明细!$H:$H,">="&AB$9,薪酬明细!$H:$H,"<="&AB$10,薪酬明细!$A:$A,AB$6)/10000 -> 11.4 | ... BG58: =SUMIFS(薪酬明细!$M:$M,薪酬明细!$D:$D,$E58,薪酬明细!$E:$E,$F58,薪酬明细!$H:$H,">="&BG$9,薪酬明细!$H:$H,"<="&BG$10,薪酬明细!$A:$A,BG$6)/10000 -> 11.3
D59: 销售中心 | E59: =IF(C59<>"",C59,E58) -> 流程中心 | F59: =IF(D59<>"",D59,"*") -> 销售中心 | G59: =SUMIFS(薪酬明细!$M:$M,薪酬明细!$D:$D,$E59,薪酬明细!$E:$E,$F59,薪酬明细!$H:$H,">="&G$9,薪酬明细!$H:$H,"<="&G$10,薪酬明细!$A:$A,G$6)/10000 -> 53 | H59: =SUMIFS(薪酬明细!$M:$M,薪酬明细!$D:$D,$E59,薪酬明细!$E:$E,$F59,薪酬明细!$H:$H,">="&H$9,薪酬明细!$H:$H,"<="&H$10,薪酬明细!$A:$A,H$6)/10000 -> 4.4 | I59: =SUMIFS(薪酬明细!$M:$M,薪酬明细!$D:$D,$E59,薪酬明细!$E:$E,$F59,薪酬明细!$H:$H,">="&I$9,薪酬明细!$H:$H,"<="&I$10,薪酬明细!$A:$A,I$6)/10000 -> 4.4 | J59: =SUMIFS(薪酬明细!$M:$M,薪酬明细!$D:$D,$E59,薪酬明细!$E:$E,$F59,薪酬明细!$H:$H,">="&J$9,薪酬明细!$H:$H,"<="&J$10,薪酬明细!$A:$A,J$6)/10000 -> 4.4 | K59: =SUMIFS(薪酬明细!$M:$M,薪酬明细!$D:$D,$E59,薪酬明细!$E:$E,$F59,薪酬明细!$H:$H,">="&K$9,薪酬明细!$H:$H,"<="&K$10,薪酬明细!$A:$A,K$6)/10000 -> 4.4 | L59: =SUMIFS(薪酬明细!$M:$M,薪酬明细!$D:$D,$E59,薪酬明细!$E:$E,$F59,薪酬明细!$H:$H,">="&L$9,薪酬明细!$H:$H,"<="&L$10,薪酬明细!$A:$A,L$6)/10000 -> 4.4 | M59: =SUMIFS(薪酬明细!$M:$M,薪酬明细!$D:$D,$E59,薪酬明细!$E:$E,$F59,薪酬明细!$H:$H,">="&M$9,薪酬明细!$H:$H,"<="&M$10,薪酬明细!$A:$A,M$6)/10000 -> 4.4 | N59: =SUMIFS(薪酬明细!$M:$M,薪酬明细!$D:$D,$E59,薪酬明细!$E:$E,$F59,薪酬明细!$H:$H,">="&N$9,薪酬明细!$H:$H,"<="&N$10,薪酬明细!$A:$A,N$6)/10000 -> 4.4 | ... S59: =SUMIFS(薪酬明细!$M:$M,薪酬明细!$D:$D,$E59,薪酬明细!$E:$E,$F59,薪酬明细!$H:$H,">="&S$9,薪酬明细!$H:$H,"<="&S$10,薪酬明细!$A:$A,S$6)/10000 -> 4.4 | T59: =U59+AH59 -> 53 | U59: =SUMIFS(薪酬明细!$M:$M,薪酬明细!$D:$D,$E59,薪酬明细!$E:$E,$F59,薪酬明细!$H:$H,">="&U$9,薪酬明细!$H:$H,"<="&U$10,薪酬明细!$A:$A,U$6)/10000 -> 39.7 | V59: =SUMIFS(薪酬明细!$M:$M,薪酬明细!$D:$D,$E59,薪酬明细!$E:$E,$F59,薪酬明细!$H:$H,">="&V$9,薪酬明细!$H:$H,"<="&V$10,薪酬明细!$A:$A,V$6)/10000 -> 4.4 | W59: =SUMIFS(薪酬明细!$M:$M,薪酬明细!$D:$D,$E59,薪酬明细!$E:$E,$F59,薪酬明细!$H:$H,">="&W$9,薪酬明细!$H:$H,"<="&W$10,薪酬明细!$A:$A,W$6)/10000 -> 4.4 | X59: =SUMIFS(薪酬明细!$M:$M,薪酬明细!$D:$D,$E59,薪酬明细!$E:$E,$F59,薪酬明细!$H:$H,">="&X$9,薪酬明细!$H:$H,"<="&X$10,薪酬明细!$A:$A,X$6)/10000 -> 4.4 | Y59: =SUMIFS(薪酬明细!$M:$M,薪酬明细!$D:$D,$E59,薪酬明细!$E:$E,$F59,薪酬明细!$H:$H,">="&Y$9,薪酬明细!$H:$H,"<="&Y$10,薪酬明细!$A:$A,Y$6)/10000 -> 4.4 | Z59: =SUMIFS(薪酬明细!$M:$M,薪酬明细!$D:$D,$E59,薪酬明细!$E:$E,$F59,薪酬明细!$H:$H,">="&Z$9,薪酬明细!$H:$H,"<="&Z$10,薪酬明细!$A:$A,Z$6)/10000 -> 4.4 | AA59: =SUMIFS(薪酬明细!$M:$M,薪酬明细!$D:$D,$E59,薪酬明细!$E:$E,$F59,薪酬明细!$H:$H,">="&AA$9,薪酬明细!$H:$H,"<="&AA$10,薪酬明细!$A:$A,AA$6)/10000 -> 4.5 | AB59: =SUMIFS(薪酬明细!$M:$M,薪酬明细!$D:$D,$E59,薪酬明细!$E:$E,$F59,薪酬明细!$H:$H,">="&AB$9,薪酬明细!$H:$H,"<="&AB$10,薪酬明细!$A:$A,AB$6)/10000 -> 4.4 | ... BG59: =SUMIFS(薪酬明细!$M:$M,薪酬明细!$D:$D,$E59,薪酬明细!$E:$E,$F59,薪酬明细!$H:$H,">="&BG$9,薪酬明细!$H:$H,"<="&BG$10,薪酬明细!$A:$A,BG$6)/10000 -> 4.4
D60: 制造中心 | E60: =IF(C60<>"",C60,E59) -> 流程中心 | F60: =IF(D60<>"",D60,"*") -> 制造中心 | G60: =SUMIFS(薪酬明细!$M:$M,薪酬明细!$D:$D,$E60,薪酬明细!$E:$E,$F60,薪酬明细!$H:$H,">="&G$9,薪酬明细!$H:$H,"<="&G$10,薪酬明细!$A:$A,G$6)/10000 -> 83.1 | H60: =SUMIFS(薪酬明细!$M:$M,薪酬明细!$D:$D,$E60,薪酬明细!$E:$E,$F60,薪酬明细!$H:$H,">="&H$9,薪酬明细!$H:$H,"<="&H$10,薪酬明细!$A:$A,H$6)/10000 -> 6.9 | I60: =SUMIFS(薪酬明细!$M:$M,薪酬明细!$D:$D,$E60,薪酬明细!$E:$E,$F60,薪酬明细!$H:$H,">="&I$9,薪酬明细!$H:$H,"<="&I$10,薪酬明细!$A:$A,I$6)/10000 -> 7 | J60: =SUMIFS(薪酬明细!$M:$M,薪酬明细!$D:$D,$E60,薪酬明细!$E:$E,$F60,薪酬明细!$H:$H,">="&J$9,薪酬明细!$H:$H,"<="&J$10,薪酬明细!$A:$A,J$6)/10000 -> 6.9 | K60: =SUMIFS(薪酬明细!$M:$M,薪酬明细!$D:$D,$E60,薪酬明细!$E:$E,$F60,薪酬明细!$H:$H,">="&K$9,薪酬明细!$H:$H,"<="&K$10,薪酬明细!$A:$A,K$6)/10000 -> 6.9 | L60: =SUMIFS(薪酬明细!$M:$M,薪酬明细!$D:$D,$E60,薪酬明细!$E:$E,$F60,薪酬明细!$H:$H,">="&L$9,薪酬明细!$H:$H,"<="&L$10,薪酬明细!$A:$A,L$6)/10000 -> 6.9 | M60: =SUMIFS(薪酬明细!$M:$M,薪酬明细!$D:$D,$E60,薪酬明细!$E:$E,$F60,薪酬明细!$H:$H,">="&M$9,薪酬明细!$H:$H,"<="&M$10,薪酬明细!$A:$A,M$6)/10000 -> 7 | N60: =SUMIFS(薪酬明细!$M:$M,薪酬明细!$D:$D,$E60,薪酬明细!$E:$E,$F60,薪酬明细!$H:$H,">="&N$9,薪酬明细!$H:$H,"<="&N$10,薪酬明细!$A:$A,N$6)/10000 -> 6.9 | ... S60: =SUMIFS(薪酬明细!$M:$M,薪酬明细!$D:$D,$E60,薪酬明细!$E:$E,$F60,薪酬明细!$H:$H,">="&S$9,薪酬明细!$H:$H,"<="&S$10,薪酬明细!$A:$A,S$6)/10000 -> 6.9 | T60: =U60+AH60 -> 83.2 | U60: =SUMIFS(薪酬明细!$M:$M,薪酬明细!$D:$D,$E60,薪酬明细!$E:$E,$F60,薪酬明细!$H:$H,">="&U$9,薪酬明细!$H:$H,"<="&U$10,薪酬明细!$A:$A,U$6)/10000 -> 62.4 | V60: =SUMIFS(薪酬明细!$M:$M,薪酬明细!$D:$D,$E60,薪酬明细!$E:$E,$F60,薪酬明细!$H:$H,">="&V$9,薪酬明细!$H:$H,"<="&V$10,薪酬明细!$A:$A,V$6)/10000 -> 6.9 | W60: =SUMIFS(薪酬明细!$M:$M,薪酬明细!$D:$D,$E60,薪酬明细!$E:$E,$F60,薪酬明细!$H:$H,">="&W$9,薪酬明细!$H:$H,"<="&W$10,薪酬明细!$A:$A,W$6)/10000 -> 6.9 | X60: =SUMIFS(薪酬明细!$M:$M,薪酬明细!$D:$D,$E60,薪酬明细!$E:$E,$F60,薪酬明细!$H:$H,">="&X$9,薪酬明细!$H:$H,"<="&X$10,薪酬明细!$A:$A,X$6)/10000 -> 6.9 | Y60: =SUMIFS(薪酬明细!$M:$M,薪酬明细!$D:$D,$E60,薪酬明细!$E:$E,$F60,薪酬明细!$H:$H,">="&Y$9,薪酬明细!$H:$H,"<="&Y$10,薪酬明细!$A:$A,Y$6)/10000 -> 6.9 | Z60: =SUMIFS(薪酬明细!$M:$M,薪酬明细!$D:$D,$E60,薪酬明细!$E:$E,$F60,薪酬明细!$H:$H,">="&Z$9,薪酬明细!$H:$H,"<="&Z$10,薪酬明细!$A:$A,Z$6)/10000 -> 6.9 | AA60: =SUMIFS(薪酬明细!$M:$M,薪酬明细!$D:$D,$E60,薪酬明细!$E:$E,$F60,薪酬明细!$H:$H,">="&AA$9,薪酬明细!$H:$H,"<="&AA$10,薪酬明细!$A:$A,AA$6)/10000 -> 6.9 | AB60: =SUMIFS(薪酬明细!$M:$M,薪酬明细!$D:$D,$E60,薪酬明细!$E:$E,$F60,薪酬明细!$H:$H,">="&AB$9,薪酬明细!$H:$H,"<="&AB$10,薪酬明细!$A:$A,AB$6)/10000 -> 7 | ... BG60: =SUMIFS(薪酬明细!$M:$M,薪酬明细!$D:$D,$E60,薪酬明细!$E:$E,$F60,薪酬明细!$H:$H,">="&BG$9,薪酬明细!$H:$H,"<="&BG$10,薪酬明细!$A:$A,BG$6)/10000 -> 6.9
C61: 创新中心 | E61: =IF(C61<>"",C61,E60) -> 创新中心 | F61: =IF(D61<>"",D61,"*") -> * | G61: =SUMIFS(薪酬明细!$M:$M,薪酬明细!$D:$D,$E61,薪酬明细!$E:$E,$F61,薪酬明细!$H:$H,">="&G$9,薪酬明细!$H:$H,"<="&G$10,薪酬明细!$A:$A,G$6)/10000 -> 75.4 | H61: =SUMIFS(薪酬明细!$M:$M,薪酬明细!$D:$D,$E61,薪酬明细!$E:$E,$F61,薪酬明细!$H:$H,">="&H$9,薪酬明细!$H:$H,"<="&H$10,薪酬明细!$A:$A,H$6)/10000 -> 6.3 | I61: =SUMIFS(薪酬明细!$M:$M,薪酬明细!$D:$D,$E61,薪酬明细!$E:$E,$F61,薪酬明细!$H:$H,">="&I$9,薪酬明细!$H:$H,"<="&I$10,薪酬明细!$A:$A,I$6)/10000 -> 6.3 | J61: =SUMIFS(薪酬明细!$M:$M,薪酬明细!$D:$D,$E61,薪酬明细!$E:$E,$F61,薪酬明细!$H:$H,">="&J$9,薪酬明细!$H:$H,"<="&J$10,薪酬明细!$A:$A,J$6)/10000 -> 6.4 | K61: =SUMIFS(薪酬明细!$M:$M,薪酬明细!$D:$D,$E61,薪酬明细!$E:$E,$F61,薪酬明细!$H:$H,">="&K$9,薪酬明细!$H:$H,"<="&K$10,薪酬明细!$A:$A,K$6)/10000 -> 6.3 | L61: =SUMIFS(薪酬明细!$M:$M,薪酬明细!$D:$D,$E61,薪酬明细!$E:$E,$F61,薪酬明细!$H:$H,">="&L$9,薪酬明细!$H:$H,"<="&L$10,薪酬明细!$A:$A,L$6)/10000 -> 6.2 | M61: =SUMIFS(薪酬明细!$M:$M,薪酬明细!$D:$D,$E61,薪酬明细!$E:$E,$F61,薪酬明细!$H:$H,">="&M$9,薪酬明细!$H:$H,"<="&M$10,薪酬明细!$A:$A,M$6)/10000 -> 6.3 | N61: =SUMIFS(薪酬明细!$M:$M,薪酬明细!$D:$D,$E61,薪酬明细!$E:$E,$F61,薪酬明细!$H:$H,">="&N$9,薪酬明细!$H:$H,"<="&N$10,薪酬明细!$A:$A,N$6)/10000 -> 6.3 | ... S61: =SUMIFS(薪酬明细!$M:$M,薪酬明细!$D:$D,$E61,薪酬明细!$E:$E,$F61,薪酬明细!$H:$H,">="&S$9,薪酬明细!$H:$H,"<="&S$10,薪酬明细!$A:$A,S$6)/10000 -> 6.4 | T61: =U61+AH61 -> 75.7 | U61: =SUMIFS(薪酬明细!$M:$M,薪酬明细!$D:$D,$E61,薪酬明细!$E:$E,$F61,薪酬明细!$H:$H,">="&U$9,薪酬明细!$H:$H,"<="&U$10,薪酬明细!$A:$A,U$6)/10000 -> 56.7 | V61: =SUMIFS(薪酬明细!$M:$M,薪酬明细!$D:$D,$E61,薪酬明细!$E:$E,$F61,薪酬明细!$H:$H,">="&V$9,薪酬明细!$H:$H,"<="&V$10,薪酬明细!$A:$A,V$6)/10000 -> 6.3 | W61: =SUMIFS(薪酬明细!$M:$M,薪酬明细!$D:$D,$E61,薪酬明细!$E:$E,$F61,薪酬明细!$H:$H,">="&W$9,薪酬明细!$H:$H,"<="&W$10,薪酬明细!$A:$A,W$6)/10000 -> 6.3 | X61: =SUMIFS(薪酬明细!$M:$M,薪酬明细!$D:$D,$E61,薪酬明细!$E:$E,$F61,薪酬明细!$H:$H,">="&X$9,薪酬明细!$H:$H,"<="&X$10,薪酬明细!$A:$A,X$6)/10000 -> 6.3 | Y61: =SUMIFS(薪酬明细!$M:$M,薪酬明细!$D:$D,$E61,薪酬明细!$E:$E,$F61,薪酬明细!$H:$H,">="&Y$9,薪酬明细!$H:$H,"<="&Y$10,薪酬明细!$A:$A,Y$6)/10000 -> 6.3 | Z61: =SUMIFS(薪酬明细!$M:$M,薪酬明细!$D:$D,$E61,薪酬明细!$E:$E,$F61,薪酬明细!$H:$H,">="&Z$9,薪酬明细!$H:$H,"<="&Z$10,薪酬明细!$A:$A,Z$6)/10000 -> 6.3 | AA61: =SUMIFS(薪酬明细!$M:$M,薪酬明细!$D:$D,$E61,薪酬明细!$E:$E,$F61,薪酬明细!$H:$H,">="&AA$9,薪酬明细!$H:$H,"<="&AA$10,薪酬明细!$A:$A,AA$6)/10000 -> 6.3 | AB61: =SUMIFS(薪酬明细!$M:$M,薪酬明细!$D:$D,$E61,薪酬明细!$E:$E,$F61,薪酬明细!$H:$H,">="&AB$9,薪酬明细!$H:$H,"<="&AB$10,薪酬明细!$A:$A,AB$6)/10000 -> 6.3 | ... BG61: =SUMIFS(薪酬明细!$M:$M,薪酬明细!$D:$D,$E61,薪酬明细!$E:$E,$F61,薪酬明细!$H:$H,">="&BG$9,薪酬明细!$H:$H,"<="&BG$10,薪酬明细!$A:$A,BG$6)/10000 -> 6.3
D62: 产品 研发部 | E62: =IF(C62<>"",C62,E61) -> 创新中心 | F62: =IF(D62<>"",D62,"*") -> 产品 研发部 | G62: =SUMIFS(薪酬明细!$M:$M,薪酬明细!$D:$D,$E62,薪酬明细!$E:$E,$F62,薪酬明细!$H:$H,">="&G$9,薪酬明细!$H:$H,"<="&G$10,薪酬明细!$A:$A,G$6)/10000 -> 30.1 | H62: =SUMIFS(薪酬明细!$M:$M,薪酬明细!$D:$D,$E62,薪酬明细!$E:$E,$F62,薪酬明细!$H:$H,">="&H$9,薪酬明细!$H:$H,"<="&H$10,薪酬明细!$A:$A,H$6)/10000 -> 2.5 | I62: =SUMIFS(薪酬明细!$M:$M,薪酬明细!$D:$D,$E62,薪酬明细!$E:$E,$F62,薪酬明细!$H:$H,">="&I$9,薪酬明细!$H:$H,"<="&I$10,薪酬明细!$A:$A,I$6)/10000 -> 2.5 | J62: =SUMIFS(薪酬明细!$M:$M,薪酬明细!$D:$D,$E62,薪酬明细!$E:$E,$F62,薪酬明细!$H:$H,">="&J$9,薪酬明细!$H:$H,"<="&J$10,薪酬明细!$A:$A,J$6)/10000 -> 2.5 | K62: =SUMIFS(薪酬明细!$M:$M,薪酬明细!$D:$D,$E62,薪酬明细!$E:$E,$F62,薪酬明细!$H:$H,">="&K$9,薪酬明细!$H:$H,"<="&K$10,薪酬明细!$A:$A,K$6)/10000 -> 2.6 | L62: =SUMIFS(薪酬明细!$M:$M,薪酬明细!$D:$D,$E62,薪酬明细!$E:$E,$F62,薪酬明细!$H:$H,">="&L$9,薪酬明细!$H:$H,"<="&L$10,薪酬明细!$A:$A,L$6)/10000 -> 2.5 | M62: =SUMIFS(薪酬明细!$M:$M,薪酬明细!$D:$D,$E62,薪酬明细!$E:$E,$F62,薪酬明细!$H:$H,">="&M$9,薪酬明细!$H:$H,"<="&M$10,薪酬明细!$A:$A,M$6)/10000 -> 2.5 | N62: =SUMIFS(薪酬明细!$M:$M,薪酬明细!$D:$D,$E62,薪酬明细!$E:$E,$F62,薪酬明细!$H:$H,">="&N$9,薪酬明细!$H:$H,"<="&N$10,薪酬明细!$A:$A,N$6)/10000 -> 2.5 | ... S62: =SUMIFS(薪酬明细!$M:$M,薪酬明细!$D:$D,$E62,薪酬明细!$E:$E,$F62,薪酬明细!$H:$H,">="&S$9,薪酬明细!$H:$H,"<="&S$10,薪酬明细!$A:$A,S$6)/10000 -> 2.6 | T62: =U62+AH62 -> 30.4 | U62: =SUMIFS(薪酬明细!$M:$M,薪酬明细!$D:$D,$E62,薪酬明细!$E:$E,$F62,薪酬明细!$H:$H,">="&U$9,薪酬明细!$H:$H,"<="&U$10,薪酬明细!$A:$A,U$6)/10000 -> 22.7 | V62: =SUMIFS(薪酬明细!$M:$M,薪酬明细!$D:$D,$E62,薪酬明细!$E:$E,$F62,薪酬明细!$H:$H,">="&V$9,薪酬明细!$H:$H,"<="&V$10,薪酬明细!$A:$A,V$6)/10000 -> 2.5 | W62: =SUMIFS(薪酬明细!$M:$M,薪酬明细!$D:$D,$E62,薪酬明细!$E:$E,$F62,薪酬明细!$H:$H,">="&W$9,薪酬明细!$H:$H,"<="&W$10,薪酬明细!$A:$A,W$6)/10000 -> 2.5 | X62: =SUMIFS(薪酬明细!$M:$M,薪酬明细!$D:$D,$E62,薪酬明细!$E:$E,$F62,薪酬明细!$H:$H,">="&X$9,薪酬明细!$H:$H,"<="&X$10,薪酬明细!$A:$A,X$6)/10000 -> 2.5 | Y62: =SUMIFS(薪酬明细!$M:$M,薪酬明细!$D:$D,$E62,薪酬明细!$E:$E,$F62,薪酬明细!$H:$H,">="&Y$9,薪酬明细!$H:$H,"<="&Y$10,薪酬明细!$A:$A,Y$6)/10000 -> 2.5 | Z62: =SUMIFS(薪酬明细!$M:$M,薪酬明细!$D:$D,$E62,薪酬明细!$E:$E,$F62,薪酬明细!$H:$H,">="&Z$9,薪酬明细!$H:$H,"<="&Z$10,薪酬明细!$A:$A,Z$6)/10000 -> 2.5 | AA62: =SUMIFS(薪酬明细!$M:$M,薪酬明细!$D:$D,$E62,薪酬明细!$E:$E,$F62,薪酬明细!$H:$H,">="&AA$9,薪酬明细!$H:$H,"<="&AA$10,薪酬明细!$A:$A,AA$6)/10000 -> 2.5 | AB62: =SUMIFS(薪酬明细!$M:$M,薪酬明细!$D:$D,$E62,薪酬明细!$E:$E,$F62,薪酬明细!$H:$H,">="&AB$9,薪酬明细!$H:$H,"<="&AB$10,薪酬明细!$A:$A,AB$6)/10000 -> 2.5 | ... BG62: =SUMIFS(薪酬明细!$M:$M,薪酬明细!$D:$D,$E62,薪酬明细!$E:$E,$F62,薪酬明细!$H:$H,">="&BG$9,薪酬明细!$H:$H,"<="&BG$10,薪酬明细!$A:$A,BG$6)/10000 -> 2.5
D63: XX 试验室 | E63: =IF(C63<>"",C63,E62) -> 创新中心 | F63: =IF(D63<>"",D63,"*") -> XX 试验室 | G63: =SUMIFS(薪酬明细!$M:$M,薪酬明细!$D:$D,$E63,薪酬明细!$E:$E,$F63,薪酬明细!$H:$H,">="&G$9,薪酬明细!$H:$H,"<="&G$10,薪酬明细!$A:$A,G$6)/10000 -> 18.9 | H63: =SUMIFS(薪酬明细!$M:$M,薪酬明细!$D:$D,$E63,薪酬明细!$E:$E,$F63,薪酬明细!$H:$H,">="&H$9,薪酬明细!$H:$H,"<="&H$10,薪酬明细!$A:$A,H$6)/10000 -> 1.6 | I63: =SUMIFS(薪酬明细!$M:$M,薪酬明细!$D:$D,$E63,薪酬明细!$E:$E,$F63,薪酬明细!$H:$H,">="&I$9,薪酬明细!$H:$H,"<="&I$10,薪酬明细!$A:$A,I$6)/10000 -> 1.6 | J63: =SUMIFS(薪酬明细!$M:$M,薪酬明细!$D:$D,$E63,薪酬明细!$E:$E,$F63,薪酬明细!$H:$H,">="&J$9,薪酬明细!$H:$H,"<="&J$10,薪酬明细!$A:$A,J$6)/10000 -> 1.6 | K63: =SUMIFS(薪酬明细!$M:$M,薪酬明细!$D:$D,$E63,薪酬明细!$E:$E,$F63,薪酬明细!$H:$H,">="&K$9,薪酬明细!$H:$H,"<="&K$10,薪酬明细!$A:$A,K$6)/10000 -> 1.6 | L63: =SUMIFS(薪酬明细!$M:$M,薪酬明细!$D:$D,$E63,薪酬明细!$E:$E,$F63,薪酬明细!$H:$H,">="&L$9,薪酬明细!$H:$H,"<="&L$10,薪酬明细!$A:$A,L$6)/10000 -> 1.6 | M63: =SUMIFS(薪酬明细!$M:$M,薪酬明细!$D:$D,$E63,薪酬明细!$E:$E,$F63,薪酬明细!$H:$H,">="&M$9,薪酬明细!$H:$H,"<="&M$10,薪酬明细!$A:$A,M$6)/10000 -> 1.6 | N63: =SUMIFS(薪酬明细!$M:$M,薪酬明细!$D:$D,$E63,薪酬明细!$E:$E,$F63,薪酬明细!$H:$H,">="&N$9,薪酬明细!$H:$H,"<="&N$10,薪酬明细!$A:$A,N$6)/10000 -> 1.5 | ... S63: =SUMIFS(薪酬明细!$M:$M,薪酬明细!$D:$D,$E63,薪酬明细!$E:$E,$F63,薪酬明细!$H:$H,">="&S$9,薪酬明细!$H:$H,"<="&S$10,薪酬明细!$A:$A,S$6)/10000 -> 1.6 | T63: =U63+AH63 -> 18.9 | U63: =SUMIFS(薪酬明细!$M:$M,薪酬明细!$D:$D,$E63,薪酬明细!$E:$E,$F63,薪酬明细!$H:$H,">="&U$9,薪酬明细!$H:$H,"<="&U$10,薪酬明细!$A:$A,U$6)/10000 -> 14.2 | V63: =SUMIFS(薪酬明细!$M:$M,薪酬明细!$D:$D,$E63,薪酬明细!$E:$E,$F63,薪酬明细!$H:$H,">="&V$9,薪酬明细!$H:$H,"<="&V$10,薪酬明细!$A:$A,V$6)/10000 -> 1.6 | W63: =SUMIFS(薪酬明细!$M:$M,薪酬明细!$D:$D,$E63,薪酬明细!$E:$E,$F63,薪酬明细!$H:$H,">="&W$9,薪酬明细!$H:$H,"<="&W$10,薪酬明细!$A:$A,W$6)/10000 -> 1.6 | X63: =SUMIFS(薪酬明细!$M:$M,薪酬明细!$D:$D,$E63,薪酬明细!$E:$E,$F63,薪酬明细!$H:$H,">="&X$9,薪酬明细!$H:$H,"<="&X$10,薪酬明细!$A:$A,X$6)/10000 -> 1.6 | Y63: =SUMIFS(薪酬明细!$M:$M,薪酬明细!$D:$D,$E63,薪酬明细!$E:$E,$F63,薪酬明细!$H:$H,">="&Y$9,薪酬明细!$H:$H,"<="&Y$10,薪酬明细!$A:$A,Y$6)/10000 -> 1.6 | Z63: =SUMIFS(薪酬明细!$M:$M,薪酬明细!$D:$D,$E63,薪酬明细!$E:$E,$F63,薪酬明细!$H:$H,">="&Z$9,薪酬明细!$H:$H,"<="&Z$10,薪酬明细!$A:$A,Z$6)/10000 -> 1.5 | AA63: =SUMIFS(薪酬明细!$M:$M,薪酬明细!$D:$D,$E63,薪酬明细!$E:$E,$F63,薪酬明细!$H:$H,">="&AA$9,薪酬明细!$H:$H,"<="&AA$10,薪酬明细!$A:$A,AA$6)/10000 -> 1.6 | AB63: =SUMIFS(薪酬明细!$M:$M,薪酬明细!$D:$D,$E63,薪酬明细!$E:$E,$F63,薪酬明细!$H:$H,">="&AB$9,薪酬明细!$H:$H,"<="&AB$10,薪酬明细!$A:$A,AB$6)/10000 -> 1.6 | ... BG63: =SUMIFS(薪酬明细!$M:$M,薪酬明细!$D:$D,$E63,薪酬明细!$E:$E,$F63,薪酬明细!$H:$H,">="&BG$9,薪酬明细!$H:$H,"<="&BG$10,薪酬明细!$A:$A,BG$6)/10000 -> 1.5
