Workbook

Sheet 主页
C5: 当年实际数据截止年月： | D5: 44500
C6: 资金占用利息率= | D6: 0.12

Sheet 应收账款
B3: 项 目 | E3: 年初 | F3: 1 | G3: 2 | H3: 3 | I3: 4 | J3: 5 | K3: 6 | L3: 7 | M3: 8 | N3: 9 | O3: 10 | P3: 11 | Q3: 12 | R3: 合计 | S3: 平均
B4: 资金占用利率= | D4: =主页!D6 -> 0.12
B5: ="实际"&YEAR(主页!$D$5)-1 -> 实际2020
C6: 销售收入 | F6: 10500 | G6: 9951 | H6: 10992 | I6: 9258 | J6: 11543 | K6: 9596 | L6: 10915 | M6: 9398 | N6: 10897 | O6: 10852 | P6: 9949 | Q6: 11467 | R6: =SUM(F6:Q6) -> 125318 | S6: —
C7: 应收账款余额 | E7: 3245 | F7: 3555 | G7: 3316 | H7: 4731 | I7: 4879 | J7: 3812 | K7: 4692 | L7: 3457 | M7: 3826 | N7: 3162 | O7: 3840 | P7: 4434 | Q7: 3593 | R7: — | S7: =SUM(E7/2,F7:P7,Q7/2)/12 -> 3926.9167
C8: 应收账款周转天数 | F8: =30/(F6/((E7+F7)/2)) -> 9.7142857 | G8: =30/(G6/((F7+G7)/2)) -> 10.357251 | H8: =30/(H6/((G7+H7)/2)) -> 10.981168 | I8: =30/(I6/((H7+I7)/2)) -> 15.570318 | J8: =30/(J6/((I7+J7)/2)) -> 11.293858 | K8: =30/(K6/((J7+K7)/2)) -> 13.293039 | L8: =30/(L6/((K7+L7)/2)) -> 11.198809 | M8: =30/(M6/((L7+M7)/2)) -> 11.624282 | ... Q8: =30/(Q6/((P7+Q7)/2)) -> 10.500131 | R8: — | S8: =360/(R6/S7) -> 11.280822
C9: 应收资金占用成本 | F9: =F7*$D$4/12 -> 35.55 | G9: =G7*$D$4/12 -> 33.16 | H9: =H7*$D$4/12 -> 47.31 | I9: =I7*$D$4/12 -> 48.79 | J9: =J7*$D$4/12 -> 38.12 | K9: =K7*$D$4/12 -> 46.92 | L9: =L7*$D$4/12 -> 34.57 | M9: =M7*$D$4/12 -> 38.26 | ... Q9: =Q7*$D$4/12 -> 35.93 | R9: =SUM(F9:Q9) -> 472.97 | S9: —
B10: ="实际/估计"&YEAR(主页!$D$5) -> 实际/估计2021
C11: 销售收入 | F11: 11431 | G11: 11189 | H11: 9600 | I11: 9170 | J11: 9511 | K11: 9859 | L11: 10711 | M11: 10947 | N11: 11380 | O11: 10767 | P11: 10626 | Q11: 10659 | R11: =SUM(F11:Q11) -> 125850 | S11: —
C12: 应收账款余额 | E12: =Q7 -> 3593 | F12: 4468 | G12: 4705 | H12: 3458 | I12: 4517 | J12: 4420 | K12: 4495 | L12: 3256 | M12: 3173 | N12: 3195 | O12: 3850 | P12: 3664 | Q12: 3064 | R12: — | S12: =SUM(E12/2,F12:P12,Q12/2)/12 -> 3877.4583
C13: 应收账款周转天数 | F13: =30/(F11/((E12+F12)/2)) -> 10.577815 | G13: =30/(G11/((F12+G12)/2)) -> 12.297346 | H13: =30/(H11/((G12+H12)/2)) -> 12.754687 | I13: =30/(I11/((H12+I12)/2)) -> 13.045256 | J13: =30/(J11/((I12+J12)/2)) -> 14.094732 | K13: =30/(K11/((J12+K12)/2)) -> 13.563749 | L13: =30/(L11/((K12+L12)/2)) -> 10.854729 | M13: =30/(M11/((L12+M12)/2)) -> 8.8092628 | ... Q13: =30/(Q11/((P12+Q12)/2)) -> 9.4680552 | R13: — | S13: =360/(R11/S12) -> 11.091657
C14: 应收资金占用成本 | F14: =F12*$D$4/12 -> 44.68 | G14: =G12*$D$4/12 -> 47.05 | H14: =H12*$D$4/12 -> 34.58 | I14: =I12*$D$4/12 -> 45.17 | J14: =J12*$D$4/12 -> 44.2 | K14: =K12*$D$4/12 -> 44.95 | L14: =L12*$D$4/12 -> 32.56 | M14: =M12*$D$4/12 -> 31.73 | ... Q14: =Q12*$D$4/12 -> 30.64 | R14: =SUM(F14:Q14) -> 462.65 | S14: —
B15: ="预算"&YEAR(主页!$D$5)+1 -> 预算2022
C16: 销售收入 | F16: 9587 | G16: 9159 | H16: 11151 | I16: 10011 | J16: 9173 | K16: 11043 | L16: 10383 | M16: 10690 | N16: 10971 | O16: 9647 | P16: 9719 | Q16: 11466 | R16: =SUM(F16:Q16) -> 123000 | S16: —
C17: 应收账款余额 | E17: =Q12 -> 3064 | F17: 4920 | G17: 4490 | H17: 3134 | I17: 3071 | J17: 3481 | K17: 3157 | L17: 4155 | M17: 3067 | N17: 3756 | O17: 4804 | P17: 4221 | Q17: 4599 | R17: — | S17: =SUM(E17/2,F17:P17,Q17/2)/12 -> 3840.625
C18: 应收账款周转天数 | F18: =30/(F16/((E17+F17)/2)) -> 12.491916 | G18: =30/(G16/((F17+G17)/2)) -> 15.411071 | H18: =30/(H16/((G17+H17)/2)) -> 10.255582 | I18: =30/(I16/((H17+I17)/2)) -> 9.297273 | J18: =30/(J16/((I17+J17)/2)) -> 10.714052 | K18: =30/(K16/((J17+K17)/2)) -> 9.0165716 | L18: =30/(L16/((K17+L17)/2)) -> 10.563421 | M18: =30/(M16/((L17+M17)/2)) -> 10.13377 | ... Q18: =30/(Q16/((P17+Q17)/2)) -> 11.538462 | R18: — | S18: =360/(R16/S17) -> 11.240854
C19: 应收资金占用成本 | F19: =F17*$D$4/12 -> 49.2 | G19: =G17*$D$4/12 -> 44.9 | H19: =H17*$D$4/12 -> 31.34 | I19: =I17*$D$4/12 -> 30.71 | J19: =J17*$D$4/12 -> 34.81 | K19: =K17*$D$4/12 -> 31.57 | L19: =L17*$D$4/12 -> 41.55 | M19: =M17*$D$4/12 -> 30.67 | ... Q19: =Q17*$D$4/12 -> 45.99 | R19: =SUM(F19:Q19) -> 468.55 | S19: —

Sheet 应付账款
B3: 项 目 | E3: 年初 | F3: 1 | G3: 2 | H3: 3 | I3: 4 | J3: 5 | K3: 6 | L3: 7 | M3: 8 | N3: 9 | O3: 10 | P3: 11 | Q3: 12 | R3: 合计 | S3: 平均
B4: 资金占用利率= | D4: =主页!D6 -> 0.12
B5: ="实际"&YEAR(主页!$D$5)-1 -> 实际2020
C6: 采购额 | F6: 6300 | G6: 5970.6 | H6: 6595.2 | I6: 5554.8 | J6: 6925.8 | K6: 5757.6 | L6: 6549 | M6: 5638.8 | N6: 6538.2 | O6: 6511.2 | P6: 5969.4 | Q6: 6880.2 | R6: =SUM(F6:Q6) -> 75190.8 | S6: —
C7: 应付账款余额 | E7: 2044 | F7: 2133 | G7: 1989.6 | H7: 2838.6 | I7: 2927.4 | J7: 2287.2 | K7: 2815.2 | L7: 2074.2 | M7: 2295.6 | N7: 1897.2 | O7: 2304 | P7: 2660.4 | Q7: 2155.8 | R7: — | S7: =SUM(E7/2,F7:P7,Q7/2)/12 -> 2360.1917
C8: 应付账款周转天数 | F8: =30/(F6/((E7+F7)/2)) -> 9.9452381 | G8: =30/(G6/((F7+G7)/2)) -> 10.357251 | H8: =30/(H6/((G7+H7)/2)) -> 10.981168 | I8: =30/(I6/((H7+I7)/2)) -> 15.570318 | J8: =30/(J6/((I7+J7)/2)) -> 11.293858 | K8: =30/(K6/((J7+K7)/2)) -> 13.293039 | L8: =30/(L6/((K7+L7)/2)) -> 11.198809 | M8: =30/(M6/((L7+M7)/2)) -> 11.624282 | ... Q8: =30/(Q6/((P7+Q7)/2)) -> 10.500131 | R8: — | S8: =360/(R6/S7) -> 11.300172
C9: 应付抵减资金占用成本 | F9: =F7*$D$4/12 -> 21.33 | G9: =G7*$D$4/12 -> 19.896 | H9: =H7*$D$4/12 -> 28.386 | I9: =I7*$D$4/12 -> 29.274 | J9: =J7*$D$4/12 -> 22.872 | K9: =K7*$D$4/12 -> 28.152 | L9: =L7*$D$4/12 -> 20.742 | M9: =M7*$D$4/12 -> 22.956 | ... Q9: =Q7*$D$4/12 -> 21.558 | R9: =SUM(F9:Q9) -> 283.782 | S9: —
B10: ="实际/估计"&YEAR(主页!$D$5) -> 实际/估计2021
C11: 采购额 | F11: 6858.6 | G11: 6713.4 | H11: 5760 | I11: 5502 | J11: 5706.6 | K11: 5915.4 | L11: 6426.6 | M11: 6568.2 | N11: 6828 | O11: 6460.2 | P11: 6375.6 | Q11: 6395.4 | R11: =SUM(F11:Q11) -> 75510 | S11: —
C12: 应付账款余额 | E12: =Q7 -> 2155.8 | F12: 2680.8 | G12: 2823 | H12: 2074.8 | I12: 2710.2 | J12: 2652 | K12: 2697 | L12: 1953.6 | M12: 1903.8 | N12: 1917 | O12: 2310 | P12: 2198.4 | Q12: 1838.4 | R12: — | S12: =SUM(E12/2,F12:P12,Q12/2)/12 -> 2326.475
C13: 应付账款周转天数 | F13: =30/(F11/((E12+F12)/2)) -> 10.577815 | G13: =30/(G11/((F12+G12)/2)) -> 12.297346 | H13: =30/(H11/((G12+H12)/2)) -> 12.754687 | I13: =30/(I11/((H12+I12)/2)) -> 13.045256 | J13: =30/(J11/((I12+J12)/2)) -> 14.094732 | K13: =30/(K11/((J12+K12)/2)) -> 13.563749 | L13: =30/(L11/((K12+L12)/2)) -> 10.854729 | M13: =30/(M11/((L12+M12)/2)) -> 8.8092628 | ... Q13: =30/(Q11/((P12+Q12)/2)) -> 9.4680552 | R13: — | S13: =360/(R11/S12) -> 11.091657
C14: 应付抵减资金占用成本 | F14: =F12*$D$4/12 -> 26.808 | G14: =G12*$D$4/12 -> 28.23 | H14: =H12*$D$4/12 -> 20.748 | I14: =I12*$D$4/12 -> 27.102 | J14: =J12*$D$4/12 -> 26.52 | K14: =K12*$D$4/12 -> 26.97 | L14: =L12*$D$4/12 -> 19.536 | M14: =M12*$D$4/12 -> 19.038 | ... Q14: =Q12*$D$4/12 -> 18.384 | R14: =SUM(F14:Q14) -> 277.59 | S14: —
B15: ="预算"&YEAR(主页!$D$5)+1 -> 预算2022
C16: 采购额 | F16: 5752.2 | G16: 5495.4 | H16: 6690.6 | I16: 6006.6 | J16: 5503.8 | K16: 6625.8 | L16: 6229.8 | M16: 6414 | N16: 6582.6 | O16: 5788.2 | P16: 5831.4 | Q16: 6879.6 | R16: =SUM(F16:Q16) -> 73800 | S16: —
C17: 应付账款余额 | E17: =Q12 -> 1838.4 | F17: 2952 | G17: 2694 | H17: 1880.4 | I17: 1842.6 | J17: 2088.6 | K17: 1894.2 | L17: 2493 | M17: 1840.2 | N17: 2253.6 | O17: 2882.4 | P17: 2532.6 | Q17: 2759.4 | R17: — | S17: =SUM(E17/2,F17:P17,Q17/2)/12 -> 2304.375
C18: 应付账款周转天数 | F18: =30/(F16/((E17+F17)/2)) -> 12.491916 | G18: =30/(G16/((F17+G17)/2)) -> 15.411071 | H18: =30/(H16/((G17+H17)/2)) -> 10.255582 | I18: =30/(I16/((H17+I17)/2)) -> 9.297273 | J18: =30/(J16/((I17+J17)/2)) -> 10.714052 | K18: =30/(K16/((J17+K17)/2)) -> 9.0165716 | L18: =30/(L16/((K17+L17)/2)) -> 10.563421 | M18: =30/(M16/((L17+M17)/2)) -> 10.13377 | ... Q18: =30/(Q16/((P17+Q17)/2)) -> 11.538462 | R18: — | S18: =360/(R16/S17) -> 11.240854
C19: 应付抵减资金占用成本 | F19: =F17*$D$4/12 -> 29.52 | G19: =G17*$D$4/12 -> 26.94 | H19: =H17*$D$4/12 -> 18.804 | I19: =I17*$D$4/12 -> 18.426 | J19: =J17*$D$4/12 -> 20.886 | K19: =K17*$D$4/12 -> 18.942 | L19: =L17*$D$4/12 -> 24.93 | M19: =M17*$D$4/12 -> 18.402 | ... Q19: =Q17*$D$4/12 -> 27.594 | R19: =SUM(F19:Q19) -> 281.13 | S19: —

Sheet 存货
B3: 项 目 | F3: 年初 | G3: 1 | H3: 2 | I3: 3 | J3: 4 | K3: 5 | L3: 6 | M3: 7 | N3: 8 | O3: 9 | P3: 10 | Q3: 11 | R3: 12 | S3: 合计 | T3: 平均
B4: 资金占用利率= | E4: =主页!D6 -> 0.12
B5: ="实际"&YEAR(主页!$D$5)-1 -> 实际2020
C6: 销售成本 | G6: 8400 | H6: 7960.8 | I6: 8793.6 | J6: 7406.4 | K6: 9234.4 | L6: 7676.8 | M6: 8732 | N6: 7518.4 | O6: 8717.6 | P6: 8681.6 | Q6: 7959.2 | R6: 9173.6 | S6: =SUM(G6:R6) -> 100254.4 | T6: —
C7: 存货 | F7: 2978.01 | G7: 3092.85 | H7: 2884.92 | I7: 4115.97 | J7: 4244.73 | K7: 3316.44 | L7: 4082.04 | M7: 3007.59 | N7: 3328.62 | O7: 2750.94 | P7: 3340.8 | Q7: 3857.58 | R7: 3125.91 | S7: — | T7: =SUM(F7/2,G7:Q7,R7/2)/12 -> 3422.87
C8: 其中: | D8: 外购成品 | F8: 1026.9 | G8: 1066.5 | H8: 994.8 | I8: 1419.3 | J8: 1463.7 | K8: 1143.6 | L8: 1407.6 | M8: 1037.1 | N8: 1147.8 | O8: 948.6 | P8: 1152 | Q8: 1330.2 | R8: 1077.9 | S8: — | T8: =SUM(F8/2,G8:Q8,R8/2)/12 -> 1180.3
D9: 材料及半成品 | F9: 1711.5 | G9: =G7-G8-G10 -> 1315.35 | H9: =H7-H8-H10 -> 1226.92 | I9: =I7-I8-I10 -> 1750.47 | J9: =J7-J8-J10 -> 1805.23 | K9: =K7-K8-K10 -> 1410.44 | L9: =L7-L8-L10 -> 1736.04 | M9: =M7-M8-M10 -> 1279.09 | N9: =N7-N8-N10 -> 1415.62 | ... R9: =R7-R8-R10 -> 1329.41 | S9: — | T9: =SUM(F9/2,G9:Q9,R9/2)/12 -> 1474.2446
D10: 自制成品 | F10: 684.6 | G10: 711 | H10: 663.2 | I10: 946.2 | J10: 975.8 | K10: 762.4 | L10: 938.4 | M10: 691.4 | N10: 765.2 | O10: 632.4 | P10: 768 | Q10: 886.8 | R10: 718.6 | S10: — | T10: =SUM(F10/2,G10:Q10,R10/2)/12 -> 786.86667
C11: 存货周转天数 | G11: =30/(G6/((F7+G7)/2)) -> 10.840821 | H11: =30/(H6/((G7+H7)/2)) -> 11.26351 | I11: =30/(I6/((H7+I7)/2)) -> 11.94202 | J11: =30/(J6/((I7+J7)/2)) -> 16.93272 | K11: =30/(K6/((J7+K7)/2)) -> 12.28207 | L11: =30/(L6/((K7+L7)/2)) -> 14.45618 | M11: =30/(M6/((L7+M7)/2)) -> 12.178705 | N11: =30/(N6/((M7+N7)/2)) -> 12.641406 | ... R11: =30/(R6/((Q7+R7)/2)) -> 11.418892 | S11: — | T11: =360/(S6/T7) -> 12.291064
C12: 存货占用资金成本 | G12: =G7*$E$4/12 -> 30.9285 | H12: =H7*$E$4/12 -> 28.8492 | I12: =I7*$E$4/12 -> 41.1597 | J12: =J7*$E$4/12 -> 42.4473 | K12: =K7*$E$4/12 -> 33.1644 | L12: =L7*$E$4/12 -> 40.8204 | M12: =M7*$E$4/12 -> 30.0759 | N12: =N7*$E$4/12 -> 33.2862 | ... R12: =R7*$E$4/12 -> 31.2591 | S12: =SUM(G12:R12) -> 411.4839 | T12: —
B13: ="实际/估计"&YEAR(主页!$D$5) -> 实际/估计2021
C14: 销售成本 | G14: 9144.8 | H14: 8951.2 | I14: 7680 | J14: 7336 | K14: 7608.8 | L14: 7887.2 | M14: 8568.8 | N14: 8757.6 | O14: 9104 | P14: 8613.6 | Q14: 8500.8 | R14: 8527.2 | S14: =SUM(G14:R14) -> 100680 | T14: —
C15: 存货 | F15: =R7 -> 3125.91 | G15: 4468 | H15: 4705 | I15: 3458 | J15: 4517 | K15: 4420 | L15: 4495 | M15: 3256 | N15: 3173 | O15: 3195 | P15: 3850 | Q15: 3664 | R15: 3064 | S15: — | T15: =SUM(F15/2,G15:Q15,R15/2)/12 -> 3857.9963
C16: 其中: | D16: 外购成品 | F16: =R8 -> 1077.9 | G16: =G15*0.3 -> 1340.4 | H16: =H15*0.3 -> 1411.5 | I16: =I15*0.3 -> 1037.4 | J16: =J15*0.3 -> 1355.1 | K16: =K15*0.3 -> 1326 | L16: =L15*0.3 -> 1348.5 | M16: =M15*0.3 -> 976.8 | N16: =N15*0.3 -> 951.9 | ... R16: =R15*0.3 -> 919.2 | S16: — | T16: =SUM(F16/2,G16:Q16,R16/2)/12 -> 1163.2375
D17: 材料及半成品 | F17: =R9 -> 1329.41 | G17: =G15-G16-G18 -> 2234 | H17: =H15-H16-H18 -> 2352.5 | I17: =I15-I16-I18 -> 1729 | J17: =J15-J16-J18 -> 2258.5 | K17: =K15-K16-K18 -> 2210 | L17: =L15-L16-L18 -> 2247.5 | M17: =M15-M16-M18 -> 1628 | N17: =N15-N16-N18 -> 1586.5 | ... R17: =R15-R16-R18 -> 1532 | S17: — | T17: =SUM(F17/2,G17:Q17,R17/2)/12 -> 1919.2671
D18: 自制成品 | F18: =R10 -> 718.6 | G18: =G$15*0.2 -> 893.6 | H18: =H$15*0.2 -> 941 | I18: =I$15*0.2 -> 691.6 | J18: =J$15*0.2 -> 903.4 | K18: =K$15*0.2 -> 884 | L18: =L$15*0.2 -> 899 | M18: =M$15*0.2 -> 651.2 | N18: =N$15*0.2 -> 634.6 | ... R18: =R$15*0.2 -> 612.8 | S18: — | T18: =SUM(F18/2,G18:Q18,R18/2)/12 -> 775.49167
C19: 存货周转天数 | G19: =30/(G14/((F15+G15)/2)) -> 12.456112 | H19: =30/(H14/((G15+H15)/2)) -> 15.371682 | I19: =30/(I14/((H15+I15)/2)) -> 15.943359 | J19: =30/(J14/((I15+J15)/2)) -> 16.30657 | K19: =30/(K14/((J15+K15)/2)) -> 17.618416 | L19: =30/(L14/((K15+L15)/2)) -> 16.954686 | M19: =30/(M14/((L15+M15)/2)) -> 13.568411 | N19: =30/(N14/((M15+N15)/2)) -> 11.011579 | ... R19: =30/(R14/((Q15+R15)/2)) -> 11.835069 | S19: — | T19: =360/(S14/T15) -> 13.794981
C20: 存货占用资金成本 | G20: =G15*$E$4/12 -> 44.68 | H20: =H15*$E$4/12 -> 47.05 | I20: =I15*$E$4/12 -> 34.58 | J20: =J15*$E$4/12 -> 45.17 | K20: =K15*$E$4/12 -> 44.2 | L20: =L15*$E$4/12 -> 44.95 | M20: =M15*$E$4/12 -> 32.56 | N20: =N15*$E$4/12 -> 31.73 | ... R20: =R15*$E$4/12 -> 30.64 | S20: =SUM(G20:R20) -> 462.65 | T20: —
B21: ="预算"&YEAR(主页!$D$5)+1 -> 预算2022
C22: 销售成本 | G22: 7669.6 | H22: 7327.2 | I22: 8920.8 | J22: 8008.8 | K22: 7338.4 | L22: 8834.4 | M22: 8306.4 | N22: 8552 | O22: 8776.8 | P22: 7717.6 | Q22: 7775.2 | R22: 9172.8 | S22: =SUM(G22:R22) -> 98400 | T22: —
C23: 存货 | F23: =R15 -> 3064 | G23: =(G22*0.3)*0.76 -> 1748.6688 | H23: 3412.4 | I23: 2381.84 | J23: 2333.96 | K23: 2645.56 | L23: 2399.32 | M23: 3157.8 | N23: 2330.92 | O23: 2854.56 | P23: 3651.04 | Q23: 3207.96 | R23: 3495.24 | S23: — | T23: =SUM(F23/2,G23:Q23,R23/2)/12 -> 2783.6374
C24: 其中: | D24: 外购成品 | F24: =R16 -> 919.2 | G24: =G$23*0.3 -> 524.60064 | H24: =H$23*0.3 -> 1023.72 | I24: =I$23*0.3 -> 714.552 | J24: =J$23*0.3 -> 700.188 | K24: =K$23*0.3 -> 793.668 | L24: =L$23*0.3 -> 719.796 | M24: =M$23*0.3 -> 947.34 | N24: =N$23*0.3 -> 699.276 | ... R24: =R$23*0.3 -> 1048.572 | S24: — | T24: =SUM(F24/2,G24:Q24,R24/2)/12 -> 835.09122
D25: 材料及半成品 | F25: =R17 -> 1532 | G25: =G23-G24-G26 -> 874.3344 | H25: =H23-H24-H26 -> 1706.2 | I25: =I23-I24-I26 -> 1190.92 | J25: =J23-J24-J26 -> 1166.98 | K25: =K23-K24-K26 -> 1322.78 | L25: =L23-L24-L26 -> 1199.66 | M25: =M23-M24-M26 -> 1578.9 | N25: =N23-N24-N26 -> 1165.46 | ... R25: =R23-R24-R26 -> 1747.62 | S25: — | T25: =SUM(F25/2,G25:Q25,R25/2)/12 -> 1391.8187
D26: 自制成品 | F26: =R18 -> 612.8 | G26: =G$23*0.2 -> 349.73376 | H26: =H$23*0.2 -> 682.48 | I26: =I$23*0.2 -> 476.368 | J26: =J$23*0.2 -> 466.792 | K26: =K$23*0.2 -> 529.112 | L26: =L$23*0.2 -> 479.864 | M26: =M$23*0.2 -> 631.56 | N26: =N$23*0.2 -> 466.184 | ... R26: =R$23*0.2 -> 699.048 | S26: — | T26: =SUM(F26/2,G26:Q26,R26/2)/12 -> 556.72748
C27: 存货周转天数 | G27: =30/(G22/((F23+G23)/2)) -> 9.4124898 | H27: =30/(H22/((G23+H23)/2)) -> 10.565568 | I27: =30/(I22/((H23+I23)/2)) -> 9.7428033 | J27: =30/(J22/((I23+J23)/2)) -> 8.8324093 | K27: =30/(K22/((J23+K23)/2)) -> 10.17835 | L27: =30/(L22/((K23+L23)/2)) -> 8.565743 | M27: =30/(M22/((L23+M23)/2)) -> 10.03525 | N27: =30/(N22/((M23+N23)/2)) -> 9.6270814 | ... R27: =30/(R22/((Q23+R23)/2)) -> 10.961538 | S27: — | T27: =360/(S22/T23) -> 10.184039
C28: 存货占用资金成本 | G28: =G23*$E$4/12 -> 17.486688 | H28: =H23*$E$4/12 -> 34.124 | I28: =I23*$E$4/12 -> 23.8184 | J28: =J23*$E$4/12 -> 23.3396 | K28: =K23*$E$4/12 -> 26.4556 | L28: =L23*$E$4/12 -> 23.9932 | M28: =M23*$E$4/12 -> 31.578 | N28: =N23*$E$4/12 -> 23.3092 | ... R28: =R23*$E$4/12 -> 34.9524 | S28: =SUM(G28:R28) -> 336.19269 | T28: —

Sheet 长期资产
B1: 固定资产净值从资产明细数据中取值
B3: 项 目 | E3: 年初 | F3: 1 | G3: 2 | H3: 3 | I3: 4 | J3: 5 | K3: 6 | L3: 7 | M3: 8 | N3: 9 | O3: 10 | P3: 11 | Q3: 12 | R3: 合计 | S3: 平均
B4: 资金占用利率= | D4: =主页!D6 -> 0.12
B5: ="实际"&YEAR(主页!$D$5)-1 -> 实际2020
C6: 销售成本 | F6: 8400 | G6: 7960.8 | H6: 8793.6 | I6: 7406.4 | J6: 9234.4 | K6: 7676.8 | L6: 8732 | M6: 7518.4 | N6: 8717.6 | O6: 8681.6 | P6: 7959.2 | Q6: 9173.6 | R6: =SUM(F6:Q6) -> 100254.4 | S6: —
C7: 长期资产净值余额 | E7: 1812 | F7: 1777.5 | G7: 1658 | H7: 2365.5 | I7: 2439.5 | J7: 1906 | K7: 2346 | L7: 1728.5 | M7: 1913 | N7: 1581 | O7: 1920 | P7: 2217 | Q7: 1796.5 | R7: — | S7: =SUM(E7/2,F7:P7,Q7/2)/12 -> 1971.3542
C8: 长期资产周转天数 | F8: =30/(F6/((E7+F7)/2)) -> 6.4098214 | G8: =30/(G6/((F7+G7)/2)) -> 6.4732816 | H8: =30/(H6/((G7+H7)/2)) -> 6.8632301 | I8: =30/(I6/((H7+I7)/2)) -> 9.7314485 | J8: =30/(J6/((I7+J7)/2)) -> 7.0586611 | K8: =30/(K6/((J7+K7)/2)) -> 8.3081492 | L8: =30/(L6/((K7+L7)/2)) -> 6.9992556 | M8: =30/(M6/((L7+M7)/2)) -> 7.2651761 | ... Q8: =30/(Q6/((P7+Q7)/2)) -> 6.5625818 | R8: — | S8: =360/(R6/S7) -> 7.0788664
C9: 长期资产占用资金成本 | F9: =F7*$D$4/12 -> 17.775 | G9: =G7*$D$4/12 -> 16.58 | H9: =H7*$D$4/12 -> 23.655 | I9: =I7*$D$4/12 -> 24.395 | J9: =J7*$D$4/12 -> 19.06 | K9: =K7*$D$4/12 -> 23.46 | L9: =L7*$D$4/12 -> 17.285 | M9: =M7*$D$4/12 -> 19.13 | ... Q9: =Q7*$D$4/12 -> 17.965 | R9: =SUM(F9:Q9) -> 236.485 | S9: —
B10: ="实际/估计"&YEAR(主页!$D$5) -> 实际/估计2021
C11: 销售成本 | F11: 9144.8 | G11: 8951.2 | H11: 7680 | I11: 7336 | J11: 7608.8 | K11: 7887.2 | L11: 8568.8 | M11: 8757.6 | N11: 9104 | O11: 8613.6 | P11: 8500.8 | Q11: 8527.2 | R11: =SUM(F11:Q11) -> 100680 | S11: —
C12: 长期资产净值余额 | E12: =Q7 -> 1796.5 | F12: 2234 | G12: 2352.5 | H12: 1729 | I12: 2258.5 | J12: 2210 | K12: 2247.5 | L12: 1628 | M12: 1586.5 | N12: 1597.5 | O12: 1925 | P12: 1832 | Q12: 1532 | R12: — | S12: =SUM(E12/2,F12:P12,Q12/2)/12 -> 1938.7292
C13: 长期资产周转天数 | F13: =30/(F11/((E12+F12)/2)) -> 6.6111342 | G13: =30/(G11/((F12+G12)/2)) -> 7.685841 | H13: =30/(H11/((G12+H12)/2)) -> 7.9716797 | I13: =30/(I11/((H12+I12)/2)) -> 8.1532852 | J13: =30/(J11/((I12+J12)/2)) -> 8.8092078 | K13: =30/(K11/((J12+K12)/2)) -> 8.477343 | L13: =30/(L11/((K12+L12)/2)) -> 6.7842055 | M13: =30/(M11/((L12+M12)/2)) -> 5.5057893 | ... Q13: =30/(Q11/((P12+Q12)/2)) -> 5.9175345 | R13: — | S13: =360/(R11/S12) -> 6.9322855
C14: 长期资产占用资金成本 | F14: =F12*$D$4/12 -> 22.34 | G14: =G12*$D$4/12 -> 23.525 | H14: =H12*$D$4/12 -> 17.29 | I14: =I12*$D$4/12 -> 22.585 | J14: =J12*$D$4/12 -> 22.1 | K14: =K12*$D$4/12 -> 22.475 | L14: =L12*$D$4/12 -> 16.28 | M14: =M12*$D$4/12 -> 15.865 | ... Q14: =Q12*$D$4/12 -> 15.32 | R14: =SUM(F14:Q14) -> 231.325 | S14: —
B15: ="预算"&YEAR(主页!$D$5)+1 -> 预算2022
C16: 销售成本 | F16: 7669.6 | G16: 7327.2 | H16: 8920.8 | I16: 8008.8 | J16: 7338.4 | K16: 8834.4 | L16: 8306.4 | M16: 8552 | N16: 8776.8 | O16: 7717.6 | P16: 7775.2 | Q16: 9172.8 | R16: =SUM(F16:Q16) -> 98400 | S16: —
C17: 长期资产净值余额 | E17: =Q12 -> 1532 | F17: 1968 | G17: 1796 | H17: 1253.6 | I17: 1228.4 | J17: 1392.4 | K17: 1262.8 | L17: 1662 | M17: 1226.8 | N17: 1502.4 | O17: 1921.6 | P17: 1688.4 | Q17: 1839.6 | R17: — | S17: =SUM(E17/2,F17:P17,Q17/2)/12 -> 1549.0167
C18: 长期资产周转天数 | F18: =30/(F16/((E17+F17)/2)) -> 6.8452071 | G18: =30/(G16/((F17+G17)/2)) -> 7.7055355 | H18: =30/(H16/((G17+H17)/2)) -> 5.1277912 | I18: =30/(I16/((H17+I17)/2)) -> 4.6486365 | J18: =30/(J16/((I17+J17)/2)) -> 5.3570261 | K18: =30/(K16/((J17+K17)/2)) -> 4.5082858 | L18: =30/(L16/((K17+L17)/2)) -> 5.2817105 | M18: =30/(M16/((L17+M17)/2)) -> 5.0668849 | ... Q18: =30/(Q16/((P17+Q17)/2)) -> 5.7692308 | R18: — | S18: =360/(R16/S17) -> 5.6671341
C19: 长期资产占用资金成本 | F19: =F17*$D$4/12 -> 19.68 | G19: =G17*$D$4/12 -> 17.96 | H19: =H17*$D$4/12 -> 12.536 | I19: =I17*$D$4/12 -> 12.284 | J19: =J17*$D$4/12 -> 13.924 | K19: =K17*$D$4/12 -> 12.628 | L19: =L17*$D$4/12 -> 16.62 | M19: =M17*$D$4/12 -> 12.268 | ... Q19: =Q17*$D$4/12 -> 18.396 | R19: =SUM(F19:Q19) -> 187.42 | S19: —

Sheet 营运资金占用预算校准
B3: 目标：资金成本/销售收入 | M3: 0.008
M4: =IF(M28<=M3,"已校准","未校准") -> 已校准
E6: ="实际"&YEAR(主页!$D$5)-1&"全年" -> 实际2020全年 | G6: ="实际"&"截止"&YEAR(主页!$D$5)-1&"年"&MONTH(主页!$D$5)&"月" -> 实际截止2020年10月 | I6: ="估计"&"从"&YEAR(主页!$D$5)-1&"年"&MONTH(主页!$D$5)+1&"月到年底" -> 估计从2020年11月到年底 | K6: ="估计"&YEAR(主页!$D$5)&"全年" -> 估计2021全年 | M6: ="预算"&YEAR(主页!$D$5)+1&"全年" -> 预算2022全年
E7: ="A"&YEAR(主页!$D$5)-1&"FY" -> A2020FY | G7: ="A"&YEAR([1]主页!$D$5)&TEXT(MONTH([1]主页!$D$5),"00")&"YTD" -> A202109YTD | I7: ="E"&YEAR([1]主页!$D$5)&TEXT(MONTH([1]主页!$D$5),"00")&"YTG" -> E202109YTG | K7: ="E"&YEAR([1]主页!$D$5)&"FY" -> E2021FY | M7: ="B"&YEAR([1]主页!$D$5)+1&"FY" -> B2022FY
B9: 销售收入 | E9: =应收账款!R6 -> 125318 | G9: =SUMIFS(应收账款!$F$11:$Q$11,应收账款!$F$3:$Q$3,"<="&MONTH(主页!$D$5)) -> 104565 | I9: =SUMIFS(应收账款!$F$11:$Q$11,应收账款!$F$3:$Q$3,">"&MONTH(主页!$D$5)) -> 21285 | K9: =应收账款!R11 -> 125850 | M9: =应收账款!R16 -> 123000
B10: 运营资金占用余额
C11: 应收账款 | E11: =应收账款!Q7 -> 3593 | G11: =INDEX(应收账款!$12:$12,1,MATCH(MONTH(主页!$D$5),应收账款!$3:$3,0)) -> 3850 | I11: =INDEX(应收账款!$12:$12,1,MATCH(12,应收账款!$3:$3,0)) -> 3064 | K11: =应收账款!Q12 -> 3064 | M11: =应收账款!Q17 -> 4599
C12: 应付账款 | E12: =应付账款!Q7 -> 2155.8 | G12: =INDEX(应付账款!$12:$12,1,MATCH(MONTH(主页!$D$5),应收账款!$3:$3,0)) -> 2310 | I12: =INDEX(应付账款!$12:$12,1,MATCH(12,应收账款!$3:$3,0)) -> 1838.4 | K12: =应付账款!Q12 -> 1838.4 | M12: =应付账款!Q17 -> 2759.4
C13: 存货 | E13: =存货!R7 -> 3125.91 | G13: =INDEX(存货!$15:$15,1,MATCH(MONTH(主页!$D$5),存货!$3:$3,0)) -> 3850 | I13: =INDEX(存货!$15:$15,1,MATCH(12,存货!$3:$3,0)) -> 3064 | K13: =存货!R15 -> 3064 | M13: =存货!R23 -> 3495.24
C14: 长期资产净值 | E14: =长期资产!Q7 -> 1796.5 | G14: =INDEX(长期资产!$12:$12,1,MATCH(MONTH(主页!$D$5),应收账款!$3:$3,0)) -> 1925 | I14: =INDEX(长期资产!$12:$12,1,MATCH(12,应收账款!$3:$3,0)) -> 1532 | K14: =长期资产!Q12 -> 1532 | M14: =长期资产!Q17 -> 1839.6
C15: 合计 | E15: =E11-E12+E13+E14 -> 6359.61 | G15: =G11-G12+G13+G14 -> 7315 | I15: =I11-I12+I13+I14 -> 5821.6 | K15: =K11-K12+K13+K14 -> 5821.6 | M15: =M11-M12+M13+M14 -> 7174.44
B16: 平均运营资金占用
C17: 应收账款 | E17: =AVERAGE(应收账款!F7:Q7) -> 3941.4167 | G17: =(应收账款!$E$12/2+SUMIFS(应收账款!$F$12:$Q$12,应收账款!$F$3:$Q$3,"<"&MONTH(主页!$D$5))+INDEX(应收账款!$F$12:$P$12,1,MATCH(MONTH(主页!$D$5),应收账款!$F$3:$P$3,0))/2)/MONTH(主页!$D$5) -> 3940.85 | I17: =(INDEX(应收账款!$F$12:$P$12,1,MATCH(MONTH(主页!$D$5),应收账款!$F$3:$P$3,0))/2+SUMIFS(应收账款!$F$12:$P$12,应收账款!$F$3:$P$3,">"&MONTH(主页!$D$5))+I11/2)/(12-MONTH(主页!$D$5)) -> 3560.5 | K17: =(应收账款!$E$12/2+SUM(应收账款!$F$12:$P$12)+应收账款!$Q$12/2)/12 -> 3877.4583 | M17: =AVERAGE(应收账款!F17:Q17) -> 3904.5833 | O17: =(G17*10+I17*2)/12-K17 -> 0
C18: 应付账款 | E18: =AVERAGE(应付账款!F7:Q7) -> 2364.85 | G18: =(应付账款!$E$12/2+SUMIFS(应付账款!$F$12:$Q$12,应付账款!$F$3:$Q$3,"<"&MONTH(主页!$D$5))+INDEX(应付账款!$F$12:$P$12,1,MATCH(MONTH(主页!$D$5),应付账款!$F$3:$P$3,0))/2)/MONTH(主页!$D$5) -> 2364.51 | I18: =(INDEX(应付账款!$F$12:$P$12,1,MATCH(MONTH(主页!$D$5),应付账款!$F$3:$P$3,0))/2+SUMIFS(应付账款!$F$12:$P$12,应付账款!$F$3:$P$3,">"&MONTH(主页!$D$5))+I12/2)/(12-MONTH(主页!$D$5)) -> 2136.3 | K18: =(应付账款!$E$12/2+SUM(应付账款!$F$12:$P$12)+应付账款!$Q$12/2)/12 -> 2326.475 | M18: =AVERAGE(应付账款!F17:Q17) -> 2342.75 | O18: =(G18*10+I18*2)/12-K18 -> 0
C19: 存货 | E19: =AVERAGE(存货!G7:R7) -> 3429.0325 | G19: =(存货!$F$15/2+SUMIFS(存货!$G$15:$R$15,存货!$G$3:$R$3,"<"&MONTH(主页!$D$5))+INDEX(存货!$G$15:Q$15,1,MATCH(MONTH(主页!$D$5),存货!$G$3:$Q$3,0))/2)/MONTH(主页!$D$5) -> 3917.4955 | I19: =(INDEX(存货!$G$15:Q$15,1,MATCH(MONTH(主页!$D$5),存货!$G$3:$Q$3,0))/2+SUMIFS(存货!$G$15:Q$15,存货!$G$3:$Q$3,">"&MONTH(主页!$D$5))+I13/2)/(12-MONTH(主页!$D$5)) -> 3560.5 | K19: =(存货!$F$15/2+SUM(存货!$G$15:Q$15)+存货!$R$15/2)/12 -> 3857.9963 | M19: =AVERAGE(存货!G23:R23) -> 2801.6057 | O19: =(G19*10+I19*2)/12-K19 -> 0
C20: 长期资产净值 | E20: =AVERAGE(长期资产!F7:Q7) -> 1970.7083 | G20: =(长期资产!$E$12/2+SUMIFS(长期资产!$F$12:$Q$12,长期资产!$F$3:$Q$3,"<"&MONTH(主页!$D$5))+INDEX(长期资产!$F$12:$P$12,1,MATCH(MONTH(主页!$D$5),长期资产!$F$3:$P$3,0))/2)/MONTH(主页!$D$5) -> 1970.425 | I20: =(INDEX(长期资产!$F$12:$P$12,1,MATCH(MONTH(主页!$D$5),长期资产!$F$3:$P$3,0))/2+SUMIFS(长期资产!$F$12:$P$12,长期资产!$F$3:$P$3,">"&MONTH(主页!$D$5))+I14/2)/(12-MONTH(主页!$D$5)) -> 1780.25 | K20: =(长期资产!$E$12/2+SUM(长期资产!$F$12:$P$12)+长期资产!$Q$12/2)/12 -> 1938.7292 | M20: =AVERAGE(长期资产!F17:Q17) -> 1561.8333 | O20: =(G20*10+I20*2)/12-K20 -> 0
C21: 合计 | E21: =E17-E18+E19+E20 -> 6976.3075 | G21: =G17-G18+G19+G20 -> 7464.2605 | I21: =I17-I18+I19+I20 -> 6764.95 | K21: =K17-K18+K19+K20 -> 7347.7087 | M21: =M17-M18+M19+M20 -> 5925.2724 | O21: =(G21*10+I21*2)/12-K21 -> 0
B22: 资金成本
C23: 应收账款 | E23: =应收账款!R9 -> 472.97 | G23: =SUMIFS(应收账款!$F$14:$Q$14,应收账款!$F$3:$Q$3,"<="&MONTH(主页!$D$5)) -> 395.37 | I23: =SUMIFS(应收账款!$F$14:$Q$14,应收账款!$F$3:$Q$3,">"&MONTH(主页!$D$5)) -> 67.28 | K23: =应收账款!R14 -> 462.65 | M23: =应收账款!R19 -> 468.55
C24: 应付账款 | E24: =应付账款!R9 -> 283.782 | G24: =SUMIFS(应付账款!$F$14:$Q$14,应付账款!$F$3:$Q$3,"<="&MONTH(主页!$D$5)) -> 237.222 | I24: =SUMIFS(应付账款!$F$14:$Q$14,应付账款!$F$3:$Q$3,">"&MONTH(主页!$D$5)) -> 40.368 | K24: =应付账款!R14 -> 277.59 | M24: =应付账款!R19 -> 281.13
C25: 存货 | E25: =存货!S12 -> 411.4839 | G25: =SUMIFS(存货!$G$20:$R$20,存货!$G$3:$R$3,"<="&MONTH(主页!$D$5)) -> 395.37 | I25: =SUMIFS(存货!$G$20:$R$20,存货!$G$3:$R$3,">"&MONTH(主页!$D$5)) -> 67.28 | K25: =存货!S20 -> 462.65 | M25: =存货!S28 -> 336.19269
C26: 长期资产净值 | E26: =长期资产!R9 -> 236.485 | G26: =SUMIFS(长期资产!$F$14:$Q$14,长期资产!$F$3:$Q$3,"<="&MONTH(主页!$D$5)) -> 197.685 | I26: =SUMIFS(长期资产!$F$14:$Q$14,长期资产!$F$3:$Q$3,">"&MONTH(主页!$D$5)) -> 33.64 | K26: =长期资产!R14 -> 231.325 | M26: =长期资产!R19 -> 187.42
C27: 合计 | E27: =E23-E24+E25+E26 -> 837.1569 | G27: =G23-G24+G25+G26 -> 751.203 | I27: =I23-I24+I25+I26 -> 127.832 | K27: =K23-K24+K25+K26 -> 879.035 | M27: =M23-M24+M25+M26 -> 711.03269
C28: 占销售收入% | E28: =E27/E9 -> 0.0066802606 | G28: =G27/G9 -> 0.0071840769 | I28: =I27/I9 -> 0.0060057317 | K28: =K27/K9 -> 0.0069847835 | M28: =M27/M9 -> 0.0057807536
