Workbook

Sheet 主页
C9: 当年实际数据截止月份 | D9: 44500
C11: 编制说明：
C12: 表格中黄色单元格中有公式，除非特别必要，尽量不要修改。白色单元格为可编辑单元格
C13: 上年、当年、下年三张表为清单式表格，可根据需要增加行、删除行。可增加列，不要删除列
C14: 注意增加行时，注意将黄色单元格中的公式往下复制

Sheet 上年
A1: 资产编号 | B1: 资产名称 | C1: 资产类别 | D1: 责任中心1 | E1: 责任中心2 | F1: 归口管理部门 | G1: 使用部门 | H1: 购建日期 | I1: 处置日期 | J1: 资产异动原因 | K1: 原值 | L1: 财务折旧年限 | M1: 预计残值率 | N1: 折旧期满日 | O1: 年初原值 | P1: 原值增加 | Q1: 原值减少 | R1: 年末原值 | S1: chk | T1: 年初累计折旧 | U1: 本年增加折旧 | V1: 折旧减少 | W1: 期末累计折旧 | X1: chk | Z1: 技术折旧年限 | AA1: 使用状态 | AB1: 当年技术折旧
A2: FA001 | B2: 生产线 | C2: 机器设备 | D2: 流程中心 | E2: 制造中心 | F2: 工程部 | G2: 生产车间 | H2: 43388 | K2: 12000000 | L2: 10 | M2: 0.05 | N2: =IF(H2=0,"-",EOMONTH(H2,L2*12)) -> 47057 | O2: =IF(AND(H2<DATE(YEAR(主页!$D$9)-1,1,1),OR(上年!I2=0,I2>=DATE(YEAR(主页!$D$9)-1,1,1))),上年!K2,0) -> 12000000 | P2: =IF(AND(H2>=DATE(YEAR(主页!$D$9)-2,12,31),H2<=DATE(YEAR(主页!$D$9)-1,12,31)),K2,0) -> 0 | Q2: =IF(AND(I2>=DATE(YEAR(主页!$D$9)-2,12,31),I2<=DATE(YEAR(主页!$D$9)-1,12,31)),K2,0) -> 0 | R2: =IF(AND(H2<DATE(YEAR(主页!$D$9),1,1),OR(上年!I2=0,I2>=DATE(YEAR(主页!$D$9),1,1))),上年!K2,0) -> 12000000 | S2: =O2+P2-Q2-R2 -> 0 | T2: =IFERROR(IF(AND(H2<DATE(YEAR(主页!$D$9)-1,1,1),OR(当年!I2=0,I2>=DATE(YEAR(主页!$D$9)-1,1,1))),MIN(K2*(1-M2),K2*(1-M2)/L2/12*DATEDIF(H2,DATE(YEAR(主页!$D$9)-2,12,31),"M")),0),0) -> 1330000 | U2: =IFERROR(K2*(1-M2)/L2/12*DATEDIF(MAX(H2,DATE(YEAR(主页!$D$9)-2,12,31)),MIN(N2,IF(OR(当年!I2=0,I2>=DATE(YEAR(主页!$D$9)-1,1,1)),DATE(YEAR(主页!$D$9)-1,12,31),I2)),"M"),0) -> 1140000 | V2: =IF(AND(I2>=DATE(YEAR(主页!$D$9)-2,12,31),I2<=DATE(YEAR(主页!$D$9)-1,12,31)),T2+U2,0) -> 0 | W2: =IF(AND(H2<DATE(YEAR(主页!$D$9),1,1),OR(当年!I2=0,I2>=DATE(YEAR(主页!$D$9),1,1))),IFERROR(K2*(1-M2)/L2/12*DATEDIF(H2,MIN(N2,IF(OR(当年!I2=0,I2>=DATE(YEAR(主页!$D$9)-1,1,1)),DATE(YEAR(主页!$D$9)-1,12,31),I2)),"M"),0),0) -> 2470000 | X2: =T2+U2-V2-W2 -> 0 | Z2: 10 | AA2: 在用 | AB2: =IFERROR(IF(AA2="在用",K2/Z2,0),0) -> 1200000
A3: FA002 | B3: 厂房 | C3: 建筑物 | D3: 流程中心 | E3: 制造中心 | F3: 行政部 | G3: 生产车间 | H3: 44359 | K3: 35000000 | L3: 20 | M3: 0.05 | N3: =IF(H3=0,"-",EOMONTH(H3,L3*12)) -> 51682 | O3: =IF(AND(H3<DATE(YEAR(主页!$D$9)-1,1,1),OR(上年!I3=0,I3>=DATE(YEAR(主页!$D$9)-1,1,1))),上年!K3,0) -> 0 | P3: =IF(AND(H3>=DATE(YEAR(主页!$D$9)-2,12,31),H3<=DATE(YEAR(主页!$D$9)-1,12,31)),K3,0) -> 0 | Q3: =IF(AND(I3>=DATE(YEAR(主页!$D$9)-2,12,31),I3<=DATE(YEAR(主页!$D$9)-1,12,31)),K3,0) -> 0 | R3: =IF(AND(H3<DATE(YEAR(主页!$D$9),1,1),OR(上年!I3=0,I3>=DATE(YEAR(主页!$D$9),1,1))),上年!K3,0) -> 0 | S3: =O3+P3-Q3-R3 -> 0 | T3: =IFERROR(IF(AND(H3<DATE(YEAR(主页!$D$9)-1,1,1),OR(当年!I3=0,I3>=DATE(YEAR(主页!$D$9)-1,1,1))),MIN(K3*(1-M3),K3*(1-M3)/L3/12*DATEDIF(H3,DATE(YEAR(主页!$D$9)-2,12,31),"M")),0),0) -> 0 | U3: =IFERROR(K3*(1-M3)/L3/12*DATEDIF(MAX(H3,DATE(YEAR(主页!$D$9)-2,12,31)),MIN(N3,IF(OR(当年!I3=0,I3>=DATE(YEAR(主页!$D$9)-1,1,1)),DATE(YEAR(主页!$D$9)-1,12,31),I3)),"M"),0) -> 0 | V3: =IF(AND(I3>=DATE(YEAR(主页!$D$9)-2,12,31),I3<=DATE(YEAR(主页!$D$9)-1,12,31)),T3+U3,0) -> 0 | W3: =IF(AND(H3<DATE(YEAR(主页!$D$9),1,1),OR(当年!I3=0,I3>=DATE(YEAR(主页!$D$9),1,1))),IFERROR(K3*(1-M3)/L3/12*DATEDIF(H3,MIN(N3,IF(OR(当年!I3=0,I3>=DATE(YEAR(主页!$D$9)-1,1,1)),DATE(YEAR(主页!$D$9)-1,12,31),I3)),"M"),0),0) -> 0 | X3: =T3+U3-V3-W3 -> 0 | Z3: 20 | AA3: 在用 | AB3: =IFERROR(IF(AA3="在用",K3/Z3,0),0) -> 1750000
A4: FA003 | B4: 检测仪 | C4: 机器设备 | D4: 流程中心 | E4: 制造中心 | F4: 技术部 | G4: 生产车间 | H4: 42270 | I4: 44408 | K4: 300000 | L4: 10 | M4: 0.05 | N4: =IF(H4=0,"-",EOMONTH(H4,L4*12)) -> 45930 | O4: =IF(AND(H4<DATE(YEAR(主页!$D$9)-1,1,1),OR(上年!I4=0,I4>=DATE(YEAR(主页!$D$9)-1,1,1))),上年!K4,0) -> 300000 | P4: =IF(AND(H4>=DATE(YEAR(主页!$D$9)-2,12,31),H4<=DATE(YEAR(主页!$D$9)-1,12,31)),K4,0) -> 0 | Q4: =IF(AND(I4>=DATE(YEAR(主页!$D$9)-2,12,31),I4<=DATE(YEAR(主页!$D$9)-1,12,31)),K4,0) -> 0 | R4: =IF(AND(H4<DATE(YEAR(主页!$D$9),1,1),OR(上年!I4=0,I4>=DATE(YEAR(主页!$D$9),1,1))),上年!K4,0) -> 300000 | S4: =O4+P4-Q4-R4 -> 0 | T4: =IFERROR(IF(AND(H4<DATE(YEAR(主页!$D$9)-1,1,1),OR(当年!I4=0,I4>=DATE(YEAR(主页!$D$9)-1,1,1))),MIN(K4*(1-M4),K4*(1-M4)/L4/12*DATEDIF(H4,DATE(YEAR(主页!$D$9)-2,12,31),"M")),0),0) -> 121125 | U4: =IFERROR(K4*(1-M4)/L4/12*DATEDIF(MAX(H4,DATE(YEAR(主页!$D$9)-2,12,31)),MIN(N4,IF(OR(当年!I4=0,I4>=DATE(YEAR(主页!$D$9)-1,1,1)),DATE(YEAR(主页!$D$9)-1,12,31),I4)),"M"),0) -> 28500 | V4: =IF(AND(I4>=DATE(YEAR(主页!$D$9)-2,12,31),I4<=DATE(YEAR(主页!$D$9)-1,12,31)),T4+U4,0) -> 0 | W4: =IF(AND(H4<DATE(YEAR(主页!$D$9),1,1),OR(当年!I4=0,I4>=DATE(YEAR(主页!$D$9),1,1))),IFERROR(K4*(1-M4)/L4/12*DATEDIF(H4,MIN(N4,IF(OR(当年!I4=0,I4>=DATE(YEAR(主页!$D$9)-1,1,1)),DATE(YEAR(主页!$D$9)-1,12,31),I4)),"M"),0),0) -> 149625 | X4: =T4+U4-V4-W4 -> 0 | Z4: 10 | AA4: 在用 | AB4: =IFERROR(IF(AA4="在用",K4/Z4,0),0) -> 30000
A5: FA004 | B5: 自动装配线 | C5: 机器设备 | D5: 流程中心 | E5: 制造中心 | F5: 工程部 | G5: 生产车间 | H5: 41518 | I5: 44135 | K5: 350000 | L5: 10 | M5: 0.05 | N5: =IF(H5=0,"-",EOMONTH(H5,L5*12)) -> 45199 | O5: =IF(AND(H5<DATE(YEAR(主页!$D$9)-1,1,1),OR(上年!I5=0,I5>=DATE(YEAR(主页!$D$9)-1,1,1))),上年!K5,0) -> 350000 | P5: =IF(AND(H5>=DATE(YEAR(主页!$D$9)-2,12,31),H5<=DATE(YEAR(主页!$D$9)-1,12,31)),K5,0) -> 0 | Q5: =IF(AND(I5>=DATE(YEAR(主页!$D$9)-2,12,31),I5<=DATE(YEAR(主页!$D$9)-1,12,31)),K5,0) -> 350000 | R5: =IF(AND(H5<DATE(YEAR(主页!$D$9),1,1),OR(上年!I5=0,I5>=DATE(YEAR(主页!$D$9),1,1))),上年!K5,0) -> 0 | S5: =O5+P5-Q5-R5 -> 0 | T5: =IFERROR(IF(AND(H5<DATE(YEAR(主页!$D$9)-1,1,1),OR(当年!I5=0,I5>=DATE(YEAR(主页!$D$9)-1,1,1))),MIN(K5*(1-M5),K5*(1-M5)/L5/12*DATEDIF(H5,DATE(YEAR(主页!$D$9)-2,12,31),"M")),0),0) -> 207812.5 | U5: =IFERROR(K5*(1-M5)/L5/12*DATEDIF(MAX(H5,DATE(YEAR(主页!$D$9)-2,12,31)),MIN(N5,IF(OR(当年!I5=0,I5>=DATE(YEAR(主页!$D$9)-1,1,1)),DATE(YEAR(主页!$D$9)-1,12,31),I5)),"M"),0) -> 33250 | V5: =IF(AND(I5>=DATE(YEAR(主页!$D$9)-2,12,31),I5<=DATE(YEAR(主页!$D$9)-1,12,31)),T5+U5,0) -> 241062.5 | W5: =IF(AND(H5<DATE(YEAR(主页!$D$9),1,1),OR(当年!I5=0,I5>=DATE(YEAR(主页!$D$9),1,1))),IFERROR(K5*(1-M5)/L5/12*DATEDIF(H5,MIN(N5,IF(OR(当年!I5=0,I5>=DATE(YEAR(主页!$D$9)-1,1,1)),DATE(YEAR(主页!$D$9)-1,12,31),I5)),"M"),0),0) -> 0 | X5: =T5+U5-V5-W5 -> 0 | Z5: 10 | AA5: 在用 | AB5: =IFERROR(IF(AA5="在用",K5/Z5,0),0) -> 35000
A6: FA005 | B6: 车床 | C6: 机器设备 | D6: 流程中心 | E6: 制造中心 | F6: 工程部 | G6: 生产车间 | H6: 38353 | K6: 50000 | L6: 10 | M6: 0.05 | N6: =IF(H6=0,"-",EOMONTH(H6,L6*12)) -> 42035 | O6: =IF(AND(H6<DATE(YEAR(主页!$D$9)-1,1,1),OR(上年!I6=0,I6>=DATE(YEAR(主页!$D$9)-1,1,1))),上年!K6,0) -> 50000 | P6: =IF(AND(H6>=DATE(YEAR(主页!$D$9)-2,12,31),H6<=DATE(YEAR(主页!$D$9)-1,12,31)),K6,0) -> 0 | Q6: =IF(AND(I6>=DATE(YEAR(主页!$D$9)-2,12,31),I6<=DATE(YEAR(主页!$D$9)-1,12,31)),K6,0) -> 0 | R6: =IF(AND(H6<DATE(YEAR(主页!$D$9),1,1),OR(上年!I6=0,I6>=DATE(YEAR(主页!$D$9),1,1))),上年!K6,0) -> 50000 | S6: =O6+P6-Q6-R6 -> 0 | T6: =IFERROR(IF(AND(H6<DATE(YEAR(主页!$D$9)-1,1,1),OR(当年!I6=0,I6>=DATE(YEAR(主页!$D$9)-1,1,1))),MIN(K6*(1-M6),K6*(1-M6)/L6/12*DATEDIF(H6,DATE(YEAR(主页!$D$9)-2,12,31),"M")),0),0) -> 47500 | U6: =IFERROR(K6*(1-M6)/L6/12*DATEDIF(MAX(H6,DATE(YEAR(主页!$D$9)-2,12,31)),MIN(N6,IF(OR(当年!I6=0,I6>=DATE(YEAR(主页!$D$9)-1,1,1)),DATE(YEAR(主页!$D$9)-1,12,31),I6)),"M"),0) -> 0 | V6: =IF(AND(I6>=DATE(YEAR(主页!$D$9)-2,12,31),I6<=DATE(YEAR(主页!$D$9)-1,12,31)),T6+U6,0) -> 0 | W6: =IF(AND(H6<DATE(YEAR(主页!$D$9),1,1),OR(当年!I6=0,I6>=DATE(YEAR(主页!$D$9),1,1))),IFERROR(K6*(1-M6)/L6/12*DATEDIF(H6,MIN(N6,IF(OR(当年!I6=0,I6>=DATE(YEAR(主页!$D$9)-1,1,1)),DATE(YEAR(主页!$D$9)-1,12,31),I6)),"M"),0),0) -> 47500 | X6: =T6+U6-V6-W6 -> 0 | Z6: 10 | AA6: 在用 | AB6: =IFERROR(IF(AA6="在用",K6/Z6,0),0) -> 5000
A7: FA006 | B7: 笔记本电脑 | C7: 电子设备 | D7: 支持中心 | E7: 财务部 | F7: IT部 | G7: 财务部 | H7: 44712 | K7: 9800 | L7: =2/12 -> 0.16666667 | M7: 0 | N7: =IF(H7=0,"-",EOMONTH(H7,L7*12)) -> 44773 | O7: =IF(AND(H7<DATE(YEAR(主页!$D$9)-1,1,1),OR(上年!I7=0,I7>=DATE(YEAR(主页!$D$9)-1,1,1))),上年!K7,0) -> 0 | P7: =IF(AND(H7>=DATE(YEAR(主页!$D$9)-2,12,31),H7<=DATE(YEAR(主页!$D$9)-1,12,31)),K7,0) -> 0 | Q7: =IF(AND(I7>=DATE(YEAR(主页!$D$9)-2,12,31),I7<=DATE(YEAR(主页!$D$9)-1,12,31)),K7,0) -> 0 | R7: =IF(AND(H7<DATE(YEAR(主页!$D$9),1,1),OR(上年!I7=0,I7>=DATE(YEAR(主页!$D$9),1,1))),上年!K7,0) -> 0 | S7: =O7+P7-Q7-R7 -> 0 | T7: =IFERROR(IF(AND(H7<DATE(YEAR(主页!$D$9)-1,1,1),OR(当年!I7=0,I7>=DATE(YEAR(主页!$D$9)-1,1,1))),MIN(K7*(1-M7),K7*(1-M7)/L7/12*DATEDIF(H7,DATE(YEAR(主页!$D$9)-2,12,31),"M")),0),0) -> 0 | U7: =IFERROR(K7*(1-M7)/L7/12*DATEDIF(MAX(H7,DATE(YEAR(主页!$D$9)-2,12,31)),MIN(N7,IF(OR(当年!I7=0,I7>=DATE(YEAR(主页!$D$9)-1,1,1)),DATE(YEAR(主页!$D$9)-1,12,31),I7)),"M"),0) -> 0 | V7: =IF(AND(I7>=DATE(YEAR(主页!$D$9)-2,12,31),I7<=DATE(YEAR(主页!$D$9)-1,12,31)),T7+U7,0) -> 0 | W7: =IF(AND(H7<DATE(YEAR(主页!$D$9),1,1),OR(当年!I7=0,I7>=DATE(YEAR(主页!$D$9),1,1))),IFERROR(K7*(1-M7)/L7/12*DATEDIF(H7,MIN(N7,IF(OR(当年!I7=0,I7>=DATE(YEAR(主页!$D$9)-1,1,1)),DATE(YEAR(主页!$D$9)-1,12,31),I7)),"M"),0),0) -> 0 | X7: =T7+U7-V7-W7 -> 0 | AA7: 在用 | AB7: =IFERROR(IF(AA7="在用",K7/Z7,0),0) -> 0
A8: FA007 | B8: 笔记本电脑 | C8: 电子设备 | D8: 支持中心 | E8: 财务部 | F8: IT部 | G8: 财务部 | H8: 44501 | K8: 9800 | L8: =2/12 -> 0.16666667 | M8: 0 | N8: =IF(H8=0,"-",EOMONTH(H8,L8*12)) -> 44592 | O8: =IF(AND(H8<DATE(YEAR(主页!$D$9)-1,1,1),OR(上年!I8=0,I8>=DATE(YEAR(主页!$D$9)-1,1,1))),上年!K8,0) -> 0 | P8: =IF(AND(H8>=DATE(YEAR(主页!$D$9)-2,12,31),H8<=DATE(YEAR(主页!$D$9)-1,12,31)),K8,0) -> 0 | Q8: =IF(AND(I8>=DATE(YEAR(主页!$D$9)-2,12,31),I8<=DATE(YEAR(主页!$D$9)-1,12,31)),K8,0) -> 0 | R8: =IF(AND(H8<DATE(YEAR(主页!$D$9),1,1),OR(上年!I8=0,I8>=DATE(YEAR(主页!$D$9),1,1))),上年!K8,0) -> 0 | S8: =O8+P8-Q8-R8 -> 0 | T8: =IFERROR(IF(AND(H8<DATE(YEAR(主页!$D$9)-1,1,1),OR(当年!I8=0,I8>=DATE(YEAR(主页!$D$9)-1,1,1))),MIN(K8*(1-M8),K8*(1-M8)/L8/12*DATEDIF(H8,DATE(YEAR(主页!$D$9)-2,12,31),"M")),0),0) -> 0 | U8: =IFERROR(K8*(1-M8)/L8/12*DATEDIF(MAX(H8,DATE(YEAR(主页!$D$9)-2,12,31)),MIN(N8,IF(OR(当年!I8=0,I8>=DATE(YEAR(主页!$D$9)-1,1,1)),DATE(YEAR(主页!$D$9)-1,12,31),I8)),"M"),0) -> 0 | V8: =IF(AND(I8>=DATE(YEAR(主页!$D$9)-2,12,31),I8<=DATE(YEAR(主页!$D$9)-1,12,31)),T8+U8,0) -> 0 | W8: =IF(AND(H8<DATE(YEAR(主页!$D$9),1,1),OR(当年!I8=0,I8>=DATE(YEAR(主页!$D$9),1,1))),IFERROR(K8*(1-M8)/L8/12*DATEDIF(H8,MIN(N8,IF(OR(当年!I8=0,I8>=DATE(YEAR(主页!$D$9)-1,1,1)),DATE(YEAR(主页!$D$9)-1,12,31),I8)),"M"),0),0) -> 0 | X8: =T8+U8-V8-W8 -> 0 | AA8: 在用 | AB8: =IFERROR(IF(AA8="在用",K8/Z8,0),0) -> 0
A9: FA008 | B9: 笔记本电脑 | C9: 电子设备 | D9: 支持中心 | E9: 财务部 | F9: IT部 | G9: 财务部 | H9: 43831 | K9: 9800 | L9: =2/12 -> 0.16666667 | M9: 0 | N9: =IF(H9=0,"-",EOMONTH(H9,L9*12)) -> 43921 | O9: =IF(AND(H9<DATE(YEAR(主页!$D$9)-1,1,1),OR(上年!I9=0,I9>=DATE(YEAR(主页!$D$9)-1,1,1))),上年!K9,0) -> 0 | P9: =IF(AND(H9>=DATE(YEAR(主页!$D$9)-2,12,31),H9<=DATE(YEAR(主页!$D$9)-1,12,31)),K9,0) -> 9800 | Q9: =IF(AND(I9>=DATE(YEAR(主页!$D$9)-2,12,31),I9<=DATE(YEAR(主页!$D$9)-1,12,31)),K9,0) -> 0 | R9: =IF(AND(H9<DATE(YEAR(主页!$D$9),1,1),OR(上年!I9=0,I9>=DATE(YEAR(主页!$D$9),1,1))),上年!K9,0) -> 9800 | S9: =O9+P9-Q9-R9 -> 0 | T9: =IFERROR(IF(AND(H9<DATE(YEAR(主页!$D$9)-1,1,1),OR(当年!I9=0,I9>=DATE(YEAR(主页!$D$9)-1,1,1))),MIN(K9*(1-M9),K9*(1-M9)/L9/12*DATEDIF(H9,DATE(YEAR(主页!$D$9)-2,12,31),"M")),0),0) -> 0 | U9: =IFERROR(K9*(1-M9)/L9/12*DATEDIF(MAX(H9,DATE(YEAR(主页!$D$9)-2,12,31)),MIN(N9,IF(OR(当年!I9=0,I9>=DATE(YEAR(主页!$D$9)-1,1,1)),DATE(YEAR(主页!$D$9)-1,12,31),I9)),"M"),0) -> 9800 | V9: =IF(AND(I9>=DATE(YEAR(主页!$D$9)-2,12,31),I9<=DATE(YEAR(主页!$D$9)-1,12,31)),T9+U9,0) -> 0 | W9: =IF(AND(H9<DATE(YEAR(主页!$D$9),1,1),OR(当年!I9=0,I9>=DATE(YEAR(主页!$D$9),1,1))),IFERROR(K9*(1-M9)/L9/12*DATEDIF(H9,MIN(N9,IF(OR(当年!I9=0,I9>=DATE(YEAR(主页!$D$9)-1,1,1)),DATE(YEAR(主页!$D$9)-1,12,31),I9)),"M"),0),0) -> 9800 | X9: =T9+U9-V9-W9 -> 0 | AA9: 在用 | AB9: =IFERROR(IF(AA9="在用",K9/Z9,0),0) -> 0
A10: FA009 | B10: 笔记本电脑 | C10: 电子设备 | D10: 支持中心 | E10: 财务部 | F10: IT部 | G10: 财务部 | H10: 43891 | K10: 9800 | L10: =2/12 -> 0.16666667 | M10: 0 | N10: =IF(H10=0,"-",EOMONTH(H10,L10*12)) -> 43982 | O10: =IF(AND(H10<DATE(YEAR(主页!$D$9)-1,1,1),OR(上年!I10=0,I10>=DATE(YEAR(主页!$D$9)-1,1,1))),上年!K10,0) -> 0 | P10: =IF(AND(H10>=DATE(YEAR(主页!$D$9)-2,12,31),H10<=DATE(YEAR(主页!$D$9)-1,12,31)),K10,0) -> 9800 | Q10: =IF(AND(I10>=DATE(YEAR(主页!$D$9)-2,12,31),I10<=DATE(YEAR(主页!$D$9)-1,12,31)),K10,0) -> 0 | R10: =IF(AND(H10<DATE(YEAR(主页!$D$9),1,1),OR(上年!I10=0,I10>=DATE(YEAR(主页!$D$9),1,1))),上年!K10,0) -> 9800 | S10: =O10+P10-Q10-R10 -> 0 | T10: =IFERROR(IF(AND(H10<DATE(YEAR(主页!$D$9)-1,1,1),OR(当年!I10=0,I10>=DATE(YEAR(主页!$D$9)-1,1,1))),MIN(K10*(1-M10),K10*(1-M10)/L10/12*DATEDIF(H10,DATE(YEAR(主页!$D$9)-2,12,31),"M")),0),0) -> 0 | U10: =IFERROR(K10*(1-M10)/L10/12*DATEDIF(MAX(H10,DATE(YEAR(主页!$D$9)-2,12,31)),MIN(N10,IF(OR(当年!I10=0,I10>=DATE(YEAR(主页!$D$9)-1,1,1)),DATE(YEAR(主页!$D$9)-1,12,31),I10)),"M"),0) -> 9800 | V10: =IF(AND(I10>=DATE(YEAR(主页!$D$9)-2,12,31),I10<=DATE(YEAR(主页!$D$9)-1,12,31)),T10+U10,0) -> 0 | W10: =IF(AND(H10<DATE(YEAR(主页!$D$9),1,1),OR(当年!I10=0,I10>=DATE(YEAR(主页!$D$9),1,1))),IFERROR(K10*(1-M10)/L10/12*DATEDIF(H10,MIN(N10,IF(OR(当年!I10=0,I10>=DATE(YEAR(主页!$D$9)-1,1,1)),DATE(YEAR(主页!$D$9)-1,12,31),I10)),"M"),0),0) -> 9800 | X10: =T10+U10-V10-W10 -> 0 | AA10: 在用 | AB10: =IFERROR(IF(AA10="在用",K10/Z10,0),0) -> 0
N11: =IF(H11=0,"-",EOMONTH(H11,L11*12)) -> - | O11: =IF(AND(H11<DATE(YEAR(主页!$D$9)-1,1,1),OR(上年!I11=0,I11>=DATE(YEAR(主页!$D$9)-1,1,1))),上年!K11,0) -> 0 | P11: =IF(AND(H11>=DATE(YEAR(主页!$D$9)-2,12,31),H11<=DATE(YEAR(主页!$D$9)-1,12,31)),K11,0) -> 0 | Q11: =IF(AND(I11>=DATE(YEAR(主页!$D$9)-2,12,31),I11<=DATE(YEAR(主页!$D$9)-1,12,31)),K11,0) -> 0 | R11: =IF(AND(H11<DATE(YEAR(主页!$D$9),1,1),OR(上年!I11=0,I11>=DATE(YEAR(主页!$D$9),1,1))),上年!K11,0) -> 0 | S11: =O11+P11-Q11-R11 -> 0 | T11: =IFERROR(IF(AND(H11<DATE(YEAR(主页!$D$9)-1,1,1),OR(当年!I11=0,I11>=DATE(YEAR(主页!$D$9)-1,1,1))),MIN(K11*(1-M11),K11*(1-M11)/L11/12*DATEDIF(H11,DATE(YEAR(主页!$D$9)-2,12,31),"M")),0),0) -> 0 | U11: =IFERROR(K11*(1-M11)/L11/12*DATEDIF(MAX(H11,DATE(YEAR(主页!$D$9)-2,12,31)),MIN(N11,IF(OR(当年!I11=0,I11>=DATE(YEAR(主页!$D$9)-1,1,1)),DATE(YEAR(主页!$D$9)-1,12,31),I11)),"M"),0) -> 0 | V11: =IF(AND(I11>=DATE(YEAR(主页!$D$9)-2,12,31),I11<=DATE(YEAR(主页!$D$9)-1,12,31)),T11+U11,0) -> 0 | W11: =IF(AND(H11<DATE(YEAR(主页!$D$9),1,1),OR(当年!I11=0,I11>=DATE(YEAR(主页!$D$9),1,1))),IFERROR(K11*(1-M11)/L11/12*DATEDIF(H11,MIN(N11,IF(OR(当年!I11=0,I11>=DATE(YEAR(主页!$D$9)-1,1,1)),DATE(YEAR(主页!$D$9)-1,12,31),I11)),"M"),0),0) -> 0 | X11: =T11+U11-V11-W11 -> 0 | AB11: =IFERROR(IF(AA11="在用",K11/Z11,0),0) -> 0

Sheet 当年
A1: 资产编号 | B1: 资产名称 | C1: 资产类别 | D1: 责任中心1 | E1: 责任中心2 | F1: 归口管理部门 | G1: 使用部门 | H1: 购建日期 | I1: 处置日期 | J1: 资产异动原因 | K1: 原值 | L1: 财务折旧年限 | M1: 预计残值率 | N1: 折旧期满日 | O1: 年初原值 | P1: 原值增加 | Q1: 原值减少 | R1: 年末原值 | S1: chk | T1: 年初累计折旧 | U1: 本年增加折旧 | V1: 折旧减少 | W1: 期末累计折旧 | X1: chk | Z1: 技术折旧年限 | AA1: 使用状态 | AB1: 当年技术折旧 | AD1: 当年已提折旧 | AE1: 当年待提折旧
A2: FA001 | B2: 生产线 | C2: 机器设备 | D2: 流程中心 | E2: 制造中心 | F2: 工程部 | G2: 生产车间 | H2: 43388 | K2: 12000000 | L2: 10 | M2: 0.05 | N2: =IF(H2=0,"-",EOMONTH(H2,L2*12)) -> 47057 | O2: =IF(AND(H2<DATE(YEAR(主页!$D$9),1,1),OR(当年!I2=0,I2>=DATE(YEAR(主页!$D$9),1,1))),当年!K2,0) -> 12000000 | P2: =IF(AND(H2>=DATE(YEAR(主页!$D$9)-1,12,31),H2<=DATE(YEAR(主页!$D$9),12,31)),K2,0) -> 0 | Q2: =IF(AND(I2>=DATE(YEAR(主页!$D$9)-1,12,31),I2<=DATE(YEAR(主页!$D$9),12,31)),K2,0) -> 0 | R2: =IF(AND(H2<DATE(YEAR(主页!$D$9)+1,1,1),OR(当年!I2=0,I2>=DATE(YEAR(主页!$D$9)+1,1,1))),当年!K2,0) -> 12000000 | S2: =O2+P2-Q2-R2 -> 0 | T2: =IFERROR(IF(AND(H2<DATE(YEAR(主页!$D$9),1,1),OR(当年!I2=0,I2>=DATE(YEAR(主页!$D$9),1,1))),MIN(K2*(1-M2),K2*(1-M2)/L2/12*DATEDIF(H2,DATE(YEAR(主页!$D$9)-1,12,31),"M")),0),0) -> 2470000 | U2: =IFERROR(K2*(1-M2)/L2/12*DATEDIF(MAX(H2,DATE(YEAR(主页!$D$9)-1,12,31)),MIN(N2,IF(OR(当年!I2=0,I2>=DATE(YEAR(主页!$D$9),1,1)),DATE(YEAR(主页!$D$9),12,31),I2)),"M"),0) -> 1140000 | V2: =IF(AND(I2>=DATE(YEAR(主页!$D$9)-1,12,31),I2<=DATE(YEAR(主页!$D$9),12,31)),T2+U2,0) -> 0 | W2: =IF(AND(H2<DATE(YEAR(主页!$D$9)+1,1,1),OR(当年!I2=0,I2>=DATE(YEAR(主页!$D$9)+1,1,1))),IFERROR(K2*(1-M2)/L2/12*DATEDIF(H2,MIN(N2,IF(OR(当年!I2=0,I2>=DATE(YEAR(主页!$D$9),1,1)),DATE(YEAR(主页!$D$9),12,31),I2)),"M"),0),0) -> 3610000 | X2: =T2+U2-V2-W2 -> 0 | Z2: 10 | AA2: 在用 | AB2: =IFERROR(IF(AA2="在用",K2/Z2,0),0) -> 1200000 | AD2: =IFERROR(K2*(1-M2)/L2/12*DATEDIF(MAX(H2,DATE(YEAR(主页!$D$9)-1,12,31)),MIN(N2,IF(OR(当年!I2=0,I2>=DATE(YEAR(主页!$D$9),1,1)),DATE(YEAR(主页!$D$9),MONTH(主页!$D$9),31),I2)),"M"),0) -> 950000 | AE2: =U2-AD2 -> 190000
A3: FA002 | B3: 厂房 | C3: 建筑物 | D3: 流程中心 | E3: 制造中心 | F3: 行政部 | G3: 生产车间 | H3: 44359 | K3: 35000000 | L3: 20 | M3: 0.05 | N3: =IF(H3=0,"-",EOMONTH(H3,L3*12)) -> 51682 | O3: =IF(AND(H3<DATE(YEAR(主页!$D$9),1,1),OR(当年!I3=0,I3>=DATE(YEAR(主页!$D$9),1,1))),当年!K3,0) -> 0 | P3: =IF(AND(H3>=DATE(YEAR(主页!$D$9)-1,12,31),H3<=DATE(YEAR(主页!$D$9),12,31)),K3,0) -> 35000000 | Q3: =IF(AND(I3>=DATE(YEAR(主页!$D$9)-1,12,31),I3<=DATE(YEAR(主页!$D$9),12,31)),K3,0) -> 0 | R3: =IF(AND(H3<DATE(YEAR(主页!$D$9)+1,1,1),OR(当年!I3=0,I3>=DATE(YEAR(主页!$D$9)+1,1,1))),当年!K3,0) -> 35000000 | S3: =O3+P3-Q3-R3 -> 0 | T3: =IFERROR(IF(AND(H3<DATE(YEAR(主页!$D$9),1,1),OR(当年!I3=0,I3>=DATE(YEAR(主页!$D$9),1,1))),MIN(K3*(1-M3),K3*(1-M3)/L3/12*DATEDIF(H3,DATE(YEAR(主页!$D$9)-1,12,31),"M")),0),0) -> 0 | U3: =IFERROR(K3*(1-M3)/L3/12*DATEDIF(MAX(H3,DATE(YEAR(主页!$D$9)-1,12,31)),MIN(N3,IF(OR(当年!I3=0,I3>=DATE(YEAR(主页!$D$9),1,1)),DATE(YEAR(主页!$D$9),12,31),I3)),"M"),0) -> 831250 | V3: =IF(AND(I3>=DATE(YEAR(主页!$D$9)-1,12,31),I3<=DATE(YEAR(主页!$D$9),12,31)),T3+U3,0) -> 0 | W3: =IF(AND(H3<DATE(YEAR(主页!$D$9)+1,1,1),OR(当年!I3=0,I3>=DATE(YEAR(主页!$D$9)+1,1,1))),IFERROR(K3*(1-M3)/L3/12*DATEDIF(H3,MIN(N3,IF(OR(当年!I3=0,I3>=DATE(YEAR(主页!$D$9),1,1)),DATE(YEAR(主页!$D$9),12,31),I3)),"M"),0),0) -> 831250 | X3: =T3+U3-V3-W3 -> 0 | Z3: 20 | AA3: 在用 | AB3: =IFERROR(IF(AA3="在用",K3/Z3,0),0) -> 1750000 | AD3: =IFERROR(K3*(1-M3)/L3/12*DATEDIF(MAX(H3,DATE(YEAR(主页!$D$9)-1,12,31)),MIN(N3,IF(OR(当年!I3=0,I3>=DATE(YEAR(主页!$D$9),1,1)),DATE(YEAR(主页!$D$9),MONTH(主页!$D$9),31),I3)),"M"),0) -> 554166.67 | AE3: =U3-AD3 -> 277083.33
A4: FA003 | B4: 检测仪 | C4: 机器设备 | D4: 流程中心 | E4: 制造中心 | F4: 技术部 | G4: 生产车间 | H4: 42270 | I4: 44408 | K4: 300000 | L4: 10 | M4: 0.05 | N4: =IF(H4=0,"-",EOMONTH(H4,L4*12)) -> 45930 | O4: =IF(AND(H4<DATE(YEAR(主页!$D$9),1,1),OR(当年!I4=0,I4>=DATE(YEAR(主页!$D$9),1,1))),当年!K4,0) -> 300000 | P4: =IF(AND(H4>=DATE(YEAR(主页!$D$9)-1,12,31),H4<=DATE(YEAR(主页!$D$9),12,31)),K4,0) -> 0 | Q4: =IF(AND(I4>=DATE(YEAR(主页!$D$9)-1,12,31),I4<=DATE(YEAR(主页!$D$9),12,31)),K4,0) -> 300000 | R4: =IF(AND(H4<DATE(YEAR(主页!$D$9)+1,1,1),OR(当年!I4=0,I4>=DATE(YEAR(主页!$D$9)+1,1,1))),当年!K4,0) -> 0 | S4: =O4+P4-Q4-R4 -> 0 | T4: =IFERROR(IF(AND(H4<DATE(YEAR(主页!$D$9),1,1),OR(当年!I4=0,I4>=DATE(YEAR(主页!$D$9),1,1))),MIN(K4*(1-M4),K4*(1-M4)/L4/12*DATEDIF(H4,DATE(YEAR(主页!$D$9)-1,12,31),"M")),0),0) -> 149625 | U4: =IFERROR(K4*(1-M4)/L4/12*DATEDIF(MAX(H4,DATE(YEAR(主页!$D$9)-1,12,31)),MIN(N4,IF(OR(当年!I4=0,I4>=DATE(YEAR(主页!$D$9),1,1)),DATE(YEAR(主页!$D$9),12,31),I4)),"M"),0) -> 28500 | V4: =IF(AND(I4>=DATE(YEAR(主页!$D$9)-1,12,31),I4<=DATE(YEAR(主页!$D$9),12,31)),T4+U4,0) -> 178125 | W4: =IF(AND(H4<DATE(YEAR(主页!$D$9)+1,1,1),OR(当年!I4=0,I4>=DATE(YEAR(主页!$D$9)+1,1,1))),IFERROR(K4*(1-M4)/L4/12*DATEDIF(H4,MIN(N4,IF(OR(当年!I4=0,I4>=DATE(YEAR(主页!$D$9),1,1)),DATE(YEAR(主页!$D$9),12,31),I4)),"M"),0),0) -> 0 | X4: =T4+U4-V4-W4 -> 0 | Z4: 10 | AA4: 在用 | AB4: =IFERROR(IF(AA4="在用",K4/Z4,0),0) -> 30000 | AD4: =IFERROR(K4*(1-M4)/L4/12*DATEDIF(MAX(H4,DATE(YEAR(主页!$D$9)-1,12,31)),MIN(N4,IF(OR(当年!I4=0,I4>=DATE(YEAR(主页!$D$9),1,1)),DATE(YEAR(主页!$D$9),MONTH(主页!$D$9),31),I4)),"M"),0) -> 23750 | AE4: =U4-AD4 -> 4750
A5: FA004 | B5: 自动装配线 | C5: 机器设备 | D5: 流程中心 | E5: 制造中心 | F5: 工程部 | G5: 生产车间 | H5: 41518 | I5: 44135 | K5: 350000 | L5: 10 | M5: 0.05 | N5: =IF(H5=0,"-",EOMONTH(H5,L5*12)) -> 45199 | O5: =IF(AND(H5<DATE(YEAR(主页!$D$9),1,1),OR(当年!I5=0,I5>=DATE(YEAR(主页!$D$9),1,1))),当年!K5,0) -> 0 | P5: =IF(AND(H5>=DATE(YEAR(主页!$D$9)-1,12,31),H5<=DATE(YEAR(主页!$D$9),12,31)),K5,0) -> 0 | Q5: =IF(AND(I5>=DATE(YEAR(主页!$D$9)-1,12,31),I5<=DATE(YEAR(主页!$D$9),12,31)),K5,0) -> 0 | R5: =IF(AND(H5<DATE(YEAR(主页!$D$9)+1,1,1),OR(当年!I5=0,I5>=DATE(YEAR(主页!$D$9)+1,1,1))),当年!K5,0) -> 0 | S5: =O5+P5-Q5-R5 -> 0 | T5: =IFERROR(IF(AND(H5<DATE(YEAR(主页!$D$9),1,1),OR(当年!I5=0,I5>=DATE(YEAR(主页!$D$9),1,1))),MIN(K5*(1-M5),K5*(1-M5)/L5/12*DATEDIF(H5,DATE(YEAR(主页!$D$9)-1,12,31),"M")),0),0) -> 0 | U5: =IFERROR(K5*(1-M5)/L5/12*DATEDIF(MAX(H5,DATE(YEAR(主页!$D$9)-1,12,31)),MIN(N5,IF(OR(当年!I5=0,I5>=DATE(YEAR(主页!$D$9),1,1)),DATE(YEAR(主页!$D$9),12,31),I5)),"M"),0) -> 0 | V5: =IF(AND(I5>=DATE(YEAR(主页!$D$9)-1,12,31),I5<=DATE(YEAR(主页!$D$9),12,31)),T5+U5,0) -> 0 | W5: =IF(AND(H5<DATE(YEAR(主页!$D$9)+1,1,1),OR(当年!I5=0,I5>=DATE(YEAR(主页!$D$9)+1,1,1))),IFERROR(K5*(1-M5)/L5/12*DATEDIF(H5,MIN(N5,IF(OR(当年!I5=0,I5>=DATE(YEAR(主页!$D$9),1,1)),DATE(YEAR(主页!$D$9),12,31),I5)),"M"),0),0) -> 0 | X5: =T5+U5-V5-W5 -> 0 | Z5: 10 | AA5: 在用 | AB5: =IFERROR(IF(AA5="在用",K5/Z5,0),0) -> 35000 | AD5: =IFERROR(K5*(1-M5)/L5/12*DATEDIF(MAX(H5,DATE(YEAR(主页!$D$9)-1,12,31)),MIN(N5,IF(OR(当年!I5=0,I5>=DATE(YEAR(主页!$D$9),1,1)),DATE(YEAR(主页!$D$9),MONTH(主页!$D$9),31),I5)),"M"),0) -> 0 | AE5: =U5-AD5 -> 0
A6: FA005 | B6: 车床 | C6: 机器设备 | D6: 流程中心 | E6: 制造中心 | F6: 工程部 | G6: 生产车间 | H6: 38353 | K6: 50000 | L6: 10 | M6: 0.05 | N6: =IF(H6=0,"-",EOMONTH(H6,L6*12)) -> 42035 | O6: =IF(AND(H6<DATE(YEAR(主页!$D$9),1,1),OR(当年!I6=0,I6>=DATE(YEAR(主页!$D$9),1,1))),当年!K6,0) -> 50000 | P6: =IF(AND(H6>=DATE(YEAR(主页!$D$9)-1,12,31),H6<=DATE(YEAR(主页!$D$9),12,31)),K6,0) -> 0 | Q6: =IF(AND(I6>=DATE(YEAR(主页!$D$9)-1,12,31),I6<=DATE(YEAR(主页!$D$9),12,31)),K6,0) -> 0 | R6: =IF(AND(H6<DATE(YEAR(主页!$D$9)+1,1,1),OR(当年!I6=0,I6>=DATE(YEAR(主页!$D$9)+1,1,1))),当年!K6,0) -> 50000 | S6: =O6+P6-Q6-R6 -> 0 | T6: =IFERROR(IF(AND(H6<DATE(YEAR(主页!$D$9),1,1),OR(当年!I6=0,I6>=DATE(YEAR(主页!$D$9),1,1))),MIN(K6*(1-M6),K6*(1-M6)/L6/12*DATEDIF(H6,DATE(YEAR(主页!$D$9)-1,12,31),"M")),0),0) -> 47500 | U6: =IFERROR(K6*(1-M6)/L6/12*DATEDIF(MAX(H6,DATE(YEAR(主页!$D$9)-1,12,31)),MIN(N6,IF(OR(当年!I6=0,I6>=DATE(YEAR(主页!$D$9),1,1)),DATE(YEAR(主页!$D$9),12,31),I6)),"M"),0) -> 0 | V6: =IF(AND(I6>=DATE(YEAR(主页!$D$9)-1,12,31),I6<=DATE(YEAR(主页!$D$9),12,31)),T6+U6,0) -> 0 | W6: =IF(AND(H6<DATE(YEAR(主页!$D$9)+1,1,1),OR(当年!I6=0,I6>=DATE(YEAR(主页!$D$9)+1,1,1))),IFERROR(K6*(1-M6)/L6/12*DATEDIF(H6,MIN(N6,IF(OR(当年!I6=0,I6>=DATE(YEAR(主页!$D$9),1,1)),DATE(YEAR(主页!$D$9),12,31),I6)),"M"),0),0) -> 47500 | X6: =T6+U6-V6-W6 -> 0 | Z6: 10 | AA6: 在用 | AB6: =IFERROR(IF(AA6="在用",K6/Z6,0),0) -> 5000 | AD6: =IFERROR(K6*(1-M6)/L6/12*DATEDIF(MAX(H6,DATE(YEAR(主页!$D$9)-1,12,31)),MIN(N6,IF(OR(当年!I6=0,I6>=DATE(YEAR(主页!$D$9),1,1)),DATE(YEAR(主页!$D$9),MONTH(主页!$D$9),31),I6)),"M"),0) -> 0 | AE6: =U6-AD6 -> 0
A7: FA006 | B7: 笔记本电脑 | C7: 电子设备 | D7: 支持中心 | E7: 财务部 | F7: IT部 | G7: 财务部 | H7: 44712 | K7: 9800 | L7: =2/12 -> 0.16666667 | M7: 0 | N7: =IF(H7=0,"-",EOMONTH(H7,L7*12)) -> 44773 | O7: =IF(AND(H7<DATE(YEAR(主页!$D$9),1,1),OR(当年!I7=0,I7>=DATE(YEAR(主页!$D$9),1,1))),当年!K7,0) -> 0 | P7: =IF(AND(H7>=DATE(YEAR(主页!$D$9)-1,12,31),H7<=DATE(YEAR(主页!$D$9),12,31)),K7,0) -> 0 | Q7: =IF(AND(I7>=DATE(YEAR(主页!$D$9)-1,12,31),I7<=DATE(YEAR(主页!$D$9),12,31)),K7,0) -> 0 | R7: =IF(AND(H7<DATE(YEAR(主页!$D$9)+1,1,1),OR(当年!I7=0,I7>=DATE(YEAR(主页!$D$9)+1,1,1))),当年!K7,0) -> 0 | S7: =O7+P7-Q7-R7 -> 0 | T7: =IFERROR(IF(AND(H7<DATE(YEAR(主页!$D$9),1,1),OR(当年!I7=0,I7>=DATE(YEAR(主页!$D$9),1,1))),MIN(K7*(1-M7),K7*(1-M7)/L7/12*DATEDIF(H7,DATE(YEAR(主页!$D$9)-1,12,31),"M")),0),0) -> 0 | U7: =IFERROR(K7*(1-M7)/L7/12*DATEDIF(MAX(H7,DATE(YEAR(主页!$D$9)-1,12,31)),MIN(N7,IF(OR(当年!I7=0,I7>=DATE(YEAR(主页!$D$9),1,1)),DATE(YEAR(主页!$D$9),12,31),I7)),"M"),0) -> 0 | V7: =IF(AND(I7>=DATE(YEAR(主页!$D$9)-1,12,31),I7<=DATE(YEAR(主页!$D$9),12,31)),T7+U7,0) -> 0 | W7: =IF(AND(H7<DATE(YEAR(主页!$D$9)+1,1,1),OR(当年!I7=0,I7>=DATE(YEAR(主页!$D$9)+1,1,1))),IFERROR(K7*(1-M7)/L7/12*DATEDIF(H7,MIN(N7,IF(OR(当年!I7=0,I7>=DATE(YEAR(主页!$D$9),1,1)),DATE(YEAR(主页!$D$9),12,31),I7)),"M"),0),0) -> 0 | X7: =T7+U7-V7-W7 -> 0 | Z7: 3 | AA7: 在用 | AB7: =IFERROR(IF(AA7="在用",K7/Z7,0),0) -> 3266.6667 | AD7: =IFERROR(K7*(1-M7)/L7/12*DATEDIF(MAX(H7,DATE(YEAR(主页!$D$9)-1,12,31)),MIN(N7,IF(OR(当年!I7=0,I7>=DATE(YEAR(主页!$D$9),1,1)),DATE(YEAR(主页!$D$9),MONTH(主页!$D$9),31),I7)),"M"),0) -> 0 | AE7: =U7-AD7 -> 0
A8: FA007 | B8: 笔记本电脑 | C8: 电子设备 | D8: 支持中心 | E8: 财务部 | F8: IT部 | G8: 财务部 | H8: 44501 | K8: 9800 | L8: =2/12 -> 0.16666667 | M8: 0 | N8: =IF(H8=0,"-",EOMONTH(H8,L8*12)) -> 44592 | O8: =IF(AND(H8<DATE(YEAR(主页!$D$9),1,1),OR(当年!I8=0,I8>=DATE(YEAR(主页!$D$9),1,1))),当年!K8,0) -> 0 | P8: =IF(AND(H8>=DATE(YEAR(主页!$D$9)-1,12,31),H8<=DATE(YEAR(主页!$D$9),12,31)),K8,0) -> 9800 | Q8: =IF(AND(I8>=DATE(YEAR(主页!$D$9)-1,12,31),I8<=DATE(YEAR(主页!$D$9),12,31)),K8,0) -> 0 | R8: =IF(AND(H8<DATE(YEAR(主页!$D$9)+1,1,1),OR(当年!I8=0,I8>=DATE(YEAR(主页!$D$9)+1,1,1))),当年!K8,0) -> 9800 | S8: =O8+P8-Q8-R8 -> 0 | T8: =IFERROR(IF(AND(H8<DATE(YEAR(主页!$D$9),1,1),OR(当年!I8=0,I8>=DATE(YEAR(主页!$D$9),1,1))),MIN(K8*(1-M8),K8*(1-M8)/L8/12*DATEDIF(H8,DATE(YEAR(主页!$D$9)-1,12,31),"M")),0),0) -> 0 | U8: =IFERROR(K8*(1-M8)/L8/12*DATEDIF(MAX(H8,DATE(YEAR(主页!$D$9)-1,12,31)),MIN(N8,IF(OR(当年!I8=0,I8>=DATE(YEAR(主页!$D$9),1,1)),DATE(YEAR(主页!$D$9),12,31),I8)),"M"),0) -> 4900 | V8: =IF(AND(I8>=DATE(YEAR(主页!$D$9)-1,12,31),I8<=DATE(YEAR(主页!$D$9),12,31)),T8+U8,0) -> 0 | W8: =IF(AND(H8<DATE(YEAR(主页!$D$9)+1,1,1),OR(当年!I8=0,I8>=DATE(YEAR(主页!$D$9)+1,1,1))),IFERROR(K8*(1-M8)/L8/12*DATEDIF(H8,MIN(N8,IF(OR(当年!I8=0,I8>=DATE(YEAR(主页!$D$9),1,1)),DATE(YEAR(主页!$D$9),12,31),I8)),"M"),0),0) -> 4900 | X8: =T8+U8-V8-W8 -> 0 | Z8: 3 | AA8: 在用 | AB8: =IFERROR(IF(AA8="在用",K8/Z8,0),0) -> 3266.6667 | AD8: =IFERROR(K8*(1-M8)/L8/12*DATEDIF(MAX(H8,DATE(YEAR(主页!$D$9)-1,12,31)),MIN(N8,IF(OR(当年!I8=0,I8>=DATE(YEAR(主页!$D$9),1,1)),DATE(YEAR(主页!$D$9),MONTH(主页!$D$9),31),I8)),"M"),0) -> 0 | AE8: =U8-AD8 -> 4900
A9: FA008 | B9: 笔记本电脑 | C9: 电子设备 | D9: 支持中心 | E9: 财务部 | F9: IT部 | G9: 财务部 | H9: 43831 | K9: 9800 | L9: =2/12 -> 0.16666667 | M9: 0 | N9: =IF(H9=0,"-",EOMONTH(H9,L9*12)) -> 43921 | O9: =IF(AND(H9<DATE(YEAR(主页!$D$9),1,1),OR(当年!I9=0,I9>=DATE(YEAR(主页!$D$9),1,1))),当年!K9,0) -> 9800 | P9: =IF(AND(H9>=DATE(YEAR(主页!$D$9)-1,12,31),H9<=DATE(YEAR(主页!$D$9),12,31)),K9,0) -> 0 | Q9: =IF(AND(I9>=DATE(YEAR(主页!$D$9)-1,12,31),I9<=DATE(YEAR(主页!$D$9),12,31)),K9,0) -> 0 | R9: =IF(AND(H9<DATE(YEAR(主页!$D$9)+1,1,1),OR(当年!I9=0,I9>=DATE(YEAR(主页!$D$9)+1,1,1))),当年!K9,0) -> 9800 | S9: =O9+P9-Q9-R9 -> 0 | T9: =IFERROR(IF(AND(H9<DATE(YEAR(主页!$D$9),1,1),OR(当年!I9=0,I9>=DATE(YEAR(主页!$D$9),1,1))),MIN(K9*(1-M9),K9*(1-M9)/L9/12*DATEDIF(H9,DATE(YEAR(主页!$D$9)-1,12,31),"M")),0),0) -> 9800 | U9: =IFERROR(K9*(1-M9)/L9/12*DATEDIF(MAX(H9,DATE(YEAR(主页!$D$9)-1,12,31)),MIN(N9,IF(OR(当年!I9=0,I9>=DATE(YEAR(主页!$D$9),1,1)),DATE(YEAR(主页!$D$9),12,31),I9)),"M"),0) -> 0 | V9: =IF(AND(I9>=DATE(YEAR(主页!$D$9)-1,12,31),I9<=DATE(YEAR(主页!$D$9),12,31)),T9+U9,0) -> 0 | W9: =IF(AND(H9<DATE(YEAR(主页!$D$9)+1,1,1),OR(当年!I9=0,I9>=DATE(YEAR(主页!$D$9)+1,1,1))),IFERROR(K9*(1-M9)/L9/12*DATEDIF(H9,MIN(N9,IF(OR(当年!I9=0,I9>=DATE(YEAR(主页!$D$9),1,1)),DATE(YEAR(主页!$D$9),12,31),I9)),"M"),0),0) -> 9800 | X9: =T9+U9-V9-W9 -> 0 | Z9: 3 | AA9: 在用 | AB9: =IFERROR(IF(AA9="在用",K9/Z9,0),0) -> 3266.6667 | AD9: =IFERROR(K9*(1-M9)/L9/12*DATEDIF(MAX(H9,DATE(YEAR(主页!$D$9)-1,12,31)),MIN(N9,IF(OR(当年!I9=0,I9>=DATE(YEAR(主页!$D$9),1,1)),DATE(YEAR(主页!$D$9),MONTH(主页!$D$9),31),I9)),"M"),0) -> 0 | AE9: =U9-AD9 -> 0
A10: FA009 | B10: 笔记本电脑 | C10: 电子设备 | D10: 支持中心 | E10: 财务部 | F10: IT部 | G10: 财务部 | H10: 43891 | K10: 9800 | L10: =2/12 -> 0.16666667 | M10: 0 | N10: =IF(H10=0,"-",EOMONTH(H10,L10*12)) -> 43982 | O10: =IF(AND(H10<DATE(YEAR(主页!$D$9),1,1),OR(当年!I10=0,I10>=DATE(YEAR(主页!$D$9),1,1))),当年!K10,0) -> 9800 | P10: =IF(AND(H10>=DATE(YEAR(主页!$D$9)-1,12,31),H10<=DATE(YEAR(主页!$D$9),12,31)),K10,0) -> 0 | Q10: =IF(AND(I10>=DATE(YEAR(主页!$D$9)-1,12,31),I10<=DATE(YEAR(主页!$D$9),12,31)),K10,0) -> 0 | R10: =IF(AND(H10<DATE(YEAR(主页!$D$9)+1,1,1),OR(当年!I10=0,I10>=DATE(YEAR(主页!$D$9)+1,1,1))),当年!K10,0) -> 9800 | S10: =O10+P10-Q10-R10 -> 0 | T10: =IFERROR(IF(AND(H10<DATE(YEAR(主页!$D$9),1,1),OR(当年!I10=0,I10>=DATE(YEAR(主页!$D$9),1,1))),MIN(K10*(1-M10),K10*(1-M10)/L10/12*DATEDIF(H10,DATE(YEAR(主页!$D$9)-1,12,31),"M")),0),0) -> 9800 | U10: =IFERROR(K10*(1-M10)/L10/12*DATEDIF(MAX(H10,DATE(YEAR(主页!$D$9)-1,12,31)),MIN(N10,IF(OR(当年!I10=0,I10>=DATE(YEAR(主页!$D$9),1,1)),DATE(YEAR(主页!$D$9),12,31),I10)),"M"),0) -> 0 | V10: =IF(AND(I10>=DATE(YEAR(主页!$D$9)-1,12,31),I10<=DATE(YEAR(主页!$D$9),12,31)),T10+U10,0) -> 0 | W10: =IF(AND(H10<DATE(YEAR(主页!$D$9)+1,1,1),OR(当年!I10=0,I10>=DATE(YEAR(主页!$D$9)+1,1,1))),IFERROR(K10*(1-M10)/L10/12*DATEDIF(H10,MIN(N10,IF(OR(当年!I10=0,I10>=DATE(YEAR(主页!$D$9),1,1)),DATE(YEAR(主页!$D$9),12,31),I10)),"M"),0),0) -> 9800 | X10: =T10+U10-V10-W10 -> 0 | Z10: 3 | AA10: 在用 | AB10: =IFERROR(IF(AA10="在用",K10/Z10,0),0) -> 3266.6667 | AD10: =IFERROR(K10*(1-M10)/L10/12*DATEDIF(MAX(H10,DATE(YEAR(主页!$D$9)-1,12,31)),MIN(N10,IF(OR(当年!I10=0,I10>=DATE(YEAR(主页!$D$9),1,1)),DATE(YEAR(主页!$D$9),MONTH(主页!$D$9),31),I10)),"M"),0) -> 0 | AE10: =U10-AD10 -> 0
A11: FA010 | B11: 复印机 | C11: 电子设备 | D11: 支持中心 | E11: 行政部 | F11: IT部 | G11: 行政部 | H11: 44267 | K11: 23000 | L11: =2/12 -> 0.16666667 | M11: 0 | N11: =IF(H11=0,"-",EOMONTH(H11,L11*12)) -> 44347 | O11: =IF(AND(H11<DATE(YEAR(主页!$D$9),1,1),OR(当年!I11=0,I11>=DATE(YEAR(主页!$D$9),1,1))),当年!K11,0) -> 0 | P11: =IF(AND(H11>=DATE(YEAR(主页!$D$9)-1,12,31),H11<=DATE(YEAR(主页!$D$9),12,31)),K11,0) -> 23000 | Q11: =IF(AND(I11>=DATE(YEAR(主页!$D$9)-1,12,31),I11<=DATE(YEAR(主页!$D$9),12,31)),K11,0) -> 0 | R11: =IF(AND(H11<DATE(YEAR(主页!$D$9)+1,1,1),OR(当年!I11=0,I11>=DATE(YEAR(主页!$D$9)+1,1,1))),当年!K11,0) -> 23000 | S11: =O11+P11-Q11-R11 -> 0 | T11: =IFERROR(IF(AND(H11<DATE(YEAR(主页!$D$9),1,1),OR(当年!I11=0,I11>=DATE(YEAR(主页!$D$9),1,1))),MIN(K11*(1-M11),K11*(1-M11)/L11/12*DATEDIF(H11,DATE(YEAR(主页!$D$9)-1,12,31),"M")),0),0) -> 0 | U11: =IFERROR(K11*(1-M11)/L11/12*DATEDIF(MAX(H11,DATE(YEAR(主页!$D$9)-1,12,31)),MIN(N11,IF(OR(当年!I11=0,I11>=DATE(YEAR(主页!$D$9),1,1)),DATE(YEAR(主页!$D$9),12,31),I11)),"M"),0) -> 23000 | V11: =IF(AND(I11>=DATE(YEAR(主页!$D$9)-1,12,31),I11<=DATE(YEAR(主页!$D$9),12,31)),T11+U11,0) -> 0 | W11: =IF(AND(H11<DATE(YEAR(主页!$D$9)+1,1,1),OR(当年!I11=0,I11>=DATE(YEAR(主页!$D$9)+1,1,1))),IFERROR(K11*(1-M11)/L11/12*DATEDIF(H11,MIN(N11,IF(OR(当年!I11=0,I11>=DATE(YEAR(主页!$D$9),1,1)),DATE(YEAR(主页!$D$9),12,31),I11)),"M"),0),0) -> 23000 | X11: =T11+U11-V11-W11 -> 0 | Z11: 3 | AA11: 在用 | AB11: =IFERROR(IF(AA11="在用",K11/Z11,0),0) -> 7666.6667 | AD11: =IFERROR(K11*(1-M11)/L11/12*DATEDIF(MAX(H11,DATE(YEAR(主页!$D$9)-1,12,31)),MIN(N11,IF(OR(当年!I11=0,I11>=DATE(YEAR(主页!$D$9),1,1)),DATE(YEAR(主页!$D$9),MONTH(主页!$D$9),31),I11)),"M"),0) -> 23000 | AE11: =U11-AD11 -> 0

Sheet 下年
A1: 资产编号 | B1: 资产名称 | C1: 资产类别 | D1: 责任中心1 | E1: 责任中心2 | F1: 归口管理部门 | G1: 使用部门 | H1: 购建日期 | I1: 处置日期 | J1: 资产异动原因 | K1: 原值 | L1: 财务折旧年限 | M1: 预计残值率 | N1: 折旧期满日 | O1: 年初原值 | P1: 原值增加 | Q1: 原值减少 | R1: 年末原值 | S1: chk | T1: 年初累计折旧 | U1: 本年增加折旧 | V1: 折旧减少 | W1: 期末累计折旧 | X1: chk | Z1: 技术折旧年限 | AA1: 使用状态 | AB1: 当年技术折旧
A2: FA001 | B2: 生产线 | C2: 机器设备 | D2: 流程中心 | E2: 制造中心 | F2: 工程部 | G2: 生产车间 | H2: 43388 | K2: 12000000 | L2: 10 | M2: 0.05 | N2: =IF(H2=0,"-",EOMONTH(H2,L2*12)) -> 47057 | O2: =IF(AND(H2<DATE(YEAR(主页!$D$9)+1,1,1),OR(下年!I2=0,I2>=DATE(YEAR(主页!$D$9)+1,1,1))),下年!K2,0) -> 12000000 | P2: =IF(AND(H2>=DATE(YEAR(主页!$D$9),12,31),H2<=DATE(YEAR(主页!$D$9)+1,12,31)),K2,0) -> 0 | Q2: =IF(AND(I2>=DATE(YEAR(主页!$D$9),12,31),I2<=DATE(YEAR(主页!$D$9)+1,12,31)),K2,0) -> 0 | R2: =IF(AND(H2<DATE(YEAR(主页!$D$9)+2,1,1),OR(下年!I2=0,I2>=DATE(YEAR(主页!$D$9)+2,1,1))),下年!K2,0) -> 12000000 | S2: =O2+P2-Q2-R2 -> 0 | T2: =IFERROR(IF(AND(H2<DATE(YEAR(主页!$D$9)+1,1,1),OR(当年!I2=0,I2>=DATE(YEAR(主页!$D$9)+1,1,1))),MIN(K2*(1-M2),K2*(1-M2)/L2/12*DATEDIF(H2,DATE(YEAR(主页!$D$9),12,31),"M")),0),0) -> 3610000 | U2: =IFERROR(K2*(1-M2)/L2/12*DATEDIF(MAX(H2,DATE(YEAR(主页!$D$9),12,31)),MIN(N2,IF(OR(当年!I2=0,I2>=DATE(YEAR(主页!$D$9)+1,1,1)),DATE(YEAR(主页!$D$9)+1,12,31),I2)),"M"),0) -> 1140000 | V2: =IF(AND(I2>=DATE(YEAR(主页!$D$9)-1,12,31),I2<=DATE(YEAR(主页!$D$9),12,31)),T2+U2,0) -> 0 | W2: =IF(AND(H2<DATE(YEAR(主页!$D$9)+2,1,1),OR(当年!I2=0,I2>=DATE(YEAR(主页!$D$9)+2,1,1))),IFERROR(K2*(1-M2)/L2/12*DATEDIF(H2,MIN(N2,IF(OR(当年!I2=0,I2>=DATE(YEAR(主页!$D$9)+1,1,1)),DATE(YEAR(主页!$D$9)+1,12,31),I2)),"M"),0),0) -> 4750000 | X2: =T2+U2-V2-W2 -> 0 | Z2: 10 | AA2: 在用 | AB2: =IFERROR(IF(AA2="在用",K2/Z2,0),0) -> 1200000
A3: FA002 | B3: 厂房 | C3: 建筑物 | D3: 流程中心 | E3: 制造中心 | F3: 行政部 | G3: 生产车间 | H3: 44359 | K3: 35000000 | L3: 20 | M3: 0.05 | N3: =IF(H3=0,"-",EOMONTH(H3,L3*12)) -> 51682 | O3: =IF(AND(H3<DATE(YEAR(主页!$D$9)+1,1,1),OR(下年!I3=0,I3>=DATE(YEAR(主页!$D$9)+1,1,1))),下年!K3,0) -> 35000000 | P3: =IF(AND(H3>=DATE(YEAR(主页!$D$9),12,31),H3<=DATE(YEAR(主页!$D$9)+1,12,31)),K3,0) -> 0 | Q3: =IF(AND(I3>=DATE(YEAR(主页!$D$9),12,31),I3<=DATE(YEAR(主页!$D$9)+1,12,31)),K3,0) -> 0 | R3: =IF(AND(H3<DATE(YEAR(主页!$D$9)+2,1,1),OR(下年!I3=0,I3>=DATE(YEAR(主页!$D$9)+2,1,1))),下年!K3,0) -> 35000000 | S3: =O3+P3-Q3-R3 -> 0 | T3: =IFERROR(IF(AND(H3<DATE(YEAR(主页!$D$9)+1,1,1),OR(当年!I3=0,I3>=DATE(YEAR(主页!$D$9)+1,1,1))),MIN(K3*(1-M3),K3*(1-M3)/L3/12*DATEDIF(H3,DATE(YEAR(主页!$D$9),12,31),"M")),0),0) -> 831250 | U3: =IFERROR(K3*(1-M3)/L3/12*DATEDIF(MAX(H3,DATE(YEAR(主页!$D$9),12,31)),MIN(N3,IF(OR(当年!I3=0,I3>=DATE(YEAR(主页!$D$9)+1,1,1)),DATE(YEAR(主页!$D$9)+1,12,31),I3)),"M"),0) -> 1662500 | V3: =IF(AND(I3>=DATE(YEAR(主页!$D$9)-1,12,31),I3<=DATE(YEAR(主页!$D$9),12,31)),T3+U3,0) -> 0 | W3: =IF(AND(H3<DATE(YEAR(主页!$D$9)+2,1,1),OR(当年!I3=0,I3>=DATE(YEAR(主页!$D$9)+2,1,1))),IFERROR(K3*(1-M3)/L3/12*DATEDIF(H3,MIN(N3,IF(OR(当年!I3=0,I3>=DATE(YEAR(主页!$D$9)+1,1,1)),DATE(YEAR(主页!$D$9)+1,12,31),I3)),"M"),0),0) -> 2493750 | X3: =T3+U3-V3-W3 -> 0 | Z3: 20 | AA3: 在用 | AB3: =IFERROR(IF(AA3="在用",K3/Z3,0),0) -> 1750000
A4: FA003 | B4: 检测仪 | C4: 机器设备 | D4: 流程中心 | E4: 制造中心 | F4: 技术部 | G4: 生产车间 | H4: 42270 | I4: 44408 | K4: 300000 | L4: 10 | M4: 0.05 | N4: =IF(H4=0,"-",EOMONTH(H4,L4*12)) -> 45930 | O4: =IF(AND(H4<DATE(YEAR(主页!$D$9)+1,1,1),OR(下年!I4=0,I4>=DATE(YEAR(主页!$D$9)+1,1,1))),下年!K4,0) -> 0 | P4: =IF(AND(H4>=DATE(YEAR(主页!$D$9),12,31),H4<=DATE(YEAR(主页!$D$9)+1,12,31)),K4,0) -> 0 | Q4: =IF(AND(I4>=DATE(YEAR(主页!$D$9),12,31),I4<=DATE(YEAR(主页!$D$9)+1,12,31)),K4,0) -> 0 | R4: =IF(AND(H4<DATE(YEAR(主页!$D$9)+2,1,1),OR(下年!I4=0,I4>=DATE(YEAR(主页!$D$9)+2,1,1))),下年!K4,0) -> 0 | S4: =O4+P4-Q4-R4 -> 0 | T4: =IFERROR(IF(AND(H4<DATE(YEAR(主页!$D$9)+1,1,1),OR(当年!I4=0,I4>=DATE(YEAR(主页!$D$9)+1,1,1))),MIN(K4*(1-M4),K4*(1-M4)/L4/12*DATEDIF(H4,DATE(YEAR(主页!$D$9),12,31),"M")),0),0) -> 0 | U4: =IFERROR(K4*(1-M4)/L4/12*DATEDIF(MAX(H4,DATE(YEAR(主页!$D$9),12,31)),MIN(N4,IF(OR(当年!I4=0,I4>=DATE(YEAR(主页!$D$9)+1,1,1)),DATE(YEAR(主页!$D$9)+1,12,31),I4)),"M"),0) -> 0 | V4: =IF(AND(I4>=DATE(YEAR(主页!$D$9)-1,12,31),I4<=DATE(YEAR(主页!$D$9),12,31)),T4+U4,0) -> 0 | W4: =IF(AND(H4<DATE(YEAR(主页!$D$9)+2,1,1),OR(当年!I4=0,I4>=DATE(YEAR(主页!$D$9)+2,1,1))),IFERROR(K4*(1-M4)/L4/12*DATEDIF(H4,MIN(N4,IF(OR(当年!I4=0,I4>=DATE(YEAR(主页!$D$9)+1,1,1)),DATE(YEAR(主页!$D$9)+1,12,31),I4)),"M"),0),0) -> 0 | X4: =T4+U4-V4-W4 -> 0 | Z4: 10 | AA4: 在用 | AB4: =IFERROR(IF(AA4="在用",K4/Z4,0),0) -> 30000
A5: FA004 | B5: 自动装配线 | C5: 机器设备 | D5: 流程中心 | E5: 制造中心 | F5: 工程部 | G5: 生产车间 | H5: 41518 | I5: 44135 | K5: 350000 | L5: 10 | M5: 0.05 | N5: =IF(H5=0,"-",EOMONTH(H5,L5*12)) -> 45199 | O5: =IF(AND(H5<DATE(YEAR(主页!$D$9)+1,1,1),OR(下年!I5=0,I5>=DATE(YEAR(主页!$D$9)+1,1,1))),下年!K5,0) -> 0 | P5: =IF(AND(H5>=DATE(YEAR(主页!$D$9),12,31),H5<=DATE(YEAR(主页!$D$9)+1,12,31)),K5,0) -> 0 | Q5: =IF(AND(I5>=DATE(YEAR(主页!$D$9),12,31),I5<=DATE(YEAR(主页!$D$9)+1,12,31)),K5,0) -> 0 | R5: =IF(AND(H5<DATE(YEAR(主页!$D$9)+2,1,1),OR(下年!I5=0,I5>=DATE(YEAR(主页!$D$9)+2,1,1))),下年!K5,0) -> 0 | S5: =O5+P5-Q5-R5 -> 0 | T5: =IFERROR(IF(AND(H5<DATE(YEAR(主页!$D$9)+1,1,1),OR(当年!I5=0,I5>=DATE(YEAR(主页!$D$9)+1,1,1))),MIN(K5*(1-M5),K5*(1-M5)/L5/12*DATEDIF(H5,DATE(YEAR(主页!$D$9),12,31),"M")),0),0) -> 0 | U5: =IFERROR(K5*(1-M5)/L5/12*DATEDIF(MAX(H5,DATE(YEAR(主页!$D$9),12,31)),MIN(N5,IF(OR(当年!I5=0,I5>=DATE(YEAR(主页!$D$9)+1,1,1)),DATE(YEAR(主页!$D$9)+1,12,31),I5)),"M"),0) -> 0 | V5: =IF(AND(I5>=DATE(YEAR(主页!$D$9)-1,12,31),I5<=DATE(YEAR(主页!$D$9),12,31)),T5+U5,0) -> 0 | W5: =IF(AND(H5<DATE(YEAR(主页!$D$9)+2,1,1),OR(当年!I5=0,I5>=DATE(YEAR(主页!$D$9)+2,1,1))),IFERROR(K5*(1-M5)/L5/12*DATEDIF(H5,MIN(N5,IF(OR(当年!I5=0,I5>=DATE(YEAR(主页!$D$9)+1,1,1)),DATE(YEAR(主页!$D$9)+1,12,31),I5)),"M"),0),0) -> 0 | X5: =T5+U5-V5-W5 -> 0 | Z5: 10 | AA5: 在用 | AB5: =IFERROR(IF(AA5="在用",K5/Z5,0),0) -> 35000
A6: FA005 | B6: 车床 | C6: 机器设备 | D6: 流程中心 | E6: 制造中心 | F6: 工程部 | G6: 生产车间 | H6: 38353 | I6: 44682 | K6: 50000 | L6: 10 | M6: 0.05 | N6: =IF(H6=0,"-",EOMONTH(H6,L6*12)) -> 42035 | O6: =IF(AND(H6<DATE(YEAR(主页!$D$9)+1,1,1),OR(下年!I6=0,I6>=DATE(YEAR(主页!$D$9)+1,1,1))),下年!K6,0) -> 50000 | P6: =IF(AND(H6>=DATE(YEAR(主页!$D$9),12,31),H6<=DATE(YEAR(主页!$D$9)+1,12,31)),K6,0) -> 0 | Q6: =IF(AND(I6>=DATE(YEAR(主页!$D$9),12,31),I6<=DATE(YEAR(主页!$D$9)+1,12,31)),K6,0) -> 50000 | R6: =IF(AND(H6<DATE(YEAR(主页!$D$9)+2,1,1),OR(下年!I6=0,I6>=DATE(YEAR(主页!$D$9)+2,1,1))),下年!K6,0) -> 0 | S6: =O6+P6-Q6-R6 -> 0 | T6: =IFERROR(IF(AND(H6<DATE(YEAR(主页!$D$9)+1,1,1),OR(当年!I6=0,I6>=DATE(YEAR(主页!$D$9)+1,1,1))),MIN(K6*(1-M6),K6*(1-M6)/L6/12*DATEDIF(H6,DATE(YEAR(主页!$D$9),12,31),"M")),0),0) -> 47500 | U6: =IFERROR(K6*(1-M6)/L6/12*DATEDIF(MAX(H6,DATE(YEAR(主页!$D$9),12,31)),MIN(N6,IF(OR(当年!I6=0,I6>=DATE(YEAR(主页!$D$9)+1,1,1)),DATE(YEAR(主页!$D$9)+1,12,31),I6)),"M"),0) -> 0 | V6: =IF(AND(I6>=DATE(YEAR(主页!$D$9)-1,12,31),I6<=DATE(YEAR(主页!$D$9),12,31)),T6+U6,0) -> 0 | W6: =IF(AND(H6<DATE(YEAR(主页!$D$9)+2,1,1),OR(当年!I6=0,I6>=DATE(YEAR(主页!$D$9)+2,1,1))),IFERROR(K6*(1-M6)/L6/12*DATEDIF(H6,MIN(N6,IF(OR(当年!I6=0,I6>=DATE(YEAR(主页!$D$9)+1,1,1)),DATE(YEAR(主页!$D$9)+1,12,31),I6)),"M"),0),0) -> 47500 | X6: =T6+U6-V6-W6 -> 0 | Z6: 10 | AA6: 在用 | AB6: =IFERROR(IF(AA6="在用",K6/Z6,0),0) -> 5000
A7: FA006 | B7: 笔记本电脑 | C7: 电子设备 | D7: 支持中心 | E7: 财务部 | F7: IT部 | G7: 财务部 | H7: 44712 | K7: 9800 | L7: =2/12 -> 0.16666667 | M7: 0 | N7: =IF(H7=0,"-",EOMONTH(H7,L7*12)) -> 44773 | O7: =IF(AND(H7<DATE(YEAR(主页!$D$9)+1,1,1),OR(下年!I7=0,I7>=DATE(YEAR(主页!$D$9)+1,1,1))),下年!K7,0) -> 0 | P7: =IF(AND(H7>=DATE(YEAR(主页!$D$9),12,31),H7<=DATE(YEAR(主页!$D$9)+1,12,31)),K7,0) -> 9800 | Q7: =IF(AND(I7>=DATE(YEAR(主页!$D$9),12,31),I7<=DATE(YEAR(主页!$D$9)+1,12,31)),K7,0) -> 0 | R7: =IF(AND(H7<DATE(YEAR(主页!$D$9)+2,1,1),OR(下年!I7=0,I7>=DATE(YEAR(主页!$D$9)+2,1,1))),下年!K7,0) -> 9800 | S7: =O7+P7-Q7-R7 -> 0 | T7: =IFERROR(IF(AND(H7<DATE(YEAR(主页!$D$9)+1,1,1),OR(当年!I7=0,I7>=DATE(YEAR(主页!$D$9)+1,1,1))),MIN(K7*(1-M7),K7*(1-M7)/L7/12*DATEDIF(H7,DATE(YEAR(主页!$D$9),12,31),"M")),0),0) -> 0 | U7: =IFERROR(K7*(1-M7)/L7/12*DATEDIF(MAX(H7,DATE(YEAR(主页!$D$9),12,31)),MIN(N7,IF(OR(当年!I7=0,I7>=DATE(YEAR(主页!$D$9)+1,1,1)),DATE(YEAR(主页!$D$9)+1,12,31),I7)),"M"),0) -> 9800 | V7: =IF(AND(I7>=DATE(YEAR(主页!$D$9)-1,12,31),I7<=DATE(YEAR(主页!$D$9),12,31)),T7+U7,0) -> 0 | W7: =IF(AND(H7<DATE(YEAR(主页!$D$9)+2,1,1),OR(当年!I7=0,I7>=DATE(YEAR(主页!$D$9)+2,1,1))),IFERROR(K7*(1-M7)/L7/12*DATEDIF(H7,MIN(N7,IF(OR(当年!I7=0,I7>=DATE(YEAR(主页!$D$9)+1,1,1)),DATE(YEAR(主页!$D$9)+1,12,31),I7)),"M"),0),0) -> 9800 | X7: =T7+U7-V7-W7 -> 0 | Z7: 3 | AA7: 在用 | AB7: =IFERROR(IF(AA7="在用",K7/Z7,0),0) -> 3266.6667
A8: FA007 | B8: 笔记本电脑 | C8: 电子设备 | D8: 支持中心 | E8: 财务部 | F8: IT部 | G8: 财务部 | H8: 44501 | K8: 9800 | L8: =2/12 -> 0.16666667 | M8: 0 | N8: =IF(H8=0,"-",EOMONTH(H8,L8*12)) -> 44592 | O8: =IF(AND(H8<DATE(YEAR(主页!$D$9)+1,1,1),OR(下年!I8=0,I8>=DATE(YEAR(主页!$D$9)+1,1,1))),下年!K8,0) -> 9800 | P8: =IF(AND(H8>=DATE(YEAR(主页!$D$9),12,31),H8<=DATE(YEAR(主页!$D$9)+1,12,31)),K8,0) -> 0 | Q8: =IF(AND(I8>=DATE(YEAR(主页!$D$9),12,31),I8<=DATE(YEAR(主页!$D$9)+1,12,31)),K8,0) -> 0 | R8: =IF(AND(H8<DATE(YEAR(主页!$D$9)+2,1,1),OR(下年!I8=0,I8>=DATE(YEAR(主页!$D$9)+2,1,1))),下年!K8,0) -> 9800 | S8: =O8+P8-Q8-R8 -> 0 | T8: =IFERROR(IF(AND(H8<DATE(YEAR(主页!$D$9)+1,1,1),OR(当年!I8=0,I8>=DATE(YEAR(主页!$D$9)+1,1,1))),MIN(K8*(1-M8),K8*(1-M8)/L8/12*DATEDIF(H8,DATE(YEAR(主页!$D$9),12,31),"M")),0),0) -> 4900 | U8: =IFERROR(K8*(1-M8)/L8/12*DATEDIF(MAX(H8,DATE(YEAR(主页!$D$9),12,31)),MIN(N8,IF(OR(当年!I8=0,I8>=DATE(YEAR(主页!$D$9)+1,1,1)),DATE(YEAR(主页!$D$9)+1,12,31),I8)),"M"),0) -> 4900 | V8: =IF(AND(I8>=DATE(YEAR(主页!$D$9)-1,12,31),I8<=DATE(YEAR(主页!$D$9),12,31)),T8+U8,0) -> 0 | W8: =IF(AND(H8<DATE(YEAR(主页!$D$9)+2,1,1),OR(当年!I8=0,I8>=DATE(YEAR(主页!$D$9)+2,1,1))),IFERROR(K8*(1-M8)/L8/12*DATEDIF(H8,MIN(N8,IF(OR(当年!I8=0,I8>=DATE(YEAR(主页!$D$9)+1,1,1)),DATE(YEAR(主页!$D$9)+1,12,31),I8)),"M"),0),0) -> 9800 | X8: =T8+U8-V8-W8 -> 0 | Z8: 3 | AA8: 在用 | AB8: =IFERROR(IF(AA8="在用",K8/Z8,0),0) -> 3266.6667
A9: FA008 | B9: 笔记本电脑 | C9: 电子设备 | D9: 支持中心 | E9: 财务部 | F9: IT部 | G9: 财务部 | H9: 43831 | K9: 9800 | L9: =2/12 -> 0.16666667 | M9: 0 | N9: =IF(H9=0,"-",EOMONTH(H9,L9*12)) -> 43921 | O9: =IF(AND(H9<DATE(YEAR(主页!$D$9)+1,1,1),OR(下年!I9=0,I9>=DATE(YEAR(主页!$D$9)+1,1,1))),下年!K9,0) -> 9800 | P9: =IF(AND(H9>=DATE(YEAR(主页!$D$9),12,31),H9<=DATE(YEAR(主页!$D$9)+1,12,31)),K9,0) -> 0 | Q9: =IF(AND(I9>=DATE(YEAR(主页!$D$9),12,31),I9<=DATE(YEAR(主页!$D$9)+1,12,31)),K9,0) -> 0 | R9: =IF(AND(H9<DATE(YEAR(主页!$D$9)+2,1,1),OR(下年!I9=0,I9>=DATE(YEAR(主页!$D$9)+2,1,1))),下年!K9,0) -> 9800 | S9: =O9+P9-Q9-R9 -> 0 | T9: =IFERROR(IF(AND(H9<DATE(YEAR(主页!$D$9)+1,1,1),OR(当年!I9=0,I9>=DATE(YEAR(主页!$D$9)+1,1,1))),MIN(K9*(1-M9),K9*(1-M9)/L9/12*DATEDIF(H9,DATE(YEAR(主页!$D$9),12,31),"M")),0),0) -> 9800 | U9: =IFERROR(K9*(1-M9)/L9/12*DATEDIF(MAX(H9,DATE(YEAR(主页!$D$9),12,31)),MIN(N9,IF(OR(当年!I9=0,I9>=DATE(YEAR(主页!$D$9)+1,1,1)),DATE(YEAR(主页!$D$9)+1,12,31),I9)),"M"),0) -> 0 | V9: =IF(AND(I9>=DATE(YEAR(主页!$D$9)-1,12,31),I9<=DATE(YEAR(主页!$D$9),12,31)),T9+U9,0) -> 0 | W9: =IF(AND(H9<DATE(YEAR(主页!$D$9)+2,1,1),OR(当年!I9=0,I9>=DATE(YEAR(主页!$D$9)+2,1,1))),IFERROR(K9*(1-M9)/L9/12*DATEDIF(H9,MIN(N9,IF(OR(当年!I9=0,I9>=DATE(YEAR(主页!$D$9)+1,1,1)),DATE(YEAR(主页!$D$9)+1,12,31),I9)),"M"),0),0) -> 9800 | X9: =T9+U9-V9-W9 -> 0 | Z9: 3 | AA9: 在用 | AB9: =IFERROR(IF(AA9="在用",K9/Z9,0),0) -> 3266.6667
A10: FA009 | B10: 笔记本电脑 | C10: 电子设备 | D10: 支持中心 | E10: 财务部 | F10: IT部 | G10: 财务部 | H10: 43891 | K10: 9800 | L10: =2/12 -> 0.16666667 | M10: 0 | N10: =IF(H10=0,"-",EOMONTH(H10,L10*12)) -> 43982 | O10: =IF(AND(H10<DATE(YEAR(主页!$D$9)+1,1,1),OR(下年!I10=0,I10>=DATE(YEAR(主页!$D$9)+1,1,1))),下年!K10,0) -> 9800 | P10: =IF(AND(H10>=DATE(YEAR(主页!$D$9),12,31),H10<=DATE(YEAR(主页!$D$9)+1,12,31)),K10,0) -> 0 | Q10: =IF(AND(I10>=DATE(YEAR(主页!$D$9),12,31),I10<=DATE(YEAR(主页!$D$9)+1,12,31)),K10,0) -> 0 | R10: =IF(AND(H10<DATE(YEAR(主页!$D$9)+2,1,1),OR(下年!I10=0,I10>=DATE(YEAR(主页!$D$9)+2,1,1))),下年!K10,0) -> 9800 | S10: =O10+P10-Q10-R10 -> 0 | T10: =IFERROR(IF(AND(H10<DATE(YEAR(主页!$D$9)+1,1,1),OR(当年!I10=0,I10>=DATE(YEAR(主页!$D$9)+1,1,1))),MIN(K10*(1-M10),K10*(1-M10)/L10/12*DATEDIF(H10,DATE(YEAR(主页!$D$9),12,31),"M")),0),0) -> 9800 | U10: =IFERROR(K10*(1-M10)/L10/12*DATEDIF(MAX(H10,DATE(YEAR(主页!$D$9),12,31)),MIN(N10,IF(OR(当年!I10=0,I10>=DATE(YEAR(主页!$D$9)+1,1,1)),DATE(YEAR(主页!$D$9)+1,12,31),I10)),"M"),0) -> 0 | V10: =IF(AND(I10>=DATE(YEAR(主页!$D$9)-1,12,31),I10<=DATE(YEAR(主页!$D$9),12,31)),T10+U10,0) -> 0 | W10: =IF(AND(H10<DATE(YEAR(主页!$D$9)+2,1,1),OR(当年!I10=0,I10>=DATE(YEAR(主页!$D$9)+2,1,1))),IFERROR(K10*(1-M10)/L10/12*DATEDIF(H10,MIN(N10,IF(OR(当年!I10=0,I10>=DATE(YEAR(主页!$D$9)+1,1,1)),DATE(YEAR(主页!$D$9)+1,12,31),I10)),"M"),0),0) -> 9800 | X10: =T10+U10-V10-W10 -> 0 | Z10: 3 | AA10: 在用 | AB10: =IFERROR(IF(AA10="在用",K10/Z10,0),0) -> 3266.6667
A11: FA010 | B11: 复印机 | C11: 电子设备 | D11: 支持中心 | E11: 行政部 | F11: IT部 | G11: 行政部 | H11: 44267 | K11: 23000 | L11: =2/12 -> 0.16666667 | M11: 0 | N11: =IF(H11=0,"-",EOMONTH(H11,L11*12)) -> 44347 | O11: =IF(AND(H11<DATE(YEAR(主页!$D$9)+1,1,1),OR(下年!I11=0,I11>=DATE(YEAR(主页!$D$9)+1,1,1))),下年!K11,0) -> 23000 | P11: =IF(AND(H11>=DATE(YEAR(主页!$D$9),12,31),H11<=DATE(YEAR(主页!$D$9)+1,12,31)),K11,0) -> 0 | Q11: =IF(AND(I11>=DATE(YEAR(主页!$D$9),12,31),I11<=DATE(YEAR(主页!$D$9)+1,12,31)),K11,0) -> 0 | R11: =IF(AND(H11<DATE(YEAR(主页!$D$9)+2,1,1),OR(下年!I11=0,I11>=DATE(YEAR(主页!$D$9)+2,1,1))),下年!K11,0) -> 23000 | S11: =O11+P11-Q11-R11 -> 0 | T11: =IFERROR(IF(AND(H11<DATE(YEAR(主页!$D$9)+1,1,1),OR(当年!I11=0,I11>=DATE(YEAR(主页!$D$9)+1,1,1))),MIN(K11*(1-M11),K11*(1-M11)/L11/12*DATEDIF(H11,DATE(YEAR(主页!$D$9),12,31),"M")),0),0) -> 23000 | U11: =IFERROR(K11*(1-M11)/L11/12*DATEDIF(MAX(H11,DATE(YEAR(主页!$D$9),12,31)),MIN(N11,IF(OR(当年!I11=0,I11>=DATE(YEAR(主页!$D$9)+1,1,1)),DATE(YEAR(主页!$D$9)+1,12,31),I11)),"M"),0) -> 0 | V11: =IF(AND(I11>=DATE(YEAR(主页!$D$9)-1,12,31),I11<=DATE(YEAR(主页!$D$9),12,31)),T11+U11,0) -> 0 | W11: =IF(AND(H11<DATE(YEAR(主页!$D$9)+2,1,1),OR(当年!I11=0,I11>=DATE(YEAR(主页!$D$9)+2,1,1))),IFERROR(K11*(1-M11)/L11/12*DATEDIF(H11,MIN(N11,IF(OR(当年!I11=0,I11>=DATE(YEAR(主页!$D$9)+1,1,1)),DATE(YEAR(主页!$D$9)+1,12,31),I11)),"M"),0),0) -> 23000 | X11: =T11+U11-V11-W11 -> 0 | Z11: 3 | AA11: 在用 | AB11: =IFERROR(IF(AA11="在用",K11/Z11,0),0) -> 7666.6667

Sheet 预算校准
B4: 金额单位：万元 | E4: ="实际"&YEAR(主页!$D$9)-1 -> 实际2020 | G4: ="估计"&YEAR(主页!$D$9) -> 估计2021 | I4: ="预算"&YEAR(主页!$D$9)+1 -> 预算2022
B5: 固定资产原值
C6: 年初 | E6: =SUM(上年!$O:$O)/10000 -> 1270 | G6: =SUM(当年!$O:$O)/10000 -> 1236.96 | H6: =E9-G6 -> 0 | I6: =SUM(下年!$O:$O)/10000 -> 4710.24 | J6: =G9-I6 -> 0
C7: 增加 | E7: =SUM(上年!$P:$P)/10000 -> 1.96 | G7: =SUM(当年!$P:$P)/10000 -> 3503.28 | I7: =SUM(下年!$P:$P)/10000 -> 0.98
C8: 减少 | E8: =SUM(上年!$Q:$Q)/10000 -> 35 | G8: =SUM(当年!$Q:$Q)/10000 -> 30 | I8: =SUM(下年!$Q:$Q)/10000 -> 5
C9: 年末 | E9: =SUM(上年!$R:$R)/10000 -> 1236.96 | G9: =SUM(当年!$R:$R)/10000 -> 4710.24 | I9: =SUM(下年!$R:$R)/10000 -> 4706.22
C10: 校验 | E10: =E6+E7-E8-E9 -> 0 | G10: =G6+G7-G8-G9 -> 0 | H10: =I6+I7-I8-I9 -> 0
B11: 累计折旧
C12: 年初 | E12: =SUM(上年!$T:$T)/10000 -> 170.64375 | G12: =SUM(当年!$T:$T)/10000 -> 268.6725 | H12: =E15-G12 -> 0 | I12: =SUM(下年!$T:$T)/10000 -> 453.625 | J12: =G15-I12 -> 0
C13: 增加 | E13: =SUM(上年!$U:$U)/10000 -> 122.135 | G13: =SUM(当年!$U:$U)/10000 -> 202.765 | I13: =SUM(下年!$U:$U)/10000 -> 281.72
C14: 减少 | E14: =SUM(上年!$V:$V)/10000 -> 24.10625 | G14: =SUM(当年!$V:$V)/10000 -> 17.8125 | I14: =SUM(下年!$V:$V)/10000 -> 0
C15: 年末 | E15: =SUM(上年!$W:$W)/10000 -> 268.6725 | G15: =SUM(当年!$W:$W)/10000 -> 453.625 | I15: =SUM(下年!$W:$W)/10000 -> 735.345
C16: 校验 | E16: =E12+E13-E14-E15 -> 0 | G16: =G12+G13-G14-G15 -> 0 | I16: =I12+I13-I14-I15 -> 0
B17: 技术折旧 | E17: =SUM(上年!$AB:$AB)/10000 -> 302 | G17: =SUM(当年!$AB:$AB)/10000 -> 304.07333 | I17: =SUM(下年!$AB:$AB)/10000 -> 304.07333
B18: 其中： | C18: 生产车间 | E18: =SUMIFS(上年!$AB:$AB,上年!$G:$G,$C18)/10000 -> 302 | G18: =SUMIFS(当年!$AB:$AB,当年!$G:$G,$C18)/10000 -> 302 | I18: =SUMIFS(下年!$AB:$AB,下年!$G:$G,$C18)/10000 -> 302
C19: 财务部 | E19: =SUMIFS(上年!$AB:$AB,上年!$G:$G,$C19)/10000 -> 0 | G19: =SUMIFS(当年!$AB:$AB,当年!$G:$G,$C19)/10000 -> 1.3066667 | I19: =SUMIFS(下年!$AB:$AB,下年!$G:$G,$C19)/10000 -> 1.3066667
C20: 行政部 | E20: =SUMIFS(上年!$AB:$AB,上年!$G:$G,$C20)/10000 -> 0 | G20: =SUMIFS(当年!$AB:$AB,当年!$G:$G,$C20)/10000 -> 0.76666667 | I20: =SUMIFS(下年!$AB:$AB,下年!$G:$G,$C20)/10000 -> 0.76666667

Sheet 财务折旧
G1: ="实际"&YEAR(主页!$D$9)-1&"全年" -> 实际2020全年 | I1: ="实际"&"截止"&YEAR(主页!$D$9)-1&"年"&MONTH(主页!$D$9)&"月" -> 实际截止2020年10月 | K1: ="估计"&"从"&YEAR(主页!$D$9)-1&"年"&MONTH(主页!$D$9)+1&"月到年底" -> 估计从2020年11月到年底 | M1: ="估计"&YEAR(主页!$D$9)&"全年" -> 估计2021全年 | O1: ="预算"&YEAR(主页!$D$9)+1&"全年" -> 预算2022全年
G2: ="A"&YEAR(主页!$D$9)-1&"FY" -> A2020FY | I2: ="A"&YEAR(主页!$D$9)&TEXT(MONTH(主页!$D$9),"00")&"YTD" -> A202110YTD | K2: ="E"&YEAR(主页!$D$9)&TEXT(MONTH(主页!$D$9),"00")&"YTG" -> E202110YTG | M2: ="E"&YEAR(主页!$D$9)&"FY" -> E2021FY | O2: ="B"&YEAR(主页!$D$9)+1&"FY" -> B2022FY
G3: 金额 | I3: 金额 | K3: 金额 | M3: 金额 | O3: 金额
B4: 合计 | E4: * | F4: * | G4: =SUMIFS(上年!$U:$U,上年!$D:$D,$E4,上年!$E:$E,$F4)/10000 -> 122.135 | I4: =SUMIFS(当年!AD:AD,当年!$D:$D,$E4,当年!$E:$E,$F4)/10000 -> 155.09167 | K4: =SUMIFS(当年!AE:AE,当年!$D:$D,$E4,当年!$E:$E,$F4)/10000 -> 47.673333 | M4: =SUMIFS(当年!$U:$U,当年!$D:$D,$E4,当年!$E:$E,$F4)/10000 -> 202.765 | O4: =SUMIFS(下年!$U:$U,下年!$D:$D,$E4,下年!$E:$E,$F4)/10000 -> 281.72
C5: 流程中心 | E5: =IF(C5<>"",C5,E4) -> 流程中心 | F5: =IF(D5<>"",D5,"*") -> * | G5: =SUMIFS(上年!$U:$U,上年!$D:$D,$E5,上年!$E:$E,$F5)/10000 -> 120.175 | I5: =SUMIFS(当年!AD:AD,当年!$D:$D,$E5,当年!$E:$E,$F5)/10000 -> 152.79167 | K5: =SUMIFS(当年!AE:AE,当年!$D:$D,$E5,当年!$E:$E,$F5)/10000 -> 47.183333 | M5: =SUMIFS(当年!$U:$U,当年!$D:$D,$E5,当年!$E:$E,$F5)/10000 -> 199.975 | O5: =SUMIFS(下年!$U:$U,下年!$D:$D,$E5,下年!$E:$E,$F5)/10000 -> 280.25
D6: 销售中心 | E6: =IF(C6<>"",C6,E5) -> 流程中心 | F6: =IF(D6<>"",D6,"*") -> 销售中心 | G6: =SUMIFS(上年!$U:$U,上年!$D:$D,$E6,上年!$E:$E,$F6)/10000 -> 0 | I6: =SUMIFS(当年!AD:AD,当年!$D:$D,$E6,当年!$E:$E,$F6)/10000 -> 0 | K6: =SUMIFS(当年!AE:AE,当年!$D:$D,$E6,当年!$E:$E,$F6)/10000 -> 0 | M6: =SUMIFS(当年!$U:$U,当年!$D:$D,$E6,当年!$E:$E,$F6)/10000 -> 0 | O6: =SUMIFS(下年!$U:$U,下年!$D:$D,$E6,下年!$E:$E,$F6)/10000 -> 0
D7: 制造中心 | E7: =IF(C7<>"",C7,E6) -> 流程中心 | F7: =IF(D7<>"",D7,"*") -> 制造中心 | G7: =SUMIFS(上年!$U:$U,上年!$D:$D,$E7,上年!$E:$E,$F7)/10000 -> 120.175 | I7: =SUMIFS(当年!AD:AD,当年!$D:$D,$E7,当年!$E:$E,$F7)/10000 -> 152.79167 | K7: =SUMIFS(当年!AE:AE,当年!$D:$D,$E7,当年!$E:$E,$F7)/10000 -> 47.183333 | M7: =SUMIFS(当年!$U:$U,当年!$D:$D,$E7,当年!$E:$E,$F7)/10000 -> 199.975 | O7: =SUMIFS(下年!$U:$U,下年!$D:$D,$E7,下年!$E:$E,$F7)/10000 -> 280.25
C8: 改善中心 | E8: =IF(C8<>"",C8,E7) -> 改善中心 | F8: =IF(D8<>"",D8,"*") -> * | G8: =SUMIFS(上年!$U:$U,上年!$D:$D,$E8,上年!$E:$E,$F8)/10000 -> 0 | I8: =SUMIFS(当年!AD:AD,当年!$D:$D,$E8,当年!$E:$E,$F8)/10000 -> 0 | K8: =SUMIFS(当年!AE:AE,当年!$D:$D,$E8,当年!$E:$E,$F8)/10000 -> 0 | M8: =SUMIFS(当年!$U:$U,当年!$D:$D,$E8,当年!$E:$E,$F8)/10000 -> 0 | O8: =SUMIFS(下年!$U:$U,下年!$D:$D,$E8,下年!$E:$E,$F8)/10000 -> 0
C9: =C8 -> 改善中心 | D9: 流程优化项目小组 | E9: =IF(C9<>"",C9,E8) -> 改善中心 | F9: =IF(D9<>"",D9,"*") -> 流程优化项目小组 | G9: =SUMIFS(上年!$U:$U,上年!$D:$D,$E9,上年!$E:$E,$F9)/10000 -> 0 | I9: =SUMIFS(当年!AD:AD,当年!$D:$D,$E9,当年!$E:$E,$F9)/10000 -> 0 | K9: =SUMIFS(当年!AE:AE,当年!$D:$D,$E9,当年!$E:$E,$F9)/10000 -> 0 | M9: =SUMIFS(当年!$U:$U,当年!$D:$D,$E9,当年!$E:$E,$F9)/10000 -> 0 | O9: =SUMIFS(下年!$U:$U,下年!$D:$D,$E9,下年!$E:$E,$F9)/10000 -> 0
C10: =C9 -> 改善中心 | D10: 战略预算项目小组 | E10: =IF(C10<>"",C10,E9) -> 改善中心 | F10: =IF(D10<>"",D10,"*") -> 战略预算项目小组 | G10: =SUMIFS(上年!$U:$U,上年!$D:$D,$E10,上年!$E:$E,$F10)/10000 -> 0 | I10: =SUMIFS(当年!AD:AD,当年!$D:$D,$E10,当年!$E:$E,$F10)/10000 -> 0 | K10: =SUMIFS(当年!AE:AE,当年!$D:$D,$E10,当年!$E:$E,$F10)/10000 -> 0 | M10: =SUMIFS(当年!$U:$U,当年!$D:$D,$E10,当年!$E:$E,$F10)/10000 -> 0 | O10: =SUMIFS(下年!$U:$U,下年!$D:$D,$E10,下年!$E:$E,$F10)/10000 -> 0
C11: 创新中心 | E11: =IF(C11<>"",C11,E10) -> 创新中心 | F11: =IF(D11<>"",D11,"*") -> * | G11: =SUMIFS(上年!$U:$U,上年!$D:$D,$E11,上年!$E:$E,$F11)/10000 -> 0 | I11: =SUMIFS(当年!AD:AD,当年!$D:$D,$E11,当年!$E:$E,$F11)/10000 -> 0 | K11: =SUMIFS(当年!AE:AE,当年!$D:$D,$E11,当年!$E:$E,$F11)/10000 -> 0 | M11: =SUMIFS(当年!$U:$U,当年!$D:$D,$E11,当年!$E:$E,$F11)/10000 -> 0 | O11: =SUMIFS(下年!$U:$U,下年!$D:$D,$E11,下年!$E:$E,$F11)/10000 -> 0
C12: =C11 -> 创新中心 | D12: 产品研发部 | E12: =IF(C12<>"",C12,E11) -> 创新中心 | F12: =IF(D12<>"",D12,"*") -> 产品研发部 | G12: =SUMIFS(上年!$U:$U,上年!$D:$D,$E12,上年!$E:$E,$F12)/10000 -> 0 | I12: =SUMIFS(当年!AD:AD,当年!$D:$D,$E12,当年!$E:$E,$F12)/10000 -> 0 | K12: =SUMIFS(当年!AE:AE,当年!$D:$D,$E12,当年!$E:$E,$F12)/10000 -> 0 | M12: =SUMIFS(当年!$U:$U,当年!$D:$D,$E12,当年!$E:$E,$F12)/10000 -> 0 | O12: =SUMIFS(下年!$U:$U,下年!$D:$D,$E12,下年!$E:$E,$F12)/10000 -> 0
C13: =C12 -> 创新中心 | D13: XX试验室 | E13: =IF(C13<>"",C13,E12) -> 创新中心 | F13: =IF(D13<>"",D13,"*") -> XX试验室 | G13: =SUMIFS(上年!$U:$U,上年!$D:$D,$E13,上年!$E:$E,$F13)/10000 -> 0 | I13: =SUMIFS(当年!AD:AD,当年!$D:$D,$E13,当年!$E:$E,$F13)/10000 -> 0 | K13: =SUMIFS(当年!AE:AE,当年!$D:$D,$E13,当年!$E:$E,$F13)/10000 -> 0 | M13: =SUMIFS(当年!$U:$U,当年!$D:$D,$E13,当年!$E:$E,$F13)/10000 -> 0 | O13: =SUMIFS(下年!$U:$U,下年!$D:$D,$E13,下年!$E:$E,$F13)/10000 -> 0
C14: =C13 -> 创新中心 | D14: XX孵化业务 | E14: =IF(C14<>"",C14,E13) -> 创新中心 | F14: =IF(D14<>"",D14,"*") -> XX孵化业务 | G14: =SUMIFS(上年!$U:$U,上年!$D:$D,$E14,上年!$E:$E,$F14)/10000 -> 0 | I14: =SUMIFS(当年!AD:AD,当年!$D:$D,$E14,当年!$E:$E,$F14)/10000 -> 0 | K14: =SUMIFS(当年!AE:AE,当年!$D:$D,$E14,当年!$E:$E,$F14)/10000 -> 0 | M14: =SUMIFS(当年!$U:$U,当年!$D:$D,$E14,当年!$E:$E,$F14)/10000 -> 0 | O14: =SUMIFS(下年!$U:$U,下年!$D:$D,$E14,下年!$E:$E,$F14)/10000 -> 0
C15: 支持中心 | E15: =IF(C15<>"",C15,E14) -> 支持中心 | F15: =IF(D15<>"",D15,"*") -> * | G15: =SUMIFS(上年!$U:$U,上年!$D:$D,$E15,上年!$E:$E,$F15)/10000 -> 1.96 | I15: =SUMIFS(当年!AD:AD,当年!$D:$D,$E15,当年!$E:$E,$F15)/10000 -> 2.3 | K15: =SUMIFS(当年!AE:AE,当年!$D:$D,$E15,当年!$E:$E,$F15)/10000 -> 0.49 | M15: =SUMIFS(当年!$U:$U,当年!$D:$D,$E15,当年!$E:$E,$F15)/10000 -> 2.79 | O15: =SUMIFS(下年!$U:$U,下年!$D:$D,$E15,下年!$E:$E,$F15)/10000 -> 1.47
C16: =C15 -> 支持中心 | D16: 财务部 | E16: =IF(C16<>"",C16,E15) -> 支持中心 | F16: =IF(D16<>"",D16,"*") -> 财务部 | G16: =SUMIFS(上年!$U:$U,上年!$D:$D,$E16,上年!$E:$E,$F16)/10000 -> 1.96 | I16: =SUMIFS(当年!AD:AD,当年!$D:$D,$E16,当年!$E:$E,$F16)/10000 -> 0 | K16: =SUMIFS(当年!AE:AE,当年!$D:$D,$E16,当年!$E:$E,$F16)/10000 -> 0.49 | M16: =SUMIFS(当年!$U:$U,当年!$D:$D,$E16,当年!$E:$E,$F16)/10000 -> 0.49 | O16: =SUMIFS(下年!$U:$U,下年!$D:$D,$E16,下年!$E:$E,$F16)/10000 -> 1.47
C17: =C16 -> 支持中心 | D17: 人力资源部 | E17: =IF(C17<>"",C17,E16) -> 支持中心 | F17: =IF(D17<>"",D17,"*") -> 人力资源部 | G17: =SUMIFS(上年!$U:$U,上年!$D:$D,$E17,上年!$E:$E,$F17)/10000 -> 0 | I17: =SUMIFS(当年!AD:AD,当年!$D:$D,$E17,当年!$E:$E,$F17)/10000 -> 0 | K17: =SUMIFS(当年!AE:AE,当年!$D:$D,$E17,当年!$E:$E,$F17)/10000 -> 0 | M17: =SUMIFS(当年!$U:$U,当年!$D:$D,$E17,当年!$E:$E,$F17)/10000 -> 0 | O17: =SUMIFS(下年!$U:$U,下年!$D:$D,$E17,下年!$E:$E,$F17)/10000 -> 0
C18: =C17 -> 支持中心 | D18: IT部 | E18: =IF(C18<>"",C18,E17) -> 支持中心 | F18: =IF(D18<>"",D18,"*") -> IT部 | G18: =SUMIFS(上年!$U:$U,上年!$D:$D,$E18,上年!$E:$E,$F18)/10000 -> 0 | I18: =SUMIFS(当年!AD:AD,当年!$D:$D,$E18,当年!$E:$E,$F18)/10000 -> 0 | K18: =SUMIFS(当年!AE:AE,当年!$D:$D,$E18,当年!$E:$E,$F18)/10000 -> 0 | M18: =SUMIFS(当年!$U:$U,当年!$D:$D,$E18,当年!$E:$E,$F18)/10000 -> 0 | O18: =SUMIFS(下年!$U:$U,下年!$D:$D,$E18,下年!$E:$E,$F18)/10000 -> 0
C19: =C18 -> 支持中心 | D19: 行政部 | E19: =IF(C19<>"",C19,E18) -> 支持中心 | F19: =IF(D19<>"",D19,"*") -> 行政部 | G19: =SUMIFS(上年!$U:$U,上年!$D:$D,$E19,上年!$E:$E,$F19)/10000 -> 0 | I19: =SUMIFS(当年!AD:AD,当年!$D:$D,$E19,当年!$E:$E,$F19)/10000 -> 2.3 | K19: =SUMIFS(当年!AE:AE,当年!$D:$D,$E19,当年!$E:$E,$F19)/10000 -> 0 | M19: =SUMIFS(当年!$U:$U,当年!$D:$D,$E19,当年!$E:$E,$F19)/10000 -> 2.3 | O19: =SUMIFS(下年!$U:$U,下年!$D:$D,$E19,下年!$E:$E,$F19)/10000 -> 0

Sheet 财务折旧年限
B3: 房屋、建筑物 | C3: 20年
B4: 飞机、火车、轮船、机器、机械和其他生产设备， | C4: 10年
B5: 与生产经营活动有关的器具、工具、家具等 | C5: 5年
B6: 飞机、火车、轮船以外的运输工具 | C6: 4年
B7: 电子设备 | C7: 3年
B10: 不得计算折旧扣除的固定资产 （1）房屋、建筑物以外未投入使用的固定资产； （2）以经营租赁方式租入的固定资产； （3）以融资租赁方式租出的固定资产； （4）已足额提取折旧仍继续使用的固定资产； （5）与经营活动无关的固定资产； （6）单独估价作为固定资产入账的土地； （7）其他不得计算折旧扣除的固定资产。
B11: 固定资产折旧的计提方法 1. 企业应当自固定资产投入使用月份的次月起计算折旧；停止使用的固定资产，应当自停止使用月份的次月起停止计算折旧。 2. 企业应当根据固定资产的性质和使用情况，合理确定固定资产的预计净残值。固定资产的预计净残值一经确定，不得变更。 3. 固定资产按照 直线法 计算的折旧，准予扣除。年折旧率 = （1- 预计净残值率）÷预计使用年限
B12: 加速折旧政策 ➤适用于全体行业 1. 根据《中华人民共和国企业所得税法》第三十二条规定，企业的固定资产由于技术进步等原因，确需加速折旧的，可以缩短折旧年限或者采取加速折旧的方法。 2.《中华人民共和国企业所得税法实施条例》 第九十八条规定，企业所得税法第三十二条所称可以采取缩短折旧年限或者采取加速折旧的方法的固定资产，包括： （一） 由于技术进步，产品更新换代较快的固定资产； （二） 常年处于强震动、高腐蚀状态的固定资产。 采取缩短折旧年限方法的，最低折旧年限不得低于本条例第六十条规定折旧年限的60%；采取加速折旧方法的，可以采取双倍余额递减法或者年数总和法。 ➤适用于特定行业 1.《财政部 国家税务总局关于进一步鼓励软件产业和集成电路产业发展企业所得税政策的通知》（财税〔2012〕27号），企业外购的软件，凡符合固定资产或无形资产进行核实，其折旧或摊销年限可以适当缩短，最短可为2年（含）；集成电路生产企业的生产设备，其折旧年限可以适当缩短，最短可为3年（含）。 2.《财政部 国家税务总局关于完善固定资产加速折旧企业所得税政策的通知》(财税〔2014〕75号)、《国家税务总局关于固定资产加速折旧税收政策有关问题的公告》（国家税务总局公告〔2014〕64号），对生物药品制造业，专用设备制造业，铁路、船舶、航空航天和其他运输设备制造业，计算机、通信和其他电子设备制造业，仪器仪表制造业，信息传输、软件和信息技术服务业等行业企业，2014年1月1日后购进的固定资产（包括自行建造），允许按不低于企业所得税法规定折旧年限的60%缩短折旧年限，或选择采取双倍余额递减法或年数总和法进行加速折旧。 3.《财政部 国家税务总局关于进一步完善固定资产加速折旧企业所得税政策的通知》（财税〔2015〕106号）、《国家税务总局关于进一步完善固定资产加速折旧企业所得税政策有关问题的公告》（国家税务总局公告〔2015〕68号），对轻工、纺织、机械、汽车等四个领域重点行业的企业2015年1月1日后新购进的固定资产（包括自行建造），可由企业选择缩短折旧年限或采取加速折旧的方法，对上述行业的小型微利企业2015年1月1日后新购进的研发和生产经营共用的仪器、设备，单位价值不超过100万元的，允许一次性计入当期成本费用在计算应纳税所得额时扣除，不再分年度计算折旧；单位价值超过100万元的，可由企业选择缩短折旧年限或采取加速折旧的方法。 这里需要注意的是，《财政部 税务总局关于扩大固定资产加速折旧优惠政策适用范围的公告》（财政部 税务总局公告2019年第66号）规定，2019年1月1日起，上述两项规定固定资产加速折旧优惠的行业范围，扩大至全部制造业领域。
B14: 一次性扣除政策 ➤不超过5000元的固定资产 根据《国家税务总局关于固定资产加速折旧税收政策有关问题的公告》（国家税务总局公告〕2014〕64号）规定，2014年1月1日起，对所有行业企业持有的单位价值不超过5000元的固定资产，允许一次性计入当期成本费用在计算应纳税所得额时扣除，不再分年度计算折旧。 ➤单位价值不超过100万元的研发仪器、设备 根据《国家税务总局关于固定资产加速折旧税收政策有关问题的公告》（国家税务总局公告〔2014〕64号）规定，对所有行业企业2014年1月1日后新购进的专门用于研发的仪器、设备，单位价值不超过100万元的，允许一次性计入当期成本费用在计算应纳税所得额时扣除，不再分年度计算折旧；单位价值超过100万元的，可缩短折旧年限或采取加速折旧的方法。 ➤单位价值不超过500万元的固定资产（房屋、建筑物除外） 根据《财政部 税务总局关于设备 器具扣除有关企业所得税政策的通知》（财税〔2018〕54号）、《国家税务总局关于设备 器具扣除有关企业所得税政策执行问题的公告》（国家税务总局公告2018年第46号）规定，企业在2018年1月1日至2020年12月31日期间新购进的设备、器具（所称设备、器具，是指除房屋、建筑物以外的固定资产），单位价值不超过500万元的，允许一次性计入当期成本费用在计算应纳税所得额时扣除，不再分年度计算折旧；单位价值超过500万元的，仍按企业所得税法实施条例、《财政部 国家税务总局关于完善固定资产加速折旧企业所得税政策的通知》（财税〔2014〕75号）、《财政部 国家税务总局关于进一步完善固定资产加速折旧企业所得税政策的通知》（财税〔2015〕106号）等相关规定执行。 注意：根据《财政部 税务总局关于支持新型冠状病毒感染的肺炎疫情防控有关税收政策的公告》（财政部 税务总局公告2020年第8号）规定，对疫情防控重点保障物资生产企业为扩大产能新购置的相关设备，允许一次性计入当期成本费用在企业所得税税前扣除，该政策根据《财政部 税务总局关于支持疫情防控保供等税费政策实施期限的公告》（财政部 税务总局公告2020年第28号）执行至2020年12月31日。
B16: 固定资产折旧差异的处理 1. 计税基础差异 企业按会计规定提取的固定资产减值准备，不得税前扣除，其折旧仍按税法规定的固定资产计税基础计算扣除。 2.折旧年限差异 企业固定资产会计折旧年限如果短于税法规定的最低折旧年限，其按会计折旧年限计提的折旧高于按税法规定的最低折旧年限计提的折旧部分，应调增当期应纳税所得额。 企业固定资产会计折旧年限如果长于税法规定的最低年限，其折旧应按会计折旧年限扣除，税法另有规定的除外。 3. 加速折旧差异 企业按税法规定实行加速折旧的，其按加速折旧办法计算的折旧额可全额在税前扣除。企业实施加速折旧但不符合税法规定条件的，按照税法规定的折旧方法计算扣除。 固定资产改扩建的税务处理 1. 未提足折旧推倒重置的——净值并入重置后固定资产的计税成本。 举例：原固定资产净值 20 万元，推倒重置支出 80 万元，重置后该资产计税成本为 100 万元。 2. 未提足折旧提升功能增加面积的——改扩建支出并入固定资产的计税基础，折旧年限按照税法规定的折旧年限与尚可使用年限 孰短 的标准重新确定。 3.已提足折旧的，按照长期待摊费用，在规定的年限内摊销。
