Workbook

Sheet 主页
B2: 预算编制年度实际数据截止月份 | D2: 44499
B4: 编制说明：
B5: 表格中黄色单元格中设有公式，可自动运算，不需要直接填写数据。如果数据行数超过表格预先留的行数，请注意复制每行的相应公式。
B7: 编制步骤：
B8: 步骤1：填写上年标准成本、上年的销售明细。 上年数据将用作分析当年数据的比较基数。
C9: 填写上年标准成本
C10: 注意事项：
C11: 在每份表格的同一个年度里，统一选择一套单位成本作为标准成本，进行销售成本的计算，以保证不同维度之间毛利数据的可比性。兼顾单位成本数据与实际成本水平的接近程度和数据的可得性，可以选择当年或最近一个月或最近一个季度的平均实际成本、或者标准成本。
C12: 填写上年实际销售明细数据
B14: 步骤2：填写当年标准成本、当年截止至最后一个结账月份的销售明细。 当年的实际数据加上当年剩余月份的估计数据，将用做分析下年预算数据的对比基数。
C15: 填写当年标准成本
C16: 填写当年实际
C17: 注意事项：
C18: 尽量详细到各个维度最末一级，如每个产品、每个客户、每份单据。因为进行数据汇总会比进行数据拆解容易得多。
B20: 步骤3：分别按渠道、业务员、客户、产品等维度估计当年剩余月份的销售数据
C21: 填写当年剩余月份估计数（ 渠道）
C22: 填写当年剩余月份估计数（部门 业务员）
C23: 填写当年剩余月份估计数（客户）
C24: 填写当年剩余月份估计数（ 产品）
B26: 步骤4：分别按渠道、业务员、客户、产品等维度填写下年的预算销售数据
C27: 填写下年预算销售数据（ 渠道）
C28: 填写下年预算销售数据（业务员）
C29: 填写下年预算销售数据（ 客户）
C30: 填写下年预算销售数据（产品）
C31: 填写下年预算分月销售额
B33: 步骤5：将分解到渠道、部门及业务员、客户、产品等各个维度的当年估计数和下年预算数与目标数进行核对、校准，对数据进行必要调整
C34: 查看并预算校准表格
B36: 步骤6：对下年预算、当年估计、上年实际进行对比分析，确认价格、毛利变化的合理性
C37: 查看并核对销售对比分析底稿
C38: 注意事项：注意确认表格中是否已经涵盖到了上年、当年、预算中涉及的所有产品，表格中公式完整
C39: 查看产品销售及毛利影响因素分析

Sheet 上年标准成本
A1: 产品大类 | B1: 产品子类 | C1: 产品名称 | D1: 产品来源 | E1: 外购价格 | F1: 材料成本 | G1: 外协加工费 | H1: 人工及制造费用 | I1: 单位成本 | K1: 返回主页
A2: PA | B2: PA01 | C2: A0111 | D2: 外购 | E2: 13 | I2: =SUM(E2:H2) -> 13
A3: PB | B3: PB01 | C3: B0122 | D3: 自制 | F3: 10 | G3: 1 | H3: 2 | I3: =SUM(E3:H3) -> 13
A4: PC | B4: PC01 | C4: C0122 | D4: 自制 | F4: 5 | G4: 1 | H4: 3 | I4: =SUM(E4:H4) -> 9
A5: PA | B5: PA01 | C5: A0111 | D5: 自制 | F5: 9 | G5: 2 | H5: 3 | I5: =SUM(E5:H5) -> 14
A6: PB | B6: PB01 | C6: B0122 | D6: 自制 | F6: 9 | H6: 5 | I6: =SUM(E6:H6) -> 14
A7: PC | B7: PC01 | C7: C0122 | D7: 自制 | F7: 4 | G7: 2 | H7: 1 | I7: =SUM(E7:H7) -> 7
A8: SE | B8: SE99 | C8: C0199 | D8: 服务 | F8: 80 | G8: 30 | H8: 10 | I8: =SUM(E8:H8) -> 120

Sheet 上年实际
A1: 订单日期 | B1: 订单号 | C1: 交付日期 | D1: 客户大类 | E1: 客户子类 | F1: 客户名称 | G1: 渠道分类 | H1: 渠道名称 | I1: 销售部门 | J1: 业务员 | K1: 产品名称 | L1: 产品大类 | M1: 产品子类 | N1: 产品来源 | O1: 销售数量 | P1: 不含税销售收入 | Q1: 增值税率 | R1: 不含税销售单价 | S1: 含税单价 | T1: 单位标准成本 | U1: 销售成本 | V1: 销售毛利 | W1: 毛利率 | X1: 毛利占比% | Z1: 返回主页
A2: 44211 | B2: SO0001 | C2: 43861 | D2: CA | E2: CA01 | F2: 天猫 | G2: SCA | H2: SCA01 | I2: DA | J2: 张三 | K2: A0111 | L2: PA | M2: PA01 | N2: 外购 | O2: 98 | P2: 1500 | Q2: 0.13 | R2: =IFERROR(P2/O2,"") -> 15.306122 | S2: =IFERROR(R2*(1+Q2),"") -> 17.295918 | T2: =IFERROR(INDEX(上年标准成本!$I:$I,MATCH(K2,上年标准成本!$C:$C,0),1),"") -> 13 | U2: =IFERROR(O2*T2,"") -> 1274 | V2: =IFERROR(P2-U2,"") -> 226 | W2: =IFERROR(V2/P2,"") -> 0.15066667 | X2: =IFERROR(IF(W2/SUM(W:W)=0,"",W2/SUM(W:W)),"") -> 0.16231745
A3: 44286 | B3: SO0002 | C3: 43951 | D3: CB | E3: CB01 | F3: 苏宁 | G3: SCB | H3: SCB01 | I3: DB | J3: 李四 | K3: B0122 | L3: PB | M3: PB01 | N3: 自制 | O3: 121 | P3: 1980 | Q3: 0.13 | R3: =IFERROR(P3/O3,"") -> 16.363636 | S3: =IFERROR(R3*(1+Q3),"") -> 18.490909 | T3: =IFERROR(INDEX(上年标准成本!$I:$I,MATCH(K3,上年标准成本!$C:$C,0),1),"") -> 13 | U3: =IFERROR(O3*T3,"") -> 1573 | V3: =IFERROR(P3-U3,"") -> 407 | W3: =IFERROR(V3/P3,"") -> 0.20555556 | X3: =IFERROR(IF(W3/SUM(W:W)=0,"",W3/SUM(W:W)),"") -> 0.2214508
A4: 44345 | B4: SO0003 | C4: 43981 | D4: CC | E4: CC01 | F4: 京东 | G4: SCC | H4: SCC01 | I4: DC | J4: 王二麻子 | K4: C0122 | L4: PC | M4: PC01 | N4: 自制 | O4: 88 | P4: 1000 | Q4: 0.13 | R4: =IFERROR(P4/O4,"") -> 11.363636 | S4: =IFERROR(R4*(1+Q4),"") -> 12.840909 | T4: =IFERROR(INDEX(上年标准成本!$I:$I,MATCH(K4,上年标准成本!$C:$C,0),1),"") -> 9 | U4: =IFERROR(O4*T4,"") -> 792 | V4: =IFERROR(P4-U4,"") -> 208 | W4: =IFERROR(V4/P4,"") -> 0.208 | X4: =IFERROR(IF(W4/SUM(W:W)=0,"",W4/SUM(W:W)),"") -> 0.22408427
A5: 44345 | B5: SO0003 | C5: 43981 | D5: CC | E5: CC01 | F5: 苏宁 | G5: SCC | H5: SCC01 | I5: DC | J5: 王二麻子 | K5: C0199 | L5: SE | M5: SE99 | N5: 服务 | O5: 3 | P5: 566.03774 | Q5: 0.06 | R5: =IFERROR(P5/O5,"") -> 188.67925 | S5: =IFERROR(R5*(1+Q5),"") -> 200 | T5: =IFERROR(INDEX(上年标准成本!$I:$I,MATCH(K5,上年标准成本!$C:$C,0),1),"") -> 120 | U5: =IFERROR(O5*T5,"") -> 360 | V5: =IFERROR(P5-U5,"") -> 206.03774 | W5: =IFERROR(V5/P5,"") -> 0.364 | X5: =IFERROR(IF(W5/SUM(W:W)=0,"",W5/SUM(W:W)),"") -> 0.39214747
R6: =IFERROR(P6/O6,"") | S6: =IFERROR(R6*(1+Q6),"") | T6: =IFERROR(INDEX(上年标准成本!$I:$I,MATCH(K6,上年标准成本!$C:$C,0),1),"") | U6: =IFERROR(O6*T6,"") | V6: =IFERROR(P6-U6,"") | W6: =IFERROR(V6/P6,"") | X6: =IFERROR(IF(W6/SUM(W:W)=0,"",W6/SUM(W:W)),"")
R7: =IFERROR(P7/O7,"") | S7: =IFERROR(R7*(1+Q7),"") | T7: =IFERROR(INDEX(上年标准成本!$I:$I,MATCH(K7,上年标准成本!$C:$C,0),1),"") | U7: =IFERROR(O7*T7,"") | V7: =IFERROR(P7-U7,"") | W7: =IFERROR(V7/P7,"") | X7: =IFERROR(IF(W7/SUM(W:W)=0,"",W7/SUM(W:W)),"")
R8: =IFERROR(P8/O8,"") | S8: =IFERROR(R8*(1+Q8),"") | T8: =IFERROR(INDEX(上年标准成本!$I:$I,MATCH(K8,上年标准成本!$C:$C,0),1),"") | U8: =IFERROR(O8*T8,"") | V8: =IFERROR(P8-U8,"") | W8: =IFERROR(V8/P8,"") | X8: =IFERROR(IF(W8/SUM(W:W)=0,"",W8/SUM(W:W)),"")
R9: =IFERROR(P9/O9,"") | S9: =IFERROR(R9*(1+Q9),"") | T9: =IFERROR(INDEX(上年标准成本!$I:$I,MATCH(K9,上年标准成本!$C:$C,0),1),"") | U9: =IFERROR(O9*T9,"") | V9: =IFERROR(P9-U9,"") | W9: =IFERROR(V9/P9,"") | X9: =IFERROR(IF(W9/SUM(W:W)=0,"",W9/SUM(W:W)),"")
R10: =IFERROR(P10/O10,"") | S10: =IFERROR(R10*(1+Q10),"") | T10: =IFERROR(INDEX(上年标准成本!$I:$I,MATCH(K10,上年标准成本!$C:$C,0),1),"") | U10: =IFERROR(O10*T10,"") | V10: =IFERROR(P10-U10,"") | W10: =IFERROR(V10/P10,"") | X10: =IFERROR(IF(W10/SUM(W:W)=0,"",W10/SUM(W:W)),"")
R11: =IFERROR(P11/O11,"") | S11: =IFERROR(R11*(1+Q11),"") | T11: =IFERROR(INDEX(上年标准成本!$I:$I,MATCH(K11,上年标准成本!$C:$C,0),1),"") | U11: =IFERROR(O11*T11,"") | V11: =IFERROR(P11-U11,"") | W11: =IFERROR(V11/P11,"") | X11: =IFERROR(IF(W11/SUM(W:W)=0,"",W11/SUM(W:W)),"")
R12: =IFERROR(P12/O12,"") | S12: =IFERROR(R12*(1+Q12),"") | T12: =IFERROR(INDEX(上年标准成本!$I:$I,MATCH(K12,上年标准成本!$C:$C,0),1),"") | U12: =IFERROR(O12*T12,"") | V12: =IFERROR(P12-U12,"") | W12: =IFERROR(V12/P12,"") | X12: =IFERROR(IF(W12/SUM(W:W)=0,"",W12/SUM(W:W)),"")
R13: =IFERROR(P13/O13,"") | S13: =IFERROR(R13*(1+Q13),"") | T13: =IFERROR(INDEX(上年标准成本!$I:$I,MATCH(K13,上年标准成本!$C:$C,0),1),"") | U13: =IFERROR(O13*T13,"") | V13: =IFERROR(P13-U13,"") | W13: =IFERROR(V13/P13,"") | X13: =IFERROR(IF(W13/SUM(W:W)=0,"",W13/SUM(W:W)),"")
R14: =IFERROR(P14/O14,"") | S14: =IFERROR(R14*(1+Q14),"") | T14: =IFERROR(INDEX(上年标准成本!$I:$I,MATCH(K14,上年标准成本!$C:$C,0),1),"") | U14: =IFERROR(O14*T14,"") | V14: =IFERROR(P14-U14,"") | W14: =IFERROR(V14/P14,"") | X14: =IFERROR(IF(W14/SUM(W:W)=0,"",W14/SUM(W:W)),"")
R15: =IFERROR(P15/O15,"") | S15: =IFERROR(R15*(1+Q15),"") | T15: =IFERROR(INDEX(上年标准成本!$I:$I,MATCH(K15,上年标准成本!$C:$C,0),1),"") | U15: =IFERROR(O15*T15,"") | V15: =IFERROR(P15-U15,"") | W15: =IFERROR(V15/P15,"") | X15: =IFERROR(IF(W15/SUM(W:W)=0,"",W15/SUM(W:W)),"")
R16: =IFERROR(P16/O16,"") | S16: =IFERROR(R16*(1+Q16),"") | T16: =IFERROR(INDEX(上年标准成本!$I:$I,MATCH(K16,上年标准成本!$C:$C,0),1),"") | U16: =IFERROR(O16*T16,"") | V16: =IFERROR(P16-U16,"") | W16: =IFERROR(V16/P16,"") | X16: =IFERROR(IF(W16/SUM(W:W)=0,"",W16/SUM(W:W)),"")
R17: =IFERROR(P17/O17,"") | S17: =IFERROR(R17*(1+Q17),"") | T17: =IFERROR(INDEX(上年标准成本!$I:$I,MATCH(K17,上年标准成本!$C:$C,0),1),"") | U17: =IFERROR(O17*T17,"") | V17: =IFERROR(P17-U17,"") | W17: =IFERROR(V17/P17,"") | X17: =IFERROR(IF(W17/SUM(W:W)=0,"",W17/SUM(W:W)),"")
... R999: =IFERROR(P999/O999,"") | S999: =IFERROR(R999*(1+Q999),"") | T999: =IFERROR(INDEX(上年标准成本!$I:$I,MATCH(K999,上年标准成本!$C:$C,0),1),"") | U999: =IFERROR(O999*T999,"") | V999: =IFERROR(P999-U999,"") | W999: =IFERROR(V999/P999,"") | X999: =IFERROR(IF(W999/SUM(W:W)=0,"",W999/SUM(W:W)),"")

Sheet 当年实际
A1: 订单日期 | B1: 订单号 | C1: 交付日期 | D1: 客户大类 | E1: 客户子类 | F1: 客户名称 | G1: 渠道分类 | H1: 渠道名称 | I1: 销售部门 | J1: 业务员 | K1: 产品名称 | L1: 产品大类 | M1: 产品子类 | N1: 产品来源 | O1: 销售数量 | P1: 不含税销售收入 | Q1: 增值税率 | R1: 不含税销售单价 | S1: 含税单价 | T1: 单位标准成本 | U1: 销售成本 | V1: 销售毛利 | W1: 毛利率 | X1: 毛利占比% | Z1: 返回主页
A2: 44211 | B2: SO0001 | C2: 44227 | D2: CA | E2: CA01 | F2: 天猫 | G2: SCA | H2: SCA01 | I2: DA | J2: 张三 | K2: A0111 | L2: PA | M2: PA01 | N2: 外购 | O2: 100 | P2: 1800 | Q2: 0.13 | R2: =IFERROR(P2/O2,"") -> 18 | S2: =IFERROR(R2*(1+Q2),"") -> 20.34 | T2: =IFERROR(INDEX(当年标准成本!$I:$I,MATCH(K2,当年标准成本!$C:$C,0),1),"") -> 13 | U2: =IFERROR(O2*T2,"") -> 1300 | V2: =IFERROR(P2-U2,"") -> 500 | W2: =IFERROR(V2/P2,"") -> 0.27777778 | X2: =IFERROR(IF(W2/SUM(W:W)=0,"",W2/SUM(W:W)),"") -> 0.35082795
A3: 44286 | B3: SO0002 | C3: 44316 | D3: CB | E3: CB01 | F3: 苏宁 | G3: SCB | H3: SCB01 | I3: DB | J3: 李四 | K3: B0122 | L3: PB | M3: PB01 | N3: 自制 | O3: 124 | P3: 2000 | Q3: 0.13 | R3: =IFERROR(P3/O3,"") -> 16.129032 | S3: =IFERROR(R3*(1+Q3),"") -> 18.225806 | T3: =IFERROR(INDEX(当年标准成本!$I:$I,MATCH(K3,当年标准成本!$C:$C,0),1),"") -> 13 | U3: =IFERROR(O3*T3,"") -> 1612 | V3: =IFERROR(P3-U3,"") -> 388 | W3: =IFERROR(V3/P3,"") -> 0.194 | X3: =IFERROR(IF(W3/SUM(W:W)=0,"",W3/SUM(W:W)),"") -> 0.24501824
A4: 44345 | B4: SO0003 | C4: 44346 | D4: CC | E4: CC01 | F4: 京东 | G4: SCC | H4: SCC01 | I4: DC | J4: 王二麻子 | K4: C0122 | L4: PC | M4: PC01 | N4: 自制 | O4: 112 | P4: 1200 | Q4: 0.13 | R4: =IFERROR(P4/O4,"") -> 10.714286 | S4: =IFERROR(R4*(1+Q4),"") -> 12.107143 | T4: =IFERROR(INDEX(当年标准成本!$I:$I,MATCH(K4,当年标准成本!$C:$C,0),1),"") -> 9 | U4: =IFERROR(O4*T4,"") -> 1008 | V4: =IFERROR(P4-U4,"") -> 192 | W4: =IFERROR(V4/P4,"") -> 0.16 | X4: =IFERROR(IF(W4/SUM(W:W)=0,"",W4/SUM(W:W)),"") -> 0.2020769
A5: 44345 | B5: SO0004 | C5: 44530 | D5: CC | E5: CC01 | F5: 京东 | G5: SCC | H5: SCC01 | I5: DC | J5: 王二麻子 | K5: C0122 | L5: PC | M5: PC01 | N5: 自制 | O5: 112 | P5: 1200 | Q5: 0.13 | R5: =IFERROR(P5/O5,"") -> 10.714286 | S5: =IFERROR(R5*(1+Q5),"") -> 12.107143 | T5: =IFERROR(INDEX(当年标准成本!$I:$I,MATCH(K5,当年标准成本!$C:$C,0),1),"") -> 9 | U5: =IFERROR(O5*T5,"") -> 1008 | V5: =IFERROR(P5-U5,"") -> 192 | W5: =IFERROR(V5/P5,"") -> 0.16 | X5: =IFERROR(IF(W5/SUM(W:W)=0,"",W5/SUM(W:W)),"") -> 0.2020769
R6: =IFERROR(P6/O6,"") | S6: =IFERROR(R6*(1+Q6),"") | T6: =IFERROR(INDEX(当年标准成本!$I:$I,MATCH(K6,当年标准成本!$C:$C,0),1),"") | U6: =IFERROR(O6*T6,"") | V6: =IFERROR(P6-U6,"") | W6: =IFERROR(V6/P6,"") | X6: =IFERROR(IF(W6/SUM(W:W)=0,"",W6/SUM(W:W)),"")
R7: =IFERROR(P7/O7,"") | S7: =IFERROR(R7*(1+Q7),"") | T7: =IFERROR(INDEX(当年标准成本!$I:$I,MATCH(K7,当年标准成本!$C:$C,0),1),"") | U7: =IFERROR(O7*T7,"") | V7: =IFERROR(P7-U7,"") | W7: =IFERROR(V7/P7,"") | X7: =IFERROR(IF(W7/SUM(W:W)=0,"",W7/SUM(W:W)),"")
R8: =IFERROR(P8/O8,"") | S8: =IFERROR(R8*(1+Q8),"") | T8: =IFERROR(INDEX(当年标准成本!$I:$I,MATCH(K8,当年标准成本!$C:$C,0),1),"") | U8: =IFERROR(O8*T8,"") | V8: =IFERROR(P8-U8,"") | W8: =IFERROR(V8/P8,"") | X8: =IFERROR(IF(W8/SUM(W:W)=0,"",W8/SUM(W:W)),"")
R9: =IFERROR(P9/O9,"") | S9: =IFERROR(R9*(1+Q9),"") | T9: =IFERROR(INDEX(当年标准成本!$I:$I,MATCH(K9,当年标准成本!$C:$C,0),1),"") | U9: =IFERROR(O9*T9,"") | V9: =IFERROR(P9-U9,"") | W9: =IFERROR(V9/P9,"") | X9: =IFERROR(IF(W9/SUM(W:W)=0,"",W9/SUM(W:W)),"")
R10: =IFERROR(P10/O10,"") | S10: =IFERROR(R10*(1+Q10),"") | T10: =IFERROR(INDEX(当年标准成本!$I:$I,MATCH(K10,当年标准成本!$C:$C,0),1),"") | U10: =IFERROR(O10*T10,"") | V10: =IFERROR(P10-U10,"") | W10: =IFERROR(V10/P10,"") | X10: =IFERROR(IF(W10/SUM(W:W)=0,"",W10/SUM(W:W)),"")
R11: =IFERROR(P11/O11,"") | S11: =IFERROR(R11*(1+Q11),"") | T11: =IFERROR(INDEX(当年标准成本!$I:$I,MATCH(K11,当年标准成本!$C:$C,0),1),"") | U11: =IFERROR(O11*T11,"") | V11: =IFERROR(P11-U11,"") | W11: =IFERROR(V11/P11,"") | X11: =IFERROR(IF(W11/SUM(W:W)=0,"",W11/SUM(W:W)),"")
R12: =IFERROR(P12/O12,"") | S12: =IFERROR(R12*(1+Q12),"") | T12: =IFERROR(INDEX(当年标准成本!$I:$I,MATCH(K12,当年标准成本!$C:$C,0),1),"") | U12: =IFERROR(O12*T12,"") | V12: =IFERROR(P12-U12,"") | W12: =IFERROR(V12/P12,"") | X12: =IFERROR(IF(W12/SUM(W:W)=0,"",W12/SUM(W:W)),"")
R13: =IFERROR(P13/O13,"") | S13: =IFERROR(R13*(1+Q13),"") | T13: =IFERROR(INDEX(当年标准成本!$I:$I,MATCH(K13,当年标准成本!$C:$C,0),1),"") | U13: =IFERROR(O13*T13,"") | V13: =IFERROR(P13-U13,"") | W13: =IFERROR(V13/P13,"") | X13: =IFERROR(IF(W13/SUM(W:W)=0,"",W13/SUM(W:W)),"")
R14: =IFERROR(P14/O14,"") | S14: =IFERROR(R14*(1+Q14),"") | T14: =IFERROR(INDEX(当年标准成本!$I:$I,MATCH(K14,当年标准成本!$C:$C,0),1),"") | U14: =IFERROR(O14*T14,"") | V14: =IFERROR(P14-U14,"") | W14: =IFERROR(V14/P14,"") | X14: =IFERROR(IF(W14/SUM(W:W)=0,"",W14/SUM(W:W)),"")
R15: =IFERROR(P15/O15,"") | S15: =IFERROR(R15*(1+Q15),"") | T15: =IFERROR(INDEX(当年标准成本!$I:$I,MATCH(K15,当年标准成本!$C:$C,0),1),"") | U15: =IFERROR(O15*T15,"") | V15: =IFERROR(P15-U15,"") | W15: =IFERROR(V15/P15,"") | X15: =IFERROR(IF(W15/SUM(W:W)=0,"",W15/SUM(W:W)),"")
R16: =IFERROR(P16/O16,"") | S16: =IFERROR(R16*(1+Q16),"") | T16: =IFERROR(INDEX(当年标准成本!$I:$I,MATCH(K16,当年标准成本!$C:$C,0),1),"") | U16: =IFERROR(O16*T16,"") | V16: =IFERROR(P16-U16,"") | W16: =IFERROR(V16/P16,"") | X16: =IFERROR(IF(W16/SUM(W:W)=0,"",W16/SUM(W:W)),"")
R17: =IFERROR(P17/O17,"") | S17: =IFERROR(R17*(1+Q17),"") | T17: =IFERROR(INDEX(当年标准成本!$I:$I,MATCH(K17,当年标准成本!$C:$C,0),1),"") | U17: =IFERROR(O17*T17,"") | V17: =IFERROR(P17-U17,"") | W17: =IFERROR(V17/P17,"") | X17: =IFERROR(IF(W17/SUM(W:W)=0,"",W17/SUM(W:W)),"")
... R999: =IFERROR(P999/O999,"") | S999: =IFERROR(R999*(1+Q999),"") | T999: =IFERROR(INDEX(当年标准成本!$I:$I,MATCH(K999,当年标准成本!$C:$C,0),1),"") | U999: =IFERROR(O999*T999,"") | V999: =IFERROR(P999-U999,"") | W999: =IFERROR(V999/P999,"") | X999: =IFERROR(IF(W999/SUM(W:W)=0,"",W999/SUM(W:W)),"")

Sheet 当年估计 渠道
A1: 渠道分类 | B1: 渠道名称 | C1: 覆盖客户数量 | D1: ="当年剩余月份估计 E"&TEXT(主页!$D$2,"YY")&"YTG" -> 当年剩余月份估计 E21YTG | J1: ="当年已过去月份实际 A"&TEXT(主页!$D$2,"YY")&"YTD" -> 当年已过去月份实际 A21YTD | L1: 返回主页
D2: 销售收入 | E2: 收入占比% | F2: 毛利率 | G2: 销售毛利 | H2: 毛利占比% | J2: 毛利率
A3: SCB | B3: SCB01 | C3: 1 | D3: 500 | E3: =IF(D3/SUM(D:D)=0,"",D3/SUM(D:D)) -> 0.090909091 | F3: 0.165 | G3: =D3*F3 -> 82.5 | H3: =IF(G3/SUM(G:G)=0,"",G3/SUM(G:G)) -> 0.06639839 | J3: =IFERROR(SUMIFS(当年实际!$V:$V,当年实际!$H:$H,$B3,当年实际!$C:$C,">="&DATE(YEAR(主页!$D$2),1,1),当年实际!$C:$C,"<="&EOMONTH(DATE(YEAR(主页!$D$2),MONTH(主页!$D$2),1),0))/SUMIFS(当年实际!$P:$P,当年实际!$H:$H,$B3,当年实际!$C:$C,">="&DATE(YEAR(主页!$D$2),1,1),当年实际!$C:$C,"<="&EOMONTH(DATE(YEAR(主页!$D$2),MONTH(主页!$D$2),1),0)),"") -> 0.194
A4: SCA | B4: SCA01 | C4: 2 | D4: 2000 | E4: =IF(D4/SUM(D:D)=0,"",D4/SUM(D:D)) -> 0.36363636 | F4: 0.28 | G4: =D4*F4 -> 560 | H4: =IF(G4/SUM(G:G)=0,"",G4/SUM(G:G)) -> 0.45070423 | J4: =IFERROR(SUMIFS(当年实际!$V:$V,当年实际!$H:$H,$B4,当年实际!$C:$C,">="&DATE(YEAR(主页!$D$2),1,1),当年实际!$C:$C,"<="&EOMONTH(DATE(YEAR(主页!$D$2),MONTH(主页!$D$2),1),0))/SUMIFS(当年实际!$P:$P,当年实际!$H:$H,$B4,当年实际!$C:$C,">="&DATE(YEAR(主页!$D$2),1,1),当年实际!$C:$C,"<="&EOMONTH(DATE(YEAR(主页!$D$2),MONTH(主页!$D$2),1),0)),"") -> 0.27777778
A5: SCC | B5: SCC01 | C5: 3 | D5: 3000 | E5: =IF(D5/SUM(D:D)=0,"",D5/SUM(D:D)) -> 0.54545455 | F5: 0.2 | G5: =D5*F5 -> 600 | H5: =IF(G5/SUM(G:G)=0,"",G5/SUM(G:G)) -> 0.48289738 | J5: =IFERROR(SUMIFS(当年实际!$V:$V,当年实际!$H:$H,$B5,当年实际!$C:$C,">="&DATE(YEAR(主页!$D$2),1,1),当年实际!$C:$C,"<="&EOMONTH(DATE(YEAR(主页!$D$2),MONTH(主页!$D$2),1),0))/SUMIFS(当年实际!$P:$P,当年实际!$H:$H,$B5,当年实际!$C:$C,">="&DATE(YEAR(主页!$D$2),1,1),当年实际!$C:$C,"<="&EOMONTH(DATE(YEAR(主页!$D$2),MONTH(主页!$D$2),1),0)),"") -> 0.16
E6: =IF(D6/SUM(D:D)=0,"",D6/SUM(D:D)) | G6: =D6*F6 -> 0 | H6: =IF(G6/SUM(G:G)=0,"",G6/SUM(G:G)) | J6: =IFERROR(SUMIFS(当年实际!$V:$V,当年实际!$H:$H,$B6,当年实际!$C:$C,">="&DATE(YEAR(主页!$D$2),1,1),当年实际!$C:$C,"<="&EOMONTH(DATE(YEAR(主页!$D$2),MONTH(主页!$D$2),1),0))/SUMIFS(当年实际!$P:$P,当年实际!$H:$H,$B6,当年实际!$C:$C,">="&DATE(YEAR(主页!$D$2),1,1),当年实际!$C:$C,"<="&EOMONTH(DATE(YEAR(主页!$D$2),MONTH(主页!$D$2),1),0)),"")
E7: =IF(D7/SUM(D:D)=0,"",D7/SUM(D:D)) | G7: =D7*F7 -> 0 | H7: =IF(G7/SUM(G:G)=0,"",G7/SUM(G:G)) | J7: =IFERROR(SUMIFS(当年实际!$V:$V,当年实际!$H:$H,$B7,当年实际!$C:$C,">="&DATE(YEAR(主页!$D$2),1,1),当年实际!$C:$C,"<="&EOMONTH(DATE(YEAR(主页!$D$2),MONTH(主页!$D$2),1),0))/SUMIFS(当年实际!$P:$P,当年实际!$H:$H,$B7,当年实际!$C:$C,">="&DATE(YEAR(主页!$D$2),1,1),当年实际!$C:$C,"<="&EOMONTH(DATE(YEAR(主页!$D$2),MONTH(主页!$D$2),1),0)),"")
E8: =IF(D8/SUM(D:D)=0,"",D8/SUM(D:D)) | G8: =D8*F8 -> 0 | H8: =IF(G8/SUM(G:G)=0,"",G8/SUM(G:G)) | J8: =IFERROR(SUMIFS(当年实际!$V:$V,当年实际!$H:$H,$B8,当年实际!$C:$C,">="&DATE(YEAR(主页!$D$2),1,1),当年实际!$C:$C,"<="&EOMONTH(DATE(YEAR(主页!$D$2),MONTH(主页!$D$2),1),0))/SUMIFS(当年实际!$P:$P,当年实际!$H:$H,$B8,当年实际!$C:$C,">="&DATE(YEAR(主页!$D$2),1,1),当年实际!$C:$C,"<="&EOMONTH(DATE(YEAR(主页!$D$2),MONTH(主页!$D$2),1),0)),"")
E9: =IF(D9/SUM(D:D)=0,"",D9/SUM(D:D)) | G9: =D9*F9 -> 0 | H9: =IF(G9/SUM(G:G)=0,"",G9/SUM(G:G)) | J9: =IFERROR(SUMIFS(当年实际!$V:$V,当年实际!$H:$H,$B9,当年实际!$C:$C,">="&DATE(YEAR(主页!$D$2),1,1),当年实际!$C:$C,"<="&EOMONTH(DATE(YEAR(主页!$D$2),MONTH(主页!$D$2),1),0))/SUMIFS(当年实际!$P:$P,当年实际!$H:$H,$B9,当年实际!$C:$C,">="&DATE(YEAR(主页!$D$2),1,1),当年实际!$C:$C,"<="&EOMONTH(DATE(YEAR(主页!$D$2),MONTH(主页!$D$2),1),0)),"")
E10: =IF(D10/SUM(D:D)=0,"",D10/SUM(D:D)) | G10: =D10*F10 -> 0 | H10: =IF(G10/SUM(G:G)=0,"",G10/SUM(G:G)) | J10: =IFERROR(SUMIFS(当年实际!$V:$V,当年实际!$H:$H,$B10,当年实际!$C:$C,">="&DATE(YEAR(主页!$D$2),1,1),当年实际!$C:$C,"<="&EOMONTH(DATE(YEAR(主页!$D$2),MONTH(主页!$D$2),1),0))/SUMIFS(当年实际!$P:$P,当年实际!$H:$H,$B10,当年实际!$C:$C,">="&DATE(YEAR(主页!$D$2),1,1),当年实际!$C:$C,"<="&EOMONTH(DATE(YEAR(主页!$D$2),MONTH(主页!$D$2),1),0)),"")
E11: =IF(D11/SUM(D:D)=0,"",D11/SUM(D:D)) | G11: =D11*F11 -> 0 | H11: =IF(G11/SUM(G:G)=0,"",G11/SUM(G:G)) | J11: =IFERROR(SUMIFS(当年实际!$V:$V,当年实际!$H:$H,$B11,当年实际!$C:$C,">="&DATE(YEAR(主页!$D$2),1,1),当年实际!$C:$C,"<="&EOMONTH(DATE(YEAR(主页!$D$2),MONTH(主页!$D$2),1),0))/SUMIFS(当年实际!$P:$P,当年实际!$H:$H,$B11,当年实际!$C:$C,">="&DATE(YEAR(主页!$D$2),1,1),当年实际!$C:$C,"<="&EOMONTH(DATE(YEAR(主页!$D$2),MONTH(主页!$D$2),1),0)),"")
E12: =IF(D12/SUM(D:D)=0,"",D12/SUM(D:D)) | G12: =D12*F12 -> 0 | H12: =IF(G12/SUM(G:G)=0,"",G12/SUM(G:G)) | J12: =IFERROR(SUMIFS(当年实际!$V:$V,当年实际!$H:$H,$B12,当年实际!$C:$C,">="&DATE(YEAR(主页!$D$2),1,1),当年实际!$C:$C,"<="&EOMONTH(DATE(YEAR(主页!$D$2),MONTH(主页!$D$2),1),0))/SUMIFS(当年实际!$P:$P,当年实际!$H:$H,$B12,当年实际!$C:$C,">="&DATE(YEAR(主页!$D$2),1,1),当年实际!$C:$C,"<="&EOMONTH(DATE(YEAR(主页!$D$2),MONTH(主页!$D$2),1),0)),"")
E13: =IF(D13/SUM(D:D)=0,"",D13/SUM(D:D)) | G13: =D13*F13 -> 0 | H13: =IF(G13/SUM(G:G)=0,"",G13/SUM(G:G)) | J13: =IFERROR(SUMIFS(当年实际!$V:$V,当年实际!$H:$H,$B13,当年实际!$C:$C,">="&DATE(YEAR(主页!$D$2),1,1),当年实际!$C:$C,"<="&EOMONTH(DATE(YEAR(主页!$D$2),MONTH(主页!$D$2),1),0))/SUMIFS(当年实际!$P:$P,当年实际!$H:$H,$B13,当年实际!$C:$C,">="&DATE(YEAR(主页!$D$2),1,1),当年实际!$C:$C,"<="&EOMONTH(DATE(YEAR(主页!$D$2),MONTH(主页!$D$2),1),0)),"")
E14: =IF(D14/SUM(D:D)=0,"",D14/SUM(D:D)) | G14: =D14*F14 -> 0 | H14: =IF(G14/SUM(G:G)=0,"",G14/SUM(G:G)) | J14: =IFERROR(SUMIFS(当年实际!$V:$V,当年实际!$H:$H,$B14,当年实际!$C:$C,">="&DATE(YEAR(主页!$D$2),1,1),当年实际!$C:$C,"<="&EOMONTH(DATE(YEAR(主页!$D$2),MONTH(主页!$D$2),1),0))/SUMIFS(当年实际!$P:$P,当年实际!$H:$H,$B14,当年实际!$C:$C,">="&DATE(YEAR(主页!$D$2),1,1),当年实际!$C:$C,"<="&EOMONTH(DATE(YEAR(主页!$D$2),MONTH(主页!$D$2),1),0)),"")
E15: =IF(D15/SUM(D:D)=0,"",D15/SUM(D:D)) | G15: =D15*F15 -> 0 | H15: =IF(G15/SUM(G:G)=0,"",G15/SUM(G:G)) | J15: =IFERROR(SUMIFS(当年实际!$V:$V,当年实际!$H:$H,$B15,当年实际!$C:$C,">="&DATE(YEAR(主页!$D$2),1,1),当年实际!$C:$C,"<="&EOMONTH(DATE(YEAR(主页!$D$2),MONTH(主页!$D$2),1),0))/SUMIFS(当年实际!$P:$P,当年实际!$H:$H,$B15,当年实际!$C:$C,">="&DATE(YEAR(主页!$D$2),1,1),当年实际!$C:$C,"<="&EOMONTH(DATE(YEAR(主页!$D$2),MONTH(主页!$D$2),1),0)),"")
E16: =IF(D16/SUM(D:D)=0,"",D16/SUM(D:D)) | G16: =D16*F16 -> 0 | H16: =IF(G16/SUM(G:G)=0,"",G16/SUM(G:G)) | J16: =IFERROR(SUMIFS(当年实际!$V:$V,当年实际!$H:$H,$B16,当年实际!$C:$C,">="&DATE(YEAR(主页!$D$2),1,1),当年实际!$C:$C,"<="&EOMONTH(DATE(YEAR(主页!$D$2),MONTH(主页!$D$2),1),0))/SUMIFS(当年实际!$P:$P,当年实际!$H:$H,$B16,当年实际!$C:$C,">="&DATE(YEAR(主页!$D$2),1,1),当年实际!$C:$C,"<="&EOMONTH(DATE(YEAR(主页!$D$2),MONTH(主页!$D$2),1),0)),"")
E17: =IF(D17/SUM(D:D)=0,"",D17/SUM(D:D)) | G17: =D17*F17 -> 0 | H17: =IF(G17/SUM(G:G)=0,"",G17/SUM(G:G)) | J17: =IFERROR(SUMIFS(当年实际!$V:$V,当年实际!$H:$H,$B17,当年实际!$C:$C,">="&DATE(YEAR(主页!$D$2),1,1),当年实际!$C:$C,"<="&EOMONTH(DATE(YEAR(主页!$D$2),MONTH(主页!$D$2),1),0))/SUMIFS(当年实际!$P:$P,当年实际!$H:$H,$B17,当年实际!$C:$C,">="&DATE(YEAR(主页!$D$2),1,1),当年实际!$C:$C,"<="&EOMONTH(DATE(YEAR(主页!$D$2),MONTH(主页!$D$2),1),0)),"")
... E1201: =IF(D1201/SUM(D:D)=0,"",D1201/SUM(D:D)) | G1201: =D1201*F1201 -> 0 | H1201: =IF(G1201/SUM(G:G)=0,"",G1201/SUM(G:G)) | J1201: =IFERROR(SUMIFS(当年实际!$V:$V,当年实际!$H:$H,$B1201,当年实际!$C:$C,">="&DATE(YEAR(主页!$D$2),1,1),当年实际!$C:$C,"<="&EOMONTH(DATE(YEAR(主页!$D$2),MONTH(主页!$D$2),1),0))/SUMIFS(当年实际!$P:$P,当年实际!$H:$H,$B1201,当年实际!$C:$C,">="&DATE(YEAR(主页!$D$2),1,1),当年实际!$C:$C,"<="&EOMONTH(DATE(YEAR(主页!$D$2),MONTH(主页!$D$2),1),0)),"")

Sheet 当年估计 业务员
A1: 销售大区 | B1: 办事处 | C1: 业务员 | D1: ="当年剩余月份估计 E"&TEXT(主页!$D$2,"YY")&"YTG" -> 当年剩余月份估计 E21YTG | J1: ="当年已过去月份实际 A"&TEXT(主页!$D$2,"YY")&"YTD" -> 当年已过去月份实际 A21YTD | M1: 返回主页
A2: 销售大区 | B2: 办事处 | C2: 业务员 | D2: 销售收入 | E2: 收入占比% | F2: 毛利率 | G2: 销售毛利 | H2: 毛利占比% | J2: 毛利率
A3: 东区 | B3: 北京 | C3: 张三 | D3: 1200 | E3: =IF(D3/SUM(D:D)=0,"",D3/SUM(D:D)) -> 0.19354839 | F3: 0.17 | G3: =D3*F3 -> 204 | H3: =IF(G3/SUM(G:G)=0,"",G3/SUM(G:G)) -> 0.1347424 | J3: =IFERROR(SUMIFS(当年实际!$V:$V,当年实际!$J:$J,$C3,当年实际!$C:$C,">="&DATE(YEAR(主页!$D$2),1,1),当年实际!$C:$C,"<="&EOMONTH(DATE(YEAR(主页!$D$2),MONTH(主页!$D$2),1),0))/SUMIFS(当年实际!$P:$P,当年实际!$J:$J,$C3,当年实际!$C:$C,">="&DATE(YEAR(主页!$D$2),1,1),当年实际!$C:$C,"<="&EOMONTH(DATE(YEAR(主页!$D$2),MONTH(主页!$D$2),1),0)),"") -> 0.27777778
A4: 南区 | B4: 上海 | C4: 李四 | D4: 2000 | E4: =IF(D4/SUM(D:D)=0,"",D4/SUM(D:D)) -> 0.32258065 | F4: 0.13 | G4: =D4*F4 -> 260 | H4: =IF(G4/SUM(G:G)=0,"",G4/SUM(G:G)) -> 0.17173052 | J4: =IFERROR(SUMIFS(当年实际!$V:$V,当年实际!$J:$J,$C4,当年实际!$C:$C,">="&DATE(YEAR(主页!$D$2),1,1),当年实际!$C:$C,"<="&EOMONTH(DATE(YEAR(主页!$D$2),MONTH(主页!$D$2),1),0))/SUMIFS(当年实际!$P:$P,当年实际!$J:$J,$C4,当年实际!$C:$C,">="&DATE(YEAR(主页!$D$2),1,1),当年实际!$C:$C,"<="&EOMONTH(DATE(YEAR(主页!$D$2),MONTH(主页!$D$2),1),0)),"") -> 0.194
A5: 北区 | B5: 广州 | C5: 王二麻子 | D5: 3000 | E5: =IF(D5/SUM(D:D)=0,"",D5/SUM(D:D)) -> 0.48387097 | F5: 0.35 | G5: =D5*F5 -> 1050 | H5: =IF(G5/SUM(G:G)=0,"",G5/SUM(G:G)) -> 0.69352708 | J5: =IFERROR(SUMIFS(当年实际!$V:$V,当年实际!$J:$J,$C5,当年实际!$C:$C,">="&DATE(YEAR(主页!$D$2),1,1),当年实际!$C:$C,"<="&EOMONTH(DATE(YEAR(主页!$D$2),MONTH(主页!$D$2),1),0))/SUMIFS(当年实际!$P:$P,当年实际!$J:$J,$C5,当年实际!$C:$C,">="&DATE(YEAR(主页!$D$2),1,1),当年实际!$C:$C,"<="&EOMONTH(DATE(YEAR(主页!$D$2),MONTH(主页!$D$2),1),0)),"") -> 0.16
E6: =IF(D6/SUM(D:D)=0,"",D6/SUM(D:D)) | G6: =D6*F6 -> 0 | H6: =IF(G6/SUM(G:G)=0,"",G6/SUM(G:G)) | J6: =IFERROR(SUMIFS(当年实际!$V:$V,当年实际!$J:$J,$C6,当年实际!$C:$C,">="&DATE(YEAR(主页!$D$2),1,1),当年实际!$C:$C,"<="&EOMONTH(DATE(YEAR(主页!$D$2),MONTH(主页!$D$2),1),0))/SUMIFS(当年实际!$P:$P,当年实际!$J:$J,$C6,当年实际!$C:$C,">="&DATE(YEAR(主页!$D$2),1,1),当年实际!$C:$C,"<="&EOMONTH(DATE(YEAR(主页!$D$2),MONTH(主页!$D$2),1),0)),"")
E7: =IF(D7/SUM(D:D)=0,"",D7/SUM(D:D)) | G7: =D7*F7 -> 0 | H7: =IF(G7/SUM(G:G)=0,"",G7/SUM(G:G)) | J7: =IFERROR(SUMIFS(当年实际!$V:$V,当年实际!$J:$J,$C7,当年实际!$C:$C,">="&DATE(YEAR(主页!$D$2),1,1),当年实际!$C:$C,"<="&EOMONTH(DATE(YEAR(主页!$D$2),MONTH(主页!$D$2),1),0))/SUMIFS(当年实际!$P:$P,当年实际!$J:$J,$C7,当年实际!$C:$C,">="&DATE(YEAR(主页!$D$2),1,1),当年实际!$C:$C,"<="&EOMONTH(DATE(YEAR(主页!$D$2),MONTH(主页!$D$2),1),0)),"")
E8: =IF(D8/SUM(D:D)=0,"",D8/SUM(D:D)) | G8: =D8*F8 -> 0 | H8: =IF(G8/SUM(G:G)=0,"",G8/SUM(G:G)) | J8: =IFERROR(SUMIFS(当年实际!$V:$V,当年实际!$J:$J,$C8,当年实际!$C:$C,">="&DATE(YEAR(主页!$D$2),1,1),当年实际!$C:$C,"<="&EOMONTH(DATE(YEAR(主页!$D$2),MONTH(主页!$D$2),1),0))/SUMIFS(当年实际!$P:$P,当年实际!$J:$J,$C8,当年实际!$C:$C,">="&DATE(YEAR(主页!$D$2),1,1),当年实际!$C:$C,"<="&EOMONTH(DATE(YEAR(主页!$D$2),MONTH(主页!$D$2),1),0)),"")
E9: =IF(D9/SUM(D:D)=0,"",D9/SUM(D:D)) | G9: =D9*F9 -> 0 | H9: =IF(G9/SUM(G:G)=0,"",G9/SUM(G:G)) | J9: =IFERROR(SUMIFS(当年实际!$V:$V,当年实际!$J:$J,$C9,当年实际!$C:$C,">="&DATE(YEAR(主页!$D$2),1,1),当年实际!$C:$C,"<="&EOMONTH(DATE(YEAR(主页!$D$2),MONTH(主页!$D$2),1),0))/SUMIFS(当年实际!$P:$P,当年实际!$J:$J,$C9,当年实际!$C:$C,">="&DATE(YEAR(主页!$D$2),1,1),当年实际!$C:$C,"<="&EOMONTH(DATE(YEAR(主页!$D$2),MONTH(主页!$D$2),1),0)),"")
E10: =IF(D10/SUM(D:D)=0,"",D10/SUM(D:D)) | G10: =D10*F10 -> 0 | H10: =IF(G10/SUM(G:G)=0,"",G10/SUM(G:G)) | J10: =IFERROR(SUMIFS(当年实际!$V:$V,当年实际!$J:$J,$C10,当年实际!$C:$C,">="&DATE(YEAR(主页!$D$2),1,1),当年实际!$C:$C,"<="&EOMONTH(DATE(YEAR(主页!$D$2),MONTH(主页!$D$2),1),0))/SUMIFS(当年实际!$P:$P,当年实际!$J:$J,$C10,当年实际!$C:$C,">="&DATE(YEAR(主页!$D$2),1,1),当年实际!$C:$C,"<="&EOMONTH(DATE(YEAR(主页!$D$2),MONTH(主页!$D$2),1),0)),"")
E11: =IF(D11/SUM(D:D)=0,"",D11/SUM(D:D)) | G11: =D11*F11 -> 0 | H11: =IF(G11/SUM(G:G)=0,"",G11/SUM(G:G)) | J11: =IFERROR(SUMIFS(当年实际!$V:$V,当年实际!$J:$J,$C11,当年实际!$C:$C,">="&DATE(YEAR(主页!$D$2),1,1),当年实际!$C:$C,"<="&EOMONTH(DATE(YEAR(主页!$D$2),MONTH(主页!$D$2),1),0))/SUMIFS(当年实际!$P:$P,当年实际!$J:$J,$C11,当年实际!$C:$C,">="&DATE(YEAR(主页!$D$2),1,1),当年实际!$C:$C,"<="&EOMONTH(DATE(YEAR(主页!$D$2),MONTH(主页!$D$2),1),0)),"")
E12: =IF(D12/SUM(D:D)=0,"",D12/SUM(D:D)) | G12: =D12*F12 -> 0 | H12: =IF(G12/SUM(G:G)=0,"",G12/SUM(G:G)) | J12: =IFERROR(SUMIFS(当年实际!$V:$V,当年实际!$J:$J,$C12,当年实际!$C:$C,">="&DATE(YEAR(主页!$D$2),1,1),当年实际!$C:$C,"<="&EOMONTH(DATE(YEAR(主页!$D$2),MONTH(主页!$D$2),1),0))/SUMIFS(当年实际!$P:$P,当年实际!$J:$J,$C12,当年实际!$C:$C,">="&DATE(YEAR(主页!$D$2),1,1),当年实际!$C:$C,"<="&EOMONTH(DATE(YEAR(主页!$D$2),MONTH(主页!$D$2),1),0)),"")
E13: =IF(D13/SUM(D:D)=0,"",D13/SUM(D:D)) | G13: =D13*F13 -> 0 | H13: =IF(G13/SUM(G:G)=0,"",G13/SUM(G:G)) | J13: =IFERROR(SUMIFS(当年实际!$V:$V,当年实际!$J:$J,$C13,当年实际!$C:$C,">="&DATE(YEAR(主页!$D$2),1,1),当年实际!$C:$C,"<="&EOMONTH(DATE(YEAR(主页!$D$2),MONTH(主页!$D$2),1),0))/SUMIFS(当年实际!$P:$P,当年实际!$J:$J,$C13,当年实际!$C:$C,">="&DATE(YEAR(主页!$D$2),1,1),当年实际!$C:$C,"<="&EOMONTH(DATE(YEAR(主页!$D$2),MONTH(主页!$D$2),1),0)),"")
E14: =IF(D14/SUM(D:D)=0,"",D14/SUM(D:D)) | G14: =D14*F14 -> 0 | H14: =IF(G14/SUM(G:G)=0,"",G14/SUM(G:G)) | J14: =IFERROR(SUMIFS(当年实际!$V:$V,当年实际!$J:$J,$C14,当年实际!$C:$C,">="&DATE(YEAR(主页!$D$2),1,1),当年实际!$C:$C,"<="&EOMONTH(DATE(YEAR(主页!$D$2),MONTH(主页!$D$2),1),0))/SUMIFS(当年实际!$P:$P,当年实际!$J:$J,$C14,当年实际!$C:$C,">="&DATE(YEAR(主页!$D$2),1,1),当年实际!$C:$C,"<="&EOMONTH(DATE(YEAR(主页!$D$2),MONTH(主页!$D$2),1),0)),"")
E15: =IF(D15/SUM(D:D)=0,"",D15/SUM(D:D)) | G15: =D15*F15 -> 0 | H15: =IF(G15/SUM(G:G)=0,"",G15/SUM(G:G)) | J15: =IFERROR(SUMIFS(当年实际!$V:$V,当年实际!$J:$J,$C15,当年实际!$C:$C,">="&DATE(YEAR(主页!$D$2),1,1),当年实际!$C:$C,"<="&EOMONTH(DATE(YEAR(主页!$D$2),MONTH(主页!$D$2),1),0))/SUMIFS(当年实际!$P:$P,当年实际!$J:$J,$C15,当年实际!$C:$C,">="&DATE(YEAR(主页!$D$2),1,1),当年实际!$C:$C,"<="&EOMONTH(DATE(YEAR(主页!$D$2),MONTH(主页!$D$2),1),0)),"")
E16: =IF(D16/SUM(D:D)=0,"",D16/SUM(D:D)) | G16: =D16*F16 -> 0 | H16: =IF(G16/SUM(G:G)=0,"",G16/SUM(G:G)) | J16: =IFERROR(SUMIFS(当年实际!$V:$V,当年实际!$J:$J,$C16,当年实际!$C:$C,">="&DATE(YEAR(主页!$D$2),1,1),当年实际!$C:$C,"<="&EOMONTH(DATE(YEAR(主页!$D$2),MONTH(主页!$D$2),1),0))/SUMIFS(当年实际!$P:$P,当年实际!$J:$J,$C16,当年实际!$C:$C,">="&DATE(YEAR(主页!$D$2),1,1),当年实际!$C:$C,"<="&EOMONTH(DATE(YEAR(主页!$D$2),MONTH(主页!$D$2),1),0)),"")
E17: =IF(D17/SUM(D:D)=0,"",D17/SUM(D:D)) | G17: =D17*F17 -> 0 | H17: =IF(G17/SUM(G:G)=0,"",G17/SUM(G:G)) | J17: =IFERROR(SUMIFS(当年实际!$V:$V,当年实际!$J:$J,$C17,当年实际!$C:$C,">="&DATE(YEAR(主页!$D$2),1,1),当年实际!$C:$C,"<="&EOMONTH(DATE(YEAR(主页!$D$2),MONTH(主页!$D$2),1),0))/SUMIFS(当年实际!$P:$P,当年实际!$J:$J,$C17,当年实际!$C:$C,">="&DATE(YEAR(主页!$D$2),1,1),当年实际!$C:$C,"<="&EOMONTH(DATE(YEAR(主页!$D$2),MONTH(主页!$D$2),1),0)),"")
... E1200: =IF(D1200/SUM(D:D)=0,"",D1200/SUM(D:D)) | G1200: =D1200*F1200 -> 0 | H1200: =IF(G1200/SUM(G:G)=0,"",G1200/SUM(G:G)) | J1200: =IFERROR(SUMIFS(当年实际!$V:$V,当年实际!$J:$J,$C1200,当年实际!$C:$C,">="&DATE(YEAR(主页!$D$2),1,1),当年实际!$C:$C,"<="&EOMONTH(DATE(YEAR(主页!$D$2),MONTH(主页!$D$2),1),0))/SUMIFS(当年实际!$P:$P,当年实际!$J:$J,$C1200,当年实际!$C:$C,">="&DATE(YEAR(主页!$D$2),1,1),当年实际!$C:$C,"<="&EOMONTH(DATE(YEAR(主页!$D$2),MONTH(主页!$D$2),1),0)),"")

Sheet 当年估计 客户
A1: 客户大类 | B1: 客户子类 | C1: 客户名称 | D1: ="当年剩余月份估计 E"&TEXT(主页!$D$2,"YY")&"YTG" -> 当年剩余月份估计 E21YTG | J1: ="当年已过去月份实际 A"&TEXT(主页!$D$2,"YY")&"YTD" -> 当年已过去月份实际 A21YTD | L1: 返回主页
A2: 客户大类 | B2: 客户子类 | C2: 客户名称 | D2: 销售收入 | E2: 收入占比% | F2: 毛利率 | G2: 销售毛利 | H2: 毛利占比% | J2: 毛利率
A3: A | B3: A01 | C3: 京东 | D3: 1200 | E3: =IF(D3/SUM(D:D)=0,"",D3/SUM(D:D)) -> 0.19354839 | F3: 0.35 | G3: =D3*F3 -> 420 | H3: =IF(G3/SUM(G:G)=0,"",G3/SUM(G:G)) -> 0.36238136 | J3: =IFERROR(SUMIFS(当年实际!$V:$V,当年实际!$F:$F,$C3,当年实际!$C:$C,">="&DATE(YEAR(主页!$D$2),1,1),当年实际!$C:$C,"<="&EOMONTH(DATE(YEAR(主页!$D$2),MONTH(主页!$D$2),1),0))/SUMIFS(当年实际!$P:$P,当年实际!$F:$F,$C3,当年实际!$C:$C,">="&DATE(YEAR(主页!$D$2),1,1),当年实际!$C:$C,"<="&EOMONTH(DATE(YEAR(主页!$D$2),MONTH(主页!$D$2),1),0)),"") -> 0.16
A4: B | B4: B01 | C4: 天猫 | D4: 2000 | E4: =IF(D4/SUM(D:D)=0,"",D4/SUM(D:D)) -> 0.32258065 | F4: 0.17 | G4: =D4*F4 -> 340 | H4: =IF(G4/SUM(G:G)=0,"",G4/SUM(G:G)) -> 0.29335634 | J4: =IFERROR(SUMIFS(当年实际!$V:$V,当年实际!$F:$F,$C4,当年实际!$C:$C,">="&DATE(YEAR(主页!$D$2),1,1),当年实际!$C:$C,"<="&EOMONTH(DATE(YEAR(主页!$D$2),MONTH(主页!$D$2),1),0))/SUMIFS(当年实际!$P:$P,当年实际!$F:$F,$C4,当年实际!$C:$C,">="&DATE(YEAR(主页!$D$2),1,1),当年实际!$C:$C,"<="&EOMONTH(DATE(YEAR(主页!$D$2),MONTH(主页!$D$2),1),0)),"") -> 0.27777778
A5: C | B5: C01 | C5: 苏宁 | D5: 3000 | E5: =IF(D5/SUM(D:D)=0,"",D5/SUM(D:D)) -> 0.48387097 | F5: 0.133 | G5: =D5*F5 -> 399 | H5: =IF(G5/SUM(G:G)=0,"",G5/SUM(G:G)) -> 0.3442623 | J5: =IFERROR(SUMIFS(当年实际!$V:$V,当年实际!$F:$F,$C5,当年实际!$C:$C,">="&DATE(YEAR(主页!$D$2),1,1),当年实际!$C:$C,"<="&EOMONTH(DATE(YEAR(主页!$D$2),MONTH(主页!$D$2),1),0))/SUMIFS(当年实际!$P:$P,当年实际!$F:$F,$C5,当年实际!$C:$C,">="&DATE(YEAR(主页!$D$2),1,1),当年实际!$C:$C,"<="&EOMONTH(DATE(YEAR(主页!$D$2),MONTH(主页!$D$2),1),0)),"") -> 0.194
E6: =IF(D6/SUM(D:D)=0,"",D6/SUM(D:D)) | G6: =D6*F6 -> 0 | H6: =IF(G6/SUM(G:G)=0,"",G6/SUM(G:G)) | J6: =IFERROR(SUMIFS(当年实际!$V:$V,当年实际!$F:$F,$C6,当年实际!$C:$C,">="&DATE(YEAR(主页!$D$2),1,1),当年实际!$C:$C,"<="&EOMONTH(DATE(YEAR(主页!$D$2),MONTH(主页!$D$2),1),0))/SUMIFS(当年实际!$P:$P,当年实际!$F:$F,$C6,当年实际!$C:$C,">="&DATE(YEAR(主页!$D$2),1,1),当年实际!$C:$C,"<="&EOMONTH(DATE(YEAR(主页!$D$2),MONTH(主页!$D$2),1),0)),"")
E7: =IF(D7/SUM(D:D)=0,"",D7/SUM(D:D)) | G7: =D7*F7 -> 0 | H7: =IF(G7/SUM(G:G)=0,"",G7/SUM(G:G)) | J7: =IFERROR(SUMIFS(当年实际!$V:$V,当年实际!$F:$F,$C7,当年实际!$C:$C,">="&DATE(YEAR(主页!$D$2),1,1),当年实际!$C:$C,"<="&EOMONTH(DATE(YEAR(主页!$D$2),MONTH(主页!$D$2),1),0))/SUMIFS(当年实际!$P:$P,当年实际!$F:$F,$C7,当年实际!$C:$C,">="&DATE(YEAR(主页!$D$2),1,1),当年实际!$C:$C,"<="&EOMONTH(DATE(YEAR(主页!$D$2),MONTH(主页!$D$2),1),0)),"")
E8: =IF(D8/SUM(D:D)=0,"",D8/SUM(D:D)) | G8: =D8*F8 -> 0 | H8: =IF(G8/SUM(G:G)=0,"",G8/SUM(G:G)) | J8: =IFERROR(SUMIFS(当年实际!$V:$V,当年实际!$F:$F,$C8,当年实际!$C:$C,">="&DATE(YEAR(主页!$D$2),1,1),当年实际!$C:$C,"<="&EOMONTH(DATE(YEAR(主页!$D$2),MONTH(主页!$D$2),1),0))/SUMIFS(当年实际!$P:$P,当年实际!$F:$F,$C8,当年实际!$C:$C,">="&DATE(YEAR(主页!$D$2),1,1),当年实际!$C:$C,"<="&EOMONTH(DATE(YEAR(主页!$D$2),MONTH(主页!$D$2),1),0)),"")
E9: =IF(D9/SUM(D:D)=0,"",D9/SUM(D:D)) | G9: =D9*F9 -> 0 | H9: =IF(G9/SUM(G:G)=0,"",G9/SUM(G:G)) | J9: =IFERROR(SUMIFS(当年实际!$V:$V,当年实际!$F:$F,$C9,当年实际!$C:$C,">="&DATE(YEAR(主页!$D$2),1,1),当年实际!$C:$C,"<="&EOMONTH(DATE(YEAR(主页!$D$2),MONTH(主页!$D$2),1),0))/SUMIFS(当年实际!$P:$P,当年实际!$F:$F,$C9,当年实际!$C:$C,">="&DATE(YEAR(主页!$D$2),1,1),当年实际!$C:$C,"<="&EOMONTH(DATE(YEAR(主页!$D$2),MONTH(主页!$D$2),1),0)),"")
E10: =IF(D10/SUM(D:D)=0,"",D10/SUM(D:D)) | G10: =D10*F10 -> 0 | H10: =IF(G10/SUM(G:G)=0,"",G10/SUM(G:G)) | J10: =IFERROR(SUMIFS(当年实际!$V:$V,当年实际!$F:$F,$C10,当年实际!$C:$C,">="&DATE(YEAR(主页!$D$2),1,1),当年实际!$C:$C,"<="&EOMONTH(DATE(YEAR(主页!$D$2),MONTH(主页!$D$2),1),0))/SUMIFS(当年实际!$P:$P,当年实际!$F:$F,$C10,当年实际!$C:$C,">="&DATE(YEAR(主页!$D$2),1,1),当年实际!$C:$C,"<="&EOMONTH(DATE(YEAR(主页!$D$2),MONTH(主页!$D$2),1),0)),"")
E11: =IF(D11/SUM(D:D)=0,"",D11/SUM(D:D)) | G11: =D11*F11 -> 0 | H11: =IF(G11/SUM(G:G)=0,"",G11/SUM(G:G)) | J11: =IFERROR(SUMIFS(当年实际!$V:$V,当年实际!$F:$F,$C11,当年实际!$C:$C,">="&DATE(YEAR(主页!$D$2),1,1),当年实际!$C:$C,"<="&EOMONTH(DATE(YEAR(主页!$D$2),MONTH(主页!$D$2),1),0))/SUMIFS(当年实际!$P:$P,当年实际!$F:$F,$C11,当年实际!$C:$C,">="&DATE(YEAR(主页!$D$2),1,1),当年实际!$C:$C,"<="&EOMONTH(DATE(YEAR(主页!$D$2),MONTH(主页!$D$2),1),0)),"")
E12: =IF(D12/SUM(D:D)=0,"",D12/SUM(D:D)) | G12: =D12*F12 -> 0 | H12: =IF(G12/SUM(G:G)=0,"",G12/SUM(G:G)) | J12: =IFERROR(SUMIFS(当年实际!$V:$V,当年实际!$F:$F,$C12,当年实际!$C:$C,">="&DATE(YEAR(主页!$D$2),1,1),当年实际!$C:$C,"<="&EOMONTH(DATE(YEAR(主页!$D$2),MONTH(主页!$D$2),1),0))/SUMIFS(当年实际!$P:$P,当年实际!$F:$F,$C12,当年实际!$C:$C,">="&DATE(YEAR(主页!$D$2),1,1),当年实际!$C:$C,"<="&EOMONTH(DATE(YEAR(主页!$D$2),MONTH(主页!$D$2),1),0)),"")
E13: =IF(D13/SUM(D:D)=0,"",D13/SUM(D:D)) | G13: =D13*F13 -> 0 | H13: =IF(G13/SUM(G:G)=0,"",G13/SUM(G:G)) | J13: =IFERROR(SUMIFS(当年实际!$V:$V,当年实际!$F:$F,$C13,当年实际!$C:$C,">="&DATE(YEAR(主页!$D$2),1,1),当年实际!$C:$C,"<="&EOMONTH(DATE(YEAR(主页!$D$2),MONTH(主页!$D$2),1),0))/SUMIFS(当年实际!$P:$P,当年实际!$F:$F,$C13,当年实际!$C:$C,">="&DATE(YEAR(主页!$D$2),1,1),当年实际!$C:$C,"<="&EOMONTH(DATE(YEAR(主页!$D$2),MONTH(主页!$D$2),1),0)),"")
E14: =IF(D14/SUM(D:D)=0,"",D14/SUM(D:D)) | G14: =D14*F14 -> 0 | H14: =IF(G14/SUM(G:G)=0,"",G14/SUM(G:G)) | J14: =IFERROR(SUMIFS(当年实际!$V:$V,当年实际!$F:$F,$C14,当年实际!$C:$C,">="&DATE(YEAR(主页!$D$2),1,1),当年实际!$C:$C,"<="&EOMONTH(DATE(YEAR(主页!$D$2),MONTH(主页!$D$2),1),0))/SUMIFS(当年实际!$P:$P,当年实际!$F:$F,$C14,当年实际!$C:$C,">="&DATE(YEAR(主页!$D$2),1,1),当年实际!$C:$C,"<="&EOMONTH(DATE(YEAR(主页!$D$2),MONTH(主页!$D$2),1),0)),"")
E15: =IF(D15/SUM(D:D)=0,"",D15/SUM(D:D)) | G15: =D15*F15 -> 0 | H15: =IF(G15/SUM(G:G)=0,"",G15/SUM(G:G)) | J15: =IFERROR(SUMIFS(当年实际!$V:$V,当年实际!$F:$F,$C15,当年实际!$C:$C,">="&DATE(YEAR(主页!$D$2),1,1),当年实际!$C:$C,"<="&EOMONTH(DATE(YEAR(主页!$D$2),MONTH(主页!$D$2),1),0))/SUMIFS(当年实际!$P:$P,当年实际!$F:$F,$C15,当年实际!$C:$C,">="&DATE(YEAR(主页!$D$2),1,1),当年实际!$C:$C,"<="&EOMONTH(DATE(YEAR(主页!$D$2),MONTH(主页!$D$2),1),0)),"")
E16: =IF(D16/SUM(D:D)=0,"",D16/SUM(D:D)) | G16: =D16*F16 -> 0 | H16: =IF(G16/SUM(G:G)=0,"",G16/SUM(G:G)) | J16: =IFERROR(SUMIFS(当年实际!$V:$V,当年实际!$F:$F,$C16,当年实际!$C:$C,">="&DATE(YEAR(主页!$D$2),1,1),当年实际!$C:$C,"<="&EOMONTH(DATE(YEAR(主页!$D$2),MONTH(主页!$D$2),1),0))/SUMIFS(当年实际!$P:$P,当年实际!$F:$F,$C16,当年实际!$C:$C,">="&DATE(YEAR(主页!$D$2),1,1),当年实际!$C:$C,"<="&EOMONTH(DATE(YEAR(主页!$D$2),MONTH(主页!$D$2),1),0)),"")
E17: =IF(D17/SUM(D:D)=0,"",D17/SUM(D:D)) | G17: =D17*F17 -> 0 | H17: =IF(G17/SUM(G:G)=0,"",G17/SUM(G:G)) | J17: =IFERROR(SUMIFS(当年实际!$V:$V,当年实际!$F:$F,$C17,当年实际!$C:$C,">="&DATE(YEAR(主页!$D$2),1,1),当年实际!$C:$C,"<="&EOMONTH(DATE(YEAR(主页!$D$2),MONTH(主页!$D$2),1),0))/SUMIFS(当年实际!$P:$P,当年实际!$F:$F,$C17,当年实际!$C:$C,">="&DATE(YEAR(主页!$D$2),1,1),当年实际!$C:$C,"<="&EOMONTH(DATE(YEAR(主页!$D$2),MONTH(主页!$D$2),1),0)),"")
... E1200: =IF(D1200/SUM(D:D)=0,"",D1200/SUM(D:D)) | G1200: =D1200*F1200 -> 0 | H1200: =IF(G1200/SUM(G:G)=0,"",G1200/SUM(G:G)) | J1200: =IFERROR(SUMIFS(当年实际!$V:$V,当年实际!$F:$F,$C1200,当年实际!$C:$C,">="&DATE(YEAR(主页!$D$2),1,1),当年实际!$C:$C,"<="&EOMONTH(DATE(YEAR(主页!$D$2),MONTH(主页!$D$2),1),0))/SUMIFS(当年实际!$P:$P,当年实际!$F:$F,$C1200,当年实际!$C:$C,">="&DATE(YEAR(主页!$D$2),1,1),当年实际!$C:$C,"<="&EOMONTH(DATE(YEAR(主页!$D$2),MONTH(主页!$D$2),1),0)),"")

Sheet 当年标准成本
A1: 产品大类 | B1: 产品子类 | C1: 产品名称 | D1: 产品来源 | E1: 外购价格 | F1: 材料成本 | G1: 外协加工费 | H1: 人工及制造费用 | I1: 单位成本 | K1: 返回主页
A2: PA | B2: PA01 | C2: A0111 | D2: 外购 | E2: 13 | I2: =SUM(E2:H2) -> 13
A3: PB | B3: PB01 | C3: B0122 | D3: 自制 | F3: 10 | G3: 1 | H3: 2 | I3: =SUM(E3:H3) -> 13
A4: PC | B4: PC01 | C4: C0122 | D4: 自制 | F4: 5 | G4: 1 | H4: 3 | I4: =SUM(E4:H4) -> 9
A5: PA | B5: PA01 | C5: A0111 | D5: 自制 | F5: 9 | G5: 2 | H5: 3 | I5: =SUM(E5:H5) -> 14
A6: PB | B6: PB01 | C6: B0122 | D6: 自制 | F6: 9 | H6: 5 | I6: =SUM(E6:H6) -> 14
A7: PC | B7: PC01 | C7: C0122 | D7: 自制 | F7: 4 | G7: 2 | H7: 1 | I7: =SUM(E7:H7) -> 7
A8: SE | B8: SE99 | C8: C0199 | D8: 服务 | F8: 80 | G8: 30 | H8: 10 | I8: =SUM(E8:H8) -> 120

Sheet 当年估计 产品
A1: 产品大类 | B1: 产品子类 | C1: 产品名称 | D1: 产品来源 | E1: 销售数量 | F1: 销售收入 | G1: 增值税率 | H1: 不含税销售单价 | I1: 含税单价 | J1: 单位标准成本 | K1: 销售成本 | L1: 销售毛利 | M1: 毛利率 | O1: 返回主页
A2: PA | B2: PA01 | C2: A0111 | D2: 外购 | E2: 70 | F2: 1800 | G2: 0.13 | H2: =IFERROR(F2/E2,"") -> 25.714286 | I2: =IFERROR(H2*(1+G2),"") -> 29.057143 | J2: =IFERROR(INDEX(当年标准成本!I:I,MATCH(C2,当年标准成本!C:C,0),1),"") -> 13 | K2: =IFERROR(E2*J2,"") -> 910 | L2: =IFERROR(F2-K2,"") -> 890 | M2: =IFERROR(L2/F2,"") -> 0.49444444
A3: PB | B3: PB01 | C3: B0122 | D3: 自制 | E3: 89 | F3: 2000 | G3: 0.13 | H3: =IFERROR(F3/E3,"") -> 22.47191 | I3: =IFERROR(H3*(1+G3),"") -> 25.393258 | J3: =IFERROR(INDEX(当年标准成本!I:I,MATCH(C3,当年标准成本!C:C,0),1),"") -> 13 | K3: =IFERROR(E3*J3,"") -> 1157 | L3: =IFERROR(F3-K3,"") -> 843 | M3: =IFERROR(L3/F3,"") -> 0.4215
A4: PC | B4: PC01 | C4: C0122 | D4: 自制 | E4: 77 | F4: 1200 | G4: 0.13 | H4: =IFERROR(F4/E4,"") -> 15.584416 | I4: =IFERROR(H4*(1+G4),"") -> 17.61039 | J4: =IFERROR(INDEX(当年标准成本!I:I,MATCH(C4,当年标准成本!C:C,0),1),"") -> 9 | K4: =IFERROR(E4*J4,"") -> 693 | L4: =IFERROR(F4-K4,"") -> 507 | M4: =IFERROR(L4/F4,"") -> 0.4225
A5: PA | B5: PA01 | C5: A0111 | D5: 自制 | E5: 65 | F5: 1500 | G5: 0.13 | H5: =IFERROR(F5/E5,"") -> 23.076923 | I5: =IFERROR(H5*(1+G5),"") -> 26.076923 | J5: =IFERROR(INDEX(当年标准成本!I:I,MATCH(C5,当年标准成本!C:C,0),1),"") -> 13 | K5: =IFERROR(E5*J5,"") -> 845 | L5: =IFERROR(F5-K5,"") -> 655 | M5: =IFERROR(L5/F5,"") -> 0.43666667
A6: PB | B6: PB01 | C6: B0122 | D6: 自制 | E6: 89 | F6: 1980 | G6: 0.13 | H6: =IFERROR(F6/E6,"") -> 22.247191 | I6: =IFERROR(H6*(1+G6),"") -> 25.139326 | J6: =IFERROR(INDEX(当年标准成本!I:I,MATCH(C6,当年标准成本!C:C,0),1),"") -> 13 | K6: =IFERROR(E6*J6,"") -> 1157 | L6: =IFERROR(F6-K6,"") -> 823 | M6: =IFERROR(L6/F6,"") -> 0.41565657
A7: PC | B7: PC01 | C7: C0122 | D7: 自制 | E7: 65 | F7: 1000 | G7: 0.13 | H7: =IFERROR(F7/E7,"") -> 15.384615 | I7: =IFERROR(H7*(1+G7),"") -> 17.384615 | J7: =IFERROR(INDEX(当年标准成本!I:I,MATCH(C7,当年标准成本!C:C,0),1),"") -> 9 | K7: =IFERROR(E7*J7,"") -> 585 | L7: =IFERROR(F7-K7,"") -> 415 | M7: =IFERROR(L7/F7,"") -> 0.415
A8: SE | B8: SE99 | C8: C0199 | D8: 服务 | E8: 2 | F8: 378 | G8: 0.06 | H8: =IFERROR(F8/E8,"") -> 189 | I8: =IFERROR(H8*(1+G8),"") -> 200.34 | J8: =IFERROR(INDEX(当年标准成本!I:I,MATCH(C8,当年标准成本!C:C,0),1),"") -> 120 | K8: =IFERROR(E8*J8,"") -> 240 | L8: =IFERROR(F8-K8,"") -> 138 | M8: =IFERROR(L8/F8,"") -> 0.36507937
H9: =IFERROR(F9/E9,"") | I9: =IFERROR(H9*(1+G9),"") | J9: =IFERROR(INDEX(当年标准成本!I:I,MATCH(C9,当年标准成本!C:C,0),1),"") | K9: =IFERROR(E9*J9,"") | L9: =IFERROR(F9-K9,"") | M9: =IFERROR(L9/F9,"")
H10: =IFERROR(F10/E10,"") | I10: =IFERROR(H10*(1+G10),"") | J10: =IFERROR(INDEX(当年标准成本!I:I,MATCH(C10,当年标准成本!C:C,0),1),"") | K10: =IFERROR(E10*J10,"") | L10: =IFERROR(F10-K10,"") | M10: =IFERROR(L10/F10,"")
H11: =IFERROR(F11/E11,"") | I11: =IFERROR(H11*(1+G11),"") | J11: =IFERROR(INDEX(当年标准成本!I:I,MATCH(C11,当年标准成本!C:C,0),1),"") | K11: =IFERROR(E11*J11,"") | L11: =IFERROR(F11-K11,"") | M11: =IFERROR(L11/F11,"")
H12: =IFERROR(F12/E12,"") | I12: =IFERROR(H12*(1+G12),"") | J12: =IFERROR(INDEX(当年标准成本!I:I,MATCH(C12,当年标准成本!C:C,0),1),"") | K12: =IFERROR(E12*J12,"") | L12: =IFERROR(F12-K12,"") | M12: =IFERROR(L12/F12,"")
H13: =IFERROR(F13/E13,"") | I13: =IFERROR(H13*(1+G13),"") | J13: =IFERROR(INDEX(当年标准成本!I:I,MATCH(C13,当年标准成本!C:C,0),1),"") | K13: =IFERROR(E13*J13,"") | L13: =IFERROR(F13-K13,"") | M13: =IFERROR(L13/F13,"")
H14: =IFERROR(F14/E14,"") | I14: =IFERROR(H14*(1+G14),"") | J14: =IFERROR(INDEX(当年标准成本!I:I,MATCH(C14,当年标准成本!C:C,0),1),"") | K14: =IFERROR(E14*J14,"") | L14: =IFERROR(F14-K14,"") | M14: =IFERROR(L14/F14,"")
H15: =IFERROR(F15/E15,"") | I15: =IFERROR(H15*(1+G15),"") | J15: =IFERROR(INDEX(当年标准成本!I:I,MATCH(C15,当年标准成本!C:C,0),1),"") | K15: =IFERROR(E15*J15,"") | L15: =IFERROR(F15-K15,"") | M15: =IFERROR(L15/F15,"")
H16: =IFERROR(F16/E16,"") | I16: =IFERROR(H16*(1+G16),"") | J16: =IFERROR(INDEX(当年标准成本!I:I,MATCH(C16,当年标准成本!C:C,0),1),"") | K16: =IFERROR(E16*J16,"") | L16: =IFERROR(F16-K16,"") | M16: =IFERROR(L16/F16,"")
H17: =IFERROR(F17/E17,"") | I17: =IFERROR(H17*(1+G17),"") | J17: =IFERROR(INDEX(当年标准成本!I:I,MATCH(C17,当年标准成本!C:C,0),1),"") | K17: =IFERROR(E17*J17,"") | L17: =IFERROR(F17-K17,"") | M17: =IFERROR(L17/F17,"")
H18: =IFERROR(F18/E18,"") | I18: =IFERROR(H18*(1+G18),"") | J18: =IFERROR(INDEX(当年标准成本!I:I,MATCH(C18,当年标准成本!C:C,0),1),"") | K18: =IFERROR(E18*J18,"") | L18: =IFERROR(F18-K18,"") | M18: =IFERROR(L18/F18,"")
H19: =IFERROR(F19/E19,"") | I19: =IFERROR(H19*(1+G19),"") | J19: =IFERROR(INDEX(当年标准成本!I:I,MATCH(C19,当年标准成本!C:C,0),1),"") | K19: =IFERROR(E19*J19,"") | L19: =IFERROR(F19-K19,"") | M19: =IFERROR(L19/F19,"")
H20: =IFERROR(F20/E20,"") | I20: =IFERROR(H20*(1+G20),"") | J20: =IFERROR(INDEX(当年标准成本!I:I,MATCH(C20,当年标准成本!C:C,0),1),"") | K20: =IFERROR(E20*J20,"") | L20: =IFERROR(F20-K20,"") | M20: =IFERROR(L20/F20,"")
... H1200: =IFERROR(F1200/E1200,"") | I1200: =IFERROR(H1200*(1+G1200),"") | J1200: =IFERROR(INDEX(当年标准成本!I:I,MATCH(C1200,当年标准成本!C:C,0),1),"") | K1200: =IFERROR(E1200*J1200,"") | L1200: =IFERROR(F1200-K1200,"") | M1200: =IFERROR(L1200/F1200,"")

Sheet 下年预算 渠道
A1: 渠道分类 | B1: 渠道名称 | C1: 覆盖客户数量 | D1: ="下年预算 B"&TEXT(主页!$D$2,"YY")+1&"FY" -> 下年预算 B22FY | J1: ="当年已过去月份实际 A"&TEXT(主页!$D$2,"YY")&"YTD" -> 当年已过去月份实际 A21YTD | L1: 返回主页
D2: 销售收入 | E2: 收入占比% | F2: 毛利率 | G2: 销售毛利 | H2: 毛利占比% | J2: 毛利率
A3: SCA | B3: SCA01 | C3: 1 | D3: 1200 | E3: =IF(D3/SUM(D:D)=0,"",D3/SUM(D:D)) -> 0.19354839 | F3: 0.28 | G3: =D3*F3 -> 336 | H3: =IF(G3/SUM(G:G)=0,"",G3/SUM(G:G)) -> 0.28093645 | J3: =IFERROR(SUMIFS(当年实际!$V:$V,当年实际!$H:$H,$B3,当年实际!$C:$C,">="&DATE(YEAR(主页!$D$2),1,1),当年实际!$C:$C,"<="&EOMONTH(DATE(YEAR(主页!$D$2),MONTH(主页!$D$2),1),0))/SUMIFS(当年实际!$P:$P,当年实际!$H:$H,$B3,当年实际!$C:$C,">="&DATE(YEAR(主页!$D$2),1,1),当年实际!$C:$C,"<="&EOMONTH(DATE(YEAR(主页!$D$2),MONTH(主页!$D$2),1),0)),"") -> 0.27777778
A4: SCB | B4: SCB01 | C4: 2 | D4: 2000 | E4: =IF(D4/SUM(D:D)=0,"",D4/SUM(D:D)) -> 0.32258065 | F4: 0.19 | G4: =D4*F4 -> 380 | H4: =IF(G4/SUM(G:G)=0,"",G4/SUM(G:G)) -> 0.31772575 | J4: =IFERROR(SUMIFS(当年实际!$V:$V,当年实际!$H:$H,$B4,当年实际!$C:$C,">="&DATE(YEAR(主页!$D$2),1,1),当年实际!$C:$C,"<="&EOMONTH(DATE(YEAR(主页!$D$2),MONTH(主页!$D$2),1),0))/SUMIFS(当年实际!$P:$P,当年实际!$H:$H,$B4,当年实际!$C:$C,">="&DATE(YEAR(主页!$D$2),1,1),当年实际!$C:$C,"<="&EOMONTH(DATE(YEAR(主页!$D$2),MONTH(主页!$D$2),1),0)),"") -> 0.194
A5: SCC | B5: SCC01 | C5: 3 | D5: 3000 | E5: =IF(D5/SUM(D:D)=0,"",D5/SUM(D:D)) -> 0.48387097 | F5: 0.16 | G5: =D5*F5 -> 480 | H5: =IF(G5/SUM(G:G)=0,"",G5/SUM(G:G)) -> 0.40133779 | J5: =IFERROR(SUMIFS(当年实际!$V:$V,当年实际!$H:$H,$B5,当年实际!$C:$C,">="&DATE(YEAR(主页!$D$2),1,1),当年实际!$C:$C,"<="&EOMONTH(DATE(YEAR(主页!$D$2),MONTH(主页!$D$2),1),0))/SUMIFS(当年实际!$P:$P,当年实际!$H:$H,$B5,当年实际!$C:$C,">="&DATE(YEAR(主页!$D$2),1,1),当年实际!$C:$C,"<="&EOMONTH(DATE(YEAR(主页!$D$2),MONTH(主页!$D$2),1),0)),"") -> 0.16
E6: =IF(D6/SUM(D:D)=0,"",D6/SUM(D:D)) | G6: =D6*F6 -> 0 | H6: =IF(G6/SUM(G:G)=0,"",G6/SUM(G:G)) | J6: =IFERROR(SUMIFS(当年实际!$V:$V,当年实际!$H:$H,$B6,当年实际!$C:$C,">="&DATE(YEAR(主页!$D$2),1,1),当年实际!$C:$C,"<="&EOMONTH(DATE(YEAR(主页!$D$2),MONTH(主页!$D$2),1),0))/SUMIFS(当年实际!$P:$P,当年实际!$H:$H,$B6,当年实际!$C:$C,">="&DATE(YEAR(主页!$D$2),1,1),当年实际!$C:$C,"<="&EOMONTH(DATE(YEAR(主页!$D$2),MONTH(主页!$D$2),1),0)),"")
E7: =IF(D7/SUM(D:D)=0,"",D7/SUM(D:D)) | G7: =D7*F7 -> 0 | H7: =IF(G7/SUM(G:G)=0,"",G7/SUM(G:G)) | J7: =IFERROR(SUMIFS(当年实际!$V:$V,当年实际!$H:$H,$B7,当年实际!$C:$C,">="&DATE(YEAR(主页!$D$2),1,1),当年实际!$C:$C,"<="&EOMONTH(DATE(YEAR(主页!$D$2),MONTH(主页!$D$2),1),0))/SUMIFS(当年实际!$P:$P,当年实际!$H:$H,$B7,当年实际!$C:$C,">="&DATE(YEAR(主页!$D$2),1,1),当年实际!$C:$C,"<="&EOMONTH(DATE(YEAR(主页!$D$2),MONTH(主页!$D$2),1),0)),"")
E8: =IF(D8/SUM(D:D)=0,"",D8/SUM(D:D)) | G8: =D8*F8 -> 0 | H8: =IF(G8/SUM(G:G)=0,"",G8/SUM(G:G)) | J8: =IFERROR(SUMIFS(当年实际!$V:$V,当年实际!$H:$H,$B8,当年实际!$C:$C,">="&DATE(YEAR(主页!$D$2),1,1),当年实际!$C:$C,"<="&EOMONTH(DATE(YEAR(主页!$D$2),MONTH(主页!$D$2),1),0))/SUMIFS(当年实际!$P:$P,当年实际!$H:$H,$B8,当年实际!$C:$C,">="&DATE(YEAR(主页!$D$2),1,1),当年实际!$C:$C,"<="&EOMONTH(DATE(YEAR(主页!$D$2),MONTH(主页!$D$2),1),0)),"")
E9: =IF(D9/SUM(D:D)=0,"",D9/SUM(D:D)) | G9: =D9*F9 -> 0 | H9: =IF(G9/SUM(G:G)=0,"",G9/SUM(G:G)) | J9: =IFERROR(SUMIFS(当年实际!$V:$V,当年实际!$H:$H,$B9,当年实际!$C:$C,">="&DATE(YEAR(主页!$D$2),1,1),当年实际!$C:$C,"<="&EOMONTH(DATE(YEAR(主页!$D$2),MONTH(主页!$D$2),1),0))/SUMIFS(当年实际!$P:$P,当年实际!$H:$H,$B9,当年实际!$C:$C,">="&DATE(YEAR(主页!$D$2),1,1),当年实际!$C:$C,"<="&EOMONTH(DATE(YEAR(主页!$D$2),MONTH(主页!$D$2),1),0)),"")
E10: =IF(D10/SUM(D:D)=0,"",D10/SUM(D:D)) | G10: =D10*F10 -> 0 | H10: =IF(G10/SUM(G:G)=0,"",G10/SUM(G:G)) | J10: =IFERROR(SUMIFS(当年实际!$V:$V,当年实际!$H:$H,$B10,当年实际!$C:$C,">="&DATE(YEAR(主页!$D$2),1,1),当年实际!$C:$C,"<="&EOMONTH(DATE(YEAR(主页!$D$2),MONTH(主页!$D$2),1),0))/SUMIFS(当年实际!$P:$P,当年实际!$H:$H,$B10,当年实际!$C:$C,">="&DATE(YEAR(主页!$D$2),1,1),当年实际!$C:$C,"<="&EOMONTH(DATE(YEAR(主页!$D$2),MONTH(主页!$D$2),1),0)),"")
E11: =IF(D11/SUM(D:D)=0,"",D11/SUM(D:D)) | G11: =D11*F11 -> 0 | H11: =IF(G11/SUM(G:G)=0,"",G11/SUM(G:G)) | J11: =IFERROR(SUMIFS(当年实际!$V:$V,当年实际!$H:$H,$B11,当年实际!$C:$C,">="&DATE(YEAR(主页!$D$2),1,1),当年实际!$C:$C,"<="&EOMONTH(DATE(YEAR(主页!$D$2),MONTH(主页!$D$2),1),0))/SUMIFS(当年实际!$P:$P,当年实际!$H:$H,$B11,当年实际!$C:$C,">="&DATE(YEAR(主页!$D$2),1,1),当年实际!$C:$C,"<="&EOMONTH(DATE(YEAR(主页!$D$2),MONTH(主页!$D$2),1),0)),"")
E12: =IF(D12/SUM(D:D)=0,"",D12/SUM(D:D)) | G12: =D12*F12 -> 0 | H12: =IF(G12/SUM(G:G)=0,"",G12/SUM(G:G)) | J12: =IFERROR(SUMIFS(当年实际!$V:$V,当年实际!$H:$H,$B12,当年实际!$C:$C,">="&DATE(YEAR(主页!$D$2),1,1),当年实际!$C:$C,"<="&EOMONTH(DATE(YEAR(主页!$D$2),MONTH(主页!$D$2),1),0))/SUMIFS(当年实际!$P:$P,当年实际!$H:$H,$B12,当年实际!$C:$C,">="&DATE(YEAR(主页!$D$2),1,1),当年实际!$C:$C,"<="&EOMONTH(DATE(YEAR(主页!$D$2),MONTH(主页!$D$2),1),0)),"")
E13: =IF(D13/SUM(D:D)=0,"",D13/SUM(D:D)) | G13: =D13*F13 -> 0 | H13: =IF(G13/SUM(G:G)=0,"",G13/SUM(G:G)) | J13: =IFERROR(SUMIFS(当年实际!$V:$V,当年实际!$H:$H,$B13,当年实际!$C:$C,">="&DATE(YEAR(主页!$D$2),1,1),当年实际!$C:$C,"<="&EOMONTH(DATE(YEAR(主页!$D$2),MONTH(主页!$D$2),1),0))/SUMIFS(当年实际!$P:$P,当年实际!$H:$H,$B13,当年实际!$C:$C,">="&DATE(YEAR(主页!$D$2),1,1),当年实际!$C:$C,"<="&EOMONTH(DATE(YEAR(主页!$D$2),MONTH(主页!$D$2),1),0)),"")
E14: =IF(D14/SUM(D:D)=0,"",D14/SUM(D:D)) | G14: =D14*F14 -> 0 | H14: =IF(G14/SUM(G:G)=0,"",G14/SUM(G:G)) | J14: =IFERROR(SUMIFS(当年实际!$V:$V,当年实际!$H:$H,$B14,当年实际!$C:$C,">="&DATE(YEAR(主页!$D$2),1,1),当年实际!$C:$C,"<="&EOMONTH(DATE(YEAR(主页!$D$2),MONTH(主页!$D$2),1),0))/SUMIFS(当年实际!$P:$P,当年实际!$H:$H,$B14,当年实际!$C:$C,">="&DATE(YEAR(主页!$D$2),1,1),当年实际!$C:$C,"<="&EOMONTH(DATE(YEAR(主页!$D$2),MONTH(主页!$D$2),1),0)),"")
E15: =IF(D15/SUM(D:D)=0,"",D15/SUM(D:D)) | G15: =D15*F15 -> 0 | H15: =IF(G15/SUM(G:G)=0,"",G15/SUM(G:G)) | J15: =IFERROR(SUMIFS(当年实际!$V:$V,当年实际!$H:$H,$B15,当年实际!$C:$C,">="&DATE(YEAR(主页!$D$2),1,1),当年实际!$C:$C,"<="&EOMONTH(DATE(YEAR(主页!$D$2),MONTH(主页!$D$2),1),0))/SUMIFS(当年实际!$P:$P,当年实际!$H:$H,$B15,当年实际!$C:$C,">="&DATE(YEAR(主页!$D$2),1,1),当年实际!$C:$C,"<="&EOMONTH(DATE(YEAR(主页!$D$2),MONTH(主页!$D$2),1),0)),"")
E16: =IF(D16/SUM(D:D)=0,"",D16/SUM(D:D)) | G16: =D16*F16 -> 0 | H16: =IF(G16/SUM(G:G)=0,"",G16/SUM(G:G)) | J16: =IFERROR(SUMIFS(当年实际!$V:$V,当年实际!$H:$H,$B16,当年实际!$C:$C,">="&DATE(YEAR(主页!$D$2),1,1),当年实际!$C:$C,"<="&EOMONTH(DATE(YEAR(主页!$D$2),MONTH(主页!$D$2),1),0))/SUMIFS(当年实际!$P:$P,当年实际!$H:$H,$B16,当年实际!$C:$C,">="&DATE(YEAR(主页!$D$2),1,1),当年实际!$C:$C,"<="&EOMONTH(DATE(YEAR(主页!$D$2),MONTH(主页!$D$2),1),0)),"")
E17: =IF(D17/SUM(D:D)=0,"",D17/SUM(D:D)) | G17: =D17*F17 -> 0 | H17: =IF(G17/SUM(G:G)=0,"",G17/SUM(G:G)) | J17: =IFERROR(SUMIFS(当年实际!$V:$V,当年实际!$H:$H,$B17,当年实际!$C:$C,">="&DATE(YEAR(主页!$D$2),1,1),当年实际!$C:$C,"<="&EOMONTH(DATE(YEAR(主页!$D$2),MONTH(主页!$D$2),1),0))/SUMIFS(当年实际!$P:$P,当年实际!$H:$H,$B17,当年实际!$C:$C,">="&DATE(YEAR(主页!$D$2),1,1),当年实际!$C:$C,"<="&EOMONTH(DATE(YEAR(主页!$D$2),MONTH(主页!$D$2),1),0)),"")
... E333: =IF(D333/SUM(D:D)=0,"",D333/SUM(D:D)) | G333: =D333*F333 -> 0 | H333: =IF(G333/SUM(G:G)=0,"",G333/SUM(G:G)) | J333: =IFERROR(SUMIFS(当年实际!$V:$V,当年实际!$H:$H,$B333,当年实际!$C:$C,">="&DATE(YEAR(主页!$D$2),1,1),当年实际!$C:$C,"<="&EOMONTH(DATE(YEAR(主页!$D$2),MONTH(主页!$D$2),1),0))/SUMIFS(当年实际!$P:$P,当年实际!$H:$H,$B333,当年实际!$C:$C,">="&DATE(YEAR(主页!$D$2),1,1),当年实际!$C:$C,"<="&EOMONTH(DATE(YEAR(主页!$D$2),MONTH(主页!$D$2),1),0)),"")

Sheet 下年预算 业务员
A1: 销售大区 | B1: 办事处 | C1: 业务员 | D1: ="下年预算 B"&TEXT(主页!$D$2,"YY")+1&"FY" -> 下年预算 B22FY | J1: ="当年已过去月份实际 A"&TEXT(主页!$D$2,"YY")&"YTD" -> 当年已过去月份实际 A21YTD | L1: 返回主页
A2: 销售大区 | B2: 办事处 | C2: 业务员 | D2: 销售收入 | E2: 收入占比% | F2: 毛利率 | G2: 销售毛利 | H2: 毛利占比% | J2: 毛利率
A3: 东区 | B3: 北京 | C3: 张三 | D3: 1300 | E3: =IF(D3/SUM(D:D)=0,"",D3/SUM(D:D)) -> 0.21311475 | F3: 0.28 | G3: =D3*F3 -> 364 | H3: =IF(G3/SUM(G:G)=0,"",G3/SUM(G:G)) -> 0.28482003 | J3: =IFERROR(SUMIFS(当年实际!$V:$V,当年实际!$J:$J,$C3,当年实际!$C:$C,">="&DATE(YEAR(主页!$D$2),1,1),当年实际!$C:$C,"<="&EOMONTH(DATE(YEAR(主页!$D$2),MONTH(主页!$D$2),1),0))/SUMIFS(当年实际!$P:$P,当年实际!$J:$J,$C3,当年实际!$C:$C,">="&DATE(YEAR(主页!$D$2),1,1),当年实际!$C:$C,"<="&EOMONTH(DATE(YEAR(主页!$D$2),MONTH(主页!$D$2),1),0)),"") -> 0.27777778
A4: 南区 | B4: 上海 | C4: 李四 | D4: 2500 | E4: =IF(D4/SUM(D:D)=0,"",D4/SUM(D:D)) -> 0.40983607 | F4: 0.2 | G4: =D4*F4 -> 500 | H4: =IF(G4/SUM(G:G)=0,"",G4/SUM(G:G)) -> 0.39123631 | J4: =IFERROR(SUMIFS(当年实际!$V:$V,当年实际!$J:$J,$C4,当年实际!$C:$C,">="&DATE(YEAR(主页!$D$2),1,1),当年实际!$C:$C,"<="&EOMONTH(DATE(YEAR(主页!$D$2),MONTH(主页!$D$2),1),0))/SUMIFS(当年实际!$P:$P,当年实际!$J:$J,$C4,当年实际!$C:$C,">="&DATE(YEAR(主页!$D$2),1,1),当年实际!$C:$C,"<="&EOMONTH(DATE(YEAR(主页!$D$2),MONTH(主页!$D$2),1),0)),"") -> 0.194
A5: 北区 | B5: 广州 | C5: 王二麻子 | D5: 2300 | E5: =IF(D5/SUM(D:D)=0,"",D5/SUM(D:D)) -> 0.37704918 | F5: 0.18 | G5: =D5*F5 -> 414 | H5: =IF(G5/SUM(G:G)=0,"",G5/SUM(G:G)) -> 0.32394366 | J5: =IFERROR(SUMIFS(当年实际!$V:$V,当年实际!$J:$J,$C5,当年实际!$C:$C,">="&DATE(YEAR(主页!$D$2),1,1),当年实际!$C:$C,"<="&EOMONTH(DATE(YEAR(主页!$D$2),MONTH(主页!$D$2),1),0))/SUMIFS(当年实际!$P:$P,当年实际!$J:$J,$C5,当年实际!$C:$C,">="&DATE(YEAR(主页!$D$2),1,1),当年实际!$C:$C,"<="&EOMONTH(DATE(YEAR(主页!$D$2),MONTH(主页!$D$2),1),0)),"") -> 0.16
E6: =IF(D6/SUM(D:D)=0,"",D6/SUM(D:D)) | G6: =D6*F6 -> 0 | H6: =IF(G6/SUM(G:G)=0,"",G6/SUM(G:G)) | J6: =IFERROR(SUMIFS(当年实际!$V:$V,当年实际!$J:$J,$C6,当年实际!$C:$C,">="&DATE(YEAR(主页!$D$2),1,1),当年实际!$C:$C,"<="&EOMONTH(DATE(YEAR(主页!$D$2),MONTH(主页!$D$2),1),0))/SUMIFS(当年实际!$P:$P,当年实际!$J:$J,$C6,当年实际!$C:$C,">="&DATE(YEAR(主页!$D$2),1,1),当年实际!$C:$C,"<="&EOMONTH(DATE(YEAR(主页!$D$2),MONTH(主页!$D$2),1),0)),"")
E7: =IF(D7/SUM(D:D)=0,"",D7/SUM(D:D)) | G7: =D7*F7 -> 0 | H7: =IF(G7/SUM(G:G)=0,"",G7/SUM(G:G)) | J7: =IFERROR(SUMIFS(当年实际!$V:$V,当年实际!$J:$J,$C7,当年实际!$C:$C,">="&DATE(YEAR(主页!$D$2),1,1),当年实际!$C:$C,"<="&EOMONTH(DATE(YEAR(主页!$D$2),MONTH(主页!$D$2),1),0))/SUMIFS(当年实际!$P:$P,当年实际!$J:$J,$C7,当年实际!$C:$C,">="&DATE(YEAR(主页!$D$2),1,1),当年实际!$C:$C,"<="&EOMONTH(DATE(YEAR(主页!$D$2),MONTH(主页!$D$2),1),0)),"")
E8: =IF(D8/SUM(D:D)=0,"",D8/SUM(D:D)) | G8: =D8*F8 -> 0 | H8: =IF(G8/SUM(G:G)=0,"",G8/SUM(G:G)) | J8: =IFERROR(SUMIFS(当年实际!$V:$V,当年实际!$J:$J,$C8,当年实际!$C:$C,">="&DATE(YEAR(主页!$D$2),1,1),当年实际!$C:$C,"<="&EOMONTH(DATE(YEAR(主页!$D$2),MONTH(主页!$D$2),1),0))/SUMIFS(当年实际!$P:$P,当年实际!$J:$J,$C8,当年实际!$C:$C,">="&DATE(YEAR(主页!$D$2),1,1),当年实际!$C:$C,"<="&EOMONTH(DATE(YEAR(主页!$D$2),MONTH(主页!$D$2),1),0)),"")
E9: =IF(D9/SUM(D:D)=0,"",D9/SUM(D:D)) | G9: =D9*F9 -> 0 | H9: =IF(G9/SUM(G:G)=0,"",G9/SUM(G:G)) | J9: =IFERROR(SUMIFS(当年实际!$V:$V,当年实际!$J:$J,$C9,当年实际!$C:$C,">="&DATE(YEAR(主页!$D$2),1,1),当年实际!$C:$C,"<="&EOMONTH(DATE(YEAR(主页!$D$2),MONTH(主页!$D$2),1),0))/SUMIFS(当年实际!$P:$P,当年实际!$J:$J,$C9,当年实际!$C:$C,">="&DATE(YEAR(主页!$D$2),1,1),当年实际!$C:$C,"<="&EOMONTH(DATE(YEAR(主页!$D$2),MONTH(主页!$D$2),1),0)),"")
E10: =IF(D10/SUM(D:D)=0,"",D10/SUM(D:D)) | G10: =D10*F10 -> 0 | H10: =IF(G10/SUM(G:G)=0,"",G10/SUM(G:G)) | J10: =IFERROR(SUMIFS(当年实际!$V:$V,当年实际!$J:$J,$C10,当年实际!$C:$C,">="&DATE(YEAR(主页!$D$2),1,1),当年实际!$C:$C,"<="&EOMONTH(DATE(YEAR(主页!$D$2),MONTH(主页!$D$2),1),0))/SUMIFS(当年实际!$P:$P,当年实际!$J:$J,$C10,当年实际!$C:$C,">="&DATE(YEAR(主页!$D$2),1,1),当年实际!$C:$C,"<="&EOMONTH(DATE(YEAR(主页!$D$2),MONTH(主页!$D$2),1),0)),"")
E11: =IF(D11/SUM(D:D)=0,"",D11/SUM(D:D)) | G11: =D11*F11 -> 0 | H11: =IF(G11/SUM(G:G)=0,"",G11/SUM(G:G)) | J11: =IFERROR(SUMIFS(当年实际!$V:$V,当年实际!$J:$J,$C11,当年实际!$C:$C,">="&DATE(YEAR(主页!$D$2),1,1),当年实际!$C:$C,"<="&EOMONTH(DATE(YEAR(主页!$D$2),MONTH(主页!$D$2),1),0))/SUMIFS(当年实际!$P:$P,当年实际!$J:$J,$C11,当年实际!$C:$C,">="&DATE(YEAR(主页!$D$2),1,1),当年实际!$C:$C,"<="&EOMONTH(DATE(YEAR(主页!$D$2),MONTH(主页!$D$2),1),0)),"")
E12: =IF(D12/SUM(D:D)=0,"",D12/SUM(D:D)) | G12: =D12*F12 -> 0 | H12: =IF(G12/SUM(G:G)=0,"",G12/SUM(G:G)) | J12: =IFERROR(SUMIFS(当年实际!$V:$V,当年实际!$J:$J,$C12,当年实际!$C:$C,">="&DATE(YEAR(主页!$D$2),1,1),当年实际!$C:$C,"<="&EOMONTH(DATE(YEAR(主页!$D$2),MONTH(主页!$D$2),1),0))/SUMIFS(当年实际!$P:$P,当年实际!$J:$J,$C12,当年实际!$C:$C,">="&DATE(YEAR(主页!$D$2),1,1),当年实际!$C:$C,"<="&EOMONTH(DATE(YEAR(主页!$D$2),MONTH(主页!$D$2),1),0)),"")
E13: =IF(D13/SUM(D:D)=0,"",D13/SUM(D:D)) | G13: =D13*F13 -> 0 | H13: =IF(G13/SUM(G:G)=0,"",G13/SUM(G:G)) | J13: =IFERROR(SUMIFS(当年实际!$V:$V,当年实际!$J:$J,$C13,当年实际!$C:$C,">="&DATE(YEAR(主页!$D$2),1,1),当年实际!$C:$C,"<="&EOMONTH(DATE(YEAR(主页!$D$2),MONTH(主页!$D$2),1),0))/SUMIFS(当年实际!$P:$P,当年实际!$J:$J,$C13,当年实际!$C:$C,">="&DATE(YEAR(主页!$D$2),1,1),当年实际!$C:$C,"<="&EOMONTH(DATE(YEAR(主页!$D$2),MONTH(主页!$D$2),1),0)),"")
E14: =IF(D14/SUM(D:D)=0,"",D14/SUM(D:D)) | G14: =D14*F14 -> 0 | H14: =IF(G14/SUM(G:G)=0,"",G14/SUM(G:G)) | J14: =IFERROR(SUMIFS(当年实际!$V:$V,当年实际!$J:$J,$C14,当年实际!$C:$C,">="&DATE(YEAR(主页!$D$2),1,1),当年实际!$C:$C,"<="&EOMONTH(DATE(YEAR(主页!$D$2),MONTH(主页!$D$2),1),0))/SUMIFS(当年实际!$P:$P,当年实际!$J:$J,$C14,当年实际!$C:$C,">="&DATE(YEAR(主页!$D$2),1,1),当年实际!$C:$C,"<="&EOMONTH(DATE(YEAR(主页!$D$2),MONTH(主页!$D$2),1),0)),"")
E15: =IF(D15/SUM(D:D)=0,"",D15/SUM(D:D)) | G15: =D15*F15 -> 0 | H15: =IF(G15/SUM(G:G)=0,"",G15/SUM(G:G)) | J15: =IFERROR(SUMIFS(当年实际!$V:$V,当年实际!$J:$J,$C15,当年实际!$C:$C,">="&DATE(YEAR(主页!$D$2),1,1),当年实际!$C:$C,"<="&EOMONTH(DATE(YEAR(主页!$D$2),MONTH(主页!$D$2),1),0))/SUMIFS(当年实际!$P:$P,当年实际!$J:$J,$C15,当年实际!$C:$C,">="&DATE(YEAR(主页!$D$2),1,1),当年实际!$C:$C,"<="&EOMONTH(DATE(YEAR(主页!$D$2),MONTH(主页!$D$2),1),0)),"")
E16: =IF(D16/SUM(D:D)=0,"",D16/SUM(D:D)) | G16: =D16*F16 -> 0 | H16: =IF(G16/SUM(G:G)=0,"",G16/SUM(G:G)) | J16: =IFERROR(SUMIFS(当年实际!$V:$V,当年实际!$J:$J,$C16,当年实际!$C:$C,">="&DATE(YEAR(主页!$D$2),1,1),当年实际!$C:$C,"<="&EOMONTH(DATE(YEAR(主页!$D$2),MONTH(主页!$D$2),1),0))/SUMIFS(当年实际!$P:$P,当年实际!$J:$J,$C16,当年实际!$C:$C,">="&DATE(YEAR(主页!$D$2),1,1),当年实际!$C:$C,"<="&EOMONTH(DATE(YEAR(主页!$D$2),MONTH(主页!$D$2),1),0)),"")
E17: =IF(D17/SUM(D:D)=0,"",D17/SUM(D:D)) | G17: =D17*F17 -> 0 | H17: =IF(G17/SUM(G:G)=0,"",G17/SUM(G:G)) | J17: =IFERROR(SUMIFS(当年实际!$V:$V,当年实际!$J:$J,$C17,当年实际!$C:$C,">="&DATE(YEAR(主页!$D$2),1,1),当年实际!$C:$C,"<="&EOMONTH(DATE(YEAR(主页!$D$2),MONTH(主页!$D$2),1),0))/SUMIFS(当年实际!$P:$P,当年实际!$J:$J,$C17,当年实际!$C:$C,">="&DATE(YEAR(主页!$D$2),1,1),当年实际!$C:$C,"<="&EOMONTH(DATE(YEAR(主页!$D$2),MONTH(主页!$D$2),1),0)),"")
... E150: =IF(D150/SUM(D:D)=0,"",D150/SUM(D:D)) | G150: =D150*F150 -> 0 | H150: =IF(G150/SUM(G:G)=0,"",G150/SUM(G:G)) | J150: =IFERROR(SUMIFS(当年实际!$V:$V,当年实际!$J:$J,$C150,当年实际!$C:$C,">="&DATE(YEAR(主页!$D$2),1,1),当年实际!$C:$C,"<="&EOMONTH(DATE(YEAR(主页!$D$2),MONTH(主页!$D$2),1),0))/SUMIFS(当年实际!$P:$P,当年实际!$J:$J,$C150,当年实际!$C:$C,">="&DATE(YEAR(主页!$D$2),1,1),当年实际!$C:$C,"<="&EOMONTH(DATE(YEAR(主页!$D$2),MONTH(主页!$D$2),1),0)),"")

Sheet 下年预算 客户
A1: 客户大类 | B1: 客户子类 | C1: 客户名称 | D1: ="当年剩余月份估计 E"&TEXT(主页!$D$2,"YY")&"YTG" -> 当年剩余月份估计 E21YTG | J1: ="当年已过去月份实际 A"&TEXT(主页!$D$2,"YY")&"YTD" -> 当年已过去月份实际 A21YTD | L1: 返回主页
A2: 客户大类 | B2: 客户子类 | C2: 客户名称 | D2: 销售收入 | E2: 收入占比% | F2: 毛利率 | G2: 销售毛利 | H2: 毛利占比% | J2: 毛利率
A3: A | B3: A01 | C3: 京东 | D3: 1200 | E3: =IF(D3/SUM(D:D)=0,"",D3/SUM(D:D)) -> 0.19354839 | F3: 0.16 | G3: =D3*F3 -> 192 | H3: =IF(G3/SUM(G:G)=0,"",G3/SUM(G:G)) -> 0.14201183 | J3: =IFERROR(SUMIFS(当年实际!$V:$V,当年实际!$F:$F,$C3,当年实际!$C:$C,">="&DATE(YEAR(主页!$D$2),1,1),当年实际!$C:$C,"<="&EOMONTH(DATE(YEAR(主页!$D$2),MONTH(主页!$D$2),1),0))/SUMIFS(当年实际!$P:$P,当年实际!$F:$F,$C3,当年实际!$C:$C,">="&DATE(YEAR(主页!$D$2),1,1),当年实际!$C:$C,"<="&EOMONTH(DATE(YEAR(主页!$D$2),MONTH(主页!$D$2),1),0)),"") -> 0.16
A4: B | B4: B01 | C4: 天猫 | D4: 2000 | E4: =IF(D4/SUM(D:D)=0,"",D4/SUM(D:D)) -> 0.32258065 | F4: 0.28 | G4: =D4*F4 -> 560 | H4: =IF(G4/SUM(G:G)=0,"",G4/SUM(G:G)) -> 0.41420118 | J4: =IFERROR(SUMIFS(当年实际!$V:$V,当年实际!$F:$F,$C4,当年实际!$C:$C,">="&DATE(YEAR(主页!$D$2),1,1),当年实际!$C:$C,"<="&EOMONTH(DATE(YEAR(主页!$D$2),MONTH(主页!$D$2),1),0))/SUMIFS(当年实际!$P:$P,当年实际!$F:$F,$C4,当年实际!$C:$C,">="&DATE(YEAR(主页!$D$2),1,1),当年实际!$C:$C,"<="&EOMONTH(DATE(YEAR(主页!$D$2),MONTH(主页!$D$2),1),0)),"") -> 0.27777778
A5: C | B5: C01 | C5: 苏宁 | D5: 3000 | E5: =IF(D5/SUM(D:D)=0,"",D5/SUM(D:D)) -> 0.48387097 | F5: 0.2 | G5: =D5*F5 -> 600 | H5: =IF(G5/SUM(G:G)=0,"",G5/SUM(G:G)) -> 0.44378698 | J5: =IFERROR(SUMIFS(当年实际!$V:$V,当年实际!$F:$F,$C5,当年实际!$C:$C,">="&DATE(YEAR(主页!$D$2),1,1),当年实际!$C:$C,"<="&EOMONTH(DATE(YEAR(主页!$D$2),MONTH(主页!$D$2),1),0))/SUMIFS(当年实际!$P:$P,当年实际!$F:$F,$C5,当年实际!$C:$C,">="&DATE(YEAR(主页!$D$2),1,1),当年实际!$C:$C,"<="&EOMONTH(DATE(YEAR(主页!$D$2),MONTH(主页!$D$2),1),0)),"") -> 0.194
E6: =IF(D6/SUM(D:D)=0,"",D6/SUM(D:D)) | G6: =D6*F6 -> 0 | H6: =IF(G6/SUM(G:G)=0,"",G6/SUM(G:G)) | J6: =IFERROR(SUMIFS(当年实际!$V:$V,当年实际!$F:$F,$C6,当年实际!$C:$C,">="&DATE(YEAR(主页!$D$2),1,1),当年实际!$C:$C,"<="&EOMONTH(DATE(YEAR(主页!$D$2),MONTH(主页!$D$2),1),0))/SUMIFS(当年实际!$P:$P,当年实际!$F:$F,$C6,当年实际!$C:$C,">="&DATE(YEAR(主页!$D$2),1,1),当年实际!$C:$C,"<="&EOMONTH(DATE(YEAR(主页!$D$2),MONTH(主页!$D$2),1),0)),"")
E7: =IF(D7/SUM(D:D)=0,"",D7/SUM(D:D)) | G7: =D7*F7 -> 0 | H7: =IF(G7/SUM(G:G)=0,"",G7/SUM(G:G)) | J7: =IFERROR(SUMIFS(当年实际!$V:$V,当年实际!$F:$F,$C7,当年实际!$C:$C,">="&DATE(YEAR(主页!$D$2),1,1),当年实际!$C:$C,"<="&EOMONTH(DATE(YEAR(主页!$D$2),MONTH(主页!$D$2),1),0))/SUMIFS(当年实际!$P:$P,当年实际!$F:$F,$C7,当年实际!$C:$C,">="&DATE(YEAR(主页!$D$2),1,1),当年实际!$C:$C,"<="&EOMONTH(DATE(YEAR(主页!$D$2),MONTH(主页!$D$2),1),0)),"")
E8: =IF(D8/SUM(D:D)=0,"",D8/SUM(D:D)) | G8: =D8*F8 -> 0 | H8: =IF(G8/SUM(G:G)=0,"",G8/SUM(G:G)) | J8: =IFERROR(SUMIFS(当年实际!$V:$V,当年实际!$F:$F,$C8,当年实际!$C:$C,">="&DATE(YEAR(主页!$D$2),1,1),当年实际!$C:$C,"<="&EOMONTH(DATE(YEAR(主页!$D$2),MONTH(主页!$D$2),1),0))/SUMIFS(当年实际!$P:$P,当年实际!$F:$F,$C8,当年实际!$C:$C,">="&DATE(YEAR(主页!$D$2),1,1),当年实际!$C:$C,"<="&EOMONTH(DATE(YEAR(主页!$D$2),MONTH(主页!$D$2),1),0)),"")
E9: =IF(D9/SUM(D:D)=0,"",D9/SUM(D:D)) | G9: =D9*F9 -> 0 | H9: =IF(G9/SUM(G:G)=0,"",G9/SUM(G:G)) | J9: =IFERROR(SUMIFS(当年实际!$V:$V,当年实际!$F:$F,$C9,当年实际!$C:$C,">="&DATE(YEAR(主页!$D$2),1,1),当年实际!$C:$C,"<="&EOMONTH(DATE(YEAR(主页!$D$2),MONTH(主页!$D$2),1),0))/SUMIFS(当年实际!$P:$P,当年实际!$F:$F,$C9,当年实际!$C:$C,">="&DATE(YEAR(主页!$D$2),1,1),当年实际!$C:$C,"<="&EOMONTH(DATE(YEAR(主页!$D$2),MONTH(主页!$D$2),1),0)),"")
E10: =IF(D10/SUM(D:D)=0,"",D10/SUM(D:D)) | G10: =D10*F10 -> 0 | H10: =IF(G10/SUM(G:G)=0,"",G10/SUM(G:G)) | J10: =IFERROR(SUMIFS(当年实际!$V:$V,当年实际!$F:$F,$C10,当年实际!$C:$C,">="&DATE(YEAR(主页!$D$2),1,1),当年实际!$C:$C,"<="&EOMONTH(DATE(YEAR(主页!$D$2),MONTH(主页!$D$2),1),0))/SUMIFS(当年实际!$P:$P,当年实际!$F:$F,$C10,当年实际!$C:$C,">="&DATE(YEAR(主页!$D$2),1,1),当年实际!$C:$C,"<="&EOMONTH(DATE(YEAR(主页!$D$2),MONTH(主页!$D$2),1),0)),"")
E11: =IF(D11/SUM(D:D)=0,"",D11/SUM(D:D)) | G11: =D11*F11 -> 0 | H11: =IF(G11/SUM(G:G)=0,"",G11/SUM(G:G)) | J11: =IFERROR(SUMIFS(当年实际!$V:$V,当年实际!$F:$F,$C11,当年实际!$C:$C,">="&DATE(YEAR(主页!$D$2),1,1),当年实际!$C:$C,"<="&EOMONTH(DATE(YEAR(主页!$D$2),MONTH(主页!$D$2),1),0))/SUMIFS(当年实际!$P:$P,当年实际!$F:$F,$C11,当年实际!$C:$C,">="&DATE(YEAR(主页!$D$2),1,1),当年实际!$C:$C,"<="&EOMONTH(DATE(YEAR(主页!$D$2),MONTH(主页!$D$2),1),0)),"")
E12: =IF(D12/SUM(D:D)=0,"",D12/SUM(D:D)) | G12: =D12*F12 -> 0 | H12: =IF(G12/SUM(G:G)=0,"",G12/SUM(G:G)) | J12: =IFERROR(SUMIFS(当年实际!$V:$V,当年实际!$F:$F,$C12,当年实际!$C:$C,">="&DATE(YEAR(主页!$D$2),1,1),当年实际!$C:$C,"<="&EOMONTH(DATE(YEAR(主页!$D$2),MONTH(主页!$D$2),1),0))/SUMIFS(当年实际!$P:$P,当年实际!$F:$F,$C12,当年实际!$C:$C,">="&DATE(YEAR(主页!$D$2),1,1),当年实际!$C:$C,"<="&EOMONTH(DATE(YEAR(主页!$D$2),MONTH(主页!$D$2),1),0)),"")
E13: =IF(D13/SUM(D:D)=0,"",D13/SUM(D:D)) | G13: =D13*F13 -> 0 | H13: =IF(G13/SUM(G:G)=0,"",G13/SUM(G:G)) | J13: =IFERROR(SUMIFS(当年实际!$V:$V,当年实际!$F:$F,$C13,当年实际!$C:$C,">="&DATE(YEAR(主页!$D$2),1,1),当年实际!$C:$C,"<="&EOMONTH(DATE(YEAR(主页!$D$2),MONTH(主页!$D$2),1),0))/SUMIFS(当年实际!$P:$P,当年实际!$F:$F,$C13,当年实际!$C:$C,">="&DATE(YEAR(主页!$D$2),1,1),当年实际!$C:$C,"<="&EOMONTH(DATE(YEAR(主页!$D$2),MONTH(主页!$D$2),1),0)),"")
E14: =IF(D14/SUM(D:D)=0,"",D14/SUM(D:D)) | G14: =D14*F14 -> 0 | H14: =IF(G14/SUM(G:G)=0,"",G14/SUM(G:G)) | J14: =IFERROR(SUMIFS(当年实际!$V:$V,当年实际!$F:$F,$C14,当年实际!$C:$C,">="&DATE(YEAR(主页!$D$2),1,1),当年实际!$C:$C,"<="&EOMONTH(DATE(YEAR(主页!$D$2),MONTH(主页!$D$2),1),0))/SUMIFS(当年实际!$P:$P,当年实际!$F:$F,$C14,当年实际!$C:$C,">="&DATE(YEAR(主页!$D$2),1,1),当年实际!$C:$C,"<="&EOMONTH(DATE(YEAR(主页!$D$2),MONTH(主页!$D$2),1),0)),"")
E15: =IF(D15/SUM(D:D)=0,"",D15/SUM(D:D)) | G15: =D15*F15 -> 0 | H15: =IF(G15/SUM(G:G)=0,"",G15/SUM(G:G)) | J15: =IFERROR(SUMIFS(当年实际!$V:$V,当年实际!$F:$F,$C15,当年实际!$C:$C,">="&DATE(YEAR(主页!$D$2),1,1),当年实际!$C:$C,"<="&EOMONTH(DATE(YEAR(主页!$D$2),MONTH(主页!$D$2),1),0))/SUMIFS(当年实际!$P:$P,当年实际!$F:$F,$C15,当年实际!$C:$C,">="&DATE(YEAR(主页!$D$2),1,1),当年实际!$C:$C,"<="&EOMONTH(DATE(YEAR(主页!$D$2),MONTH(主页!$D$2),1),0)),"")
E16: =IF(D16/SUM(D:D)=0,"",D16/SUM(D:D)) | G16: =D16*F16 -> 0 | H16: =IF(G16/SUM(G:G)=0,"",G16/SUM(G:G)) | J16: =IFERROR(SUMIFS(当年实际!$V:$V,当年实际!$F:$F,$C16,当年实际!$C:$C,">="&DATE(YEAR(主页!$D$2),1,1),当年实际!$C:$C,"<="&EOMONTH(DATE(YEAR(主页!$D$2),MONTH(主页!$D$2),1),0))/SUMIFS(当年实际!$P:$P,当年实际!$F:$F,$C16,当年实际!$C:$C,">="&DATE(YEAR(主页!$D$2),1,1),当年实际!$C:$C,"<="&EOMONTH(DATE(YEAR(主页!$D$2),MONTH(主页!$D$2),1),0)),"")
E17: =IF(D17/SUM(D:D)=0,"",D17/SUM(D:D)) | G17: =D17*F17 -> 0 | H17: =IF(G17/SUM(G:G)=0,"",G17/SUM(G:G)) | J17: =IFERROR(SUMIFS(当年实际!$V:$V,当年实际!$F:$F,$C17,当年实际!$C:$C,">="&DATE(YEAR(主页!$D$2),1,1),当年实际!$C:$C,"<="&EOMONTH(DATE(YEAR(主页!$D$2),MONTH(主页!$D$2),1),0))/SUMIFS(当年实际!$P:$P,当年实际!$F:$F,$C17,当年实际!$C:$C,">="&DATE(YEAR(主页!$D$2),1,1),当年实际!$C:$C,"<="&EOMONTH(DATE(YEAR(主页!$D$2),MONTH(主页!$D$2),1),0)),"")
... E1230: =IF(D1230/SUM(D:D)=0,"",D1230/SUM(D:D)) | G1230: =D1230*F1230 -> 0 | H1230: =IF(G1230/SUM(G:G)=0,"",G1230/SUM(G:G)) | J1230: =IFERROR(SUMIFS(当年实际!$V:$V,当年实际!$F:$F,$C1230,当年实际!$C:$C,">="&DATE(YEAR(主页!$D$2),1,1),当年实际!$C:$C,"<="&EOMONTH(DATE(YEAR(主页!$D$2),MONTH(主页!$D$2),1),0))/SUMIFS(当年实际!$P:$P,当年实际!$F:$F,$C1230,当年实际!$C:$C,">="&DATE(YEAR(主页!$D$2),1,1),当年实际!$C:$C,"<="&EOMONTH(DATE(YEAR(主页!$D$2),MONTH(主页!$D$2),1),0)),"")

Sheet 下年标准成本
A1: 产品大类 | B1: 产品子类 | C1: 产品名称 | D1: 产品来源 | E1: 外购价格 | F1: 材料成本 | G1: 外协加工费 | H1: 人工及制造费用 | I1: 单位成本 | K1: 返回主页
A2: PA | B2: PA01 | C2: A0111 | D2: 外购 | E2: 14 | I2: =SUM(E2:H2) -> 14
A3: PB | B3: PB01 | C3: B0122 | D3: 自制 | F3: 11 | G3: 1 | H3: 2 | I3: =SUM(E3:H3) -> 14
A4: PC | B4: PC01 | C4: C0122 | D4: 自制 | F4: 6 | G4: 1 | H4: 3 | I4: =SUM(E4:H4) -> 10
A5: PA | B5: PA01 | C5: A0111 | D5: 自制 | F5: 12 | G5: 2 | H5: 3 | I5: =SUM(E5:H5) -> 17
A6: PB | B6: PB01 | C6: B0122 | D6: 自制 | F6: 7 | H6: 5 | I6: =SUM(E6:H6) -> 12
A7: PC | B7: PC01 | C7: C0122 | D7: 自制 | F7: 3 | G7: 2 | H7: 1 | I7: =SUM(E7:H7) -> 6
A8: SE | B8: SE99 | C8: C0199 | D8: 服务 | F8: 76 | G8: 30 | H8: 10 | I8: =SUM(E8:H8) -> 116

Sheet 下年预算 产品
A1: 产品大类 | B1: 产品子类 | C1: 产品名称 | D1: 产品来源 | E1: 销售数量 | F1: 销售收入 | G1: 增值税率 | H1: 不含税销售单价 | I1: 含税单价 | J1: 单位标准成本 | K1: 销售成本 | L1: 销售毛利 | M1: 毛利率 | O1: 返回主页
A2: PA | B2: PA01 | C2: A0111 | D2: 外购 | E2: 280 | F2: 4800 | G2: 0.13 | H2: =IFERROR(F2/E2,"") -> 17.142857 | I2: =IFERROR(H2*(1+G2),"") -> 19.371429 | J2: =IFERROR(INDEX(下年标准成本!I:I,MATCH(C2,下年标准成本!C:C,0),1),"") -> 14 | K2: =IFERROR(E2*J2,"") -> 3920 | L2: =IFERROR(F2-K2,"") -> 880 | M2: =IFERROR(L2/F2,"") -> 0.18333333
A3: PB | B3: PB01 | C3: B0122 | D3: 自制 | E3: 320 | F3: 5000 | G3: 0.13 | H3: =IFERROR(F3/E3,"") -> 15.625 | I3: =IFERROR(H3*(1+G3),"") -> 17.65625 | J3: =IFERROR(INDEX(下年标准成本!I:I,MATCH(C3,下年标准成本!C:C,0),1),"") -> 14 | K3: =IFERROR(E3*J3,"") -> 4480 | L3: =IFERROR(F3-K3,"") -> 520 | M3: =IFERROR(L3/F3,"") -> 0.104
A4: PC | B4: PC01 | C4: C0122 | D4: 自制 | E4: 290 | F4: 3200 | G4: 0.13 | H4: =IFERROR(F4/E4,"") -> 11.034483 | I4: =IFERROR(H4*(1+G4),"") -> 12.468966 | J4: =IFERROR(INDEX(下年标准成本!I:I,MATCH(C4,下年标准成本!C:C,0),1),"") -> 10 | K4: =IFERROR(E4*J4,"") -> 2900 | L4: =IFERROR(F4-K4,"") -> 300 | M4: =IFERROR(L4/F4,"") -> 0.09375
A5: PA | B5: PA01 | C5: A0111 | D5: 自制 | E5: 240 | F5: 4000 | G5: 0.13 | H5: =IFERROR(F5/E5,"") -> 16.666667 | I5: =IFERROR(H5*(1+G5),"") -> 18.833333 | J5: =IFERROR(INDEX(下年标准成本!I:I,MATCH(C5,下年标准成本!C:C,0),1),"") -> 14 | K5: =IFERROR(E5*J5,"") -> 3360 | L5: =IFERROR(F5-K5,"") -> 640 | M5: =IFERROR(L5/F5,"") -> 0.16
A6: PB | B6: PB01 | C6: B0122 | D6: 自制 | E6: 320 | F6: 5000 | G6: 0.13 | H6: =IFERROR(F6/E6,"") -> 15.625 | I6: =IFERROR(H6*(1+G6),"") -> 17.65625 | J6: =IFERROR(INDEX(下年标准成本!I:I,MATCH(C6,下年标准成本!C:C,0),1),"") -> 14 | K6: =IFERROR(E6*J6,"") -> 4480 | L6: =IFERROR(F6-K6,"") -> 520 | M6: =IFERROR(L6/F6,"") -> 0.104
A7: PC | B7: PC01 | C7: C0122 | D7: 自制 | E7: 243 | F7: 2000 | G7: 0.13 | H7: =IFERROR(F7/E7,"") -> 8.2304527 | I7: =IFERROR(H7*(1+G7),"") -> 9.3004115 | J7: =IFERROR(INDEX(下年标准成本!I:I,MATCH(C7,下年标准成本!C:C,0),1),"") -> 10 | K7: =IFERROR(E7*J7,"") -> 2430 | L7: =IFERROR(F7-K7,"") -> -430 | M7: =IFERROR(L7/F7,"") -> -0.215
A8: SE | B8: SE99 | C8: C0199 | D8: 服务 | E8: 9 | F8: 2600 | G8: 0.06 | H8: =IFERROR(F8/E8,"") -> 288.88889 | I8: =IFERROR(H8*(1+G8),"") -> 306.22222 | J8: =IFERROR(INDEX(下年标准成本!I:I,MATCH(C8,下年标准成本!C:C,0),1),"") -> 116 | K8: =IFERROR(E8*J8,"") -> 1044 | L8: =IFERROR(F8-K8,"") -> 1556 | M8: =IFERROR(L8/F8,"") -> 0.59846154
H9: =IFERROR(F9/E9,"") | I9: =IFERROR(H9*(1+G9),"") | J9: =IFERROR(INDEX(下年标准成本!I:I,MATCH(C9,下年标准成本!C:C,0),1),"") | K9: =IFERROR(E9*J9,"") | L9: =IFERROR(F9-K9,"") | M9: =IFERROR(L9/F9,"")
H10: =IFERROR(F10/E10,"") | I10: =IFERROR(H10*(1+G10),"") | J10: =IFERROR(INDEX(下年标准成本!I:I,MATCH(C10,下年标准成本!C:C,0),1),"") | K10: =IFERROR(E10*J10,"") | L10: =IFERROR(F10-K10,"") | M10: =IFERROR(L10/F10,"")
H11: =IFERROR(F11/E11,"") | I11: =IFERROR(H11*(1+G11),"") | J11: =IFERROR(INDEX(下年标准成本!I:I,MATCH(C11,下年标准成本!C:C,0),1),"") | K11: =IFERROR(E11*J11,"") | L11: =IFERROR(F11-K11,"") | M11: =IFERROR(L11/F11,"")
H12: =IFERROR(F12/E12,"") | I12: =IFERROR(H12*(1+G12),"") | J12: =IFERROR(INDEX(下年标准成本!I:I,MATCH(C12,下年标准成本!C:C,0),1),"") | K12: =IFERROR(E12*J12,"") | L12: =IFERROR(F12-K12,"") | M12: =IFERROR(L12/F12,"")
H13: =IFERROR(F13/E13,"") | I13: =IFERROR(H13*(1+G13),"") | J13: =IFERROR(INDEX(下年标准成本!I:I,MATCH(C13,下年标准成本!C:C,0),1),"") | K13: =IFERROR(E13*J13,"") | L13: =IFERROR(F13-K13,"") | M13: =IFERROR(L13/F13,"")
H14: =IFERROR(F14/E14,"") | I14: =IFERROR(H14*(1+G14),"") | J14: =IFERROR(INDEX(下年标准成本!I:I,MATCH(C14,下年标准成本!C:C,0),1),"") | K14: =IFERROR(E14*J14,"") | L14: =IFERROR(F14-K14,"") | M14: =IFERROR(L14/F14,"")
H15: =IFERROR(F15/E15,"") | I15: =IFERROR(H15*(1+G15),"") | J15: =IFERROR(INDEX(下年标准成本!I:I,MATCH(C15,下年标准成本!C:C,0),1),"") | K15: =IFERROR(E15*J15,"") | L15: =IFERROR(F15-K15,"") | M15: =IFERROR(L15/F15,"")
H16: =IFERROR(F16/E16,"") | I16: =IFERROR(H16*(1+G16),"") | J16: =IFERROR(INDEX(下年标准成本!I:I,MATCH(C16,下年标准成本!C:C,0),1),"") | K16: =IFERROR(E16*J16,"") | L16: =IFERROR(F16-K16,"") | M16: =IFERROR(L16/F16,"")
H17: =IFERROR(F17/E17,"") | I17: =IFERROR(H17*(1+G17),"") | J17: =IFERROR(INDEX(下年标准成本!I:I,MATCH(C17,下年标准成本!C:C,0),1),"") | K17: =IFERROR(E17*J17,"") | L17: =IFERROR(F17-K17,"") | M17: =IFERROR(L17/F17,"")
H18: =IFERROR(F18/E18,"") | I18: =IFERROR(H18*(1+G18),"") | J18: =IFERROR(INDEX(下年标准成本!I:I,MATCH(C18,下年标准成本!C:C,0),1),"") | K18: =IFERROR(E18*J18,"") | L18: =IFERROR(F18-K18,"") | M18: =IFERROR(L18/F18,"")
H19: =IFERROR(F19/E19,"") | I19: =IFERROR(H19*(1+G19),"") | J19: =IFERROR(INDEX(下年标准成本!I:I,MATCH(C19,下年标准成本!C:C,0),1),"") | K19: =IFERROR(E19*J19,"") | L19: =IFERROR(F19-K19,"") | M19: =IFERROR(L19/F19,"")
H20: =IFERROR(F20/E20,"") | I20: =IFERROR(H20*(1+G20),"") | J20: =IFERROR(INDEX(下年标准成本!I:I,MATCH(C20,下年标准成本!C:C,0),1),"") | K20: =IFERROR(E20*J20,"") | L20: =IFERROR(F20-K20,"") | M20: =IFERROR(L20/F20,"")
... H1200: =IFERROR(F1200/E1200,"") | I1200: =IFERROR(H1200*(1+G1200),"") | J1200: =IFERROR(INDEX(下年标准成本!I:I,MATCH(C1200,下年标准成本!C:C,0),1),"") | K1200: =IFERROR(E1200*J1200,"") | L1200: =IFERROR(F1200-K1200,"") | M1200: =IFERROR(L1200/F1200,"")

Sheet 下年预算分月
Q1: 返回主页
B2: 年份 | C2: 1 | D2: 2 | E2: 3 | F2: 4 | G2: 5 | H2: 6 | I2: 7 | J2: 8 | K2: 9 | L2: 10 | M2: 11 | N2: 12 | O2: 全年
B3: ="A"&YEAR(主页!$D$2)-1 -> A2020 | C3: =SUMIFS(上年实际!$P:$P,上年实际!$C:$C,">="&DATE(YEAR(主页!$D$2)-1,C$2,1),上年实际!$C:$C,"<="&EOMONTH(DATE(YEAR(主页!$D$2)-1,C$2,1),0)) -> 1500 | D3: =SUMIFS(上年实际!$P:$P,上年实际!$C:$C,">="&DATE(YEAR(主页!$D$2)-1,D$2,1),上年实际!$C:$C,"<="&EOMONTH(DATE(YEAR(主页!$D$2)-1,D$2,1),0)) -> 0 | E3: =SUMIFS(上年实际!$P:$P,上年实际!$C:$C,">="&DATE(YEAR(主页!$D$2)-1,E$2,1),上年实际!$C:$C,"<="&EOMONTH(DATE(YEAR(主页!$D$2)-1,E$2,1),0)) -> 0 | F3: =SUMIFS(上年实际!$P:$P,上年实际!$C:$C,">="&DATE(YEAR(主页!$D$2)-1,F$2,1),上年实际!$C:$C,"<="&EOMONTH(DATE(YEAR(主页!$D$2)-1,F$2,1),0)) -> 1980 | G3: =SUMIFS(上年实际!$P:$P,上年实际!$C:$C,">="&DATE(YEAR(主页!$D$2)-1,G$2,1),上年实际!$C:$C,"<="&EOMONTH(DATE(YEAR(主页!$D$2)-1,G$2,1),0)) -> 1566.0377 | H3: =SUMIFS(上年实际!$P:$P,上年实际!$C:$C,">="&DATE(YEAR(主页!$D$2)-1,H$2,1),上年实际!$C:$C,"<="&EOMONTH(DATE(YEAR(主页!$D$2)-1,H$2,1),0)) -> 0 | I3: =SUMIFS(上年实际!$P:$P,上年实际!$C:$C,">="&DATE(YEAR(主页!$D$2)-1,I$2,1),上年实际!$C:$C,"<="&EOMONTH(DATE(YEAR(主页!$D$2)-1,I$2,1),0)) -> 0 | J3: =SUMIFS(上年实际!$P:$P,上年实际!$C:$C,">="&DATE(YEAR(主页!$D$2)-1,J$2,1),上年实际!$C:$C,"<="&EOMONTH(DATE(YEAR(主页!$D$2)-1,J$2,1),0)) -> 0 | ... N3: =SUMIFS(上年实际!$P:$P,上年实际!$C:$C,">="&DATE(YEAR(主页!$D$2)-1,N$2,1),上年实际!$C:$C,"<="&EOMONTH(DATE(YEAR(主页!$D$2)-1,N$2,1),0)) -> 0 | O3: =SUM(C3:N3) -> 5046.0377
B4: 占比% | C4: =C3/$O3 -> 0.29726294 | D4: =D3/$O3 -> 0 | E4: =E3/$O3 -> 0 | F4: =F3/$O3 -> 0.39238708 | G4: =G3/$O3 -> 0.31034999 | H4: =H3/$O3 -> 0 | I4: =I3/$O3 -> 0 | J4: =J3/$O3 -> 0 | ... N4: =N3/$O3 -> 0 | O4: =SUM(C4:N4) -> 1
B6: ="A"&YEAR(主页!$D$2)&"YTD" -> A2021YTD | C6: =IF(MONTH(主页!$D$2)>=C$2,SUMIFS(当年实际!$P:$P,当年实际!$C:$C,">="&DATE(YEAR(主页!$D$2),C$2,1),当年实际!$C:$C,"<="&EOMONTH(DATE(YEAR(主页!$D$2),C$2,1),0)),0) -> 1800 | D6: =IF(MONTH(主页!$D$2)>=D$2,SUMIFS(当年实际!$P:$P,当年实际!$C:$C,">="&DATE(YEAR(主页!$D$2),D$2,1),当年实际!$C:$C,"<="&EOMONTH(DATE(YEAR(主页!$D$2),D$2,1),0)),0) -> 0 | E6: =IF(MONTH(主页!$D$2)>=E$2,SUMIFS(当年实际!$P:$P,当年实际!$C:$C,">="&DATE(YEAR(主页!$D$2),E$2,1),当年实际!$C:$C,"<="&EOMONTH(DATE(YEAR(主页!$D$2),E$2,1),0)),0) -> 0 | F6: =IF(MONTH(主页!$D$2)>=F$2,SUMIFS(当年实际!$P:$P,当年实际!$C:$C,">="&DATE(YEAR(主页!$D$2),F$2,1),当年实际!$C:$C,"<="&EOMONTH(DATE(YEAR(主页!$D$2),F$2,1),0)),0) -> 2000 | G6: =IF(MONTH(主页!$D$2)>=G$2,SUMIFS(当年实际!$P:$P,当年实际!$C:$C,">="&DATE(YEAR(主页!$D$2),G$2,1),当年实际!$C:$C,"<="&EOMONTH(DATE(YEAR(主页!$D$2),G$2,1),0)),0) -> 1200 | H6: =IF(MONTH(主页!$D$2)>=H$2,SUMIFS(当年实际!$P:$P,当年实际!$C:$C,">="&DATE(YEAR(主页!$D$2),H$2,1),当年实际!$C:$C,"<="&EOMONTH(DATE(YEAR(主页!$D$2),H$2,1),0)),0) -> 0 | I6: =IF(MONTH(主页!$D$2)>=I$2,SUMIFS(当年实际!$P:$P,当年实际!$C:$C,">="&DATE(YEAR(主页!$D$2),I$2,1),当年实际!$C:$C,"<="&EOMONTH(DATE(YEAR(主页!$D$2),I$2,1),0)),0) -> 0 | J6: =IF(MONTH(主页!$D$2)>=J$2,SUMIFS(当年实际!$P:$P,当年实际!$C:$C,">="&DATE(YEAR(主页!$D$2),J$2,1),当年实际!$C:$C,"<="&EOMONTH(DATE(YEAR(主页!$D$2),J$2,1),0)),0) -> 0 | ... N6: =IF(MONTH(主页!$D$2)>=N$2,SUMIFS(当年实际!$P:$P,当年实际!$C:$C,">="&DATE(YEAR(主页!$D$2),N$2,1),当年实际!$C:$C,"<="&EOMONTH(DATE(YEAR(主页!$D$2),N$2,1),0)),0) -> 0 | O6: =SUM(C6:N6) -> 5000
B7: ="E"&YEAR(主页!$D$2)&"YTG" -> E2021YTG | K7: 3000 | L7: 1200 | M7: 900 | N7: 3000 | O7: =SUM(C7:N7) -> 8100
B8: ="E"&YEAR(主页!$D$2) -> E2021 | C8: =C6+C7 -> 1800 | D8: =D6+D7 -> 0 | E8: =E6+E7 -> 0 | F8: =F6+F7 -> 2000 | G8: =G6+G7 -> 1200 | H8: =H6+H7 -> 0 | I8: =I6+I7 -> 0 | J8: =J6+J7 -> 0 | ... N8: =N6+N7 -> 3000 | O8: =SUM(C8:N8) -> 13100
B9: 占比% | C9: =C6/$O8 -> 0.13740458 | D9: =D6/$O8 -> 0 | E9: =E6/$O8 -> 0 | F9: =F6/$O8 -> 0.15267176 | G9: =G6/$O8 -> 0.091603053 | H9: =H6/$O8 -> 0 | I9: =I6/$O8 -> 0 | J9: =J6/$O8 -> 0 | K9: =K7/$O8 -> 0.22900763 | L9: =L7/$O8 -> 0.091603053 | M9: =M7/$O8 -> 0.06870229 | N9: =N7/$O8 -> 0.22900763 | O9: =SUM(C9:N9) -> 1
B11: ="B"&YEAR(主页!$D$2)+1 -> B2022 | C11: 1120 | E11: 3400 | H11: 500 | K11: 600 | M11: 800 | O11: =SUM(C11:N11) -> 6420
B12: 占比% | C12: =C11/$O11 -> 0.17445483 | D12: =D11/$O11 -> 0 | E12: =E11/$O11 -> 0.52959502 | F12: =F11/$O11 -> 0 | G12: =G11/$O11 -> 0 | H12: =H11/$O11 -> 0.07788162 | I12: =I11/$O11 -> 0 | J12: =J11/$O11 -> 0 | ... N12: =N11/$O11 -> 0 | O12: =SUM(C12:N12) -> 1
C17: 白色单元格可填入数字
C18: 黄色单元格中设有自动计算的公式，不需要手工填数字

Sheet 预算校准
B1: A:实际数 E:估计数 B:预算数 YTD：从1月1日至报表中实际数的截止日 YTG: 从报表中实际数的截止日次日开始到年底 FY: 全年数 | Q1: 返回主页
B2: 销售预算校准表
B3: 当年实际截止日期 | C3: =主页!D2 -> 44499
B5: 销售收入目标（O) | F5: ="E"&TEXT($C$3,"yyyy")&"FY" -> E2021FY | K5: ="B"&TEXT($C$3,"yyyy")+1&"FY" -> B2022FY
F6: 11200 | K6: 43000
B8: 明细表格 | C8: 上年实际 | D8: 当年截止目前实际 | E8: 当年剩余月份估计 | F8: 当年估计 | H8: ="当年估计vs上年实际"&" E"&TEXT($C$3,"yy")&"/A"&TEXT($C$3,"yy")-1 -> 当年估计vs上年实际 E21/A20 | K8: 预算 | M8: ="下年预算vs当年估计"&" B"&TEXT($C$3,"yy")+1&"/E"&TEXT($C$3,"yy") -> 下年预算vs当年估计 B22/E21
C9: ="A"&TEXT($C$3,"yy")-1&"FY" -> A20FY | D9: ="A"&TEXT($C$3,"yy")&TEXT(MONTH($C$3),"00")&"YTD" -> A2110YTD | E9: ="E"&TEXT($C$3,"yy")&TEXT(MONTH($C$3),"00")&"YTG" -> E2110YTG | F9: ="E"&TEXT($C$3,"yyyy")&"FY" -> E2021FY | H9: 差异 | I9: % | J9: 说明 | K9: ="B"&YEAR($C$3)+1&"FY" -> B2022FY | M9: 差异 | N9: % | O9: 说明
B10: 销售明细（客户） | C10: =SUMIFS(上年实际!$P:$P,上年实际!$C:$C,">="&DATE(YEAR($C$3)-1,1,1),上年实际!$C:$C,"<="&DATE(YEAR($C$3)-1,12,DAY($C$3))) -> 5046.0377 | D10: =SUMIFS(当年实际!$P:$P,当年实际!$C:$C,">="&DATE(YEAR($C$3),1,1),当年实际!$C:$C,"<="&$C$3) -> 5000 | E10: =SUM('当年估计 客户'!D:D) -> 6200 | F10: =D10+E10 -> 11200 | G10: =IF(AND(F10/F$6<1.2,F10>=F$6),"已较准","未较准") -> 已较准 | H10: =F10-D10 -> 6200 | I10: =IFERROR(H10/D10,"-") -> 1.24 | J10: 请说明差异原因 | K10: =SUM('下年预算 客户'!D:D) -> 6200 | L10: =IF(AND(K10/K$6<1.2,K10>=K$6),"已较准","未较准") -> 未较准 | M10: =K10-F10 -> -5000 | N10: =M10/F10 -> -0.44642857 | O10: 请说明差异原因
B11: 销售明细（产品） | C11: =C10 -> 5046.0377 | D11: =D10 -> 5000 | E11: =SUM('当年估计 产品'!F:F) -> 9858 | F11: =D11+E11 -> 14858 | G11: =IF(AND(F11/F$6<1.01,F11>=F$6),"已较准","未较准") -> 未较准 | H11: =F11-D11 -> 9858 | I11: =IFERROR(H11/D11,"-") -> 1.9716 | J11: 请说明差异原因 | K11: =SUM('下年预算 产品'!F:F) -> 26600 | L11: =IF(AND(K11/K$6<1.01,K11>=K$6),"已较准","未较准") -> 未较准 | M11: =K11-F11 -> 11742 | N11: =M11/F11 -> 0.79028133 | O11: 请说明差异原因
B12: 销售明细（渠道） | C12: =C10 -> 5046.0377 | D12: =D10 -> 5000 | E12: =SUM('当年估计 渠道'!D:D) -> 5500 | F12: =D12+E12 -> 10500 | G12: =IF(AND(F12/F$6<1.2,F12>=F$6),"已较准","未较准") -> 未较准 | H12: =F12-D12 -> 5500 | I12: =IFERROR(H12/D12,"-") -> 1.1 | J12: 请说明差异原因 | K12: =SUM('下年预算 渠道'!D:D) -> 6200 | L12: =IF(AND(K12/K$6<1.2,K12>=K$6),"已较准","未较准") -> 未较准 | M12: =K12-F12 -> -4300 | N12: =M12/F12 -> -0.40952381 | O12: 请说明差异原因
B13: 销售明细（部门/业务员） | C13: =C10 -> 5046.0377 | D13: =D10 -> 5000 | E13: =SUM('当年估计 业务员'!D:D) -> 6200 | F13: =D13+E13 -> 11200 | G13: =IF(AND(F13/F$6<1.2,F13>=F$6),"已较准","未较准") -> 已较准 | H13: =F13-D13 -> 6200 | I13: =IFERROR(H13/D13,"-") -> 1.24 | J13: 请说明差异原因 | K13: =SUM('下年预算 业务员'!D:D) -> 6100 | L13: =IF(AND(K13/K$6<1.2,K13>=K$6),"已较准","未较准") -> 未较准 | M13: =K13-F13 -> -5100 | N13: =M13/F13 -> -0.45535714 | O13: 请说明差异原因
B14: 销售明细（月份） | C14: =C10 -> 5046.0377 | D14: =D10 -> 5000 | E14: =F14-D14 -> 8100 | F14: =下年预算分月!O8 -> 13100 | G14: =IF(AND(F14/F$6<1.2,F14>=F$6),"已较准","未较准") -> 已较准 | H14: =F14-D14 -> 8100 | I14: =IFERROR(H14/D14,"-") -> 1.62 | J14: 请说明差异原因 | K14: =下年预算分月!O11 -> 6420 | L14: =IF(AND(K14/K$6<1.2,K14>=K$6),"已较准","未较准") -> 未较准 | M14: =K14-F14 -> -6680 | N14: =M14/F14 -> -0.50992366 | O14: 请说明差异原因
B16: 销售毛利率目标（O) | F16: ="E"&YEAR($C$3)&"FY" -> E2021FY | K16: ="B"&YEAR($C$3)+1&"FY" -> B2022FY
F17: 0.341 | K17: 0.188
B19: 明细表格 | C19: 实际 | D19: 实际 | E19: 估计 | F19: 估计 | H19: ="当年估计vs上年实际"&" E"&TEXT($C$3,"yy")&"/A"&TEXT($C$3,"yy")-1 -> 当年估计vs上年实际 E21/A20 | K19: 预算 | M19: ="下年预算vs当年估计"&" B"&TEXT($C$3,"yy")+1&"/E"&TEXT($C$3,"yy") -> 下年预算vs当年估计 B22/E21
C20: ="A"&YEAR($C$3)-1&"FY" -> A2020FY | D20: ="A"&YEAR($C$3)&TEXT(MONTH($C$3),"00")&"YTD" -> A202110YTD | E20: ="E"&YEAR($C$3)&TEXT(MONTH($C$3),"00")&"YTG" -> E202110YTG | F20: ="E"&YEAR($C$3)&"FY" -> E2021FY | H20: 差异 | I20: 说明 | K20: ="B"&YEAR($C$3)+1&"FY" -> B2022FY | M20: 差异 | N20: 说明
B21: 销售明细（客户） | C21: =SUMIFS(上年实际!V:V,上年实际!$C:$C,">="&DATE(YEAR($C$3)-1,1,1),上年实际!$C:$C,"<="&DATE(YEAR($C$3)-1,12,31))/SUMIFS(上年实际!$P:$P,上年实际!$C:$C,">="&DATE(YEAR($C$3)-1,1,1),上年实际!$C:$C,"<="&DATE(YEAR($C$3)-1,12,31)) -> 0.20749701 | D21: =SUMIFS(当年实际!$V:$V,当年实际!$C:$C,">="&DATE(YEAR($C$3),1,1),当年实际!$C:$C,"<="&$C$3)/SUMIFS(当年实际!$P:$P,当年实际!$C:$C,">="&DATE(YEAR($C$3),1,1),当年实际!$C:$C,"<="&$C$3) -> 0.216 | E21: =SUM('当年估计 客户'!G:G)/SUM('当年估计 客户'!D:D) -> 0.18693548 | F21: =(D21*D10+E10*E21)/F10 -> 0.19991071 | G21: =IF(AND(F21/F$17<1.2,F21>=F$17),"已较准","未较准") -> 未较准 | H21: =F21-D21 -> -0.016089286 | K21: =SUM('下年预算 客户'!G:G)/SUM('下年预算 客户'!D:D) -> 0.21806452 | L21: =IF(AND(K21/K$17<1.2,K21>=K$17),"已较准","未较准") -> 已较准 | M21: =K21-F21 -> 0.018153802
B22: 销售明细（产品） | C22: =C21 -> 0.20749701 | D22: =D21 -> 0.216 | E22: =SUM('当年估计 产品'!L:L)/SUM('当年估计 产品'!F:F) -> 0.43325218 | F22: =(D22*D11+E11*E22)/F11 -> 0.36014268 | G22: =IF(AND(F22/F$17<1.01,F22>=F$17),"已较准","未较准") -> 未较准 | H22: =F22-D22 -> 0.14414268 | K22: =SUM('下年预算 产品'!L:L)/SUM('下年预算 产品'!F:F) -> 0.14984962 | L22: =IF(AND(K22/K$17<1.01,K22>=K$17),"已较准","未较准") -> 未较准 | M22: =K22-F22 -> -0.21029306
B23: 销售明细（渠道） | C23: =C21 -> 0.20749701 | D23: =D21 -> 0.216 | E23: =SUM('当年估计 渠道'!G:G)/SUM('当年估计 渠道'!D:D) -> 0.22590909 | F23: =(D23*D12+E12*E23)/F12 -> 0.22119048 | G23: =IF(AND(F23/F$17<1.2,F23>=F$17),"已较准","未较准") -> 未较准 | H23: =F23-D23 -> 0.0051904762 | K23: =SUM('下年预算 渠道'!G:G)/SUM('下年预算 渠道'!D:D) -> 0.19290323 | L23: =IF(AND(K23/K$17<1.2,K23>=K$17),"已较准","未较准") -> 已较准 | M23: =K23-F23 -> -0.02828725
B24: 销售明细（部门/业务员） | C24: =C21 -> 0.20749701 | D24: =D21 -> 0.216 | E24: =SUM('当年估计 业务员'!G:G)/SUM('当年估计 业务员'!D:D) -> 0.24419355 | F24: =(D24*D13+E13*E24)/F13 -> 0.23160714 | G24: =IF(AND(F24/F$17<1.2,F24>=F$17),"已较准","未较准") -> 未较准 | H24: =F24-D24 -> 0.015607143 | K24: =SUM('下年预算 业务员'!G:G)/SUM('下年预算 业务员'!D:D) -> 0.2095082 | L24: =IF(AND(K24/K$17<1.2,K24>=K$17),"已较准","未较准") -> 已较准 | M24: =K24-F24 -> -0.022098946
B25: 销售明细（月份） | C25: =C21 -> 0.20749701 | D25: =D21 -> 0.216 | E25: =(F25*F14-D14*D25)/E14 -> 0.41816049 | F25: =F17 -> 0.341 | G25: =IF(AND(F25/F$17<1.2,F25>=F$17),"已较准","未较准") -> 已较准 | H25: =F25-D25 -> 0.125 | K25: =K17 -> 0.188 | L25: =IF(AND(K25/K$17<1.2,K25>=K$17),"已较准","未较准") -> 已较准 | M25: =K25-F25 -> -0.153
C27: 当分解到产品的明细与目标之间的差异小于0.1%、其他明细与目标之间的差异小于20%即视为已校准
D29: 历年实际数，从历年销售明细表中自动取数
D30: 当年估计数，需要手工输入
D31: 下年预算数，需要手工输入
C33: 已较准 | D33: 上级预算与下级预算的差异幅度在可接受幅度范围内。
C34: 未较准 | D34: 上级预算与下级预算的差异幅度超过可接受幅度，需要调整预算
C35: 可接受 | D35: 上级预算与下级预算未校准，但差异不影响战略落地。可接受

Sheet 销售对比分析底稿
B2: 产品名称 | C2: 产品大类 | D2: 产品子类 | E2: 产品来源 | F2: ="A"&YEAR(主页!$D$2)-1&"FY" -> A2020FY | G2: ="A"&YEAR(主页!$D$2)-1&"FY" -> A2020FY | H2: ="A"&YEAR(主页!$D$2)-1&"FY" -> A2020FY | I2: ="A"&YEAR(主页!$D$2)&TEXT(MONTH(主页!$D$2),"00")&"YTD" -> A202110YTD | J2: ="A"&YEAR(主页!$D$2)&TEXT(MONTH(主页!$D$2),"00")&"YTD" -> A202110YTD | K2: ="A"&YEAR(主页!$D$2)&TEXT(MONTH(主页!$D$2),"00")&"YTD" -> A202110YTD | L2: ="E"&YEAR(主页!$D$2)&TEXT(MONTH(主页!$D$2),"00")&"YTG" -> E202110YTG | M2: ="E"&YEAR(主页!$D$2)&TEXT(MONTH(主页!$D$2),"00")&"YTG" -> E202110YTG | N2: ="E"&YEAR(主页!$D$2)&TEXT(MONTH(主页!$D$2),"00")&"YTG" -> E202110YTG | O2: ="E"&YEAR(主页!$D$2)&"FY" -> E2021FY | P2: ="E"&YEAR(主页!$D$2)&"FY" -> E2021FY | Q2: ="E"&YEAR(主页!$D$2)&"FY" -> E2021FY | R2: ="E"&YEAR(主页!$D$2)&"/A"&YEAR(主页!$D$2)-1 -> E2021/A2020 | AE2: ="B"&YEAR(主页!$D$2)+1&"FY" -> B2022FY | AF2: ="B"&YEAR(主页!$D$2)+1&"FY" -> B2022FY | AG2: ="B"&YEAR(主页!$D$2)+1&"FY" -> B2022FY | AH2: ="B"&YEAR(主页!$D$2)+1&"/E"&YEAR(主页!$D$2) -> B2022/E2021 | AV2: 返回主页
F3: 销量 | G3: 销售额 | H3: 毛利 | I3: 销量 | J3: 销售额 | K3: 毛利 | L3: 销量 | M3: 销售额 | N3: 毛利 | O3: 销量 | P3: 销售额 | Q3: 毛利 | R3: p1 | S3: p2 | T3: q2*p1 | U3: 量差 | V3: 价差 | W3: STV | X3: c1 | Y3: c2 | Z3: q2*c1 | AA3: 量差c | AB3: 成本差 | AC3: CTV | AD3: 结构差 | AE3: 销量 | AF3: 销售额 | AG3: 毛利 | AH3: p1 | AI3: p2 | AJ3: q2*p1 | AK3: 量差p | AL3: 价差 | AM3: STV | AN3: c1 | AO3: c2 | AP3: q2*c1 | AQ3: 量差c | AR3: 成本差 | AS3: CTV | AT3: 结构差
B4: A0111 | C4: PA | D4: PA01 | E4: 外购 | F4: =SUMIFS(上年实际!$O:$O,上年实际!$K:$K,$B4,上年实际!$L:$L,$C4,上年实际!$M:$M,$D4,上年实际!$N:$N,$E4,上年实际!$C:$C,">="&DATE(YEAR(主页!$D$2)-1,1,1),上年实际!$C:$C,"<="&DATE(YEAR(主页!$D$2),12,31)) -> 98 | G4: =SUMIFS(上年实际!$P:$P,上年实际!$K:$K,$B4,上年实际!$L:$L,$C4,上年实际!$M:$M,$D4,上年实际!$N:$N,$E4,上年实际!$C:$C,">="&DATE(YEAR(主页!$D$2)-1,1,1),上年实际!$C:$C,"<="&DATE(YEAR(主页!$D$2),12,31)) -> 1500 | H4: =SUMIFS(上年实际!$V:$V,上年实际!$K:$K,$B4,上年实际!$L:$L,$C4,上年实际!$M:$M,$D4,上年实际!$N:$N,$E4,上年实际!$C:$C,">="&DATE(YEAR(主页!$D$2)-1,1,1),上年实际!$C:$C,"<="&DATE(YEAR(主页!$D$2),12,31)) -> 226 | I4: =SUMIFS(当年实际!$O:$O,当年实际!$K:$K,$B4,当年实际!$L:$L,$C4,当年实际!$M:$M,$D4,当年实际!$N:$N,$E4,当年实际!$C:$C,">="&DATE(YEAR(主页!$D$2),1,1),当年实际!$C:$C,"<="&EOMONTH(DATE(YEAR(主页!$D$2),MONTH(主页!$D$2),1),0)) -> 100 | J4: =SUMIFS(当年实际!$P:$P,当年实际!$K:$K,$B4,当年实际!$L:$L,$C4,当年实际!$M:$M,$D4,当年实际!$N:$N,$E4,当年实际!$C:$C,">="&DATE(YEAR(主页!$D$2),1,1),当年实际!$C:$C,"<="&EOMONTH(DATE(YEAR(主页!$D$2),MONTH(主页!$D$2),1),0)) -> 1800 | K4: =SUMIFS(当年实际!$V:$V,当年实际!$K:$K,$B4,当年实际!$L:$L,$C4,当年实际!$M:$M,$D4,当年实际!$N:$N,$E4,当年实际!$C:$C,">="&DATE(YEAR(主页!$D$2),1,1),当年实际!$C:$C,"<="&EOMONTH(DATE(YEAR(主页!$D$2),MONTH(主页!$D$2),1),0)) -> 500 | L4: =SUMIFS('当年估计 产品'!$E:$E,'当年估计 产品'!$A:$A,$C4,'当年估计 产品'!$B:$B,$D4,'当年估计 产品'!$C:$C,$B4,'当年估计 产品'!$D:$D,$E4) -> 70 | M4: =SUMIFS('当年估计 产品'!$F:$F,'当年估计 产品'!$A:$A,$C4,'当年估计 产品'!$B:$B,$D4,'当年估计 产品'!$C:$C,$B4,'当年估计 产品'!$D:$D,$E4) -> 1800 | N4: =SUMIFS('当年估计 产品'!$L:$L,'当年估计 产品'!$A:$A,$C4,'当年估计 产品'!$B:$B,$D4,'当年估计 产品'!$C:$C,$B4,'当年估计 产品'!$D:$D,$E4) -> 890 | O4: =I4+L4 -> 170 | P4: =J4+M4 -> 3600 | Q4: =K4+N4 -> 1390 | R4: =IFERROR(G4/F4,"na") -> 15.306122 | S4: =IFERROR(P4/O4,"na") -> 21.176471 | T4: =O4*IF(R4="NA",IF(S4="NA",0,S4),R4) -> 2602.0408 | U4: =T4-G4 -> 1102.0408 | V4: =P4-G4-U4 -> 997.95918 | W4: =P4-G4 -> 2100 | X4: =IFERROR((G4-H4)/F4,"NA") -> 13 | Y4: =IFERROR((P4-Q4)/O4,"NA") -> 13 | Z4: =O4*IF(X4="NA",IF(Y4="NA",0,Y4),X4) -> 2210 | AA4: =Z4-(G4-H4) -> 936 | AB4: =AC4-AA4 -> 0 | AC4: =(P4-Q4)-(G4-H4) -> 936 | AD4: =Q4-G4/SUM(G:G)*SUM(P:P)*Q4/P4 -> -315.34958 | AE4: =SUMIFS('下年预算 产品'!$E:$E,'下年预算 产品'!$A:$A,$C4,'下年预算 产品'!$B:$B,$D4,'下年预算 产品'!$C:$C,$B4,'下年预算 产品'!$D:$D,$E4) -> 280 | AF4: =SUMIFS('下年预算 产品'!$F:$F,'下年预算 产品'!$A:$A,$C4,'下年预算 产品'!$B:$B,$D4,'下年预算 产品'!$C:$C,$B4,'下年预算 产品'!$D:$D,$E4) -> 4800 | AG4: =SUMIFS('下年预算 产品'!$L:$L,'下年预算 产品'!$A:$A,$C4,'下年预算 产品'!$B:$B,$D4,'下年预算 产品'!$C:$C,$B4,'下年预算 产品'!$D:$D,$E4) -> 880 | AH4: =IFERROR(P4/O4,"na") -> 21.176471 | AI4: =IFERROR(AF4/AE4,"na") -> 17.142857 | AJ4: =AE4*IF(AH4="NA",IF(AI4="NA",0,AI4),AH4) -> 5929.4118 | AK4: =AJ4-P4 -> 2329.4118 | AL4: =AF4-P4-AK4 -> -1129.4118 | AM4: =AF4-P4 -> 1200 | AN4: =IFERROR((P4-Q4)/O4,"NA") -> 13 | AO4: =IFERROR((AF4-AG4)/AE4,"NA") -> 14 | AP4: =AE4*IF(AN4="NA",IF(AO4="NA",0,AO4),AN4) -> 3640 | AQ4: =AP4-(P4-Q4) -> 1430 | AR4: =(AF4-AG4)-(P4-Q4)-(AP4-(P4-Q4)) -> 280 | AS4: =(AF4-AG4)-(P4-Q4) -> 1710 | AT4: =AG4-P4/SUM(P:P)*SUM(AF:AF)*AG4/AF4 -> -301.58568
B5: B0122 | C5: PB | D5: PB01 | E5: 自制 | F5: =SUMIFS(上年实际!$O:$O,上年实际!$K:$K,$B5,上年实际!$L:$L,$C5,上年实际!$M:$M,$D5,上年实际!$N:$N,$E5,上年实际!$C:$C,">="&DATE(YEAR(主页!$D$2)-1,1,1),上年实际!$C:$C,"<="&DATE(YEAR(主页!$D$2),12,31)) -> 121 | G5: =SUMIFS(上年实际!$P:$P,上年实际!$K:$K,$B5,上年实际!$L:$L,$C5,上年实际!$M:$M,$D5,上年实际!$N:$N,$E5,上年实际!$C:$C,">="&DATE(YEAR(主页!$D$2)-1,1,1),上年实际!$C:$C,"<="&DATE(YEAR(主页!$D$2),12,31)) -> 1980 | H5: =SUMIFS(上年实际!$V:$V,上年实际!$K:$K,$B5,上年实际!$L:$L,$C5,上年实际!$M:$M,$D5,上年实际!$N:$N,$E5,上年实际!$C:$C,">="&DATE(YEAR(主页!$D$2)-1,1,1),上年实际!$C:$C,"<="&DATE(YEAR(主页!$D$2),12,31)) -> 407 | I5: =SUMIFS(当年实际!$O:$O,当年实际!$K:$K,$B5,当年实际!$L:$L,$C5,当年实际!$M:$M,$D5,当年实际!$N:$N,$E5,当年实际!$C:$C,">="&DATE(YEAR(主页!$D$2),1,1),当年实际!$C:$C,"<="&EOMONTH(DATE(YEAR(主页!$D$2),MONTH(主页!$D$2),1),0)) -> 124 | J5: =SUMIFS(当年实际!$P:$P,当年实际!$K:$K,$B5,当年实际!$L:$L,$C5,当年实际!$M:$M,$D5,当年实际!$N:$N,$E5,当年实际!$C:$C,">="&DATE(YEAR(主页!$D$2),1,1),当年实际!$C:$C,"<="&EOMONTH(DATE(YEAR(主页!$D$2),MONTH(主页!$D$2),1),0)) -> 2000 | K5: =SUMIFS(当年实际!$V:$V,当年实际!$K:$K,$B5,当年实际!$L:$L,$C5,当年实际!$M:$M,$D5,当年实际!$N:$N,$E5,当年实际!$C:$C,">="&DATE(YEAR(主页!$D$2),1,1),当年实际!$C:$C,"<="&EOMONTH(DATE(YEAR(主页!$D$2),MONTH(主页!$D$2),1),0)) -> 388 | L5: =SUMIFS('当年估计 产品'!$E:$E,'当年估计 产品'!$A:$A,$C5,'当年估计 产品'!$B:$B,$D5,'当年估计 产品'!$C:$C,$B5,'当年估计 产品'!$D:$D,$E5) -> 178 | M5: =SUMIFS('当年估计 产品'!$F:$F,'当年估计 产品'!$A:$A,$C5,'当年估计 产品'!$B:$B,$D5,'当年估计 产品'!$C:$C,$B5,'当年估计 产品'!$D:$D,$E5) -> 3980 | N5: =SUMIFS('当年估计 产品'!$L:$L,'当年估计 产品'!$A:$A,$C5,'当年估计 产品'!$B:$B,$D5,'当年估计 产品'!$C:$C,$B5,'当年估计 产品'!$D:$D,$E5) -> 1666 | O5: =I5+L5 -> 302 | P5: =J5+M5 -> 5980 | Q5: =K5+N5 -> 2054 | R5: =IFERROR(G5/F5,"na") -> 16.363636 | S5: =IFERROR(P5/O5,"na") -> 19.801325 | T5: =O5*IF(R5="NA",IF(S5="NA",0,S5),R5) -> 4941.8182 | U5: =T5-G5 -> 2961.8182 | V5: =P5-G5-U5 -> 1038.1818 | W5: =P5-G5 -> 4000 | X5: =IFERROR((G5-H5)/F5,"NA") -> 13 | Y5: =IFERROR((P5-Q5)/O5,"NA") -> 13 | Z5: =O5*IF(X5="NA",IF(Y5="NA",0,Y5),X5) -> 3926 | AA5: =Z5-(G5-H5) -> 2353 | AB5: =AC5-AA5 -> 0 | AC5: =(P5-Q5)-(G5-H5) -> 2353 | AD5: =Q5-G5/SUM(G:G)*SUM(P:P)*Q5/P5 -> 51.491789 | AE5: =SUMIFS('下年预算 产品'!$E:$E,'下年预算 产品'!$A:$A,$C5,'下年预算 产品'!$B:$B,$D5,'下年预算 产品'!$C:$C,$B5,'下年预算 产品'!$D:$D,$E5) -> 640 | AF5: =SUMIFS('下年预算 产品'!$F:$F,'下年预算 产品'!$A:$A,$C5,'下年预算 产品'!$B:$B,$D5,'下年预算 产品'!$C:$C,$B5,'下年预算 产品'!$D:$D,$E5) -> 10000 | AG5: =SUMIFS('下年预算 产品'!$L:$L,'下年预算 产品'!$A:$A,$C5,'下年预算 产品'!$B:$B,$D5,'下年预算 产品'!$C:$C,$B5,'下年预算 产品'!$D:$D,$E5) -> 1040 | AH5: =IFERROR(P5/O5,"na") -> 19.801325 | AI5: =IFERROR(AF5/AE5,"na") -> 15.625 | AJ5: =AE5*IF(AH5="NA",IF(AI5="NA",0,AI5),AH5) -> 12672.848 | AK5: =AJ5-P5 -> 6692.8477 | AL5: =AF5-P5-AK5 -> -2672.8477 | AM5: =AF5-P5 -> 4020 | AN5: =IFERROR((P5-Q5)/O5,"NA") -> 13 | AO5: =IFERROR((AF5-AG5)/AE5,"NA") -> 14 | AP5: =AE5*IF(AN5="NA",IF(AO5="NA",0,AO5),AN5) -> 8320 | AQ5: =AP5-(P5-Q5) -> 4394 | AR5: =(AF5-AG5)-(P5-Q5)-(AP5-(P5-Q5)) -> 640 | AS5: =(AF5-AG5)-(P5-Q5) -> 5034 | AT5: =AG5-P5/SUM(P:P)*SUM(AF:AF)*AG5/AF5 -> -73.411765
B6: C0122 | C6: PC | D6: PC01 | E6: 自制 | F6: =SUMIFS(上年实际!$O:$O,上年实际!$K:$K,$B6,上年实际!$L:$L,$C6,上年实际!$M:$M,$D6,上年实际!$N:$N,$E6,上年实际!$C:$C,">="&DATE(YEAR(主页!$D$2)-1,1,1),上年实际!$C:$C,"<="&DATE(YEAR(主页!$D$2),12,31)) -> 88 | G6: =SUMIFS(上年实际!$P:$P,上年实际!$K:$K,$B6,上年实际!$L:$L,$C6,上年实际!$M:$M,$D6,上年实际!$N:$N,$E6,上年实际!$C:$C,">="&DATE(YEAR(主页!$D$2)-1,1,1),上年实际!$C:$C,"<="&DATE(YEAR(主页!$D$2),12,31)) -> 1000 | H6: =SUMIFS(上年实际!$V:$V,上年实际!$K:$K,$B6,上年实际!$L:$L,$C6,上年实际!$M:$M,$D6,上年实际!$N:$N,$E6,上年实际!$C:$C,">="&DATE(YEAR(主页!$D$2)-1,1,1),上年实际!$C:$C,"<="&DATE(YEAR(主页!$D$2),12,31)) -> 208 | I6: =SUMIFS(当年实际!$O:$O,当年实际!$K:$K,$B6,当年实际!$L:$L,$C6,当年实际!$M:$M,$D6,当年实际!$N:$N,$E6,当年实际!$C:$C,">="&DATE(YEAR(主页!$D$2),1,1),当年实际!$C:$C,"<="&EOMONTH(DATE(YEAR(主页!$D$2),MONTH(主页!$D$2),1),0)) -> 112 | J6: =SUMIFS(当年实际!$P:$P,当年实际!$K:$K,$B6,当年实际!$L:$L,$C6,当年实际!$M:$M,$D6,当年实际!$N:$N,$E6,当年实际!$C:$C,">="&DATE(YEAR(主页!$D$2),1,1),当年实际!$C:$C,"<="&EOMONTH(DATE(YEAR(主页!$D$2),MONTH(主页!$D$2),1),0)) -> 1200 | K6: =SUMIFS(当年实际!$V:$V,当年实际!$K:$K,$B6,当年实际!$L:$L,$C6,当年实际!$M:$M,$D6,当年实际!$N:$N,$E6,当年实际!$C:$C,">="&DATE(YEAR(主页!$D$2),1,1),当年实际!$C:$C,"<="&EOMONTH(DATE(YEAR(主页!$D$2),MONTH(主页!$D$2),1),0)) -> 192 | L6: =SUMIFS('当年估计 产品'!$E:$E,'当年估计 产品'!$A:$A,$C6,'当年估计 产品'!$B:$B,$D6,'当年估计 产品'!$C:$C,$B6,'当年估计 产品'!$D:$D,$E6) -> 142 | M6: =SUMIFS('当年估计 产品'!$F:$F,'当年估计 产品'!$A:$A,$C6,'当年估计 产品'!$B:$B,$D6,'当年估计 产品'!$C:$C,$B6,'当年估计 产品'!$D:$D,$E6) -> 2200 | N6: =SUMIFS('当年估计 产品'!$L:$L,'当年估计 产品'!$A:$A,$C6,'当年估计 产品'!$B:$B,$D6,'当年估计 产品'!$C:$C,$B6,'当年估计 产品'!$D:$D,$E6) -> 922 | O6: =I6+L6 -> 254 | P6: =J6+M6 -> 3400 | Q6: =K6+N6 -> 1114 | R6: =IFERROR(G6/F6,"na") -> 11.363636 | S6: =IFERROR(P6/O6,"na") -> 13.385827 | T6: =O6*IF(R6="NA",IF(S6="NA",0,S6),R6) -> 2886.3636 | U6: =T6-G6 -> 1886.3636 | V6: =P6-G6-U6 -> 513.63636 | W6: =P6-G6 -> 2400 | X6: =IFERROR((G6-H6)/F6,"NA") -> 9 | Y6: =IFERROR((P6-Q6)/O6,"NA") -> 9 | Z6: =O6*IF(X6="NA",IF(Y6="NA",0,Y6),X6) -> 2286 | AA6: =Z6-(G6-H6) -> 1494 | AB6: =AC6-AA6 -> 0 | AC6: =(P6-Q6)-(G6-H6) -> 1494 | AD6: =Q6-G6/SUM(G:G)*SUM(P:P)*Q6/P6 -> 149.24701 | AE6: =SUMIFS('下年预算 产品'!$E:$E,'下年预算 产品'!$A:$A,$C6,'下年预算 产品'!$B:$B,$D6,'下年预算 产品'!$C:$C,$B6,'下年预算 产品'!$D:$D,$E6) -> 533 | AF6: =SUMIFS('下年预算 产品'!$F:$F,'下年预算 产品'!$A:$A,$C6,'下年预算 产品'!$B:$B,$D6,'下年预算 产品'!$C:$C,$B6,'下年预算 产品'!$D:$D,$E6) -> 5200 | AG6: =SUMIFS('下年预算 产品'!$L:$L,'下年预算 产品'!$A:$A,$C6,'下年预算 产品'!$B:$B,$D6,'下年预算 产品'!$C:$C,$B6,'下年预算 产品'!$D:$D,$E6) -> -130 | AH6: =IFERROR(P6/O6,"na") -> 13.385827 | AI6: =IFERROR(AF6/AE6,"na") -> 9.7560976 | AJ6: =AE6*IF(AH6="NA",IF(AI6="NA",0,AI6),AH6) -> 7134.6457 | AK6: =AJ6-P6 -> 3734.6457 | AL6: =AF6-P6-AK6 -> -1934.6457 | AM6: =AF6-P6 -> 1800 | AN6: =IFERROR((P6-Q6)/O6,"NA") -> 9 | AO6: =IFERROR((AF6-AG6)/AE6,"NA") -> 10 | AP6: =AE6*IF(AN6="NA",IF(AO6="NA",0,AO6),AN6) -> 4797 | AQ6: =AP6-(P6-Q6) -> 2511 | AR6: =(AF6-AG6)-(P6-Q6)-(AP6-(P6-Q6)) -> 533 | AS6: =(AF6-AG6)-(P6-Q6) -> 3044 | AT6: =AG6-P6/SUM(P:P)*SUM(AF:AF)*AG6/AF6 -> 22.173913
B7: C0199 | C7: SE | D7: SE99 | E7: 服务 | F7: =SUMIFS(上年实际!$O:$O,上年实际!$K:$K,$B7,上年实际!$L:$L,$C7,上年实际!$M:$M,$D7,上年实际!$N:$N,$E7,上年实际!$C:$C,">="&DATE(YEAR(主页!$D$2)-1,1,1),上年实际!$C:$C,"<="&DATE(YEAR(主页!$D$2),12,31)) -> 3 | G7: =SUMIFS(上年实际!$P:$P,上年实际!$K:$K,$B7,上年实际!$L:$L,$C7,上年实际!$M:$M,$D7,上年实际!$N:$N,$E7,上年实际!$C:$C,">="&DATE(YEAR(主页!$D$2)-1,1,1),上年实际!$C:$C,"<="&DATE(YEAR(主页!$D$2),12,31)) -> 566.03774 | H7: =SUMIFS(上年实际!$V:$V,上年实际!$K:$K,$B7,上年实际!$L:$L,$C7,上年实际!$M:$M,$D7,上年实际!$N:$N,$E7,上年实际!$C:$C,">="&DATE(YEAR(主页!$D$2)-1,1,1),上年实际!$C:$C,"<="&DATE(YEAR(主页!$D$2),12,31)) -> 206.03774 | I7: =SUMIFS(当年实际!$O:$O,当年实际!$K:$K,$B7,当年实际!$L:$L,$C7,当年实际!$M:$M,$D7,当年实际!$N:$N,$E7,当年实际!$C:$C,">="&DATE(YEAR(主页!$D$2),1,1),当年实际!$C:$C,"<="&EOMONTH(DATE(YEAR(主页!$D$2),MONTH(主页!$D$2),1),0)) -> 0 | J7: =SUMIFS(当年实际!$P:$P,当年实际!$K:$K,$B7,当年实际!$L:$L,$C7,当年实际!$M:$M,$D7,当年实际!$N:$N,$E7,当年实际!$C:$C,">="&DATE(YEAR(主页!$D$2),1,1),当年实际!$C:$C,"<="&EOMONTH(DATE(YEAR(主页!$D$2),MONTH(主页!$D$2),1),0)) -> 0 | K7: =SUMIFS(当年实际!$V:$V,当年实际!$K:$K,$B7,当年实际!$L:$L,$C7,当年实际!$M:$M,$D7,当年实际!$N:$N,$E7,当年实际!$C:$C,">="&DATE(YEAR(主页!$D$2),1,1),当年实际!$C:$C,"<="&EOMONTH(DATE(YEAR(主页!$D$2),MONTH(主页!$D$2),1),0)) -> 0 | L7: =SUMIFS('当年估计 产品'!$E:$E,'当年估计 产品'!$A:$A,$C7,'当年估计 产品'!$B:$B,$D7,'当年估计 产品'!$C:$C,$B7,'当年估计 产品'!$D:$D,$E7) -> 2 | M7: =SUMIFS('当年估计 产品'!$F:$F,'当年估计 产品'!$A:$A,$C7,'当年估计 产品'!$B:$B,$D7,'当年估计 产品'!$C:$C,$B7,'当年估计 产品'!$D:$D,$E7) -> 378 | N7: =SUMIFS('当年估计 产品'!$L:$L,'当年估计 产品'!$A:$A,$C7,'当年估计 产品'!$B:$B,$D7,'当年估计 产品'!$C:$C,$B7,'当年估计 产品'!$D:$D,$E7) -> 138 | O7: =I7+L7 -> 2 | P7: =J7+M7 -> 378 | Q7: =K7+N7 -> 138 | R7: =IFERROR(G7/F7,"na") -> 188.67925 | S7: =IFERROR(P7/O7,"na") -> 189 | T7: =O7*IF(R7="NA",IF(S7="NA",0,S7),R7) -> 377.35849 | U7: =T7-G7 -> -188.67925 | V7: =P7-G7-U7 -> 0.64150943 | W7: =P7-G7 -> -188.03774 | X7: =IFERROR((G7-H7)/F7,"NA") -> 120 | Y7: =IFERROR((P7-Q7)/O7,"NA") -> 120 | Z7: =O7*IF(X7="NA",IF(Y7="NA",0,Y7),X7) -> 240 | AA7: =Z7-(G7-H7) -> -120 | AB7: =AC7-AA7 -> 0 | AC7: =(P7-Q7)-(G7-H7) -> -120 | AD7: =Q7-G7/SUM(G:G)*SUM(P:P)*Q7/P7 -> -470.47471 | AE7: =SUMIFS('下年预算 产品'!$E:$E,'下年预算 产品'!$A:$A,$C7,'下年预算 产品'!$B:$B,$D7,'下年预算 产品'!$C:$C,$B7,'下年预算 产品'!$D:$D,$E7) -> 9 | AF7: =SUMIFS('下年预算 产品'!$F:$F,'下年预算 产品'!$A:$A,$C7,'下年预算 产品'!$B:$B,$D7,'下年预算 产品'!$C:$C,$B7,'下年预算 产品'!$D:$D,$E7) -> 2600 | AG7: =SUMIFS('下年预算 产品'!$L:$L,'下年预算 产品'!$A:$A,$C7,'下年预算 产品'!$B:$B,$D7,'下年预算 产品'!$C:$C,$B7,'下年预算 产品'!$D:$D,$E7) -> 1556 | AH7: =IFERROR(P7/O7,"na") -> 189 | AI7: =IFERROR(AF7/AE7,"na") -> 288.88889 | AJ7: =AE7*IF(AH7="NA",IF(AI7="NA",0,AI7),AH7) -> 1701 | AK7: =AJ7-P7 -> 1323 | AL7: =AF7-P7-AK7 -> 899 | AM7: =AF7-P7 -> 2222 | AN7: =IFERROR((P7-Q7)/O7,"NA") -> 120 | AO7: =IFERROR((AF7-AG7)/AE7,"NA") -> 116 | AP7: =AE7*IF(AN7="NA",IF(AO7="NA",0,AO7),AN7) -> 1080 | AQ7: =AP7-(P7-Q7) -> 840 | AR7: =(AF7-AG7)-(P7-Q7)-(AP7-(P7-Q7)) -> -36 | AS7: =(AF7-AG7)-(P7-Q7) -> 804 | AT7: =AG7-P7/SUM(P:P)*SUM(AF:AF)*AG7/AF7 -> 1151.0053
B8: A0111 | C8: PA | D8: PA01 | E8: 自制 | F8: =SUMIFS(上年实际!$O:$O,上年实际!$K:$K,$B8,上年实际!$L:$L,$C8,上年实际!$M:$M,$D8,上年实际!$N:$N,$E8,上年实际!$C:$C,">="&DATE(YEAR(主页!$D$2)-1,1,1),上年实际!$C:$C,"<="&DATE(YEAR(主页!$D$2),12,31)) -> 0 | G8: =SUMIFS(上年实际!$P:$P,上年实际!$K:$K,$B8,上年实际!$L:$L,$C8,上年实际!$M:$M,$D8,上年实际!$N:$N,$E8,上年实际!$C:$C,">="&DATE(YEAR(主页!$D$2)-1,1,1),上年实际!$C:$C,"<="&DATE(YEAR(主页!$D$2),12,31)) -> 0 | H8: =SUMIFS(上年实际!$V:$V,上年实际!$K:$K,$B8,上年实际!$L:$L,$C8,上年实际!$M:$M,$D8,上年实际!$N:$N,$E8,上年实际!$C:$C,">="&DATE(YEAR(主页!$D$2)-1,1,1),上年实际!$C:$C,"<="&DATE(YEAR(主页!$D$2),12,31)) -> 0 | I8: =SUMIFS(当年实际!$O:$O,当年实际!$K:$K,$B8,当年实际!$L:$L,$C8,当年实际!$M:$M,$D8,当年实际!$N:$N,$E8,当年实际!$C:$C,">="&DATE(YEAR(主页!$D$2),1,1),当年实际!$C:$C,"<="&EOMONTH(DATE(YEAR(主页!$D$2),MONTH(主页!$D$2),1),0)) -> 0 | J8: =SUMIFS(当年实际!$P:$P,当年实际!$K:$K,$B8,当年实际!$L:$L,$C8,当年实际!$M:$M,$D8,当年实际!$N:$N,$E8,当年实际!$C:$C,">="&DATE(YEAR(主页!$D$2),1,1),当年实际!$C:$C,"<="&EOMONTH(DATE(YEAR(主页!$D$2),MONTH(主页!$D$2),1),0)) -> 0 | K8: =SUMIFS(当年实际!$V:$V,当年实际!$K:$K,$B8,当年实际!$L:$L,$C8,当年实际!$M:$M,$D8,当年实际!$N:$N,$E8,当年实际!$C:$C,">="&DATE(YEAR(主页!$D$2),1,1),当年实际!$C:$C,"<="&EOMONTH(DATE(YEAR(主页!$D$2),MONTH(主页!$D$2),1),0)) -> 0 | L8: =SUMIFS('当年估计 产品'!$E:$E,'当年估计 产品'!$A:$A,$C8,'当年估计 产品'!$B:$B,$D8,'当年估计 产品'!$C:$C,$B8,'当年估计 产品'!$D:$D,$E8) -> 65 | M8: =SUMIFS('当年估计 产品'!$F:$F,'当年估计 产品'!$A:$A,$C8,'当年估计 产品'!$B:$B,$D8,'当年估计 产品'!$C:$C,$B8,'当年估计 产品'!$D:$D,$E8) -> 1500 | N8: =SUMIFS('当年估计 产品'!$L:$L,'当年估计 产品'!$A:$A,$C8,'当年估计 产品'!$B:$B,$D8,'当年估计 产品'!$C:$C,$B8,'当年估计 产品'!$D:$D,$E8) -> 655 | O8: =I8+L8 -> 65 | P8: =J8+M8 -> 1500 | Q8: =K8+N8 -> 655 | R8: =IFERROR(G8/F8,"na") -> na | S8: =IFERROR(P8/O8,"na") -> 23.076923 | T8: =O8*IF(R8="NA",IF(S8="NA",0,S8),R8) -> 1500 | U8: =T8-G8 -> 1500 | V8: =P8-G8-U8 -> 0 | W8: =P8-G8 -> 1500 | X8: =IFERROR((G8-H8)/F8,"NA") -> NA | Y8: =IFERROR((P8-Q8)/O8,"NA") -> 13 | Z8: =O8*IF(X8="NA",IF(Y8="NA",0,Y8),X8) -> 845 | AA8: =Z8-(G8-H8) -> 845 | AB8: =AC8-AA8 -> 0 | AC8: =(P8-Q8)-(G8-H8) -> 845 | AD8: =Q8-G8/SUM(G:G)*SUM(P:P)*Q8/P8 -> 655 | AE8: =SUMIFS('下年预算 产品'!$E:$E,'下年预算 产品'!$A:$A,$C8,'下年预算 产品'!$B:$B,$D8,'下年预算 产品'!$C:$C,$B8,'下年预算 产品'!$D:$D,$E8) -> 240 | AF8: =SUMIFS('下年预算 产品'!$F:$F,'下年预算 产品'!$A:$A,$C8,'下年预算 产品'!$B:$B,$D8,'下年预算 产品'!$C:$C,$B8,'下年预算 产品'!$D:$D,$E8) -> 4000 | AG8: =SUMIFS('下年预算 产品'!$L:$L,'下年预算 产品'!$A:$A,$C8,'下年预算 产品'!$B:$B,$D8,'下年预算 产品'!$C:$C,$B8,'下年预算 产品'!$D:$D,$E8) -> 640 | AH8: =IFERROR(P8/O8,"na") -> 23.076923 | AI8: =IFERROR(AF8/AE8,"na") -> 16.666667 | AJ8: =AE8*IF(AH8="NA",IF(AI8="NA",0,AI8),AH8) -> 5538.4615 | AK8: =AJ8-P8 -> 4038.4615 | AL8: =AF8-P8-AK8 -> -1538.4615 | AM8: =AF8-P8 -> 2500 | AN8: =IFERROR((P8-Q8)/O8,"NA") -> 13 | AO8: =IFERROR((AF8-AG8)/AE8,"NA") -> 14 | AP8: =AE8*IF(AN8="NA",IF(AO8="NA",0,AO8),AN8) -> 3120 | AQ8: =AP8-(P8-Q8) -> 2275 | AR8: =(AF8-AG8)-(P8-Q8)-(AP8-(P8-Q8)) -> 240 | AS8: =(AF8-AG8)-(P8-Q8) -> 2515 | AT8: =AG8-P8/SUM(P:P)*SUM(AF:AF)*AG8/AF8 -> 210.33248

Sheet 产品销售及毛利影响因素分析
B2: 项目 | E2: ="A"&YEAR(主页!$D$2)-1 -> A2020 | G2: ="E"&YEAR(主页!$D$2) -> E2021 | H2: ="E"&YEAR(主页!$D$2)&"/A"&YEAR(主页!$D$2)-1 -> E2021/A2020 | K2: ="B"&YEAR(主页!$D$2)+1 -> B2022 | L2: ="B"&YEAR(主页!$D$2)+1&"/E"&YEAR(主页!$D$2) -> B2022/E2021 | O2: 返回主页
H3: 差异 | I3: % | L3: 差异 | M3: %
B4: 销售收入 | E4: =SUM(销售对比分析底稿!G:G) -> 5046.0377 | G4: =SUM(销售对比分析底稿!P:P) -> 14858 | H4: =G4-E4 -> 9811.9623 | I4: =H4/E4 -> 1.9444885 | K4: =SUM(销售对比分析底稿!AF:AF) -> 26600 | L4: =K4-G4 -> 11742 | M4: =L4/G4 -> 0.79028133
E5: =ROUND(ABS(SUMIFS(上年实际!$P:$P,上年实际!$C:$C,">="&DATE(YEAR(主页!$D$2)-1,1,1),上年实际!$C:$C,"<="&EOMONTH(DATE(YEAR(主页!$D$2),12,1),0))-E4),0) -> 0 | G5: =ROUND(ABS(SUMIFS(当年实际!$P:$P,当年实际!$C:$C,">="&DATE(YEAR(主页!$D$2),1,1),当年实际!$C:$C,"<="&EOMONTH(DATE(YEAR(主页!$D$2),MONTH(主页!$D$2),1),0))+SUM('当年估计 产品'!$F:$F)-G4),0) -> 0 | K5: =SUM('下年预算 产品'!$F:$F)-K4 -> 0
C6: 销量变化影响 | H6: =SUM(销售对比分析底稿!U:U) -> 7261.5434 | I6: =H6/E4 -> 1.4390585 | L6: =SUM(销售对比分析底稿!AK:AK) -> 18118.367 | M6: =L6/G4 -> 1.2194351
C7: 价格变化影响 | H7: =SUM(销售对比分析底稿!V:V) -> 2550.4189 | I7: =H7/(E4+H6) -> 0.20722341 | L7: =SUM(销售对比分析底稿!AL:AL) -> -6376.3667 | M7: =L7/(G4+L6) -> -0.19336171
I8: =1+I4-(1+I6)*(1+I7) -> 0 | M8: =1+M4-(1+M6)*(1+M7) -> 0
B10: 毛利 | E10: =SUM(销售对比分析底稿!H:H) -> 1047.0377 | G10: =SUM(销售对比分析底稿!Q:Q) -> 5351 | H10: =G10-E10 -> 4303.9623 | I10: =H10/E10 -> 4.1106085 | K10: =SUM(销售对比分析底稿!AG:AG) -> 3986 | L10: =K10-G10 -> -1365 | M10: =L10/G10 -> -0.25509251
B11: 毛利率 | E11: =E10/E4 -> 0.20749701 | G11: =G10/G4 -> 0.36014268 | I11: =G11-E11 -> 0.15264568 | K11: =K10/K4 -> 0.14984962 | M11: =K11-G11 -> -0.21029306
E12: =ROUND(ABS(SUMIFS(上年实际!$V:$V,上年实际!$C:$C,">="&DATE(YEAR(主页!$D$2)-1,1,1),上年实际!$C:$C,"<="&EOMONTH(DATE(YEAR(主页!$D$2),12,1),0))-E10),0) -> 0 | G12: =ROUND(ABS(SUMIFS(当年实际!$V:$V,当年实际!$C:$C,">="&DATE(YEAR(主页!$D$2),1,1),当年实际!$C:$C,"<="&EOMONTH(DATE(YEAR(主页!$D$2),MONTH(主页!$D$2),1),0))+SUM('当年估计 产品'!$L:$L)-G10),0) -> 0 | K12: =SUM('下年预算 产品'!$L:$L)-K10 -> 0
B14: 因素分析 | G14: 变化幅度 | H14: 影响毛利 | K14: 变化幅度 | L14: 影响毛利
H15: 金额 | I15: % | L15: 金额 | M15: %
C16: 销量变化 | G16: =SUM(销售对比分析底稿!U:U)/E4 -> 1.4390585 | H16: =SUM(销售对比分析底稿!U:U)*E11 -> 1506.7485 | I16: NA | K16: =SUM(销售对比分析底稿!AK:AK)/SUM(销售对比分析底稿!P:P) -> 1.2194351 | L16: =SUM(销售对比分析底稿!AK:AK)*G11 -> 6525.1972 | M16: NA
C17: 售价变化 | G17: =SUM(销售对比分析底稿!V:V)/SUM(销售对比分析底稿!T:T) -> 0.20722341 | H17: =SUM(销售对比分析底稿!V:V) -> 2550.4189 | I17: =H17/G$4 -> 0.17165291 | K17: =SUM(销售对比分析底稿!AL:AL)/SUM(销售对比分析底稿!AJ:AJ) -> -0.19336171 | L17: =SUM(销售对比分析底稿!AL:AL) -> -6376.3667 | M17: =L17/K$4 -> -0.23971303
C18: 成本变化 | G18: =SUM(销售对比分析底稿!AB:AB)/SUM(销售对比分析底稿!Z:Z) -> 0 | H18: =SUM(销售对比分析底稿!AB:AB) -> 0 | I18: =H18/G$4 -> 0 | K18: =SUM(销售对比分析底稿!AR:AR)/SUM(销售对比分析底稿!AP:AP) -> 0.07906666 | L18: =-SUM(销售对比分析底稿!AR:AR) -> -1657 | M18: =L18/K$4 -> -0.062293233
C19: 销售结构 | H19: =SUM(销售对比分析底稿!AD:AD) -> 69.914508 | I19: =H19/G$4 -> 0.0047055128 | L19: =SUM(销售对比分析底稿!AT:AT) -> 1008.5143 | M19: =L19/K$4 -> 0.03791407
C20: 其他 | H20: =H10-SUM(H16:H19) -> 176.88035 | I20: =I11-SUM(I17:I19) -> -0.023712743 | L20: =L10-SUM(L16:L19) -> -865.34481 | M20: =M11-SUM(M17:M19) -> 0.053799135
E23: =E2 -> A2020 | G23: =E10 -> 1047.0377 | K23: =G10 -> 5351 | L23: =G2 -> E2021
E24: =C16 -> 销量变化 | G24: =H16 -> 1506.7485 | K24: =L16 -> 6525.1972 | L24: =C16 -> 销量变化
E25: =C17 -> 售价变化 | G25: =H17 -> 2550.4189 | K25: =L17 -> -6376.3667 | L25: =C17 -> 售价变化
E26: =C18 -> 成本变化 | G26: =H18 -> 0 | K26: =L18 -> -1657 | L26: =C18 -> 成本变化
E27: =C19 -> 销售结构 | G27: =H19 -> 69.914508 | K27: =L19 -> 1008.5143 | L27: =C19 -> 销售结构
E28: =C20 -> 其他 | G28: =H20 -> 176.88035 | K28: =L20 -> -865.34481 | L28: =C20 -> 其他
E29: =G2 -> E2021 | G29: =G10 -> 5351 | K29: =K10 -> 3986 | L29: =K2 -> B2022
