Workbook

Sheet 制造成本
B1: 项目 | F1: 金额 | G1: 理论公式 | H1: 预算方法
B2: 方法1：基于标准成本快速推算
C3: 标准制造成本 | F3: =SUM(销售标准成本!G:G) -> 282940 | G3: =∑产量*单位标准成本 | H3: 先假设存货水平不变化，产量=销量
C4: 预实差异 | H4: 一般情况下，预算时不会出现这类差异。在预算的“标准用量”、“标准单价”、“标准工时”、”标准费率“等标准的计算基础不是来自于最终预算时会出现这种差异
D5: 直接材料
E6: 材料用量差异 | F6: =SUMIFS(标实差异!E:E,标实差异!D:D,$E6) -> -5000 | G6: =∑（实际材料用量-标准材料用量）*标准材料单价 | H6: 逐项检视分析改变材料消耗量变化因素对材料成本的影响
E7: 材料价格差异 | F7: =SUMIFS(标实差异!E:E,标实差异!D:D,$E7) -> -3000 | G7: =∑（实际材料价格-标准材料价格）*实际材料用量 | H7: 逐项检视分析材料价格变化因素对成本的影响
D8: 直接人工 | F8: =SUMIFS(标实差异!E:E,标实差异!D:D,$E8) -> 0 | H8: 标准工费率=人工费预算总额/预算产量下的标准总工时
E9: 人工费率差异 | F9: =SUMIFS(标实差异!E:E,标实差异!D:D,$E9) -> -4000 | G9: =实际薪酬福利总额-∑标准工费率*实际工时 | H9: 逐项检视分析改变人工效率变化因素对人工成本的影响
E10: 人工效率差异 | F10: =SUMIFS(标实差异!E:E,标实差异!D:D,$E10) -> 0 | G10: =（实际工时总额-∑产品标准工时*实际产量）*标准工费率 | H10: 逐项检视分析改变人工费率变化因素对人工成本的影响
D11: 变动制造费用 | F11: =SUMIFS(标实差异!E:E,标实差异!D:D,$E11) -> 0 | H11: 标准变动制费率=变动制造费用预算总额/预算产量下的标准总工时
E12: 耗费差异 | F12: =SUMIFS(标实差异!E:E,标实差异!D:D,$E12) -> 0 | G12: =实际变动制费总额-∑标准费率*产品标准工时*实际产量 | H12: 逐项分析列举可能的差异影响因素
E13: 效率差异 | F13: =SUMIFS(标实差异!E:E,标实差异!D:D,$E13) -> -6000 | G13: =∑（实际总工时-实际产量*产品标准工时）*标准费率 | H13: 逐项分析列举可能的差异影响因素
D14: 固定制造费用差异 | F14: =SUMIFS(标实差异!E:E,标实差异!D:D,$E14) -> 0 | H14: 标准固定制费率=固定制造费用预算总额/预算产量下的标准总工时
E15: 管理差异 | F15: =SUMIFS(标实差异!E:E,标实差异!D:D,$E15) -> 0 | G15: =费用实际数-费用预算数 | H15: 逐项分析列举可能的差异影响因素
E16: 产能利用差异 | F16: =SUMIFS(标实差异!E:E,标实差异!D:D,$E16) -> 0 | G16: =（实际产量-预算产量）*产品标准工时*标准费率 | H16: 逐项分析列举可能的差异影响因素
E17: 效率差异 | F17: =SUMIFS(标实差异!E:E,标实差异!D:D,$E17) -> -6000 | G17: =实际工时总额-实际产量*产品标准工时*标准费率 | H17: 逐项分析列举可能的差异影响因素
C18: 制造成本合计 | F18: =SUM(F3:F17) -> 258940
B20: 方法2：逐项详细计算后归集汇总
C21: 材料成本总额 | F21: =SUM(标准材料!G:G) -> 190940 | G21: =∑BOM用量*材料价格 | H21: 用BOM和产量套算，得到材料用量；再用材料用量乘以材料价格；再求和
C22: 人工成本总额 | F22: =SUM(人工!I:I) -> 50000 | G22: =∑人工数*薪酬福利 | H22: 根据产量推算出工人数；再按薪酬福利标准套算出人工成本总额
C23: 制造费用总额 | F23: =SUM(变动制造费用!C:C) -> 42000 | G23: =∑各种制造费用 | H23: 汇总制造过程中消耗的各种其他费用，材料、人工除外
C24: 制造成本合计 | F24: =SUM(F21:F23) -> 282940
B26: 数据验证
C27: 方法1计算的制造成本合计 | F27: =F18 -> 258940
C28: 方法2计算的制造成本合计 | F28: =F24 -> 282940
C29: 两种方法的差异 | F29: =F27-F28 -> -24000
C30: 其中：
D31: 差异原因1：预算标实差异 | F31: =SUM(F6:F17) -> -24000
D32: 差异原因2
D33: 差异原因3

Sheet 人工
B2: 1.假设预算年度生产量=销量，将销量用BOM里的标准工艺工时进行套算，得出需要预算产量的总标准工时
B3: 2.将当年的生产量用BOM里的标准工艺工时进行套算，得出当年产出产品的总标准工时
B4: 3. 预算人工数=当年人工数*预算总标准工时/当年总标准工时
B5: 4.考虑可能的生产效率变化因素，对预算人工数进行调整
B7: 工作中心 | C7: 工种 | D7: 当年产出总标准工时 | E7: 当年工人数 | F7: 预算产出总标准工时 | G7: 预算工人数 | H7: 平均薪酬福利 | I7: 薪酬福利总额
B8: 成品组装 | C8: 装配工
B9: 金属件加工 | C9: 车工
B10: 注塑 | C10: 注塑技工 | I10: 50000

Sheet Sheet4
A1: 材料用量差异
A2: 材料价格差异
A3: 人工费率差异
A4: 人工效率差异
A5: 耗费差异
A6: 效率差异
A7: 管理差异
A8: 产能利用差异
A9: 效率差异

Sheet 变动制造费用
B2: 费用项目 | C2: 费用金额 | D2: 说明
B3: 水电 | C3: 12000
B4: 辅料 | C4: 30000

Sheet 固定制造费用
B2: 费用项目 | C2: 费用金额 | D2: 说明
B3: 水电 | C3: 12000
B4: 辅料 | C4: 30000
B5: 机器社保折旧 | C5: 560000
B6: 其他折旧 | C6: 4000

Sheet 销售标准成本
B2: 数据来自于销售预算
B3: 产品 | C3: 销售量 | D3: 销售单价 | E3: 销售额 | F3: 单位标准成本 | G3: 销售成本 | H3: 销售毛利 | I3: 毛利率 | K3: 注：销售成本和毛利均基于标准成本计算
B4: A | C4: 3000 | D4: 30 | E4: =C4*D4 -> 90000 | F4: =INDEX(单位标准成本!E:E,MATCH(B4,单位标准成本!B:B,0),1) -> 43.502242 | G4: =C4*F4 -> 130506.73 | H4: =E4-G4 -> -40506.726 | I4: =H4/E4 -> -0.45007474
B5: B | C5: 1200 | D5: 50 | E5: =C5*D5 -> 60000 | F5: =INDEX(单位标准成本!E:E,MATCH(B5,单位标准成本!B:B,0),1) -> 97.877429 | G5: =C5*F5 -> 117452.91 | H5: =E5-G5 -> -57452.915 | I5: =H5/E5 -> -0.95754858
B6: C | C6: 340 | D6: 80 | E6: =C6*D6 -> 27200 | F6: =INDEX(单位标准成本!E:E,MATCH(B6,单位标准成本!B:B,0),1) -> 102.88341 | G6: =C6*F6 -> 34980.359 | H6: =E6-G6 -> -7780.3587 | I6: =H6/E6 -> -0.2860426

Sheet 单位标准成本
B2: 有ERP系统时，直接用ERP系统计算结果
B3: 产品 | C3: 标准材料 | D3: 标准工费 | E3: 标准成本
B4: A | C4: =SUMIFS(标准材料!H:H,标准材料!B:B,B4) -> 27 | D4: =INDEX(标准工费!F:F,MATCH(B4,标准工费!B:B,0),1) -> 16.502242 | E4: =C4+D4 -> 43.502242
B5: B | C5: =SUMIFS(标准材料!H:H,标准材料!B:B,B5) -> 80 | D5: =INDEX(标准工费!F:F,MATCH(B5,标准工费!B:B,0),1) -> 17.877429 | E5: =C5+D5 -> 97.877429
B6: C | C6: =SUMIFS(标准材料!H:H,标准材料!B:B,B6) -> 41 | D6: =INDEX(标准工费!F:F,MATCH(B6,标准工费!B:B,0),1) -> 61.883408 | E6: =C6+D6 -> 102.88341

Sheet 标准材料
B2: BOM(产品的材料用量清单）由技术部门提供。如果缺失，也可以暂时凭经验推算。
B3: 有ERP系统时，直接用ERP系统计算结果
B4: 产品 | C4: 材料 | D4: 单位产品材料用量 | E4: 标准材料单价 | F4: 预算材料用量 | G4: 预算材料成本 | H4: 单位产品材料成本 | I4: 产量 | J4: 预算材料成本
B5: A | C5: A1 | D5: 3 | E5: =INDEX(标准采购价格!C:C,MATCH(C5,标准采购价格!B:B,0),1) -> 3 | F5: =D5*I5 -> 9000 | G5: =F5*E5 -> 27000 | H5: =D5*E5 -> 9 | I5: =INDEX(销售标准成本!C:C,MATCH(B5,销售标准成本!B:B,0),1) -> 3000 | J5: =H5*I5 -> 27000
B6: A | C6: A2 | D6: 2 | E6: =INDEX(标准采购价格!C:C,MATCH(C6,标准采购价格!B:B,0),1) -> 5 | F6: =D6*I6 -> 6000 | G6: =F6*E6 -> 30000 | H6: =D6*E6 -> 10 | I6: =INDEX(销售标准成本!C:C,MATCH(B6,销售标准成本!B:B,0),1) -> 3000 | J6: =H6*I6 -> 30000
B7: A | C7: A3 | D7: 4 | E7: =INDEX(标准采购价格!C:C,MATCH(C7,标准采购价格!B:B,0),1) -> 2 | F7: =D7*I7 -> 12000 | G7: =F7*E7 -> 24000 | H7: =D7*E7 -> 8 | I7: =INDEX(销售标准成本!C:C,MATCH(B7,销售标准成本!B:B,0),1) -> 3000 | J7: =H7*I7 -> 24000
B8: B | C8: B1 | D8: 6 | E8: =INDEX(标准采购价格!C:C,MATCH(C8,标准采购价格!B:B,0),1) -> 4 | F8: =D8*I8 -> 7200 | G8: =F8*E8 -> 28800 | H8: =D8*E8 -> 24 | I8: =INDEX(销售标准成本!C:C,MATCH(B8,销售标准成本!B:B,0),1) -> 1200 | J8: =H8*I8 -> 28800
B9: B | C9: B2 | D9: 8 | E9: =INDEX(标准采购价格!C:C,MATCH(C9,标准采购价格!B:B,0),1) -> 7 | F9: =D9*I9 -> 9600 | G9: =F9*E9 -> 67200 | H9: =D9*E9 -> 56 | I9: =INDEX(销售标准成本!C:C,MATCH(B9,销售标准成本!B:B,0),1) -> 1200 | J9: =H9*I9 -> 67200
B10: C | C10: C1 | D10: 5 | E10: =INDEX(标准采购价格!C:C,MATCH(C10,标准采购价格!B:B,0),1) -> 1 | F10: =D10*I10 -> 1700 | G10: =F10*E10 -> 1700 | H10: =D10*E10 -> 5 | I10: =INDEX(销售标准成本!C:C,MATCH(B10,销售标准成本!B:B,0),1) -> 340 | J10: =H10*I10 -> 1700
B11: C | C11: C2 | D11: 4 | E11: =INDEX(标准采购价格!C:C,MATCH(C11,标准采购价格!B:B,0),1) -> 9 | F11: =D11*I11 -> 1360 | G11: =F11*E11 -> 12240 | H11: =D11*E11 -> 36 | I11: =INDEX(销售标准成本!C:C,MATCH(B11,销售标准成本!B:B,0),1) -> 340 | J11: =H11*I11 -> 12240
B16: 1.假设生产量=销量，将销量用BOM套算，即可计算出材料消耗量
B17: 2. 假设预算年度材料价格保持不变，则材料单价可采用预算的采购价格

Sheet 标准采购价格
B2: 根据对预算年度价格走势的判断，基于历史价格，推测预算价格
B3: 材料 | C3: 当年材料平均单价 | D3: 预算材料单价
B4: A1 | C4: 3 | D4: 3
B5: A2 | C5: 5 | D5: 5
B6: A3 | C6: 2 | D6: 2
B7: B1 | C7: 4 | D7: 4
B8: B2 | C8: 7 | D8: 7
B9: C1 | C9: 1 | D9: 1
B10: C2 | C10: 9 | D10: 9

Sheet 标准工费
B1: 产品的标准工时根据技术资料测算。如果没有技术资料，可以凭经验估算。由于此处的标准工时只用于计算分摊工费的小时工费率，因此，标准工时不“标准”，只要的偏差幅度不要巨大到存在结构性问题，一般不会影响成本计算的准确性。
C3: 小时工费率= | D3: =(SUM(变动制造费用!C:C)+SUM(人工!I:I))/SUM(标准工费!E:E) -> 1.3751868
B5: 产品 | C5: 产量 | D5: 单位标准工时 | E5: 标准工时 | F5: 单位标准工费 | G5: 标准工费
B6: A | C6: =INDEX(销售标准成本!C:C,MATCH(B6,销售标准成本!B:B,0),1) -> 3000 | D6: 12 | E6: =C6*D6 -> 36000 | F6: =D6*$D$3 -> 16.502242 | G6: =E6*$D$3 -> 49506.726
B7: B | C7: =INDEX(销售标准成本!C:C,MATCH(B7,销售标准成本!B:B,0),1) -> 1200 | D7: 13 | E7: =C7*D7 -> 15600 | F7: =D7*$D$3 -> 17.877429 | G7: =E7*$D$3 -> 21452.915
B8: C | C8: =INDEX(销售标准成本!C:C,MATCH(B8,销售标准成本!B:B,0),1) -> 340 | D8: 45 | E8: =C8*D8 -> 15300 | F8: =D8*$D$3 -> 61.883408 | G8: =E8*$D$3 -> 21040.359

Sheet 标实差异
B2: 逐个项目测算，列出对预算年度成本的影响数。仅罗列没有被考虑到标准成本的差异。
B3: 差异事项 | C3: OTR编号 | D3: 差异类型 | E3: 差异额 | F3: 差异说明 | G3: 附表
B4: 供应商谈判降价 | D4: 材料价格差异 | E4: -3000 | F4: 要求塑料件供应商降价5% | G4: NTC
B5: 改进注塑生产工艺降低损耗 | D5: 材料用量差异 | E5: -5000 | F5: 详见项目计划书
B6: 培养多能工 | D6: 人工费率差异 | E6: -4000
B7: 装配车间试行一件流 | D7: 效率差异 | E7: -6000
