Workbook
Name BM: #REF!
Name Database: #REF!
Name GL_accvouch: #REF!
Name UFPrn20091118105414: #REF!
Name UFPrn20091118105431: #REF!
Name UFPrn20091118112339: #REF!
Name UFPrn20091118135707: #REF!
Name UFPrn20091119090711: #REF!
Name UFPrn20091119093632: #REF!
Name 销售: 'F:\金财\课程研发\财务军团\财务军团D3练习资料\2.0 销售数据（原始数据）.xlsx'!sales[#Data]

Sheet 主页
C5: 预算编制年度实际数截止日期 | D5: 44469
C6: 注意检查表格之间数据取数期间是否一致！
B8: 编制说明：
B9: 1. 利润表预算：
C10: 1.1 利润表的源数据全部取自于其他表格。
C11: 1.2 注意检查数据源是否正确，取数公式是否正确。
B12: 2.现金流预算
C13: 2.1 先做销售及收现预算，根据应收账款管理策略的变化和销售数据预计期末的应收账款余额，反推当期收现金额
C14: 2.2 再做采购及付现预算，根据应付账款管理策略的变化和采购数据预计期末的应付账款余额，反推当期付现金额
C15: 2.3 员工薪酬和日常费用假设产生当期即付现，则可简化为付现额=费用额
C16: 2.4 税金根据销售、采购、利润数据推算。为了简化，如果年度之间变化幅度不大，可以忽略实际发生、申报和实缴的时间差对现金流的影响。反之，则需要考虑。
C17: 2.5 购置资产对现金流的影响一般比较大，需要根据资产预算数据尽量准确估计发生时间和金额。
C18: 2.6 缺口如何补？富余的资金如何用？资金的缺口和结余在预算时就要有计划。
B19: 3.资产负债表预算
C20: 3.1 所有资产科目都可以用公式 期末=期初+变动额 推算出来。
C21: 3.2 一般企业，资产负债表不是特别必要做。
C22: 3.3 企业可根据实际需要，决定是否做资产负债表或是否做完整的预算资产负债表

Sheet  利润表
E2: ="实际"&YEAR(主页!$D$5)-1&"全年" -> 实际2020全年 | H2: ="实际"&"截止"&YEAR(主页!$D$5)-1&"年"&MONTH(主页!$D$5)&"月" -> 实际截止2020年9月 | K2: ="估计"&"从"&YEAR(主页!$D$5)-1&"年"&MONTH(主页!$D$5)+1&"月到年底" -> 估计从2020年10月到年底 | N2: ="估计"&YEAR(主页!$D$5)&"全年" -> 估计2021全年 | Q2: ="预算"&YEAR(主页!$D$5)+1&"全年" -> 预算2022全年
B3: 金额单位：万元 | E3: ="A"&YEAR(主页!$D$5)-1&"FY" -> A2020FY | H3: ="A"&YEAR(主页!$D$5)&TEXT(MONTH(主页!$D$5),"00")&"YTD" -> A202109YTD | K3: ="E"&YEAR(主页!$D$5)&TEXT(MONTH(主页!$D$5),"00")&"YTG" -> E202109YTG | N3: ="E"&YEAR(主页!$D$5)&"FY" -> E2021FY | Q3: ="B"&YEAR(主页!$D$5)+1&"FY" -> B2022FY
E4: 金额 | F4: 占营收% | H4: 金额 | I4: 占营收% | K4: 金额 | L4: 占营收% | N4: 金额 | O4: 占营收% | Q4: 金额 | R4: 占营收%
B5: 主营业务收入 | E5: =INDEX(销售收入及毛利!$1:$1048576,MATCH($B5,销售收入及毛利!$A:$A,0),MATCH(E$3,销售收入及毛利!$4:$4,0)) -> 10046.038 | F5: =E5/E$5 -> 1 | H5: =INDEX(销售收入及毛利!$1:$1048576,MATCH($B5,销售收入及毛利!$A:$A,0),MATCH(H$3,销售收入及毛利!$4:$4,0)) -> 5000 | I5: =H5/H$5 -> 1 | K5: =INDEX(销售收入及毛利!$1:$1048576,MATCH($B5,销售收入及毛利!$A:$A,0),MATCH(K$3,销售收入及毛利!$4:$4,0)) -> 9857.3585 | L5: =K5/K$5 -> 1 | N5: =INDEX(销售收入及毛利!$1:$1048576,MATCH($B5,销售收入及毛利!$A:$A,0),MATCH(N$3,销售收入及毛利!$4:$4,0)) -> 14857.358 | O5: =N5/N$5 -> 1 | Q5: =INDEX(销售收入及毛利!$1:$1048576,MATCH($B5,销售收入及毛利!$A:$A,0),MATCH(Q$3,销售收入及毛利!$4:$4,0)) -> 26600 | R5: =Q5/Q$5 -> 1 | S5: 数据来自于销售及毛利预算表
B6: 主营业务成本 | E6: =INDEX(销售收入及毛利!$1:$1048576,MATCH($B6,销售收入及毛利!$A:$A,0),MATCH(E$3,销售收入及毛利!$4:$4,0)) -> 8160 | F6: =E6/E$5 -> 0.81226054 | H6: =INDEX(销售收入及毛利!$1:$1048576,MATCH($B6,销售收入及毛利!$A:$A,0),MATCH(H$3,销售收入及毛利!$4:$4,0)) -> 4020 | I6: =H6/H$5 -> 0.804 | K6: =INDEX(销售收入及毛利!$1:$1048576,MATCH($B6,销售收入及毛利!$A:$A,0),MATCH(K$3,销售收入及毛利!$4:$4,0)) -> 5751 | L6: =K6/K$5 -> 0.58342202 | N6: =INDEX(销售收入及毛利!$1:$1048576,MATCH($B6,销售收入及毛利!$A:$A,0),MATCH(N$3,销售收入及毛利!$4:$4,0)) -> 9771 | O6: =N6/N$5 -> 0.65765392 | Q6: =INDEX(销售收入及毛利!$1:$1048576,MATCH($B6,销售收入及毛利!$A:$A,0),MATCH(Q$3,销售收入及毛利!$4:$4,0)) -> 21809 | R6: =Q6/Q$5 -> 0.81988722 | S6: 数据来自于销售及毛利预算表
B7: 毛利 | E7: =E5-E6 -> 1886.0377 | F7: =E7/E$5 -> 0.18773946 | H7: =H5-H6 -> 980 | I7: =H7/H$5 -> 0.196 | K7: =K5-K6 -> 4106.3585 | L7: =K7/K$5 -> 0.41657798 | N7: =N5-N6 -> 5086.3585 | O7: =N7/N$5 -> 0.34234608 | Q7: =Q5-Q6 -> 4791 | R7: =Q7/Q$5 -> 0.18011278
B8: 销售及管理费用 | E8: =SUM(E9:E11) -> 2005.3404 | F8: =E8/E$5 -> 0.19961506 | H8: =SUM(H9:H11) -> 1472.7682 | I8: =H8/H$5 -> 0.29455364 | K8: =SUM(K9:K11) -> 570.61471 | L8: =K8/K$5 -> 0.057887182 | N8: =SUM(N9:N11) -> 2043.3829 | O8: =N8/N$5 -> 0.13753339 | Q8: =SUM(Q9:Q11) -> 2767.8811 | R8: =Q8/Q$5 -> 0.10405568
C9: 人力资源费用 | E9: =SUMIFS(人力资源!$G:$G,人力资源!$A:$A,$B$8) -> 1333.7749 | F9: =E9/E$5 -> 0.13276627 | H9: =SUMIFS(人力资源!U:U,人力资源!$A:$A,$B$8) -> 1008.9299 | I9: =H9/H$5 -> 0.20178598 | K9: =SUMIFS(人力资源!AH:AH,人力资源!$A:$A,$B$8) -> 340.40547 | L9: =K9/K$5 -> 0.034533133 | N9: =SUMIFS(人力资源!T:T,人力资源!$A:$A,$B$8) -> 1349.3354 | O9: =N9/N$5 -> 0.090819333 | Q9: =SUMIFS(人力资源!AU:AU,人力资源!$A:$A,$B$8) -> 1361.248 | R9: =Q9/Q$5 -> 0.051174738 | S9: 数据来自于人力资源预算表
C10: 折旧摊销 | E10: =SUMIFS(财务折旧!G:G,财务折旧!$A:$A,$B$8) -> 1.96 | F10: =E10/E$5 -> 0.0001951018 | H10: =SUMIFS(财务折旧!I:I,财务折旧!$A:$A,$B$8) -> 2.3 | I10: =H10/H$5 -> 0.00046 | K10: =SUMIFS(财务折旧!K:K,财务折旧!$A:$A,$B$8) -> 0.49 | L10: =K10/K$5 -> 4.9709057e-05 | N10: =SUMIFS(财务折旧!M:M,财务折旧!$A:$A,$B$8) -> 2.79 | O10: =N10/N$5 -> 0.00018778574 | Q10: =SUMIFS(财务折旧!O:O,财务折旧!$A:$A,$B$8) -> 3.77 | R10: =Q10/Q$5 -> 0.00014172932 | S10: 数据来自于长期资产折旧摊销预算表
C11: 其他费用 | E11: =SUMIFS(日常费用!L:L,日常费用!$A:$A,$B$8) -> 669.60551 | F11: =E11/E$5 -> 0.066653692 | H11: =SUMIFS(日常费用!O:O,日常费用!$A:$A,$B$8) -> 461.53831 | I11: =H11/H$5 -> 0.092307663 | K11: =SUMIFS(日常费用!Q:Q,日常费用!$A:$A,$B$8) -> 229.71923 | L11: =K11/K$5 -> 0.02330434 | N11: =SUMIFS(日常费用!S:S,日常费用!$A:$A,$B$8) -> 691.25755 | O11: =N11/N$5 -> 0.046526275 | Q11: =SUMIFS(日常费用!Y:Y,日常费用!$A:$A,$B$8) -> 1402.8631 | R11: =Q11/Q$5 -> 0.052739213 | S11: 数据来自于日常经营费用预算表
B12: 其他收支 | E12: =其他!G14 -> 1 | F12: =E12/E$5 -> 9.9541732e-05 | H12: =其他!I14 -> 1 | I12: =H12/H$5 -> 0.0002 | K12: =其他!K14 -> 0.5 | L12: =K12/K$5 -> 5.0723528e-05 | N12: =其他!M14 -> 1.5 | O12: =N12/N$5 -> 0.00010096007 | Q12: =其他!O14 -> 1 | R12: =Q12/Q$5 -> 3.7593985e-05 | S12: 数据来自于其他损益科目预算表
B13: 经营利润 | E13: =E7-E8-E12 -> -120.30271 | F13: =E13/E$5 -> -0.01197514 | H13: =H7-H8-H12 -> -493.76822 | I13: =H13/H$5 -> -0.098753644 | K13: =K7-K8-K12 -> 3535.2438 | L13: =K13/K$5 -> 0.35864007 | N13: =N7-N8-N12 -> 3041.4756 | O13: =N13/N$5 -> 0.20471173 | Q13: =Q7-Q8-Q12 -> 2022.1189 | R13: =Q13/Q$5 -> 0.076019508
B14: 财务费用 | E14: =其他!G17 -> 1.9 | F14: =E14/E$5 -> 0.00018912929 | H14: =其他!I17 -> 1.5 | I14: =H14/H$5 -> 0.0003 | K14: =其他!K17 -> 2.4 | L14: =K14/K$5 -> 0.00024347293 | N14: =其他!M17 -> 3.9 | O14: =N14/N$5 -> 0.00026249619 | Q14: =其他!O17 -> -0.5 | R14: =Q14/Q$5 -> -1.8796992e-05 | S14: 数据来自于其他损益科目预算表
B15: 投资收益 | F15: =E15/E$5 -> 0 | I15: =H15/H$5 -> 0 | L15: =K15/K$5 -> 0 | O15: =N15/N$5 -> 0 | R15: =Q15/Q$5 -> 0 | S15: 数据来自于其他损益科目预算表
B16: 补贴收入 | F16: =E16/E$5 -> 0 | I16: =H16/H$5 -> 0 | L16: =K16/K$5 -> 0 | O16: =N16/N$5 -> 0 | R16: =Q16/Q$5 -> 0 | S16: 数据来自于其他损益科目预算表
B17: 税前利润 | E17: =E13-E14+E15+E16 -> -122.20271 | F17: =E17/E$5 -> -0.01216427 | H17: =H13-H14+H15+H16 -> -495.26822 | I17: =H17/H$5 -> -0.099053644 | K17: =K13-K14+K15+K16 -> 3532.8438 | L17: =K17/K$5 -> 0.3583966 | N17: =N13-N14+N15+N16 -> 3037.5756 | O17: =N17/N$5 -> 0.20444923 | Q17: =Q13-Q14+Q15+Q16 -> 2022.6189 | R17: =Q17/Q$5 -> 0.076038305
B18: 税金 | E18: =E19+E20 -> 38.543336 | F18: =E18/E$5 -> 0.0038366704 | H18: =H19+H20 -> 17.602013 | I18: =H18/H$5 -> 0.0035204026 | K18: =K19+K20 -> 801.40118 | L18: =K18/K$5 -> 0.08129979 | N18: =N19+N20 -> 819.00319 | O18: =N18/N$5 -> 0.055124415 | Q18: =Q19+Q20 -> 587.2914 | R18: =Q18/Q$5 -> 0.022078624
C19: 所得税 | E19: =INDEX(税金!$1:$1048576,MATCH($C19,税金!$A:$A,0),MATCH(E$3,税金!$4:$4,0)) -> 0 | F19: =E19/E$5 -> 0 | H19: =INDEX(税金!$1:$1048576,MATCH($C19,税金!$A:$A,0),MATCH(H$3,税金!$4:$4,0)) -> 0 | I19: =H19/H$5 -> 0 | K19: =INDEX(税金!$1:$1048576,MATCH($C19,税金!$A:$A,0),MATCH(K$3,税金!$4:$4,0)) -> 738.59321 | L19: =K19/K$5 -> 0.074928107 | N19: =INDEX(税金!$1:$1048576,MATCH($C19,税金!$A:$A,0),MATCH(N$3,税金!$4:$4,0)) -> 738.59321 | O19: =N19/N$5 -> 0.049712283 | Q19: =INDEX(税金!$1:$1048576,MATCH($C19,税金!$A:$A,0),MATCH(Q$3,税金!$4:$4,0)) -> 511.40473 | R19: =Q19/Q$5 -> 0.019225742 | S19: 数据来自与税金预算
C20: 其他税金 | E20: =INDEX(税金!$1:$1048576,MATCH($C20,税金!$A:$A,0),MATCH(E$3,税金!$4:$4,0)) -> 38.543336 | F20: =E20/E$5 -> 0.0038366704 | H20: =INDEX(税金!$1:$1048576,MATCH($C20,税金!$A:$A,0),MATCH(H$3,税金!$4:$4,0)) -> 17.602013 | I20: =H20/H$5 -> 0.0035204026 | K20: =INDEX(税金!$1:$1048576,MATCH($C20,税金!$A:$A,0),MATCH(K$3,税金!$4:$4,0)) -> 62.807966 | L20: =K20/K$5 -> 0.0063716833 | N20: =INDEX(税金!$1:$1048576,MATCH($C20,税金!$A:$A,0),MATCH(N$3,税金!$4:$4,0)) -> 80.409979 | O20: =N20/N$5 -> 0.0054121316 | Q20: =INDEX(税金!$1:$1048576,MATCH($C20,税金!$A:$A,0),MATCH(Q$3,税金!$4:$4,0)) -> 75.886668 | R20: =Q20/Q$5 -> 0.0028528823 | S20: 数据来自与税金预算
B21: 净利润 | E21: =E17-E18 -> -160.74605 | F21: =E21/E$5 -> -0.01600094 | H21: =H17-H18 -> -512.87023 | I21: =H21/H$5 -> -0.10257405 | K21: =K17-K18 -> 2731.4426 | L21: =K21/K$5 -> 0.27709681 | N21: =N17-N18 -> 2218.5724 | O21: =N21/N$5 -> 0.14932482 | Q21: =Q17-Q18 -> 1435.3275 | R21: =Q21/Q$5 -> 0.053959681

Sheet 现金流
E2: ="实际"&YEAR(主页!$D$5)-1&"全年" -> 实际2020全年 | G2: ="估计"&YEAR(主页!$D$5)&"全年" -> 估计2021全年 | I2: ="预算"&YEAR(主页!$D$5)+1&"全年" -> 预算2022全年 | K2: 现金流除了做预算之外，也有必要每个月做预测，及时规划。
B3: 金额单位：万元 | E3: ="A"&YEAR(主页!$D$5)-1&"FY" -> A2020FY | G3: ="E"&YEAR(主页!$D$5)&"FY" -> E2021FY | I3: ="B"&YEAR(主页!$D$5)+1&"FY" -> B2022FY
E4: 金额 | G4: 金额 | I4: 金额
B5: 上期资金结余 | E5: 23 | G5: =E29 -> 5876.4123 | I5: =G29 -> 2220.7463
B7: 预计资金流入 | E7: =SUM(E8:E10) -> 11264.4 | G7: =SUM(G8:G10) -> 17491.4 | I7: =SUM(I8:I10) -> 30636
C8: 销售回款 | E8: =销售及收现!H15 -> 10964.4 | G8: =销售及收现!T15 -> 17291.4 | I8: =销售及收现!X15 -> 30536 | J8: 数据来自于销售收入及收现预算
C9: 其他资金流入 | E9: 300 | G9: 200 | I9: 100 | J9: 手工填列
C10: …
B12: 预计资金消耗 | E12: =SUM(E13:E18) -> 5410.9877 | G12: =SUM(G13:G18) -> 13147.066 | I12: =SUM(I13:I18) -> 15361.129
C13: 付到期货款 | E13: =生产、采购及付现!F28 -> 3011.11 | G13: =生产、采购及付现!L28 -> 6053.19 | I13: =生产、采购及付现!N28 -> 11318.868 | J13: 数据来自于采购及付现预算
C14: 付员工薪酬 | E14: =人力资源!G87+人力资源!G102+人力资源!G117+人力资源!G132+人力资源!G147 -> 1333.7749 | G14: =人力资源!T87+人力资源!T102+人力资源!T117+人力资源!T132+人力资源!T147 -> 1349.3354 | I14: =人力资源!AU87+人力资源!AU102+人力资源!AU117+人力资源!AU132+人力资源!AU147 -> 1361.248 | J14: 数据来自于人力资源预算
C15: 日常费用 | E15: =日常费用!L14 -> 675.20551 | G15: =日常费用!S14 -> 691.25755 | I15: =日常费用!Y14 -> 1402.8631 | J15: 数据来自于日常费用预算
C16: 支付税金 | E16: =税金!F28 -> 388.9373 | G16: =税金!L28 -> 1550.003 | I16: =税金!N28 -> 1277.1702 | J16: 数据来自于税金预算。为了简便，忽略了纳税申报期和实缴期之间的时间差。
C17: 购置资产付款 | E17: =长期资产!E7 -> 1.96 | G17: =长期资产!G7 -> 3503.28 | I17: =长期资产!I7 -> 0.98 | J17: 数据来自于资产预算
C18: …
B20: 资金盈余或缺口 | E20: =E5+E7-E12 -> 5876.4123 | G20: =G5+G7-G12 -> 10220.746 | I20: =I5+I7-I12 -> 17495.617
B22: 资金补充计划 | E22: =SUM(E23:E27) -> 0 | G22: =SUM(G23:G27) -> -8000 | I22: =SUM(I23:I27) -> -10000
C23: 供应链融资
C24: 向员工及合作伙伴融资
C25: 向金融机构融资 | G25: -8000 | J25: 负数表示还款
C26: 股东投入 | I26: -10000 | J26: 负数表示股东抽出资金
C27: …
B29: 本期资金结余 | E29: =E20+E22 -> 5876.4123 | G29: =G20+G22 -> 2220.7463 | I29: =I20+I22 -> 7495.617

Sheet 资产
E2: ="实际"&YEAR(主页!$D$5)-1&"全年" -> 实际2020全年 | I2: ="估计"&YEAR(主页!$D$5)&"全年" -> 估计2021全年 | M2: ="预算"&YEAR(主页!$D$5)+1&"全年" -> 预算2022全年
E3: ="A"&YEAR(主页!$D$5)-1&"FY" -> A2020FY | I3: ="E"&YEAR(主页!$D$5)&"FY" -> E2021FY | M3: ="B"&YEAR(主页!$D$5)+1&"FY" -> B2022FY
E4: 期初 | F4: 期末 | G4: 变动 | I4: 期初 | J4: 期末 | K4: 变动 | M4: 期初 | N4: 期末 | O4: 变动
B5: 货币资金 | E5: =现金流!E5 -> 23 | F5: =现金流!E29 -> 5876.4123 | G5: =F5-E5 -> 5853.4123 | I5: =现金流!G5 -> 5876.4123 | J5: =现金流!G29 -> 2220.7463 | K5: =J5-I5 -> -3655.6659 | M5: =现金流!I5 -> 2220.7463 | N5: =现金流!I29 -> 7495.617 | O5: =N5-M5 -> 5274.8707
B7: 应收账款 | E7: =销售及收现!H17 -> 3245 | F7: =销售及收现!H18 -> 3593 | G7: =F7-E7 -> 348 | I7: =销售及收现!T17 -> 3593 | J7: =销售及收现!T18 -> 3064 | K7: =J7-I7 -> -529 | M7: =销售及收现!X17 -> 3064 | N7: =销售及收现!X18 -> 4599 | O7: =N7-M7 -> 1535
B9: 存货 | E9: =生产、采购及付现!F5+生产、采购及付现!F12+生产、采购及付现!F22 -> 3423 | F9: =生产、采购及付现!F8+生产、采购及付现!F15+生产、采购及付现!F25 -> 3125.91 | G9: =F9-E9 -> -297.09 | I9: =生产、采购及付现!L5+生产、采购及付现!L12+生产、采购及付现!L22 -> 3125.91 | J9: =生产、采购及付现!L8+生产、采购及付现!L15+生产、采购及付现!L25 -> 3064 | K9: =J9-I9 -> -61.91 | M9: =生产、采购及付现!N5+生产、采购及付现!N12+生产、采购及付现!N22 -> 3064 | N9: =生产、采购及付现!N8+生产、采购及付现!N15+生产、采购及付现!N25 -> 3495.24 | O9: =N9-M9 -> 431.24
B11: 长期资产 | E11: =长期资产!E6-长期资产!E12 -> 1099.3563 | F11: =长期资产!E9-长期资产!E15 -> 968.2875 | G11: =F11-E11 -> -131.06875 | I11: =长期资产!G6-长期资产!G12 -> 968.2875 | J11: =长期资产!G9-长期资产!G15 -> 4256.615 | K11: =J11-I11 -> 3288.3275 | M11: =长期资产!I6-长期资产!G15 -> 4256.615 | N11: =长期资产!I9-长期资产!I15 -> 3970.875 | O11: =N11-M11 -> -285.74
B13: 应付账款 | E13: =生产、采购及付现!F30 -> 2044 | F13: =生产、采购及付现!F31 -> 2155.8 | G13: =F13-E13 -> 111.8 | I13: =生产、采购及付现!L30 -> 2155.8 | J13: =生产、采购及付现!L31 -> 1838.4 | K13: =J13-I13 -> -317.4 | M13: =生产、采购及付现!N30 -> 1838.4 | N13: =生产、采购及付现!N31 -> 2759.4 | O13: =N13-M13 -> 921
B15: 本年利润 | F15: =' 利润表'!E21 -> -160.74605 | G15: =F15-E15 -> -160.74605 | J15: =' 利润表'!N21 -> 2218.5724 | K15: =J15-I15 -> 2218.5724 | N15: =' 利润表'!Q21 -> 1435.3275 | O15: =N15-M15 -> 1435.3275
B17: 所有资产科目都可以用公式 期末=期初+变动额 推算出来。
B18: 一般企业，资产负债表不是特别必要做。
B19: 企业，根据实际需要，决定是否做资产负债表或是否做完整的预算资产负债表

Sheet 税金
F3: ="实际"&YEAR(主页!$D$5)-1&"全年" -> 实际2020全年 | H3: ="实际"&"截止"&YEAR(主页!$D$5)-1&"年"&MONTH(主页!$D$5)&"月" -> 实际截止2020年9月 | J3: ="估计"&"从"&YEAR(主页!$D$5)-1&"年"&MONTH(主页!$D$5)+1&"月到年底" -> 估计从2020年10月到年底 | L3: ="估计"&YEAR(主页!$D$5)&"全年" -> 估计2021全年 | N3: ="预算"&YEAR(主页!$D$5)+1&"全年" -> 预算2022全年
B4: 金额单位：万元 | F4: ="A"&YEAR(主页!$D$5)-1&"FY" -> A2020FY | H4: ="A"&YEAR(主页!$D$5)&TEXT(MONTH(主页!$D$5),"00")&"YTD" -> A202109YTD | J4: ="E"&YEAR(主页!$D$5)&TEXT(MONTH(主页!$D$5),"00")&"YTG" -> E202109YTG | L4: ="E"&YEAR(主页!$D$5)&"FY" -> E2021FY | N4: ="B"&YEAR(主页!$D$5)+1&"FY" -> B2022FY
F5: 金额 | H5: 金额 | J5: 金额 | L5: 金额 | N5: 金额
B6: 增值税 | F6: =IF(F7-F10-F14>0,F7-F10-F14,0) -> 350.39396 | H6: =IF(H7-H10-H14>0,H7-H10-H14,0) -> 160.0183 | J6: =IF(J7-J10-J14>0,J7-J10-J14,0) -> 570.98151 | L6: =IF(L7-L10-L14>0,L7-L10-L14,0) -> 730.99981 | N6: =IF(N7-N10-N14>0,N7-N10-N14,0) -> 689.8788
C7: 销项税额 | F7: =SUM(F8:F9) -> 1266.3623 | H7: =SUM(H8:H9) -> 650 | J7: =SUM(J8:J9) -> 1255.0415 | L7: =SUM(L8:L9) -> 1905.0415 | N7: =SUM(N8:N9) -> 3276
C8: 其中： | D8: 正常销售的销项 | F8: =销售及收现!H14-销售及收现!F14 -> 1266.3623 | H8: =销售及收现!L14-销售及收现!J14 -> 650 | J8: =销售及收现!P14-销售及收现!N14 -> 1255.0415 | L8: =销售及收现!T14-销售及收现!R14 -> 1905.0415 | N8: =销售及收现!X14-销售及收现!V14 -> 3276
D9: 视同销售或其他销售的销项
C10: 进项税额 | F10: =F11-F12+F13 -> 915.9683 | H10: =H11-H12+H13 -> 489.9817 | J10: =J11-J12+J13 -> 684.06 | L10: =L11-L12+L13 -> 1174.0417 | N10: =N11-N12+N13 -> 2586.1212
C11: 其中： | D11: 有专票采购的进项 | F11: =(生产、采购及付现!F9+生产、采购及付现!F18+生产、采购及付现!F26)*0.13 -> 915.9683 | H11: =(生产、采购及付现!H9+生产、采购及付现!H18+生产、采购及付现!H26)*0.13 -> 489.9817 | J11: =(生产、采购及付现!J9+生产、采购及付现!J18+生产、采购及付现!J26)*0.13 -> 684.06 | L11: =(生产、采购及付现!L9+生产、采购及付现!L18+生产、采购及付现!L26)*0.13 -> 1174.0417 | N11: =(生产、采购及付现!N9+生产、采购及付现!N18+生产、采购及付现!N26)*0.13 -> 2586.1212
D12: 减：无票采购的进项
D13: 加：费用中的可抵扣进项
C14: 上期留抵的进项 | H14: =F15 -> 0 | J14: =H15 -> 0 | L14: =F15 -> 0 | N14: =L15 -> 0
C15: 期末留抵的进项 | F15: =IF(F7-F10-F14<=0,-(F7-F10-F14),0) -> 0 | H15: =IF(H7-H10-H14<=0,-(H7-H10-H14),0) -> 0 | J15: =IF(J7-J10-J14<=0,-(J7-J10-J14),0) -> 0 | L15: =IF(L7-L10-L14<=0,-(L7-L10-L14),0) -> 0 | N15: =IF(N7-N10-N14<=0,-(N7-N10-N14),0) -> 0
A16: 所得税 | B16: 所得税 | F16: =F21*$E$17 -> 0 | H16: =H21*$E$17 -> 0 | J16: =L16-H16 -> 738.59321 | L16: =L21*$E$17 -> 738.59321 | N16: =N21*$E$17 -> 511.40473
C17: 所得税率= | E17: 0.25
D18: 税前利润 | F18: =' 利润表'!E7-' 利润表'!E8-' 利润表'!E12-' 利润表'!E14+' 利润表'!E15+' 利润表'!E16 -> -122.20271 | H18: =' 利润表'!H7-' 利润表'!H8-' 利润表'!H12-' 利润表'!H14+' 利润表'!H15+' 利润表'!H16 -> -495.26822 | J18: =' 利润表'!K7-' 利润表'!K8-' 利润表'!K12-' 利润表'!K14+' 利润表'!K15+' 利润表'!K16 -> 3532.8438 | L18: =' 利润表'!N7-' 利润表'!N8-' 利润表'!N12-' 利润表'!N14+' 利润表'!N15+' 利润表'!N16 -> 3037.5756 | N18: =' 利润表'!Q7-' 利润表'!Q8-' 利润表'!Q12-' 利润表'!Q14+' 利润表'!Q15+' 利润表'!Q16 -> 2022.6189
D19: 不能在税前列支的费用 | F19: 20 | H19: 18 | J19: 3 | L19: =H19+J19 -> 21 | N19: 23
D20: 以前年底可弥补亏损 | F20: 2 | L20: =F22 -> 104.20271 | N20: =L22 -> 0
D21: 应纳税所得 | F21: =IF(F18+F19-F20>0,F18+F19-F20,0) -> 0 | H21: =IF(H18+H19-H20>0,H18+H19-H20,0) -> 0 | J21: =IF(J18+J19-J20>0,J18+J19-J20,0) -> 3535.8438 | L21: =IF(L18+L19-L20>0,L18+L19-L20,0) -> 2954.3728 | N21: =IF(N18+N19-N20>0,N18+N19-N20,0) -> 2045.6189
D22: 以后年度可弥补亏损 | F22: =-IF(F18+F19-F20<0,F18+F19-F20,0) -> 104.20271 | H22: =-IF(H18+H19-H20<0,H18+H19-H20,0) -> 477.26822 | J22: =-IF(J18+J19-J20<0,J18+J19-J20,0) -> 0 | L22: =-IF(L18+L19-L20<0,L18+L19-L20,0) -> 0 | N22: =-IF(N18+N19-N20<0,N18+N19-N20,0) -> 0
A23: 其他税金 | B23: 其他税金 | F23: =SUM(F24:F26) -> 38.543336 | H23: =SUM(H24:H26) -> 17.602013 | J23: =SUM(J24:J26) -> 62.807966 | L23: =SUM(L24:L26) -> 80.409979 | N23: =SUM(N24:N26) -> 75.886668
C24: 城建税及教育附加， 税率 | E24: 0.11 | F24: =F6*$E$24 -> 38.543336 | H24: =H6*$E$24 -> 17.602013 | J24: =J6*$E$24 -> 62.807966 | L24: =L6*$E$24 -> 80.409979 | N24: =N6*$E$24 -> 75.886668
C25: 印花税
C26: …
B28: 税金合计 | F28: =SUM(F6,F16,F24:F26) -> 388.9373 | H28: =SUM(H6,H16,H24:H26) -> 177.62031 | J28: =SUM(J6,J16,J24:J26) -> 1372.3827 | L28: =SUM(L6,L16,L24:L26) -> 1550.003 | N28: =SUM(N6,N16,N24:N26) -> 1277.1702

Sheet 其他
G2: 实际2020全年 | I2: 实际截止2020年10月 | K2: 估计从2020年11月到年底 | M2: 估计2021全年 | O2: 预算2022全年
C3: 金额单位：万元 | G3: A2020FY | I3: A202110YTD | K3: E202110YTG | M3: E2021FY | O3: B2022FY
G4: 金额 | I4: 金额 | K4: 金额 | M4: 金额 | O4: 金额
C6: 其他业务收入 | G6: =SUM(G7:G8) -> 3 | I6: =SUM(I7:I8) -> 2 | K6: =SUM(K7:K8) -> 1 | M6: =SUM(M7:M8) -> 3 | O6: =SUM(O7:O8) -> 4
D7: 废料销售 | G7: 3 | I7: 2 | K7: 1 | M7: =I7+K7 -> 3 | O7: 4
D8: …
C10: 其他业务支出 | G10: =SUM(G11:G12) -> 2 | I10: =SUM(I11:I12) -> 1 | K10: =SUM(K11:K12) -> 0.5 | M10: =SUM(M11:M12) -> 1.5 | O10: =SUM(O11:O12) -> 3
D11: 其他材料消耗 | G11: 2 | I11: 1 | K11: 0.5 | M11: =I11+K11 -> 1.5 | O11: 3
D12: …
C14: 收支净额 | G14: =G6-G10 -> 1 | I14: =I6-I10 -> 1 | K14: =K6-K10 -> 0.5 | M14: =M6-M10 -> 1.5 | O14: =O6-O10 -> 1
C17: 财务费用 | G17: =-G18+G19+G20 -> 1.9 | I17: =-I18+I19+I20 -> 1.5 | K17: =-K18+K19+K20 -> 2.4 | M17: =-M18+M19+M20 -> 3.9 | O17: =-O18+O19+O20 -> -0.5
D18: 利息收入 | G18: 2 | I18: 1 | K18: 1 | M18: =I18+K18 -> 2 | O18: 3
D19: 利息支出 | G19: 3 | I19: 2 | K19: 3 | M19: =I19+K19 -> 5 | O19: 2
D20: 银行手续费及其他 | G20: 0.9 | I20: 0.5 | K20: 0.4 | M20: =I20+K20 -> 0.9 | O20: 0.5
C22: 投资收益

Sheet 销售收入及毛利
B2: 销售数据来源：销售收入及毛利预算
B3: 金额单位：万元 | E3: ="实际"&YEAR(主页!$D$5)-1&"全年" -> 实际2020全年 | G3: ="实际"&"截止"&YEAR(主页!$D$5)-1&"年"&MONTH(主页!$D$5)&"月" -> 实际截止2020年9月 | I3: ="估计"&"从"&YEAR(主页!$D$5)-1&"年"&MONTH(主页!$D$5)+1&"月到年底" -> 估计从2020年10月到年底 | K3: ="估计"&YEAR(主页!$D$5)&"全年" -> 估计2021全年 | M3: ="预算"&YEAR(主页!$D$5)+1&"全年" -> 预算2022全年
E4: ="A"&YEAR(主页!$D$5)-1&"FY" -> A2020FY | G4: ="A"&YEAR(主页!$D$5)&TEXT(MONTH(主页!$D$5),"00")&"YTD" -> A202109YTD | I4: ="E"&YEAR(主页!$D$5)&TEXT(MONTH(主页!$D$5),"00")&"YTG" -> E202109YTG | K4: ="E"&YEAR(主页!$D$5)&"FY" -> E2021FY | M4: ="B"&YEAR(主页!$D$5)+1&"FY" -> B2022FY
B5: 外购成品
C6: 销售收入 | E6: =SUMIFS(销售差异分析底稿!$G:$G,销售差异分析底稿!$E:$E,LEFT($B$5,2)) -> 3300 | G6: =SUMIFS(销售差异分析底稿!J:J,销售差异分析底稿!$E:$E,LEFT($B$5,2)) -> 1800 | I6: =SUMIFS(销售差异分析底稿!M:M,销售差异分析底稿!$E:$E,LEFT($B$5,2)) -> 1800 | K6: =SUMIFS(销售差异分析底稿!P:P,销售差异分析底稿!$E:$E,LEFT($B$5,2)) -> 3600 | M6: =SUMIFS(销售差异分析底稿!AF:AF,销售差异分析底稿!$E:$E,LEFT($B$5,2)) -> 4800
C7: 销售成本 | E7: =E6-E8 -> 2970 | G7: =G6-G8 -> 1500 | I7: =I6-I8 -> 1050 | K7: =K6-K8 -> 2550 | M7: =M6-M8 -> 3920
C8: 毛利 | E8: =SUMIFS(销售差异分析底稿!$H:$H,销售差异分析底稿!$E:$E,LEFT($B$5,2)) -> 330 | G8: =SUMIFS(销售差异分析底稿!K:K,销售差异分析底稿!$E:$E,LEFT($B$5,2)) -> 300 | I8: =SUMIFS(销售差异分析底稿!N:N,销售差异分析底稿!$E:$E,LEFT($B$5,2)) -> 750 | K8: =SUMIFS(销售差异分析底稿!Q:Q,销售差异分析底稿!$E:$E,LEFT($B$5,2)) -> 1050 | M8: =SUMIFS(销售差异分析底稿!AG:AG,销售差异分析底稿!$E:$E,LEFT($B$5,2)) -> 880
C9: 毛利率 | E9: =IFERROR(E8/E6,0) -> 0.1 | G9: =IFERROR(G8/G6,0) -> 0.16666667 | I9: =IFERROR(I8/I6,0) -> 0.41666667 | K9: =IFERROR(K8/K6,0) -> 0.29166667 | M9: =IFERROR(M8/M6,0) -> 0.18333333
B11: 自制成品
C12: 销售收入 | E12: =SUMIFS(销售差异分析底稿!$G:$G,销售差异分析底稿!$E:$E,LEFT($B$11,2)) -> 6180 | G12: =SUMIFS(销售差异分析底稿!J:J,销售差异分析底稿!$E:$E,LEFT($B$11,2)) -> 3200 | I12: =SUMIFS(销售差异分析底稿!M:M,销售差异分析底稿!$E:$E,LEFT($B$11,2)) -> 7680 | K12: =SUMIFS(销售差异分析底稿!P:P,销售差异分析底稿!$E:$E,LEFT($B$11,2)) -> 10880 | M12: =SUMIFS(销售差异分析底稿!AF:AF,销售差异分析底稿!$E:$E,LEFT($B$11,2)) -> 19200
C13: 销售成本 | E13: =E12-E14 -> 4830 | G13: =G12-G14 -> 2520 | I13: =I12-I14 -> 4461 | K13: =K12-K14 -> 6981 | M13: =M12-M14 -> 16827
C14: 毛利 | E14: =SUMIFS(销售差异分析底稿!$H:$H,销售差异分析底稿!$E:$E,LEFT($B$11,2)) -> 1350 | G14: =SUMIFS(销售差异分析底稿!K:K,销售差异分析底稿!$E:$E,LEFT($B$11,2)) -> 680 | I14: =SUMIFS(销售差异分析底稿!N:N,销售差异分析底稿!$E:$E,LEFT($B$11,2)) -> 3219 | K14: =SUMIFS(销售差异分析底稿!Q:Q,销售差异分析底稿!$E:$E,LEFT($B$11,2)) -> 3899 | M14: =SUMIFS(销售差异分析底稿!AG:AG,销售差异分析底稿!$E:$E,LEFT($B$11,2)) -> 2373
C15: 毛利率 | E15: =IFERROR(E14/E12,0) -> 0.2184466 | G15: =IFERROR(G14/G12,0) -> 0.2125 | I15: =IFERROR(I14/I12,0) -> 0.41914062 | K15: =IFERROR(K14/K12,0) -> 0.35836397 | M15: =IFERROR(M14/M12,0) -> 0.12359375
B17: 设计服务
C18: 销售收入 | E18: =SUMIFS(销售差异分析底稿!$G:$G,销售差异分析底稿!$E:$E,$B$17) -> 566.03774 | G18: =SUMIFS(销售差异分析底稿!J:J,销售差异分析底稿!$E:$E,$B$17) -> 0 | I18: =SUMIFS(销售差异分析底稿!M:M,销售差异分析底稿!$E:$E,$B$17) -> 377.35849 | K18: =SUMIFS(销售差异分析底稿!P:P,销售差异分析底稿!$E:$E,$B$17) -> 377.35849 | M18: =SUMIFS(销售差异分析底稿!AF:AF,销售差异分析底稿!$E:$E,$B$17) -> 2600
C19: 销售成本 | E19: =E18-E20 -> 360 | G19: =G18-G20 -> 0 | I19: =I18-I20 -> 240 | K19: =K18-K20 -> 240 | M19: =M18-M20 -> 1062
C20: 毛利 | E20: =SUMIFS(销售差异分析底稿!$H:$H,销售差异分析底稿!$E:$E,$B$17) -> 206.03774 | G20: =SUMIFS(销售差异分析底稿!K:K,销售差异分析底稿!$E:$E,$B$17) -> 0 | I20: =SUMIFS(销售差异分析底稿!N:N,销售差异分析底稿!$E:$E,$B$17) -> 137.35849 | K20: =SUMIFS(销售差异分析底稿!Q:Q,销售差异分析底稿!$E:$E,$B$17) -> 137.35849 | M20: =SUMIFS(销售差异分析底稿!AG:AG,销售差异分析底稿!$E:$E,$B$17) -> 1538
C21: 毛利率 | E21: =IFERROR(E20/E18,0) -> 0.364 | G21: =IFERROR(G20/G18,0) -> 0 | I21: =IFERROR(I20/I18,0) -> 0.364 | K21: =IFERROR(K20/K18,0) -> 0.364 | M21: =IFERROR(M20/M18,0) -> 0.59153846
B23: 合计
A24: 主营业务收入 | C24: 销售收入 | E24: =SUMIFS(销售差异分析底稿!$G:$G,销售差异分析底稿!$E:$E,"*") -> 10046.038 | G24: =SUMIFS(销售差异分析底稿!J:J,销售差异分析底稿!$E:$E,"*") -> 5000 | I24: =SUMIFS(销售差异分析底稿!M:M,销售差异分析底稿!$E:$E,"*") -> 9857.3585 | K24: =SUMIFS(销售差异分析底稿!P:P,销售差异分析底稿!$E:$E,"*") -> 14857.358 | M24: =SUMIFS(销售差异分析底稿!AF:AF,销售差异分析底稿!$E:$E,"*") -> 26600 | N24: =ROUND(M24-SUM(M6,M12,M18),0) -> 0
A25: 主营业务成本 | C25: 销售成本 | E25: =E24-E26 -> 8160 | G25: =G24-G26 -> 4020 | I25: =I24-I26 -> 5751 | K25: =K24-K26 -> 9771 | M25: =M24-M26 -> 21809 | N25: =ROUND(M25-SUM(M7,M13,M19),0) -> 0
C26: 毛利 | E26: =SUMIFS(销售差异分析底稿!$H:$H,销售差异分析底稿!$E:$E,"*") -> 1886.0377 | G26: =SUMIFS(销售差异分析底稿!K:K,销售差异分析底稿!$E:$E,"*") -> 980 | I26: =SUMIFS(销售差异分析底稿!N:N,销售差异分析底稿!$E:$E,"*") -> 4106.3585 | K26: =SUMIFS(销售差异分析底稿!Q:Q,销售差异分析底稿!$E:$E,"*") -> 5086.3585 | M26: =SUMIFS(销售差异分析底稿!AG:AG,销售差异分析底稿!$E:$E,"*") -> 4791 | N26: =ROUND(M26-SUM(M8,M14,M20),0) -> 0
C27: 毛利率 | E27: =IFERROR(E26/E24,0) -> 0.18773946 | G27: =IFERROR(G26/G24,0) -> 0.196 | I27: =IFERROR(I26/I24,0) -> 0.41657798 | K27: =IFERROR(K26/K24,0) -> 0.34234608 | M27: =IFERROR(M26/M24,0) -> 0.18011278

Sheet 销售及收现
B2: 销售数据来源：销售收入及毛利预算
B3: 产品分类 （按不同增值税率） | F3: ="实际"&YEAR(主页!$D$5)-1&"全年" -> 实际2020全年 | J3: ="实际"&"截止"&YEAR(主页!$D$5)-1&"年"&MONTH(主页!$D$5)&"月" -> 实际截止2020年9月 | N3: ="估计"&"从"&YEAR(主页!$D$5)-1&"年"&MONTH(主页!$D$5)+1&"月到年底" -> 估计从2020年10月到年底 | R3: ="估计"&YEAR(主页!$D$5)&"全年" -> 估计2021全年 | V3: ="预算"&YEAR(主页!$D$5)+1&"全年" -> 预算2022全年
F4: ="A"&YEAR(主页!$D$5)-1&"FY" -> A2020FY | J4: ="A"&YEAR(主页!$D$5)&TEXT(MONTH(主页!$D$5),"00")&"YTD" -> A202109YTD | N4: ="E"&YEAR(主页!$D$5)&TEXT(MONTH(主页!$D$5),"00")&"YTG" -> E202109YTG | R4: ="E"&YEAR(主页!$D$5)&"FY" -> E2021FY | V4: ="B"&YEAR(主页!$D$5)+1&"FY" -> B2022FY
F5: 不含税销售额 | G5: 税率 | H5: 含税销售额 | J5: 不含税销售额 | K5: 税率 | L5: 含税销售额 | N5: 不含税销售额 | O5: 税率 | P5: 含税销售额 | R5: 不含税销售额 | S5: 税率 | T5: 含税销售额 | V5: 不含税销售额 | W5: 税率 | X5: 含税销售额
B6: 自制 | C6: xx产品 | F6: =SUMIFS(销售差异分析底稿!$G:$G,销售差异分析底稿!$E:$E,$B6&"*") -> 6180 | G6: 0.13 | H6: =F6*(1+G6) -> 6983.4 | J6: =SUMIFS(销售差异分析底稿!$J:$J,销售差异分析底稿!$E:$E,$B6&"*") -> 3200 | K6: 0.13 | L6: =J6*(1+K6) -> 3616 | N6: =SUMIFS(销售差异分析底稿!M:M,销售差异分析底稿!$E:$E,$B6&"*") -> 7680 | O6: 0.13 | P6: =N6*(1+O6) -> 8678.4 | R6: =J6+N6 -> 10880 | S6: =IFERROR(T6/R6-1,"-") -> 0.13 | T6: =L6+P6 -> 12294.4 | V6: =SUMIFS(销售差异分析底稿!AF:AF,销售差异分析底稿!$E:$E,$B6&"*") -> 19200 | W6: 0.13 | X6: =V6*(1+W6) -> 21696
B7: 外购 | C7: xx产品 | F7: =SUMIFS(销售差异分析底稿!$G:$G,销售差异分析底稿!$E:$E,$B7&"*") -> 3300 | G7: 0.13 | H7: =F7*(1+G7) -> 3729 | J7: =SUMIFS(销售差异分析底稿!$J:$J,销售差异分析底稿!$E:$E,$B7&"*") -> 1800 | K7: 0.13 | L7: =J7*(1+K7) -> 2034 | N7: =SUMIFS(销售差异分析底稿!M:M,销售差异分析底稿!$E:$E,$B7&"*") -> 1800 | O7: 0.13 | P7: =N7*(1+O7) -> 2034 | R7: =J7+N7 -> 3600 | S7: =IFERROR(T7/R7-1,"-") -> 0.13 | T7: =L7+P7 -> 4068 | V7: =SUMIFS(销售差异分析底稿!AF:AF,销售差异分析底稿!$E:$E,$B7&"*") -> 4800 | W7: 0.13 | X7: =V7*(1+W7) -> 5424
B8: 安装服务 | C8: xx工程安装 | F8: =SUMIFS(销售差异分析底稿!$G:$G,销售差异分析底稿!$E:$E,$B8&"*") -> 0 | G8: 0.09 | H8: =F8*(1+G8) -> 0 | J8: =SUMIFS(销售差异分析底稿!$J:$J,销售差异分析底稿!$E:$E,$B8&"*") -> 0 | K8: 0.09 | L8: =J8*(1+K8) -> 0 | N8: =SUMIFS(销售差异分析底稿!M:M,销售差异分析底稿!$E:$E,$B8&"*") -> 0 | O8: 0.09 | P8: =N8*(1+O8) -> 0 | R8: =J8+N8 -> 0 | S8: =IFERROR(T8/R8-1,"-") -> - | T8: =L8+P8 -> 0 | V8: =SUMIFS(销售差异分析底稿!AF:AF,销售差异分析底稿!$E:$E,$B8&"*") -> 0 | W8: 0.09 | X8: =V8*(1+W8) -> 0
B9: 设计服务 | C9: xx设计 | F9: =SUMIFS(销售差异分析底稿!$G:$G,销售差异分析底稿!$E:$E,$B9&"*") -> 566.03774 | G9: 0.06 | H9: =F9*(1+G9) -> 600 | J9: =SUMIFS(销售差异分析底稿!$J:$J,销售差异分析底稿!$E:$E,$B9&"*") -> 0 | K9: 0.06 | L9: =J9*(1+K9) -> 0 | N9: =SUMIFS(销售差异分析底稿!M:M,销售差异分析底稿!$E:$E,$B9&"*") -> 377.35849 | O9: 0.06 | P9: =N9*(1+O9) -> 400 | R9: =J9+N9 -> 377.35849 | S9: =IFERROR(T9/R9-1,"-") -> 0.06 | T9: =L9+P9 -> 400 | V9: =SUMIFS(销售差异分析底稿!AF:AF,销售差异分析底稿!$E:$E,$B9&"*") -> 2600 | W9: 0.06 | X9: =V9*(1+W9) -> 2756
G10: 0.05 | H10: =F10*(1+G10) -> 0 | K10: 0.05 | L10: =J10*(1+K10) -> 0 | O10: 0.05 | P10: =N10*(1+O10) -> 0 | R10: =J10+N10 -> 0 | S10: =IFERROR(T10/R10-1,"-") -> - | T10: =L10+P10 -> 0 | W10: 0.05 | X10: =V10*(1+W10) -> 0
G11: 0.03 | H11: =F11*(1+G11) -> 0 | K11: 0.03 | L11: =J11*(1+K11) -> 0 | O11: 0.03 | P11: =N11*(1+O11) -> 0 | R11: =J11+N11 -> 0 | S11: =IFERROR(T11/R11-1,"-") -> - | T11: =L11+P11 -> 0 | W11: 0.03 | X11: =V11*(1+W11) -> 0
G12: 0.01 | H12: =F12*(1+G12) -> 0 | K12: 0.01 | L12: =J12*(1+K12) -> 0 | O12: 0.01 | P12: =N12*(1+O12) -> 0 | R12: =J12+N12 -> 0 | S12: =IFERROR(T12/R12-1,"-") -> - | T12: =L12+P12 -> 0 | W12: 0.01 | X12: =V12*(1+W12) -> 0
G13: 0 | H13: =F13*(1+G13) -> 0 | K13: 0 | L13: =J13*(1+K13) -> 0 | O13: 0 | P13: =N13*(1+O13) -> 0 | R13: =J13+N13 -> 0 | S13: =IFERROR(T13/R13-1,"-") -> - | T13: =L13+P13 -> 0 | W13: 0 | X13: =V13*(1+W13) -> 0
B14: 合计 | F14: =SUM(F6:F12) -> 10046.038 | H14: =SUM(H6:H13) -> 11312.4 | J14: =SUM(J6:J12) -> 5000 | L14: =SUM(L6:L13) -> 5650 | N14: =SUM(N6:N12) -> 9857.3585 | P14: =SUM(P6:P13) -> 11112.4 | R14: =SUM(R6:R12) -> 14857.358 | T14: =SUM(T6:T13) -> 16762.4 | V14: =SUM(V6:V12) -> 26600 | X14: =SUM(X6:X13) -> 29876
B15: 其中：销售回款收现 | H15: =H14-H19 -> 10964.4 | L15: =L14-L19 -> 6048 | P15: =P14-P19 -> 11243.4 | T15: =T14-T19 -> 17291.4 | X15: =X14-X19 -> 30536
B17: 期初应收账款 | F17: 数据取于营运资金预算表-> | H17: =[1]应收账款!$E$7 -> 3245 | J17: 数据取于营运资金预算表-> | L17: =H18 -> 3593 | N17: 数据取于营运资金预算表-> | P17: =L18 -> 3195 | R17: 数据取于营运资金预算表-> | T17: =H18 -> 3593 | V17: 数据取于营运资金预算表-> | X17: =T18 -> 3064
B18: 期末应收账款 | F18: 数据取于营运资金预算表-> | H18: =[1]应收账款!$Q$7 -> 3593 | J18: 数据取于营运资金预算表-> | L18: =INDEX([1]应收账款!$12:$12,1,MATCH(MONTH(主页!$D$5),[1]应收账款!$3:$3,0)) -> 3195 | N18: 数据取于营运资金预算表-> | P18: =[1]应收账款!$Q$12 -> 3064 | R18: 数据取于营运资金预算表-> | T18: =P18 -> 3064 | V18: 数据取于营运资金预算表-> | X18: =[1]应收账款!$Q$17 -> 4599
B19: 应收余额增（+）减（-） | H19: =H18-H17 -> 348 | L19: =L18-L17 -> -398 | P19: =P18-P17 -> -131 | T19: =T18-T17 -> -529 | X19: =P19+T19 -> -660
B20: 应收款控制策略说明：

Sheet 销售差异分析底稿
B2: 产品名称 | C2: 产品大类 | D2: 产品子类 | E2: 产品类型 | F2: A2020FY | G2: A2020FY | H2: A2020FY | I2: A202109YTD | J2: A202109YTD | K2: A202109YTD | L2: E202109YTG | M2: E202109YTG | N2: E202109YTG | O2: E2021FY | P2: E2021FY | Q2: E2021FY | R2: E2021/A2020 | AE2: B2022FY | AF2: B2022FY | AG2: B2022FY | AH2: B2022/E2021
F3: 销量 | G3: 销售额 | H3: 毛利 | I3: 销量 | J3: 销售额 | K3: 毛利 | L3: 销量 | M3: 销售额 | N3: 毛利 | O3: 销量 | P3: 销售额 | Q3: 毛利 | R3: p1 | S3: p2 | T3: q2*p1 | U3: 量差 | V3: 价差 | W3: STV | X3: c1 | Y3: c2 | Z3: q2*c1 | AA3: 量差c | AB3: 成本差 | AC3: CTV | AD3: 结构差 | AE3: 销量 | AF3: 销售额 | AG3: 毛利 | AH3: p1 | AI3: p2 | AJ3: q2*p1 | AK3: 量差p | AL3: 价差 | AM3: STV | AN3: c1 | AO3: c2 | AP3: q2*c1 | AQ3: 量差c | AR3: 成本差 | AS3: CTV | AT3: 结构差
B4: A0111 | C4: PA | D4: PA01 | E4: 外购 | F4: 198 | G4: 3300 | H4: 330 | I4: 100 | J4: 1800 | K4: 300 | L4: 70 | M4: 1800 | N4: 750 | O4: 170 | P4: 3600 | Q4: 1050 | R4: 16.666667 | S4: 21.176471 | T4: 2833.3333 | U4: -466.66667 | V4: 766.66667 | W4: 300 | X4: 15 | Y4: 15 | Z4: 2550 | AA4: -420 | AB4: 0 | AC4: -420 | AD4: -373.46743 | AE4: 280 | AF4: 4800 | AG4: 880 | AH4: 21.176471 | AI4: 17.142857 | AJ4: 5929.4118 | AK4: 2329.4118 | AL4: -1129.4118 | AM4: 1200 | AN4: 15 | AO4: 14 | AP4: 4200 | AQ4: 1650 | AR4: -280 | AS4: 1370 | AT4: -301.6367
B5: B0122 | C5: PB | D5: PB01 | E5: 自制 | F5: 245 | G5: 3980 | H5: 550 | I5: 124 | J5: 2000 | K5: 264 | L5: 178 | M5: 3980 | N5: 1488 | O5: 302 | P5: 5980 | Q5: 1752 | R5: 16.244898 | S5: 19.801325 | T5: 4905.9592 | U5: 925.95918 | V5: 1074.0408 | W5: 2000 | X5: 14 | Y5: 14 | Z5: 4228 | AA5: 798 | AB5: 0 | AC5: 798 | AD5: 27.501634 | AE5: 640 | AF5: 10000 | AG5: 1040 | AH5: 19.801325 | AI5: 15.625 | AJ5: 12672.848 | AK5: 6692.8477 | AL5: -2672.8477 | AM5: 4020 | AN5: 14 | AO5: 14 | AP5: 8960 | AQ5: 4732 | AR5: 0 | AS5: 4732 | AT5: -73.459839
B6: C0122 | C6: PC | D6: PC01 | E6: 自制 | F6: 200 | G6: 2200 | H6: 800 | I6: 112 | J6: 1200 | K6: 416 | L6: 142 | M6: 2200 | N6: 1206 | O6: 254 | P6: 3400 | Q6: 1622 | R6: 11 | S6: 13.385827 | T6: 2794 | U6: 594 | V6: 606 | W6: 1200 | X6: 7 | Y6: 7 | Z6: 1778 | AA6: 378 | AB6: 0 | AC6: 378 | AD6: 69.822403 | AE6: 533 | AF6: 5200 | AG6: 693 | AH6: 13.385827 | AI6: 9.7560976 | AJ6: 7134.6457 | AK6: 3734.6457 | AL6: -1934.6457 | AM6: 1800 | AN6: 7 | AO6: 8.4559099 | AP6: 3731 | AQ6: 1953 | AR6: 776 | AS6: 2729 | AT6: -118.23904
B7: C0199 | C7: SE | D7: SE99 | E7: 设计服务 | F7: 3 | G7: 566.03774 | H7: 206.03774 | I7: 0 | J7: 0 | K7: 0 | L7: 2 | M7: 377.35849 | N7: 137.35849 | O7: 2 | P7: 377.35849 | Q7: 137.35849 | R7: 188.67925 | S7: 188.67925 | T7: 377.35849 | U7: -188.67925 | V7: 0 | W7: -188.67925 | X7: 120 | Y7: 120 | Z7: 240 | AA7: -120 | AB7: 0 | AC7: -120 | AD7: -167.35632 | AE7: 9 | AF7: 2600 | AG7: 1538 | AH7: 188.67925 | AI7: 288.88889 | AJ7: 1698.1132 | AK7: 1320.7547 | AL7: 901.88679 | AM7: 2222.6415 | AN7: 120 | AO7: 118 | AP7: 1080 | AQ7: 840 | AR7: -18 | AS7: 822 | AT7: 1138.3525
B8: A0111 | C8: PA | D8: PA01 | E8: 自制 | F8: 0 | G8: 0 | H8: 0 | I8: 0 | J8: 0 | K8: 0 | L8: 65 | M8: 1500 | N8: 525 | O8: 65 | P8: 1500 | Q8: 525 | R8: na | S8: 23.076923 | T8: 1500 | U8: 1500 | V8: 0 | W8: 1500 | X8: NA | Y8: 15 | Z8: 975 | AA8: 975 | AB8: 0 | AC8: 975 | AD8: 525 | AE8: 240 | AF8: 4000 | AG8: 640 | AH8: 23.076923 | AI8: 16.666667 | AJ8: 5538.4615 | AK8: 4038.4615 | AL8: -1538.4615 | AM8: 2500 | AN8: 15 | AO8: 14 | AP8: 3600 | AQ8: 2625 | AR8: -240 | AS8: 2385 | AT8: 210.31393

Sheet 生产、采购及付现
B2: 金额单位：万元 | F2: ="实际"&YEAR(主页!$D$5)-1&"全年" -> 实际2020全年 | H2: ="实际"&"截止"&YEAR(主页!$D$5)-1&"年"&MONTH(主页!$D$5)&"月" -> 实际截止2020年9月 | J2: ="估计"&"从"&YEAR(主页!$D$5)-1&"年"&MONTH(主页!$D$5)+1&"月到年底" -> 估计从2020年10月到年底 | L2: ="估计"&YEAR(主页!$D$5)&"全年" -> 估计2021全年 | N2: ="预算"&YEAR(主页!$D$5)+1&"全年" -> 预算2022全年
F3: ="A"&YEAR(主页!$D$5)-1&"FY" -> A2020FY | H3: ="A"&YEAR(主页!$D$5)&TEXT(MONTH(主页!$D$5),"00")&"YTD" -> A202109YTD | J3: ="E"&YEAR(主页!$D$5)&TEXT(MONTH(主页!$D$5),"00")&"YTG" -> E202109YTG | L3: ="E"&YEAR(主页!$D$5)&"FY" -> E2021FY | N3: ="B"&YEAR(主页!$D$5)+1&"FY" -> B2022FY
B4: 外购成品
C5: 期初库存 | F5: =[1]存货!$F$8 -> 1026.9 | H5: =F8 -> 1077.9 | J5: =H8 -> 958.5 | L5: =F8 -> 1077.9 | N5: =L8 -> 919.2 | O5: 数据取于营运资金预算表
C6: 外购成品销售成本 | F6: =销售收入及毛利!E7 -> 2970 | H6: =销售收入及毛利!G7 -> 1500 | J6: =销售收入及毛利!I7 -> 1050 | L6: =销售收入及毛利!K7 -> 2550 | N6: =销售收入及毛利!M7 -> 3920 | O6: 数据来自于销售成本预算
C7: 领用损耗 | F7: 12 | H7: 3 | J7: 1 | L7: =H7+J7 -> 4 | N7: 4 | O7: 根据经验估计
C8: 期末库存 | F8: =[1]存货!$R$8 -> 1077.9 | H8: =INDEX([1]存货!$16:$16,1,MATCH(MONTH(主页!$D$5),[1]存货!$3:$3,0)) -> 958.5 | J8: =[1]存货!$R$16 -> 919.2 | L8: =J8 -> 919.2 | N8: =[1]存货!$R$24 -> 1048.572 | O8: 数据取于营运资金预算表
C9: 本期采购额 | F9: =F6-F5+F7+F8 -> 3033 | H9: =H6-H5+H7+H8 -> 1383.6 | J9: =J6-J5+J7+J8 -> 1011.7 | L9: =L6-L5+L7+L8 -> 2395.3 | N9: =N6-N5+N7+N8 -> 4053.372 | O9: 自动计算
B11: 自制产品
C12: 期初库存 | F12: =[1]存货!$F$10 -> 684.6 | H12: =F15 -> 718.6 | J12: =H15 -> 639 | L12: =F15 -> 718.6 | N12: =L15 -> 612.8 | O12: 数据取于营运资金预算表
C13: 自制产品销售成本 | F13: =销售收入及毛利!E13 -> 4830 | H13: =销售收入及毛利!G13 -> 2520 | J13: =销售收入及毛利!I13 -> 4461 | L13: =销售收入及毛利!K13 -> 6981 | N13: =销售收入及毛利!M13 -> 16827 | O13: 数据来自于销售成本预算
C14: 领用损耗 | F14: 10 | H14: 5 | J14: 3 | L14: =H14+J14 -> 8 | N14: 7 | O14: 根据经验估计
C15: 期末库存 | F15: =[1]存货!$R$10 -> 718.6 | H15: =INDEX([1]存货!$18:$18,1,MATCH(MONTH(主页!$D$5),[1]存货!$3:$3,0)) -> 639 | J15: =[1]存货!$R$18 -> 612.8 | L15: =J15 -> 612.8 | N15: =[1]存货!$R$26 -> 699.048 | O15: 数据取于营运资金预算表
C16: 本期生产成本 | F16: =F13-F12+F14+F15 -> 4874 | H16: =H13-H12+H14+H15 -> 2445.4 | J16: =J13-J12+J14+J15 -> 4437.8 | L16: =L13-L12+L14+L15 -> 6883.2 | N16: =N13-N12+N14+N15 -> 16920.248 | O16: 自动计算
C17: 其中： | D17: 自制成品的材料成本 | F17: 3500 | H17: =H16-H18-H19 -> 1515.4 | J17: =J16-J18-J19 -> 4014.8 | L17: =H17+J17 -> 5530.2 | N17: =N16-N18-N19 -> 12020.248 | O17: 数据来自于制造成本实际核算和预算
D18: 外协加工费 | F18: 890 | H18: 600 | J18: 300 | L18: =H18+J18 -> 900 | N18: 3600 | O18: 数据来自于制造成本实际核算和预算
D19: 人工及制造费用 | F19: =F13-F17-F18 -> 440 | H19: 330 | J19: 123 | L19: =H19+J19 -> 453 | N19: 1300 | O19: 数据来自于制造成本实际核算和预算
B21: 材料及半成品
C22: 期初库存 | F22: =[1]存货!$F$9 -> 1711.5 | H22: =F25 -> 1329.41 | J22: =H25 -> 1597.5 | L22: =F25 -> 1329.41 | N22: =L25 -> 1532 | O22: 数据取于营运资金预算表
C23: 生产消耗 | F23: =F17 -> 3500 | H23: =H17 -> 1515.4 | J23: =J17 -> 4014.8 | L23: =L17 -> 5530.2 | N23: =N17 -> 12020.248 | O23: 数据来自于销售成本预算
C24: 领用损耗 | F24: 5 | H24: 2 | J24: 1 | L24: =H24+J24 -> 3 | N24: 4 | O24: 根据经验估计
C25: 期末库存 | F25: =[1]存货!$R$9 -> 1329.41 | H25: =INDEX([1]存货!$1:$17,17,MATCH(MONTH(主页!$D$5),[1]存货!$3:$3,0)) -> 1597.5 | J25: =[1]存货!$R$17 -> 1532 | L25: =J25 -> 1532 | N25: =[1]存货!$R$25 -> 1747.62 | O25: 数据取于营运资金预算表
C26: 本期采购额 | F26: =F23-F22+F24+F25 -> 3122.91 | H26: =H23-H22+H24+H25 -> 1785.49 | J26: =J23-J22+J24+J25 -> 3950.3 | L26: =L23-L22+L24+L25 -> 5735.79 | N26: =N23-N22+N24+N25 -> 12239.868 | O26: 自动计算
B28: 其中：采购付现 | F28: =F26-F32 -> 3011.11 | H28: =H26-H32 -> 2024.29 | J28: =J26-J32 -> 4028.9 | L28: =L26-L32 -> 6053.19 | N28: =N26-N32 -> 11318.868 | O28: 自动计算
B30: 期初应付账款 | F30: =[1]应付账款!$E$7 -> 2044 | H30: =F31 -> 2155.8 | J30: =H31 -> 1917 | L30: =F31 -> 2155.8 | N30: =L31 -> 1838.4 | O30: 数据取于营运资金预算表
B31: 期末应付账款 | F31: =[1]应付账款!$Q$7 -> 2155.8 | H31: =INDEX([1]应付账款!$12:$12,1,MATCH(MONTH(主页!$D$5),[1]应付账款!$3:$3,0)) -> 1917 | J31: =[1]应付账款!$Q$12 -> 1838.4 | L31: =[1]应付账款!$Q$12 -> 1838.4 | N31: =[1]应付账款!$Q$17 -> 2759.4 | O31: 数据取于营运资金预算表
B32: 应付账款增（+）减（-） | F32: =F31-F30 -> 111.8 | H32: =H31-H30 -> -238.8 | J32: =J31-J30 -> -78.6 | L32: =L31-L30 -> -317.4 | N32: =N31-N30 -> 921 | O32: 自动计算
B33: 应付款控制策略说明：

Sheet 人力资源
B2: 人力资源分类汇总表
C3: 当年实际截止月份 | G3: =主页!D5 -> 44469
B4: 数据来自于人力资源预算表
B5: 金额单位：万元 | G5: ="A"&YEAR($G$3)-1&"FY" -> A2020FY | H5: 其中： | T5: ="E"&YEAR($G$3)&"FY" -> E2021FY | U5: ="A"&YEAR($G$3)&TEXT(MONTH($G$3),"00")&"YTD" -> A202109YTD | V5: 其中： | AH5: ="E"&YEAR($G$3)&TEXT(MONTH($G$3),"00")&"YTG" -> E202109YTG | AI5: 其中： | AU5: ="B"&YEAR($G$3)+1&"FY" -> B2022FY | AV5: 其中：
G6: =LEFT(G5,1) -> A | H6: =LEFT(G5,1) -> A | I6: =H6 -> A | J6: =I6 -> A | K6: =J6 -> A | L6: =K6 -> A | M6: =L6 -> A | N6: =M6 -> A | O6: =N6 -> A | P6: =O6 -> A | ... S6: =R6 -> A | T6: =LEFT(T5,1) -> E | U6: =LEFT(U5,1) -> A | V6: =LEFT(U5,1) -> A | W6: =V6 -> A | X6: =W6 -> A | Y6: =X6 -> A | Z6: =Y6 -> A | AA6: =Z6 -> A | AB6: =AA6 -> A | AC6: =AB6 -> A | AD6: =AC6 -> A | ... AG6: =AF6 -> A | AH6: =LEFT(AH5,1) -> E | AI6: =LEFT(AH5,1) -> E | AJ6: =AI6 -> E | AK6: =AJ6 -> E | AL6: =AK6 -> E | AM6: =AL6 -> E | AN6: =AM6 -> E | AO6: =AN6 -> E | AP6: =AO6 -> E | AQ6: =AP6 -> E | ... AT6: =AS6 -> E | AU6: =LEFT(AU5,1) -> B | AV6: =LEFT(AU5,1) -> B | AW6: =AV6 -> B | AX6: =AW6 -> B | AY6: =AX6 -> B | AZ6: =AY6 -> B | BA6: =AZ6 -> B | BB6: =BA6 -> B | BC6: =BB6 -> B | BD6: =BC6 -> B | ... BG6: =BF6 -> B
G7: 合计 | H7: =YEAR($G$3)-1 -> 2020 | I7: =H7 -> 2020 | J7: =I7 -> 2020 | K7: =J7 -> 2020 | L7: =K7 -> 2020 | M7: =L7 -> 2020 | N7: =M7 -> 2020 | O7: =N7 -> 2020 | P7: =O7 -> 2020 | ... S7: =R7 -> 2020 | T7: 合计 | U7: 合计 | V7: =YEAR($G$3) -> 2021 | W7: =V7 -> 2021 | X7: =W7 -> 2021 | Y7: =X7 -> 2021 | Z7: =Y7 -> 2021 | AA7: =Z7 -> 2021 | AB7: =AA7 -> 2021 | AC7: =AB7 -> 2021 | AD7: =AC7 -> 2021 | ... AG7: =AF7 -> 2021 | AH7: 合计 | AI7: =YEAR($G$3) -> 2021 | AJ7: =AI7 -> 2021 | AK7: =AJ7 -> 2021 | AL7: =AK7 -> 2021 | AM7: =AL7 -> 2021 | AN7: =AM7 -> 2021 | AO7: =AN7 -> 2021 | AP7: =AO7 -> 2021 | AQ7: =AP7 -> 2021 | ... AT7: =AS7 -> 2021 | AU7: 合计 | AV7: =YEAR($G$3)+1 -> 2022 | AW7: =AV7 -> 2022 | AX7: =AW7 -> 2022 | AY7: =AX7 -> 2022 | AZ7: =AY7 -> 2022 | BA7: =AZ7 -> 2022 | BB7: =BA7 -> 2022 | BC7: =BB7 -> 2022 | BD7: =BC7 -> 2022 | ... BG7: =BF7 -> 2022
H8: 1 | I8: 2 | J8: 3 | K8: 4 | L8: 5 | M8: 6 | N8: 7 | O8: 8 | P8: 9 | Q8: 10 | R8: 11 | S8: 12 | V8: 1 | W8: 2 | X8: 3 | Y8: 4 | Z8: 5 | AA8: 6 | AB8: 7 | AC8: 8 | AD8: 9 | AE8: 10 | AF8: 11 | AG8: 12 | AI8: 1 | AJ8: 2 | AK8: 3 | AL8: 4 | AM8: 5 | AN8: 6 | AO8: 7 | AP8: 8 | AQ8: 9 | AR8: 10 | AS8: 11 | AT8: 12 | AV8: 1 | AW8: 2 | AX8: 3 | AY8: 4 | AZ8: 5 | BA8: 6 | BB8: 7 | BC8: 8 | BD8: 9 | BE8: 10 | BF8: 11 | BG8: 12
G9: =DATE(YEAR($G$3)-1,1,1) -> 43831 | H9: =DATE(H7,H8,1) -> 43831 | I9: =DATE(I7,I8,1) -> 43862 | J9: =DATE(J7,J8,1) -> 43891 | K9: =DATE(K7,K8,1) -> 43922 | L9: =DATE(L7,L8,1) -> 43952 | M9: =DATE(M7,M8,1) -> 43983 | N9: =DATE(N7,N8,1) -> 44013 | O9: =DATE(O7,O8,1) -> 44044 | ... S9: =DATE(S7,S8,1) -> 44166 | T9: =DATE(YEAR($G$3),1,1) -> 44197 | U9: =DATE(YEAR($G$3),1,1) -> 44197 | V9: =DATE(V7,V8,1) -> 44197 | W9: =DATE(W7,W8,1) -> 44228 | X9: =DATE(X7,X8,1) -> 44256 | Y9: =DATE(Y7,Y8,1) -> 44287 | Z9: =DATE(Z7,Z8,1) -> 44317 | AA9: =DATE(AA7,AA8,1) -> 44348 | AB9: =DATE(AB7,AB8,1) -> 44378 | AC9: =DATE(AC7,AC8,1) -> 44409 | ... AG9: =DATE(AG7,AG8,1) -> 44531 | AH9: =DATE(YEAR($G$3),MONTH($G$3)+1,1) -> 44470 | AI9: =DATE(AI7,AI8,1) -> 44197 | AJ9: =DATE(AJ7,AJ8,1) -> 44228 | AK9: =DATE(AK7,AK8,1) -> 44256 | AL9: =DATE(AL7,AL8,1) -> 44287 | AM9: =DATE(AM7,AM8,1) -> 44317 | AN9: =DATE(AN7,AN8,1) -> 44348 | AO9: =DATE(AO7,AO8,1) -> 44378 | AP9: =DATE(AP7,AP8,1) -> 44409 | ... AT9: =DATE(AT7,AT8,1) -> 44531 | AU9: =DATE(YEAR($G$3)+1,1,1) -> 44562 | AV9: =DATE(AV7,AV8,1) -> 44562 | AW9: =DATE(AW7,AW8,1) -> 44593 | AX9: =DATE(AX7,AX8,1) -> 44621 | AY9: =DATE(AY7,AY8,1) -> 44652 | AZ9: =DATE(AZ7,AZ8,1) -> 44682 | BA9: =DATE(BA7,BA8,1) -> 44713 | BB9: =DATE(BB7,BB8,1) -> 44743 | BC9: =DATE(BC7,BC8,1) -> 44774 | ... BG9: =DATE(BG7,BG8,1) -> 44896
G10: =EOMONTH(DATE(YEAR($G$3)-1,12,1),0) -> 44196 | H10: =EOMONTH(H9,0) -> 43861 | I10: =EOMONTH(I9,0) -> 43890 | J10: =EOMONTH(J9,0) -> 43921 | K10: =EOMONTH(K9,0) -> 43951 | L10: =EOMONTH(L9,0) -> 43982 | M10: =EOMONTH(M9,0) -> 44012 | N10: =EOMONTH(N9,0) -> 44043 | O10: =EOMONTH(O9,0) -> 44074 | ... S10: =EOMONTH(S9,0) -> 44196 | T10: =EOMONTH(DATE(YEAR($G$3),12,1),0) -> 44561 | U10: =EOMONTH(DATE(YEAR($G$3),MONTH(G3),1),0) -> 44469 | V10: =EOMONTH(V9,0) -> 44227 | W10: =EOMONTH(W9,0) -> 44255 | X10: =EOMONTH(X9,0) -> 44286 | Y10: =EOMONTH(Y9,0) -> 44316 | Z10: =EOMONTH(Z9,0) -> 44347 | AA10: =EOMONTH(AA9,0) -> 44377 | AB10: =EOMONTH(AB9,0) -> 44408 | AC10: =EOMONTH(AC9,0) -> 44439 | ... AG10: =EOMONTH(AG9,0) -> 44561 | AH10: =EOMONTH(DATE(YEAR($G$3),12,1),0) -> 44561 | AI10: =EOMONTH(AI9,0) -> 44227 | AJ10: =EOMONTH(AJ9,0) -> 44255 | AK10: =EOMONTH(AK9,0) -> 44286 | AL10: =EOMONTH(AL9,0) -> 44316 | AM10: =EOMONTH(AM9,0) -> 44347 | AN10: =EOMONTH(AN9,0) -> 44377 | AO10: =EOMONTH(AO9,0) -> 44408 | AP10: =EOMONTH(AP9,0) -> 44439 | ... AT10: =EOMONTH(AT9,0) -> 44561 | AU10: =EOMONTH(DATE(YEAR($G$3)+1,12,1),0) -> 44926 | AV10: =EOMONTH(AV9,0) -> 44592 | AW10: =EOMONTH(AW9,0) -> 44620 | AX10: =EOMONTH(AX9,0) -> 44651 | AY10: =EOMONTH(AY9,0) -> 44681 | AZ10: =EOMONTH(AZ9,0) -> 44712 | BA10: =EOMONTH(BA9,0) -> 44742 | BB10: =EOMONTH(BB9,0) -> 44773 | BC10: =EOMONTH(BC9,0) -> 44804 | ... BG10: =EOMONTH(BG9,0) -> 44926
B11: 注册人数
B12: 合计 | E12: * | F12: * | G12: 70 | H12: 71 | I12: 71 | J12: 71 | K12: 71 | L12: 71 | M12: 71 | N12: 71 | O12: 71 | P12: 71 | Q12: 71 | R12: 70 | S12: 70 | T12: =AT12 -> 68 | U12: 69 | V12: 70 | W12: 70 | X12: 70 | Y12: 68 | Z12: 69 | AA12: 69 | AB12: 70 | AC12: 69 | AD12: 69 | AE12: 0 | AF12: 0 | AG12: 0 | AH12: =AT12 -> 68 | AI12: 0 | AJ12: 0 | AK12: 0 | AL12: 0 | AM12: 0 | AN12: 0 | AO12: 0 | AP12: 0 | AQ12: 0 | AR12: 69 | AS12: 70 | AT12: 68 | AU12: =BG12 -> 74 | AV12: 68 | AW12: 68 | AX12: 73 | AY12: 73 | AZ12: 74 | BA12: 74 | BB12: 74 | BC12: 74 | BD12: 74 | BE12: 74 | BF12: 74 | BG12: 74
C13: 流程中心 | E13: =IF(C13<>"",C13,#REF!) -> 流程中心 | F13: =IF(D13<>"",D13,"*") -> * | G13: 34 | H13: 35 | I13: 35 | J13: 35 | K13: 35 | L13: 35 | M13: 35 | N13: 35 | O13: 35 | P13: 35 | Q13: 35 | R13: 34 | S13: 34 | T13: =AT13 -> 31 | U13: 32 | V13: 34 | W13: 34 | X13: 34 | Y13: 32 | Z13: 33 | AA13: 33 | AB13: 33 | AC13: 32 | AD13: 32 | AE13: 0 | AF13: 0 | AG13: 0 | AH13: =AT13 -> 31 | AI13: 0 | AJ13: 0 | AK13: 0 | AL13: 0 | AM13: 0 | AN13: 0 | AO13: 0 | AP13: 0 | AQ13: 0 | AR13: 32 | AS13: 33 | AT13: 31 | AU13: =BG13 -> 37 | AV13: 31 | AW13: 31 | AX13: 36 | AY13: 36 | AZ13: 37 | BA13: 37 | BB13: 37 | BC13: 37 | BD13: 37 | BE13: 37 | BF13: 37 | BG13: 37
D14: 销售中心 | E14: =IF(C14<>"",C14,E13) -> 流程中心 | F14: =IF(D14<>"",D14,"*") -> 销售中心 | G14: 13 | H14: 13 | I14: 13 | J14: 13 | K14: 13 | L14: 13 | M14: 13 | N14: 13 | O14: 13 | P14: 13 | Q14: 13 | R14: 13 | S14: 13 | T14: =AT14 -> 13 | U14: 13 | V14: 13 | W14: 13 | X14: 13 | Y14: 13 | Z14: 14 | AA14: 14 | AB14: 14 | AC14: 13 | AD14: 13 | AE14: 0 | AF14: 0 | AG14: 0 | AH14: =AT14 -> 13 | AI14: 0 | AJ14: 0 | AK14: 0 | AL14: 0 | AM14: 0 | AN14: 0 | AO14: 0 | AP14: 0 | AQ14: 0 | AR14: 13 | AS14: 13 | AT14: 13 | AU14: =BG14 -> 14 | AV14: 13 | AW14: 13 | AX14: 13 | AY14: 13 | AZ14: 14 | BA14: 14 | BB14: 14 | BC14: 14 | BD14: 14 | BE14: 14 | BF14: 14 | BG14: 14
D15: 制造中心 | E15: =IF(C15<>"",C15,E14) -> 流程中心 | F15: =IF(D15<>"",D15,"*") -> 制造中心 | G15: 21 | H15: 22 | I15: 22 | J15: 22 | K15: 22 | L15: 22 | M15: 22 | N15: 22 | O15: 22 | P15: 22 | Q15: 22 | R15: 21 | S15: 21 | T15: =AT15 -> 18 | U15: 19 | V15: 21 | W15: 21 | X15: 21 | Y15: 19 | Z15: 19 | AA15: 19 | AB15: 19 | AC15: 19 | AD15: 19 | AE15: 0 | AF15: 0 | AG15: 0 | AH15: =AT15 -> 18 | AI15: 0 | AJ15: 0 | AK15: 0 | AL15: 0 | AM15: 0 | AN15: 0 | AO15: 0 | AP15: 0 | AQ15: 0 | AR15: 19 | AS15: 20 | AT15: 18 | AU15: =BG15 -> 23 | AV15: 18 | AW15: 18 | AX15: 23 | AY15: 23 | AZ15: 23 | BA15: 23 | BB15: 23 | BC15: 23 | BD15: 23 | BE15: 23 | BF15: 23 | BG15: 23
C16: 创新中心 | E16: =IF(C16<>"",C16,E15) -> 创新中心 | F16: =IF(D16<>"",D16,"*") -> * | G16: 19 | H16: 19 | I16: 19 | J16: 19 | K16: 19 | L16: 19 | M16: 19 | N16: 19 | O16: 19 | P16: 19 | Q16: 19 | R16: 19 | S16: 19 | T16: =AT16 -> 20 | U16: 20 | V16: 19 | W16: 19 | X16: 19 | Y16: 19 | Z16: 19 | AA16: 19 | AB16: 20 | AC16: 20 | AD16: 20 | AE16: 0 | AF16: 0 | AG16: 0 | AH16: =AT16 -> 20 | AI16: 0 | AJ16: 0 | AK16: 0 | AL16: 0 | AM16: 0 | AN16: 0 | AO16: 0 | AP16: 0 | AQ16: 0 | AR16: 20 | AS16: 20 | AT16: 20 | AU16: =BG16 -> 20 | AV16: 20 | AW16: 20 | AX16: 20 | AY16: 20 | AZ16: 20 | BA16: 20 | BB16: 20 | BC16: 20 | BD16: 20 | BE16: 20 | BF16: 20 | BG16: 20
D17: 产品 研发部 | E17: =IF(C17<>"",C17,E16) -> 创新中心 | F17: =IF(D17<>"",D17,"*") -> 产品 研发部 | G17: 8 | H17: 8 | I17: 8 | J17: 8 | K17: 8 | L17: 8 | M17: 8 | N17: 8 | O17: 8 | P17: 8 | Q17: 8 | R17: 8 | S17: 8 | T17: =AT17 -> 8 | U17: 8 | V17: 8 | W17: 8 | X17: 8 | Y17: 8 | Z17: 8 | AA17: 8 | AB17: 8 | AC17: 8 | AD17: 8 | AE17: 0 | AF17: 0 | AG17: 0 | AH17: =AT17 -> 8 | AI17: 0 | AJ17: 0 | AK17: 0 | AL17: 0 | AM17: 0 | AN17: 0 | AO17: 0 | AP17: 0 | AQ17: 0 | AR17: 8 | AS17: 8 | AT17: 8 | AU17: =BG17 -> 8 | AV17: 8 | AW17: 8 | AX17: 8 | AY17: 8 | AZ17: 8 | BA17: 8 | BB17: 8 | BC17: 8 | BD17: 8 | BE17: 8 | BF17: 8 | BG17: 8
D18: XX 试验室 | E18: =IF(C18<>"",C18,E17) -> 创新中心 | F18: =IF(D18<>"",D18,"*") -> XX 试验室 | G18: 5 | H18: 5 | I18: 5 | J18: 5 | K18: 5 | L18: 5 | M18: 5 | N18: 5 | O18: 5 | P18: 5 | Q18: 5 | R18: 5 | S18: 5 | T18: =AT18 -> 5 | U18: 5 | V18: 5 | W18: 5 | X18: 5 | Y18: 5 | Z18: 5 | AA18: 5 | AB18: 5 | AC18: 5 | AD18: 5 | AE18: 0 | AF18: 0 | AG18: 0 | AH18: =AT18 -> 5 | AI18: 0 | AJ18: 0 | AK18: 0 | AL18: 0 | AM18: 0 | AN18: 0 | AO18: 0 | AP18: 0 | AQ18: 0 | AR18: 5 | AS18: 5 | AT18: 5 | AU18: =BG18 -> 5 | AV18: 5 | AW18: 5 | AX18: 5 | AY18: 5 | AZ18: 5 | BA18: 5 | BB18: 5 | BC18: 5 | BD18: 5 | BE18: 5 | BF18: 5 | BG18: 5
D19: XX 孵化业务 | E19: =IF(C19<>"",C19,E18) -> 创新中心 | F19: =IF(D19<>"",D19,"*") -> XX 孵化业务 | G19: 6 | H19: 6 | I19: 6 | J19: 6 | K19: 6 | L19: 6 | M19: 6 | N19: 6 | O19: 6 | P19: 6 | Q19: 6 | R19: 6 | S19: 6 | T19: =AT19 -> 7 | U19: 7 | V19: 6 | W19: 6 | X19: 6 | Y19: 6 | Z19: 6 | AA19: 6 | AB19: 7 | AC19: 7 | AD19: 7 | AE19: 0 | AF19: 0 | AG19: 0 | AH19: =AT19 -> 7 | AI19: 0 | AJ19: 0 | AK19: 0 | AL19: 0 | AM19: 0 | AN19: 0 | AO19: 0 | AP19: 0 | AQ19: 0 | AR19: 7 | AS19: 7 | AT19: 7 | AU19: =BG19 -> 7 | AV19: 7 | AW19: 7 | AX19: 7 | AY19: 7 | AZ19: 7 | BA19: 7 | BB19: 7 | BC19: 7 | BD19: 7 | BE19: 7 | BF19: 7 | BG19: 7
C20: 支持中心 | E20: =IF(C20<>"",C20,E19) -> 支持中心 | F20: =IF(D20<>"",D20,"*") -> * | G20: 17 | H20: 17 | I20: 17 | J20: 17 | K20: 17 | L20: 17 | M20: 17 | N20: 17 | O20: 17 | P20: 17 | Q20: 17 | R20: 17 | S20: 17 | T20: =AT20 -> 17 | U20: 17 | V20: 17 | W20: 17 | X20: 17 | Y20: 17 | Z20: 17 | AA20: 17 | AB20: 17 | AC20: 17 | AD20: 17 | AE20: 0 | AF20: 0 | AG20: 0 | AH20: =AT20 -> 17 | AI20: 0 | AJ20: 0 | AK20: 0 | AL20: 0 | AM20: 0 | AN20: 0 | AO20: 0 | AP20: 0 | AQ20: 0 | AR20: 17 | AS20: 17 | AT20: 17 | AU20: =BG20 -> 17 | AV20: 17 | AW20: 17 | AX20: 17 | AY20: 17 | AZ20: 17 | BA20: 17 | BB20: 17 | BC20: 17 | BD20: 17 | BE20: 17 | BF20: 17 | BG20: 17
D21: 财务部 | E21: =IF(C21<>"",C21,E20) -> 支持中心 | F21: =IF(D21<>"",D21,"*") -> 财务部 | G21: 7 | H21: 7 | I21: 7 | J21: 7 | K21: 7 | L21: 7 | M21: 7 | N21: 7 | O21: 7 | P21: 7 | Q21: 7 | R21: 7 | S21: 7 | T21: =AT21 -> 7 | U21: 7 | V21: 7 | W21: 7 | X21: 7 | Y21: 7 | Z21: 7 | AA21: 7 | AB21: 7 | AC21: 7 | AD21: 7 | AE21: 0 | AF21: 0 | AG21: 0 | AH21: =AT21 -> 7 | AI21: 0 | AJ21: 0 | AK21: 0 | AL21: 0 | AM21: 0 | AN21: 0 | AO21: 0 | AP21: 0 | AQ21: 0 | AR21: 7 | AS21: 7 | AT21: 7 | AU21: =BG21 -> 7 | AV21: 7 | AW21: 7 | AX21: 7 | AY21: 7 | AZ21: 7 | BA21: 7 | BB21: 7 | BC21: 7 | BD21: 7 | BE21: 7 | BF21: 7 | BG21: 7
D22: 人力资源部 | E22: =IF(C22<>"",C22,E21) -> 支持中心 | F22: =IF(D22<>"",D22,"*") -> 人力资源部 | G22: 6 | H22: 6 | I22: 6 | J22: 6 | K22: 6 | L22: 6 | M22: 6 | N22: 6 | O22: 6 | P22: 6 | Q22: 6 | R22: 6 | S22: 6 | T22: =AT22 -> 6 | U22: 6 | V22: 6 | W22: 6 | X22: 6 | Y22: 6 | Z22: 6 | AA22: 6 | AB22: 6 | AC22: 6 | AD22: 6 | AE22: 0 | AF22: 0 | AG22: 0 | AH22: =AT22 -> 6 | AI22: 0 | AJ22: 0 | AK22: 0 | AL22: 0 | AM22: 0 | AN22: 0 | AO22: 0 | AP22: 0 | AQ22: 0 | AR22: 6 | AS22: 6 | AT22: 6 | AU22: =BG22 -> 6 | AV22: 6 | AW22: 6 | AX22: 6 | AY22: 6 | AZ22: 6 | BA22: 6 | BB22: 6 | BC22: 6 | BD22: 6 | BE22: 6 | BF22: 6 | BG22: 6
D23: IT部 | E23: =IF(C23<>"",C23,E22) -> 支持中心 | F23: =IF(D23<>"",D23,"*") -> IT部 | G23: 3 | H23: 3 | I23: 3 | J23: 3 | K23: 3 | L23: 3 | M23: 3 | N23: 3 | O23: 3 | P23: 3 | Q23: 3 | R23: 3 | S23: 3 | T23: =AT23 -> 3 | U23: 3 | V23: 3 | W23: 3 | X23: 3 | Y23: 3 | Z23: 3 | AA23: 3 | AB23: 3 | AC23: 3 | AD23: 3 | AE23: 0 | AF23: 0 | AG23: 0 | AH23: =AT23 -> 3 | AI23: 0 | AJ23: 0 | AK23: 0 | AL23: 0 | AM23: 0 | AN23: 0 | AO23: 0 | AP23: 0 | AQ23: 0 | AR23: 3 | AS23: 3 | AT23: 3 | AU23: =BG23 -> 3 | AV23: 3 | AW23: 3 | AX23: 3 | AY23: 3 | AZ23: 3 | BA23: 3 | BB23: 3 | BC23: 3 | BD23: 3 | BE23: 3 | BF23: 3 | BG23: 3
D24: 总经办 | E24: =IF(C24<>"",C24,E23) -> 支持中心 | F24: =IF(D24<>"",D24,"*") -> 总经办 | G24: 1 | H24: 1 | I24: 1 | J24: 1 | K24: 1 | L24: 1 | M24: 1 | N24: 1 | O24: 1 | P24: 1 | Q24: 1 | R24: 1 | S24: 1 | T24: =AT24 -> 1 | U24: 1 | V24: 1 | W24: 1 | X24: 1 | Y24: 1 | Z24: 1 | AA24: 1 | AB24: 1 | AC24: 1 | AD24: 1 | AE24: 0 | AF24: 0 | AG24: 0 | AH24: =AT24 -> 1 | AI24: 0 | AJ24: 0 | AK24: 0 | AL24: 0 | AM24: 0 | AN24: 0 | AO24: 0 | AP24: 0 | AQ24: 0 | AR24: 1 | AS24: 1 | AT24: 1 | AU24: =BG24 -> 1 | AV24: 1 | AW24: 1 | AX24: 1 | AY24: 1 | AZ24: 1 | BA24: 1 | BB24: 1 | BC24: 1 | BD24: 1 | BE24: 1 | BF24: 1 | BG24: 1
B26: 平均人数
B27: 合计 | E27: * | F27: * | G27: 73 | H27: 73 | I27: 73 | J27: 73 | K27: 73 | L27: 73 | M27: 73 | N27: 73 | O27: 73 | P27: 73 | Q27: 73 | R27: 73 | S27: 73 | T27: =(U27*MONTH($G$3)+AH27*(12-MONTH($G$3)))/12 -> 73 | U27: 73 | V27: 73 | W27: 73 | X27: 73 | Y27: 73 | Z27: 73 | AA27: 73 | AB27: 73 | AC27: 73 | AD27: 73 | AE27: 0 | AF27: 0 | AG27: 0 | AH27: 73 | AI27: 0 | AJ27: 0 | AK27: 0 | AL27: 0 | AM27: 0 | AN27: 0 | AO27: 0 | AP27: 0 | AQ27: 0 | AR27: 73 | AS27: 73 | AT27: 73 | AU27: 73 | AV27: 73 | AW27: 73 | AX27: 73 | AY27: 73 | AZ27: 73 | BA27: 73 | BB27: 73 | BC27: 73 | BD27: 73 | BE27: 73 | BF27: 73 | BG27: 73
C28: 流程中心 | E28: =IF(C28<>"",C28,#REF!) -> 流程中心 | F28: =IF(D28<>"",D28,"*") -> * | G28: 36 | H28: 36 | I28: 36 | J28: 36 | K28: 36 | L28: 36 | M28: 36 | N28: 36 | O28: 36 | P28: 36 | Q28: 36 | R28: 36 | S28: 36 | T28: =(U28*MONTH($G$3)+AH28*(12-MONTH($G$3)))/12 -> 36 | U28: 36 | V28: 36 | W28: 36 | X28: 36 | Y28: 36 | Z28: 36 | AA28: 36 | AB28: 36 | AC28: 36 | AD28: 36 | AE28: 0 | AF28: 0 | AG28: 0 | AH28: 36 | AI28: 0 | AJ28: 0 | AK28: 0 | AL28: 0 | AM28: 0 | AN28: 0 | AO28: 0 | AP28: 0 | AQ28: 0 | AR28: 36 | AS28: 36 | AT28: 36 | AU28: 36 | AV28: 36 | AW28: 36 | AX28: 36 | AY28: 36 | AZ28: 36 | BA28: 36 | BB28: 36 | BC28: 36 | BD28: 36 | BE28: 36 | BF28: 36 | BG28: 36
D29: 销售中心 | E29: =IF(C29<>"",C29,E28) -> 流程中心 | F29: =IF(D29<>"",D29,"*") -> 销售中心 | G29: 14 | H29: 14 | I29: 14 | J29: 14 | K29: 14 | L29: 14 | M29: 14 | N29: 14 | O29: 14 | P29: 14 | Q29: 14 | R29: 14 | S29: 14 | T29: =(U29*MONTH($G$3)+AH29*(12-MONTH($G$3)))/12 -> 14 | U29: 14 | V29: 14 | W29: 14 | X29: 14 | Y29: 14 | Z29: 14 | AA29: 14 | AB29: 14 | AC29: 14 | AD29: 14 | AE29: 0 | AF29: 0 | AG29: 0 | AH29: 14 | AI29: 0 | AJ29: 0 | AK29: 0 | AL29: 0 | AM29: 0 | AN29: 0 | AO29: 0 | AP29: 0 | AQ29: 0 | AR29: 14 | AS29: 14 | AT29: 14 | AU29: 14 | AV29: 14 | AW29: 14 | AX29: 14 | AY29: 14 | AZ29: 14 | BA29: 14 | BB29: 14 | BC29: 14 | BD29: 14 | BE29: 14 | BF29: 14 | BG29: 14
D30: 制造中心 | E30: =IF(C30<>"",C30,E29) -> 流程中心 | F30: =IF(D30<>"",D30,"*") -> 制造中心 | G30: 22 | H30: 22 | I30: 22 | J30: 22 | K30: 22 | L30: 22 | M30: 22 | N30: 22 | O30: 22 | P30: 22 | Q30: 22 | R30: 22 | S30: 22 | T30: =(U30*MONTH($G$3)+AH30*(12-MONTH($G$3)))/12 -> 22 | U30: 22 | V30: 22 | W30: 22 | X30: 22 | Y30: 22 | Z30: 22 | AA30: 22 | AB30: 22 | AC30: 22 | AD30: 22 | AE30: 0 | AF30: 0 | AG30: 0 | AH30: 22 | AI30: 0 | AJ30: 0 | AK30: 0 | AL30: 0 | AM30: 0 | AN30: 0 | AO30: 0 | AP30: 0 | AQ30: 0 | AR30: 22 | AS30: 22 | AT30: 22 | AU30: 22 | AV30: 22 | AW30: 22 | AX30: 22 | AY30: 22 | AZ30: 22 | BA30: 22 | BB30: 22 | BC30: 22 | BD30: 22 | BE30: 22 | BF30: 22 | BG30: 22
C31: 创新中心 | E31: =IF(C31<>"",C31,E30) -> 创新中心 | F31: =IF(D31<>"",D31,"*") -> * | G31: 20 | H31: 20 | I31: 20 | J31: 20 | K31: 20 | L31: 20 | M31: 20 | N31: 20 | O31: 20 | P31: 20 | Q31: 20 | R31: 20 | S31: 20 | T31: =(U31*MONTH($G$3)+AH31*(12-MONTH($G$3)))/12 -> 20 | U31: 20 | V31: 20 | W31: 20 | X31: 20 | Y31: 20 | Z31: 20 | AA31: 20 | AB31: 20 | AC31: 20 | AD31: 20 | AE31: 0 | AF31: 0 | AG31: 0 | AH31: 20 | AI31: 0 | AJ31: 0 | AK31: 0 | AL31: 0 | AM31: 0 | AN31: 0 | AO31: 0 | AP31: 0 | AQ31: 0 | AR31: 20 | AS31: 20 | AT31: 20 | AU31: 20 | AV31: 20 | AW31: 20 | AX31: 20 | AY31: 20 | AZ31: 20 | BA31: 20 | BB31: 20 | BC31: 20 | BD31: 20 | BE31: 20 | BF31: 20 | BG31: 20
D32: 产品 研发部 | E32: =IF(C32<>"",C32,E31) -> 创新中心 | F32: =IF(D32<>"",D32,"*") -> 产品 研发部 | G32: 8 | H32: 8 | I32: 8 | J32: 8 | K32: 8 | L32: 8 | M32: 8 | N32: 8 | O32: 8 | P32: 8 | Q32: 8 | R32: 8 | S32: 8 | T32: =(U32*MONTH($G$3)+AH32*(12-MONTH($G$3)))/12 -> 8 | U32: 8 | V32: 8 | W32: 8 | X32: 8 | Y32: 8 | Z32: 8 | AA32: 8 | AB32: 8 | AC32: 8 | AD32: 8 | AE32: 0 | AF32: 0 | AG32: 0 | AH32: 8 | AI32: 0 | AJ32: 0 | AK32: 0 | AL32: 0 | AM32: 0 | AN32: 0 | AO32: 0 | AP32: 0 | AQ32: 0 | AR32: 8 | AS32: 8 | AT32: 8 | AU32: 8 | AV32: 8 | AW32: 8 | AX32: 8 | AY32: 8 | AZ32: 8 | BA32: 8 | BB32: 8 | BC32: 8 | BD32: 8 | BE32: 8 | BF32: 8 | BG32: 8
D33: XX 试验室 | E33: =IF(C33<>"",C33,E32) -> 创新中心 | F33: =IF(D33<>"",D33,"*") -> XX 试验室 | G33: 5 | H33: 5 | I33: 5 | J33: 5 | K33: 5 | L33: 5 | M33: 5 | N33: 5 | O33: 5 | P33: 5 | Q33: 5 | R33: 5 | S33: 5 | T33: =(U33*MONTH($G$3)+AH33*(12-MONTH($G$3)))/12 -> 5 | U33: 5 | V33: 5 | W33: 5 | X33: 5 | Y33: 5 | Z33: 5 | AA33: 5 | AB33: 5 | AC33: 5 | AD33: 5 | AE33: 0 | AF33: 0 | AG33: 0 | AH33: 5 | AI33: 0 | AJ33: 0 | AK33: 0 | AL33: 0 | AM33: 0 | AN33: 0 | AO33: 0 | AP33: 0 | AQ33: 0 | AR33: 5 | AS33: 5 | AT33: 5 | AU33: 5 | AV33: 5 | AW33: 5 | AX33: 5 | AY33: 5 | AZ33: 5 | BA33: 5 | BB33: 5 | BC33: 5 | BD33: 5 | BE33: 5 | BF33: 5 | BG33: 5
D34: XX 孵化业务 | E34: =IF(C34<>"",C34,E33) -> 创新中心 | F34: =IF(D34<>"",D34,"*") -> XX 孵化业务 | G34: 7 | H34: 7 | I34: 7 | J34: 7 | K34: 7 | L34: 7 | M34: 7 | N34: 7 | O34: 7 | P34: 7 | Q34: 7 | R34: 7 | S34: 7 | T34: =(U34*MONTH($G$3)+AH34*(12-MONTH($G$3)))/12 -> 7 | U34: 7 | V34: 7 | W34: 7 | X34: 7 | Y34: 7 | Z34: 7 | AA34: 7 | AB34: 7 | AC34: 7 | AD34: 7 | AE34: 0 | AF34: 0 | AG34: 0 | AH34: 7 | AI34: 0 | AJ34: 0 | AK34: 0 | AL34: 0 | AM34: 0 | AN34: 0 | AO34: 0 | AP34: 0 | AQ34: 0 | AR34: 7 | AS34: 7 | AT34: 7 | AU34: 7 | AV34: 7 | AW34: 7 | AX34: 7 | AY34: 7 | AZ34: 7 | BA34: 7 | BB34: 7 | BC34: 7 | BD34: 7 | BE34: 7 | BF34: 7 | BG34: 7
C35: 支持中心 | E35: =IF(C35<>"",C35,E34) -> 支持中心 | F35: =IF(D35<>"",D35,"*") -> * | G35: 17 | H35: 17 | I35: 17 | J35: 17 | K35: 17 | L35: 17 | M35: 17 | N35: 17 | O35: 17 | P35: 17 | Q35: 17 | R35: 17 | S35: 17 | T35: =(U35*MONTH($G$3)+AH35*(12-MONTH($G$3)))/12 -> 17 | U35: 17 | V35: 17 | W35: 17 | X35: 17 | Y35: 17 | Z35: 17 | AA35: 17 | AB35: 17 | AC35: 17 | AD35: 17 | AE35: 0 | AF35: 0 | AG35: 0 | AH35: 17 | AI35: 0 | AJ35: 0 | AK35: 0 | AL35: 0 | AM35: 0 | AN35: 0 | AO35: 0 | AP35: 0 | AQ35: 0 | AR35: 17 | AS35: 17 | AT35: 17 | AU35: 17 | AV35: 17 | AW35: 17 | AX35: 17 | AY35: 17 | AZ35: 17 | BA35: 17 | BB35: 17 | BC35: 17 | BD35: 17 | BE35: 17 | BF35: 17 | BG35: 17
D36: 财务部 | E36: =IF(C36<>"",C36,E35) -> 支持中心 | F36: =IF(D36<>"",D36,"*") -> 财务部 | G36: 7 | H36: 7 | I36: 7 | J36: 7 | K36: 7 | L36: 7 | M36: 7 | N36: 7 | O36: 7 | P36: 7 | Q36: 7 | R36: 7 | S36: 7 | T36: =(U36*MONTH($G$3)+AH36*(12-MONTH($G$3)))/12 -> 7 | U36: 7 | V36: 7 | W36: 7 | X36: 7 | Y36: 7 | Z36: 7 | AA36: 7 | AB36: 7 | AC36: 7 | AD36: 7 | AE36: 0 | AF36: 0 | AG36: 0 | AH36: 7 | AI36: 0 | AJ36: 0 | AK36: 0 | AL36: 0 | AM36: 0 | AN36: 0 | AO36: 0 | AP36: 0 | AQ36: 0 | AR36: 7 | AS36: 7 | AT36: 7 | AU36: 7 | AV36: 7 | AW36: 7 | AX36: 7 | AY36: 7 | AZ36: 7 | BA36: 7 | BB36: 7 | BC36: 7 | BD36: 7 | BE36: 7 | BF36: 7 | BG36: 7
D37: 人力资源部 | E37: =IF(C37<>"",C37,E36) -> 支持中心 | F37: =IF(D37<>"",D37,"*") -> 人力资源部 | G37: 6 | H37: 6 | I37: 6 | J37: 6 | K37: 6 | L37: 6 | M37: 6 | N37: 6 | O37: 6 | P37: 6 | Q37: 6 | R37: 6 | S37: 6 | T37: =(U37*MONTH($G$3)+AH37*(12-MONTH($G$3)))/12 -> 6 | U37: 6 | V37: 6 | W37: 6 | X37: 6 | Y37: 6 | Z37: 6 | AA37: 6 | AB37: 6 | AC37: 6 | AD37: 6 | AE37: 0 | AF37: 0 | AG37: 0 | AH37: 6 | AI37: 0 | AJ37: 0 | AK37: 0 | AL37: 0 | AM37: 0 | AN37: 0 | AO37: 0 | AP37: 0 | AQ37: 0 | AR37: 6 | AS37: 6 | AT37: 6 | AU37: 6 | AV37: 6 | AW37: 6 | AX37: 6 | AY37: 6 | AZ37: 6 | BA37: 6 | BB37: 6 | BC37: 6 | BD37: 6 | BE37: 6 | BF37: 6 | BG37: 6
D38: IT部 | E38: =IF(C38<>"",C38,E37) -> 支持中心 | F38: =IF(D38<>"",D38,"*") -> IT部 | G38: 3 | H38: 3 | I38: 3 | J38: 3 | K38: 3 | L38: 3 | M38: 3 | N38: 3 | O38: 3 | P38: 3 | Q38: 3 | R38: 3 | S38: 3 | T38: =(U38*MONTH($G$3)+AH38*(12-MONTH($G$3)))/12 -> 3 | U38: 3 | V38: 3 | W38: 3 | X38: 3 | Y38: 3 | Z38: 3 | AA38: 3 | AB38: 3 | AC38: 3 | AD38: 3 | AE38: 0 | AF38: 0 | AG38: 0 | AH38: 3 | AI38: 0 | AJ38: 0 | AK38: 0 | AL38: 0 | AM38: 0 | AN38: 0 | AO38: 0 | AP38: 0 | AQ38: 0 | AR38: 3 | AS38: 3 | AT38: 3 | AU38: 3 | AV38: 3 | AW38: 3 | AX38: 3 | AY38: 3 | AZ38: 3 | BA38: 3 | BB38: 3 | BC38: 3 | BD38: 3 | BE38: 3 | BF38: 3 | BG38: 3
D39: 总经办 | E39: =IF(C39<>"",C39,E38) -> 支持中心 | F39: =IF(D39<>"",D39,"*") -> 总经办 | G39: 1 | H39: 1 | I39: 1 | J39: 1 | K39: 1 | L39: 1 | M39: 1 | N39: 1 | O39: 1 | P39: 1 | Q39: 1 | R39: 1 | S39: 1 | T39: =(U39*MONTH($G$3)+AH39*(12-MONTH($G$3)))/12 -> 1 | U39: 1 | V39: 1 | W39: 1 | X39: 1 | Y39: 1 | Z39: 1 | AA39: 1 | AB39: 1 | AC39: 1 | AD39: 1 | AE39: 0 | AF39: 0 | AG39: 0 | AH39: 1 | AI39: 0 | AJ39: 0 | AK39: 0 | AL39: 0 | AM39: 0 | AN39: 0 | AO39: 0 | AP39: 0 | AQ39: 0 | AR39: 1 | AS39: 1 | AT39: 1 | AU39: 1 | AV39: 1 | AW39: 1 | AX39: 1 | AY39: 1 | AZ39: 1 | BA39: 1 | BB39: 1 | BC39: 1 | BD39: 1 | BE39: 1 | BF39: 1 | BG39: 1
B41: 固定工资
B42: 合计 | E42: * | F42: * | G42: 710.10124 | H42: 59.260488 | I42: 59.105741 | J42: 59.129369 | K42: 59.129574 | L42: 59.144403 | M42: 59.264234 | N42: 59.36844 | O42: 59.213341 | P42: 59.404849 | Q42: 58.873232 | R42: 59.153304 | S42: 59.054263 | T42: =U42+AH42 -> 710.06266 | U42: 532.37749 | V42: 59.345351 | W42: 59.180223 | X42: 59.189103 | Y42: 59.18707 | Z42: 58.810737 | AA42: 59.117967 | AB42: 59.073285 | AC42: 59.183913 | AD42: 59.289837 | AE42: 0 | AF42: 0 | AG42: 0 | AH42: 177.68518 | AI42: 0 | AJ42: 0 | AK42: 0 | AL42: 0 | AM42: 0 | AN42: 0 | AO42: 0 | AP42: 0 | AQ42: 0 | AR42: 59.343942 | AS42: 59.49469 | AT42: 58.846545 | AU42: 709.81109 | AV42: 59.046236 | AW42: 59.507313 | AX42: 59.242299 | AY42: 59.183162 | AZ42: 59.398796 | BA42: 59.009558 | BB42: 59.104384 | BC42: 59.278429 | BD42: 59.181318 | BE42: 59.358979 | BF42: 58.571179 | BG42: 58.929434
C43: 流程中心 | E43: =IF(C43<>"",C43,E10) -> 流程中心 | F43: =IF(D43<>"",D43,"*") -> * | G43: 261.53308 | H43: 21.716272 | I43: 21.73396 | J43: 21.891732 | K43: 21.668929 | L43: 21.904793 | M43: 21.694205 | N43: 21.946395 | O43: 21.796895 | P43: 21.907518 | Q43: 21.754735 | R43: 21.795594 | S43: 21.72205 | T43: =U43+AH43 -> 260.49755 | U43: 195.36958 | V43: 21.892134 | W43: 21.702368 | X43: 21.629345 | Y43: 21.773223 | Z43: 21.532599 | AA43: 21.594651 | AB43: 21.594805 | AC43: 21.711472 | AD43: 21.938984 | AE43: 0 | AF43: 0 | AG43: 0 | AH43: 65.127973 | AI43: 0 | AJ43: 0 | AK43: 0 | AL43: 0 | AM43: 0 | AN43: 0 | AO43: 0 | AP43: 0 | AQ43: 0 | AR43: 21.762175 | AS43: 21.812886 | AT43: 21.552912 | AU43: 261.08139 | AV43: 21.653745 | AW43: 21.840451 | AX43: 22.028228 | AY43: 21.775478 | AZ43: 21.813125 | BA43: 21.743572 | BB43: 21.756288 | BC43: 21.923546 | BD43: 21.551819 | BE43: 21.733236 | BF43: 21.599116 | BG43: 21.662786
D44: 销售中心 | E44: =IF(C44<>"",C44,E43) -> 流程中心 | F44: =IF(D44<>"",D44,"*") -> 销售中心 | G44: 151.6226 | H44: 12.513929 | I44: 12.505339 | J44: 12.678314 | K44: 12.521455 | L44: 12.739761 | M44: 12.6124 | N44: 12.63848 | O44: 12.675823 | P44: 12.767804 | Q44: 12.66764 | R44: 12.69709 | S44: 12.604564 | T44: =U44+AH44 -> 151.05013 | U44: 113.05777 | V44: 12.769178 | W44: 12.576882 | X44: 12.422458 | Y44: 12.579652 | Z44: 12.494867 | AA44: 12.556698 | AB44: 12.420457 | AC44: 12.493558 | AD44: 12.744019 | AE44: 0 | AF44: 0 | AG44: 0 | AH44: 37.99236 | AI44: 0 | AJ44: 0 | AK44: 0 | AL44: 0 | AM44: 0 | AN44: 0 | AO44: 0 | AP44: 0 | AQ44: 0 | AR44: 12.684444 | AS44: 12.751957 | AT44: 12.555959 | AU44: 151.28011 | AV44: 12.529124 | AW44: 12.689807 | AX44: 12.73209 | AY44: 12.707603 | AZ44: 12.67087 | BA44: 12.65578 | BB44: 12.556257 | BC44: 12.696519 | BD44: 12.444357 | BE44: 12.593529 | BF44: 12.548552 | BG44: 12.455627
D45: 制造中心 | E45: =IF(C45<>"",C45,E44) -> 流程中心 | F45: =IF(D45<>"",D45,"*") -> 制造中心 | G45: 109.91048 | H45: 9.202343 | I45: 9.228621 | J45: 9.213418 | K45: 9.147474 | L45: 9.165032 | M45: 9.081805 | N45: 9.307915 | O45: 9.121072 | P45: 9.139714 | Q45: 9.087095 | R45: 9.098504 | S45: 9.117486 | T45: =U45+AH45 -> 109.44742 | U45: 82.311812 | V45: 9.122956 | W45: 9.125486 | X45: 9.206887 | Y45: 9.193571 | Z45: 9.037732 | AA45: 9.037953 | AB45: 9.174348 | AC45: 9.217914 | AD45: 9.194965 | AE45: 0 | AF45: 0 | AG45: 0 | AH45: 27.135613 | AI45: 0 | AJ45: 0 | AK45: 0 | AL45: 0 | AM45: 0 | AN45: 0 | AO45: 0 | AP45: 0 | AQ45: 0 | AR45: 9.077731 | AS45: 9.060929 | AT45: 8.996953 | AU45: 109.80128 | AV45: 9.124621 | AW45: 9.150644 | AX45: 9.296138 | AY45: 9.067875 | AZ45: 9.142255 | BA45: 9.087792 | BB45: 9.200031 | BC45: 9.227027 | BD45: 9.107462 | BE45: 9.139707 | BF45: 9.050564 | BG45: 9.207159
C46: 创新中心 | E46: =IF(C46<>"",C46,E45) -> 创新中心 | F46: =IF(D46<>"",D46,"*") -> * | G46: 239.99715 | H46: 20.055641 | I46: 20.123442 | J46: 19.966468 | K46: 19.983139 | L46: 19.958972 | M46: 20.172677 | N46: 19.888776 | O46: 20.121842 | P46: 20.224372 | Q46: 19.765595 | R46: 19.818626 | S46: 19.9176 | T46: =U46+AH46 -> 240.45106 | U46: 180.31737 | V46: 19.933192 | W46: 20.194645 | X46: 20.18892 | Y46: 19.961873 | Z46: 19.890783 | AA46: 19.99334 | AB46: 19.97859 | AC46: 20.062749 | AD46: 20.113283 | AE46: 0 | AF46: 0 | AG46: 0 | AH46: 60.133684 | AI46: 0 | AJ46: 0 | AK46: 0 | AL46: 0 | AM46: 0 | AN46: 0 | AO46: 0 | AP46: 0 | AQ46: 0 | AR46: 20.090046 | AS46: 20.167759 | AT46: 19.875879 | AU46: 240.23161 | AV46: 20.148099 | AW46: 19.93007 | AX46: 19.990783 | AY46: 19.985617 | AZ46: 20.171078 | BA46: 20.109361 | BB46: 19.935884 | BC46: 19.872959 | BD46: 20.186413 | BE46: 20.103043 | BF46: 19.739754 | BG46: 20.058545
D47: 产品 研发部 | E47: =IF(C47<>"",C47,E46) -> 创新中心 | F47: =IF(D47<>"",D47,"*") -> 产品 研发部 | G47: 82.933697 | H47: 6.916616 | I47: 6.919854 | J47: 6.815808 | K47: 6.87673 | L47: 6.910697 | M47: 6.978602 | N47: 6.785503 | O47: 7.033505 | P47: 6.963359 | Q47: 6.838525 | R47: 7.065249 | S47: 6.829249 | T47: =U47+AH47 -> 83.54734 | U47: 62.579386 | V47: 6.944574 | W47: 7.041769 | X47: 6.967711 | Y47: 6.934121 | Z47: 6.889598 | AA47: 6.844845 | AB47: 6.997112 | AC47: 6.992912 | AD47: 6.966744 | AE47: 0 | AF47: 0 | AG47: 0 | AH47: 20.967954 | AI47: 0 | AJ47: 0 | AK47: 0 | AL47: 0 | AM47: 0 | AN47: 0 | AO47: 0 | AP47: 0 | AQ47: 0 | AR47: 6.989039 | AS47: 6.999775 | AT47: 6.97914 | AU47: 82.949281 | AV47: 6.951659 | AW47: 6.836954 | AX47: 6.875982 | AY47: 6.942492 | AZ47: 6.899305 | BA47: 7.083242 | BB47: 6.956108 | BC47: 6.881786 | BD47: 6.882811 | BE47: 6.975948 | BF47: 6.769402 | BG47: 6.893592
D48: XX 试验室 | E48: =IF(C48<>"",C48,E47) -> 创新中心 | F48: =IF(D48<>"",D48,"*") -> XX 试验室 | G48: 56.504227 | H48: 4.705381 | I48: 4.736296 | J48: 4.736328 | K48: 4.667334 | L48: 4.771641 | M48: 4.666539 | N48: 4.689495 | O48: 4.633434 | P48: 4.882722 | Q48: 4.63943 | R48: 4.642409 | S48: 4.733218 | T48: =U48+AH48 -> 56.264332 | U48: 42.239794 | V48: 4.64632 | W48: 4.830742 | X48: 4.699817 | Y48: 4.626747 | Z48: 4.680638 | AA48: 4.788265 | AB48: 4.623612 | AC48: 4.61691 | AD48: 4.726743 | AE48: 0 | AF48: 0 | AG48: 0 | AH48: 14.024538 | AI48: 0 | AJ48: 0 | AK48: 0 | AL48: 0 | AM48: 0 | AN48: 0 | AO48: 0 | AP48: 0 | AQ48: 0 | AR48: 4.623072 | AS48: 4.774258 | AT48: 4.627208 | AU48: 56.506257 | AV48: 4.778514 | AW48: 4.697742 | AX48: 4.683599 | AY48: 4.657547 | AZ48: 4.831474 | BA48: 4.708919 | BB48: 4.68336 | BC48: 4.674017 | BD48: 4.70177 | BE48: 4.692688 | BF48: 4.720491 | BG48: 4.676136
D49: XX 孵化业务 | E49: =IF(C49<>"",C49,E48) -> 创新中心 | F49: =IF(D49<>"",D49,"*") -> XX 孵化业务 | G49: 100.55923 | H49: 8.433644 | I49: 8.467292 | J49: 8.414332 | K49: 8.439075 | L49: 8.276634 | M49: 8.527536 | N49: 8.413778 | O49: 8.454903 | P49: 8.378291 | Q49: 8.28764 | R49: 8.110968 | S49: 8.355133 | T49: =U49+AH49 -> 100.63939 | U49: 75.498195 | V49: 8.342298 | W49: 8.322134 | X49: 8.521392 | Y49: 8.401005 | Z49: 8.320547 | AA49: 8.36023 | AB49: 8.357866 | AC49: 8.452927 | AD49: 8.419796 | AE49: 0 | AF49: 0 | AG49: 0 | AH49: 25.141192 | AI49: 0 | AJ49: 0 | AK49: 0 | AL49: 0 | AM49: 0 | AN49: 0 | AO49: 0 | AP49: 0 | AQ49: 0 | AR49: 8.477935 | AS49: 8.393726 | AT49: 8.269531 | AU49: 100.77607 | AV49: 8.417926 | AW49: 8.395374 | AX49: 8.431202 | AY49: 8.385578 | AZ49: 8.440299 | BA49: 8.3172 | BB49: 8.296416 | BC49: 8.317156 | BD49: 8.601832 | BE49: 8.434407 | BF49: 8.249861 | BG49: 8.488817
C50: 支持中心 | E50: =IF(C50<>"",C50,E49) -> 支持中心 | F50: =IF(D50<>"",D50,"*") -> * | G50: 208.57101 | H50: 17.488575 | I50: 17.248339 | J50: 17.271169 | K50: 17.477506 | L50: 17.280638 | M50: 17.397352 | N50: 17.533269 | O50: 17.294604 | P50: 17.272959 | Q50: 17.352902 | R50: 17.539084 | S50: 17.414613 | T50: =U50+AH50 -> 209.11405 | U50: 156.69053 | V50: 17.520025 | W50: 17.28321 | X50: 17.370838 | Y50: 17.451974 | Z50: 17.387355 | AA50: 17.529976 | AB50: 17.49989 | AC50: 17.409692 | AD50: 17.23757 | AE50: 0 | AF50: 0 | AG50: 0 | AH50: 52.42352 | AI50: 0 | AJ50: 0 | AK50: 0 | AL50: 0 | AM50: 0 | AN50: 0 | AO50: 0 | AP50: 0 | AQ50: 0 | AR50: 17.491721 | AS50: 17.514045 | AT50: 17.417754 | AU50: 208.49809 | AV50: 17.244392 | AW50: 17.736792 | AX50: 17.223288 | AY50: 17.422067 | AZ50: 17.414593 | BA50: 17.156625 | BB50: 17.412212 | BC50: 17.481924 | BD50: 17.443086 | BE50: 17.5227 | BF50: 17.232309 | BG50: 17.208103
D51: 财务部 | E51: =IF(C51<>"",C51,E50) -> 支持中心 | F51: =IF(D51<>"",D51,"*") -> 财务部 | G51: 81.410264 | H51: 6.829875 | I51: 6.800089 | J51: 6.692602 | K51: 6.758078 | L51: 6.782841 | M51: 6.864555 | N51: 6.739991 | O51: 6.692284 | P51: 6.867011 | Q51: 6.854819 | R51: 6.773134 | S51: 6.754985 | T51: =U51+AH51 -> 81.581968 | U51: 61.081961 | V51: 6.840379 | W51: 6.769798 | X51: 6.833027 | Y51: 6.718364 | Z51: 6.767125 | AA51: 6.799088 | AB51: 6.767283 | AC51: 6.839301 | AD51: 6.747596 | AE51: 0 | AF51: 0 | AG51: 0 | AH51: 20.500007 | AI51: 0 | AJ51: 0 | AK51: 0 | AL51: 0 | AM51: 0 | AN51: 0 | AO51: 0 | AP51: 0 | AQ51: 0 | AR51: 6.898817 | AS51: 6.802753 | AT51: 6.798437 | AU51: 81.712282 | AV51: 6.706875 | AW51: 6.955072 | AX51: 6.730929 | AY51: 6.87979 | AZ51: 6.794345 | BA51: 6.74414 | BB51: 6.832184 | BC51: 6.879973 | BD51: 6.817406 | BE51: 6.903329 | BF51: 6.797192 | BG51: 6.671047
D52: 人力资源部 | E52: =IF(C52<>"",C52,E51) -> 支持中心 | F52: =IF(D52<>"",D52,"*") -> 人力资源部 | G52: 72.520069 | H52: 6.016295 | I52: 5.913852 | J52: 6.019238 | K52: 6.094679 | L52: 5.943344 | M52: 6.006876 | N52: 6.163882 | O52: 6.1128 | P52: 5.991669 | Q52: 6.009212 | R52: 6.159249 | S52: 6.088973 | T52: =U52+AH52 -> 72.997355 | U52: 54.680603 | V52: 6.060242 | W52: 5.985086 | X52: 6.026445 | Y52: 6.166771 | Z52: 6.098762 | AA52: 6.188494 | AB52: 6.122925 | AC52: 6.030256 | AD52: 6.001622 | AE52: 0 | AF52: 0 | AG52: 0 | AH52: 18.316752 | AI52: 0 | AJ52: 0 | AK52: 0 | AL52: 0 | AM52: 0 | AN52: 0 | AO52: 0 | AP52: 0 | AQ52: 0 | AR52: 6.158302 | AS52: 6.103141 | AT52: 6.055309 | AU52: 72.310562 | AV52: 5.927609 | AW52: 6.117178 | AX52: 6.022355 | AY52: 6.033594 | AZ52: 6.066046 | BA52: 5.985094 | BB52: 5.972896 | BC52: 6.040918 | BD52: 6.051511 | BE52: 6.098935 | BF52: 5.957409 | BG52: 6.037017
D53: IT部 | E53: =IF(C53<>"",C53,E52) -> 支持中心 | F53: =IF(D53<>"",D53,"*") -> IT部 | G53: 34.235522 | H53: 2.947431 | I53: 2.878424 | J53: 2.826563 | K53: 2.879288 | L53: 2.874803 | M53: 2.811999 | N53: 2.895252 | O53: 2.792007 | P53: 2.799536 | Q53: 2.829252 | R53: 2.859485 | S53: 2.841482 | T53: =U53+AH53 -> 34.156208 | U53: 25.598813 | V53: 2.876186 | W53: 2.842663 | X53: 2.863811 | Y53: 2.808498 | Z53: 2.796585 | AA53: 2.886274 | AB53: 2.869874 | AC53: 2.810867 | AD53: 2.844055 | AE53: 0 | AF53: 0 | AG53: 0 | AH53: 8.557395 | AI53: 0 | AJ53: 0 | AK53: 0 | AL53: 0 | AM53: 0 | AN53: 0 | AO53: 0 | AP53: 0 | AQ53: 0 | AR53: 2.810652 | AS53: 2.894343 | AT53: 2.8524 | AU53: 34.130997 | AV53: 2.8585 | AW53: 2.959455 | AX53: 2.80276 | AY53: 2.860893 | AZ53: 2.810758 | BA53: 2.793934 | BB53: 2.881054 | BC53: 2.801325 | BD53: 2.90003 | BE53: 2.833324 | BF53: 2.840899 | BG53: 2.788065
D54: 总经办 | E54: =IF(C54<>"",C54,E53) -> 支持中心 | F54: =IF(D54<>"",D54,"*") -> 总经办 | G54: 20.405155 | H54: 1.694974 | I54: 1.655974 | J54: 1.732766 | K54: 1.745461 | L54: 1.67965 | M54: 1.713922 | N54: 1.734144 | O54: 1.697513 | P54: 1.614743 | Q54: 1.659619 | R54: 1.747216 | S54: 1.729173 | T54: =U54+AH54 -> 20.378519 | U54: 15.329153 | V54: 1.743218 | W54: 1.685663 | X54: 1.647555 | Y54: 1.758341 | Z54: 1.724883 | AA54: 1.65612 | AB54: 1.739808 | AC54: 1.729268 | AD54: 1.644297 | AE54: 0 | AF54: 0 | AG54: 0 | AH54: 5.049366 | AI54: 0 | AJ54: 0 | AK54: 0 | AL54: 0 | AM54: 0 | AN54: 0 | AO54: 0 | AP54: 0 | AQ54: 0 | AR54: 1.62395 | AS54: 1.713808 | AT54: 1.711608 | AU54: 20.34425 | AV54: 1.751408 | AW54: 1.705087 | AX54: 1.667244 | AY54: 1.64779 | AZ54: 1.743444 | BA54: 1.633457 | BB54: 1.726078 | BC54: 1.759708 | BD54: 1.674139 | BE54: 1.687112 | BF54: 1.636809 | BG54: 1.711974
B56: 变动薪酬
B57: 合计 | E57: * | F57: * | G57: 275.62988 | H57: 22.952588 | I57: 23.087957 | J57: 23.079723 | K57: 22.920293 | L57: 22.817947 | M57: 23.012541 | N57: 22.975488 | O57: 22.837759 | P57: 22.974263 | Q57: 22.98142 | R57: 22.970561 | S57: 23.019338 | T57: =U57+AH57 -> 276.04006 | U57: 206.97588 | V57: 22.786752 | W57: 22.951831 | X57: 23.0078 | Y57: 22.963112 | Z57: 22.958504 | AA57: 23.085475 | AB57: 23.146199 | AC57: 23.092904 | AD57: 22.983301 | AE57: 0 | AF57: 0 | AG57: 0 | AH57: 69.064179 | AI57: 0 | AJ57: 0 | AK57: 0 | AL57: 0 | AM57: 0 | AN57: 0 | AO57: 0 | AP57: 0 | AQ57: 0 | AR57: 23.110223 | AS57: 22.952206 | AT57: 23.00175 | AU57: 275.49811 | AV57: 23.001378 | AW57: 22.951502 | AX57: 22.946894 | AY57: 22.917313 | AZ57: 22.913841 | BA57: 22.915856 | BB57: 23.023323 | BC57: 23.016934 | BD57: 22.989173 | BE57: 22.94277 | BF57: 22.947504 | BG57: 22.931622
C58: 流程中心 | E58: =IF(C58<>"",C58,E55) -> 流程中心 | F58: =IF(D58<>"",D58,"*") -> * | G58: 136.04284 | H58: 11.313824 | I58: 11.434362 | J58: 11.326935 | K58: 11.269357 | L58: 11.257579 | M58: 11.402418 | N58: 11.361103 | O58: 11.302216 | P58: 11.3904 | Q58: 11.364476 | R58: 11.327892 | S58: 11.29228 | T58: =U58+AH58 -> 136.19727 | U58: 102.12602 | V58: 11.20836 | W58: 11.30615 | X58: 11.354422 | Y58: 11.292066 | Z58: 11.361711 | AA58: 11.402723 | AB58: 11.400253 | AC58: 11.435157 | AD58: 11.365179 | AE58: 0 | AF58: 0 | AG58: 0 | AH58: 34.071252 | AI58: 0 | AJ58: 0 | AK58: 0 | AL58: 0 | AM58: 0 | AN58: 0 | AO58: 0 | AP58: 0 | AQ58: 0 | AR58: 11.43306 | AS58: 11.280763 | AT58: 11.357429 | AU58: 135.92884 | AV58: 11.329852 | AW58: 11.387936 | AX58: 11.314249 | AY58: 11.25725 | AZ58: 11.311845 | BA58: 11.315922 | BB58: 11.40146 | BC58: 11.370761 | BD58: 11.301794 | BE58: 11.266148 | BF58: 11.390343 | BG58: 11.281276
D59: 销售中心 | E59: =IF(C59<>"",C59,E58) -> 流程中心 | F59: =IF(D59<>"",D59,"*") -> 销售中心 | G59: 52.952033 | H59: 4.399665 | I59: 4.440754 | J59: 4.406111 | K59: 4.35059 | L59: 4.389138 | M59: 4.387154 | N59: 4.428552 | O59: 4.429868 | P59: 4.436651 | Q59: 4.439016 | R59: 4.441663 | S59: 4.402871 | T59: =U59+AH59 -> 53.047264 | U59: 39.746388 | V59: 4.35404 | W59: 4.416294 | X59: 4.422487 | Y59: 4.409484 | Z59: 4.435866 | AA59: 4.467198 | AB59: 4.399194 | AC59: 4.429687 | AD59: 4.412138 | AE59: 0 | AF59: 0 | AG59: 0 | AH59: 13.300876 | AI59: 0 | AJ59: 0 | AK59: 0 | AL59: 0 | AM59: 0 | AN59: 0 | AO59: 0 | AP59: 0 | AQ59: 0 | AR59: 4.458892 | AS59: 4.413407 | AT59: 4.428577 | AU59: 52.942326 | AV59: 4.419124 | AW59: 4.445818 | AX59: 4.404894 | AY59: 4.379271 | AZ59: 4.460816 | BA59: 4.367551 | BB59: 4.447554 | BC59: 4.422641 | BD59: 4.39038 | BE59: 4.377221 | BF59: 4.45631 | BG59: 4.370746
D60: 制造中心 | E60: =IF(C60<>"",C60,E59) -> 流程中心 | F60: =IF(D60<>"",D60,"*") -> 制造中心 | G60: 83.090809 | H60: 6.914159 | I60: 6.993608 | J60: 6.920824 | K60: 6.918767 | L60: 6.868441 | M60: 7.015264 | N60: 6.932551 | O60: 6.872348 | P60: 6.953749 | Q60: 6.92546 | R60: 6.886229 | S60: 6.889409 | T60: =U60+AH60 -> 83.150009 | U60: 62.379633 | V60: 6.85432 | W60: 6.889856 | X60: 6.931935 | Y60: 6.882582 | Z60: 6.925845 | AA60: 6.935525 | AB60: 7.001059 | AC60: 7.00547 | AD60: 6.953041 | AE60: 0 | AF60: 0 | AG60: 0 | AH60: 20.770376 | AI60: 0 | AJ60: 0 | AK60: 0 | AL60: 0 | AM60: 0 | AN60: 0 | AO60: 0 | AP60: 0 | AQ60: 0 | AR60: 6.974168 | AS60: 6.867356 | AT60: 6.928852 | AU60: 82.98651 | AV60: 6.910728 | AW60: 6.942118 | AX60: 6.909355 | AY60: 6.877979 | AZ60: 6.851029 | BA60: 6.948371 | BB60: 6.953906 | BC60: 6.94812 | BD60: 6.911414 | BE60: 6.888927 | BF60: 6.934033 | BG60: 6.91053
C61: 创新中心 | E61: =IF(C61<>"",C61,E60) -> 创新中心 | F61: =IF(D61<>"",D61,"*") -> * | G61: 75.439247 | H61: 6.272822 | I61: 6.345348 | J61: 6.36437 | K61: 6.315579 | L61: 6.218339 | M61: 6.263924 | N61: 6.258416 | O61: 6.193419 | P61: 6.245067 | Q61: 6.287554 | R61: 6.304404 | S61: 6.370005 | T61: =U61+AH61 -> 75.703961 | U61: 56.745986 | V61: 6.267225 | W61: 6.305816 | X61: 6.310222 | Y61: 6.320903 | Z61: 6.255087 | AA61: 6.309757 | AB61: 6.321746 | AC61: 6.356301 | AD61: 6.298929 | AE61: 0 | AF61: 0 | AG61: 0 | AH61: 18.957975 | AI61: 0 | AJ61: 0 | AK61: 0 | AL61: 0 | AM61: 0 | AN61: 0 | AO61: 0 | AP61: 0 | AQ61: 0 | AR61: 6.302443 | AS61: 6.339868 | AT61: 6.315664 | AU61: 75.542454 | AV61: 6.328546 | AW61: 6.253154 | AX61: 6.271404 | AY61: 6.301547 | AZ61: 6.311292 | BA61: 6.286734 | BB61: 6.315052 | BC61: 6.328494 | BD61: 6.347717 | BE61: 6.283902 | BF61: 6.212294 | BG61: 6.302318
D62: 产品 研发部 | E62: =IF(C62<>"",C62,E61) -> 创新中心 | F62: =IF(D62<>"",D62,"*") -> 产品 研发部 | G62: 30.145554 | H62: 2.507286 | I62: 2.539775 | J62: 2.546255 | K62: 2.557072 | L62: 2.461859 | M62: 2.494866 | N62: 2.497904 | O62: 2.437477 | P62: 2.47286 | Q62: 2.536034 | R62: 2.524791 | S62: 2.569375 | T62: =U62+AH62 -> 30.385373 | U62: 22.717046 | V62: 2.524289 | W62: 2.514491 | X62: 2.519502 | Y62: 2.494257 | Z62: 2.548469 | AA62: 2.541495 | AB62: 2.52343 | AC62: 2.514346 | AD62: 2.536767 | AE62: 0 | AF62: 0 | AG62: 0 | AH62: 7.668327 | AI62: 0 | AJ62: 0 | AK62: 0 | AL62: 0 | AM62: 0 | AN62: 0 | AO62: 0 | AP62: 0 | AQ62: 0 | AR62: 2.554923 | AS62: 2.56795 | AT62: 2.545454 | AU62: 30.26366 | AV62: 2.519897 | AW62: 2.512736 | AX62: 2.532279 | AY62: 2.486363 | AZ62: 2.527101 | BA62: 2.545339 | BB62: 2.521614 | BC62: 2.569049 | BD62: 2.522106 | BE62: 2.518393 | BF62: 2.481135 | BG62: 2.527648
D63: XX 试验室 | E63: =IF(C63<>"",C63,E62) -> 创新中心 | F63: =IF(D63<>"",D63,"*") -> XX 试验室 | G63: 18.863796 | H63: 1.573762 | I63: 1.584661 | J63: 1.585615 | K63: 1.5537 | L63: 1.596009 | M63: 1.576289 | N63: 1.548637 | O63: 1.547148 | P63: 1.560281 | Q63: 1.561877 | R63: 1.57229 | S63: 1.603527 | T63: =U63+AH63 -> 18.896253 | U63: 14.185061 | V63: 1.565929 | W63: 1.58067 | X63: 1.608151 | Y63: 1.594318 | Z63: 1.522619 | AA63: 1.568055 | AB63: 1.581536 | AC63: 1.602722 | AD63: 1.561061 | AE63: 0 | AF63: 0 | AG63: 0 | AH63: 4.711192 | AI63: 0 | AJ63: 0 | AK63: 0 | AL63: 0 | AM63: 0 | AN63: 0 | AO63: 0 | AP63: 0 | AQ63: 0 | AR63: 1.547917 | AS63: 1.574192 | AT63: 1.589083 | AU63: 18.729947 | AV63: 1.603082 | AW63: 1.554556 | AX63: 1.528946 | AY63: 1.570546 | AZ63: 1.562595 | BA63: 1.546931 | BB63: 1.561745 | BC63: 1.559046 | BD63: 1.594133 | BE63: 1.542542 | BF63: 1.555875 | BG63: 1.54995
D64: XX 孵化业务 | E64: =IF(C64<>"",C64,E63) -> 创新中心 | F64: =IF(D64<>"",D64,"*") -> XX 孵化业务 | G64: 26.429897 | H64: 2.191774 | I64: 2.220912 | J64: 2.2325 | K64: 2.204807 | L64: 2.160471 | M64: 2.192769 | N64: 2.211875 | O64: 2.208794 | P64: 2.211926 | Q64: 2.189643 | R64: 2.207323 | S64: 2.197103 | T64: =U64+AH64 -> 26.422335 | U64: 19.843879 | V64: 2.177007 | W64: 2.210655 | X64: 2.182569 | Y64: 2.232328 | Z64: 2.183999 | AA64: 2.200207 | AB64: 2.21678 | AC64: 2.239233 | AD64: 2.201101 | AE64: 0 | AF64: 0 | AG64: 0 | AH64: 6.578456 | AI64: 0 | AJ64: 0 | AK64: 0 | AL64: 0 | AM64: 0 | AN64: 0 | AO64: 0 | AP64: 0 | AQ64: 0 | AR64: 2.199603 | AS64: 2.197726 | AT64: 2.181127 | AU64: 26.548847 | AV64: 2.205567 | AW64: 2.185862 | AX64: 2.210179 | AY64: 2.244638 | AZ64: 2.221596 | BA64: 2.194464 | BB64: 2.231693 | BC64: 2.200399 | BD64: 2.231478 | BE64: 2.222967 | BF64: 2.175284 | BG64: 2.22472
C65: 支持中心 | E65: =IF(C65<>"",C65,E64) -> 支持中心 | F65: =IF(D65<>"",D65,"*") -> * | G65: 64.147789 | H65: 5.365942 | I65: 5.308247 | J65: 5.388418 | K65: 5.335357 | L65: 5.342029 | M65: 5.346199 | N65: 5.355969 | O65: 5.342124 | P65: 5.338796 | Q65: 5.32939 | R65: 5.338265 | S65: 5.357053 | T65: =U65+AH65 -> 64.138823 | U65: 48.103871 | V65: 5.311167 | W65: 5.339865 | X65: 5.343156 | Y65: 5.350143 | Z65: 5.341706 | AA65: 5.372995 | AB65: 5.4242 | AC65: 5.301446 | AD65: 5.319193 | AE65: 0 | AF65: 0 | AG65: 0 | AH65: 16.034952 | AI65: 0 | AJ65: 0 | AK65: 0 | AL65: 0 | AM65: 0 | AN65: 0 | AO65: 0 | AP65: 0 | AQ65: 0 | AR65: 5.37472 | AS65: 5.331575 | AT65: 5.328657 | AU65: 64.02682 | AV65: 5.34298 | AW65: 5.310412 | AX65: 5.361241 | AY65: 5.358516 | AZ65: 5.290704 | BA65: 5.3132 | BB65: 5.306811 | BC65: 5.317679 | BD65: 5.339662 | BE65: 5.39272 | BF65: 5.344867 | BG65: 5.348028
D66: 财务部 | E66: =IF(C66<>"",C66,E65) -> 支持中心 | F66: =IF(D66<>"",D66,"*") -> 财务部 | G66: 26.48584 | H66: 2.227686 | I66: 2.164031 | J66: 2.241147 | K66: 2.191723 | L66: 2.18325 | M66: 2.215137 | N66: 2.236393 | O66: 2.198369 | P66: 2.200339 | Q66: 2.230911 | R66: 2.209664 | S66: 2.18719 | T66: =U66+AH66 -> 26.436883 | U66: 19.827719 | V66: 2.189222 | W66: 2.183322 | X66: 2.222922 | Y66: 2.19848 | Z66: 2.210994 | AA66: 2.237855 | AB66: 2.217378 | AC66: 2.163227 | AD66: 2.204319 | AE66: 0 | AF66: 0 | AG66: 0 | AH66: 6.609164 | AI66: 0 | AJ66: 0 | AK66: 0 | AL66: 0 | AM66: 0 | AN66: 0 | AO66: 0 | AP66: 0 | AQ66: 0 | AR66: 2.225275 | AS66: 2.215963 | AT66: 2.167926 | AU66: 26.283545 | AV66: 2.158315 | AW66: 2.184421 | AX66: 2.206105 | AY66: 2.184398 | AZ66: 2.171474 | BA66: 2.196505 | BB66: 2.166657 | BC66: 2.209717 | BD66: 2.192067 | BE66: 2.23751 | BF66: 2.159657 | BG66: 2.216719
D67: 人力资源部 | E67: =IF(C67<>"",C67,E66) -> 支持中心 | F67: =IF(D67<>"",D67,"*") -> 人力资源部 | G67: 22.579278 | H67: 1.899433 | I67: 1.870848 | J67: 1.874461 | K67: 1.873516 | L67: 1.902455 | M67: 1.88217 | N67: 1.883104 | O67: 1.88505 | P67: 1.86051 | Q67: 1.860599 | R67: 1.877359 | S67: 1.909773 | T67: =U67+AH67 -> 22.591385 | U67: 16.912151 | V67: 1.876012 | W67: 1.873913 | X67: 1.856889 | Y67: 1.89385 | Z67: 1.877074 | AA67: 1.892585 | AB67: 1.913318 | AC67: 1.874879 | AD67: 1.853631 | AE67: 0 | AF67: 0 | AG67: 0 | AH67: 5.679234 | AI67: 0 | AJ67: 0 | AK67: 0 | AL67: 0 | AM67: 0 | AN67: 0 | AO67: 0 | AP67: 0 | AQ67: 0 | AR67: 1.903514 | AS67: 1.882064 | AT67: 1.893656 | AU67: 22.571159 | AV67: 1.910679 | AW67: 1.870318 | AX67: 1.881756 | AY67: 1.896937 | AZ67: 1.875428 | BA67: 1.871137 | BB67: 1.880263 | BC67: 1.874258 | BD67: 1.892045 | BE67: 1.880804 | BF67: 1.884264 | BG67: 1.85327
D68: IT部 | E68: =IF(C68<>"",C68,E67) -> 支持中心 | F68: =IF(D68<>"",D68,"*") -> IT部 | G68: 11.36717 | H68: 0.919036 | I68: 0.962752 | J68: 0.958906 | K68: 0.951984 | L68: 0.941206 | M68: 0.946944 | N68: 0.933147 | O68: 0.950006 | P68: 0.972376 | Q68: 0.937848 | R68: 0.948849 | S68: 0.944116 | T68: =U68+AH68 -> 11.321749 | U68: 8.511263 | V68: 0.917372 | W68: 0.955079 | X68: 0.954415 | Y68: 0.946536 | Z68: 0.944249 | AA68: 0.941421 | AB68: 0.966195 | AC68: 0.941789 | AD68: 0.944207 | AE68: 0 | AF68: 0 | AG68: 0 | AH68: 2.810486 | AI68: 0 | AJ68: 0 | AK68: 0 | AL68: 0 | AM68: 0 | AN68: 0 | AO68: 0 | AP68: 0 | AQ68: 0 | AR68: 0.92756 | AS68: 0.930361 | AT68: 0.952565 | AU68: 11.375117 | AV68: 0.953994 | AW68: 0.945944 | AX68: 0.955744 | AY68: 0.954241 | AZ68: 0.94209 | BA68: 0.944424 | BB68: 0.93301 | BC68: 0.919603 | BD68: 0.948921 | BE68: 0.951104 | BF68: 0.976387 | BG68: 0.949655
D69: 总经办 | E69: =IF(C69<>"",C69,E68) -> 支持中心 | F69: =IF(D69<>"",D69,"*") -> 总经办 | G69: 3.715501 | H69: 0.319787 | I69: 0.310616 | J69: 0.313904 | K69: 0.318134 | L69: 0.315118 | M69: 0.301948 | N69: 0.303325 | O69: 0.308699 | P69: 0.305571 | Q69: 0.300032 | R69: 0.302393 | S69: 0.315974 | T69: =U69+AH69 -> 3.788806 | U69: 2.852738 | V69: 0.328561 | W69: 0.327551 | X69: 0.30893 | Y69: 0.311277 | Z69: 0.309389 | AA69: 0.301134 | AB69: 0.327309 | AC69: 0.321551 | AD69: 0.317036 | AE69: 0 | AF69: 0 | AG69: 0 | AH69: 0.936068 | AI69: 0 | AJ69: 0 | AK69: 0 | AL69: 0 | AM69: 0 | AN69: 0 | AO69: 0 | AP69: 0 | AQ69: 0 | AR69: 0.318371 | AS69: 0.303187 | AT69: 0.31451 | AU69: 3.796999 | AV69: 0.319992 | AW69: 0.309729 | AX69: 0.317636 | AY69: 0.32294 | AZ69: 0.301712 | BA69: 0.301134 | BB69: 0.326881 | BC69: 0.314101 | BD69: 0.306629 | BE69: 0.323302 | BF69: 0.324559 | BG69: 0.328384
B71: 其他薪酬
B72: 合计 | E72: * | F72: * | G72: 76.241581 | H72: 6.36858 | I72: 6.373974 | J72: 6.351489 | K72: 6.311171 | L72: 6.332852 | M72: 6.355494 | N72: 6.364232 | O72: 6.345037 | P72: 6.360801 | Q72: 6.398771 | R72: 6.341626 | S72: 6.337554 | T72: =U72+AH72 -> 76.316322 | U72: 57.218613 | V72: 6.353244 | W72: 6.368606 | X72: 6.382287 | Y72: 6.366384 | Z72: 6.397316 | AA72: 6.325348 | AB72: 6.344589 | AC72: 6.373042 | AD72: 6.307797 | AE72: 0 | AF72: 0 | AG72: 0 | AH72: 19.097709 | AI72: 0 | AJ72: 0 | AK72: 0 | AL72: 0 | AM72: 0 | AN72: 0 | AO72: 0 | AP72: 0 | AQ72: 0 | AR72: 6.386689 | AS72: 6.373978 | AT72: 6.337042 | AU72: 76.376321 | AV72: 6.351112 | AW72: 6.329146 | AX72: 6.387524 | AY72: 6.344793 | AZ72: 6.407248 | BA72: 6.336409 | BB72: 6.355256 | BC72: 6.377366 | BD72: 6.367207 | BE72: 6.381772 | BF72: 6.379095 | BG72: 6.359393
C73: 流程中心 | E73: =IF(C73<>"",C73,E70) -> 流程中心 | F73: =IF(D73<>"",D73,"*") -> * | G73: 26.119635 | H73: 2.191697 | I73: 2.184467 | J73: 2.173013 | K73: 2.161188 | L73: 2.171043 | M73: 2.164463 | N73: 2.166482 | O73: 2.176146 | P73: 2.18568 | Q73: 2.191422 | R73: 2.172641 | S73: 2.181393 | T73: =U73+AH73 -> 26.12878 | U73: 19.550217 | V73: 2.161013 | W73: 2.188124 | X73: 2.172857 | Y73: 2.174699 | Z73: 2.18779 | AA73: 2.155672 | AB73: 2.182094 | AC73: 2.157474 | AD73: 2.170494 | AE73: 0 | AF73: 0 | AG73: 0 | AH73: 6.578563 | AI73: 0 | AJ73: 0 | AK73: 0 | AL73: 0 | AM73: 0 | AN73: 0 | AO73: 0 | AP73: 0 | AQ73: 0 | AR73: 2.200735 | AS73: 2.203792 | AT73: 2.174036 | AU73: 26.104351 | AV73: 2.163751 | AW73: 2.148605 | AX73: 2.199874 | AY73: 2.16878 | AZ73: 2.177952 | BA73: 2.159416 | BB73: 2.184097 | BC73: 2.184791 | BD73: 2.185277 | BE73: 2.173707 | BF73: 2.178551 | BG73: 2.17955
D74: 销售中心 | E74: =IF(C74<>"",C74,E73) -> 流程中心 | F74: =IF(D74<>"",D74,"*") -> 销售中心 | G74: 15.161059 | H74: 1.274302 | I74: 1.272698 | J74: 1.258859 | K74: 1.252721 | L74: 1.254125 | M74: 1.252324 | N74: 1.269346 | O74: 1.254944 | P74: 1.265665 | Q74: 1.278776 | R74: 1.261311 | S74: 1.265988 | T74: =U74+AH74 -> 15.119625 | U74: 11.30668 | V74: 1.251733 | W74: 1.260993 | X74: 1.244951 | Y74: 1.258888 | Z74: 1.273798 | AA74: 1.246626 | AB74: 1.267484 | AC74: 1.242296 | AD74: 1.259911 | AE74: 0 | AF74: 0 | AG74: 0 | AH74: 3.812945 | AI74: 0 | AJ74: 0 | AK74: 0 | AL74: 0 | AM74: 0 | AN74: 0 | AO74: 0 | AP74: 0 | AQ74: 0 | AR74: 1.274967 | AS74: 1.281271 | AT74: 1.256707 | AU74: 15.129775 | AV74: 1.253242 | AW74: 1.247087 | AX74: 1.275293 | AY74: 1.262977 | AZ74: 1.255196 | BA74: 1.244101 | BB74: 1.272081 | BC74: 1.26292 | BD74: 1.261153 | BE74: 1.269341 | BF74: 1.258876 | BG74: 1.267508
D75: 制造中心 | E75: =IF(C75<>"",C75,E74) -> 流程中心 | F75: =IF(D75<>"",D75,"*") -> 制造中心 | G75: 10.958576 | H75: 0.917395 | I75: 0.911769 | J75: 0.914154 | K75: 0.908467 | L75: 0.916918 | M75: 0.912139 | N75: 0.897136 | O75: 0.921202 | P75: 0.920015 | Q75: 0.912646 | R75: 0.91133 | S75: 0.915405 | T75: =U75+AH75 -> 11.009155 | U75: 8.243537 | V75: 0.90928 | W75: 0.927131 | X75: 0.927906 | Y75: 0.915811 | Z75: 0.913992 | AA75: 0.909046 | AB75: 0.91461 | AC75: 0.915178 | AD75: 0.910583 | AE75: 0 | AF75: 0 | AG75: 0 | AH75: 2.765618 | AI75: 0 | AJ75: 0 | AK75: 0 | AL75: 0 | AM75: 0 | AN75: 0 | AO75: 0 | AP75: 0 | AQ75: 0 | AR75: 0.925768 | AS75: 0.922521 | AT75: 0.917329 | AU75: 10.974576 | AV75: 0.910509 | AW75: 0.901518 | AX75: 0.924581 | AY75: 0.905803 | AZ75: 0.922756 | BA75: 0.915315 | BB75: 0.912016 | BC75: 0.921871 | BD75: 0.924124 | BE75: 0.904366 | BF75: 0.919675 | BG75: 0.912042
C76: 创新中心 | E76: =IF(C76<>"",C76,E75) -> 创新中心 | F76: =IF(D76<>"",D76,"*") -> * | G76: 24.05573 | H76: 1.996573 | I76: 2.000484 | J76: 2.025467 | K76: 1.985626 | L76: 1.994369 | M76: 2.014204 | N76: 2.011618 | O76: 1.98852 | P76: 2.017589 | Q76: 2.011925 | R76: 2.0159 | S76: 1.993455 | T76: =U76+AH76 -> 24.080608 | U76: 18.110348 | V76: 2.023052 | W76: 1.998653 | X76: 2.021874 | Y76: 2.000012 | Z76: 2.032978 | AA76: 2.005348 | AB76: 2.00583 | AC76: 2.024832 | AD76: 1.997769 | AE76: 0 | AF76: 0 | AG76: 0 | AH76: 5.97026 | AI76: 0 | AJ76: 0 | AK76: 0 | AL76: 0 | AM76: 0 | AN76: 0 | AO76: 0 | AP76: 0 | AQ76: 0 | AR76: 1.994532 | AS76: 1.996211 | AT76: 1.979517 | AU76: 24.132011 | AV76: 2.008992 | AW76: 2.00751 | AX76: 2.008239 | AY76: 1.99263 | AZ76: 2.023919 | BA76: 2.010013 | BB76: 1.99371 | BC76: 2.014657 | BD76: 2.011998 | BE76: 2.012929 | BF76: 2.028382 | BG76: 2.019032
D77: 产品 研发部 | E77: =IF(C77<>"",C77,E76) -> 创新中心 | F77: =IF(D77<>"",D77,"*") -> 产品 研发部 | G77: 8.313064 | H77: 0.701288 | I77: 0.70102 | J77: 0.696482 | K77: 0.689966 | L77: 0.683834 | M77: 0.694926 | N77: 0.699079 | O77: 0.68831 | P77: 0.695184 | Q77: 0.69475 | R77: 0.691808 | S77: 0.676417 | T77: =U77+AH77 -> 8.2977 | U77: 6.252779 | V77: 0.690125 | W77: 0.70445 | X77: 0.69446 | Y77: 0.683807 | Z77: 0.70262 | AA77: 0.688212 | AB77: 0.699813 | AC77: 0.692095 | AD77: 0.697197 | AE77: 0 | AF77: 0 | AG77: 0 | AH77: 2.044921 | AI77: 0 | AJ77: 0 | AK77: 0 | AL77: 0 | AM77: 0 | AN77: 0 | AO77: 0 | AP77: 0 | AQ77: 0 | AR77: 0.679507 | AS77: 0.683012 | AT77: 0.682402 | AU77: 8.319997 | AV77: 0.692179 | AW77: 0.69842 | AX77: 0.687858 | AY77: 0.676326 | AZ77: 0.698767 | BA77: 0.68567 | BB77: 0.68378 | BC77: 0.690648 | BD77: 0.70125 | BE77: 0.695019 | BF77: 0.710925 | BG77: 0.699155
D78: XX 试验室 | E78: =IF(C78<>"",C78,E77) -> 创新中心 | F78: =IF(D78<>"",D78,"*") -> XX 试验室 | G78: 5.701424 | H78: 0.471084 | I78: 0.471775 | J78: 0.481917 | K78: 0.46122 | L78: 0.473659 | M78: 0.474608 | N78: 0.480449 | O78: 0.474768 | P78: 0.474666 | Q78: 0.480648 | R78: 0.481682 | S78: 0.474948 | T78: =U78+AH78 -> 5.648278 | U78: 4.249725 | V78: 0.47512 | W78: 0.464604 | X78: 0.478106 | Y78: 0.473568 | Z78: 0.471606 | AA78: 0.479678 | AB78: 0.465524 | AC78: 0.475049 | AD78: 0.46647 | AE78: 0 | AF78: 0 | AG78: 0 | AH78: 1.398553 | AI78: 0 | AJ78: 0 | AK78: 0 | AL78: 0 | AM78: 0 | AN78: 0 | AO78: 0 | AP78: 0 | AQ78: 0 | AR78: 0.464638 | AS78: 0.466648 | AT78: 0.467267 | AU78: 5.684959 | AV78: 0.471429 | AW78: 0.464719 | AX78: 0.476778 | AY78: 0.481475 | AZ78: 0.468237 | BA78: 0.476409 | BB78: 0.467212 | BC78: 0.47473 | BD78: 0.479318 | BE78: 0.473035 | BF78: 0.481018 | BG78: 0.470599
D79: XX 孵化业务 | E79: =IF(C79<>"",C79,E78) -> 创新中心 | F79: =IF(D79<>"",D79,"*") -> XX 孵化业务 | G79: 10.041242 | H79: 0.824201 | I79: 0.827689 | J79: 0.847068 | K79: 0.83444 | L79: 0.836876 | M79: 0.84467 | N79: 0.83209 | O79: 0.825442 | P79: 0.847739 | Q79: 0.836527 | R79: 0.84241 | S79: 0.84209 | T79: =U79+AH79 -> 10.13463 | U79: 7.607844 | V79: 0.857807 | W79: 0.829599 | X79: 0.849308 | Y79: 0.842637 | Z79: 0.858752 | AA79: 0.837458 | AB79: 0.840493 | AC79: 0.857688 | AD79: 0.834102 | AE79: 0 | AF79: 0 | AG79: 0 | AH79: 2.526786 | AI79: 0 | AJ79: 0 | AK79: 0 | AL79: 0 | AM79: 0 | AN79: 0 | AO79: 0 | AP79: 0 | AQ79: 0 | AR79: 0.850387 | AS79: 0.846551 | AT79: 0.829848 | AU79: 10.127055 | AV79: 0.845384 | AW79: 0.844371 | AX79: 0.843603 | AY79: 0.834829 | AZ79: 0.856915 | BA79: 0.847934 | BB79: 0.842718 | BC79: 0.849279 | BD79: 0.83143 | BE79: 0.844875 | BF79: 0.836439 | BG79: 0.849278
C80: 支持中心 | E80: =IF(C80<>"",C80,E79) -> 支持中心 | F80: =IF(D80<>"",D80,"*") -> * | G80: 26.066216 | H80: 2.18031 | I80: 2.189023 | J80: 2.153009 | K80: 2.164357 | L80: 2.16744 | M80: 2.176827 | N80: 2.186132 | O80: 2.180371 | P80: 2.157532 | Q80: 2.195424 | R80: 2.153085 | S80: 2.162706 | T80: =U80+AH80 -> 26.106934 | U80: 19.558048 | V80: 2.169179 | W80: 2.181829 | X80: 2.187556 | Y80: 2.191673 | Z80: 2.176548 | AA80: 2.164328 | AB80: 2.156665 | AC80: 2.190736 | AD80: 2.139534 | AE80: 0 | AF80: 0 | AG80: 0 | AH80: 6.548886 | AI80: 0 | AJ80: 0 | AK80: 0 | AL80: 0 | AM80: 0 | AN80: 0 | AO80: 0 | AP80: 0 | AQ80: 0 | AR80: 2.191422 | AS80: 2.173975 | AT80: 2.183489 | AU80: 26.139959 | AV80: 2.178369 | AW80: 2.173031 | AX80: 2.179411 | AY80: 2.183383 | AZ80: 2.205377 | BA80: 2.16698 | BB80: 2.177449 | BC80: 2.177918 | BD80: 2.169932 | BE80: 2.195136 | BF80: 2.172162 | BG80: 2.160811
D81: 财务部 | E81: =IF(C81<>"",C81,E80) -> 支持中心 | F81: =IF(D81<>"",D81,"*") -> 财务部 | G81: 10.220648 | H81: 0.852167 | I81: 0.856249 | J81: 0.847313 | K81: 0.849026 | L81: 0.853271 | M81: 0.859167 | N81: 0.85685 | O81: 0.86455 | P81: 0.84177 | Q81: 0.854818 | R81: 0.833818 | S81: 0.851649 | T81: =U81+AH81 -> 10.181782 | U81: 7.621265 | V81: 0.863102 | W81: 0.85502 | X81: 0.846417 | Y81: 0.85148 | Z81: 0.844626 | AA81: 0.847214 | AB81: 0.837834 | AC81: 0.839054 | AD81: 0.836518 | AE81: 0 | AF81: 0 | AG81: 0 | AH81: 2.560517 | AI81: 0 | AJ81: 0 | AK81: 0 | AL81: 0 | AM81: 0 | AN81: 0 | AO81: 0 | AP81: 0 | AQ81: 0 | AR81: 0.867929 | AS81: 0.845008 | AT81: 0.84758 | AU81: 10.194448 | AV81: 0.844008 | AW81: 0.847324 | AX81: 0.863778 | AY81: 0.84755 | AZ81: 0.846975 | BA81: 0.848965 | BB81: 0.862363 | BC81: 0.834602 | BD81: 0.85904 | BE81: 0.854021 | BF81: 0.847411 | BG81: 0.838411
D82: 人力资源部 | E82: =IF(C82<>"",C82,E81) -> 支持中心 | F82: =IF(D82<>"",D82,"*") -> 人力资源部 | G82: 9.057363 | H82: 0.760457 | I82: 0.764703 | J82: 0.746045 | K82: 0.758253 | L82: 0.743745 | M82: 0.750512 | N82: 0.751814 | O82: 0.740608 | P82: 0.757869 | Q82: 0.76619 | R82: 0.764996 | S82: 0.752171 | T82: =U82+AH82 -> 9.058353 | U82: 6.799579 | V82: 0.747243 | W82: 0.765752 | X82: 0.759923 | Y82: 0.759788 | Z82: 0.75712 | AA82: 0.744823 | AB82: 0.754935 | AC82: 0.770553 | AD82: 0.739442 | AE82: 0 | AF82: 0 | AG82: 0 | AH82: 2.258774 | AI82: 0 | AJ82: 0 | AK82: 0 | AL82: 0 | AM82: 0 | AN82: 0 | AO82: 0 | AP82: 0 | AQ82: 0 | AR82: 0.747684 | AS82: 0.758163 | AT82: 0.752927 | AU82: 9.095708 | AV82: 0.765564 | AW82: 0.74674 | AX82: 0.754815 | AY82: 0.753437 | AZ82: 0.773267 | BA82: 0.753192 | BB82: 0.750481 | BC82: 0.759501 | BD82: 0.754671 | BE82: 0.766789 | BF82: 0.760057 | BG82: 0.757194
D83: IT部 | E83: =IF(C83<>"",C83,E82) -> 支持中心 | F83: =IF(D83<>"",D83,"*") -> IT部 | G83: 4.277058 | H83: 0.358038 | I83: 0.357826 | J83: 0.355543 | K83: 0.352682 | L83: 0.358122 | M83: 0.358184 | N83: 0.359416 | O83: 0.360984 | P83: 0.354436 | Q83: 0.362219 | R83: 0.353256 | S83: 0.346352 | T83: =U83+AH83 -> 4.323863 | U83: 3.229455 | V83: 0.344819 | W83: 0.360514 | X83: 0.3628 | Y83: 0.360503 | Z83: 0.367113 | AA83: 0.359187 | AB83: 0.349351 | AC83: 0.366995 | AD83: 0.358173 | AE83: 0 | AF83: 0 | AG83: 0 | AH83: 1.094408 | AI83: 0 | AJ83: 0 | AK83: 0 | AL83: 0 | AM83: 0 | AN83: 0 | AO83: 0 | AP83: 0 | AQ83: 0 | AR83: 0.358455 | AS83: 0.367319 | AT83: 0.368634 | AU83: 4.324981 | AV83: 0.367475 | AW83: 0.362364 | AX83: 0.36048 | AY83: 0.368402 | AZ83: 0.366646 | BA83: 0.351181 | BB83: 0.350393 | BC83: 0.369896 | BD83: 0.355669 | BE83: 0.362196 | BF83: 0.353961 | BG83: 0.356318
D84: 总经办 | E84: =IF(C84<>"",C84,E83) -> 支持中心 | F84: =IF(D84<>"",D84,"*") -> 总经办 | G84: 2.511147 | H84: 0.209648 | I84: 0.210245 | J84: 0.204108 | K84: 0.204396 | L84: 0.212302 | M84: 0.208964 | N84: 0.218052 | O84: 0.214229 | P84: 0.203457 | Q84: 0.212197 | R84: 0.201015 | S84: 0.212534 | T84: =U84+AH84 -> 2.542936 | U84: 1.907749 | V84: 0.214015 | W84: 0.200543 | X84: 0.218416 | Y84: 0.219902 | Z84: 0.207689 | AA84: 0.213104 | AB84: 0.214545 | AC84: 0.214134 | AD84: 0.205401 | AE84: 0 | AF84: 0 | AG84: 0 | AH84: 0.635187 | AI84: 0 | AJ84: 0 | AK84: 0 | AL84: 0 | AM84: 0 | AN84: 0 | AO84: 0 | AP84: 0 | AQ84: 0 | AR84: 0.217354 | AS84: 0.203485 | AT84: 0.214348 | AU84: 2.524822 | AV84: 0.201322 | AW84: 0.216603 | AX84: 0.200338 | AY84: 0.213994 | AZ84: 0.218489 | BA84: 0.213642 | BB84: 0.214212 | BC84: 0.213919 | BD84: 0.200552 | BE84: 0.21213 | BF84: 0.210733 | BG84: 0.208888
B86: 薪酬合计
B87: 合计 | E87: * | F87: * | G87: 1061.9727 | H87: 88.581656 | I87: 88.567672 | J87: 88.560581 | K87: 88.361038 | L87: 88.295202 | M87: 88.632269 | N87: 88.70816 | O87: 88.396137 | P87: 88.739913 | Q87: 88.253423 | R87: 88.465491 | S87: 88.411155 | T87: =U87+AH87 -> 1062.419 | U87: 796.57198 | V87: 88.485347 | W87: 88.50066 | X87: 88.57919 | Y87: 88.516566 | Z87: 88.166557 | AA87: 88.52879 | AB87: 88.564073 | AC87: 88.649859 | AD87: 88.580935 | AE87: 0 | AF87: 0 | AG87: 0 | AH87: 265.84706 | AI87: 0 | AJ87: 0 | AK87: 0 | AL87: 0 | AM87: 0 | AN87: 0 | AO87: 0 | AP87: 0 | AQ87: 0 | AR87: 88.840854 | AS87: 88.820874 | AT87: 88.185337 | AU87: 1061.6855 | AV87: 88.398726 | AW87: 88.787961 | AX87: 88.576717 | AY87: 88.445268 | AZ87: 88.719885 | BA87: 88.261823 | BB87: 88.482963 | BC87: 88.672729 | BD87: 88.537698 | BE87: 88.683521 | BF87: 87.897778 | BG87: 88.220449
C88: 流程中心 | E88: =IF(C88<>"",C88,E85) -> 流程中心 | F88: =IF(D88<>"",D88,"*") -> * | G88: 423.69556 | H88: 35.221793 | I88: 35.352789 | J88: 35.39168 | K88: 35.099474 | L88: 35.333415 | M88: 35.261086 | N88: 35.47398 | O88: 35.275257 | P88: 35.483598 | Q88: 35.310633 | R88: 35.296127 | S88: 35.195723 | T88: =U88+AH88 -> 422.82361 | U88: 317.04582 | V88: 35.261507 | W88: 35.196642 | X88: 35.156624 | Y88: 35.239988 | Z88: 35.0821 | AA88: 35.153046 | AB88: 35.177152 | AC88: 35.304103 | AD88: 35.474657 | AE88: 0 | AF88: 0 | AG88: 0 | AH88: 105.77779 | AI88: 0 | AJ88: 0 | AK88: 0 | AL88: 0 | AM88: 0 | AN88: 0 | AO88: 0 | AP88: 0 | AQ88: 0 | AR88: 35.39597 | AS88: 35.297441 | AT88: 35.084377 | AU88: 423.11458 | AV88: 35.147348 | AW88: 35.376992 | AX88: 35.542351 | AY88: 35.201508 | AZ88: 35.302922 | BA88: 35.21891 | BB88: 35.341845 | BC88: 35.479098 | BD88: 35.03889 | BE88: 35.173091 | BF88: 35.16801 | BG88: 35.123612
A89: 销售及管理费用 | D89: 销售中心 | E89: =IF(C89<>"",C89,E88) -> 流程中心 | F89: =IF(D89<>"",D89,"*") -> 销售中心 | G89: 219.73569 | H89: 18.187896 | I89: 18.218791 | J89: 18.343284 | K89: 18.124766 | L89: 18.383024 | M89: 18.251878 | N89: 18.336378 | O89: 18.360635 | P89: 18.47012 | Q89: 18.385432 | R89: 18.400064 | S89: 18.273423 | T89: =U89+AH89 -> 219.21702 | U89: 164.11084 | V89: 18.374951 | W89: 18.254169 | X89: 18.089896 | Y89: 18.248024 | Z89: 18.204531 | AA89: 18.270522 | AB89: 18.087135 | AC89: 18.165541 | AD89: 18.416068 | AE89: 0 | AF89: 0 | AG89: 0 | AH89: 55.106181 | AI89: 0 | AJ89: 0 | AK89: 0 | AL89: 0 | AM89: 0 | AN89: 0 | AO89: 0 | AP89: 0 | AQ89: 0 | AR89: 18.418303 | AS89: 18.446635 | AT89: 18.241243 | AU89: 219.35222 | AV89: 18.20149 | AW89: 18.382712 | AX89: 18.412277 | AY89: 18.349851 | AZ89: 18.386882 | BA89: 18.267432 | BB89: 18.275892 | BC89: 18.38208 | BD89: 18.09589 | BE89: 18.240091 | BF89: 18.263738 | BG89: 18.093881
A90: 销售及管理费用 | D90: 制造中心 | E90: =IF(C90<>"",C90,E89) -> 流程中心 | F90: =IF(D90<>"",D90,"*") -> 制造中心 | G90: 203.95986 | H90: 17.033897 | I90: 17.133998 | J90: 17.048396 | K90: 16.974708 | L90: 16.950391 | M90: 17.009208 | N90: 17.137602 | O90: 16.914622 | P90: 17.013478 | Q90: 16.925201 | R90: 16.896063 | S90: 16.9223 | T90: =U90+AH90 -> 203.60659 | U90: 152.93498 | V90: 16.886556 | W90: 16.942473 | X90: 17.066728 | Y90: 16.991964 | Z90: 16.877569 | AA90: 16.882524 | AB90: 17.090017 | AC90: 17.138562 | AD90: 17.058589 | AE90: 0 | AF90: 0 | AG90: 0 | AH90: 50.671607 | AI90: 0 | AJ90: 0 | AK90: 0 | AL90: 0 | AM90: 0 | AN90: 0 | AO90: 0 | AP90: 0 | AQ90: 0 | AR90: 16.977667 | AS90: 16.850806 | AT90: 16.843134 | AU90: 203.76236 | AV90: 16.945858 | AW90: 16.99428 | AX90: 17.130074 | AY90: 16.851657 | AZ90: 16.91604 | BA90: 16.951478 | BB90: 17.065953 | BC90: 17.097018 | BD90: 16.943 | BE90: 16.933 | BF90: 16.904272 | BG90: 17.029731
C91: 创新中心 | E91: =IF(C91<>"",C91,E90) -> 创新中心 | F91: =IF(D91<>"",D91,"*") -> * | G91: 339.49213 | H91: 28.325036 | I91: 28.469274 | J91: 28.356305 | K91: 28.284344 | L91: 28.17168 | M91: 28.450805 | N91: 28.15881 | O91: 28.303781 | P91: 28.487028 | Q91: 28.065074 | R91: 28.13893 | S91: 28.28106 | T91: =U91+AH91 -> 340.23563 | U91: 255.17371 | V91: 28.223469 | W91: 28.499114 | X91: 28.521016 | Y91: 28.282788 | Z91: 28.178848 | AA91: 28.308445 | AB91: 28.306166 | AC91: 28.443882 | AD91: 28.409981 | AE91: 0 | AF91: 0 | AG91: 0 | AH91: 85.061919 | AI91: 0 | AJ91: 0 | AK91: 0 | AL91: 0 | AM91: 0 | AN91: 0 | AO91: 0 | AP91: 0 | AQ91: 0 | AR91: 28.387021 | AS91: 28.503838 | AT91: 28.17106 | AU91: 339.90607 | AV91: 28.485637 | AW91: 28.190734 | AX91: 28.270426 | AY91: 28.279794 | AZ91: 28.506289 | BA91: 28.406108 | BB91: 28.244646 | BC91: 28.21611 | BD91: 28.546128 | BE91: 28.399874 | BF91: 27.98043 | BG91: 28.379895
A92: 销售及管理费用 | D92: 产品 研发部 | E92: =IF(C92<>"",C92,E91) -> 创新中心 | F92: =IF(D92<>"",D92,"*") -> 产品 研发部 | G92: 121.39231 | H92: 10.12519 | I92: 10.160649 | J92: 10.058545 | K92: 10.123768 | L92: 10.05639 | M92: 10.168394 | N92: 9.982486 | O92: 10.159292 | P92: 10.131403 | Q92: 10.069309 | R92: 10.281848 | S92: 10.075041 | T92: =U92+AH92 -> 122.23041 | U92: 91.549211 | V92: 10.158988 | W92: 10.26071 | X92: 10.181673 | Y92: 10.112185 | Z92: 10.140687 | AA92: 10.074552 | AB92: 10.220355 | AC92: 10.199353 | AD92: 10.200708 | AE92: 0 | AF92: 0 | AG92: 0 | AH92: 30.681202 | AI92: 0 | AJ92: 0 | AK92: 0 | AL92: 0 | AM92: 0 | AN92: 0 | AO92: 0 | AP92: 0 | AQ92: 0 | AR92: 10.223469 | AS92: 10.250737 | AT92: 10.206996 | AU92: 121.53294 | AV92: 10.163735 | AW92: 10.04811 | AX92: 10.096119 | AY92: 10.105181 | AZ92: 10.125173 | BA92: 10.314251 | BB92: 10.161502 | BC92: 10.141483 | BD92: 10.106167 | BE92: 10.18936 | BF92: 9.961462 | BG92: 10.120395
A93: 销售及管理费用 | D93: XX 试验室 | E93: =IF(C93<>"",C93,E92) -> 创新中心 | F93: =IF(D93<>"",D93,"*") -> XX 试验室 | G93: 81.069447 | H93: 6.750227 | I93: 6.792732 | J93: 6.80386 | K93: 6.682254 | L93: 6.841309 | M93: 6.717436 | N93: 6.718581 | O93: 6.65535 | P93: 6.917669 | Q93: 6.681955 | R93: 6.696381 | S93: 6.811693 | T93: =U93+AH93 -> 80.808863 | U93: 60.67458 | V93: 6.687369 | W93: 6.876016 | X93: 6.786074 | Y93: 6.694633 | Z93: 6.674863 | AA93: 6.835998 | AB93: 6.670672 | AC93: 6.694681 | AD93: 6.754274 | AE93: 0 | AF93: 0 | AG93: 0 | AH93: 20.134283 | AI93: 0 | AJ93: 0 | AK93: 0 | AL93: 0 | AM93: 0 | AN93: 0 | AO93: 0 | AP93: 0 | AQ93: 0 | AR93: 6.635627 | AS93: 6.815098 | AT93: 6.683558 | AU93: 80.921163 | AV93: 6.853025 | AW93: 6.717017 | AX93: 6.689323 | AY93: 6.709568 | AZ93: 6.862306 | BA93: 6.732259 | BB93: 6.712317 | BC93: 6.707793 | BD93: 6.775221 | BE93: 6.708265 | BF93: 6.757384 | BG93: 6.696685
A94: 销售及管理费用 | D94: XX 孵化业务 | E94: =IF(C94<>"",C94,E93) -> 创新中心 | F94: =IF(D94<>"",D94,"*") -> XX 孵化业务 | G94: 137.03036 | H94: 11.449619 | I94: 11.515893 | J94: 11.4939 | K94: 11.478322 | L94: 11.273981 | M94: 11.564975 | N94: 11.457743 | O94: 11.489139 | P94: 11.437956 | Q94: 11.31381 | R94: 11.160701 | S94: 11.394326 | T94: =U94+AH94 -> 137.19635 | U94: 102.94992 | V94: 11.377112 | W94: 11.362388 | X94: 11.553269 | Y94: 11.47597 | Z94: 11.363298 | AA94: 11.397895 | AB94: 11.415139 | AC94: 11.549848 | AD94: 11.454999 | AE94: 0 | AF94: 0 | AG94: 0 | AH94: 34.246434 | AI94: 0 | AJ94: 0 | AK94: 0 | AL94: 0 | AM94: 0 | AN94: 0 | AO94: 0 | AP94: 0 | AQ94: 0 | AR94: 11.527925 | AS94: 11.438003 | AT94: 11.280506 | AU94: 137.45197 | AV94: 11.468877 | AW94: 11.425607 | AX94: 11.484984 | AY94: 11.465045 | AZ94: 11.51881 | BA94: 11.359598 | BB94: 11.370827 | BC94: 11.366834 | BD94: 11.66474 | BE94: 11.502249 | BF94: 11.261584 | BG94: 11.562815
C95: 支持中心 | E95: =IF(C95<>"",C95,E94) -> 支持中心 | F95: =IF(D95<>"",D95,"*") -> * | G95: 298.78501 | H95: 25.034827 | I95: 24.745609 | J95: 24.812596 | K95: 24.97722 | L95: 24.790107 | M95: 24.920378 | N95: 25.07537 | O95: 24.817099 | P95: 24.769287 | Q95: 24.877716 | R95: 25.030434 | S95: 24.934372 | T95: =U95+AH95 -> 299.35981 | U95: 224.35245 | V95: 25.000371 | W95: 24.804904 | X95: 24.90155 | Y95: 24.99379 | Z95: 24.905609 | AA95: 25.067299 | AB95: 25.080755 | AC95: 24.901874 | AD95: 24.696297 | AE95: 0 | AF95: 0 | AG95: 0 | AH95: 75.007358 | AI95: 0 | AJ95: 0 | AK95: 0 | AL95: 0 | AM95: 0 | AN95: 0 | AO95: 0 | AP95: 0 | AQ95: 0 | AR95: 25.057863 | AS95: 25.019595 | AT95: 24.9299 | AU95: 298.66487 | AV95: 24.765741 | AW95: 25.220235 | AX95: 24.76394 | AY95: 24.963966 | AZ95: 24.910674 | BA95: 24.636805 | BB95: 24.896472 | BC95: 24.977521 | BD95: 24.95268 | BE95: 25.110556 | BF95: 24.749338 | BG95: 24.716942
A96: 销售及管理费用 | D96: 财务部 | E96: =IF(C96<>"",C96,E95) -> 支持中心 | F96: =IF(D96<>"",D96,"*") -> 财务部 | G96: 118.11675 | H96: 9.909728 | I96: 9.820369 | J96: 9.781062 | K96: 9.798827 | L96: 9.819362 | M96: 9.938859 | N96: 9.833234 | O96: 9.755203 | P96: 9.90912 | Q96: 9.940548 | R96: 9.816616 | S96: 9.793824 | T96: =U96+AH96 -> 118.20063 | U96: 88.530945 | V96: 9.892703 | W96: 9.80814 | X96: 9.902366 | Y96: 9.768324 | Z96: 9.822745 | AA96: 9.884157 | AB96: 9.822495 | AC96: 9.841582 | AD96: 9.788433 | AE96: 0 | AF96: 0 | AG96: 0 | AH96: 29.669688 | AI96: 0 | AJ96: 0 | AK96: 0 | AL96: 0 | AM96: 0 | AN96: 0 | AO96: 0 | AP96: 0 | AQ96: 0 | AR96: 9.992021 | AS96: 9.863724 | AT96: 9.813943 | AU96: 118.19027 | AV96: 9.709198 | AW96: 9.986817 | AX96: 9.800812 | AY96: 9.911738 | AZ96: 9.812794 | BA96: 9.78961 | BB96: 9.861204 | BC96: 9.924292 | BD96: 9.868513 | BE96: 9.99486 | BF96: 9.80426 | BG96: 9.726177
A97: 销售及管理费用 | D97: 人力资源部 | E97: =IF(C97<>"",C97,E96) -> 支持中心 | F97: =IF(D97<>"",D97,"*") -> 人力资源部 | G97: 104.15671 | H97: 8.676185 | I97: 8.549403 | J97: 8.639744 | K97: 8.726448 | L97: 8.589544 | M97: 8.639558 | N97: 8.7988 | O97: 8.738458 | P97: 8.610048 | Q97: 8.636001 | R97: 8.801604 | S97: 8.750917 | T97: =U97+AH97 -> 104.64709 | U97: 78.392333 | V97: 8.683497 | W97: 8.624751 | X97: 8.643257 | Y97: 8.820409 | Z97: 8.732956 | AA97: 8.825902 | AB97: 8.791178 | AC97: 8.675688 | AD97: 8.594695 | AE97: 0 | AF97: 0 | AG97: 0 | AH97: 26.25476 | AI97: 0 | AJ97: 0 | AK97: 0 | AL97: 0 | AM97: 0 | AN97: 0 | AO97: 0 | AP97: 0 | AQ97: 0 | AR97: 8.8095 | AS97: 8.743368 | AT97: 8.701892 | AU97: 103.97743 | AV97: 8.603852 | AW97: 8.734236 | AX97: 8.658926 | AY97: 8.683968 | AZ97: 8.714741 | BA97: 8.609423 | BB97: 8.60364 | BC97: 8.674677 | BD97: 8.698227 | BE97: 8.746528 | BF97: 8.60173 | BG97: 8.647481
A98: 销售及管理费用 | D98: IT部 | E98: =IF(C98<>"",C98,E97) -> 支持中心 | F98: =IF(D98<>"",D98,"*") -> IT部 | G98: 49.87975 | H98: 4.224505 | I98: 4.199002 | J98: 4.141012 | K98: 4.183954 | L98: 4.174131 | M98: 4.117127 | N98: 4.187815 | O98: 4.102997 | P98: 4.126348 | Q98: 4.129319 | R98: 4.16159 | S98: 4.13195 | T98: =U98+AH98 -> 49.80182 | U98: 37.339531 | V98: 4.138377 | W98: 4.158256 | X98: 4.181026 | Y98: 4.115537 | Z98: 4.107947 | AA98: 4.186882 | AB98: 4.18542 | AC98: 4.119651 | AD98: 4.146435 | AE98: 0 | AF98: 0 | AG98: 0 | AH98: 12.462289 | AI98: 0 | AJ98: 0 | AK98: 0 | AL98: 0 | AM98: 0 | AN98: 0 | AO98: 0 | AP98: 0 | AQ98: 0 | AR98: 4.096667 | AS98: 4.192023 | AT98: 4.173599 | AU98: 49.831095 | AV98: 4.179969 | AW98: 4.267763 | AX98: 4.118984 | AY98: 4.183536 | AZ98: 4.119494 | BA98: 4.089539 | BB98: 4.164457 | BC98: 4.090824 | BD98: 4.20462 | BE98: 4.146624 | BF98: 4.171247 | BG98: 4.094038
A99: 销售及管理费用 | D99: 总经办 | E99: =IF(C99<>"",C99,E98) -> 支持中心 | F99: =IF(D99<>"",D99,"*") -> 总经办 | G99: 26.631803 | H99: 2.224409 | I99: 2.176835 | J99: 2.250778 | K99: 2.267991 | L99: 2.20707 | M99: 2.224834 | N99: 2.255521 | O99: 2.220441 | P99: 2.123771 | Q99: 2.171848 | R99: 2.250624 | S99: 2.257681 | T99: =U99+AH99 -> 26.710261 | U99: 20.08964 | V99: 2.285794 | W99: 2.213757 | X99: 2.174901 | Y99: 2.28952 | Z99: 2.241961 | AA99: 2.170358 | AB99: 2.281662 | AC99: 2.264953 | AD99: 2.166734 | AE99: 0 | AF99: 0 | AG99: 0 | AH99: 6.620621 | AI99: 0 | AJ99: 0 | AK99: 0 | AL99: 0 | AM99: 0 | AN99: 0 | AO99: 0 | AP99: 0 | AQ99: 0 | AR99: 2.159675 | AS99: 2.22048 | AT99: 2.240466 | AU99: 26.666071 | AV99: 2.272722 | AW99: 2.231419 | AX99: 2.185218 | AY99: 2.184724 | AZ99: 2.263645 | BA99: 2.148233 | BB99: 2.267171 | BC99: 2.287728 | BD99: 2.18132 | BE99: 2.222544 | BF99: 2.172101 | BG99: 2.249246
B101: 社保
B102: 合计 | E102: * | F102: * | G102: 207.70472 | H102: 17.333698 | I102: 17.288439 | J102: 17.295349 | K102: 17.295408 | L102: 17.29975 | M102: 17.334797 | N102: 17.365278 | O102: 17.31991 | P102: 17.375937 | Q102: 17.220423 | R102: 17.302356 | S102: 17.27338 | T102: =U102+AH102 -> 207.69344 | U102: 155.7205 | V102: 17.358525 | W102: 17.310225 | X102: 17.312825 | Y102: 17.312228 | Z102: 17.202149 | AA102: 17.292011 | AB102: 17.278945 | AC102: 17.311306 | AD102: 17.342289 | AE102: 0 | AF102: 0 | AG102: 0 | AH102: 51.972936 | AI102: 0 | AJ102: 0 | AK102: 0 | AL102: 0 | AM102: 0 | AN102: 0 | AO102: 0 | AP102: 0 | AQ102: 0 | AR102: 17.358113 | AS102: 17.402202 | AT102: 17.212621 | AU102: 207.61985 | AV102: 17.271032 | AW102: 17.405898 | AX102: 17.32838 | AY102: 17.311086 | AZ102: 17.374152 | BA102: 17.260302 | BB102: 17.288043 | BC102: 17.33895 | BD102: 17.31055 | BE102: 17.362508 | BF102: 17.132078 | BG102: 17.236873
C103: 流程中心 | E103: =IF(C103<>"",C103,E100) -> 流程中心 | F103: =IF(D103<>"",D103,"*") -> * | G103: 76.498481 | H103: 6.352014 | I103: 6.357188 | J103: 6.403337 | K103: 6.338166 | L103: 6.40716 | M103: 6.345557 | N103: 6.419326 | O103: 6.375592 | P103: 6.407957 | Q103: 6.363262 | R103: 6.375218 | S103: 6.353704 | T103: =U103+AH103 -> 76.195584 | U103: 57.145645 | V103: 6.403452 | W103: 6.347949 | X103: 6.326589 | Y103: 6.368674 | Z103: 6.29829 | AA103: 6.316439 | AB103: 6.316484 | AC103: 6.350608 | AD103: 6.41716 | AE103: 0 | AF103: 0 | AG103: 0 | AH103: 19.049939 | AI103: 0 | AJ103: 0 | AK103: 0 | AL103: 0 | AM103: 0 | AN103: 0 | AO103: 0 | AP103: 0 | AQ103: 0 | AR103: 6.36544 | AS103: 6.38027 | AT103: 6.304229 | AU103: 76.366367 | AV103: 6.333725 | AW103: 6.388336 | AX103: 6.443261 | AY103: 6.369333 | AZ103: 6.380343 | BA103: 6.359998 | BB103: 6.363721 | BC103: 6.412643 | BD103: 6.303917 | BE103: 6.356973 | BF103: 6.317747 | BG103: 6.33637
A104: 销售及管理费用 | D104: 销售中心 | E104: =IF(C104<>"",C104,E103) -> 流程中心 | F104: =IF(D104<>"",D104,"*") -> 销售中心 | G104: 44.349634 | H104: 3.660325 | I104: 3.657812 | J104: 3.708408 | K104: 3.662527 | L104: 3.726385 | M104: 3.689128 | N104: 3.696757 | O104: 3.70768 | P104: 3.734585 | Q104: 3.705286 | R104: 3.713901 | S104: 3.68684 | T104: =U104+AH104 -> 44.182177 | U104: 33.069408 | V104: 3.734986 | W104: 3.678742 | X104: 3.633569 | Y104: 3.679548 | Z104: 3.654752 | AA104: 3.672835 | AB104: 3.632983 | AC104: 3.654365 | AD104: 3.727628 | AE104: 0 | AF104: 0 | AG104: 0 | AH104: 11.112769 | AI104: 0 | AJ104: 0 | AK104: 0 | AL104: 0 | AM104: 0 | AN104: 0 | AO104: 0 | AP104: 0 | AQ104: 0 | AR104: 3.710202 | AS104: 3.729947 | AT104: 3.67262 | AU104: 44.249452 | AV104: 3.664769 | AW104: 3.711769 | AX104: 3.724138 | AY104: 3.716975 | AZ104: 3.706229 | BA104: 3.701818 | BB104: 3.672707 | BC104: 3.713734 | BD104: 3.639979 | BE104: 3.683608 | BF104: 3.670452 | BG104: 3.643274
A105: 销售及管理费用 | D105: 制造中心 | E105: =IF(C105<>"",C105,E104) -> 流程中心 | F105: =IF(D105<>"",D105,"*") -> 制造中心 | G105: 32.148847 | H105: 2.691689 | I105: 2.699376 | J105: 2.694929 | K105: 2.675639 | L105: 2.680775 | M105: 2.656429 | N105: 2.722569 | O105: 2.667912 | P105: 2.673372 | Q105: 2.657976 | R105: 2.661317 | S105: 2.666864 | T105: =U105+AH105 -> 32.013407 | U105: 24.076237 | V105: 2.668466 | W105: 2.669207 | X105: 2.69302 | Y105: 2.689126 | Z105: 2.643538 | AA105: 2.643604 | AB105: 2.683501 | AC105: 2.696243 | AD105: 2.689532 | AE105: 0 | AF105: 0 | AG105: 0 | AH105: 7.93717 | AI105: 0 | AJ105: 0 | AK105: 0 | AL105: 0 | AM105: 0 | AN105: 0 | AO105: 0 | AP105: 0 | AQ105: 0 | AR105: 2.655238 | AS105: 2.650323 | AT105: 2.631609 | AU105: 32.116915 | AV105: 2.668956 | AW105: 2.676567 | AX105: 2.719123 | AY105: 2.652358 | AZ105: 2.674114 | BA105: 2.65818 | BB105: 2.691014 | BC105: 2.698909 | BD105: 2.663938 | BE105: 2.673365 | BF105: 2.647295 | BG105: 2.693096
C106: 创新中心 | E106: =IF(C106<>"",C106,E105) -> 创新中心 | F106: =IF(D106<>"",D106,"*") -> * | G106: 70.199198 | H106: 5.866275 | I106: 5.88611 | J106: 5.840194 | K106: 5.845071 | L106: 5.838 | M106: 5.90051 | N106: 5.817469 | O106: 5.885643 | P106: 5.915634 | Q106: 5.781438 | R106: 5.796954 | S106: 5.8259 | T106: =U106+AH106 -> 70.331964 | U106: 52.742856 | V106: 5.830462 | W106: 5.906935 | X106: 5.905264 | Y106: 5.83885 | Z106: 5.818056 | AA106: 5.848054 | AB106: 5.843739 | AC106: 5.868359 | AD106: 5.883137 | AE106: 0 | AF106: 0 | AG106: 0 | AH106: 17.589108 | AI106: 0 | AJ106: 0 | AK106: 0 | AL106: 0 | AM106: 0 | AN106: 0 | AO106: 0 | AP106: 0 | AQ106: 0 | AR106: 5.87634 | AS106: 5.899071 | AT106: 5.813697 | AU106: 70.267768 | AV106: 5.893321 | AW106: 5.829548 | AX106: 5.847306 | AY106: 5.845795 | AZ106: 5.900041 | BA106: 5.88199 | BB106: 5.831248 | BC106: 5.812842 | BD106: 5.904528 | BE106: 5.880141 | BF106: 5.77388 | BG106: 5.867128
A107: 销售及管理费用 | D107: 产品 研发部 | E107: =IF(C107<>"",C107,E106) -> 创新中心 | F107: =IF(D107<>"",D107,"*") -> 产品 研发部 | G107: 24.258118 | H107: 2.02311 | I107: 2.024059 | J107: 1.993625 | K107: 2.011445 | L107: 2.021379 | M107: 2.041242 | N107: 1.98476 | O107: 2.057303 | P107: 2.036783 | Q107: 2.000267 | R107: 2.066588 | S107: 1.997557 | T107: =U107+AH107 -> 24.437605 | U107: 18.304477 | V107: 2.03129 | W107: 2.059718 | X107: 2.038057 | Y107: 2.02823 | Z107: 2.015207 | AA107: 2.002118 | AB107: 2.046655 | AC107: 2.045429 | AD107: 2.037773 | AE107: 0 | AF107: 0 | AG107: 0 | AH107: 6.133128 | AI107: 0 | AJ107: 0 | AK107: 0 | AL107: 0 | AM107: 0 | AN107: 0 | AO107: 0 | AP107: 0 | AQ107: 0 | AR107: 2.044294 | AS107: 2.047434 | AT107: 2.0414 | AU107: 24.262676 | AV107: 2.033362 | AW107: 1.999809 | AX107: 2.011226 | AY107: 2.030681 | AZ107: 2.018046 | BA107: 2.07185 | BB107: 2.034663 | BC107: 2.012923 | BD107: 2.013224 | BE107: 2.040464 | BF107: 1.980051 | BG107: 2.016377
...

Sheet 财务折旧
G1: 实际2020全年 | I1: 实际截止2020年10月 | K1: 估计从2020年11月到年底 | M1: 估计2021全年 | O1: 预算2022全年
G2: A2020FY | I2: A202110YTD | K2: E202110YTG | M2: E2021FY | O2: B2022FY
G3: 金额 | I3: 金额 | K3: 金额 | M3: 金额 | O3: 金额
B4: 合计 | E4: * | F4: * | G4: 122.135 | I4: 155.09167 | K4: 47.673333 | M4: 202.765 | O4: 284.02
C5: 流程中心 | E5: =IF(C5<>"",C5,E4) -> 流程中心 | F5: =IF(D5<>"",D5,"*") -> * | G5: 120.175 | I5: 152.79167 | K5: 47.183333 | M5: 199.975 | O5: 280.25
A6: 销售及管理费用 | D6: 销售中心 | E6: =IF(C6<>"",C6,E5) -> 流程中心 | F6: =IF(D6<>"",D6,"*") -> 销售中心 | G6: 0 | I6: 0 | K6: 0 | M6: 0 | O6: 0
D7: 制造中心 | E7: =IF(C7<>"",C7,E6) -> 流程中心 | F7: =IF(D7<>"",D7,"*") -> 制造中心 | G7: 120.175 | I7: 152.79167 | K7: 47.183333 | M7: 199.975 | O7: 280.25
C8: 改善中心 | E8: =IF(C8<>"",C8,E7) -> 改善中心 | F8: =IF(D8<>"",D8,"*") -> * | G8: 0 | I8: 0 | K8: 0 | M8: 0 | O8: 0
A9: 销售及管理费用 | C9: =C8 -> 改善中心 | D9: 流程优化项目小组 | E9: =IF(C9<>"",C9,E8) -> 改善中心 | F9: =IF(D9<>"",D9,"*") -> 流程优化项目小组 | G9: 0 | I9: 0 | K9: 0 | M9: 0 | O9: 0
A10: 销售及管理费用 | C10: =C9 -> 改善中心 | D10: 战略预算项目小组 | E10: =IF(C10<>"",C10,E9) -> 改善中心 | F10: =IF(D10<>"",D10,"*") -> 战略预算项目小组 | G10: 0 | I10: 0 | K10: 0 | M10: 0 | O10: 0
C11: 创新中心 | E11: =IF(C11<>"",C11,E10) -> 创新中心 | F11: =IF(D11<>"",D11,"*") -> * | G11: 0 | I11: 0 | K11: 0 | M11: 0 | O11: 0
A12: 销售及管理费用 | C12: =C11 -> 创新中心 | D12: 产品研发部 | E12: =IF(C12<>"",C12,E11) -> 创新中心 | F12: =IF(D12<>"",D12,"*") -> 产品研发部 | G12: 0 | I12: 0 | K12: 0 | M12: 0 | O12: 0
A13: 销售及管理费用 | C13: =C12 -> 创新中心 | D13: XX试验室 | E13: =IF(C13<>"",C13,E12) -> 创新中心 | F13: =IF(D13<>"",D13,"*") -> XX试验室 | G13: 0 | I13: 0 | K13: 0 | M13: 0 | O13: 0
A14: 销售及管理费用 | C14: =C13 -> 创新中心 | D14: XX孵化业务 | E14: =IF(C14<>"",C14,E13) -> 创新中心 | F14: =IF(D14<>"",D14,"*") -> XX孵化业务 | G14: 0 | I14: 0 | K14: 0 | M14: 0 | O14: 0
C15: 支持中心 | E15: =IF(C15<>"",C15,E14) -> 支持中心 | F15: =IF(D15<>"",D15,"*") -> * | G15: 1.96 | I15: 2.3 | K15: 0.49 | M15: 2.79 | O15: 3.77
A16: 销售及管理费用 | C16: =C15 -> 支持中心 | D16: 财务部 | E16: =IF(C16<>"",C16,E15) -> 支持中心 | F16: =IF(D16<>"",D16,"*") -> 财务部 | G16: 1.96 | I16: 0 | K16: 0.49 | M16: 0.49 | O16: 1.47
A17: 销售及管理费用 | C17: =C16 -> 支持中心 | D17: 人力资源部 | E17: =IF(C17<>"",C17,E16) -> 支持中心 | F17: =IF(D17<>"",D17,"*") -> 人力资源部 | G17: 0 | I17: 0 | K17: 0 | M17: 0 | O17: 0
A18: 销售及管理费用 | C18: =C17 -> 支持中心 | D18: IT部 | E18: =IF(C18<>"",C18,E17) -> 支持中心 | F18: =IF(D18<>"",D18,"*") -> IT部 | G18: 0 | I18: 0 | K18: 0 | M18: 0 | O18: 0
A19: 销售及管理费用 | C19: =C18 -> 支持中心 | D19: 行政部 | E19: =IF(C19<>"",C19,E18) -> 支持中心 | F19: =IF(D19<>"",D19,"*") -> 行政部 | G19: 0 | I19: 2.3 | K19: 0 | M19: 2.3 | O19: 2.3

Sheet 日常费用
B2: 日常运营费预算校准表
B4: 当年实际截止月份 | I4: 44469
B5: 责任中心\部门\预算科目 | I5: ="B"&YEAR(I4)+1 -> B2022 | J5: 占营收% | K5: 校准状态 | L5: ="A"&YEAR($I$4)-1 -> A2020 | M5: 占营收% | O5: ="A"&YEAR($I$4) -> A2021 | P5: 占营收% | Q5: ="E"&YEAR($I$4) -> E2021 | R5: 占营收% | S5: ="E"&YEAR($I$4) -> E2021 | T5: 占营收% | U5: E2021/A2020 | Y5: ="B"&YEAR($I$4)+1 -> B2022 | Z5: 占营收% | AA5: B2022/E2021
I6: (大帐) | L6: (细账) | O6: YTD | Q6: YTG | S6: (细账) | U6: 差异 | V6: % | W6: 说明 | Y6: (细账) | AA6: 差异 | AB6: % | AC6: 说明
L7: =LEFT(L5,1) -> A | O7: =LEFT(O5,1) -> A | Q7: =LEFT(Q5,1) -> E | Y7: =LEFT(Y5,1) -> B
L8: =DATE(YEAR($I$4)-1,1,1) -> 43831 | O8: =DATE(YEAR($I$4),1,1) -> 44197 | Q8: =O9+1 -> 44470 | Y8: =DATE(YEAR($I$4)+1,1,1) -> 44562
L9: =DATE(YEAR($I$4)-1,12,31) -> 44196 | O9: =EOMONTH(DATE(YEAR($I$4),MONTH(I4),1),0) -> 44469 | Q9: =DATE(YEAR($I$4),12,31) -> 44561 | Y9: =DATE(YEAR($I$4)+1,12,31) -> 44926
B11: 营业收入 | I11: 9200 | K11: =IF(AND(Y11>=I11,Y11/I11<=1.2),"已校准",IF(Y11<I11,"未校准","可接受")) -> 已校准 | L11: 8700 | O11: 6900 | Q11: =S11-O11 -> 2000 | S11: 8900 | U11: =S11-L11 -> 200 | V11: =IFERROR(U11/O11,"NA") -> 0.028985507 | Y11: 9300 | AA11: =Y11-S11 -> 400 | AB11: =AA11/S11 -> 0.04494382
B12: 毛利额 | I12: =I11*J12 -> 3036 | J12: 0.33 | K12: =IF(AND(Y12>=I12,Y12/I12<=1.2),"已校准",IF(Y12<I12,"未校准","可接受")) -> 已校准 | L12: =L11*M12 -> 2958 | M12: 0.34 | O12: =O11*P12 -> 2484 | P12: 0.36 | Q12: =S12-O12 -> 720 | R12: =Q12/Q11 -> 0.36 | S12: =S11*T12 -> 3204 | T12: 0.36 | U12: =S12-L12 -> 246 | V12: =IFERROR(U12/O12,"NA") -> 0.099033816 | Y12: =Y11*Z12 -> 3069 | Z12: 0.33 | AA12: =Y12-S12 -> -135 | AB12: =AA12/S12 -> -0.042134831
B14: 日常运营费用合计 | F14: * | G14: * | H14: * | I14: 1410 | J14: =I14/I$11 -> 0.15326087 | K14: =IF(AND(I14>=Y14,I14/IF(Y14=0,0.001,Y14)<=1.2),"已校准",IF(I14<Y14,"未校准","可接受")) -> 已校准 | L14: 675.20551 | M14: =L14/L$11 -> 0.077609829 | O14: 461.53831 | P14: =O14/O$11 -> 0.066889611 | Q14: 229.71923 | R14: =Q14/Q$11 -> 0.11485962 | S14: =O14+Q14 -> 691.25755 | T14: =S14/S$11 -> 0.077669387 | U14: =S14-L14 -> 16.052037 | V14: =IFERROR(U14/O14,"NA") -> 0.034779425 | Y14: 1402.8631 | Z14: =Y14/Y$11 -> 0.15084549 | AA14: =Y14-S14 -> 711.60551 | AB14: =IFERROR(AA14/S14,"NA") -> 1.0294362
C15: 流程中心 | F15: =IF(C15=0,F14,C15) -> 流程中心 | G15: =IF(D15=0,IF(COUNTA($C15:C15)=0,G14,"*"),D15) -> * | H15: =IF(E15=0,IF(COUNTA($C15:D15)=0,H14,"*"),E15) -> * | I15: 1300 | J15: =I15/I$11 -> 0.14130435 | K15: =IF(AND(I15>=Y15,I15/IF(Y15=0,0.001,Y15)<=1.2),"已校准",IF(I15<Y15,"未校准","可接受")) -> 未校准 | L15: 675.20551 | M15: =L15/L$11 -> 0.077609829 | O15: 461.53831 | P15: =O15/O$11 -> 0.066889611 | Q15: 221.71923 | R15: =Q15/Q$11 -> 0.11085962 | S15: =O15+Q15 -> 683.25755 | T15: =S15/S$11 -> 0.076770511 | U15: =S15-L15 -> 8.0520372 | V15: =IFERROR(U15/O15,"NA") -> 0.017446086 | Y15: 1352.8631 | Z15: =Y15/Y$11 -> 0.14546915 | AA15: =Y15-S15 -> 669.60551 | AB15: =IFERROR(AA15/S15,"NA") -> 0.98001919
A16: 销售及管理费用 | D16: 销售中心 | F16: =IF(C16=0,F15,C16) -> 流程中心 | G16: =IF(D16=0,IF(COUNTA($C16:C16)=0,G15,"*"),D16) -> 销售中心 | H16: =IF(E16=0,IF(COUNTA($C16:D16)=0,H15,"*"),E16) -> * | J16: =I16/I$11 -> 0 | L16: 669.60551 | M16: =L16/L$11 -> 0.076966151 | O16: 461.53831 | P16: =O16/O$11 -> 0.066889611 | Q16: 221.71923 | R16: =Q16/Q$11 -> 0.11085962 | S16: =O16+Q16 -> 683.25755 | T16: =S16/S$11 -> 0.076770511 | U16: =S16-L16 -> 13.652037 | V16: =IFERROR(U16/O16,"NA") -> 0.029579423 | Y16: 1352.8631 | Z16: =Y16/Y$11 -> 0.14546915 | AA16: =Y16-S16 -> 669.60551 | AB16: =IFERROR(AA16/S16,"NA") -> 0.98001919
D17: 制造中心 | F17: =IF(C17=0,F16,C17) -> 流程中心 | G17: =IF(D17=0,IF(COUNTA($C17:C17)=0,G16,"*"),D17) -> 制造中心 | H17: =IF(E17=0,IF(COUNTA($C17:D17)=0,H16,"*"),E17) -> * | J17: =I17/I$11 -> 0 | L17: 5.6 | M17: =L17/L$11 -> 0.00064367816 | O17: 0 | P17: =O17/O$11 -> 0 | Q17: 0 | R17: =Q17/Q$11 -> 0 | S17: =O17+Q17 -> 0 | T17: =S17/S$11 -> 0 | U17: =S17-L17 -> -5.6 | V17: =IFERROR(U17/O17,"NA") -> NA | Y17: 0 | Z17: =Y17/Y$11 -> 0 | AA17: =Y17-S17 -> 0 | AB17: =IFERROR(AA17/S17,"NA") -> NA
C18: 改善中心 | F18: =IF(C18=0,F17,C18) -> 改善中心 | G18: =IF(D18=0,IF(COUNTA($C18:C18)=0,G17,"*"),D18) -> * | H18: =IF(E18=0,IF(COUNTA($C18:D18)=0,H17,"*"),E18) -> * | I18: 23 | J18: =I18/I$11 -> 0.0025 | K18: =IF(AND(I18>=Y18,I18/IF(Y18=0,0.001,Y18)<=1.2),"已校准",IF(I18<Y18,"未校准","可接受")) -> 可接受 | L18: 0 | M18: =L18/L$11 -> 0 | O18: 0 | P18: =O18/O$11 -> 0 | Q18: 0 | R18: =Q18/Q$11 -> 0 | S18: =O18+Q18 -> 0 | T18: =S18/S$11 -> 0 | U18: =S18-L18 -> 0 | V18: =IFERROR(U18/O18,"NA") -> NA | Y18: 15 | Z18: =Y18/Y$11 -> 0.0016129032 | AA18: =Y18-S18 -> 15 | AB18: =IFERROR(AA18/S18,"NA") -> NA
A19: 销售及管理费用 | D19: 流程优化项目小组 | F19: =IF(C19=0,F18,C19) -> 改善中心 | G19: =IF(D19=0,IF(COUNTA($C19:C19)=0,G18,"*"),D19) -> 流程优化项目小组 | H19: =IF(E19=0,IF(COUNTA($C19:D19)=0,H18,"*"),E19) -> * | J19: =I19/I$11 -> 0 | L19: 0 | M19: =L19/L$11 -> 0 | O19: 0 | P19: =O19/O$11 -> 0 | Q19: 0 | R19: =Q19/Q$11 -> 0 | S19: =O19+Q19 -> 0 | T19: =S19/S$11 -> 0 | U19: =S19-L19 -> 0 | V19: =IFERROR(U19/O19,"NA") -> NA | Y19: 0 | Z19: =Y19/Y$11 -> 0 | AA19: =Y19-S19 -> 0 | AB19: =IFERROR(AA19/S19,"NA") -> NA
A20: 销售及管理费用 | D20: 战略预算项目小组 | F20: =IF(C20=0,F19,C20) -> 改善中心 | G20: =IF(D20=0,IF(COUNTA($C20:C20)=0,G19,"*"),D20) -> 战略预算项目小组 | H20: =IF(E20=0,IF(COUNTA($C20:D20)=0,H19,"*"),E20) -> * | J20: =I20/I$11 -> 0 | L20: 0 | M20: =L20/L$11 -> 0 | O20: 0 | P20: =O20/O$11 -> 0 | Q20: 0 | R20: =Q20/Q$11 -> 0 | S20: =O20+Q20 -> 0 | T20: =S20/S$11 -> 0 | U20: =S20-L20 -> 0 | V20: =IFERROR(U20/O20,"NA") -> NA | Y20: 15 | Z20: =Y20/Y$11 -> 0.0016129032 | AA20: =Y20-S20 -> 15 | AB20: =IFERROR(AA20/S20,"NA") -> NA
C21: 创新中心 | F21: =IF(C21=0,F20,C21) -> 创新中心 | G21: =IF(D21=0,IF(COUNTA($C21:C21)=0,G20,"*"),D21) -> * | H21: =IF(E21=0,IF(COUNTA($C21:D21)=0,H20,"*"),E21) -> * | I21: 15 | J21: =I21/I$11 -> 0.0016304348 | K21: =IF(AND(I21>=Y21,I21/IF(Y21=0,0.001,Y21)<=1.2),"已校准",IF(I21<Y21,"未校准","可接受")) -> 未校准 | L21: 0 | M21: =L21/L$11 -> 0 | O21: 0 | P21: =O21/O$11 -> 0 | Q21: 0 | R21: =Q21/Q$11 -> 0 | S21: =O21+Q21 -> 0 | T21: =S21/S$11 -> 0 | U21: =S21-L21 -> 0 | V21: =IFERROR(U21/O21,"NA") -> NA | Y21: 35 | Z21: =Y21/Y$11 -> 0.0037634409 | AA21: =Y21-S21 -> 35 | AB21: =IFERROR(AA21/S21,"NA") -> NA
A22: 销售及管理费用 | D22: 产品研发部 | F22: =IF(C22=0,F21,C22) -> 创新中心 | G22: =IF(D22=0,IF(COUNTA($C22:C22)=0,G21,"*"),D22) -> 产品研发部 | H22: =IF(E22=0,IF(COUNTA($C22:D22)=0,H21,"*"),E22) -> * | J22: =I22/I$11 -> 0 | L22: 0 | M22: =L22/L$11 -> 0 | O22: 0 | P22: =O22/O$11 -> 0 | Q22: 0 | R22: =Q22/Q$11 -> 0 | S22: =O22+Q22 -> 0 | T22: =S22/S$11 -> 0 | U22: =S22-L22 -> 0 | V22: =IFERROR(U22/O22,"NA") -> NA | Y22: 35 | Z22: =Y22/Y$11 -> 0.0037634409 | AA22: =Y22-S22 -> 35 | AB22: =IFERROR(AA22/S22,"NA") -> NA
A23: 销售及管理费用 | D23: XX试验室 | F23: =IF(C23=0,F22,C23) -> 创新中心 | G23: =IF(D23=0,IF(COUNTA($C23:C23)=0,G22,"*"),D23) -> XX试验室 | H23: =IF(E23=0,IF(COUNTA($C23:D23)=0,H22,"*"),E23) -> * | J23: =I23/I$11 -> 0 | L23: 0 | M23: =L23/L$11 -> 0 | O23: 0 | P23: =O23/O$11 -> 0 | Q23: 0 | R23: =Q23/Q$11 -> 0 | S23: =O23+Q23 -> 0 | T23: =S23/S$11 -> 0 | U23: =S23-L23 -> 0 | V23: =IFERROR(U23/O23,"NA") -> NA | Y23: 0 | Z23: =Y23/Y$11 -> 0 | AA23: =Y23-S23 -> 0 | AB23: =IFERROR(AA23/S23,"NA") -> NA
A24: 销售及管理费用 | D24: XX孵化业务 | F24: =IF(C24=0,F23,C24) -> 创新中心 | G24: =IF(D24=0,IF(COUNTA($C24:C24)=0,G23,"*"),D24) -> XX孵化业务 | H24: =IF(E24=0,IF(COUNTA($C24:D24)=0,H23,"*"),E24) -> * | J24: =I24/I$11 -> 0 | L24: 0 | M24: =L24/L$11 -> 0 | O24: 0 | P24: =O24/O$11 -> 0 | Q24: 0 | R24: =Q24/Q$11 -> 0 | S24: =O24+Q24 -> 0 | T24: =S24/S$11 -> 0 | U24: =S24-L24 -> 0 | V24: =IFERROR(U24/O24,"NA") -> NA | Y24: 0 | Z24: =Y24/Y$11 -> 0 | AA24: =Y24-S24 -> 0 | AB24: =IFERROR(AA24/S24,"NA") -> NA
C25: 支持中心 | F25: =IF(C25=0,F24,C25) -> 支持中心 | G25: =IF(D25=0,IF(COUNTA($C25:C25)=0,G24,"*"),D25) -> * | H25: =IF(E25=0,IF(COUNTA($C25:D25)=0,H24,"*"),E25) -> * | I25: 8 | J25: =I25/I$11 -> 0.00086956522 | K25: =IF(AND(I25>=Y25,I25/IF(Y25=0,0.001,Y25)<=1.2),"已校准",IF(I25<Y25,"未校准","可接受")) -> 可接受 | L25: 0 | M25: =L25/L$11 -> 0 | O25: 0 | P25: =O25/O$11 -> 0 | Q25: 8 | R25: =Q25/Q$11 -> 0.004 | S25: =O25+Q25 -> 8 | T25: =S25/S$11 -> 0.0008988764 | U25: =S25-L25 -> 8 | V25: =IFERROR(U25/O25,"NA") -> NA | Y25: 0 | Z25: =Y25/Y$11 -> 0 | AA25: =Y25-S25 -> -8 | AB25: =IFERROR(AA25/S25,"NA") -> -1
A26: 销售及管理费用 | D26: 财务部 | F26: =IF(C26=0,F25,C26) -> 支持中心 | G26: =IF(D26=0,IF(COUNTA($C26:C26)=0,G25,"*"),D26) -> 财务部 | H26: =IF(E26=0,IF(COUNTA($C26:D26)=0,H25,"*"),E26) -> * | J26: =I26/I$11 -> 0 | L26: 0 | M26: =L26/L$11 -> 0 | O26: 0 | P26: =O26/O$11 -> 0 | Q26: 8 | R26: =Q26/Q$11 -> 0.004 | S26: =O26+Q26 -> 8 | T26: =S26/S$11 -> 0.0008988764 | U26: =S26-L26 -> 8 | V26: =IFERROR(U26/O26,"NA") -> NA | Y26: 0 | Z26: =Y26/Y$11 -> 0 | AA26: =Y26-S26 -> -8 | AB26: =IFERROR(AA26/S26,"NA") -> -1
A27: 销售及管理费用 | D27: 人力资源部 | F27: =IF(C27=0,F26,C27) -> 支持中心 | G27: =IF(D27=0,IF(COUNTA($C27:C27)=0,G26,"*"),D27) -> 人力资源部 | H27: =IF(E27=0,IF(COUNTA($C27:D27)=0,H26,"*"),E27) -> * | J27: =I27/I$11 -> 0 | L27: 0 | M27: =L27/L$11 -> 0 | O27: 0 | P27: =O27/O$11 -> 0 | Q27: 0 | R27: =Q27/Q$11 -> 0 | S27: =O27+Q27 -> 0 | T27: =S27/S$11 -> 0 | U27: =S27-L27 -> 0 | V27: =IFERROR(U27/O27,"NA") -> NA | Y27: 0 | Z27: =Y27/Y$11 -> 0 | AA27: =Y27-S27 -> 0 | AB27: =IFERROR(AA27/S27,"NA") -> NA
A28: 销售及管理费用 | D28: IT部 | F28: =IF(C28=0,F27,C28) -> 支持中心 | G28: =IF(D28=0,IF(COUNTA($C28:C28)=0,G27,"*"),D28) -> IT部 | H28: =IF(E28=0,IF(COUNTA($C28:D28)=0,H27,"*"),E28) -> * | J28: =I28/I$11 -> 0 | L28: 0 | M28: =L28/L$11 -> 0 | O28: 0 | P28: =O28/O$11 -> 0 | Q28: 0 | R28: =Q28/Q$11 -> 0 | S28: =O28+Q28 -> 0 | T28: =S28/S$11 -> 0 | U28: =S28-L28 -> 0 | V28: =IFERROR(U28/O28,"NA") -> NA | Y28: 0 | Z28: =Y28/Y$11 -> 0 | AA28: =Y28-S28 -> 0 | AB28: =IFERROR(AA28/S28,"NA") -> NA
B34: A:实际数 E:估计数 B:预算数 YTD：从年初到当年实际截止日 YTG：当年实际截止日次日到年底
E35: 需要手工填入数据
B37: 可接受 | E37: 上级预算与下级预算未校准，但差异不影响战略落地。可接受
B38: 未校准 | E38: 上级预算与下级预算的差异幅度超过可接受幅度，需要调整预算
B39: 已校准 | E39: 上级预算与下级预算的差异幅度在可接受幅度范围内。
B41: 表格中有隐藏的公式。需要添加责任中心、部门、科目时，请采用复制某现有行插入表格再修改的方式。

Sheet 长期资产
B4: 金额单位：万元 | E4: ="实际"&YEAR([2]主页!$D$9)-1 -> 实际2020 | G4: ="估计"&YEAR([2]主页!$D$9) -> 估计2021 | I4: ="预算"&YEAR([2]主页!$D$9)+1 -> 预算2022
B5: 长期资产原值
C6: 年初 | E6: =SUM([2]上年!$O:$O)/10000 -> 1270 | G6: =SUM([2]当年!$O:$O)/10000 -> 1236.96 | H6: =E9-G6 -> 0 | I6: =SUM([2]下年!$O:$O)/10000 -> 4710.24 | J6: =G9-I6 -> 0
C7: 增加 | E7: =SUM([2]上年!$P:$P)/10000 -> 1.96 | G7: =SUM([2]当年!$P:$P)/10000 -> 3503.28 | I7: =SUM([2]下年!$P:$P)/10000 -> 0.98
C8: 减少 | E8: =SUM([2]上年!$Q:$Q)/10000 -> 35 | G8: =SUM([2]当年!$Q:$Q)/10000 -> 30 | I8: =SUM([2]下年!$Q:$Q)/10000 -> 5
C9: 年末 | E9: =SUM([2]上年!$R:$R)/10000 -> 1236.96 | G9: =SUM([2]当年!$R:$R)/10000 -> 4710.24 | I9: =SUM([2]下年!$R:$R)/10000 -> 4706.22
C10: 校验 | E10: =E6+E7-E8-E9 -> 0 | G10: =G6+G7-G8-G9 -> 0 | H10: =I6+I7-I8-I9 -> 0
B11: 累计折旧摊销
C12: 年初 | E12: =SUM([2]上年!$T:$T)/10000 -> 170.64375 | G12: =SUM([2]当年!$T:$T)/10000 -> 268.6725 | H12: =E15-G12 -> 0 | I12: =SUM([2]下年!$T:$T)/10000 -> 453.625 | J12: =G15-I12 -> 0
C13: 增加 | E13: =SUM([2]上年!$U:$U)/10000 -> 122.135 | G13: =SUM([2]当年!$U:$U)/10000 -> 202.765 | I13: =SUM([2]下年!$U:$U)/10000 -> 281.72
C14: 减少 | E14: =SUM([2]上年!$V:$V)/10000 -> 24.10625 | G14: =SUM([2]当年!$V:$V)/10000 -> 17.8125 | I14: =SUM([2]下年!$V:$V)/10000 -> 0
C15: 年末 | E15: =SUM([2]上年!$W:$W)/10000 -> 268.6725 | G15: =SUM([2]当年!$W:$W)/10000 -> 453.625 | I15: =SUM([2]下年!$W:$W)/10000 -> 735.345
C16: 校验 | E16: =E12+E13-E14-E15 -> 0 | G16: =G12+G13-G14-G15 -> 0 | I16: =I12+I13-I14-I15 -> 0
B17: 技术折旧 | E17: =SUM([2]上年!$AB:$AB)/10000 -> 302 | G17: =SUM([2]当年!$AB:$AB)/10000 -> 304.07333 | I17: =SUM([2]下年!$AB:$AB)/10000 -> 304.07333
B18: 其中： | C18: 生产车间 | E18: =SUMIFS([2]上年!$AB:$AB,[2]上年!$G:$G,$C18)/10000 -> 302 | G18: =SUMIFS([2]当年!$AB:$AB,[2]当年!$G:$G,$C18)/10000 -> 302 | I18: =SUMIFS([2]下年!$AB:$AB,[2]下年!$G:$G,$C18)/10000 -> 302
C19: 财务部 | E19: =SUMIFS([2]上年!$AB:$AB,[2]上年!$G:$G,$C19)/10000 -> 0 | G19: =SUMIFS([2]当年!$AB:$AB,[2]当年!$G:$G,$C19)/10000 -> 1.3066667 | I19: =SUMIFS([2]下年!$AB:$AB,[2]下年!$G:$G,$C19)/10000 -> 1.3066667
C20: 行政部 | E20: =SUMIFS([2]上年!$AB:$AB,[2]上年!$G:$G,$C20)/10000 -> 0 | G20: =SUMIFS([2]当年!$AB:$AB,[2]当年!$G:$G,$C20)/10000 -> 0.76666667 | I20: =SUMIFS([2]下年!$AB:$AB,[2]下年!$G:$G,$C20)/10000 -> 0.76666667
